Workbook
Name \0: #N/A
Name \1: #REF!
Name \2: #REF!
Name \3: #REF!
Name \4: #REF!
Name \5: #REF!
Name \a: #N/A
Name \b: #N/A
Name \c: #N/A
Name \d: #N/A
Name \DSUM: #REF!
Name \e: #N/A
Name \EXP: #REF!
Name \f: #N/A
Name \g: #N/A
Name \GL: #REF!
Name \h: #REF!
Name \I: #REF!
Name \k: #REF!
Name \l: #REF!
Name \m: #N/A
Name \MPR2: #REF!
Name \n: #REF!
Name \o: #REF!
Name \p: #N/A
Name \q: #REF!
Name \R: #REF!
Name \s: #N/A
Name \t: #REF!
Name \u: #N/A
Name \w: #REF!
Name \x: #REF!
Name \y: #REF!
Name \z: #REF!
Name _: #REF!
Name __?Business___Market_Spr: #REF!
Name __?End_Use_Analysis___Sectoral_Gro: #REF!
Name __?INDUSTRY_MATERIAL_BALA: #REF!
Name __?INDUSTRY_MATERIAL_BALANCE___PROJECTI: #REF!
Name __?PE___Q1_REV: #REF!
Name __?PE_1996: #REF!
Name __?PE_BUSINESS___PAST___FUT: #REF!
Name __?PE_REV: #REF!
Name __?PRICE_FORECAST___1995: #REF!
Name __?PROFITABILITY__Q3_1996__: #REF!
Name __?Q3___SUMM: #REF!
Name __?Quarterwise_Collection_P: #REF!
Name __?Quarterwise_Export_P: #REF!
Name __?QUARTERWISE_PERFORMA: #REF!
Name __?RE: #REF!
Name _______________________________DAT5: #REF!
Name _______________________________DAT7: #REF!
Name ______________________________DAT1: #REF!
Name ______________________________DAT10: #REF!
Name _____________________________DAT5: #REF!
Name _____________________________DAT7: #REF!
Name ____________________________DAT1: #REF!
Name ____________________________DAT10: #REF!
Name ____________________________DAT5: #REF!
Name ____________________________DAT7: #REF!

Sheet AR - slide BoD
B1: Amounts in 000
B2: Total receivables | I2: =I22/1000 -> 59548.326 | J2: =J22/1000 -> 95548.817
B4: Receivables as on 28th Feb 25 | D4: BU | E4: Overdue | F4: Not Due | G4: Not Due | I4: Provision | J4: Provision | L4: Provision risks - overdue receivables | P4: Remark
L5: Probable | M5: Possible | N5: Rare
B6: Central do Adubo | D6: Fertilizer | E6: =E26/1000 -> 7560.7278 | F6: =F26/1000 -> 0 | G6: =G26/1000 -> 7560.7278 | I6: =I26/1000 -> 0 | J6: =J26/1000 -> 0 | L6: =L26/1000 -> 0 | M6: =M26/1000 -> 7560.7278 | N6: =N26/1000 -> 0 | P6: Creditor´s assembly Judicial recovery plan has not yet been approved by Creditors. Adfert advisors believe that the AS-IS plan will not be approved and new financial conditions will need to be presented.
B7: SM Agro / Fazenda Baturi | D7: Fertilizer | E7: =E27/1000 -> 3088.5311 | F7: =F27/1000 -> 0 | G7: =G27/1000 -> 3088.5311 | I7: =I27/1000 -> 3088.5311 | J7: =J27/1000 -> 0 | L7: =L27/1000 -> 3088.5311 | M7: =M27/1000 -> 0 | N7: =N27/1000 -> 0 | P7: Judicial collection lawsuit is ongoing.
B8: CBM Fertilizantes | D8: Fertilizer | E8: =E28/1000 -> 3044.8509 | F8: =F28/1000 -> 0 | G8: =G28/1000 -> 3044.8509 | I8: =I28/1000 -> 3044.8509 | J8: =J28/1000 -> 0 | L8: =L28/1000 -> 3044.8509 | M8: =M28/1000 -> 0 | N8: =N28/1000 -> 0 | P8: Adfert has taken legal action and collection recovery lawsuit has been filed. Payment plan was not succesful.
B9: Mogiana Tecno Agro | D9: Fertilizer | E9: =E29/1000 -> 2492.8421 | F9: =F29/1000 -> 0 | G9: =G29/1000 -> 2492.8421 | I9: =I29/1000 -> 0 | J9: =J29/1000 -> 0 | L9: =L29/1000 -> 0 | M9: =M29/1000 -> 2492.8421 | N9: =N29/1000 -> 0 | P9: AFT received a renewalled payment proposal. Monthly payments along 2 yrs, with Machineary as guarantee and worth 25% of Open Exposure. Formal proposal still pending full disclosre on documents and valuation on Machinery.
B10: Casa das Sementes | D10: Fertilizer | E10: =E30/1000 -> 1863.2009 | F10: =F30/1000 -> 0 | G10: =G30/1000 -> 1863.2009 | I10: =I30/1000 -> 1863.2009 | J10: =J30/1000 -> 0 | L10: =L30/1000 -> 1863.2009 | M10: =M30/1000 -> 0 | N10: =N30/1000 -> 0 | P10: Legal process ongoing and 100% of the invoices we provisioned.
B11: Terra Fértil | D11: Fertilizer | E11: =E31/1000 -> 1702.8487 | F11: =F31/1000 -> 0 | G11: =G31/1000 -> 1702.8487 | I11: =I31/1000 -> 1702.8487 | J11: =J31/1000 -> 0 | L11: =L31/1000 -> 1702.8487 | M11: =M31/1000 -> 0 | N11: =N31/1000 -> 0 | P11: AFT has reached a payment agreement: 15% paid by Oct 25 and 3 yearly installments (Oct 26-27-28). No discount on principal and price inflation indexed
B12: Agro Beraldo | D12: Fertilizer | E12: =E32/1000 -> 876.01175 | F12: =F32/1000 -> 0 | G12: =G32/1000 -> 876.01175 | I12: =I32/1000 -> 0 | J12: =J32/1000 -> 0 | L12: =L32/1000 -> 0 | M12: =M32/1000 -> 876.01175 | N12: =N32/1000 -> 0 | P12: Judicial collection lawsuit is ongoing.
B14: Total Over Due in Litigation (TOP 7) | E14: =E39/1000 -> 22315.752 | F14: 0 | G14: 0 | I14: =I39/1000 -> 10937.332 | J14: =J39/1000 -> 0 | L14: =L39/1000 -> 10937.332 | M14: =M39/1000 -> 11378.42 | N14: 0
B15: Total Over Due with Possible Loss | E15: =E45/1000 -> 6.07632 | F15: 0 | G15: 0 | I15: =I45/1000 -> 6.07632 | J15: =J45/1000 -> 0 | L15: =L45/1000 -> 6.07632 | M15: =M45/1000 -> 0 | N15: 0
B16: Low Risk - Expect to Receive soon | E16: =E46/1000 -> 1226.0065 | F16: =F46/1000 -> 0 | G16: =G46/1000 -> 1226.0065 | I16: =I46/1000 -> 177.60127 | J16: =J46/1000 -> 0 | L16: =L46/1000 -> 0 | M16: =M46/1000 -> 0 | N16: =N46/1000 -> 1226.0065 | P16: Provision as per corporate policy
B17: Total | E17: =E16+E15+E14 -> 23547.835 | F17: =F16+F15+F14 -> 0 | G17: =G16+G15+G14 -> 1226.0065 | I17: =I16+I15+I14 -> 11121.01 | J17: =J16+J15+J14 -> 0 | L17: =L14+L15 -> 10943.409 | M17: =M16+M14 -> 11378.42 | N17: =N16+N14 -> 1226.0065
B19: in BRl
B22: Total receivables | I22: =SUM(E123:F123) -> 59548326 | J22: =SUM(F123:G123) -> 95548817
B24: Receivables as on 30th Apr 26 | D24: BU | E24: Overdue | F24: Not Due | G24: Total | I24: Provision | J24: Write Off | L24: Collection Risk | P24: Remark
L25: Probable | M25: Possible | N25: Rare
B26: CENTRAL DO ADUBO COM E REPRESENTACAO LTD | D26: Fertilizers | E26: 7560727.8 | F26: 0 | G26: =SUM(E26:F26) -> 7560727.8 | I26: 0 | L26: =I26 -> 0 | M26: =E26-I26 -> 7560727.8 | P26: Current Status: Creditor´s Assembly has been approved. All suppliers to receive 35% (65% haircut) of total Outstanding in 10 years (2x per year installments) after a 18-months grace period, corrected by TR inflation index. Prefered suppliers, such as AFT, are eligible to full Overdue recovery based on future sales. 3% of all new CAD Sales to offset Old Overdues and 4% for sales with tenor (credit). This condition is non-binding and the client is to grant AFT a real estate guarantee of BRL 1MM. Upcoming Actions: Decision will now need to undergo approval and pass the entire appeal period. This step may still take a couple months to be completed.
B27: GRUPO LEANDRO SARTI | D27: Fertilizers | E27: 3088531.1 | F27: 0 | G27: =SUM(E27:F27) -> 3088531.1 | I27: 3088531.1 | L27: =I27 -> 3088531.1 | M27: =E27-I27 -> 0 | P27: Current Status: In Litigation via Collection enforcement claim. The judicial process is still in the initial phase, and we are in the period of notifying the parties involved. Upcoming Actions: We will await the procedures set forth by the court.
B28: AGRO BERALDO | D28: Fertilizers | E28: 3044850.9 | F28: 0 | G28: =SUM(E28:F28) -> 3044850.9 | I28: 3044850.9 | L28: =I28 -> 3044850.9 | M28: =E28-I28 -> 0 | P28: Current Status: The Litigation Collection enforcement claim process is ongoing. Upcoming Actions: AFT awaiting for further updates by the court.
B29: TERRA FERTIL - MACHADO | D29: Fertilizers | E29: 2492842.1 | F29: 0 | G29: =SUM(E29:F29) -> 2492842.1 | I29: 0 | L29: =I29 -> 0 | M29: =E29-I29 -> 2492842.1 | P29: Current Status: In Litigation via Collection enforcement claim. An agreement has been reached between parties, under the following terms: (i) Total settlement amount: R$ 3,192,985.64; (ii) Down payment: R$ 478,947.84, to be paid by October 30, 2025; (iii) Remaining balance: R$ 2,714,037.80, to be paid in three annual installments of R$ 904,679.26 each (2026 / 2027 / 2028), to be duly adjusted by inflation/court index. Upcoming Actions: AFT awaiting for the downpayment from the debtor to fulfill the agreement (Oct 20th 2025).
B30: MOGIANA TECNO AGRO | D30: Fertilizers | E30: 1863200.9 | F30: 0 | G30: =SUM(E30:F30) -> 1863200.9 | I30: 1863200.9 | L30: =I30 -> 1863200.9 | M30: =E30-I30 -> 0 | P30: Current Status: In Litigation via Collection enforcement claim. AFT received a proposal agreement, consisting of 12 initial installments of R$ 50,000.00, beginning March 28, which we had previously agreed after trying to negotiate a higher amount. From the 13th month, the proposal would be to rise monthly installments to R$ 100,000.00. This payment agreement would include both principal (R$ 2,502,567.34) and Interest (R$ 204,693.57). We have, via the enforcement collection claim received BRL 29k from the clients account via judicial decison. Upcoming Actions: we´ve not received feedback and are still assessing the viability of an agreed payment plan proposal. AFT is continuing to follow up on a payment schedule definition. AFT continues to follow on enforcement of any assets available from the client.
B31: CASA DAS SEMENTES | D31: Fertilizers | E31: 1702848.7 | F31: 0 | G31: =SUM(E31:F31) -> 1702848.7 | I31: 1702848.7 | L31: =I31 -> 1702848.7 | M31: =E31-I31 -> 0 | P31: Current Status: In Litigation via Collection enforcement claim. The process is ongoing, and we have successfully notified the debtor via judicial court. Upcoming Actions: AFT is seeking to seize assets from the debtor via the judicial claim which is ongoing.
B32: CBM FERTILIZANTES | D32: Fertilizers | E32: 876011.75 | F32: 0 | G32: =SUM(E32:F32) -> 876011.75 | I32: 0 | L32: =I32 -> 0 | M32: =E32-I32 -> 876011.75 | P32: Judicial settlement has been signed, under the following terms: (i) Total settlement amount: R$ 1,179,964.76, to be paid under the following conditions; (ii) Agreed payment in Two installments of R$ 100,000.00 each, due on April 24, 2025, and September 30th, 2025; Client has paid BRL 100k of the 1st installment and 2nd to be paid on the 30th of Sept. (iii) Three annual installments of R$ 326,654.92 , due on September 30, 2026, September 30, 2027, and September 30, 2028; Upcoming Actions: AFT awaiting for the payment plan agreed ofr September (another BRL 100k payment).
B33: GRUPO TRIANGULO AGRO | D33: Fertilizers | E33: 237309.12 | F33: 0 | G33: =SUM(E33:F33) -> 237309.12 | I33: 237309.12 | L33: =I33 -> 237309.12 | M33: =E33-I33 -> 0 | P33: Current Status: Client has issue a Judicial Recovery claim. The judicial process is still in the initial phase, and AFT has been notified. Upcoming Actions: AFT awaiting for the next steps to be set by court.
B34: TERRA FERTILIZANTES LTDA - ARAXÁ | D34: Additives | E34: 226233.6 | F34: 0 | G34: =SUM(E34:F34) -> 226233.6 | I34: 226233.6 | L34: =I34 -> 226233.6 | M34: =E34-I34 -> 0 | P34: May - 2024. In Litigation via collection enforcement. We don´t expect to have the collection. Client has been operation with a different Tax Id and we´re investigating how to link both companies to this claim.
B35: FAZENDA ARCOS SÃO JOÃO | D35: Fertilizers | E35: 988506.24 | F35: 0 | G35: =SUM(E35:F35) -> 988506.24 | I35: 539667.84 | L35: =I35 -> 539667.84 | M35: =E35-I35 -> 448838.4 | P35: Aug- 2025 Payment plan negotiation ongoing.
B36: ITERUM - RONDONOPOLIS | D36: Additives | E36: 213750 | F36: 0 | G36: =SUM(E36:F36) -> 213750 | I36: 213750 | L36: =I36 -> 213750 | M36: =E36-I36 -> 0 | P36: Dec- 2024 - Client facing fanancial difficulties and offered to return non-used final products. AFT is validating samples collected for quality assurance.
B37: GLINFERTIL - SAO FRANCISCO DO SUL | D37: Additives | E37: 20940 | F37: 0 | G37: =SUM(E37:F37) -> 20940 | I37: 20940 | L37: =I37 -> 20940 | M37: =E37-I37 -> 0 | P37: Nov 2023 Overdue. We don´t expect to receive collection from this client. The current status is that the client awaits for a court decision to accept the Judicial recovery process.
B39: Total Over Due in Litigation (TOP 12) | E39: =SUM(E26:E37) -> 22315752 | F39: =SUM(F26:F37) -> 0 | G39: =SUM(G26:G37) -> 22315752 | I39: =SUM(I26:I37) -> 10937332 | J39: =SUM(J26:J37) -> 0 | L39: =SUM(L26:L37) -> 10937332 | M39: =SUM(M26:M37) -> 11378420 | N39: =SUM(N26:N37) -> 0
B40: KLEYTON DUARTE SOARES | D40: Additives | E40: 100 | F40: 0 | G40: =SUM(E40:F40) -> 100 | I40: 100 | L40: =I40 -> 100 | M40: =E40-L40 -> 0 | P40: Jul - 2024 - Sale of old fixed assets to employees (chairs, desks etc) and it was not duly debited in employees payroll. Employee has left the company.
B41: MARIA JOSE DA SILVA | D41: Additives | E41: 50 | F41: 0 | G41: =SUM(E41:F41) -> 50 | I41: 50 | L41: =I41 -> 50 | M41: =E41-L41 -> 0 | P41: Aug - 2024 - Sale of old fixed assets to employees (chairs, desks etc) and it was not duly debited in employees payroll. Employee has left the company.
B42: GRUPO YARA | D42: Additives | E42: 5626.32 | F42: 0 | G42: =SUM(E42:F42) -> 5626.32 | I42: 5626.32 | L42: =I42 -> 5626.32 | M42: =E42-L42 -> 0 | P42: June 2024 - invoice underpayment due client claim of weight divergence
B43: SEU LIXO | D43: Additives | E43: 300 | F43: 0 | G43: =SUM(E43:F43) -> 300 | I43: 300 | L43: =I43 -> 300 | M43: =E43-L43 -> 0 | P43: Nov 2024 - sale of scrap materials.
B45: Total Over Due with Probable Loss | E45: =SUM(E40:E44) -> 6076.32 | F45: =SUM(F40:F44) -> 0 | G45: =SUM(G40:G44) -> 6076.32 | I45: =SUM(I40:I44) -> 6076.32 | J45: =SUM(J40:J44) -> 0 | L45: =SUM(L40:L44) -> 6076.32 | M45: =SUM(M40:M44) -> 0 | N45: =SUM(N40:N44) -> 0
B46: Low Risk - Expect to Receive soon | E46: =SUM(E47:E56) -> 1226006.5 | F46: =F57+F58+F59 -> 0 | G46: =SUM(G47:G56) -> 1226006.5 | I46: =SUM(I47:I56) -> 177601.27 | J46: =SUM(J47:J56) -> 0 | L46: =SUM(L47:L56) -> 0 | M46: =SUM(M47:M56) -> 0 | N46: =SUM(N47:N56) -> 1226006.5 | P46: Provision as per corporate policy
B47: AGROBROKERS - COLÔMBIA | D47: Additive Intl. | E47: 449507.69 | G47: 449507.69 | I47: 13485.231 | N47: =E47 -> 449507.69 | P47: Cargo cleared at Colombia port customs. AFT is in contact with the customer for validation of the payment plan.
B48: FERTIBAL - EQUADOR | D48: Additive Intl. | E48: 14548.35 | G48: =SUM(E48:F48) -> 14548.35 | I48: 436.4505 | N48: =E48 -> 14548.35 | P48: Jan - 2026 The client paid 50% of the amount in January 2026; the remainder will be paid in March.
B49: AURORA MINERAÇÃO LTDA | D49: Additives | E49: 37491.5 | G49: =SUM(E49:F49) -> 37491.5 | I49: 0 | N49: =E49 -> 37491.5
B50: JOSÉ FRANCISCO PIRES DE SOUZA | D50: Additives | E50: 100 | G50: =SUM(E50:F50) -> 100 | I50: 0 | N50: =E50 -> 100
B51: ARSLOG SOLUCOES EM TRANSPORTE | D51: Additives | E51: 49440 | G51: =SUM(E51:F51) -> 49440 | I51: 0 | N51: =E51 -> 49440 | P51: March - 2026 -
B52: EUROCHEM SERRA DO SALITRE | D52: Additives | E52: 315971.7 | G52: =SUM(E52:F52) -> 315971.7 | I52: 0 | N52: =E52 -> 315971.7
B53: TAKI AGRO - SOCORRO | D53: Additives | E53: 184217.94 | G53: =SUM(E53:F53) -> 184217.94 | I53: 0 | N53: =E53 -> 184217.94
B54: GRUPO MOSAIC FERTILIZANTES DO BRASIL | D54: Additives | E54: 16818.92 | G54: =SUM(E54:F54) -> 16818.92 | I54: 16756.646 | N54: =E54 -> 16818.92 | P54: Return goods invoices in dispute with client
B55: ORGANITEC - PARAGUAY | D55: Additive Intl. | E55: 527.28 | G55: =SUM(E55:F55) -> 527.28 | I55: 15.8184 | N55: =E55 -> 527.28 | P55: Sep 2025: Residual value from partial payment.
B56: Freight Debit Notes | D56: Additives | E56: 157383.12 | G56: =SUM(E56:F56) -> 157383.12 | I56: 146907.12 | N56: =E56 -> 157383.12 | P56: In validation - AFT and Logistics companies in agreement to pay only Freight overstay only from 2024 onwards. BRL 112k invoices are from before 2024 and unders discussion to be addressed in Sept month end closing.
B57: Not Due | D57: Additives
D58: Additive Intl.
D59: Fertilizers
B60: GRUPO MOSAIC FERTILIZANTES P K LTDA | D60: Additives | F60: 6765009.9 | G60: =E60+F60 -> 6765009.9 | O60: 475235
B61: GRUPO YARA | D61: Additives | F61: 4084092.2 | G61: =E61+F61 -> 4084092.2 | O61: 3633158.1
B62: GRUPO UNIFERTIL | D62: Additives | F62: 3756608.9 | G62: =E62+F62 -> 3756608.9
B63: GRUPO MOSAIC FERTILIZANTES DO BRASIL | D63: Additives | F63: 2961615.4 | G63: =E63+F63 -> 2961615.4
B64: EUROCHEM SERRA DO SALITRE | D64: Additives | F64: 477840 | G64: =E64+F64 -> 477840
B65: STRATOS/MOSAIC - ROSARIO DO CATETE | D65: Additives | F65: 707551.6 | G65: =E65+F65 -> 707551.6 | O65: 3231664.8
B66: FECOAGRO FEDERACAO DAS COOPERATIVAS | D66: Additives | F66: 654535.73 | G66: =E66+F66 -> 654535.73 | O66: 225884.2
B67: GRUPO CIBRA | D67: Additives | F67: 654015.7 | G67: =E67+F67 -> 654015.7 | O67: 6158350.9
B68: GRUPO HINOVE | D68: Additives | F68: 604009.9 | G68: =E68+F68 -> 604009.9 | O68: 866804.7
B69: FOSNOR - LUIS EDUARDO MAGALHAES | D69: Additives | F69: 517338.2 | G69: =E69+F69 -> 517338.2 | O69: 158126.4
B70: ULTRAFERTIL | D70: Additives | F70: 516611.4 | G70: =E70+F70 -> 516611.4 | O70: 1227102.4
B71: ADUFERTIL JUNDIAI | D71: Additives | F71: 410856.52 | G71: =E71+F71 -> 410856.52 | O71: 53489.3
B72: GRUPO FERTILIZ TOCANTINS | D72: Additives | F72: 409551.4 | G72: =E72+F72 -> 409551.4
B73: BENTONIT UNIAO - CAMPINA GRANDE | D73: Additives | F73: 395265 | G73: =E73+F73 -> 395265 | O73: 528498.8
B74: AGROPECUARIA MARATA LTDA - MARUIM | D74: Additives | F74: 290220 | G74: =E74+F74 -> 290220 | O74: 417989.8
B75: GRUPO HERINGER | D75: Additives | F75: 248897.61 | G75: =E75+F75 -> 248897.61 | O75: 1424871.4
B76: NUTRIENTES IND DE FERTILIZANTES LTDA | D76: Additives | F76: 244032 | G76: =E76+F76 -> 244032 | O76: 1708772
B77: GRUPO FERTIPAR FERTILIZANTES MATO GROSSO | D77: Additives | F77: 243513 | G77: =E77+F77 -> 243513 | O77: 324729
B78: BIOSAFRA - MARUIM | D78: Additives | F78: 215702.86 | G78: =E78+F78 -> 215702.86 | O78: 1034572.5
B79: AURORA MINERAÇÃO LTDA | D79: Additives | F79: 151537.2 | G79: =E79+F79 -> 151537.2 | O79: 444240
B80: GRUPO JOSAPAR | D80: Additives | F80: 185040 | G80: =E80+F80 -> 185040 | O80: 159679.8
B81: GRUPO AMAGGI | D81: Additives | F81: 153263.8 | G81: =E81+F81 -> 153263.8 | O81: 23451.75
B82: FERTGROW S.A | D82: Additives | F82: 105829.4 | G82: =E82+F82 -> 105829.4
B83: COONAGRO COOPERATIVA - PARANAGUA | D83: Additives | F83: 80079.3 | G83: =E83+F83 -> 80079.3
B84: GRUPO ADUBOS ARAGUAIA | D84: Additives | F84: 65330 | G84: =E84+F84 -> 65330
B85: GRUPO LOUIS DREYFUS | D85: Additives | F85: 62566.4 | G85: =E85+F85 -> 62566.4
B86: INTERFERTIL - SAO FRANCISCO DO SUL | D86: Additives | F86: 44919 | G86: =E86+F86 -> 44919
B87: GRANUPAR - RIO BRANCO DO SUL | D87: Additives | F87: 43569.75 | G87: =E87+F87 -> 43569.75
B88: ADUBOS LEAO - LARANJEIRAS | D88: Additives | F88: 26290 | G88: =E88+F88 -> 26290
B89: FREIGHT DEBIT NOTES | D89: Additives | F89: 19200 | G89: =E89+F89 -> 19200
B90: GRUPO CARGILL | D90: Additives | F90: 13431 | G90: =E90+F90 -> 13431
B91: MARCELO HONORIO DE CARVALHO RAMOS | D91: Additives | F91: 1743 | G91: =E91+F91 -> 1743 | O91: 73440
B92: ANDRESSA CAROLINA SILVA RODRIGUES | D92: Additives | F92: 583.34 | G92: =E92+F92 -> 583.34 | O92: 112012.5
B93: ELYMAR JOSE DA SILVA FERREIRA | D93: Additives | F93: 331 | G93: =E93+F93 -> 331 | O93: 42240
B94: AGROVIVA | D94: Fertilizers | F94: 1200190.4 | G94: =E94+F94 -> 1200190.4
B95: CONNTACTA AGRONEGOCIOS | D95: Fertilizers | F95: 739540.06 | G95: =E95+F95 -> 739540.06
B96: ADUFÉRTIL - CAMPEVO | D96: Fertilizers | F96: 734953.47 | G96: =E96+F96 -> 734953.47
B97: GA AGRONEGOCIOS | D97: Fertilizers | F97: 482989 | G97: =E97+F97 -> 482989
B98: FAZENDA FERRADURA | D98: Fertilizers | F98: 329327.91 | G98: =E98+F98 -> 329327.91
B99: GRUPO TAKI AGRO | D99: Fertilizers | F99: 306727.12 | G99: =E99+F99 -> 306727.12
B100: AGROREP. REPRESENTACOES AGRICOLAS | D100: Fertilizers | F100: 299642.08 | G100: =E100+F100 -> 299642.08
B101: TAKI AGRO - POUSO ALEGRE | D101: Fertilizers | F101: 222808.17 | G101: =E101+F101 -> 222808.17
B102: GRUPO BOLSA AGRONEGOCIO | D102: Fertilizers | F102: 133718 | G102: =E102+F102 -> 133718
B103: VEGA AGRO | D103: Fertilizers | F103: 131680 | G103: =E103+F103 -> 131680
B104: GRUPO SAGRA | D104: Fertilizers | F104: 5030.5 | G104: =E104+F104 -> 5030.5
B105: NITROFERT SAS - COLOMBIA | D105: Additive Intl. | F105: 3280155.2 | G105: =E105+F105 -> 3280155.2
... B122: ORGANITEC - PARAGUAY | D122: Additive Intl. | F122: 853.24 | G122: =E122+F122 -> 853.24
B123: Total | E123: =E46+E45+E39+SUM(E60:E122) -> 23547835 | F123: =F46+F45+F39+SUM(F60:F122) -> 36000491 | G123: =G46+G45+G39+SUM(G60:G122) -> 59548326 | I123: =I46+I45+I39+SUM(I60:I122) -> 11121010 | J123: =J46+J45+J39+SUM(J60:J122) -> 0 | L123: =L46+L45+L39+SUM(L60:L122) -> 10943409 | M123: =M46+M45+M39+SUM(M60:M122) -> 11378420 | N123: =N46+N45+N39+SUM(N60:N122) -> 1226006.5
D125: Additive Intl. | E125: =SUMIF($D$26:$D$123,$D125,E$26:E$123) -> 464583.32 | F125: =SUMIF($D$26:$D$123,$D125,F$26:F$123) -> 6302903.6 | G125: =SUMIF($D$26:$D$123,$D125,G$26:G$123) -> 6767486.9 | H125: =SUMIF($D$26:$D$123,$D125,H$26:H$123) -> 0 | I125: =SUMIF($D$26:$D$123,$D125,I$26:I$123) -> 13937.5 | J125: =SUMIF($D$26:$D$123,$D125,J$26:J$123) -> 0 | K125: =SUMIF($D$26:$D$123,$D125,K$26:K$123) -> 0 | L125: =SUMIF($D$26:$D$123,$D125,L$26:L$123) -> 0 | ... N125: =SUMIF($D$26:$D$123,$D125,N$26:N$123) -> 464583.32
...

Sheet AR - slide
B1: in BRl
B2: Receivables as on 31st March 25 | D2: BU | E2: Overdue | F2: Not Due | G2: Provision | I2: Risk Provisions | M2: Remark
I3: Probable | J3: Possible | K3: Rare
B4: Central do Adubo | D4: Fertilizer | E4: 7560727.8 | G4: 3780363.9 | I4: 3780363.9 | J4: 3780363.9 | M4: Creditor´s assembly has been schedulled for May 2025. Central has reached out to Adfert for preferred suppliers status and conditions are in negotiation along April early May to be presented in the Assembly.
B5: SM Agro / Fazenda Baturi | D5: Fertilizer | E5: 3088531.1 | F5: 0 | G5: 3088531.1 | I5: 3088531.1 | M5: Judicial collection lawsuit is ongoing.
B6: CBM Fertilizantes | D6: Fertilizer | E6: 1076345 | F6: 0 | G6: 1076345 | I6: 1076345 | M6: Payment plan in negotiation: 10% payment in 2025 + 3 bullet yearly payments for the remaining debt.
B7: Mogiana Tecno Agro | D7: Fertilizer | E7: 1892360 | F7: 0 | G7: 0 | I7: 0 | J7: 1892360 | M7: AFT received a renewalled payment proposal. Monthly payments along 2 yrs, with Machineary as guarantee and worth 25% of Open Exposure. Formal proposal still pending full disclosre on documents and valuation on Machinery.
B8: Casa das Sementes | D8: Fertilizer | E8: 1716645.3 | G8: 1716645.3 | I8: 1716645.3 | M8: Legal process ongoing and 100% of the invoices we provisioned.
B9: Terra Fértil | D9: Fertilizer | E9: 2971789.9 | G9: 89153.697 | J9: 2971789.9 | M9: AFT has reached a payment agreement: 15% paid by Oct 25 and 3 yearly installments (Oct 26-27-28). No discount on principal and price inflation indexed
B10: Agro Beraldo | D10: Fertilizer | E10: 3044850.9 | F10: 0 | G10: 91345.528 | J10: 3044850.9 | M10: Judicial collection lawsuit is ongoing.
B12: Total Over Due in Litigation (TOP 7) | E12: =SUM(E4:E10) -> 21351250 | F12: =SUM(F4:F10) -> 0 | G12: =SUM(G4:G10) -> 9842384.5 | I12: =SUM(I4:I10) -> 9661885.3 | J12: =SUM(J4:J10) -> 11689365 | K12: =SUM(K4:K10) -> 0
B13: Planta Rica Agronegócios Ltda | D13: Fertilizers | E13: 110528 | F13: 0 | G13: 110528 | I13: 110528 | M13: old overdue
B14: Equilíbrio - Mogi Mirim | D14: Fertilizers | E14: 22222.25 | F14: 0 | G14: 22222.25 | I14: 22222.25 | M14: old overdue due to Quality issues
B15: Terra Fertilizantes Ltda | D15: Additives | E15: 226233.6 | F15: 0 | G15: 6787.008 | I15: 226233.6 | M15: Judicial recovery started
B16: Plant Bem - Paranagua | D16: Additives | E16: 140872.6 | F16: 0 | G16: 140872.6 | I16: 140872.6 | M16: old overdue
B17: Fertisanta Fertilizantes | D17: Additives | E17: 41379 | F17: 0 | G17: 41379 | I17: 41379 | M17: old overdue
B18: GLINFERTIL - SAO FRANCISCO DO SUL | D18: Additives | E18: 20940 | G18: 20940 | I18: 20940
B19: Superbac | D19: Additives | E19: 102008.2 | G19: 3060.25 | I19: 102008.2 | M19: No agreenment on payment. Judicial recovery process to begin
B20: Delcorp S.A | D20: Additives | E20: 84291.45 | F20: 0 | G20: 84291.45 | I20: 84291.45 | M20: old overdue
B21: Total Over Due with Possible Loss | E21: =SUM(E13:E20) -> 748475.1 | F21: =SUM(F13:F20) -> 0 | G21: =SUM(G13:G20) -> 430080.56 | I21: =SUM(I13:I20) -> 748475.1 | J21: =SUM(J13:J20) -> 0 | K21: =SUM(K13:K20) -> 0
B22: Low Risk - Expect to Receive soon | E22: =SUM(E23:E43) -> 7425775.8 | F22: =F44+F45+F46 -> 35847180 | G22: =SUM(G23:G43) -> 526944.99 | M22: Provision as per corporate policy
B23: Grupo Fert Tocantins | D23: Additives | E23: =1991399-67239 -> 1924160 | G23: 67314 | K23: =E23 -> 1924160 | M23: Overdue received in the beginning of March
B24: GRUPO MOSAIC FERTILIZANTES DO BRASIL | D24: Additives | E24: =765704.79-80843.12 -> 684861.67 | G24: 66674.04 | K24: =E24 -> 684861.67
B25: ITERUM - RONDONOPOLIS | D25: Additives | E25: 213750 | G25: 1475.1
B26: GRUPO AMAGGI | D26: Additives | E26: 56400
B27: GRUPO HERINGER | D27: Additives | E27: 397800
B28: GRUPO MOSAIC FERTILIZANTES P K LTDA | D28: Additives | E28: =123685.2-16500 -> 107185.2
B29: GRUPO CIBRA | D29: Additives | E29: =414240-1200 -> 413040
B30: GRUPO YARA | D30: Additives | E30: =63226.32-57600 -> 5626.32
B31: LYCSA Argentina | D31: Int'll | E31: 256935.85 | G31: 256935.85 | J31: 256935.85
B32: FERTYMEND - EQUADOR | D32: Int'll | E32: 69886.47
B33: AGRO MIL AGROS SAS - COLOMBIA | D33: Int'll | E33: 136847.67
B34: FERTIBAL - EQUADOR | D34: Int'll | E34: 82123.57
B35: ASOCIACION DE COOPERATIVAS ARGENTINAS CL | D35: Int'll | E35: 703377.76
B36: TECNOMYL S.A. - PARAGUAY | D36: Int'll | E36: 201503.56
B37: ABOPAR - PARAGUAY | D37: Int'll | E37: 150938.02
B38: C I ACEPALMA SA - COLOMBIA | D38: Int'll | E38: 317041.26 | K38: =E38 -> 317041.26
B39: Indorama Senegal | D39: Int'll | E39: 381748.49 | G39: 0 | K39: =E39 -> 381748.49
B40: GRUPO TRIANGULO AGRO | D40: Fertilizers | E40: 237309.12 | G40: 0 | K40: 117330.4
B41: GRUPO R3 | D41: Fertilizers | E41: 659074 | G41: 0 | J41: 659074
B42: GRUPO TAKI AGRO | D42: Fertilizers | E42: 110937.09
B43: Freight Debit Notes | D43: Additives | E43: 315229.74 | G43: 134546 | J43: 175719.14
B44: Not Due | D44: Additives | F44: =SUM(F47:F78) -> 18871537
D45: Int'll | F45: =SUM(F79:F86) -> 3652295.6
D46: Fertilizers | F46: =SUM(F87:F101) -> 13323347
B47: GRUPO MOSAIC FERTILIZANTES DO BRASIL | D47: Additives | F47: 4854100.6
B48: GRUPO CIBRA | D48: Additives | F48: 1106366.4
B49: GRUPO YARA | D49: Additives | F49: 1274871.2
B50: GRUPO ADUBOS ARAGUAIA | D50: Additives | F50: 731100.8
B51: GRUPO AMAGGI | D51: Additives | F51: 262079.7
B52: GRUPO UNIFERTIL | D52: Additives | F52: 1077992.3
B53: GRUPO HINOVE | D53: Additives | F53: 449952
B54: GRUPO FERTIPAR | D54: Additives | F54: 253506.3
B55: ADUFERTIL JUNDIAI | D55: Additives | F55: 31680
B56: FECOAGRO - SAO FRANCISCO DO SUL | D56: Additives | F56: 52255
B57: AURORA MINERAÇÃO LTDA | D57: Additives | F57: 338567.45
B58: COONAGRO COOPERATIVA - PARANAGUA | D58: Additives | F58: 137577.7
... B101: FAZENDA SANTA ELIZA | D101: Fertilizers | F101: 143620.48
B102: Total | E102: =SUM(E23:E43)+E12+E21+F22 -> 65372681 | F102: =SUM(F21:F22)+F12 -> 35847180 | G102: =+G22+G21+G12 -> 10799410

Sheet AR
J3: Credit Analysis | N3: Guarantee | S3: Remark
C4: CUSTOMER | D4: BU | E4: Total AR | F4: Overdue | G4: Not Due | H4: Provision | J4: Value | K4: Type | L4: Period days | N4: Value | O4: Type | P4: Due date | Q4: Tenor
C5: CENTRAL DO ADUBO | D5: Fertilizer | E5: =F5+G5 -> 7560727.8 | F5: ='Painel Fertilizers'!O4 -> 7560727.8 | G5: ='Painel Fertilizers'!P4 -> 0 | H5: ='Painel Fertilizers'!X4 -> 0 | J5: 0 | K5: 0 | L5: 0 | N5: 0 | O5: 0 | P5: 0 | Q5: 0 | S5: Judicial recovery plan presented but yet to be approved by Creditors Asembly: a meeting was held with AFT and a proposal of 65% discount on face value presented with a 18-month grace period and repayment over 10 years (in 20 installments). Adfert has not received further details on the restructuring plan as previously agreed in the end of Oct. Creditors assembly yet to be marked and a vote will occur for the Debtors recovery plan approval. Adfert advisors have a strong believe that the plan as AS-IS will not be approved and new financial conditions will be needed by the debtors
C6: SM AGRO / FAZ. BATURI | D6: Fertilizer | E6: =F6+G6 -> #REF! | F6: ='Painel Fertilizers'!#REF! -> #REF! | G6: ='Painel Fertilizers'!#REF! -> #REF! | H6: ='Painel Fertilizers'!#REF! -> #REF! | J6: 300000 | K6: Clean | L6: 0 | N6: 740000 | O6: CPR | P6: 45566 | Q6: 10 months | S6: Client has phisycally closed its reseller shop. Current overdue invoices were dully protested at the registry office and legal action has been filed. Awaiting court´s decision ordering the defendants to be served for payment
C7: CBM FERTILIZANTES | D7: Fertilizer | E7: =F7+G7 -> 0 | F7: ='Painel Fertilizers'!O20 -> 0 | G7: 0 | H7: 0 | N7: 4000000 | O7: CPR-G | P7: 45505 | Q7: 1 year | S7: Adfert has taken legal action and collection recovery lawsuit to be filed within November. An agreement for a payment plan was not successfull
C8: MOGIANA TECNO AGRO | D8: Fertilizer | E8: =F8+G8 -> 2026078 | F8: 1892360 | G8: ='Painel Fertilizers'!P20 -> 133718 | H8: ='Painel Fertilizers'!X5 -> 3088531.1 | J8: 1000000 | K8: Surety Bond | L8: 360 | N8: 1892360 | O8: Surety Bond | P8: 45597 | Q8: 1 year | S8: The judicial collection lawsuit plan was signed and filed. Court decision has approved the settement agreement establishing a 24 months payment plan (montlhy payment). 1st installment not paid and the judicial collection is ongoing
C9: CASA DAS SEMENTES | D9: Fertilizer | E9: =F9+G9 -> 3044850.9 | F9: ='Painel Fertilizers'!O6 -> 3044850.9 | G9: ='Painel Fertilizers'!P6 -> 0 | H9: ='Painel Fertilizers'!X6 -> 3044850.9 | J9: 2000000 | K9: Surety Bond | L9: 120 | S9: Provision 100%. Client’s overdues were protested at the registry office. Legal process ongoing
C10: TERRA FERTIL - MACHADO | D10: Fertilizer | E10: =F10+G10 -> 876011.75 | F10: ='Painel Fertilizers'!O10 -> 876011.75 | G10: ='Painel Fertilizers'!P10 -> 0 | H10: ='Painel Fertilizers'!X10 -> 0 | N10: 5517407.7 | O10: Surety Bond | P10: 45606 | Q10: 1 year | S10: Guarantee sent to the legal department so that they begin legal proceedings to collect the amount due
C11: AGROBERALDO | D11: Fertilizer | E11: =F11+G11 -> 0 | F11: ='Painel Fertilizers'!O22 -> 0 | G11: ='Painel Fertilizers'!P22 -> 0 | H11: ='Painel Fertilizers'!X22 -> 0 | N11: 3000000 | O11: Surety Bond | P11: 45627 | Q11: 1 year | S11: Guarantee sent to the legal department so that they begin legal proceedings to collect the amount due
C12: Total Over Due in Litigation | E12: =SUM(E5:E11) -> #REF! | F12: =SUM(F5:F11) -> #REF! | G12: =SUM(G5:G11) -> #REF! | H12: =SUM(H5:H11) -> #REF!
C13: PLANTA RICA AGRONEGÓCIOS LTDA | D13: Fertilizers | E13: =F13+G13 -> 110528 | F13: 110528 | G13: 0 | H13: 110528 | S13: old overdue
C14: FAZENDA BRAVINHOS | D14: Fertilizers | E14: =F14+G14 -> 34132.18 | F14: 34132.18 | G14: 0 | H14: 1023.9654 | S14: Judicial recovery started
C15: EQUILIBRIO - MOGI MIRIM | D15: Fertilizers | E15: =F15+G15 -> 22222.25 | F15: 22222.25 | G15: 0 | H15: 22222.25 | S15: old overdue
C16: TERRA FERTILIZANTES LTDA | D16: Aditives | E16: =F16+G16 -> 226233.6 | F16: 226233.6 | G16: 0 | H16: ='Painel Additive'!X6 -> 63226.32 | S16: Judicial recovery started
C17: PLANT BEM - PARANAGUÁ | D17: Aditives | E17: =F17+G17 -> 140872.6 | F17: 140872.6 | G17: 0 | H17: 140872.6 | S17: old overdue
C18: FERTISANTA FERTILIZANTES | D18: Aditives | E18: =F18+G18 -> 41379 | F18: 41379 | G18: 0 | H18: 41379 | S18: old overdue
C19: DELCORP S.A | D19: Aditives | E19: =F19+G19 -> 84291.45 | F19: 84291.45 | G19: 0 | H19: 84291.45 | S19: old overdue
C20: Total Over Due with Possible Loss | E20: =SUM(E13:E19) -> 659659.08 | F20: =SUM(F13:F19) -> 659659.08 | G20: =SUM(G13:G19) -> 0 | H20: =SUM(H13:H19) -> 463543.59
C21: Low Risk - Expect to Receive soon | E21: =F21+G21 -> #REF! | F21: =-(F20+F12)+'Painel Additive'!O1+'Painel Fertilizers'!O1+'Painel International'!O1 -> #REF! | G21: 0 | H21: ='Bad Debt Provision'!#REF! - (H12+H20) -> #REF! | S21: Provision as per corporate policy
C22: Not Due | E22: =F22+G22 -> 34736830 | F22: 0 | G22: ='Painel Additive'!P1+'Painel Fertilizers'!P1+'Painel International'!P1 -> 34736830 | H22: 0
C23: Total | E23: =SUM(E20:E22)+E12 -> #REF! | F23: =SUM(F20:F22)+F12 -> #REF! | G23: =SUM(G20:G22)+G12 -> #REF! | H23: =SUM(H20:H22)+H12 -> #REF!

Sheet Data total
D1: =SUBTOTAL(9,D3:D1086) -> 59548326 | E1: ='Data Additive'!D1+'Data Fertilizers'!D1+'Data International'!D1 -> 59371743 | F1: ='Data Additive'!D1+'Data Fertilizers'!D1+'Data International'!D1+'freight debit notes'!D1 -> 59548326 | G1: =D1-F1 -> 0 | R1: 46141
A2: CODPARC | B2: NOMEPARC | C2: CNPJ | D2: Valor | E2: NUFIN | F2: DTVENC | G2: DHBAIXA | H2: AD_BU | I2: NOME_BU | J2: NUMNOTA | K2: DTENTSAI | L2: CODNAT | M2: DESCRNAT | N2: CODTIPOPER | O2: OPERACAO | P2: Grupo | Q2: Dias vencidos
A3: 205 | B3: FERTIPAR - RONDONÓPOLIS | C3: 09.384.948/0002-43 | D3: 80589.6 | E3: 1246271690 | F3: 46157 | H3: 1 | I3: Adtives | J3: 11158 | K3: 46129 | L3: 1010100 | M3: VENDAS MERCADO INTERNO | N3: 161 | O3: VENDA PROD. INDUSTRIALIZADO - NFE | P3: GRUPO FERTIPAR FERTILIZANTES MATO GROSSO | Q3: =$R$1-F3 -> -16 | R3: =_xlfn.XLOOKUP(E3,'Data Additive'!E:E,'Data Additive'!E:E,0) -> 1246271690
A4: 205 | B4: FERTIPAR - RONDONÓPOLIS | C4: 09.384.948/0002-43 | D4: 81051.4 | E4: 1246273002 | F4: 46168 | H4: 1 | I4: Adtives | J4: 11248 | K4: 46140 | L4: 1010100 | M4: VENDAS MERCADO INTERNO | N4: 161 | O4: VENDA PROD. INDUSTRIALIZADO - NFE | P4: GRUPO FERTIPAR FERTILIZANTES MATO GROSSO | Q4: =$R$1-F4 -> -27 | R4: =_xlfn.XLOOKUP(E4,'Data Additive'!E:E,'Data Additive'!E:E,0) -> 1246273002
A5: 1257 | B5: MOSAIC - CAMPO GRANDE | C5: 61.156.501/0081-30 | D5: 1980.8 | E5: 1246032946 | F5: 44774 | H5: 1 | I5: Adtives | J5: 17935 | K5: 44714 | L5: 1010100 | M5: VENDAS MERCADO INTERNO | N5: 56 | O5: VENDA A ORDEM | P5: GRUPO MOSAIC FERTILIZANTES DO BRASIL | Q5: =$R$1-F5 -> 1367 | R5: =_xlfn.XLOOKUP(E5,'Data Additive'!E:E,'Data Additive'!E:E,0) -> 1246032946
A6: 1953 | B6: AMAGGI - COMODORO | C6: 77.294.254/0075-20 | D6: 58917.8 | E6: 1246267986 | F6: 46158 | H6: 1 | I6: Adtives | J6: 10907 | K6: 46098 | L6: 1010100 | M6: VENDAS MERCADO INTERNO | N6: 161 | O6: VENDA PROD. INDUSTRIALIZADO - NFE | P6: GRUPO AMAGGI | Q6: =$R$1-F6 -> -17 | R6: =_xlfn.XLOOKUP(E6,'Data Additive'!E:E,'Data Additive'!E:E,0) -> 1246267986
A7: 1787 | B7: MOSAIC - UBERABA (CIU1) | C7: 33.931.486/0014-55 | D7: 107059.2 | E7: 1246262114 | F7: 46146 | G7: 46146 | H7: 1 | I7: Adtives | J7: 10629 | K7: 46056 | L7: 1010100 | M7: VENDAS MERCADO INTERNO | N7: 161 | O7: VENDA PROD. INDUSTRIALIZADO - NFE | P7: GRUPO MOSAIC FERTILIZANTES P K LTDA | Q7: =$R$1-F7 -> -5 | R7: =_xlfn.XLOOKUP(E7,'Data Additive'!E:E,'Data Additive'!E:E,0) -> 1246262114
A8: 1787 | B8: MOSAIC - UBERABA (CIU1) | C8: 33.931.486/0014-55 | D8: 3600 | E8: 1246031589 | F8: 44784 | H8: 1 | I8: Adtives | J8: 1246031589 | K8: 44769 | L8: 3041000 | M8: FRETES DIVERSOS | N8: 46 | O8: FINANCEIRO GERAL | P8: GRUPO MOSAIC FERTILIZANTES P K LTDA | Q8: =$R$1-F8 -> 1357 | R8: =_xlfn.XLOOKUP(E8,'Data Additive'!E:E,'Data Additive'!E:E,0) -> 0
A9: 1787 | B9: MOSAIC - UBERABA (CIU1) | C9: 33.931.486/0014-55 | D9: 2700 | E9: 1246055596 | F9: 44889 | H9: 1 | I9: Adtives | J9: 1246055596 | K9: 44889 | L9: 3041000 | M9: FRETES DIVERSOS | N9: 46 | O9: FINANCEIRO GERAL | P9: GRUPO MOSAIC FERTILIZANTES P K LTDA | Q9: =$R$1-F9 -> 1252 | R9: =_xlfn.XLOOKUP(E9,'Data Additive'!E:E,'Data Additive'!E:E,0) -> 0
A10: 1787 | B10: MOSAIC - UBERABA (CIU1) | C10: 33.931.486/0014-55 | D10: 109862.4 | E10: 1246271310 | F10: 46216 | H10: 1 | I10: Adtives | J10: 11116 | K10: 46126 | L10: 1010100 | M10: VENDAS MERCADO INTERNO | N10: 161 | O10: VENDA PROD. INDUSTRIALIZADO - NFE | P10: GRUPO MOSAIC FERTILIZANTES P K LTDA | Q10: =$R$1-F10 -> -75 | R10: =_xlfn.XLOOKUP(E10,'Data Additive'!E:E,'Data Additive'!E:E,0) -> 1246271310
A11: 1787 | B11: MOSAIC - UBERABA (CIU1) | C11: 33.931.486/0014-55 | D11: 116928 | E11: 1246267948 | F11: 46187 | H11: 1 | I11: Adtives | J11: 10899 | K11: 46097 | L11: 1010100 | M11: VENDAS MERCADO INTERNO | N11: 161 | O11: VENDA PROD. INDUSTRIALIZADO - NFE | P11: GRUPO MOSAIC FERTILIZANTES P K LTDA | Q11: =$R$1-F11 -> -46 | R11: =_xlfn.XLOOKUP(E11,'Data Additive'!E:E,'Data Additive'!E:E,0) -> 1246267948
A12: 1787 | B12: MOSAIC - UBERABA (CIU1) | C12: 33.931.486/0014-55 | D12: 115891.2 | E12: 1246262540 | F12: 46149 | H12: 1 | I12: Adtives | J12: 10652 | K12: 46059 | L12: 1010100 | M12: VENDAS MERCADO INTERNO | N12: 161 | O12: VENDA PROD. INDUSTRIALIZADO - NFE | P12: GRUPO MOSAIC FERTILIZANTES P K LTDA | Q12: =$R$1-F12 -> -8 | R12: =_xlfn.XLOOKUP(E12,'Data Additive'!E:E,'Data Additive'!E:E,0) -> 1246262540
A13: 1787 | B13: MOSAIC - UBERABA (CIU1) | C13: 33.931.486/0014-55 | D13: 103795.2 | E13: 1246268633 | F13: 46194 | H13: 1 | I13: Adtives | J13: 10957 | K13: 46104 | L13: 1010100 | M13: VENDAS MERCADO INTERNO | N13: 161 | O13: VENDA PROD. INDUSTRIALIZADO - NFE | P13: GRUPO MOSAIC FERTILIZANTES P K LTDA | Q13: =$R$1-F13 -> -53 | R13: =_xlfn.XLOOKUP(E13,'Data Additive'!E:E,'Data Additive'!E:E,0) -> 1246268633
A14: 1787 | B14: MOSAIC - UBERABA (CIU1) | C14: 33.931.486/0014-55 | D14: 111360 | E14: 1246268748 | F14: 46195 | H14: 1 | I14: Adtives | J14: 10965 | K14: 46105 | L14: 1010100 | M14: VENDAS MERCADO INTERNO | N14: 161 | O14: VENDA PROD. INDUSTRIALIZADO - NFE | P14: GRUPO MOSAIC FERTILIZANTES P K LTDA | Q14: =$R$1-F14 -> -54 | R14: =_xlfn.XLOOKUP(E14,'Data Additive'!E:E,'Data Additive'!E:E,0) -> 1246268748
A15: 1787 | B15: MOSAIC - UBERABA (CIU1) | C15: 33.931.486/0014-55 | D15: 114662.4 | E15: 1246268585 | F15: 46161 | H15: 1 | I15: Adtives | J15: 10953 | K15: 46101 | L15: 1010100 | M15: VENDAS MERCADO INTERNO | N15: 161 | O15: VENDA PROD. INDUSTRIALIZADO - NFE | P15: GRUPO MOSAIC FERTILIZANTES P K LTDA | Q15: =$R$1-F15 -> -20 | R15: =_xlfn.XLOOKUP(E15,'Data Additive'!E:E,'Data Additive'!E:E,0) -> 1246268585
A16: 1787 | B16: MOSAIC - UBERABA (CIU1) | C16: 33.931.486/0014-55 | D16: 115852.8 | E16: 1246270635 | F16: 46210 | H16: 1 | I16: Adtives | J16: 11072 | K16: 46120 | L16: 1010100 | M16: VENDAS MERCADO INTERNO | N16: 161 | O16: VENDA PROD. INDUSTRIALIZADO - NFE | P16: GRUPO MOSAIC FERTILIZANTES P K LTDA | Q16: =$R$1-F16 -> -69 | R16: =_xlfn.XLOOKUP(E16,'Data Additive'!E:E,'Data Additive'!E:E,0) -> 1246270635
A17: 1787 | B17: MOSAIC - UBERABA (CIU1) | C17: 33.931.486/0014-55 | D17: 114739.2 | E17: 1246271165 | F17: 46215 | H17: 1 | I17: Adtives | J17: 11105 | K17: 46125 | L17: 1010100 | M17: VENDAS MERCADO INTERNO | N17: 161 | O17: VENDA PROD. INDUSTRIALIZADO - NFE | P17: GRUPO MOSAIC FERTILIZANTES P K LTDA | Q17: =$R$1-F17 -> -74 | R17: =_xlfn.XLOOKUP(E17,'Data Additive'!E:E,'Data Additive'!E:E,0) -> 1246271165
A18: 1787 | B18: MOSAIC - UBERABA (CIU1) | C18: 33.931.486/0014-55 | D18: 114969.6 | E18: 1246264543 | F18: 46166 | H18: 1 | I18: Adtives | J18: 10746 | K18: 46076 | L18: 1010100 | M18: VENDAS MERCADO INTERNO | N18: 161 | O18: VENDA PROD. INDUSTRIALIZADO - NFE | P18: GRUPO MOSAIC FERTILIZANTES P K LTDA | Q18: =$R$1-F18 -> -25 | R18: =_xlfn.XLOOKUP(E18,'Data Additive'!E:E,'Data Additive'!E:E,0) -> 1246264543
A19: 1787 | B19: MOSAIC - UBERABA (CIU1) | C19: 33.931.486/0014-55 | D19: 113356.8 | E19: 1246269731 | F19: 46202 | H19: 1 | I19: Adtives | J19: 11014 | K19: 46112 | L19: 1010100 | M19: VENDAS MERCADO INTERNO | N19: 161 | O19: VENDA PROD. INDUSTRIALIZADO - NFE | P19: GRUPO MOSAIC FERTILIZANTES P K LTDA | Q19: =$R$1-F19 -> -61 | R19: =_xlfn.XLOOKUP(E19,'Data Additive'!E:E,'Data Additive'!E:E,0) -> 1246269731
... A76: 33 | B76: HERINGER - PARANAGUÁ | C76: 22.266.175/0031-01 | D76: 99167.6 | E76: 1246271248 | F76: 46155 | H76: 1 | I76: Adtives | J76: 11114 | K76: 46125 | L76: 1010100 | M76: VENDAS MERCADO INTERNO | N76: 161 | O76: VENDA PROD. INDUSTRIALIZADO - NFE | P76: GRUPO HERINGER | Q76: =$R$1-F76 -> -14 | R76: =_xlfn.XLOOKUP(E76,'Data Additive'!E:E,'Data Additive'!E:E,0) -> 1246271248
A77: 214 | B77: UNIFERTIL - CANOAS UN1 | C77: 87.249.561/0001-07 | D77: 82931.8 | E77: 1246270505 | F77: 46147 | G77: 46147 | H77: 1 | I77: Adtives | J77: 11065 | K77: 46119 | L77: 1010100 | M77: VENDAS MERCADO INTERNO | N77: 161 | O77: VENDA PROD. INDUSTRIALIZADO - NFE | P77: GRUPO UNIFERTIL | Q77: =$R$1-F77 -> -6 | R77: =_xlfn.XLOOKUP(E77,'Data Additive'!E:E,'Data Additive'!E:E,0) -> 1246270505
A78: 214 | B78: UNIFERTIL - CANOAS UN1 | C78: 87.249.561/0001-07 | D78: 82854.1 | E78: 1246272851 | F78: 46167 | H78: 1 | I78: Adtives | J78: 11237 | K78: 46139 | L78: 1010100 | M78: VENDAS MERCADO INTERNO | N78: 161 | O78: VENDA PROD. INDUSTRIALIZADO - NFE | P78: GRUPO UNIFERTIL | Q78: =$R$1-F78 -> -26 | R78: =_xlfn.XLOOKUP(E78,'Data Additive'!E:E,'Data Additive'!E:E,0) -> 1246272851
A79: 214 | B79: UNIFERTIL - CANOAS UN1 | C79: 87.249.561/0001-07 | D79: 99281.7 | E79: 1246271672 | F79: 46157 | H79: 1 | I79: Adtives | J79: 11156 | K79: 46129 | L79: 1010100 | M79: VENDAS MERCADO INTERNO | N79: 161 | O79: VENDA PROD. INDUSTRIALIZADO - NFE | P79: GRUPO UNIFERTIL | Q79: =$R$1-F79 -> -16 | R79: =_xlfn.XLOOKUP(E79,'Data Additive'!E:E,'Data Additive'!E:E,0) -> 1246271672
A80: 2 | B80: CARGILL - UBERLÂNDIA | C80: 60.498.706/0134-88 | D80: 13431 | E80: 1246272905 | F80: 46168 | G80: 46146 | H80: 3 | I80: Job Work | J80: 2898 | K80: 46140 | L80: 1010100 | M80: VENDAS MERCADO INTERNO | N80: 199 | O80: VENDA MERC INDUSTRIALIZADA TERCEIROS | P80: GRUPO CARGILL | Q80: =$R$1-F80 -> -27 | R80: =_xlfn.XLOOKUP(E80,'Data Additive'!E:E,'Data Additive'!E:E,0) -> 1246272905
A81: 183 | B81: HERINGER - RONDONÓPOLIS II | C81: 22.266.175/0036-08 | D81: 4231.96 | E81: 1246014155 | F81: 47847 | H81: 1 | I81: Adtives | J81: 8361 | K81: 43384 | L81: 1010100 | M81: VENDAS MERCADO INTERNO | N81: 161 | O81: VENDA PROD. INDUSTRIALIZADO - NFE | P81: GRUPO HERINGER | Q81: =$R$1-F81 -> -1706 | R81: =_xlfn.XLOOKUP(E81,'Data Additive'!E:E,'Data Additive'!E:E,0) -> 1246014155
A82: 183 | B82: HERINGER - RONDONÓPOLIS II | C82: 22.266.175/0036-08 | D82: 4045.01 | E82: 1246014156 | F82: 48212 | H82: 1 | I82: Adtives | J82: 8361 | K82: 43384 | L82: 1010100 | M82: VENDAS MERCADO INTERNO | N82: 161 | O82: VENDA PROD. INDUSTRIALIZADO - NFE | P82: GRUPO HERINGER | Q82: =$R$1-F82 -> -2071 | R82: =_xlfn.XLOOKUP(E82,'Data Additive'!E:E,'Data Additive'!E:E,0) -> 1246014156
A83: 183 | B83: HERINGER - RONDONÓPOLIS II | C83: 22.266.175/0036-08 | D83: 4339.6 | E83: 1246014157 | F83: 48578 | H83: 1 | I83: Adtives | J83: 8361 | K83: 43384 | L83: 1010100 | M83: VENDAS MERCADO INTERNO | N83: 161 | O83: VENDA PROD. INDUSTRIALIZADO - NFE | P83: GRUPO HERINGER | Q83: =$R$1-F83 -> -2437 | R83: =_xlfn.XLOOKUP(E83,'Data Additive'!E:E,'Data Additive'!E:E,0) -> 1246014157
A84: 183 | B84: HERINGER - RONDONÓPOLIS II | C84: 22.266.175/0036-08 | D84: 7512.16 | E84: 1246014158 | F84: 48943 | H84: 1 | I84: Adtives | J84: 8361 | K84: 43384 | L84: 1010100 | M84: VENDAS MERCADO INTERNO | N84: 161 | O84: VENDA PROD. INDUSTRIALIZADO - NFE | P84: GRUPO HERINGER | Q84: =$R$1-F84 -> -2802 | R84: =_xlfn.XLOOKUP(E84,'Data Additive'!E:E,'Data Additive'!E:E,0) -> 1246014158
A85: 183 | B85: HERINGER - RONDONÓPOLIS II | C85: 22.266.175/0036-08 | D85: 30552.86 | E85: 1246014159 | F85: 49308 | H85: 1 | I85: Adtives | J85: 8361 | K85: 43384 | L85: 1010100 | M85: VENDAS MERCADO INTERNO | N85: 161 | O85: VENDA PROD. INDUSTRIALIZADO - NFE | P85: GRUPO HERINGER | Q85: =$R$1-F85 -> -3167 | R85: =_xlfn.XLOOKUP(E85,'Data Additive'!E:E,'Data Additive'!E:E,0) -> 1246014159
A86: 183 | B86: HERINGER - RONDONÓPOLIS II | C86: 22.266.175/0036-08 | D86: 1512.63 | E86: 1246014161 | F86: 50039 | H86: 1 | I86: Adtives | J86: 8361 | K86: 43384 | L86: 1010100 | M86: VENDAS MERCADO INTERNO | N86: 161 | O86: VENDA PROD. INDUSTRIALIZADO - NFE | P86: GRUPO HERINGER | Q86: =$R$1-F86 -> -3898 | R86: =_xlfn.XLOOKUP(E86,'Data Additive'!E:E,'Data Additive'!E:E,0) -> 1246014161
A87: 183 | B87: HERINGER - RONDONÓPOLIS II | C87: 22.266.175/0036-08 | D87: 1982.85 | E87: 1246014162 | F87: 50404 | H87: 1 | I87: Adtives | J87: 8361 | K87: 43384 | L87: 1010100 | M87: VENDAS MERCADO INTERNO | N87: 161 | O87: VENDA PROD. INDUSTRIALIZADO - NFE | P87: GRUPO HERINGER | Q87: =$R$1-F87 -> -4263 | R87: =_xlfn.XLOOKUP(E87,'Data Additive'!E:E,'Data Additive'!E:E,0) -> 1246014162
A88: 183 | B88: HERINGER - RONDONÓPOLIS II | C88: 22.266.175/0036-08 | D88: 2549.38 | E88: 1246014163 | F88: 50769 | H88: 1 | I88: Adtives | J88: 8361 | K88: 43384 | L88: 1010100 | M88: VENDAS MERCADO INTERNO | N88: 161 | O88: VENDA PROD. INDUSTRIALIZADO - NFE | P88: GRUPO HERINGER | Q88: =$R$1-F88 -> -4628 | R88: =_xlfn.XLOOKUP(E88,'Data Additive'!E:E,'Data Additive'!E:E,0) -> 1246014163
A89: 183 | B89: HERINGER - RONDONÓPOLIS II | C89: 22.266.175/0036-08 | D89: 5546.31 | E89: 1246014165 | F89: 51500 | H89: 1 | I89: Adtives | J89: 8361 | K89: 43384 | L89: 1010100 | M89: VENDAS MERCADO INTERNO | N89: 161 | O89: VENDA PROD. INDUSTRIALIZADO - NFE | P89: GRUPO HERINGER | Q89: =$R$1-F89 -> -5359 | R89: =_xlfn.XLOOKUP(E89,'Data Additive'!E:E,'Data Additive'!E:E,0) -> 1246014165
A90: 183 | B90: HERINGER - RONDONÓPOLIS II | C90: 22.266.175/0036-08 | D90: 5546.31 | E90: 1246014166 | F90: 51865 | H90: 1 | I90: Adtives | J90: 8361 | K90: 43384 | L90: 1010100 | M90: VENDAS MERCADO INTERNO | N90: 161 | O90: VENDA PROD. INDUSTRIALIZADO - NFE | P90: GRUPO HERINGER | Q90: =$R$1-F90 -> -5724 | R90: =_xlfn.XLOOKUP(E90,'Data Additive'!E:E,'Data Additive'!E:E,0) -> 1246014166
A91: 183 | B91: HERINGER - RONDONÓPOLIS II | C91: 22.266.175/0036-08 | D91: 5546.31 | E91: 1246014167 | F91: 52230 | H91: 1 | I91: Adtives | J91: 8361 | K91: 43384 | L91: 1010100 | M91: VENDAS MERCADO INTERNO | N91: 161 | O91: VENDA PROD. INDUSTRIALIZADO - NFE | P91: GRUPO HERINGER | Q91: =$R$1-F91 -> -6089 | R91: =_xlfn.XLOOKUP(E91,'Data Additive'!E:E,'Data Additive'!E:E,0) -> 1246014167
A92: 183 | B92: HERINGER - RONDONÓPOLIS II | C92: 22.266.175/0036-08 | D92: 5546.31 | E92: 1246014168 | F92: 52595 | H92: 1 | I92: Adtives | J92: 8361 | K92: 43384 | L92: 1010100 | M92: VENDAS MERCADO INTERNO | N92: 161 | O92: VENDA PROD. INDUSTRIALIZADO - NFE | P92: GRUPO HERINGER | Q92: =$R$1-F92 -> -6454 | R92: =_xlfn.XLOOKUP(E92,'Data Additive'!E:E,'Data Additive'!E:E,0) -> 1246014168
... A112: 201 | B112: JOSAPAR - PELOTAS | C112: 87.456.562/0006-37 | D112: 185040 | E112: 1246269671 | F112: 46231 | H112: 1 | I112: Adtives | J112: 2855 | K112: 46111 | L112: 1010100 | M112: VENDAS MERCADO INTERNO | N112: 161 | O112: VENDA PROD. INDUSTRIALIZADO - NFE | P112: GRUPO JOSAPAR | Q112: =$R$1-F112 -> -90 | R112: =_xlfn.XLOOKUP(E112,'Data Additive'!E:E,'Data Additive'!E:E,0) -> 1246269671
A113: 903 | B113: YARA - PONTA GROSSA | C113: 92.660.604/0138-37 | D113: 133334.43 | E113: 1246268951 | F113: 46146 | G113: 46146 | H113: 1 | I113: Adtives | J113: 10971 | K113: 46106 | L113: 1010100 | M113: VENDAS MERCADO INTERNO | N113: 161 | O113: VENDA PROD. INDUSTRIALIZADO - NFE | P113: GRUPO YARA | Q113: =$R$1-F113 -> -5 | R113: =_xlfn.XLOOKUP(E113,'Data Additive'!E:E,'Data Additive'!E:E,0) -> 1246268951
A114: 903 | B114: YARA - PONTA GROSSA | C114: 92.660.604/0138-37 | D114: 135135.03 | E114: 1246272230 | F114: 46175 | H114: 1 | I114: Adtives | J114: 11199 | K114: 46135 | L114: 1010100 | M114: VENDAS MERCADO INTERNO | N114: 161 | O114: VENDA PROD. INDUSTRIALIZADO - NFE | P114: GRUPO YARA | Q114: =$R$1-F114 -> -34 | R114: =_xlfn.XLOOKUP(E114,'Data Additive'!E:E,'Data Additive'!E:E,0) -> 1246272230
A115: 903 | B115: YARA - PONTA GROSSA | C115: 92.660.604/0138-37 | D115: 134594.85 | E115: 1246270087 | F115: 46154 | H115: 1 | I115: Adtives | J115: 11034 | K115: 46114 | L115: 1010100 | M115: VENDAS MERCADO INTERNO | N115: 161 | O115: VENDA PROD. INDUSTRIALIZADO - NFE | P115: GRUPO YARA | Q115: =$R$1-F115 -> -13 | R115: =_xlfn.XLOOKUP(E115,'Data Additive'!E:E,'Data Additive'!E:E,0) -> 1246270087
A116: 903 | B116: YARA - PONTA GROSSA | C116: 92.660.604/0138-37 | D116: 134504.82 | E116: 1246271047 | F116: 46162 | H116: 1 | I116: Adtives | J116: 11098 | K116: 46122 | L116: 1010100 | M116: VENDAS MERCADO INTERNO | N116: 161 | O116: VENDA PROD. INDUSTRIALIZADO - NFE | P116: GRUPO YARA | Q116: =$R$1-F116 -> -21 | R116: =_xlfn.XLOOKUP(E116,'Data Additive'!E:E,'Data Additive'!E:E,0) -> 1246271047
A117: 903 | B117: YARA - PONTA GROSSA | C117: 92.660.604/0138-37 | D117: 134864.94 | E117: 1246269425 | F117: 46148 | H117: 1 | I117: Adtives | J117: 10990 | K117: 46108 | L117: 1010100 | M117: VENDAS MERCADO INTERNO | N117: 161 | O117: VENDA PROD. INDUSTRIALIZADO - NFE | P117: GRUPO YARA | Q117: =$R$1-F117 -> -7 | R117: =_xlfn.XLOOKUP(E117,'Data Additive'!E:E,'Data Additive'!E:E,0) -> 1246269425
A118: 903 | B118: YARA - PONTA GROSSA | C118: 92.660.604/0138-37 | D118: 134774.91 | E118: 1246273177 | F118: 46182 | H118: 1 | I118: Adtives | J118: 11266 | K118: 46142 | L118: 1010100 | M118: VENDAS MERCADO INTERNO | N118: 161 | O118: VENDA PROD. INDUSTRIALIZADO - NFE | P118: GRUPO YARA | Q118: =$R$1-F118 -> -41 | R118: =_xlfn.XLOOKUP(E118,'Data Additive'!E:E,'Data Additive'!E:E,0) -> 1246273177
A119: 86 | B119: ADUBOS ARAGUAIA - ANAPOLIS | C119: 03.306.578/0012-11 | D119: 35810 | E119: 1246273225 | F119: 46202 | H119: 1 | I119: Adtives | J119: 11271 | K119: 46142 | L119: 1010100 | M119: VENDAS MERCADO INTERNO | N119: 161 | O119: VENDA PROD. INDUSTRIALIZADO - NFE | P119: GRUPO ADUBOS ARAGUAIA | Q119: =$R$1-F119 -> -61 | R119: =_xlfn.XLOOKUP(E119,'Data Additive'!E:E,'Data Additive'!E:E,0) -> 1246273225
A120: 729 | B120: FERTILIZ. TOCANTINS - SÃO LUIS | C120: 05.571.228/0003-17 | D120: 69762.4 | E120: 1246273030 | F120: 46201 | H120: 1 | I120: Adtives | J120: 11251 | K120: 46141 | L120: 1010100 | M120: VENDAS MERCADO INTERNO | N120: 161 | O120: VENDA PROD. INDUSTRIALIZADO - NFE | P120: GRUPO FERTILIZ TOCANTINS | Q120: =$R$1-F120 -> -60 | R120: =_xlfn.XLOOKUP(E120,'Data Additive'!E:E,'Data Additive'!E:E,0) -> 1246273030
A121: 1159 | B121: YARA - RIO GRANDE | C121: 92.660.604/0013-16 | D121: 272555.72 | E121: 1246268636 | F121: 46144 | G121: 46146 | H121: 1 | I121: Adtives | J121: 10958 | K121: 46104 | L121: 1010100 | M121: VENDAS MERCADO INTERNO | N121: 161 | O121: VENDA PROD. INDUSTRIALIZADO - NFE | P121: GRUPO YARA | Q121: =$R$1-F121 -> -3 | R121: =_xlfn.XLOOKUP(E121,'Data Additive'!E:E,'Data Additive'!E:E,0) -> 1246268636
A122: 1159 | B122: YARA - RIO GRANDE | C122: 92.660.604/0013-16 | D122: 8928.75 | E122: 1246273695 | F122: 46180 | G122: 46148 | H122: 1 | I122: Adtives | J122: 11240 | K122: 46140 | L122: 1010100 | M122: VENDAS MERCADO INTERNO | N122: 161 | O122: VENDA PROD. INDUSTRIALIZADO - NFE | P122: GRUPO YARA | Q122: =$R$1-F122 -> -39 | R122: =_xlfn.XLOOKUP(E122,'Data Additive'!E:E,'Data Additive'!E:E,0) -> 1246273695
A123: 1159 | B123: YARA - RIO GRANDE | C123: 92.660.604/0013-16 | D123: 1800 | E123: 1246087936 | F123: 45112 | H123: 1 | I123: Adtives | J123: 1246087936 | K123: 45097 | L123: 3041000 | M123: FRETES DIVERSOS | N123: 46 | O123: FINANCEIRO GERAL | P123: GRUPO YARA | Q123: =$R$1-F123 -> 1029 | R123: =_xlfn.XLOOKUP(E123,'Data Additive'!E:E,'Data Additive'!E:E,0) -> 0
A124: 1159 | B124: YARA - RIO GRANDE | C124: 92.660.604/0013-16 | D124: 2700 | E124: 1246087941 | F124: 45112 | H124: 1 | I124: Adtives | J124: 1246087941 | K124: 45097 | L124: 3041000 | M124: FRETES DIVERSOS | N124: 46 | O124: FINANCEIRO GERAL | P124: GRUPO YARA | Q124: =$R$1-F124 -> 1029 | R124: =_xlfn.XLOOKUP(E124,'Data Additive'!E:E,'Data Additive'!E:E,0) -> 0
A125: 1159 | B125: YARA - RIO GRANDE | C125: 92.660.604/0013-16 | D125: 1800 | E125: 1246087939 | F125: 45112 | H125: 1 | I125: Adtives | J125: 1246087939 | K125: 45097 | L125: 3041000 | M125: FRETES DIVERSOS | N125: 46 | O125: FINANCEIRO GERAL | P125: GRUPO YARA | Q125: =$R$1-F125 -> 1029 | R125: =_xlfn.XLOOKUP(E125,'Data Additive'!E:E,'Data Additive'!E:E,0) -> 0
A126: 1159 | B126: YARA - RIO GRANDE | C126: 92.660.604/0013-16 | D126: 1800 | E126: 1246087937 | F126: 45112 | H126: 1 | I126: Adtives | J126: 1246087937 | K126: 45097 | L126: 3041000 | M126: FRETES DIVERSOS | N126: 46 | O126: FINANCEIRO GERAL | P126: GRUPO YARA | Q126: =$R$1-F126 -> 1029 | R126: =_xlfn.XLOOKUP(E126,'Data Additive'!E:E,'Data Additive'!E:E,0) -> 0
A127: 1159 | B127: YARA - RIO GRANDE | C127: 92.660.604/0013-16 | D127: 1800 | E127: 1246087943 | F127: 45112 | H127: 1 | I127: Adtives | J127: 1246087943 | K127: 45097 | L127: 3041000 | M127: FRETES DIVERSOS | N127: 46 | O127: FINANCEIRO GERAL | P127: GRUPO YARA | Q127: =$R$1-F127 -> 1029 | R127: =_xlfn.XLOOKUP(E127,'Data Additive'!E:E,'Data Additive'!E:E,0) -> 0
A128: 1159 | B128: YARA - RIO GRANDE | C128: 92.660.604/0013-16 | D128: 2700 | E128: 1246121301 | F128: 45297 | H128: 1 | I128: Adtives | J128: 1246121301 | K128: 45282 | L128: 3041000 | M128: FRETES DIVERSOS | N128: 46 | O128: FINANCEIRO GERAL | P128: GRUPO YARA | Q128: =$R$1-F128 -> 844 | R128: =_xlfn.XLOOKUP(E128,'Data Additive'!E:E,'Data Additive'!E:E,0) -> 0
A129: 1159 | B129: YARA - RIO GRANDE | C129: 92.660.604/0013-16 | D129: 4800 | E129: 1246121285 | F129: 45297 | H129: 1 | I129: Adtives | J129: 1246121285 | K129: 45282 | L129: 3041000 | M129: FRETES DIVERSOS | N129: 46 | O129: FINANCEIRO GERAL | P129: GRUPO YARA | Q129: =$R$1-F129 -> 844 | R129: =_xlfn.XLOOKUP(E129,'Data Additive'!E:E,'Data Additive'!E:E,0) -> 0
A130: 1159 | B130: YARA - RIO GRANDE | C130: 92.660.604/0013-16 | D130: 2700 | E130: 1246121300 | F130: 45297 | H130: 1 | I130: Adtives | J130: 1246121300 | K130: 45282 | L130: 3041000 | M130: FRETES DIVERSOS | N130: 46 | O130: FINANCEIRO GERAL | P130: GRUPO YARA | Q130: =$R$1-F130 -> 844 | R130: =_xlfn.XLOOKUP(E130,'Data Additive'!E:E,'Data Additive'!E:E,0) -> 0
A131: 1159 | B131: YARA - RIO GRANDE | C131: 92.660.604/0013-16 | D131: 1800 | E131: 1246121298 | F131: 45297 | H131: 1 | I131: Adtives | J131: 1246121298 | K131: 45282 | L131: 3041000 | M131: FRETES DIVERSOS | N131: 46 | O131: FINANCEIRO GERAL | P131: GRUPO YARA | Q131: =$R$1-F131 -> 844 | R131: =_xlfn.XLOOKUP(E131,'Data Additive'!E:E,'Data Additive'!E:E,0) -> 0
A132: 1159 | B132: YARA - RIO GRANDE | C132: 92.660.604/0013-16 | D132: 2700 | E132: 1246121302 | F132: 45297 | H132: 1 | I132: Adtives | J132: 1246121302 | K132: 45282 | L132: 3041000 | M132: FRETES DIVERSOS | N132: 46 | O132: FINANCEIRO GERAL | P132: GRUPO YARA | Q132: =$R$1-F132 -> 844 | R132: =_xlfn.XLOOKUP(E132,'Data Additive'!E:E,'Data Additive'!E:E,0) -> 0
A133: 1159 | B133: YARA - RIO GRANDE | C133: 92.660.604/0013-16 | D133: 1200 | E133: 1246121295 | F133: 45297 | H133: 1 | I133: Adtives | J133: 1246121295 | K133: 45282 | L133: 3041000 | M133: FRETES DIVERSOS | N133: 46 | O133: FINANCEIRO GERAL | P133: GRUPO YARA | Q133: =$R$1-F133 -> 844 | R133: =_xlfn.XLOOKUP(E133,'Data Additive'!E:E,'Data Additive'!E:E,0) -> 0
A134: 1159 | B134: YARA - RIO GRANDE | C134: 92.660.604/0013-16 | D134: 2700 | E134: 1246121297 | F134: 45297 | H134: 1 | I134: Adtives | J134: 1246121297 | K134: 45282 | L134: 3041000 | M134: FRETES DIVERSOS | N134: 46 | O134: FINANCEIRO GERAL | P134: GRUPO YARA | Q134: =$R$1-F134 -> 844 | R134: =_xlfn.XLOOKUP(E134,'Data Additive'!E:E,'Data Additive'!E:E,0) -> 0
... A177: 6124 | B177: MOSAIC - UBERABA (UBA III) | C177: 61.156.501/0110-00 | D177: 52374 | E177: 1246267926 | F177: 46187 | H177: 1 | I177: Adtives | J177: 10897 | K177: 46097 | L177: 1010100 | M177: VENDAS MERCADO INTERNO | N177: 161 | O177: VENDA PROD. INDUSTRIALIZADO - NFE | P177: GRUPO MOSAIC FERTILIZANTES DO BRASIL | Q177: =$R$1-F177 -> -46 | R177: =_xlfn.XLOOKUP(E177,'Data Additive'!E:E,'Data Additive'!E:E,0) -> 1246267926
A178: 7102 | B178: MOSAIC - RONDONOPOLIS | C178: 61.156.501/0115-14 | D178: 62553.7 | E178: 1246262017 | F178: 46145 | G178: 46146 | H178: 1 | I178: Adtives | J178: 10626 | K178: 46055 | L178: 1010100 | M178: VENDAS MERCADO INTERNO | N178: 161 | O178: VENDA PROD. INDUSTRIALIZADO - NFE | P178: GRUPO MOSAIC FERTILIZANTES DO BRASIL | Q178: =$R$1-F178 -> -4 | R178: =_xlfn.XLOOKUP(E178,'Data Additive'!E:E,'Data Additive'!E:E,0) -> 1246262017
A179: 7102 | B179: MOSAIC - RONDONOPOLIS | C179: 61.156.501/0115-14 | D179: 63327 | E179: 1246270569 | F179: 46210 | H179: 1 | I179: Adtives | J179: 11069 | K179: 46120 | L179: 1010100 | M179: VENDAS MERCADO INTERNO | N179: 161 | O179: VENDA PROD. INDUSTRIALIZADO - NFE | P179: GRUPO MOSAIC FERTILIZANTES DO BRASIL | Q179: =$R$1-F179 -> -69 | R179: =_xlfn.XLOOKUP(E179,'Data Additive'!E:E,'Data Additive'!E:E,0) -> 1246270569
A180: 7102 | B180: MOSAIC - RONDONOPOLIS | C180: 61.156.501/0115-14 | D180: 62637.3 | E180: 1246268784 | F180: 46195 | H180: 1 | I180: Adtives | J180: 10966 | K180: 46105 | L180: 1010100 | M180: VENDAS MERCADO INTERNO | N180: 161 | O180: VENDA PROD. INDUSTRIALIZADO - NFE | P180: GRUPO MOSAIC FERTILIZANTES DO BRASIL | Q180: =$R$1-F180 -> -54 | R180: =_xlfn.XLOOKUP(E180,'Data Additive'!E:E,'Data Additive'!E:E,0) -> 1246268784
A181: 7102 | B181: MOSAIC - RONDONOPOLIS | C181: 61.156.501/0115-14 | D181: 62700 | E181: 1246262728 | F181: 46152 | H181: 1 | I181: Adtives | J181: 10663 | K181: 46062 | L181: 1010100 | M181: VENDAS MERCADO INTERNO | N181: 161 | O181: VENDA PROD. INDUSTRIALIZADO - NFE | P181: GRUPO MOSAIC FERTILIZANTES DO BRASIL | Q181: =$R$1-F181 -> -11 | R181: =_xlfn.XLOOKUP(E181,'Data Additive'!E:E,'Data Additive'!E:E,0) -> 1246262728
A182: 7102 | B182: MOSAIC - RONDONOPOLIS | C182: 61.156.501/0115-14 | D182: 4800 | E182: 1246247639 | F182: 45982 | H182: 1 | I182: Adtives | J182: 1246247639 | K182: 45967 | L182: 3041000 | M182: FRETES DIVERSOS | N182: 46 | O182: FINANCEIRO GERAL | P182: GRUPO MOSAIC FERTILIZANTES DO BRASIL | Q182: =$R$1-F182 -> 159 | R182: =_xlfn.XLOOKUP(E182,'Data Additive'!E:E,'Data Additive'!E:E,0) -> 0
A183: 7662 | B183: BENTONIT UNIAO - BOA VISTA | C183: 08.811.119/0008-22 | D183: 57795 | E183: 1246266876 | F183: 46147 | G183: 46147 | H183: 1 | I183: Adtives | J183: 2799 | K183: 46087 | L183: 1010100 | M183: VENDAS MERCADO INTERNO | N183: 161 | O183: VENDA PROD. INDUSTRIALIZADO - NFE | P183: BENTONIT UNIAO - CAMPINA GRANDE | Q183: =$R$1-F183 -> -6 | R183: =_xlfn.XLOOKUP(E183,'Data Additive'!E:E,'Data Additive'!E:E,0) -> 1246266876
A184: 7662 | B184: BENTONIT UNIAO - BOA VISTA | C184: 08.811.119/0008-22 | D184: 91675 | E184: 1246273180 | F184: 46202 | H184: 1 | I184: Adtives | J184: 2902 | K184: 46142 | L184: 1010100 | M184: VENDAS MERCADO INTERNO | N184: 161 | O184: VENDA PROD. INDUSTRIALIZADO - NFE | P184: BENTONIT UNIAO - CAMPINA GRANDE | Q184: =$R$1-F184 -> -61 | R184: =_xlfn.XLOOKUP(E184,'Data Additive'!E:E,'Data Additive'!E:E,0) -> 1246273180
A185: 7662 | B185: BENTONIT UNIAO - BOA VISTA | C185: 08.811.119/0008-22 | D185: 91675 | E185: 1246273179 | F185: 46187 | H185: 1 | I185: Adtives | J185: 2902 | K185: 46142 | L185: 1010100 | M185: VENDAS MERCADO INTERNO | N185: 161 | O185: VENDA PROD. INDUSTRIALIZADO - NFE | P185: BENTONIT UNIAO - CAMPINA GRANDE | Q185: =$R$1-F185 -> -46 | R185: =_xlfn.XLOOKUP(E185,'Data Additive'!E:E,'Data Additive'!E:E,0) -> 1246273179
A186: 7662 | B186: BENTONIT UNIAO - BOA VISTA | C186: 08.811.119/0008-22 | D186: 77060 | E186: 1246269689 | F186: 46157 | H186: 1 | I186: Adtives | J186: 2856 | K186: 46112 | L186: 1010100 | M186: VENDAS MERCADO INTERNO | N186: 161 | O186: VENDA PROD. INDUSTRIALIZADO - NFE | P186: BENTONIT UNIAO - CAMPINA GRANDE | Q186: =$R$1-F186 -> -16 | R186: =_xlfn.XLOOKUP(E186,'Data Additive'!E:E,'Data Additive'!E:E,0) -> 1246269689
A187: 7662 | B187: BENTONIT UNIAO - BOA VISTA | C187: 08.811.119/0008-22 | D187: 77060 | E187: 1246269690 | F187: 46172 | H187: 1 | I187: Adtives | J187: 2856 | K187: 46112 | L187: 1010100 | M187: VENDAS MERCADO INTERNO | N187: 161 | O187: VENDA PROD. INDUSTRIALIZADO - NFE | P187: BENTONIT UNIAO - CAMPINA GRANDE | Q187: =$R$1-F187 -> -31 | R187: =_xlfn.XLOOKUP(E187,'Data Additive'!E:E,'Data Additive'!E:E,0) -> 1246269690
A188: 7479 | B188: MOSAIC - CUBATÃO | C188: 61.156.501/0099-60 | D188: 64104.8 | E188: 1246264518 | F188: 46166 | H188: 1 | I188: Adtives | J188: 10739 | K188: 46076 | L188: 1010100 | M188: VENDAS MERCADO INTERNO | N188: 56 | O188: VENDA A ORDEM | P188: GRUPO MOSAIC FERTILIZANTES DO BRASIL | Q188: =$R$1-F188 -> -25 | R188: =_xlfn.XLOOKUP(E188,'Data Additive'!E:E,'Data Additive'!E:E,0) -> 1246264518
A189: 6477 | B189: MOSAIC - PARANAGUA II | C189: 61.156.501/0109-76 | D189: 167720 | E189: 1246262010 | F189: 46145 | G189: 46146 | H189: 1 | I189: Adtives | J189: 10625 | K189: 46055 | L189: 1010100 | M189: VENDAS MERCADO INTERNO | N189: 161 | O189: VENDA PROD. INDUSTRIALIZADO - NFE | P189: GRUPO MOSAIC FERTILIZANTES DO BRASIL | Q189: =$R$1-F189 -> -4 | R189: =_xlfn.XLOOKUP(E189,'Data Additive'!E:E,'Data Additive'!E:E,0) -> 1246262010
A190: 6477 | B190: MOSAIC - PARANAGUA II | C190: 61.156.501/0109-76 | D190: 5400 | E190: 1246054441 | F190: 44897 | H190: 1 | I190: Adtives | J190: 1246054441 | K190: 44882 | L190: 3041000 | M190: FRETES DIVERSOS | N190: 46 | O190: FINANCEIRO GERAL | P190: GRUPO MOSAIC FERTILIZANTES DO BRASIL | Q190: =$R$1-F190 -> 1244 | R190: =_xlfn.XLOOKUP(E190,'Data Additive'!E:E,'Data Additive'!E:E,0) -> 0
A191: 6477 | B191: MOSAIC - PARANAGUA II | C191: 61.156.501/0109-76 | D191: 166320 | E191: 1246263184 | F191: 46153 | H191: 1 | I191: Adtives | J191: 10673 | K191: 46063 | L191: 1010100 | M191: VENDAS MERCADO INTERNO | N191: 161 | O191: VENDA PROD. INDUSTRIALIZADO - NFE | P191: GRUPO MOSAIC FERTILIZANTES DO BRASIL | Q191: =$R$1-F191 -> -12 | R191: =_xlfn.XLOOKUP(E191,'Data Additive'!E:E,'Data Additive'!E:E,0) -> 1246263184
A192: 6477 | B192: MOSAIC - PARANAGUA II | C192: 61.156.501/0109-76 | D192: 6302.6 | E192: 1246212732 | F192: 45682 | H192: 1 | I192: Adtives | J192: 6197 | K192: 45622 | L192: 1010100 | M192: VENDAS MERCADO INTERNO | N192: 161 | O192: VENDA PROD. INDUSTRIALIZADO - NFE | P192: GRUPO MOSAIC FERTILIZANTES DO BRASIL | Q192: =$R$1-F192 -> 459 | R192: =_xlfn.XLOOKUP(E192,'Data Additive'!E:E,'Data Additive'!E:E,0) -> 1246212732
A193: 7097 | B193: MOSAIC - SÃO FRANCISCO SUL | C193: 61.156.501/0125-96 | D193: 177977.8 | E193: 1246265921 | F193: 46173 | G193: 46146 | H193: 1 | I193: Adtives | J193: 10795 | K193: 46083 | L193: 1010100 | M193: VENDAS MERCADO INTERNO | N193: 161 | O193: VENDA PROD. INDUSTRIALIZADO - NFE | P193: GRUPO MOSAIC FERTILIZANTES DO BRASIL | Q193: =$R$1-F193 -> -32 | R193: =_xlfn.XLOOKUP(E193,'Data Additive'!E:E,'Data Additive'!E:E,0) -> 1246265921
A194: 7097 | B194: MOSAIC - SÃO FRANCISCO SUL | C194: 61.156.501/0125-96 | D194: 11300 | E194: 1246058687 | F194: 44925 | H194: 1 | I194: Adtives | J194: 1246058687 | K194: 44910 | L194: 3041000 | M194: FRETES DIVERSOS | N194: 46 | O194: FINANCEIRO GERAL | P194: GRUPO MOSAIC FERTILIZANTES DO BRASIL | Q194: =$R$1-F194 -> 1216 | R194: =_xlfn.XLOOKUP(E194,'Data Additive'!E:E,'Data Additive'!E:E,0) -> 0
A195: 7097 | B195: MOSAIC - SÃO FRANCISCO SUL | C195: 61.156.501/0125-96 | D195: 10183.12 | E195: 1246057240 | F195: 44922 | H195: 1 | I195: Adtives | J195: 71222 | K195: 44902 | L195: 3041000 | M195: FRETES DIVERSOS | N195: 46 | O195: FINANCEIRO GERAL | P195: GRUPO MOSAIC FERTILIZANTES DO BRASIL | Q195: =$R$1-F195 -> 1219 | R195: =_xlfn.XLOOKUP(E195,'Data Additive'!E:E,'Data Additive'!E:E,0) -> 0
A196: 7443 | B196: MOSAIC - CATALÃO - MISTURA | C196: 61.156.501/0113-52 | D196: 1200 | E196: 1246156403 | F196: 45496 | H196: 1 | I196: Adtives | J196: 1246156403 | K196: 45481 | L196: 3041000 | M196: FRETES DIVERSOS | N196: 46 | O196: FINANCEIRO GERAL | P196: GRUPO MOSAIC FERTILIZANTES DO BRASIL | Q196: =$R$1-F196 -> 645 | R196: =_xlfn.XLOOKUP(E196,'Data Additive'!E:E,'Data Additive'!E:E,0) -> 0
A197: 7443 | B197: MOSAIC - CATALÃO - MISTURA | C197: 61.156.501/0113-52 | D197: 1200 | E197: 1246156396 | F197: 45496 | H197: 1 | I197: Adtives | J197: 1246156396 | K197: 45481 | L197: 3041000 | M197: FRETES DIVERSOS | N197: 46 | O197: FINANCEIRO GERAL | P197: GRUPO MOSAIC FERTILIZANTES DO BRASIL | Q197: =$R$1-F197 -> 645 | R197: =_xlfn.XLOOKUP(E197,'Data Additive'!E:E,'Data Additive'!E:E,0) -> 0
A198: 7024 | B198: MOSAIC - SORRISO | C198: 61.156.501/0092-93 | D198: 70855.2 | E198: 1246269662 | F198: 46201 | H198: 1 | I198: Adtives | J198: 11011 | K198: 46111 | L198: 1010100 | M198: VENDAS MERCADO INTERNO | N198: 161 | O198: VENDA PROD. INDUSTRIALIZADO - NFE | P198: GRUPO MOSAIC FERTILIZANTES DO BRASIL | Q198: =$R$1-F198 -> -60 | R198: =_xlfn.XLOOKUP(E198,'Data Additive'!E:E,'Data Additive'!E:E,0) -> 1246269662
A199: 7024 | B199: MOSAIC - SORRISO | C199: 61.156.501/0092-93 | D199: 71323.2 | E199: 1246270943 | F199: 46212 | H199: 1 | I199: Adtives | J199: 11084 | K199: 46122 | L199: 1010100 | M199: VENDAS MERCADO INTERNO | N199: 161 | O199: VENDA PROD. INDUSTRIALIZADO - NFE | P199: GRUPO MOSAIC FERTILIZANTES DO BRASIL | Q199: =$R$1-F199 -> -71 | R199: =_xlfn.XLOOKUP(E199,'Data Additive'!E:E,'Data Additive'!E:E,0) -> 1246270943
A200: 7024 | B200: MOSAIC - SORRISO | C200: 61.156.501/0092-93 | D200: 70410.6 | E200: 1246265856 | F200: 46170 | H200: 1 | I200: Adtives | J200: 10790 | K200: 46080 | L200: 1010100 | M200: VENDAS MERCADO INTERNO | N200: 161 | O200: VENDA PROD. INDUSTRIALIZADO - NFE | P200: GRUPO MOSAIC FERTILIZANTES DO BRASIL | Q200: =$R$1-F200 -> -29 | R200: =_xlfn.XLOOKUP(E200,'Data Additive'!E:E,'Data Additive'!E:E,0) -> 1246265856
A201: 7302 | B201: MOSAIC - PARANAGUA I | C201: 61.156.501/0080-50 | D201: 167720 | E201: 1246262004 | F201: 46145 | G201: 46146 | H201: 1 | I201: Adtives | J201: 10622 | K201: 46055 | L201: 1010100 | M201: VENDAS MERCADO INTERNO | N201: 161 | O201: VENDA PROD. INDUSTRIALIZADO - NFE | P201: GRUPO MOSAIC FERTILIZANTES DO BRASIL | Q201: =$R$1-F201 -> -4 | R201: =_xlfn.XLOOKUP(E201,'Data Additive'!E:E,'Data Additive'!E:E,0) -> 1246262004
A202: 7302 | B202: MOSAIC - PARANAGUA I | C202: 61.156.501/0080-50 | D202: 1800 | E202: 1246045752 | F202: 44848 | H202: 1 | I202: Adtives | J202: 290922 | K202: 44833 | L202: 3041000 | M202: FRETES DIVERSOS | N202: 46 | O202: FINANCEIRO GERAL | P202: GRUPO MOSAIC FERTILIZANTES DO BRASIL | Q202: =$R$1-F202 -> 1293 | R202: =_xlfn.XLOOKUP(E202,'Data Additive'!E:E,'Data Additive'!E:E,0) -> 0
A203: 7302 | B203: MOSAIC - PARANAGUA I | C203: 61.156.501/0080-50 | D203: 7200 | E203: 1246033417 | F203: 44792 | H203: 1 | I203: Adtives | J203: 1246033417 | K203: 44777 | L203: 3041000 | M203: FRETES DIVERSOS | N203: 46 | O203: FINANCEIRO GERAL | P203: GRUPO MOSAIC FERTILIZANTES DO BRASIL | Q203: =$R$1-F203 -> 1349 | R203: =_xlfn.XLOOKUP(E203,'Data Additive'!E:E,'Data Additive'!E:E,0) -> 0
A204: 7302 | B204: MOSAIC - PARANAGUA I | C204: 61.156.501/0080-50 | D204: 1431.76 | E204: 1246062794 | F204: 44939 | H204: 1 | I204: Adtives | J204: 19884 | K204: 44879 | L204: 1010100 | M204: VENDAS MERCADO INTERNO | N204: 80 | O204: VENDA PROD REMETIDO P/ INDUSTRIALIZAÇÃO | P204: GRUPO MOSAIC FERTILIZANTES DO BRASIL | Q204: =$R$1-F204 -> 1202 | R204: =_xlfn.XLOOKUP(E204,'Data Additive'!E:E,'Data Additive'!E:E,0) -> 1246062794
A205: 7302 | B205: MOSAIC - PARANAGUA I | C205: 61.156.501/0080-50 | D205: 9000 | E205: 1246054438 | F205: 44897 | H205: 1 | I205: Adtives | J205: 1246054438 | K205: 44882 | L205: 3041000 | M205: FRETES DIVERSOS | N205: 46 | O205: FINANCEIRO GERAL | P205: GRUPO MOSAIC FERTILIZANTES DO BRASIL | Q205: =$R$1-F205 -> 1244 | R205: =_xlfn.XLOOKUP(E205,'Data Additive'!E:E,'Data Additive'!E:E,0) -> 0
A206: 7302 | B206: MOSAIC - PARANAGUA I | C206: 61.156.501/0080-50 | D206: 7200 | E206: 1246057914 | F206: 44922 | H206: 1 | I206: Adtives | J206: 1246057914 | K206: 44907 | L206: 3041000 | M206: FRETES DIVERSOS | N206: 46 | O206: FINANCEIRO GERAL | P206: GRUPO MOSAIC FERTILIZANTES DO BRASIL | Q206: =$R$1-F206 -> 1219 | R206: =_xlfn.XLOOKUP(E206,'Data Additive'!E:E,'Data Additive'!E:E,0) -> 0
A207: 7302 | B207: MOSAIC - PARANAGUA I | C207: 61.156.501/0080-50 | D207: 2517.4 | E207: 1246055324 | F207: 44887 | H207: 1 | I207: Adtives | J207: 19314 | K207: 44827 | L207: 1010100 | M207: VENDAS MERCADO INTERNO | N207: 161 | O207: VENDA PROD. INDUSTRIALIZADO - NFE | P207: GRUPO MOSAIC FERTILIZANTES DO BRASIL | Q207: =$R$1-F207 -> 1254 | R207: =_xlfn.XLOOKUP(E207,'Data Additive'!E:E,'Data Additive'!E:E,0) -> 1246055324
A208: 7302 | B208: MOSAIC - PARANAGUA I | C208: 61.156.501/0080-50 | D208: 36679.8 | E208: 1246272740 | F208: 46229 | H208: 1 | I208: Adtives | J208: 11223 | K208: 46139 | L208: 1010100 | M208: VENDAS MERCADO INTERNO | N208: 161 | O208: VENDA PROD. INDUSTRIALIZADO - NFE | P208: GRUPO MOSAIC FERTILIZANTES DO BRASIL | Q208: =$R$1-F208 -> -88 | R208: =_xlfn.XLOOKUP(E208,'Data Additive'!E:E,'Data Additive'!E:E,0) -> 1246272740
A209: 7302 | B209: MOSAIC - PARANAGUA I | C209: 61.156.501/0080-50 | D209: 166320 | E209: 1246263181 | F209: 46153 | H209: 1 | I209: Adtives | J209: 10672 | K209: 46063 | L209: 1010100 | M209: VENDAS MERCADO INTERNO | N209: 161 | O209: VENDA PROD. INDUSTRIALIZADO - NFE | P209: GRUPO MOSAIC FERTILIZANTES DO BRASIL | Q209: =$R$1-F209 -> -12 | R209: =_xlfn.XLOOKUP(E209,'Data Additive'!E:E,'Data Additive'!E:E,0) -> 1246263181
A210: 7302 | B210: MOSAIC - PARANAGUA I | C210: 61.156.501/0080-50 | D210: 67867.8 | E210: 1246270495 | F210: 46209 | H210: 1 | I210: Adtives | J210: 11064 | K210: 46119 | L210: 1010100 | M210: VENDAS MERCADO INTERNO | N210: 161 | O210: VENDA PROD. INDUSTRIALIZADO - NFE | P210: GRUPO MOSAIC FERTILIZANTES DO BRASIL | Q210: =$R$1-F210 -> -68 | R210: =_xlfn.XLOOKUP(E210,'Data Additive'!E:E,'Data Additive'!E:E,0) -> 1246270495
A211: 7302 | B211: MOSAIC - PARANAGUA I | C211: 61.156.501/0080-50 | D211: 181231 | E211: 1246273299 | F211: 46232 | H211: 1 | I211: Adtives | J211: 11276 | K211: 46142 | L211: 1010100 | M211: VENDAS MERCADO INTERNO | N211: 161 | O211: VENDA PROD. INDUSTRIALIZADO - NFE | P211: GRUPO MOSAIC FERTILIZANTES DO BRASIL | Q211: =$R$1-F211 -> -91 | R211: =_xlfn.XLOOKUP(E211,'Data Additive'!E:E,'Data Additive'!E:E,0) -> 1246273299
A212: 7302 | B212: MOSAIC - PARANAGUA I | C212: 61.156.501/0080-50 | D212: 129924 | E212: 1246268530 | F212: 46191 | H212: 1 | I212: Adtives | J212: 10941 | K212: 46101 | L212: 1010100 | M212: VENDAS MERCADO INTERNO | N212: 56 | O212: VENDA A ORDEM | P212: GRUPO MOSAIC FERTILIZANTES DO BRASIL | Q212: =$R$1-F212 -> -50 | R212: =_xlfn.XLOOKUP(E212,'Data Additive'!E:E,'Data Additive'!E:E,0) -> 1246268530
A213: 7302 | B213: MOSAIC - PARANAGUA I | C213: 61.156.501/0080-50 | D213: 64.2 | E213: 1246226087 | F213: 45919 | H213: 1 | I213: Adtives | J213: 8559 | K213: 45859 | L213: 1010100 | M213: VENDAS MERCADO INTERNO | N213: 161 | O213: VENDA PROD. INDUSTRIALIZADO - NFE | P213: GRUPO MOSAIC FERTILIZANTES DO BRASIL | Q213: =$R$1-F213 -> 222 | R213: =_xlfn.XLOOKUP(E213,'Data Additive'!E:E,'Data Additive'!E:E,0) -> 1246226087
... A268: 12741 | B268: HINOVE AGROCIENCIA - GUARÁ | C268: 14.031.191/0009-10 | D268: 137256 | E268: 1246268240 | F268: 46167 | H268: 1 | I268: Adtives | J268: 10917 | K268: 46099 | L268: 1010100 | M268: VENDAS MERCADO INTERNO | N268: 161 | O268: VENDA PROD. INDUSTRIALIZADO - NFE | P268: GRUPO HINOVE | Q268: =$R$1-F268 -> -26 | R268: =_xlfn.XLOOKUP(E268,'Data Additive'!E:E,'Data Additive'!E:E,0) -> 1246268240
A269: 14166 | B269: TAKI AGRO - TRES CORAÇÕES | C269: 08.684.752/0001-20 | D269: 82152 | E269: 1246231876 | F269: 46144 | G269: 46146 | H269: 2 | I269: Fertilizers | J269: 8933 | K269: 45888 | L269: 1010100 | M269: VENDAS MERCADO INTERNO | N269: 161 | O269: VENDA PROD. INDUSTRIALIZADO - NFE | P269: GRUPO TAKI AGRO | Q269: =$R$1-F269 -> -3 | R269: =_xlfn.XLOOKUP(E269,'Data Additive'!E:E,'Data Additive'!E:E,0) -> 0
A270: 14166 | B270: TAKI AGRO - TRES CORAÇÕES | C270: 08.684.752/0001-20 | D270: 93462.6 | E270: 1246231878 | F270: 46144 | G270: 46146 | H270: 2 | I270: Fertilizers | J270: 8934 | K270: 45888 | L270: 1010100 | M270: VENDAS MERCADO INTERNO | N270: 161 | O270: VENDA PROD. INDUSTRIALIZADO - NFE | P270: GRUPO TAKI AGRO | Q270: =$R$1-F270 -> -3 | R270: =_xlfn.XLOOKUP(E270,'Data Additive'!E:E,'Data Additive'!E:E,0) -> 0
A271: 14166 | B271: TAKI AGRO - TRES CORAÇÕES | C271: 08.684.752/0001-20 | D271: 131112.52 | E271: 1246231981 | F271: 46143 | G271: 46146 | H271: 2 | I271: Fertilizers | J271: 8941 | K271: 45889 | L271: 1010100 | M271: VENDAS MERCADO INTERNO | N271: 56 | O271: VENDA A ORDEM | P271: GRUPO TAKI AGRO | Q271: =$R$1-F271 -> -2 | R271: =_xlfn.XLOOKUP(E271,'Data Additive'!E:E,'Data Additive'!E:E,0) -> 0
...

Sheet freight debit notes
D1: =SUBTOTAL(9,D3:D999) -> 176583.12 | Q1: 46141
A2: CODPARC | B2: NOMEPARC | C2: CNPJ | D2: Valor | E2: NUFIN | F2: DTVENC | G2: DHBAIXA | H2: AD_BU | I2: NOME_BU | J2: NUMNOTA | K2: DTENTSAI | L2: CODNAT | M2: DESCRNAT | N2: CODTIPOPER | O2: OPERACAO | P2: Grupo | Q2: Dias vencidos
A3: 1787 | B3: MOSAIC - UBERABA (CIU1) | C3: 33.931.486/0014-55 | D3: 3600 | E3: 1246031589 | F3: 44784 | H3: 1 | I3: Adtives | J3: 1246031589 | K3: 44769 | L3: 3041000 | M3: FRETES DIVERSOS | N3: 46 | O3: FINANCEIRO GERAL | P3: GRUPO MOSAIC FERTILIZANTES P K LTDA | Q3: =$Q$1-F3 -> 1357
A4: 1787 | B4: MOSAIC - UBERABA (CIU1) | C4: 33.931.486/0014-55 | D4: 2700 | E4: 1246055596 | F4: 44889 | H4: 1 | I4: Adtives | J4: 1246055596 | K4: 44889 | L4: 3041000 | M4: FRETES DIVERSOS | N4: 46 | O4: FINANCEIRO GERAL | P4: GRUPO MOSAIC FERTILIZANTES P K LTDA | Q4: =$Q$1-F4 -> 1252
A5: 1788 | B5: MOSAIC - UBERABA (CIU2) | C5: 33.931.486/0021-84 | D5: 5400 | E5: 1246055599 | F5: 44889 | H5: 1 | I5: Adtives | J5: 1246055599 | K5: 44889 | L5: 3041000 | M5: FRETES DIVERSOS | N5: 46 | O5: FINANCEIRO GERAL | P5: GRUPO MOSAIC FERTILIZANTES P K LTDA | Q5: =$Q$1-F5 -> 1252
A6: 1788 | B6: MOSAIC - UBERABA (CIU2) | C6: 33.931.486/0021-84 | D6: 1200 | E6: 1246190701 | F6: 45674 | H6: 1 | I6: Adtives | J6: 1246190701 | K6: 45659 | L6: 3041000 | M6: FRETES DIVERSOS | N6: 46 | O6: FINANCEIRO GERAL | P6: GRUPO MOSAIC FERTILIZANTES P K LTDA | Q6: =$Q$1-F6 -> 467
A7: 1789 | B7: MOSAIC - ARAXA (CMA) | C7: 33.931.486/0019-60 | D7: 2700 | E7: 1246120461 | F7: 45294 | H7: 1 | I7: Adtives | J7: 191223 | K7: 45279 | L7: 3041000 | M7: FRETES DIVERSOS | N7: 46 | O7: FINANCEIRO GERAL | P7: GRUPO MOSAIC FERTILIZANTES P K LTDA | Q7: =$Q$1-F7 -> 847
A8: 1789 | B8: MOSAIC - ARAXA (CMA) | C8: 33.931.486/0019-60 | D8: 900 | E8: 1246146095 | F8: 45428 | H8: 1 | I8: Adtives | J8: 1246120461 | K8: 45428 | L8: 3041000 | M8: FRETES DIVERSOS | N8: 46 | O8: FINANCEIRO GERAL | P8: GRUPO MOSAIC FERTILIZANTES P K LTDA | Q8: =$Q$1-F8 -> 713
A9: 43 | B9: CIBRA - CAMACARI | C9: 00.117.842/0001-28 | D9: 3600 | E9: 1246271938 | F9: 46147 | H9: 1 | I9: Adtives | J9: 1246271938 | K9: 46132 | L9: 3042200 | M9: DIÁRIAS E ESTADIA DE MOTORISTAS | N9: 46 | O9: FINANCEIRO GERAL | P9: GRUPO CIBRA | Q9: =$Q$1-F9 -> -6
A10: 43 | B10: CIBRA - CAMACARI | C10: 00.117.842/0001-28 | D10: 3600 | E10: 1246271937 | F10: 46147 | H10: 1 | I10: Adtives | J10: 1246271937 | K10: 46132 | L10: 3042200 | M10: DIÁRIAS E ESTADIA DE MOTORISTAS | N10: 46 | O10: FINANCEIRO GERAL | P10: GRUPO CIBRA | Q10: =$Q$1-F10 -> -6
A11: 43 | B11: CIBRA - CAMACARI | C11: 00.117.842/0001-28 | D11: 3600 | E11: 1246271931 | F11: 46147 | H11: 1 | I11: Adtives | J11: 1246271931 | K11: 46132 | L11: 3042200 | M11: DIÁRIAS E ESTADIA DE MOTORISTAS | N11: 46 | O11: FINANCEIRO GERAL | P11: GRUPO CIBRA | Q11: =$Q$1-F11 -> -6
A12: 43 | B12: CIBRA - CAMACARI | C12: 00.117.842/0001-28 | D12: 6000 | E12: 1246271936 | F12: 46147 | H12: 1 | I12: Adtives | J12: 1246271936 | K12: 46132 | L12: 3042200 | M12: DIÁRIAS E ESTADIA DE MOTORISTAS | N12: 46 | O12: FINANCEIRO GERAL | P12: GRUPO CIBRA | Q12: =$Q$1-F12 -> -6
A13: 43 | B13: CIBRA - CAMACARI | C13: 00.117.842/0001-28 | D13: 2400 | E13: 1246271921 | F13: 46147 | H13: 1 | I13: Adtives | J13: 1246271921 | K13: 46132 | L13: 3042200 | M13: DIÁRIAS E ESTADIA DE MOTORISTAS | N13: 46 | O13: FINANCEIRO GERAL | P13: GRUPO CIBRA | Q13: =$Q$1-F13 -> -6
A14: 1159 | B14: YARA - RIO GRANDE | C14: 92.660.604/0013-16 | D14: 1800 | E14: 1246087936 | F14: 45112 | H14: 1 | I14: Adtives | J14: 1246087936 | K14: 45097 | L14: 3041000 | M14: FRETES DIVERSOS | N14: 46 | O14: FINANCEIRO GERAL | P14: GRUPO YARA | Q14: =$Q$1-F14 -> 1029
... A54: 7022 | B54: STRATOS/MOSAIC - ROSARIO DO CATETE | C54: 31.009.644/0001-74 | D54: 1800 | E54: 1246054442 | F54: 44897 | H54: 1 | I54: Adtives | J54: 1246054442 | K54: 44882 | L54: 3041000 | M54: FRETES DIVERSOS | N54: 46 | O54: FINANCEIRO GERAL | P54: STRATOS/MOSAIC - ROSARIO DO CATETE | Q54: =$Q$1-F54 -> 1244

Sheet Data Additive
D1: =SUBTOTAL(9,$D$3:$D$866) -> 25978603 | R1: 46141
A2: CODPARC | B2: NOMEPARC | C2: CNPJ | D2: Valor | E2: NUFIN | F2: DTVENC | G2: DHBAIXA | H2: AD_BU | I2: NOME_BU | J2: NUMNOTA | K2: DTENTSAI | L2: CODNAT | M2: DESCRNAT | N2: CODTIPOPER | O2: OPERACAO | P2: Grupo | Q2: Dias vencidos
A3: 205 | B3: FERTIPAR - RONDONÓPOLIS | C3: 09.384.948/0002-43 | D3: 80589.6 | E3: 1246271690 | F3: 46157 | H3: 1 | I3: Adtives | J3: 11158 | K3: 46129 | L3: 1010100 | M3: VENDAS MERCADO INTERNO | N3: 161 | O3: VENDA PROD. INDUSTRIALIZADO - NFE | P3: GRUPO FERTIPAR FERTILIZANTES MATO GROSSO | Q3: =$R$1-F3 -> -16 | R3: =_xlfn.XLOOKUP(P3,'Painel Additive'!$B:$B,'Painel Additive'!$B:$B,0) -> GRUPO FERTIPAR FERTILIZANTES MATO GROSSO | S3: =F3-K3 -> 28
A4: 205 | B4: FERTIPAR - RONDONÓPOLIS | C4: 09.384.948/0002-43 | D4: 81051.4 | E4: 1246273002 | F4: 46168 | H4: 1 | I4: Adtives | J4: 11248 | K4: 46140 | L4: 1010100 | M4: VENDAS MERCADO INTERNO | N4: 161 | O4: VENDA PROD. INDUSTRIALIZADO - NFE | P4: GRUPO FERTIPAR FERTILIZANTES MATO GROSSO | Q4: =$R$1-F4 -> -27 | R4: =_xlfn.XLOOKUP(P4,'Painel Additive'!$B:$B,'Painel Additive'!$B:$B,0) -> GRUPO FERTIPAR FERTILIZANTES MATO GROSSO | S4: =F4-K4 -> 28
A5: 1257 | B5: MOSAIC - CAMPO GRANDE | C5: 61.156.501/0081-30 | D5: 1980.8 | E5: 1246032946 | F5: 44774 | H5: 1 | I5: Adtives | J5: 17935 | K5: 44714 | L5: 1010100 | M5: VENDAS MERCADO INTERNO | N5: 56 | O5: VENDA A ORDEM | P5: GRUPO MOSAIC FERTILIZANTES DO BRASIL | Q5: =$R$1-F5 -> 1367 | R5: =_xlfn.XLOOKUP(P5,'Painel Additive'!$B:$B,'Painel Additive'!$B:$B,0) -> GRUPO MOSAIC FERTILIZANTES DO BRASIL | S5: =F5-K5 -> 60
A6: 1953 | B6: AMAGGI - COMODORO | C6: 77.294.254/0075-20 | D6: 58917.8 | E6: 1246267986 | F6: 46158 | H6: 1 | I6: Adtives | J6: 10907 | K6: 46098 | L6: 1010100 | M6: VENDAS MERCADO INTERNO | N6: 161 | O6: VENDA PROD. INDUSTRIALIZADO - NFE | P6: GRUPO AMAGGI | Q6: =$R$1-F6 -> -17 | R6: =_xlfn.XLOOKUP(P6,'Painel Additive'!$B:$B,'Painel Additive'!$B:$B,0) -> GRUPO AMAGGI | S6: =F6-K6 -> 60
A7: 1787 | B7: MOSAIC - UBERABA (CIU1) | C7: 33.931.486/0014-55 | D7: 107059.2 | E7: 1246262114 | F7: 46146 | G7: 46146 | H7: 1 | I7: Adtives | J7: 10629 | K7: 46056 | L7: 1010100 | M7: VENDAS MERCADO INTERNO | N7: 161 | O7: VENDA PROD. INDUSTRIALIZADO - NFE | P7: GRUPO MOSAIC FERTILIZANTES P K LTDA | Q7: =$R$1-F7 -> -5 | R7: =_xlfn.XLOOKUP(P7,'Painel Additive'!$B:$B,'Painel Additive'!$B:$B,0) -> GRUPO MOSAIC FERTILIZANTES P K LTDA | S7: =F7-K7 -> 90
A8: 1787 | B8: MOSAIC - UBERABA (CIU1) | C8: 33.931.486/0014-55 | D8: 109862.4 | E8: 1246271310 | F8: 46216 | H8: 1 | I8: Adtives | J8: 11116 | K8: 46126 | L8: 1010100 | M8: VENDAS MERCADO INTERNO | N8: 161 | O8: VENDA PROD. INDUSTRIALIZADO - NFE | P8: GRUPO MOSAIC FERTILIZANTES P K LTDA | Q8: =$R$1-F8 -> -75 | R8: =_xlfn.XLOOKUP(P8,'Painel Additive'!$B:$B,'Painel Additive'!$B:$B,0) -> GRUPO MOSAIC FERTILIZANTES P K LTDA | S8: =F8-K8 -> 90
A9: 1787 | B9: MOSAIC - UBERABA (CIU1) | C9: 33.931.486/0014-55 | D9: 116928 | E9: 1246267948 | F9: 46187 | H9: 1 | I9: Adtives | J9: 10899 | K9: 46097 | L9: 1010100 | M9: VENDAS MERCADO INTERNO | N9: 161 | O9: VENDA PROD. INDUSTRIALIZADO - NFE | P9: GRUPO MOSAIC FERTILIZANTES P K LTDA | Q9: =$R$1-F9 -> -46 | R9: =_xlfn.XLOOKUP(P9,'Painel Additive'!$B:$B,'Painel Additive'!$B:$B,0) -> GRUPO MOSAIC FERTILIZANTES P K LTDA | S9: =F9-K9 -> 90
A10: 1787 | B10: MOSAIC - UBERABA (CIU1) | C10: 33.931.486/0014-55 | D10: 115891.2 | E10: 1246262540 | F10: 46149 | H10: 1 | I10: Adtives | J10: 10652 | K10: 46059 | L10: 1010100 | M10: VENDAS MERCADO INTERNO | N10: 161 | O10: VENDA PROD. INDUSTRIALIZADO - NFE | P10: GRUPO MOSAIC FERTILIZANTES P K LTDA | Q10: =$R$1-F10 -> -8 | R10: =_xlfn.XLOOKUP(P10,'Painel Additive'!$B:$B,'Painel Additive'!$B:$B,0) -> GRUPO MOSAIC FERTILIZANTES P K LTDA | S10: =F10-K10 -> 90
A11: 1787 | B11: MOSAIC - UBERABA (CIU1) | C11: 33.931.486/0014-55 | D11: 103795.2 | E11: 1246268633 | F11: 46194 | H11: 1 | I11: Adtives | J11: 10957 | K11: 46104 | L11: 1010100 | M11: VENDAS MERCADO INTERNO | N11: 161 | O11: VENDA PROD. INDUSTRIALIZADO - NFE | P11: GRUPO MOSAIC FERTILIZANTES P K LTDA | Q11: =$R$1-F11 -> -53 | R11: =_xlfn.XLOOKUP(P11,'Painel Additive'!$B:$B,'Painel Additive'!$B:$B,0) -> GRUPO MOSAIC FERTILIZANTES P K LTDA | S11: =F11-K11 -> 90
A12: 1787 | B12: MOSAIC - UBERABA (CIU1) | C12: 33.931.486/0014-55 | D12: 111360 | E12: 1246268748 | F12: 46195 | H12: 1 | I12: Adtives | J12: 10965 | K12: 46105 | L12: 1010100 | M12: VENDAS MERCADO INTERNO | N12: 161 | O12: VENDA PROD. INDUSTRIALIZADO - NFE | P12: GRUPO MOSAIC FERTILIZANTES P K LTDA | Q12: =$R$1-F12 -> -54 | R12: =_xlfn.XLOOKUP(P12,'Painel Additive'!$B:$B,'Painel Additive'!$B:$B,0) -> GRUPO MOSAIC FERTILIZANTES P K LTDA | S12: =F12-K12 -> 90
A13: 1787 | B13: MOSAIC - UBERABA (CIU1) | C13: 33.931.486/0014-55 | D13: 114662.4 | E13: 1246268585 | F13: 46161 | H13: 1 | I13: Adtives | J13: 10953 | K13: 46101 | L13: 1010100 | M13: VENDAS MERCADO INTERNO | N13: 161 | O13: VENDA PROD. INDUSTRIALIZADO - NFE | P13: GRUPO MOSAIC FERTILIZANTES P K LTDA | Q13: =$R$1-F13 -> -20 | R13: =_xlfn.XLOOKUP(P13,'Painel Additive'!$B:$B,'Painel Additive'!$B:$B,0) -> GRUPO MOSAIC FERTILIZANTES P K LTDA | S13: =F13-K13 -> 60
A14: 1787 | B14: MOSAIC - UBERABA (CIU1) | C14: 33.931.486/0014-55 | D14: 115852.8 | E14: 1246270635 | F14: 46210 | H14: 1 | I14: Adtives | J14: 11072 | K14: 46120 | L14: 1010100 | M14: VENDAS MERCADO INTERNO | N14: 161 | O14: VENDA PROD. INDUSTRIALIZADO - NFE | P14: GRUPO MOSAIC FERTILIZANTES P K LTDA | Q14: =$R$1-F14 -> -69 | R14: =_xlfn.XLOOKUP(P14,'Painel Additive'!$B:$B,'Painel Additive'!$B:$B,0) -> GRUPO MOSAIC FERTILIZANTES P K LTDA | S14: =F14-K14 -> 90
A15: 1787 | B15: MOSAIC - UBERABA (CIU1) | C15: 33.931.486/0014-55 | D15: 114739.2 | E15: 1246271165 | F15: 46215 | H15: 1 | I15: Adtives | J15: 11105 | K15: 46125 | L15: 1010100 | M15: VENDAS MERCADO INTERNO | N15: 161 | O15: VENDA PROD. INDUSTRIALIZADO - NFE | P15: GRUPO MOSAIC FERTILIZANTES P K LTDA | Q15: =$R$1-F15 -> -74 | R15: =_xlfn.XLOOKUP(P15,'Painel Additive'!$B:$B,'Painel Additive'!$B:$B,0) -> GRUPO MOSAIC FERTILIZANTES P K LTDA | S15: =F15-K15 -> 90
A16: 1787 | B16: MOSAIC - UBERABA (CIU1) | C16: 33.931.486/0014-55 | D16: 114969.6 | E16: 1246264543 | F16: 46166 | H16: 1 | I16: Adtives | J16: 10746 | K16: 46076 | L16: 1010100 | M16: VENDAS MERCADO INTERNO | N16: 161 | O16: VENDA PROD. INDUSTRIALIZADO - NFE | P16: GRUPO MOSAIC FERTILIZANTES P K LTDA | Q16: =$R$1-F16 -> -25 | R16: =_xlfn.XLOOKUP(P16,'Painel Additive'!$B:$B,'Painel Additive'!$B:$B,0) -> GRUPO MOSAIC FERTILIZANTES P K LTDA | S16: =F16-K16 -> 90
A17: 1787 | B17: MOSAIC - UBERABA (CIU1) | C17: 33.931.486/0014-55 | D17: 113356.8 | E17: 1246269731 | F17: 46202 | H17: 1 | I17: Adtives | J17: 11014 | K17: 46112 | L17: 1010100 | M17: VENDAS MERCADO INTERNO | N17: 161 | O17: VENDA PROD. INDUSTRIALIZADO - NFE | P17: GRUPO MOSAIC FERTILIZANTES P K LTDA | Q17: =$R$1-F17 -> -61 | R17: =_xlfn.XLOOKUP(P17,'Painel Additive'!$B:$B,'Painel Additive'!$B:$B,0) -> GRUPO MOSAIC FERTILIZANTES P K LTDA | S17: =F17-K17 -> 90
A18: 1787 | B18: MOSAIC - UBERABA (CIU1) | C18: 33.931.486/0014-55 | D18: 110246.4 | E18: 1246272757 | F18: 46229 | H18: 1 | I18: Adtives | J18: 11229 | K18: 46139 | L18: 1010100 | M18: VENDAS MERCADO INTERNO | N18: 161 | O18: VENDA PROD. INDUSTRIALIZADO - NFE | P18: GRUPO MOSAIC FERTILIZANTES P K LTDA | Q18: =$R$1-F18 -> -88 | R18: =_xlfn.XLOOKUP(P18,'Painel Additive'!$B:$B,'Painel Additive'!$B:$B,0) -> GRUPO MOSAIC FERTILIZANTES P K LTDA | S18: =F18-K18 -> 90
A19: 1787 | B19: MOSAIC - UBERABA (CIU1) | C19: 33.931.486/0014-55 | D19: 115392 | E19: 1246265885 | F19: 46173 | H19: 1 | I19: Adtives | J19: 10791 | K19: 46083 | L19: 1010100 | M19: VENDAS MERCADO INTERNO | N19: 161 | O19: VENDA PROD. INDUSTRIALIZADO - NFE | P19: GRUPO MOSAIC FERTILIZANTES P K LTDA | Q19: =$R$1-F19 -> -32 | R19: =_xlfn.XLOOKUP(P19,'Painel Additive'!$B:$B,'Painel Additive'!$B:$B,0) -> GRUPO MOSAIC FERTILIZANTES P K LTDA | S19: =F19-K19 -> 90
... A65: 33 | B65: HERINGER - PARANAGUÁ | C65: 22.266.175/0031-01 | D65: 99167.6 | E65: 1246271248 | F65: 46155 | H65: 1 | I65: Adtives | J65: 11114 | K65: 46125 | L65: 1010100 | M65: VENDAS MERCADO INTERNO | N65: 161 | O65: VENDA PROD. INDUSTRIALIZADO - NFE | P65: GRUPO HERINGER | Q65: =$R$1-F65 -> -14 | R65: =_xlfn.XLOOKUP(P65,'Painel Additive'!$B:$B,'Painel Additive'!$B:$B,0) -> GRUPO HERINGER | S65: =F65-K65 -> 30
A66: 214 | B66: UNIFERTIL - CANOAS UN1 | C66: 87.249.561/0001-07 | D66: 82931.8 | E66: 1246270505 | F66: 46147 | G66: 46147 | H66: 1 | I66: Adtives | J66: 11065 | K66: 46119 | L66: 1010100 | M66: VENDAS MERCADO INTERNO | N66: 161 | O66: VENDA PROD. INDUSTRIALIZADO - NFE | P66: GRUPO UNIFERTIL | Q66: =$R$1-F66 -> -6 | R66: =_xlfn.XLOOKUP(P66,'Painel Additive'!$B:$B,'Painel Additive'!$B:$B,0) -> GRUPO UNIFERTIL | S66: =F66-K66 -> 28
A67: 214 | B67: UNIFERTIL - CANOAS UN1 | C67: 87.249.561/0001-07 | D67: 82854.1 | E67: 1246272851 | F67: 46167 | H67: 1 | I67: Adtives | J67: 11237 | K67: 46139 | L67: 1010100 | M67: VENDAS MERCADO INTERNO | N67: 161 | O67: VENDA PROD. INDUSTRIALIZADO - NFE | P67: GRUPO UNIFERTIL | Q67: =$R$1-F67 -> -26 | R67: =_xlfn.XLOOKUP(P67,'Painel Additive'!$B:$B,'Painel Additive'!$B:$B,0) -> GRUPO UNIFERTIL | S67: =F67-K67 -> 28
A68: 214 | B68: UNIFERTIL - CANOAS UN1 | C68: 87.249.561/0001-07 | D68: 99281.7 | E68: 1246271672 | F68: 46157 | H68: 1 | I68: Adtives | J68: 11156 | K68: 46129 | L68: 1010100 | M68: VENDAS MERCADO INTERNO | N68: 161 | O68: VENDA PROD. INDUSTRIALIZADO - NFE | P68: GRUPO UNIFERTIL | Q68: =$R$1-F68 -> -16 | R68: =_xlfn.XLOOKUP(P68,'Painel Additive'!$B:$B,'Painel Additive'!$B:$B,0) -> GRUPO UNIFERTIL | S68: =F68-K68 -> 28
A69: 2 | B69: CARGILL - UBERLÂNDIA | C69: 60.498.706/0134-88 | D69: 13431 | E69: 1246272905 | F69: 46168 | G69: 46146 | H69: 3 | I69: Job Work | J69: 2898 | K69: 46140 | L69: 1010100 | M69: VENDAS MERCADO INTERNO | N69: 199 | O69: VENDA MERC INDUSTRIALIZADA TERCEIROS | P69: GRUPO CARGILL | Q69: =$R$1-F69 -> -27 | R69: =_xlfn.XLOOKUP(P69,'Painel Additive'!$B:$B,'Painel Additive'!$B:$B,0) -> GRUPO CARGILL | S69: =F69-K69 -> 28
A70: 183 | B70: HERINGER - RONDONÓPOLIS II | C70: 22.266.175/0036-08 | D70: 4231.96 | E70: 1246014155 | F70: 47847 | H70: 1 | I70: Adtives | J70: 8361 | K70: 43384 | L70: 1010100 | M70: VENDAS MERCADO INTERNO | N70: 161 | O70: VENDA PROD. INDUSTRIALIZADO - NFE | P70: GRUPO HERINGER | Q70: =$R$1-F70 -> -1706 | R70: =_xlfn.XLOOKUP(P70,'Painel Additive'!$B:$B,'Painel Additive'!$B:$B,0) -> GRUPO HERINGER | S70: =F70-K70 -> 4463
A71: 183 | B71: HERINGER - RONDONÓPOLIS II | C71: 22.266.175/0036-08 | D71: 4045.01 | E71: 1246014156 | F71: 48212 | H71: 1 | I71: Adtives | J71: 8361 | K71: 43384 | L71: 1010100 | M71: VENDAS MERCADO INTERNO | N71: 161 | O71: VENDA PROD. INDUSTRIALIZADO - NFE | P71: GRUPO HERINGER | Q71: =$R$1-F71 -> -2071 | R71: =_xlfn.XLOOKUP(P71,'Painel Additive'!$B:$B,'Painel Additive'!$B:$B,0) -> GRUPO HERINGER | S71: =F71-K71 -> 4828
A72: 183 | B72: HERINGER - RONDONÓPOLIS II | C72: 22.266.175/0036-08 | D72: 4339.6 | E72: 1246014157 | F72: 48578 | H72: 1 | I72: Adtives | J72: 8361 | K72: 43384 | L72: 1010100 | M72: VENDAS MERCADO INTERNO | N72: 161 | O72: VENDA PROD. INDUSTRIALIZADO - NFE | P72: GRUPO HERINGER | Q72: =$R$1-F72 -> -2437 | R72: =_xlfn.XLOOKUP(P72,'Painel Additive'!$B:$B,'Painel Additive'!$B:$B,0) -> GRUPO HERINGER | S72: =F72-K72 -> 5194
A73: 183 | B73: HERINGER - RONDONÓPOLIS II | C73: 22.266.175/0036-08 | D73: 7512.16 | E73: 1246014158 | F73: 48943 | H73: 1 | I73: Adtives | J73: 8361 | K73: 43384 | L73: 1010100 | M73: VENDAS MERCADO INTERNO | N73: 161 | O73: VENDA PROD. INDUSTRIALIZADO - NFE | P73: GRUPO HERINGER | Q73: =$R$1-F73 -> -2802 | R73: =_xlfn.XLOOKUP(P73,'Painel Additive'!$B:$B,'Painel Additive'!$B:$B,0) -> GRUPO HERINGER | S73: =F73-K73 -> 5559
A74: 183 | B74: HERINGER - RONDONÓPOLIS II | C74: 22.266.175/0036-08 | D74: 30552.86 | E74: 1246014159 | F74: 49308 | H74: 1 | I74: Adtives | J74: 8361 | K74: 43384 | L74: 1010100 | M74: VENDAS MERCADO INTERNO | N74: 161 | O74: VENDA PROD. INDUSTRIALIZADO - NFE | P74: GRUPO HERINGER | Q74: =$R$1-F74 -> -3167 | R74: =_xlfn.XLOOKUP(P74,'Painel Additive'!$B:$B,'Painel Additive'!$B:$B,0) -> GRUPO HERINGER | S74: =F74-K74 -> 5924
A75: 183 | B75: HERINGER - RONDONÓPOLIS II | C75: 22.266.175/0036-08 | D75: 1512.63 | E75: 1246014161 | F75: 50039 | H75: 1 | I75: Adtives | J75: 8361 | K75: 43384 | L75: 1010100 | M75: VENDAS MERCADO INTERNO | N75: 161 | O75: VENDA PROD. INDUSTRIALIZADO - NFE | P75: GRUPO HERINGER | Q75: =$R$1-F75 -> -3898 | R75: =_xlfn.XLOOKUP(P75,'Painel Additive'!$B:$B,'Painel Additive'!$B:$B,0) -> GRUPO HERINGER | S75: =F75-K75 -> 6655
A76: 183 | B76: HERINGER - RONDONÓPOLIS II | C76: 22.266.175/0036-08 | D76: 1982.85 | E76: 1246014162 | F76: 50404 | H76: 1 | I76: Adtives | J76: 8361 | K76: 43384 | L76: 1010100 | M76: VENDAS MERCADO INTERNO | N76: 161 | O76: VENDA PROD. INDUSTRIALIZADO - NFE | P76: GRUPO HERINGER | Q76: =$R$1-F76 -> -4263 | R76: =_xlfn.XLOOKUP(P76,'Painel Additive'!$B:$B,'Painel Additive'!$B:$B,0) -> GRUPO HERINGER | S76: =F76-K76 -> 7020
A77: 183 | B77: HERINGER - RONDONÓPOLIS II | C77: 22.266.175/0036-08 | D77: 2549.38 | E77: 1246014163 | F77: 50769 | H77: 1 | I77: Adtives | J77: 8361 | K77: 43384 | L77: 1010100 | M77: VENDAS MERCADO INTERNO | N77: 161 | O77: VENDA PROD. INDUSTRIALIZADO - NFE | P77: GRUPO HERINGER | Q77: =$R$1-F77 -> -4628 | R77: =_xlfn.XLOOKUP(P77,'Painel Additive'!$B:$B,'Painel Additive'!$B:$B,0) -> GRUPO HERINGER | S77: =F77-K77 -> 7385
A78: 183 | B78: HERINGER - RONDONÓPOLIS II | C78: 22.266.175/0036-08 | D78: 5546.31 | E78: 1246014165 | F78: 51500 | H78: 1 | I78: Adtives | J78: 8361 | K78: 43384 | L78: 1010100 | M78: VENDAS MERCADO INTERNO | N78: 161 | O78: VENDA PROD. INDUSTRIALIZADO - NFE | P78: GRUPO HERINGER | Q78: =$R$1-F78 -> -5359 | R78: =_xlfn.XLOOKUP(P78,'Painel Additive'!$B:$B,'Painel Additive'!$B:$B,0) -> GRUPO HERINGER | S78: =F78-K78 -> 8116
A79: 183 | B79: HERINGER - RONDONÓPOLIS II | C79: 22.266.175/0036-08 | D79: 5546.31 | E79: 1246014166 | F79: 51865 | H79: 1 | I79: Adtives | J79: 8361 | K79: 43384 | L79: 1010100 | M79: VENDAS MERCADO INTERNO | N79: 161 | O79: VENDA PROD. INDUSTRIALIZADO - NFE | P79: GRUPO HERINGER | Q79: =$R$1-F79 -> -5724 | R79: =_xlfn.XLOOKUP(P79,'Painel Additive'!$B:$B,'Painel Additive'!$B:$B,0) -> GRUPO HERINGER | S79: =F79-K79 -> 8481
A80: 183 | B80: HERINGER - RONDONÓPOLIS II | C80: 22.266.175/0036-08 | D80: 5546.31 | E80: 1246014167 | F80: 52230 | H80: 1 | I80: Adtives | J80: 8361 | K80: 43384 | L80: 1010100 | M80: VENDAS MERCADO INTERNO | N80: 161 | O80: VENDA PROD. INDUSTRIALIZADO - NFE | P80: GRUPO HERINGER | Q80: =$R$1-F80 -> -6089 | R80: =_xlfn.XLOOKUP(P80,'Painel Additive'!$B:$B,'Painel Additive'!$B:$B,0) -> GRUPO HERINGER | S80: =F80-K80 -> 8846
A81: 183 | B81: HERINGER - RONDONÓPOLIS II | C81: 22.266.175/0036-08 | D81: 5546.31 | E81: 1246014168 | F81: 52595 | H81: 1 | I81: Adtives | J81: 8361 | K81: 43384 | L81: 1010100 | M81: VENDAS MERCADO INTERNO | N81: 161 | O81: VENDA PROD. INDUSTRIALIZADO - NFE | P81: GRUPO HERINGER | Q81: =$R$1-F81 -> -6454 | R81: =_xlfn.XLOOKUP(P81,'Painel Additive'!$B:$B,'Painel Additive'!$B:$B,0) -> GRUPO HERINGER | S81: =F81-K81 -> 9211
... A101: 201 | B101: JOSAPAR - PELOTAS | C101: 87.456.562/0006-37 | D101: 185040 | E101: 1246269671 | F101: 46231 | H101: 1 | I101: Adtives | J101: 2855 | K101: 46111 | L101: 1010100 | M101: VENDAS MERCADO INTERNO | N101: 161 | O101: VENDA PROD. INDUSTRIALIZADO - NFE | P101: GRUPO JOSAPAR | Q101: =$R$1-F101 -> -90 | R101: =_xlfn.XLOOKUP(P101,'Painel Additive'!$B:$B,'Painel Additive'!$B:$B,0) -> GRUPO JOSAPAR | S101: =F101-K101 -> 120
A102: 903 | B102: YARA - PONTA GROSSA | C102: 92.660.604/0138-37 | D102: 133334.43 | E102: 1246268951 | F102: 46146 | G102: 46146 | H102: 1 | I102: Adtives | J102: 10971 | K102: 46106 | L102: 1010100 | M102: VENDAS MERCADO INTERNO | N102: 161 | O102: VENDA PROD. INDUSTRIALIZADO - NFE | P102: GRUPO YARA | Q102: =$R$1-F102 -> -5 | R102: =_xlfn.XLOOKUP(P102,'Painel Additive'!$B:$B,'Painel Additive'!$B:$B,0) -> GRUPO YARA | S102: =F102-K102 -> 40
A103: 903 | B103: YARA - PONTA GROSSA | C103: 92.660.604/0138-37 | D103: 135135.03 | E103: 1246272230 | F103: 46175 | H103: 1 | I103: Adtives | J103: 11199 | K103: 46135 | L103: 1010100 | M103: VENDAS MERCADO INTERNO | N103: 161 | O103: VENDA PROD. INDUSTRIALIZADO - NFE | P103: GRUPO YARA | Q103: =$R$1-F103 -> -34 | R103: =_xlfn.XLOOKUP(P103,'Painel Additive'!$B:$B,'Painel Additive'!$B:$B,0) -> GRUPO YARA | S103: =F103-K103 -> 40
A104: 903 | B104: YARA - PONTA GROSSA | C104: 92.660.604/0138-37 | D104: 134594.85 | E104: 1246270087 | F104: 46154 | H104: 1 | I104: Adtives | J104: 11034 | K104: 46114 | L104: 1010100 | M104: VENDAS MERCADO INTERNO | N104: 161 | O104: VENDA PROD. INDUSTRIALIZADO - NFE | P104: GRUPO YARA | Q104: =$R$1-F104 -> -13 | R104: =_xlfn.XLOOKUP(P104,'Painel Additive'!$B:$B,'Painel Additive'!$B:$B,0) -> GRUPO YARA | S104: =F104-K104 -> 40
A105: 903 | B105: YARA - PONTA GROSSA | C105: 92.660.604/0138-37 | D105: 134504.82 | E105: 1246271047 | F105: 46162 | H105: 1 | I105: Adtives | J105: 11098 | K105: 46122 | L105: 1010100 | M105: VENDAS MERCADO INTERNO | N105: 161 | O105: VENDA PROD. INDUSTRIALIZADO - NFE | P105: GRUPO YARA | Q105: =$R$1-F105 -> -21 | R105: =_xlfn.XLOOKUP(P105,'Painel Additive'!$B:$B,'Painel Additive'!$B:$B,0) -> GRUPO YARA | S105: =F105-K105 -> 40
A106: 903 | B106: YARA - PONTA GROSSA | C106: 92.660.604/0138-37 | D106: 134864.94 | E106: 1246269425 | F106: 46148 | H106: 1 | I106: Adtives | J106: 10990 | K106: 46108 | L106: 1010100 | M106: VENDAS MERCADO INTERNO | N106: 161 | O106: VENDA PROD. INDUSTRIALIZADO - NFE | P106: GRUPO YARA | Q106: =$R$1-F106 -> -7 | R106: =_xlfn.XLOOKUP(P106,'Painel Additive'!$B:$B,'Painel Additive'!$B:$B,0) -> GRUPO YARA | S106: =F106-K106 -> 40
A107: 903 | B107: YARA - PONTA GROSSA | C107: 92.660.604/0138-37 | D107: 134774.91 | E107: 1246273177 | F107: 46182 | H107: 1 | I107: Adtives | J107: 11266 | K107: 46142 | L107: 1010100 | M107: VENDAS MERCADO INTERNO | N107: 161 | O107: VENDA PROD. INDUSTRIALIZADO - NFE | P107: GRUPO YARA | Q107: =$R$1-F107 -> -41 | R107: =_xlfn.XLOOKUP(P107,'Painel Additive'!$B:$B,'Painel Additive'!$B:$B,0) -> GRUPO YARA | S107: =F107-K107 -> 40
A108: 86 | B108: ADUBOS ARAGUAIA - ANAPOLIS | C108: 03.306.578/0012-11 | D108: 35810 | E108: 1246273225 | F108: 46202 | H108: 1 | I108: Adtives | J108: 11271 | K108: 46142 | L108: 1010100 | M108: VENDAS MERCADO INTERNO | N108: 161 | O108: VENDA PROD. INDUSTRIALIZADO - NFE | P108: GRUPO ADUBOS ARAGUAIA | Q108: =$R$1-F108 -> -61 | R108: =_xlfn.XLOOKUP(P108,'Painel Additive'!$B:$B,'Painel Additive'!$B:$B,0) -> GRUPO ADUBOS ARAGUAIA | S108: =F108-K108 -> 60
A109: 729 | B109: FERTILIZ. TOCANTINS - SÃO LUIS | C109: 05.571.228/0003-17 | D109: 69762.4 | E109: 1246273030 | F109: 46201 | H109: 1 | I109: Adtives | J109: 11251 | K109: 46141 | L109: 1010100 | M109: VENDAS MERCADO INTERNO | N109: 161 | O109: VENDA PROD. INDUSTRIALIZADO - NFE | P109: GRUPO FERTILIZ TOCANTINS | Q109: =$R$1-F109 -> -60 | R109: =_xlfn.XLOOKUP(P109,'Painel Additive'!$B:$B,'Painel Additive'!$B:$B,0) -> GRUPO FERTILIZ TOCANTINS | S109: =F109-K109 -> 60
A110: 1159 | B110: YARA - RIO GRANDE | C110: 92.660.604/0013-16 | D110: 272555.72 | E110: 1246268636 | F110: 46144 | G110: 46146 | H110: 1 | I110: Adtives | J110: 10958 | K110: 46104 | L110: 1010100 | M110: VENDAS MERCADO INTERNO | N110: 161 | O110: VENDA PROD. INDUSTRIALIZADO - NFE | P110: GRUPO YARA | Q110: =$R$1-F110 -> -3 | R110: =_xlfn.XLOOKUP(P110,'Painel Additive'!$B:$B,'Painel Additive'!$B:$B,0) -> GRUPO YARA | S110: =F110-K110 -> 40
A111: 1159 | B111: YARA - RIO GRANDE | C111: 92.660.604/0013-16 | D111: 8928.75 | E111: 1246273695 | F111: 46180 | G111: 46148 | H111: 1 | I111: Adtives | J111: 11240 | K111: 46140 | L111: 1010100 | M111: VENDAS MERCADO INTERNO | N111: 161 | O111: VENDA PROD. INDUSTRIALIZADO - NFE | P111: GRUPO YARA | Q111: =$R$1-F111 -> -39 | R111: =_xlfn.XLOOKUP(P111,'Painel Additive'!$B:$B,'Painel Additive'!$B:$B,0) -> GRUPO YARA | S111: =F111-K111 -> 40
A112: 1159 | B112: YARA - RIO GRANDE | C112: 92.660.604/0013-16 | D112: 1458 | E112: 1246148463 | F112: 45443 | H112: 1 | I112: Adtives | J112: 3446 | K112: 45415 | L112: 1010100 | M112: VENDAS MERCADO INTERNO | N112: 161 | O112: VENDA PROD. INDUSTRIALIZADO - NFE | P112: GRUPO YARA | Q112: =$R$1-F112 -> 698 | R112: =_xlfn.XLOOKUP(P112,'Painel Additive'!$B:$B,'Painel Additive'!$B:$B,0) -> GRUPO YARA | S112: =F112-K112 -> 28
A113: 1159 | B113: YARA - RIO GRANDE | C113: 92.660.604/0013-16 | D113: 274909.24 | E113: 1246271894 | F113: 46172 | H113: 1 | I113: Adtives | J113: 11179 | K113: 46132 | L113: 1010100 | M113: VENDAS MERCADO INTERNO | N113: 161 | O113: VENDA PROD. INDUSTRIALIZADO - NFE | P113: GRUPO YARA | Q113: =$R$1-F113 -> -31 | R113: =_xlfn.XLOOKUP(P113,'Painel Additive'!$B:$B,'Painel Additive'!$B:$B,0) -> GRUPO YARA | S113: =F113-K113 -> 40
A114: 1159 | B114: YARA - RIO GRANDE | C114: 92.660.604/0013-16 | D114: 271741.04 | E114: 1246269608 | F114: 46151 | H114: 1 | I114: Adtives | J114: 11006 | K114: 46111 | L114: 1010100 | M114: VENDAS MERCADO INTERNO | N114: 161 | O114: VENDA PROD. INDUSTRIALIZADO - NFE | P114: GRUPO YARA | Q114: =$R$1-F114 -> -10 | R114: =_xlfn.XLOOKUP(P114,'Painel Additive'!$B:$B,'Painel Additive'!$B:$B,0) -> GRUPO YARA | S114: =F114-K114 -> 40
A115: 1159 | B115: YARA - RIO GRANDE | C115: 92.660.604/0013-16 | D115: 272193.64 | E115: 1246269418 | F115: 46148 | H115: 1 | I115: Adtives | J115: 10988 | K115: 46108 | L115: 1010100 | M115: VENDAS MERCADO INTERNO | N115: 161 | O115: VENDA PROD. INDUSTRIALIZADO - NFE | P115: GRUPO YARA | Q115: =$R$1-F115 -> -7 | R115: =_xlfn.XLOOKUP(P115,'Painel Additive'!$B:$B,'Painel Additive'!$B:$B,0) -> GRUPO YARA | S115: =F115-K115 -> 40
A116: 1159 | B116: YARA - RIO GRANDE | C116: 92.660.604/0013-16 | D116: 271469.48 | E116: 1246270981 | F116: 46162 | H116: 1 | I116: Adtives | J116: 11089 | K116: 46122 | L116: 1010100 | M116: VENDAS MERCADO INTERNO | N116: 161 | O116: VENDA PROD. INDUSTRIALIZADO - NFE | P116: GRUPO YARA | Q116: =$R$1-F116 -> -21 | R116: =_xlfn.XLOOKUP(P116,'Painel Additive'!$B:$B,'Painel Additive'!$B:$B,0) -> GRUPO YARA | S116: =F116-K116 -> 40
A117: 1159 | B117: YARA - RIO GRANDE | C117: 92.660.604/0013-16 | D117: 271650.52 | E117: 1246270614 | F117: 46160 | H117: 1 | I117: Adtives | J117: 11070 | K117: 46120 | L117: 1010100 | M117: VENDAS MERCADO INTERNO | N117: 161 | O117: VENDA PROD. INDUSTRIALIZADO - NFE | P117: GRUPO YARA | Q117: =$R$1-F117 -> -19 | R117: =_xlfn.XLOOKUP(P117,'Painel Additive'!$B:$B,'Painel Additive'!$B:$B,0) -> GRUPO YARA | S117: =F117-K117 -> 40
A118: 1159 | B118: YARA - RIO GRANDE | C118: 92.660.604/0013-16 | D118: 271831.56 | E118: 1246269882 | F118: 46153 | H118: 1 | I118: Adtives | J118: 11024 | K118: 46113 | L118: 1010100 | M118: VENDAS MERCADO INTERNO | N118: 161 | O118: VENDA PROD. INDUSTRIALIZADO - NFE | P118: GRUPO YARA | Q118: =$R$1-F118 -> -12 | R118: =_xlfn.XLOOKUP(P118,'Painel Additive'!$B:$B,'Painel Additive'!$B:$B,0) -> GRUPO YARA | S118: =F118-K118 -> 40
A119: 1159 | B119: YARA - RIO GRANDE | C119: 92.660.604/0013-16 | D119: 271469.48 | E119: 1246273041 | F119: 46181 | H119: 1 | I119: Adtives | J119: 11254 | K119: 46141 | L119: 1010100 | M119: VENDAS MERCADO INTERNO | N119: 161 | O119: VENDA PROD. INDUSTRIALIZADO - NFE | P119: GRUPO YARA | Q119: =$R$1-F119 -> -40 | R119: =_xlfn.XLOOKUP(P119,'Painel Additive'!$B:$B,'Painel Additive'!$B:$B,0) -> GRUPO YARA | S119: =F119-K119 -> 40
A120: 1159 | B120: YARA - RIO GRANDE | C120: 92.660.604/0013-16 | D120: 272193.64 | E120: 1246273282 | F120: 46182 | H120: 1 | I120: Adtives | J120: 11274 | K120: 46142 | L120: 1010100 | M120: VENDAS MERCADO INTERNO | N120: 161 | O120: VENDA PROD. INDUSTRIALIZADO - NFE | P120: GRUPO YARA | Q120: =$R$1-F120 -> -41 | R120: =_xlfn.XLOOKUP(P120,'Painel Additive'!$B:$B,'Painel Additive'!$B:$B,0) -> GRUPO YARA | S120: =F120-K120 -> 40
A121: 1159 | B121: YARA - RIO GRANDE | C121: 92.660.604/0013-16 | D121: 272012.6 | E121: 1246272754 | F121: 46179 | H121: 1 | I121: Adtives | J121: 11228 | K121: 46139 | L121: 1010100 | M121: VENDAS MERCADO INTERNO | N121: 161 | O121: VENDA PROD. INDUSTRIALIZADO - NFE | P121: GRUPO YARA | Q121: =$R$1-F121 -> -38 | R121: =_xlfn.XLOOKUP(P121,'Painel Additive'!$B:$B,'Painel Additive'!$B:$B,0) -> GRUPO YARA | S121: =F121-K121 -> 40
A122: 1159 | B122: YARA - RIO GRANDE | C122: 92.660.604/0013-16 | D122: 271107.4 | E122: 1246271171 | F122: 46165 | H122: 1 | I122: Adtives | J122: 11108 | K122: 46125 | L122: 1010100 | M122: VENDAS MERCADO INTERNO | N122: 161 | O122: VENDA PROD. INDUSTRIALIZADO - NFE | P122: GRUPO YARA | Q122: =$R$1-F122 -> -24 | R122: =_xlfn.XLOOKUP(P122,'Painel Additive'!$B:$B,'Painel Additive'!$B:$B,0) -> GRUPO YARA | S122: =F122-K122 -> 40
A123: 1159 | B123: YARA - RIO GRANDE | C123: 92.660.604/0013-16 | D123: 2445.45 | E123: 1246272869 | F123: 46180 | H123: 1 | I123: Adtives | J123: 11240 | K123: 46140 | L123: 1010100 | M123: VENDAS MERCADO INTERNO | N123: 161 | O123: VENDA PROD. INDUSTRIALIZADO - NFE | P123: GRUPO YARA | Q123: =$R$1-F123 -> -39 | R123: =_xlfn.XLOOKUP(P123,'Painel Additive'!$B:$B,'Painel Additive'!$B:$B,0) -> GRUPO YARA | S123: =F123-K123 -> 40
... A138: 6124 | B138: MOSAIC - UBERABA (UBA III) | C138: 61.156.501/0110-00 | D138: 52374 | E138: 1246267926 | F138: 46187 | H138: 1 | I138: Adtives | J138: 10897 | K138: 46097 | L138: 1010100 | M138: VENDAS MERCADO INTERNO | N138: 161 | O138: VENDA PROD. INDUSTRIALIZADO - NFE | P138: GRUPO MOSAIC FERTILIZANTES DO BRASIL | Q138: =$R$1-F138 -> -46 | R138: =_xlfn.XLOOKUP(P138,'Painel Additive'!$B:$B,'Painel Additive'!$B:$B,0) -> GRUPO MOSAIC FERTILIZANTES DO BRASIL | S138: =F138-K138 -> 90
A139: 7102 | B139: MOSAIC - RONDONOPOLIS | C139: 61.156.501/0115-14 | D139: 62553.7 | E139: 1246262017 | F139: 46145 | G139: 46146 | H139: 1 | I139: Adtives | J139: 10626 | K139: 46055 | L139: 1010100 | M139: VENDAS MERCADO INTERNO | N139: 161 | O139: VENDA PROD. INDUSTRIALIZADO - NFE | P139: GRUPO MOSAIC FERTILIZANTES DO BRASIL | Q139: =$R$1-F139 -> -4 | R139: =_xlfn.XLOOKUP(P139,'Painel Additive'!$B:$B,'Painel Additive'!$B:$B,0) -> GRUPO MOSAIC FERTILIZANTES DO BRASIL | S139: =F139-K139 -> 90
A140: 7102 | B140: MOSAIC - RONDONOPOLIS | C140: 61.156.501/0115-14 | D140: 63327 | E140: 1246270569 | F140: 46210 | H140: 1 | I140: Adtives | J140: 11069 | K140: 46120 | L140: 1010100 | M140: VENDAS MERCADO INTERNO | N140: 161 | O140: VENDA PROD. INDUSTRIALIZADO - NFE | P140: GRUPO MOSAIC FERTILIZANTES DO BRASIL | Q140: =$R$1-F140 -> -69 | R140: =_xlfn.XLOOKUP(P140,'Painel Additive'!$B:$B,'Painel Additive'!$B:$B,0) -> GRUPO MOSAIC FERTILIZANTES DO BRASIL | S140: =F140-K140 -> 90
A141: 7102 | B141: MOSAIC - RONDONOPOLIS | C141: 61.156.501/0115-14 | D141: 62637.3 | E141: 1246268784 | F141: 46195 | H141: 1 | I141: Adtives | J141: 10966 | K141: 46105 | L141: 1010100 | M141: VENDAS MERCADO INTERNO | N141: 161 | O141: VENDA PROD. INDUSTRIALIZADO - NFE | P141: GRUPO MOSAIC FERTILIZANTES DO BRASIL | Q141: =$R$1-F141 -> -54 | R141: =_xlfn.XLOOKUP(P141,'Painel Additive'!$B:$B,'Painel Additive'!$B:$B,0) -> GRUPO MOSAIC FERTILIZANTES DO BRASIL | S141: =F141-K141 -> 90
A142: 7102 | B142: MOSAIC - RONDONOPOLIS | C142: 61.156.501/0115-14 | D142: 62700 | E142: 1246262728 | F142: 46152 | H142: 1 | I142: Adtives | J142: 10663 | K142: 46062 | L142: 1010100 | M142: VENDAS MERCADO INTERNO | N142: 161 | O142: VENDA PROD. INDUSTRIALIZADO - NFE | P142: GRUPO MOSAIC FERTILIZANTES DO BRASIL | Q142: =$R$1-F142 -> -11 | R142: =_xlfn.XLOOKUP(P142,'Painel Additive'!$B:$B,'Painel Additive'!$B:$B,0) -> GRUPO MOSAIC FERTILIZANTES DO BRASIL | S142: =F142-K142 -> 90
A143: 7662 | B143: BENTONIT UNIAO - BOA VISTA | C143: 08.811.119/0008-22 | D143: 57795 | E143: 1246266876 | F143: 46147 | G143: 46147 | H143: 1 | I143: Adtives | J143: 2799 | K143: 46087 | L143: 1010100 | M143: VENDAS MERCADO INTERNO | N143: 161 | O143: VENDA PROD. INDUSTRIALIZADO - NFE | P143: BENTONIT UNIAO - CAMPINA GRANDE | Q143: =$R$1-F143 -> -6 | R143: =_xlfn.XLOOKUP(P143,'Painel Additive'!$B:$B,'Painel Additive'!$B:$B,0) -> BENTONIT UNIAO - CAMPINA GRANDE | S143: =F143-K143 -> 60
A144: 7662 | B144: BENTONIT UNIAO - BOA VISTA | C144: 08.811.119/0008-22 | D144: 91675 | E144: 1246273180 | F144: 46202 | H144: 1 | I144: Adtives | J144: 2902 | K144: 46142 | L144: 1010100 | M144: VENDAS MERCADO INTERNO | N144: 161 | O144: VENDA PROD. INDUSTRIALIZADO - NFE | P144: BENTONIT UNIAO - CAMPINA GRANDE | Q144: =$R$1-F144 -> -61 | R144: =_xlfn.XLOOKUP(P144,'Painel Additive'!$B:$B,'Painel Additive'!$B:$B,0) -> BENTONIT UNIAO - CAMPINA GRANDE | S144: =F144-K144 -> 60
A145: 7662 | B145: BENTONIT UNIAO - BOA VISTA | C145: 08.811.119/0008-22 | D145: 91675 | E145: 1246273179 | F145: 46187 | H145: 1 | I145: Adtives | J145: 2902 | K145: 46142 | L145: 1010100 | M145: VENDAS MERCADO INTERNO | N145: 161 | O145: VENDA PROD. INDUSTRIALIZADO - NFE | P145: BENTONIT UNIAO - CAMPINA GRANDE | Q145: =$R$1-F145 -> -46 | R145: =_xlfn.XLOOKUP(P145,'Painel Additive'!$B:$B,'Painel Additive'!$B:$B,0) -> BENTONIT UNIAO - CAMPINA GRANDE | S145: =F145-K145 -> 45
A146: 7662 | B146: BENTONIT UNIAO - BOA VISTA | C146: 08.811.119/0008-22 | D146: 77060 | E146: 1246269689 | F146: 46157 | H146: 1 | I146: Adtives | J146: 2856 | K146: 46112 | L146: 1010100 | M146: VENDAS MERCADO INTERNO | N146: 161 | O146: VENDA PROD. INDUSTRIALIZADO - NFE | P146: BENTONIT UNIAO - CAMPINA GRANDE | Q146: =$R$1-F146 -> -16 | R146: =_xlfn.XLOOKUP(P146,'Painel Additive'!$B:$B,'Painel Additive'!$B:$B,0) -> BENTONIT UNIAO - CAMPINA GRANDE | S146: =F146-K146 -> 45
A147: 7662 | B147: BENTONIT UNIAO - BOA VISTA | C147: 08.811.119/0008-22 | D147: 77060 | E147: 1246269690 | F147: 46172 | H147: 1 | I147: Adtives | J147: 2856 | K147: 46112 | L147: 1010100 | M147: VENDAS MERCADO INTERNO | N147: 161 | O147: VENDA PROD. INDUSTRIALIZADO - NFE | P147: BENTONIT UNIAO - CAMPINA GRANDE | Q147: =$R$1-F147 -> -31 | R147: =_xlfn.XLOOKUP(P147,'Painel Additive'!$B:$B,'Painel Additive'!$B:$B,0) -> BENTONIT UNIAO - CAMPINA GRANDE | S147: =F147-K147 -> 60
A148: 7479 | B148: MOSAIC - CUBATÃO | C148: 61.156.501/0099-60 | D148: 64104.8 | E148: 1246264518 | F148: 46166 | H148: 1 | I148: Adtives | J148: 10739 | K148: 46076 | L148: 1010100 | M148: VENDAS MERCADO INTERNO | N148: 56 | O148: VENDA A ORDEM | P148: GRUPO MOSAIC FERTILIZANTES DO BRASIL | Q148: =$R$1-F148 -> -25 | R148: =_xlfn.XLOOKUP(P148,'Painel Additive'!$B:$B,'Painel Additive'!$B:$B,0) -> GRUPO MOSAIC FERTILIZANTES DO BRASIL | S148: =F148-K148 -> 90
A149: 6477 | B149: MOSAIC - PARANAGUA II | C149: 61.156.501/0109-76 | D149: 167720 | E149: 1246262010 | F149: 46145 | G149: 46146 | H149: 1 | I149: Adtives | J149: 10625 | K149: 46055 | L149: 1010100 | M149: VENDAS MERCADO INTERNO | N149: 161 | O149: VENDA PROD. INDUSTRIALIZADO - NFE | P149: GRUPO MOSAIC FERTILIZANTES DO BRASIL | Q149: =$R$1-F149 -> -4 | R149: =_xlfn.XLOOKUP(P149,'Painel Additive'!$B:$B,'Painel Additive'!$B:$B,0) -> GRUPO MOSAIC FERTILIZANTES DO BRASIL | S149: =F149-K149 -> 90
A150: 6477 | B150: MOSAIC - PARANAGUA II | C150: 61.156.501/0109-76 | D150: 166320 | E150: 1246263184 | F150: 46153 | H150: 1 | I150: Adtives | J150: 10673 | K150: 46063 | L150: 1010100 | M150: VENDAS MERCADO INTERNO | N150: 161 | O150: VENDA PROD. INDUSTRIALIZADO - NFE | P150: GRUPO MOSAIC FERTILIZANTES DO BRASIL | Q150: =$R$1-F150 -> -12 | R150: =_xlfn.XLOOKUP(P150,'Painel Additive'!$B:$B,'Painel Additive'!$B:$B,0) -> GRUPO MOSAIC FERTILIZANTES DO BRASIL | S150: =F150-K150 -> 90
A151: 6477 | B151: MOSAIC - PARANAGUA II | C151: 61.156.501/0109-76 | D151: 6302.6 | E151: 1246212732 | F151: 45682 | H151: 1 | I151: Adtives | J151: 6197 | K151: 45622 | L151: 1010100 | M151: VENDAS MERCADO INTERNO | N151: 161 | O151: VENDA PROD. INDUSTRIALIZADO - NFE | P151: GRUPO MOSAIC FERTILIZANTES DO BRASIL | Q151: =$R$1-F151 -> 459 | R151: =_xlfn.XLOOKUP(P151,'Painel Additive'!$B:$B,'Painel Additive'!$B:$B,0) -> GRUPO MOSAIC FERTILIZANTES DO BRASIL | S151: =F151-K151 -> 60
A152: 7097 | B152: MOSAIC - SÃO FRANCISCO SUL | C152: 61.156.501/0125-96 | D152: 177977.8 | E152: 1246265921 | F152: 46173 | G152: 46146 | H152: 1 | I152: Adtives | J152: 10795 | K152: 46083 | L152: 1010100 | M152: VENDAS MERCADO INTERNO | N152: 161 | O152: VENDA PROD. INDUSTRIALIZADO - NFE | P152: GRUPO MOSAIC FERTILIZANTES DO BRASIL | Q152: =$R$1-F152 -> -32 | R152: =_xlfn.XLOOKUP(P152,'Painel Additive'!$B:$B,'Painel Additive'!$B:$B,0) -> GRUPO MOSAIC FERTILIZANTES DO BRASIL | S152: =F152-K152 -> 90
A153: 7024 | B153: MOSAIC - SORRISO | C153: 61.156.501/0092-93 | D153: 70855.2 | E153: 1246269662 | F153: 46201 | H153: 1 | I153: Adtives | J153: 11011 | K153: 46111 | L153: 1010100 | M153: VENDAS MERCADO INTERNO | N153: 161 | O153: VENDA PROD. INDUSTRIALIZADO - NFE | P153: GRUPO MOSAIC FERTILIZANTES DO BRASIL | Q153: =$R$1-F153 -> -60 | R153: =_xlfn.XLOOKUP(P153,'Painel Additive'!$B:$B,'Painel Additive'!$B:$B,0) -> GRUPO MOSAIC FERTILIZANTES DO BRASIL | S153: =F153-K153 -> 90
A154: 7024 | B154: MOSAIC - SORRISO | C154: 61.156.501/0092-93 | D154: 71323.2 | E154: 1246270943 | F154: 46212 | H154: 1 | I154: Adtives | J154: 11084 | K154: 46122 | L154: 1010100 | M154: VENDAS MERCADO INTERNO | N154: 161 | O154: VENDA PROD. INDUSTRIALIZADO - NFE | P154: GRUPO MOSAIC FERTILIZANTES DO BRASIL | Q154: =$R$1-F154 -> -71 | R154: =_xlfn.XLOOKUP(P154,'Painel Additive'!$B:$B,'Painel Additive'!$B:$B,0) -> GRUPO MOSAIC FERTILIZANTES DO BRASIL | S154: =F154-K154 -> 90
A155: 7024 | B155: MOSAIC - SORRISO | C155: 61.156.501/0092-93 | D155: 70410.6 | E155: 1246265856 | F155: 46170 | H155: 1 | I155: Adtives | J155: 10790 | K155: 46080 | L155: 1010100 | M155: VENDAS MERCADO INTERNO | N155: 161 | O155: VENDA PROD. INDUSTRIALIZADO - NFE | P155: GRUPO MOSAIC FERTILIZANTES DO BRASIL | Q155: =$R$1-F155 -> -29 | R155: =_xlfn.XLOOKUP(P155,'Painel Additive'!$B:$B,'Painel Additive'!$B:$B,0) -> GRUPO MOSAIC FERTILIZANTES DO BRASIL | S155: =F155-K155 -> 90
A156: 7302 | B156: MOSAIC - PARANAGUA I | C156: 61.156.501/0080-50 | D156: 167720 | E156: 1246262004 | F156: 46145 | G156: 46146 | H156: 1 | I156: Adtives | J156: 10622 | K156: 46055 | L156: 1010100 | M156: VENDAS MERCADO INTERNO | N156: 161 | O156: VENDA PROD. INDUSTRIALIZADO - NFE | P156: GRUPO MOSAIC FERTILIZANTES DO BRASIL | Q156: =$R$1-F156 -> -4 | R156: =_xlfn.XLOOKUP(P156,'Painel Additive'!$B:$B,'Painel Additive'!$B:$B,0) -> GRUPO MOSAIC FERTILIZANTES DO BRASIL | S156: =F156-K156 -> 90
A157: 7302 | B157: MOSAIC - PARANAGUA I | C157: 61.156.501/0080-50 | D157: 1431.76 | E157: 1246062794 | F157: 44939 | H157: 1 | I157: Adtives | J157: 19884 | K157: 44879 | L157: 1010100 | M157: VENDAS MERCADO INTERNO | N157: 80 | O157: VENDA PROD REMETIDO P/ INDUSTRIALIZAÇÃO | P157: GRUPO MOSAIC FERTILIZANTES DO BRASIL | Q157: =$R$1-F157 -> 1202 | R157: =_xlfn.XLOOKUP(P157,'Painel Additive'!$B:$B,'Painel Additive'!$B:$B,0) -> GRUPO MOSAIC FERTILIZANTES DO BRASIL | S157: =F157-K157 -> 60
A158: 7302 | B158: MOSAIC - PARANAGUA I | C158: 61.156.501/0080-50 | D158: 2517.4 | E158: 1246055324 | F158: 44887 | H158: 1 | I158: Adtives | J158: 19314 | K158: 44827 | L158: 1010100 | M158: VENDAS MERCADO INTERNO | N158: 161 | O158: VENDA PROD. INDUSTRIALIZADO - NFE | P158: GRUPO MOSAIC FERTILIZANTES DO BRASIL | Q158: =$R$1-F158 -> 1254 | R158: =_xlfn.XLOOKUP(P158,'Painel Additive'!$B:$B,'Painel Additive'!$B:$B,0) -> GRUPO MOSAIC FERTILIZANTES DO BRASIL | S158: =F158-K158 -> 60
A159: 7302 | B159: MOSAIC - PARANAGUA I | C159: 61.156.501/0080-50 | D159: 36679.8 | E159: 1246272740 | F159: 46229 | H159: 1 | I159: Adtives | J159: 11223 | K159: 46139 | L159: 1010100 | M159: VENDAS MERCADO INTERNO | N159: 161 | O159: VENDA PROD. INDUSTRIALIZADO - NFE | P159: GRUPO MOSAIC FERTILIZANTES DO BRASIL | Q159: =$R$1-F159 -> -88 | R159: =_xlfn.XLOOKUP(P159,'Painel Additive'!$B:$B,'Painel Additive'!$B:$B,0) -> GRUPO MOSAIC FERTILIZANTES DO BRASIL | S159: =F159-K159 -> 90
A160: 7302 | B160: MOSAIC - PARANAGUA I | C160: 61.156.501/0080-50 | D160: 166320 | E160: 1246263181 | F160: 46153 | H160: 1 | I160: Adtives | J160: 10672 | K160: 46063 | L160: 1010100 | M160: VENDAS MERCADO INTERNO | N160: 161 | O160: VENDA PROD. INDUSTRIALIZADO - NFE | P160: GRUPO MOSAIC FERTILIZANTES DO BRASIL | Q160: =$R$1-F160 -> -12 | R160: =_xlfn.XLOOKUP(P160,'Painel Additive'!$B:$B,'Painel Additive'!$B:$B,0) -> GRUPO MOSAIC FERTILIZANTES DO BRASIL | S160: =F160-K160 -> 90
A161: 7302 | B161: MOSAIC - PARANAGUA I | C161: 61.156.501/0080-50 | D161: 67867.8 | E161: 1246270495 | F161: 46209 | H161: 1 | I161: Adtives | J161: 11064 | K161: 46119 | L161: 1010100 | M161: VENDAS MERCADO INTERNO | N161: 161 | O161: VENDA PROD. INDUSTRIALIZADO - NFE | P161: GRUPO MOSAIC FERTILIZANTES DO BRASIL | Q161: =$R$1-F161 -> -68 | R161: =_xlfn.XLOOKUP(P161,'Painel Additive'!$B:$B,'Painel Additive'!$B:$B,0) -> GRUPO MOSAIC FERTILIZANTES DO BRASIL | S161: =F161-K161 -> 90
A162: 7302 | B162: MOSAIC - PARANAGUA I | C162: 61.156.501/0080-50 | D162: 181231 | E162: 1246273299 | F162: 46232 | H162: 1 | I162: Adtives | J162: 11276 | K162: 46142 | L162: 1010100 | M162: VENDAS MERCADO INTERNO | N162: 161 | O162: VENDA PROD. INDUSTRIALIZADO - NFE | P162: GRUPO MOSAIC FERTILIZANTES DO BRASIL | Q162: =$R$1-F162 -> -91 | R162: =_xlfn.XLOOKUP(P162,'Painel Additive'!$B:$B,'Painel Additive'!$B:$B,0) -> GRUPO MOSAIC FERTILIZANTES DO BRASIL | S162: =F162-K162 -> 90
A163: 7302 | B163: MOSAIC - PARANAGUA I | C163: 61.156.501/0080-50 | D163: 129924 | E163: 1246268530 | F163: 46191 | H163: 1 | I163: Adtives | J163: 10941 | K163: 46101 | L163: 1010100 | M163: VENDAS MERCADO INTERNO | N163: 56 | O163: VENDA A ORDEM | P163: GRUPO MOSAIC FERTILIZANTES DO BRASIL | Q163: =$R$1-F163 -> -50 | R163: =_xlfn.XLOOKUP(P163,'Painel Additive'!$B:$B,'Painel Additive'!$B:$B,0) -> GRUPO MOSAIC FERTILIZANTES DO BRASIL | S163: =F163-K163 -> 90
A164: 7302 | B164: MOSAIC - PARANAGUA I | C164: 61.156.501/0080-50 | D164: 64.2 | E164: 1246226087 | F164: 45919 | H164: 1 | I164: Adtives | J164: 8559 | K164: 45859 | L164: 1010100 | M164: VENDAS MERCADO INTERNO | N164: 161 | O164: VENDA PROD. INDUSTRIALIZADO - NFE | P164: GRUPO MOSAIC FERTILIZANTES DO BRASIL | Q164: =$R$1-F164 -> 222 | R164: =_xlfn.XLOOKUP(P164,'Painel Additive'!$B:$B,'Painel Additive'!$B:$B,0) -> GRUPO MOSAIC FERTILIZANTES DO BRASIL | S164: =F164-K164 -> 60
A165: 7103 | B165: MOSAIC - RIO VERDE | C165: 61.156.501/0207-77 | D165: 57019 | E165: 1246269403 | F165: 46198 | H165: 1 | I165: Adtives | J165: 10985 | K165: 46108 | L165: 1010100 | M165: VENDAS MERCADO INTERNO | N165: 161 | O165: VENDA PROD. INDUSTRIALIZADO - NFE | P165: GRUPO MOSAIC FERTILIZANTES DO BRASIL | Q165: =$R$1-F165 -> -57 | R165: =_xlfn.XLOOKUP(P165,'Painel Additive'!$B:$B,'Painel Additive'!$B:$B,0) -> GRUPO MOSAIC FERTILIZANTES DO BRASIL | S165: =F165-K165 -> 90
A166: 8413 | B166: AMAGGI - SINOP | C166: 77.294.254/0024-80 | D166: 94346 | E166: 1246273107 | F166: 46201 | H166: 1 | I166: Adtives | J166: 11262 | K166: 46141 | L166: 1010100 | M166: VENDAS MERCADO INTERNO | N166: 161 | O166: VENDA PROD. INDUSTRIALIZADO - NFE | P166: GRUPO AMAGGI | Q166: =$R$1-F166 -> -60 | R166: =_xlfn.XLOOKUP(P166,'Painel Additive'!$B:$B,'Painel Additive'!$B:$B,0) -> GRUPO AMAGGI | S166: =F166-K166 -> 60
A167: 10473 | B167: LOUIS DREYFUS - RONDONÓPOLIS | C167: 47.067.525/0222-68 | D167: 62566.4 | E167: 1246272889 | F167: 46175 | H167: 1 | I167: Adtives | J167: 11243 | K167: 46140 | L167: 1010100 | M167: VENDAS MERCADO INTERNO | N167: 161 | O167: VENDA PROD. INDUSTRIALIZADO - NFE | P167: GRUPO LOUIS DREYFUS | Q167: =$R$1-F167 -> -34 | R167: =_xlfn.XLOOKUP(P167,'Painel Additive'!$B:$B,'Painel Additive'!$B:$B,0) -> GRUPO LOUIS DREYFUS | S167: =F167-K167 -> 35
A168: 11724 | B168: HINOVE - REGISTRO/SP | C168: 14.031.191/0004-06 | D168: 143868 | E168: 1246267487 | F168: 46167 | H168: 1 | I168: Adtives | J168: 10867 | K168: 46092 | L168: 1010100 | M168: VENDAS MERCADO INTERNO | N168: 161 | O168: VENDA PROD. INDUSTRIALIZADO - NFE | P168: GRUPO HINOVE | Q168: =$R$1-F168 -> -26 | R168: =_xlfn.XLOOKUP(P168,'Painel Additive'!$B:$B,'Painel Additive'!$B:$B,0) -> GRUPO HINOVE | S168: =F168-K168 -> 75
... A190: 707 | B190: TERRA FERTILIZANTES LTDA - ARAXÁ | C190: 10.482.668/0001-76 | D190: 16800 | E190: 1246141445 | F190: 45433 | H190: 1 | I190: Adtives | J190: 3345 | K190: 45405 | L190: 1010100 | M190: VENDAS MERCADO INTERNO | N190: 161 | O190: VENDA PROD. INDUSTRIALIZADO - NFE | P190: TERRA FERTILIZANTES LTDA - ARAXÁ | Q190: =$R$1-F190 -> 708 | R190: =_xlfn.XLOOKUP(P190,'Painel Additive'!$B:$B,'Painel Additive'!$B:$B,0) -> TERRA FERTILIZANTES LTDA - ARAXÁ | S190: =F190-K190 -> 28
A191: 707 | B191: TERRA FERTILIZANTES LTDA - ARAXÁ | C191: 10.482.668/0001-76 | D191: 40353.6 | E191: 1246143397 | F191: 45443 | H191: 1 | I191: Adtives | J191: 3448 | K191: 45415 | L191: 1010100 | M191: VENDAS MERCADO INTERNO | N191: 161 | O191: VENDA PROD. INDUSTRIALIZADO - NFE | P191: TERRA FERTILIZANTES LTDA - ARAXÁ | Q191: =$R$1-F191 -> 698 | R191: =_xlfn.XLOOKUP(P191,'Painel Additive'!$B:$B,'Painel Additive'!$B:$B,0) -> TERRA FERTILIZANTES LTDA - ARAXÁ | S191: =F191-K191 -> 28 | T191: =F191-$R$1 -> -698
A192: 1462 | B192: AURORA MINERAÇÃO LTDA | C192: 02.964.101/0001-08 | D192: 37608.4 | E192: 1246266894 | F192: 46147 | G192: 46147 | H192: 1 | I192: Adtives | J192: 10834 | K192: 46087 | L192: 1010100 | M192: VENDAS MERCADO INTERNO | N192: 161 | O192: VENDA PROD. INDUSTRIALIZADO - NFE | P192: AURORA MINERAÇÃO LTDA | Q192: =$R$1-F192 -> -6 | R192: =_xlfn.XLOOKUP(P192,'Painel Additive'!$B:$B,'Painel Additive'!$B:$B,0) -> AURORA MINERAÇÃO LTDA | S192: =F192-K192 -> 60 | T192: =F192-$R$1 -> 6
A193: 1462 | B193: AURORA MINERAÇÃO LTDA | C193: 02.964.101/0001-08 | D193: 37608.4 | E193: 1246266895 | F193: 46157 | H193: 1 | I193: Adtives | J193: 10834 | K193: 46087 | L193: 1010100 | M193: VENDAS MERCADO INTERNO | N193: 161 | O193: VENDA PROD. INDUSTRIALIZADO - NFE | P193: AURORA MINERAÇÃO LTDA | Q193: =$R$1-F193 -> -16 | R193: =_xlfn.XLOOKUP(P193,'Painel Additive'!$B:$B,'Painel Additive'!$B:$B,0) -> AURORA MINERAÇÃO LTDA | S193: =F193-K193 -> 70 | T193: =F193-$R$1 -> 16
A194: 1462 | B194: AURORA MINERAÇÃO LTDA | C194: 02.964.101/0001-08 | D194: 38160.2 | E194: 1246270126 | F194: 46174 | H194: 1 | I194: Adtives | J194: 11041 | K194: 46114 | L194: 1010100 | M194: VENDAS MERCADO INTERNO | N194: 161 | O194: VENDA PROD. INDUSTRIALIZADO - NFE | P194: AURORA MINERAÇÃO LTDA | Q194: =$R$1-F194 -> -33 | R194: =_xlfn.XLOOKUP(P194,'Painel Additive'!$B:$B,'Painel Additive'!$B:$B,0) -> AURORA MINERAÇÃO LTDA | S194: =F194-K194 -> 60
A195: 1462 | B195: AURORA MINERAÇÃO LTDA | C195: 02.964.101/0001-08 | D195: 38160.2 | E195: 1246270127 | F195: 46184 | H195: 1 | I195: Adtives | J195: 11041 | K195: 46114 | L195: 1010100 | M195: VENDAS MERCADO INTERNO | N195: 161 | O195: VENDA PROD. INDUSTRIALIZADO - NFE | P195: AURORA MINERAÇÃO LTDA | Q195: =$R$1-F195 -> -43 | R195: =_xlfn.XLOOKUP(P195,'Painel Additive'!$B:$B,'Painel Additive'!$B:$B,0) -> AURORA MINERAÇÃO LTDA | S195: =F195-K195 -> 70
A196: 1462 | B196: AURORA MINERAÇÃO LTDA | C196: 02.964.101/0001-08 | D196: 37491.5 | E196: 1246262009 | F196: 46125 | H196: 1 | I196: Adtives | J196: 10624 | K196: 46055 | L196: 1010100 | M196: VENDAS MERCADO INTERNO | N196: 161 | O196: VENDA PROD. INDUSTRIALIZADO - NFE | P196: AURORA MINERAÇÃO LTDA | Q196: =$R$1-F196 -> 16 | R196: =_xlfn.XLOOKUP(P196,'Painel Additive'!$B:$B,'Painel Additive'!$B:$B,0) -> AURORA MINERAÇÃO LTDA | S196: =F196-K196 -> 70
A197: 2011 | B197: FERTGROW S.A | C197: 14.267.717/0001-09 | D197: 105829.4 | E197: 1246271331 | F197: 46154 | H197: 1 | I197: Adtives | J197: 11121 | K197: 46126 | L197: 1010100 | M197: VENDAS MERCADO INTERNO | N197: 161 | O197: VENDA PROD. INDUSTRIALIZADO - NFE | P197: FERTGROW S.A | Q197: =$R$1-F197 -> -13 | R197: =_xlfn.XLOOKUP(P197,'Painel Additive'!$B:$B,'Painel Additive'!$B:$B,0) -> FERTGROW S.A | S197: =F197-K197 -> 28
A198: 2247 | B198: ADUBOS LEAO - LARANJEIRAS | C198: 27.360.944/0001-26 | D198: 12189 | E198: 1246272759 | F198: 46167 | H198: 1 | I198: Adtives | J198: 2896 | K198: 46139 | L198: 1010100 | M198: VENDAS MERCADO INTERNO | N198: 161 | O198: VENDA PROD. INDUSTRIALIZADO - NFE | P198: ADUBOS LEAO - LARANJEIRAS | Q198: =$R$1-F198 -> -26 | R198: =_xlfn.XLOOKUP(P198,'Painel Additive'!$B:$B,'Painel Additive'!$B:$B,0) -> ADUBOS LEAO - LARANJEIRAS | S198: =F198-K198 -> 28
A199: 2247 | B199: ADUBOS LEAO - LARANJEIRAS | C199: 27.360.944/0001-26 | D199: 12189 | E199: 1246272760 | F199: 46195 | H199: 1 | I199: Adtives | J199: 2896 | K199: 46139 | L199: 1010100 | M199: VENDAS MERCADO INTERNO | N199: 161 | O199: VENDA PROD. INDUSTRIALIZADO - NFE | P199: ADUBOS LEAO - LARANJEIRAS | Q199: =$R$1-F199 -> -54 | R199: =_xlfn.XLOOKUP(P199,'Painel Additive'!$B:$B,'Painel Additive'!$B:$B,0) -> ADUBOS LEAO - LARANJEIRAS | S199: =F199-K199 -> 56
...

Sheet Data International
D1: =SUBTOTAL(9,D3:D995) -> 6767486.9 | R1: 46141
A2: CODPARC | B2: NOMEPARC | C2: CNPJ | D2: Valor | E2: NUFIN | F2: DTVENC | G2: DHBAIXA | H2: AD_BU | I2: NOME_BU | J2: NUMNOTA | K2: DTENTSAI | L2: CODNAT | M2: DESCRNAT | N2: CODTIPOPER | O2: OPERACAO | P2: Grupo | Q2: Dias vencidos
A3: 3297 | B3: MACROSOURCE PERU S.R.L. | C3: ..- | D3: 49956.68 | E3: 1246271355 | F3: 46186 | H3: 1 | I3: Adtives | J3: 11123 | K3: 46126 | L3: 1010200 | M3: VENDAS MERCADO EXTERNO | N3: 40 | O3: VENDA - NFE (EXPORTAÇÃO) | P3: MACROSOURCE PERU S.R.L. | Q3: =$R$1-F3 -> -45 | R3: =_xlfn.XLOOKUP(P3,'Painel International'!$B:$B,'Painel International'!$B:$B,0) -> MACROSOURCE PERU S.R.L.
A4: 3426 | B4: C I ACEPALMA SA - COLOMBIA | C4: 00.000.000/0000-00 | D4: 250261.53 | E4: 1246272081 | F4: 46194 | H4: 1 | I4: Adtives | J4: 2886 | K4: 46134 | L4: 1010200 | M4: VENDAS MERCADO EXTERNO | N4: 40 | O4: VENDA - NFE (EXPORTAÇÃO) | P4: C I ACEPALMA SA - COLOMBIA | Q4: =$R$1-F4 -> -53 | R4: =_xlfn.XLOOKUP(P4,'Painel International'!$B:$B,'Painel International'!$B:$B,0) -> C I ACEPALMA SA - COLOMBIA
A5: 2680 | B5: FERMAGRI S.A - EQUADOR | C5: ..- | D5: 224812.61 | E5: 1246263810 | F5: 46144 | H5: 1 | I5: Adtives | J5: 2743 | K5: 46069 | L5: 1010200 | M5: VENDAS MERCADO EXTERNO | N5: 40 | O5: VENDA - NFE (EXPORTAÇÃO) | P5: FERMAGRI S.A - EQUADOR | Q5: =$R$1-F5 -> -3 | R5: =_xlfn.XLOOKUP(P5,'Painel International'!$B:$B,'Painel International'!$B:$B,0) -> FERMAGRI S.A - EQUADOR
A6: 2680 | B6: FERMAGRI S.A - EQUADOR | C6: ..- | D6: 175275.24 | E6: 1246272069 | F6: 46194 | H6: 1 | I6: Adtives | J6: 11191 | K6: 46134 | L6: 1010200 | M6: VENDAS MERCADO EXTERNO | N6: 40 | O6: VENDA - NFE (EXPORTAÇÃO) | P6: FERMAGRI S.A - EQUADOR | Q6: =$R$1-F6 -> -53 | R6: =_xlfn.XLOOKUP(P6,'Painel International'!$B:$B,'Painel International'!$B:$B,0) -> FERMAGRI S.A - EQUADOR
A7: 2925 | B7: COPEVAL - CHILE | C7: ..- | D7: 92361.18 | E7: 1246273169 | F7: 46172 | H7: 1 | I7: Adtives | J7: 11264 | K7: 46142 | L7: 1010200 | M7: VENDAS MERCADO EXTERNO | N7: 40 | O7: VENDA - NFE (EXPORTAÇÃO) | P7: COPEVAL - CHILE | Q7: =$R$1-F7 -> -31 | R7: =_xlfn.XLOOKUP(P7,'Painel International'!$B:$B,'Painel International'!$B:$B,0) -> COPEVAL - CHILE
A8: 2346 | B8: TEPEYAC - MÉXICO | C8: 11.091.524/0001-51 | D8: 103419.89 | E8: 1246265843 | F8: 46170 | H8: 1 | I8: Adtives | J8: 2789 | K8: 46080 | L8: 1010200 | M8: VENDAS MERCADO EXTERNO | N8: 40 | O8: VENDA - NFE (EXPORTAÇÃO) | P8: TEPEYAC - MÉXICO | Q8: =$R$1-F8 -> -29 | R8: =_xlfn.XLOOKUP(P8,'Painel International'!$B:$B,'Painel International'!$B:$B,0) -> TEPEYAC - MÉXICO
A9: 2651 | B9: AGROBROKERS - COLÔMBIA | C9: ..- | D9: 252226.12 | E9: 1246223341 | F9: 45935 | H9: 1 | I9: Adtives | J9: 8388 | K9: 45845 | L9: 1010200 | M9: VENDAS MERCADO EXTERNO | N9: 40 | O9: VENDA - NFE (EXPORTAÇÃO) | P9: AGROBROKERS - COLÔMBIA | Q9: =$R$1-F9 -> 206 | R9: =_xlfn.XLOOKUP(P9,'Painel International'!$B:$B,'Painel International'!$B:$B,0) -> AGROBROKERS - COLÔMBIA
A10: 2651 | B10: AGROBROKERS - COLÔMBIA | C10: ..- | D10: 197281.57 | E10: 1246213269 | F10: 45849 | H10: 1 | I10: Adtives | J10: 1965 | K10: 45789 | L10: 1010200 | M10: VENDAS MERCADO EXTERNO | N10: 40 | O10: VENDA - NFE (EXPORTAÇÃO) | P10: AGROBROKERS - COLÔMBIA | Q10: =$R$1-F10 -> 292 | R10: =_xlfn.XLOOKUP(P10,'Painel International'!$B:$B,'Painel International'!$B:$B,0) -> AGROBROKERS - COLÔMBIA
A11: 2652 | B11: FERTIMAX PARAGUAY | C11: ..- | D11: 157149.47 | E11: 1246271559 | F11: 46158 | H11: 1 | I11: Adtives | J11: 11137 | K11: 46128 | L11: 1010200 | M11: VENDAS MERCADO EXTERNO | N11: 40 | O11: VENDA - NFE (EXPORTAÇÃO) | P11: FERTIMAX PARAGUAY | Q11: =$R$1-F11 -> -17 | R11: =_xlfn.XLOOKUP(P11,'Painel International'!$B:$B,'Painel International'!$B:$B,0) -> FERTIMAX PARAGUAY
A12: 2287 | B12: BUNGE PARAGUAY S.A | C12: 99.999.999/9999-99 | D12: 150064.83 | E12: 1246273103 | F12: 46171 | H12: 1 | I12: Adtives | J12: 11261 | K12: 46141 | L12: 1010200 | M12: VENDAS MERCADO EXTERNO | N12: 40 | O12: VENDA - NFE (EXPORTAÇÃO) | P12: BUNGE PARAGUAY S.A | Q12: =$R$1-F12 -> -30 | R12: =_xlfn.XLOOKUP(P12,'Painel International'!$B:$B,'Painel International'!$B:$B,0) -> BUNGE PARAGUAY S.A
A13: 2655 | B13: EQUILIBRA PERU S.A | C13: ..- | D13: 40017.64 | E13: 1246268741 | F13: 46165 | H13: 1 | I13: Adtives | J13: 10964 | K13: 46105 | L13: 1010200 | M13: VENDAS MERCADO EXTERNO | N13: 40 | O13: VENDA - NFE (EXPORTAÇÃO) | P13: EQUILIBRA PERU S.A | Q13: =$R$1-F13 -> -24 | R13: =_xlfn.XLOOKUP(P13,'Painel International'!$B:$B,'Painel International'!$B:$B,0) -> EQUILIBRA PERU S.A
A14: 2656 | B14: ISUSA - URUGUAI | C14: ..- | D14: 131960.06 | E14: 1246271948 | F14: 46162 | H14: 1 | I14: Adtives | J14: 11185 | K14: 46132 | L14: 1010200 | M14: VENDAS MERCADO EXTERNO | N14: 40 | O14: VENDA - NFE (EXPORTAÇÃO) | P14: ISUSA - URUGUAI | Q14: =$R$1-F14 -> -21 | R14: =_xlfn.XLOOKUP(P14,'Painel International'!$B:$B,'Painel International'!$B:$B,0) -> ISUSA - URUGUAI
... A16: 6370 | B16: YTL S.A. - PARAGUAI | C16: 00.000.000/0000-00 | D16: 172806.77 | E16: 1246272162 | F16: 46164 | H16: 1 | I16: Adtives | J16: 11193 | K16: 46134 | L16: 1010200 | M16: VENDAS MERCADO EXTERNO | N16: 40 | O16: VENDA - NFE (EXPORTAÇÃO) | P16: YTL S.A. - PARAGUAI | Q16: =$R$1-F16 -> -23 | R16: =_xlfn.XLOOKUP(P16,'Painel International'!$B:$B,'Painel International'!$B:$B,0) -> YTL S.A. - PARAGUAI
A17: 9708 | B17: CARGILL ARGENTINA | C17: ..- | D17: 687688.91 | E17: 1246271322 | F17: 46186 | I17: Não encontrado | J17: 11122 | K17: 46126 | L17: 1010200 | M17: VENDAS MERCADO EXTERNO | N17: 40 | O17: VENDA - NFE (EXPORTAÇÃO) | P17: CARGILL ARGENTINA | Q17: =$R$1-F17 -> -45 | R17: =_xlfn.XLOOKUP(P17,'Painel International'!$B:$B,'Painel International'!$B:$B,0) -> CARGILL ARGENTINA
A18: 9295 | B18: TECNOMYL S.A. - PARAGUAY | C18: 99.999.999/9999-99 | D18: 130127.06 | E18: 1246270982 | F18: 46152 | H18: 1 | I18: Adtives | J18: 11090 | K18: 46122 | L18: 1010200 | M18: VENDAS MERCADO EXTERNO | N18: 40 | O18: VENDA - NFE (EXPORTAÇÃO) | P18: TECNOMYL S.A. - PARAGUAY | Q18: =$R$1-F18 -> -11 | R18: =_xlfn.XLOOKUP(P18,'Painel International'!$B:$B,'Painel International'!$B:$B,0) -> TECNOMYL S.A. - PARAGUAY
A19: 9295 | B19: TECNOMYL S.A. - PARAGUAY | C19: 99.999.999/9999-99 | D19: 132185.95 | E19: 1246270621 | F19: 46150 | H19: 1 | I19: Adtives | J19: 11071 | K19: 46120 | L19: 1010200 | M19: VENDAS MERCADO EXTERNO | N19: 40 | O19: VENDA - NFE (EXPORTAÇÃO) | P19: TECNOMYL S.A. - PARAGUAY | Q19: =$R$1-F19 -> -9 | R19: =_xlfn.XLOOKUP(P19,'Painel International'!$B:$B,'Painel International'!$B:$B,0) -> TECNOMYL S.A. - PARAGUAY
A20: 9355 | B20: NITROFERT SAS - COLOMBIA | C20: ..- | D20: 604265.82 | E20: 1246264749 | F20: 46177 | H20: 1 | I20: Adtives | J20: 2768 | K20: 46077 | L20: 1010200 | M20: VENDAS MERCADO EXTERNO | N20: 40 | O20: VENDA - NFE (EXPORTAÇÃO) | P20: NITROFERT SAS - COLOMBIA | Q20: =$R$1-F20 -> -36 | R20: =_xlfn.XLOOKUP(P20,'Painel International'!$B:$B,'Painel International'!$B:$B,0) -> NITROFERT SAS - COLOMBIA
A21: 9355 | B21: NITROFERT SAS - COLOMBIA | C21: ..- | D21: 1191855.3 | E21: 1246265046 | F21: 46180 | H21: 1 | I21: Adtives | J21: 10762 | K21: 46078 | L21: 1010200 | M21: VENDAS MERCADO EXTERNO | N21: 40 | O21: VENDA - NFE (EXPORTAÇÃO) | P21: NITROFERT SAS - COLOMBIA | Q21: =$R$1-F21 -> -39 | R21: =_xlfn.XLOOKUP(P21,'Painel International'!$B:$B,'Painel International'!$B:$B,0) -> NITROFERT SAS - COLOMBIA
A22: 9355 | B22: NITROFERT SAS - COLOMBIA | C22: ..- | D22: 292178.84 | E22: 1246264769 | F22: 46180 | H22: 1 | I22: Adtives | J22: 10753 | K22: 46077 | L22: 1010200 | M22: VENDAS MERCADO EXTERNO | N22: 40 | O22: VENDA - NFE (EXPORTAÇÃO) | P22: NITROFERT SAS - COLOMBIA | Q22: =$R$1-F22 -> -39 | R22: =_xlfn.XLOOKUP(P22,'Painel International'!$B:$B,'Painel International'!$B:$B,0) -> NITROFERT SAS - COLOMBIA
A23: 9355 | B23: NITROFERT SAS - COLOMBIA | C23: ..- | D23: 1191855.3 | E23: 1246265200 | F23: 46177 | H23: 1 | I23: Adtives | J23: 2778 | K23: 46078 | L23: 1010200 | M23: VENDAS MERCADO EXTERNO | N23: 40 | O23: VENDA - NFE (EXPORTAÇÃO) | P23: NITROFERT SAS - COLOMBIA | Q23: =$R$1-F23 -> -36 | R23: =_xlfn.XLOOKUP(P23,'Painel International'!$B:$B,'Painel International'!$B:$B,0) -> NITROFERT SAS - COLOMBIA
A24: 11768 | B24: CERES PERU S.A | C24: ..- | D24: 86689.1 | E24: 1246264534 | F24: 46158 | H24: 1 | I24: Adtives | J24: 10744 | K24: 46076 | L24: 1010200 | M24: VENDAS MERCADO EXTERNO | N24: 40 | O24: VENDA - NFE (EXPORTAÇÃO) | P24: CERES PERU S.A | Q24: =$R$1-F24 -> -17 | R24: =_xlfn.XLOOKUP(P24,'Painel International'!$B:$B,'Painel International'!$B:$B,0) -> CERES PERU S.A
A25: 11770 | B25: FERTIBAL - EQUADOR | C25: ..- | D25: 14548.35 | E25: 1246263524 | F25: 46039 | H25: 1 | I25: Adtives | J25: 9853 | K25: 45959 | L25: 1010200 | M25: VENDAS MERCADO EXTERNO | N25: 40 | O25: VENDA - NFE (EXPORTAÇÃO) | P25: FERTIBAL - EQUADOR | Q25: =$R$1-F25 -> 102 | R25: =_xlfn.XLOOKUP(P25,'Painel International'!$B:$B,'Painel International'!$B:$B,0) -> FERTIBAL - EQUADOR
A26: 11580 | B26: AGRO MIL AGROS SAS - COLOMBIA | C26: ..- | D26: 76480.23 | E26: 1246268734 | F26: 46440 | H26: 1 | I26: Adtives | J26: 2837 | K26: 46105 | L26: 1010200 | M26: VENDAS MERCADO EXTERNO | N26: 40 | O26: VENDA - NFE (EXPORTAÇÃO) | P26: AGRO MIL AGROS SAS - COLOMBIA | Q26: =$R$1-F26 -> -299 | R26: =_xlfn.XLOOKUP(P26,'Painel International'!$B:$B,'Painel International'!$B:$B,0) -> AGRO MIL AGROS SAS - COLOMBIA
A27: 13330 | B27: ORGANITEC - PARAGUAY | C27: 800.909.976- | D27: 853.24 | E27: 1246272264 | F27: 46148 | I27: Não encontrado | J27: 11057 | K27: 46118 | L27: 1010200 | M27: VENDAS MERCADO EXTERNO | N27: 40 | O27: VENDA - NFE (EXPORTAÇÃO) | P27: ORGANITEC - PARAGUAY | Q27: =$R$1-F27 -> -7 | R27: =_xlfn.XLOOKUP(P27,'Painel International'!$B:$B,'Painel International'!$B:$B,0) -> ORGANITEC - PARAGUAY
A28: 13330 | B28: ORGANITEC - PARAGUAY | C28: 800.909.976- | D28: 527.28 | E28: 1246238356 | F28: 45927 | I28: Não encontrado | J28: 9092 | K28: 45897 | L28: 1010200 | M28: VENDAS MERCADO EXTERNO | N28: 40 | O28: VENDA - NFE (EXPORTAÇÃO) | P28: ORGANITEC - PARAGUAY | Q28: =$R$1-F28 -> 214 | R28: =_xlfn.XLOOKUP(P28,'Painel International'!$B:$B,'Painel International'!$B:$B,0) -> ORGANITEC - PARAGUAY
A29: 15508 | B29: SOMAX - PARAGUAI | C29: 800.553.179- | D29: 137716.91 | E29: 1246270312 | F29: 46148 | H29: 1 | I29: Adtives | J29: 11050 | K29: 46118 | L29: 1010200 | M29: VENDAS MERCADO EXTERNO | N29: 40 | O29: VENDA - NFE (EXPORTAÇÃO) | P29: SOMAX - PARAGUAI | Q29: =$R$1-F29 -> -7 | R29: =_xlfn.XLOOKUP(P29,'Painel International'!$B:$B,'Painel International'!$B:$B,0) -> SOMAX - PARAGUAI
A30: 15543 | B30: GOTLAND EQUADOR (SOLINAG) | C30: 19.512.950/9001- | D30: 45718.46 | E30: 1246264533 | F30: 46181 | I30: Não encontrado | J30: 10745 | K30: 46076 | L30: 1010200 | M30: VENDAS MERCADO EXTERNO | N30: 40 | O30: VENDA - NFE (EXPORTAÇÃO) | P30: GOTLAND EQUADOR (SOLINAG) | Q30: =$R$1-F30 -> -40 | R30: =_xlfn.XLOOKUP(P30,'Painel International'!$B:$B,'Painel International'!$B:$B,0) -> GOTLAND EQUADOR (SOLINAG)
Q31: =$R$1-F31 -> 46141 | R31: =_xlfn.XLOOKUP(P31,'Painel International'!$B:$B,'Painel International'!$B:$B,0) -> 0
Q32: =$R$1-F32 -> 46141 | R32: =_xlfn.XLOOKUP(P32,'Painel International'!$B:$B,'Painel International'!$B:$B,0) -> 0
Q33: =$R$1-F33 -> 46141 | R33: =_xlfn.XLOOKUP(P33,'Painel International'!$B:$B,'Painel International'!$B:$B,0) -> 0
Q34: =$R$1-F34 -> 46141 | R34: =_xlfn.XLOOKUP(P34,'Painel International'!$B:$B,'Painel International'!$B:$B,0) -> 0
Q35: =$R$1-F35 -> 46141 | R35: =_xlfn.XLOOKUP(P35,'Painel International'!$B:$B,'Painel International'!$B:$B,0) -> 0
Q36: =$R$1-F36 -> 46141 | R36: =_xlfn.XLOOKUP(P36,'Painel International'!$B:$B,'Painel International'!$B:$B,0) -> 0
Q37: =$R$1-F37 -> 46141 | R37: =_xlfn.XLOOKUP(P37,'Painel International'!$B:$B,'Painel International'!$B:$B,0) -> 0
Q38: =$R$1-F38 -> 46141 | R38: =_xlfn.XLOOKUP(P38,'Painel International'!$B:$B,'Painel International'!$B:$B,0) -> 0
Q39: =$R$1-F39 -> 46141 | R39: =_xlfn.XLOOKUP(P39,'Painel International'!$B:$B,'Painel International'!$B:$B,0) -> 0
Q40: =$R$1-F40 -> 46141 | R40: =_xlfn.XLOOKUP(P40,'Painel International'!$B:$B,'Painel International'!$B:$B,0) -> 0
Q41: =$R$1-F41 -> 46141 | R41: =_xlfn.XLOOKUP(P41,'Painel International'!$B:$B,'Painel International'!$B:$B,0) -> 0

Sheet Data Fertilizers
D1: =SUBTOTAL(9,D3:D995) -> 26625653 | R1: 46141
A2: CODPARC | B2: NOMEPARC | C2: CNPJ | D2: Valor | E2: NUFIN | F2: DTVENC | G2: DHBAIXA | H2: AD_BU | I2: NOME_BU | J2: NUMNOTA | K2: DTENTSAI | L2: CODNAT | M2: DESCRNAT | N2: CODTIPOPER | O2: OPERACAO | P2: GRUPO | Q2: Dias vencidos
A3: 9824 | B3: TRIANGULO AGRO CONSULTORIA C/PRESCISAO | C3: 11.827.200/0001-39 | D3: 69971.2 | E3: 1246154720 | F3: 45738 | H3: 2 | I3: Fertilizers | J3: 4113 | K3: 45475 | L3: 1010100 | M3: VENDAS MERCADO INTERNO | N3: 161 | O3: VENDA PROD. INDUSTRIALIZADO - NFE | P3: GRUPO TRIANGULO AGRO | Q3: =$R$1-F3 -> 403 | R3: =_xlfn.XLOOKUP(P3,'Painel Fertilizers'!$B:$B,'Painel Fertilizers'!$B:$B,0) -> GRUPO TRIANGULO AGRO
A4: 9824 | B4: TRIANGULO AGRO CONSULTORIA C/PRESCISAO | C4: 11.827.200/0001-39 | D4: 60656 | E4: 1246154724 | F4: 45738 | H4: 2 | I4: Fertilizers | J4: 4114 | K4: 45475 | L4: 1010100 | M4: VENDAS MERCADO INTERNO | N4: 161 | O4: VENDA PROD. INDUSTRIALIZADO - NFE | P4: GRUPO TRIANGULO AGRO | Q4: =$R$1-F4 -> 403 | R4: =_xlfn.XLOOKUP(P4,'Painel Fertilizers'!$B:$B,'Painel Fertilizers'!$B:$B,0) -> GRUPO TRIANGULO AGRO
A5: 10371 | B5: TRIANGULO AGRO – POMPEU | C5: 11.827.200/0004-81 | D5: 56674.77 | E5: 1246161059 | F5: 45736 | H5: 2 | I5: Fertilizers | J5: 4516 | K5: 45502 | L5: 1010100 | M5: VENDAS MERCADO INTERNO | N5: 161 | O5: VENDA PROD. INDUSTRIALIZADO - NFE | P5: GRUPO TRIANGULO AGRO | Q5: =$R$1-F5 -> 405 | R5: =_xlfn.XLOOKUP(P5,'Painel Fertilizers'!$B:$B,'Painel Fertilizers'!$B:$B,0) -> GRUPO TRIANGULO AGRO
A6: 10371 | B6: TRIANGULO AGRO – POMPEU | C6: 11.827.200/0004-81 | D6: 50007.15 | E6: 1246161057 | F6: 45736 | H6: 2 | I6: Fertilizers | J6: 4515 | K6: 45502 | L6: 1010100 | M6: VENDAS MERCADO INTERNO | N6: 161 | O6: VENDA PROD. INDUSTRIALIZADO - NFE | P6: GRUPO TRIANGULO AGRO | Q6: =$R$1-F6 -> 405 | R6: =_xlfn.XLOOKUP(P6,'Painel Fertilizers'!$B:$B,'Painel Fertilizers'!$B:$B,0) -> GRUPO TRIANGULO AGRO
A7: 11207 | B7: S M AGRO | C7: 08.685.699/0001-82 | D7: 153825.49 | E7: 1246067872 | F7: 45412 | H7: 2 | I7: Fertilizers | J7: 20696 | K7: 44973 | L7: 1010100 | M7: VENDAS MERCADO INTERNO | N7: 161 | O7: VENDA PROD. INDUSTRIALIZADO - NFE | P7: GRUPO LEANDRO SARTI | Q7: =$R$1-F7 -> 729 | R7: =_xlfn.XLOOKUP(P7,'Painel Fertilizers'!$B:$B,'Painel Fertilizers'!$B:$B,0) -> GRUPO LEANDRO SARTI
A8: 11207 | B8: S M AGRO | C8: 08.685.699/0001-82 | D8: 91167.15 | E8: 1246075550 | F8: 45412 | H8: 2 | I8: Fertilizers | J8: 21053 | K8: 45022 | L8: 1010100 | M8: VENDAS MERCADO INTERNO | N8: 161 | O8: VENDA PROD. INDUSTRIALIZADO - NFE | P8: GRUPO LEANDRO SARTI | Q8: =$R$1-F8 -> 729 | R8: =_xlfn.XLOOKUP(P8,'Painel Fertilizers'!$B:$B,'Painel Fertilizers'!$B:$B,0) -> GRUPO LEANDRO SARTI
A9: 11207 | B9: S M AGRO | C9: 08.685.699/0001-82 | D9: 43771.16 | E9: 1246094423 | F9: 45423 | H9: 2 | I9: Fertilizers | J9: 356 | K9: 45133 | L9: 1010100 | M9: VENDAS MERCADO INTERNO | N9: 161 | O9: VENDA PROD. INDUSTRIALIZADO - NFE | P9: GRUPO LEANDRO SARTI | Q9: =$R$1-F9 -> 718 | R9: =_xlfn.XLOOKUP(P9,'Painel Fertilizers'!$B:$B,'Painel Fertilizers'!$B:$B,0) -> GRUPO LEANDRO SARTI
A10: 11207 | B10: S M AGRO | C10: 08.685.699/0001-82 | D10: 44760.26 | E10: 1246092027 | F10: 45504 | H10: 2 | I10: Fertilizers | J10: 138 | K10: 45119 | L10: 1010100 | M10: VENDAS MERCADO INTERNO | N10: 161 | O10: VENDA PROD. INDUSTRIALIZADO - NFE | P10: GRUPO LEANDRO SARTI | Q10: =$R$1-F10 -> 637 | R10: =_xlfn.XLOOKUP(P10,'Painel Fertilizers'!$B:$B,'Painel Fertilizers'!$B:$B,0) -> GRUPO LEANDRO SARTI
A11: 11207 | B11: S M AGRO | C11: 08.685.699/0001-82 | D11: 43771.16 | E11: 1246093362 | F11: 45417 | H11: 2 | I11: Fertilizers | J11: 253 | K11: 45127 | L11: 1010100 | M11: VENDAS MERCADO INTERNO | N11: 161 | O11: VENDA PROD. INDUSTRIALIZADO - NFE | P11: GRUPO LEANDRO SARTI | Q11: =$R$1-F11 -> 724 | R11: =_xlfn.XLOOKUP(P11,'Painel Fertilizers'!$B:$B,'Painel Fertilizers'!$B:$B,0) -> GRUPO LEANDRO SARTI
A12: 11207 | B12: S M AGRO | C12: 08.685.699/0001-82 | D12: 47925.4 | E12: 1246094864 | F12: 45544 | H12: 2 | I12: Fertilizers | J12: 407 | K12: 45135 | L12: 1010100 | M12: VENDAS MERCADO INTERNO | N12: 161 | O12: VENDA PROD. INDUSTRIALIZADO - NFE | P12: GRUPO LEANDRO SARTI | Q12: =$R$1-F12 -> 597 | R12: =_xlfn.XLOOKUP(P12,'Painel Fertilizers'!$B:$B,'Painel Fertilizers'!$B:$B,0) -> GRUPO LEANDRO SARTI
A13: 11207 | B13: S M AGRO | C13: 08.685.699/0001-82 | D13: 106301.38 | E13: 1246094863 | F13: 45425 | H13: 2 | I13: Fertilizers | J13: 406 | K13: 45135 | L13: 1010100 | M13: VENDAS MERCADO INTERNO | N13: 161 | O13: VENDA PROD. INDUSTRIALIZADO - NFE | P13: GRUPO LEANDRO SARTI | Q13: =$R$1-F13 -> 716 | R13: =_xlfn.XLOOKUP(P13,'Painel Fertilizers'!$B:$B,'Painel Fertilizers'!$B:$B,0) -> GRUPO LEANDRO SARTI
A14: 11207 | B14: S M AGRO | C14: 08.685.699/0001-82 | D14: 150072.54 | E14: 1246095554 | F14: 45415 | H14: 2 | I14: Fertilizers | J14: 485 | K14: 45140 | L14: 1010100 | M14: VENDAS MERCADO INTERNO | N14: 161 | O14: VENDA PROD. INDUSTRIALIZADO - NFE | P14: GRUPO LEANDRO SARTI | Q14: =$R$1-F14 -> 726 | R14: =_xlfn.XLOOKUP(P14,'Painel Fertilizers'!$B:$B,'Painel Fertilizers'!$B:$B,0) -> GRUPO LEANDRO SARTI
... A271: 16107 | B271: CONNTACTA AGRONEGOCIOS | C271: 54.764.341/0001-62 | D271: 2217.78 | E271: 1246235696 | F271: 46265 | H271: 2 | I271: Fertilizers | J271: 9248 | K271: 45908 | L271: 1010100 | M271: VENDAS MERCADO INTERNO | N271: 161 | O271: VENDA PROD. INDUSTRIALIZADO - NFE | P271: CONNTACTA AGRONEGOCIOS | Q271: =$R$1-F271 -> -124 | R271: =_xlfn.XLOOKUP(P271,'Painel Fertilizers'!$B:$B,'Painel Fertilizers'!$B:$B,0) -> CONNTACTA AGRONEGOCIOS
Q272: =$R$1-F272 -> 46141 | R272: =_xlfn.XLOOKUP(P272,'Painel Fertilizers'!$B:$B,'Painel Fertilizers'!$B:$B,0) -> 0
Q273: =$R$1-F273 -> 46141 | R273: =_xlfn.XLOOKUP(P273,'Painel Fertilizers'!$B:$B,'Painel Fertilizers'!$B:$B,0) -> 0
Q274: =$R$1-F274 -> 46141 | R274: =_xlfn.XLOOKUP(P274,'Painel Fertilizers'!$B:$B,'Painel Fertilizers'!$B:$B,0) -> 0
Q275: =$R$1-F275 -> 46141 | R275: =_xlfn.XLOOKUP(P275,'Painel Fertilizers'!$B:$B,'Painel Fertilizers'!$B:$B,0) -> 0
Q276: =$R$1-F276 -> 46141 | R276: =_xlfn.XLOOKUP(P276,'Painel Fertilizers'!$B:$B,'Painel Fertilizers'!$B:$B,0) -> 0
Q277: =$R$1-F277 -> 46141 | R277: =_xlfn.XLOOKUP(P277,'Painel Fertilizers'!$B:$B,'Painel Fertilizers'!$B:$B,0) -> 0
Q278: =$R$1-F278 -> 46141 | R278: =_xlfn.XLOOKUP(P278,'Painel Fertilizers'!$B:$B,'Painel Fertilizers'!$B:$B,0) -> 0
Q279: =$R$1-F279 -> 46141 | R279: =_xlfn.XLOOKUP(P279,'Painel Fertilizers'!$B:$B,'Painel Fertilizers'!$B:$B,0) -> 0
Q280: =$R$1-F280 -> 46141 | R280: =_xlfn.XLOOKUP(P280,'Painel Fertilizers'!$B:$B,'Painel Fertilizers'!$B:$B,0) -> 0
Q281: =$R$1-F281 -> 46141 | R281: =_xlfn.XLOOKUP(P281,'Painel Fertilizers'!$B:$B,'Painel Fertilizers'!$B:$B,0) -> 0
Q282: =$R$1-F282 -> 46141 | R282: =_xlfn.XLOOKUP(P282,'Painel Fertilizers'!$B:$B,'Painel Fertilizers'!$B:$B,0) -> 0
Q283: =$R$1-F283 -> 46141 | R283: =_xlfn.XLOOKUP(P283,'Painel Fertilizers'!$B:$B,'Painel Fertilizers'!$B:$B,0) -> 0
... Q392: =$R$1-F392 -> 46141 | R392: =_xlfn.XLOOKUP(P392,'Painel Fertilizers'!$B:$B,'Painel Fertilizers'!$B:$B,0) -> 0

Sheet Clientes Consolidado.
C1: 46142 | H1: =SUBTOTAL(9,H4:H1048576) -> 59371743 | I1: =SUBTOTAL(9,I4:I1048576) -> 537781.14 | J1: =SUBTOTAL(9,J4:J1048576) -> 49440 | K1: =SUBTOTAL(9,K4:K1048576) -> 0 | L1: =SUBTOTAL(9,L4:L1048576) -> 14548.35 | M1: =SUBTOTAL(9,M4:M1048576) -> 0 | N1: =SUBTOTAL(9,N4:N1048576) -> 912819.17 | O1: =SUBTOTAL(9,O4:O1048576) -> 21875863 | ... Y1: =SUBTOTAL(9,Y4:Y1048576) -> 11119210 | AB1: =SUBTOTAL(9,AB4:AB1048576) -> 88842500 | AH1: =SUBTOTAL(9,AH4:AH1048050) -> 30675950 | AJ1: =P1/H1 -> 0.39396607
I2: Aging Overdue | R2: Aging Not Due | AJ2: Treasury Risk Status
A3: x | B3: BU | C3: CUSTOMER | D3: RATING | F3: Approved Credit | G3: Credit Balance | H3: Total AR | I3: 1-30 Days | J3: 31-60 Days | K3: 61-90 Days | L3: 91-120 Days | M3: 121-180 Days | N3: 181-360 Days | O3: Above 360 Days | P3: Overdue | Q3: Not Due | R3: 1-30 Days | S3: 31-60 Days | T3: 61-90 Days | U3: 91-120 Days | V3: 121-180 Days | W3: 181-360 Days | X3: Above 360 Days | Y3: Bad debt provision | Z3: x | AA3: x | AB3: Credit Insurance | AC3: Guarantee Value | AD3: Type | AE3: Due Date | AF3: Tenor | AG3: x | AH3: Open Exposure | AI3: x | AJ3: Probable | AK3: Possible | AL3: Rare
B4: =_xlfn.XLOOKUP(C4,Planilha3!A:A,Planilha3!B:B) -> Fertilizer / Litigation | C4: CENTRAL DO ADUBO COM E REPRESENTACAO LTD | D4: 0 | F4: 0 | G4: -7560727.8 | H4: 7560727.8 | I4: 0 | J4: 0 | K4: 0 | L4: 0 | M4: 0 | N4: 0 | O4: 7560727.8 | P4: 7560727.8 | Q4: 0 | R4: 0 | S4: 0 | T4: 0 | U4: 0 | V4: 0 | W4: 0 | X4: 0 | Y4: 0 | AB4: 0 | AH4: =MAX(H4-AB4,0) -> 7560727.8
B5: =_xlfn.XLOOKUP(C5,Planilha3!A:A,Planilha3!B:B) -> Additive | C5: GRUPO MOSAIC FERTILIZANTES P K LTDA | D5: B | F5: 10000000 | G5: 3234990.1 | H5: 6765009.9 | I5: 0 | J5: 0 | K5: 0 | L5: 0 | M5: 0 | N5: 0 | O5: 0 | P5: 0 | Q5: 6765009.9 | R5: 1136498.7 | S5: 3096134.7 | T5: 2532376.5 | U5: 0 | V5: 0 | W5: 0 | X5: 0 | Y5: 16500 | AB5: 10000000 | AH5: =MAX(H5-AB5,0) -> 0
B6: =_xlfn.XLOOKUP(C6,Planilha3!A:A,Planilha3!B:B) -> Additive | C6: GRUPO YARA | D6: B | F6: 6000000 | G6: 1910281.5 | H6: 4089718.5 | I6: 0 | J6: 0 | K6: 0 | L6: 0 | M6: 0 | N6: 0 | O6: 5626.32 | P6: 5626.32 | Q6: 4084092.2 | R6: 2439848.4 | S6: 1644243.8 | T6: 0 | U6: 0 | V6: 0 | W6: 0 | X6: 0 | Y6: 63226.32 | AB6: 6000000 | AH6: =MAX(H6-AB6,0) -> 0
B7: =_xlfn.XLOOKUP(C7,Planilha3!A:A,Planilha3!B:B) -> Additive | C7: GRUPO UNIFERTIL | D7: B | F7: 4500000 | G7: 743391.1 | H7: 3756608.9 | I7: 0 | J7: 0 | K7: 0 | L7: 0 | M7: 0 | N7: 0 | O7: 0 | P7: 0 | Q7: 3756608.9 | R7: 3756608.9 | S7: 0 | T7: 0 | U7: 0 | V7: 0 | W7: 0 | X7: 0 | Y7: 0 | AB7: 4500000 | AH7: =MAX(H7-AB7,0) -> 0
B8: =_xlfn.XLOOKUP(C8,Planilha3!A:A,Planilha3!B:B) -> Additive Intl. | C8: NITROFERT SAS - COLOMBIA | D8: 0 | F8: 0 | G8: -3280155.2 | H8: 3280155.2 | I8: 0 | J8: 0 | K8: 0 | L8: 0 | M8: 0 | N8: 0 | O8: 0 | P8: 0 | Q8: 3280155.2 | R8: 0 | S8: 3280155.2 | T8: 0 | U8: 0 | V8: 0 | W8: 0 | X8: 0 | Y8: 0 | AB8: 0 | AH8: =MAX(H8-AB8,0) -> 3280155.2
B9: =_xlfn.XLOOKUP(C9,Planilha3!A:A,Planilha3!B:B) -> Fertilizer / Litigation | C9: GRUPO LEANDRO SARTI | D9: 0 | F9: 0 | G9: -3088531.1 | H9: 3088531.1 | I9: 0 | J9: 0 | K9: 0 | L9: 0 | M9: 0 | N9: 0 | O9: 3088531.1 | P9: 3088531.1 | Q9: 0 | R9: 0 | S9: 0 | T9: 0 | U9: 0 | V9: 0 | W9: 0 | X9: 0 | Y9: 3088531.1 | AB9: 0 | AH9: =MAX(H9-AB9,0) -> 3088531.1
B10: =_xlfn.XLOOKUP(C10,Planilha3!A:A,Planilha3!B:B) -> Fertilizer / Litigation | C10: AGRO BERALDO | D10: 0 | F10: 0 | G10: -3044850.9 | H10: 3044850.9 | I10: 0 | J10: 0 | K10: 0 | L10: 0 | M10: 0 | N10: 0 | O10: 3044850.9 | P10: 3044850.9 | Q10: 0 | R10: 0 | S10: 0 | T10: 0 | U10: 0 | V10: 0 | W10: 0 | X10: 0 | Y10: 3044850.9 | AB10: 0 | AH10: =MAX(H10-AB10,0) -> 3044850.9
B11: =_xlfn.XLOOKUP(C11,Planilha3!A:A,Planilha3!B:B) -> Additive | C11: GRUPO MOSAIC FERTILIZANTES DO BRASIL | D11: 0 | F11: 20000000 | G11: 17021566 | H11: 2978434.3 | I11: 0 | J11: 0 | K11: 0 | L11: 0 | M11: 0 | N11: 64.2 | O11: 16754.72 | P11: 16818.92 | Q11: 2961615.4 | R11: 1468196.9 | S11: 550787.3 | T11: 761400.2 | U11: 181231 | V11: 0 | W11: 0 | X11: 0 | Y11: 84763.766 | AB11: 15000000 | AH11: =MAX(H11-AB11,0) -> 0
B12: =_xlfn.XLOOKUP(C12,Planilha3!A:A,Planilha3!B:B) -> Fertilizer / Litigation | C12: TERRA FERTIL - MACHADO | D12: 0 | F12: 0 | G12: -2492842.1 | H12: 2492842.1 | I12: 0 | J12: 0 | K12: 0 | L12: 0 | M12: 0 | N12: 0 | O12: 2492842.1 | P12: 2492842.1 | Q12: 0 | R12: 0 | S12: 0 | T12: 0 | U12: 0 | V12: 0 | W12: 0 | X12: 0 | Y12: 0 | AB12: 0 | AH12: =MAX(H12-AB12,0) -> 2492842.1
B13: =_xlfn.XLOOKUP(C13,Planilha3!A:A,Planilha3!B:B) -> Fertilizer / Litigation | C13: MOGIANA TECNO AGRO | D13: 0 | F13: 0 | G13: -1863200.9 | H13: 1863200.9 | I13: 0 | J13: 0 | K13: 0 | L13: 0 | M13: 0 | N13: 0 | O13: 1863200.9 | P13: 1863200.9 | Q13: 0 | R13: 0 | S13: 0 | T13: 0 | U13: 0 | V13: 0 | W13: 0 | X13: 0 | Y13: 1863200.9 | AB13: 0 | AH13: =MAX(H13-AB13,0) -> 1863200.9
B14: =_xlfn.XLOOKUP(C14,Planilha3!A:A,Planilha3!B:B) -> Fertilizer / Litigation | C14: CASA DAS SEMENTES | D14: 0 | F14: 0 | G14: -1702848.7 | H14: 1702848.7 | I14: 0 | J14: 0 | K14: 0 | L14: 0 | M14: 0 | N14: 0 | O14: 1702848.7 | P14: 1702848.7 | Q14: 0 | R14: 0 | S14: 0 | T14: 0 | U14: 0 | V14: 0 | W14: 0 | X14: 0 | Y14: 1702848.7 | AB14: 0 | AH14: =MAX(H14-AB14,0) -> 1702848.7
B15: =_xlfn.XLOOKUP(C15,Planilha3!A:A,Planilha3!B:B) -> Fertilizer | C15: AGROVIVA | D15: B | F15: 1800000 | G15: 599809.58 | H15: 1200190.4 | I15: 0 | J15: 0 | K15: 0 | L15: 0 | M15: 0 | N15: 0 | O15: 0 | P15: 0 | Q15: 1200190.4 | R15: 274733.36 | S15: 0 | T15: 0 | U15: 0 | V15: 925457.06 | W15: 0 | X15: 0 | Y15: 0 | AB15: 500000 | AH15: =MAX(H15-AB15,0) -> 700190.42
B16: =_xlfn.XLOOKUP(C16,Planilha3!A:A,Planilha3!B:B) -> Fertilizer / Litigation | C16: FAZENDA ARCOS SÃO JOÃO | D16: 0 | F16: 0 | G16: -988506.24 | H16: 988506.24 | I16: 0 | J16: 0 | K16: 0 | L16: 0 | M16: 0 | N16: 462720 | O16: 525786.24 | P16: 988506.24 | Q16: 0 | R16: 0 | S16: 0 | T16: 0 | U16: 0 | V16: 0 | W16: 0 | X16: 0 | Y16: 539667.84 | AB16: 0 | AH16: =MAX(H16-AB16,0) -> 988506.24
B17: =_xlfn.XLOOKUP(C17,Planilha3!A:A,Planilha3!B:B) -> Fertilizer / Litigation | C17: CBM FERTILIZANTES | D17: 0 | F17: 0 | G17: -876011.75 | H17: 876011.75 | I17: 0 | J17: 0 | K17: 0 | L17: 0 | M17: 0 | N17: 0 | O17: 876011.75 | P17: 876011.75 | Q17: 0 | R17: 0 | S17: 0 | T17: 0 | U17: 0 | V17: 0 | W17: 0 | X17: 0 | Y17: 0 | AB17: 0 | AH17: =MAX(H17-AB17,0) -> 876011.75
B18: =_xlfn.XLOOKUP(C18,Planilha3!A:A,Planilha3!B:B) -> Additive | C18: EUROCHEM SERRA DO SALITRE | D18: 0 | F18: 2500000 | G18: 1706188.3 | H18: 793811.7 | I18: 315971.7 | J18: 0 | K18: 0 | L18: 0 | M18: 0 | N18: 0 | O18: 0 | P18: 315971.7 | Q18: 477840 | R18: 477840 | S18: 0 | T18: 0 | U18: 0 | V18: 0 | W18: 0 | X18: 0 | Y18: 0 | AB18: 0 | AH18: =MAX(H18-AB18,0) -> 793811.7
B19: =_xlfn.XLOOKUP(C19,Planilha3!A:A,Planilha3!B:B) -> Fertilizer | C19: CONNTACTA AGRONEGOCIOS | D19: 0 | E19: 180 | F19: 0 | G19: -739540.06 | H19: 739540.06 | I19: 0 | J19: 0 | K19: 0 | L19: 0 | M19: 0 | N19: 0 | O19: 0 | P19: 0 | Q19: 739540.06 | R19: 0 | S19: 0 | T19: 0 | U19: 0 | V19: 739540.06 | W19: 0 | X19: 0 | Y19: 0 | AB19: 0 | AH19: =MAX(H19-AB19,0) -> 739540.06
B20: =_xlfn.XLOOKUP(C20,Planilha3!A:A,Planilha3!B:B) -> Fertilizer | C20: ADUFÉRTIL - CAMPEVO | D20: B | E20: 180 | F20: 3000000 | G20: 2265046.5 | H20: 734953.47 | I20: 0 | J20: 0 | K20: 0 | L20: 0 | M20: 0 | N20: 0 | O20: 0 | P20: 0 | Q20: 734953.47 | R20: 0 | S20: 662365.68 | T20: 72587.79 | U20: 0 | V20: 0 | W20: 0 | X20: 0 | Y20: 0 | AB20: 3000000 | AH20: =MAX(H20-AB20,0) -> 0
B21: =_xlfn.XLOOKUP(C21,Planilha3!A:A,Planilha3!B:B) -> Additive | C21: STRATOS/MOSAIC - ROSARIO DO CATETE | D21: A | F21: 1500000 | G21: 792448.4 | H21: 707551.6 | I21: 0 | J21: 0 | K21: 0 | L21: 0 | M21: 0 | N21: 0 | O21: 0 | P21: 0 | Q21: 707551.6 | R21: 70705.6 | S21: 141600 | T21: 495246 | U21: 0 | V21: 0 | W21: 0 | X21: 0 | Y21: 1800 | AB21: 1500000 | AH21: =MAX(H21-AB21,0) -> 0
B22: =_xlfn.XLOOKUP(C22,Planilha3!A:A,Planilha3!B:B) -> Additive Intl. | C22: CARGILL ARGENTINA | D22: A | F22: 1100000 | G22: 412311.09 | H22: 687688.91 | I22: 0 | J22: 0 | K22: 0 | L22: 0 | M22: 0 | N22: 0 | O22: 0 | P22: 0 | Q22: 687688.91 | R22: 0 | S22: 687688.91 | T22: 0 | U22: 0 | V22: 0 | W22: 0 | X22: 0 | Y22: 0 | AB22: 1100000 | AH22: =MAX(H22-AB22,0) -> 0
B23: =_xlfn.XLOOKUP(C23,Planilha3!A:A,Planilha3!B:B) -> Additive | C23: FECOAGRO FEDERACAO DAS COOPERATIVAS | D23: B | F23: 3000000 | G23: 2345464.3 | H23: 654535.73 | I23: 0 | J23: 0 | K23: 0 | L23: 0 | M23: 0 | N23: 0 | O23: 0 | P23: 0 | Q23: 654535.73 | R23: 654535.73 | S23: 0 | T23: 0 | U23: 0 | V23: 0 | W23: 0 | X23: 0 | Y23: 0 | AB23: 3000000 | AH23: =MAX(H23-AB23,0) -> 0
B24: =_xlfn.XLOOKUP(C24,Planilha3!A:A,Planilha3!B:B) -> Additive | C24: GRUPO CIBRA | D24: 0 | F24: 6900000 | G24: 6245984.3 | H24: 654015.7 | I24: 0 | J24: 0 | K24: 0 | L24: 0 | M24: 0 | N24: 0 | O24: 0 | P24: 0 | Q24: 654015.7 | R24: 654015.7 | S24: 0 | T24: 0 | U24: 0 | V24: 0 | W24: 0 | X24: 0 | Y24: 1200 | AB24: 2315000 | AH24: =MAX(H24-AB24,0) -> 0
B25: =_xlfn.XLOOKUP(C25,Planilha3!A:A,Planilha3!B:B) -> Additive | C25: GRUPO HINOVE | D25: 0 | F25: 0 | G25: -604009.9 | H25: 604009.9 | I25: 0 | J25: 0 | K25: 0 | L25: 0 | M25: 0 | N25: 0 | O25: 0 | P25: 0 | Q25: 604009.9 | R25: 281124 | S25: 322885.9 | T25: 0 | U25: 0 | V25: 0 | W25: 0 | X25: 0 | Y25: 0 | AB25: 0 | AH25: =MAX(H25-AB25,0) -> 604009.9
B26: =_xlfn.XLOOKUP(C26,Planilha3!A:A,Planilha3!B:B) -> Additive | C26: FOSNOR - LUIS EDUARDO MAGALHAES | D26: B | F26: 2600000 | G26: 2082661.8 | H26: 517338.2 | I26: 0 | J26: 0 | K26: 0 | L26: 0 | M26: 0 | N26: 0 | O26: 0 | P26: 0 | Q26: 517338.2 | R26: 517338.2 | S26: 0 | T26: 0 | U26: 0 | V26: 0 | W26: 0 | X26: 0 | Y26: 0 | AB26: 2600000 | AH26: =MAX(H26-AB26,0) -> 0
B27: =_xlfn.XLOOKUP(C27,Planilha3!A:A,Planilha3!B:B) -> Additive | C27: ULTRAFERTIL | D27: B | F27: 1500000 | G27: 983388.6 | H27: 516611.4 | I27: 0 | J27: 0 | K27: 0 | L27: 0 | M27: 0 | N27: 0 | O27: 0 | P27: 0 | Q27: 516611.4 | R27: 516611.4 | S27: 0 | T27: 0 | U27: 0 | V27: 0 | W27: 0 | X27: 0 | Y27: 0 | AB27: 1500000 | AH27: =MAX(H27-AB27,0) -> 0
B28: =_xlfn.XLOOKUP(C28,Planilha3!A:A,Planilha3!B:B) -> Fertilizer | C28: GA AGRONEGOCIOS | D28: C | F28: 500000 | G28: 17011 | H28: 482989 | I28: 0 | J28: 0 | K28: 0 | L28: 0 | M28: 0 | N28: 0 | O28: 0 | P28: 0 | Q28: 482989 | R28: 482989 | S28: 0 | T28: 0 | U28: 0 | V28: 0 | W28: 0 | X28: 0 | Y28: 0 | AB28: 500000 | AH28: =MAX(H28-AB28,0) -> 0
B29: =_xlfn.XLOOKUP(C29,Planilha3!A:A,Planilha3!B:B) -> Additive Intl. | C29: AGROBROKERS - COLÔMBIA | D29: 0 | F29: 0 | G29: -449507.69 | H29: 449507.69 | I29: 0 | J29: 0 | K29: 0 | L29: 0 | M29: 0 | N29: 449507.69 | O29: 0 | P29: 449507.69 | Q29: 0 | R29: 0 | S29: 0 | T29: 0 | U29: 0 | V29: 0 | W29: 0 | X29: 0 | Y29: 13485.231 | AB29: 0 | AH29: =MAX(H29-AB29,0) -> 449507.69
B30: =_xlfn.XLOOKUP(C30,Planilha3!A:A,Planilha3!B:B) -> Additive | C30: ADUFERTIL JUNDIAI | D30: B | F30: 3000000 | G30: 2589143.5 | H30: 410856.52 | I30: 0 | J30: 0 | K30: 0 | L30: 0 | M30: 0 | N30: 0 | O30: 0 | P30: 0 | Q30: 410856.52 | R30: 0 | S30: 410856.52 | T30: 0 | U30: 0 | V30: 0 | W30: 0 | X30: 0 | Y30: 0 | AB30: 3000000 | AH30: =MAX(H30-AB30,0) -> 0
B31: =_xlfn.XLOOKUP(C31,Planilha3!A:A,Planilha3!B:B) -> Additive | C31: GRUPO FERTILIZ TOCANTINS | D31: 0 | F31: 10000000 | G31: 9590448.6 | H31: 409551.4 | I31: 0 | J31: 0 | K31: 0 | L31: 0 | M31: 0 | N31: 0 | O31: 0 | P31: 0 | Q31: 409551.4 | R31: 0 | S31: 409551.4 | T31: 0 | U31: 0 | V31: 0 | W31: 0 | X31: 0 | Y31: 0 | AB31: 0 | AH31: =MAX(H31-AB31,0) -> 409551.4
B32: =_xlfn.XLOOKUP(C32,Planilha3!A:A,Planilha3!B:B) -> Additive Intl. | C32: FERMAGRI S.A - EQUADOR | D32: A | F32: 770000 | G32: 369912.15 | H32: 400087.85 | I32: 0 | J32: 0 | K32: 0 | L32: 0 | M32: 0 | N32: 0 | O32: 0 | P32: 0 | Q32: 400087.85 | R32: 224812.61 | S32: 175275.24 | T32: 0 | U32: 0 | V32: 0 | W32: 0 | X32: 0 | Y32: 0 | AB32: 770000 | AH32: =MAX(H32-AB32,0) -> 0
B33: =_xlfn.XLOOKUP(C33,Planilha3!A:A,Planilha3!B:B) -> Additive | C33: BENTONIT UNIAO - CAMPINA GRANDE | D33: B | F33: 700000 | G33: 304735 | H33: 395265 | I33: 0 | J33: 0 | K33: 0 | L33: 0 | M33: 0 | N33: 0 | O33: 0 | P33: 0 | Q33: 395265 | R33: 134855 | S33: 168735 | T33: 91675 | U33: 0 | V33: 0 | W33: 0 | X33: 0 | Y33: 0 | AB33: 700000 | AH33: =MAX(H33-AB33,0) -> 0
B34: =_xlfn.XLOOKUP(C34,Planilha3!A:A,Planilha3!B:B) -> Additive Intl. | C34: YTL S.A. - PARAGUAI | D34: B | F34: 550000 | G34: 199990.55 | H34: 350009.45 | I34: 0 | J34: 0 | K34: 0 | L34: 0 | M34: 0 | N34: 0 | O34: 0 | P34: 0 | Q34: 350009.45 | R34: 350009.45 | S34: 0 | T34: 0 | U34: 0 | V34: 0 | W34: 0 | X34: 0 | Y34: 0 | AB34: 550000 | AH34: =MAX(H34-AB34,0) -> 0
B35: =_xlfn.XLOOKUP(C35,Planilha3!A:A,Planilha3!B:B) -> Fertilizer | C35: FAZENDA FERRADURA | D35: 0 | F35: 0 | G35: -329327.91 | H35: 329327.91 | I35: 0 | J35: 0 | K35: 0 | L35: 0 | M35: 0 | N35: 0 | O35: 0 | P35: 0 | Q35: 329327.91 | R35: 329327.91 | S35: 0 | T35: 0 | U35: 0 | V35: 0 | W35: 0 | X35: 0 | Y35: 0 | AB35: 0 | AH35: =MAX(H35-AB35,0) -> 329327.91
B36: =_xlfn.XLOOKUP(C36,Planilha3!A:A,Planilha3!B:B) -> Fertilizer | C36: GRUPO TAKI AGRO | D36: B | E36: 270 | F36: 1500000 | G36: 1193272.9 | H36: 306727.12 | I36: 0 | J36: 0 | K36: 0 | L36: 0 | M36: 0 | N36: 0 | O36: 0 | P36: 0 | Q36: 306727.12 | R36: 306727.12 | S36: 0 | T36: 0 | U36: 0 | V36: 0 | W36: 0 | X36: 0 | Y36: 0 | AB36: 1000000 | AH36: =MAX(H36-AB36,0) -> 0
B37: =_xlfn.XLOOKUP(C37,Planilha3!A:A,Planilha3!B:B) -> Fertilizer | C37: AGROREP. REPRESENTACOES AGRICOLAS | D37: B | E37: 180 | F37: 4000000 | G37: 3700357.9 | H37: 299642.08 | I37: 0 | J37: 0 | K37: 0 | L37: 0 | M37: 0 | N37: 0 | O37: 0 | P37: 0 | Q37: 299642.08 | R37: 0 | S37: 0 | T37: 0 | U37: 0 | V37: 0 | W37: 299642.08 | X37: 0 | Y37: 0 | AB37: 1000000 | AH37: =MAX(H37-AB37,0) -> 0
B38: =_xlfn.XLOOKUP(C38,Planilha3!A:A,Planilha3!B:B) -> Additive | C38: AGROPECUARIA MARATA LTDA - MARUIM | D38: 0 | F38: 0 | G38: -290220 | H38: 290220 | I38: 0 | J38: 0 | K38: 0 | L38: 0 | M38: 0 | N38: 0 | O38: 0 | P38: 0 | Q38: 290220 | R38: 290220 | S38: 0 | T38: 0 | U38: 0 | V38: 0 | W38: 0 | X38: 0 | Y38: 0 | AB38: 0 | AH38: =MAX(H38-AB38,0) -> 290220
B39: =_xlfn.XLOOKUP(C39,Planilha3!A:A,Planilha3!B:B) -> Additive Intl. | C39: TECNOMYL S.A. - PARAGUAY | D39: B | F39: 990000 | G39: 727686.99 | H39: 262313.01 | I39: 0 | J39: 0 | K39: 0 | L39: 0 | M39: 0 | N39: 0 | O39: 0 | P39: 0 | Q39: 262313.01 | R39: 262313.01 | S39: 0 | T39: 0 | U39: 0 | V39: 0 | W39: 0 | X39: 0 | Y39: 0 | AB39: 990000 | AH39: =MAX(H39-AB39,0) -> 0
B40: =_xlfn.XLOOKUP(C40,Planilha3!A:A,Planilha3!B:B) -> Additive Intl. | C40: C I ACEPALMA SA - COLOMBIA | D40: A | F40: 660000 | G40: 409738.47 | H40: 250261.53 | I40: 0 | J40: 0 | K40: 0 | L40: 0 | M40: 0 | N40: 0 | O40: 0 | P40: 0 | Q40: 250261.53 | R40: 0 | S40: 250261.53 | T40: 0 | U40: 0 | V40: 0 | W40: 0 | X40: 0 | Y40: 0 | AB40: 660000 | AH40: =MAX(H40-AB40,0) -> 0
B41: =_xlfn.XLOOKUP(C41,Planilha3!A:A,Planilha3!B:B) -> Additive | C41: GRUPO HERINGER | D41: B | F41: 3000000 | G41: 2751102.4 | H41: 248897.61 | I41: 0 | J41: 0 | K41: 0 | L41: 0 | M41: 0 | N41: 0 | O41: 0 | P41: 0 | Q41: 248897.61 | R41: 152127.6 | S41: 0 | T41: 0 | U41: 0 | V41: 0 | W41: 0 | X41: 96770.01 | Y41: 0 | AB41: 0 | AH41: =MAX(H41-AB41,0) -> 248897.61
B42: =_xlfn.XLOOKUP(C42,Planilha3!A:A,Planilha3!B:B) -> Additive | C42: NUTRIENTES IND DE FERTILIZANTES LTDA | D42: B | F42: 850000 | G42: 605968 | H42: 244032 | I42: 0 | J42: 0 | K42: 0 | L42: 0 | M42: 0 | N42: 0 | O42: 0 | P42: 0 | Q42: 244032 | R42: 121852 | S42: 122180 | T42: 0 | U42: 0 | V42: 0 | W42: 0 | X42: 0 | Y42: 0 | AB42: 850000 | AH42: =MAX(H42-AB42,0) -> 0
B43: =_xlfn.XLOOKUP(C43,Planilha3!A:A,Planilha3!B:B) -> Additive | C43: GRUPO FERTIPAR FERTILIZANTES MATO GROSSO | D43: B | F43: 1500000 | G43: 1256487 | H43: 243513 | I43: 0 | J43: 0 | K43: 0 | L43: 0 | M43: 0 | N43: 0 | O43: 0 | P43: 0 | Q43: 243513 | R43: 243513 | S43: 0 | T43: 0 | U43: 0 | V43: 0 | W43: 0 | X43: 0 | Y43: 0 | AB43: 1500000 | AH43: =MAX(H43-AB43,0) -> 0
B44: =_xlfn.XLOOKUP(C44,Planilha3!A:A,Planilha3!B:B) -> Fertilizer / Litigation | C44: GRUPO TRIANGULO AGRO | D44: 0 | F44: 0 | G44: -237309.12 | H44: 237309.12 | I44: 0 | J44: 0 | K44: 0 | L44: 0 | M44: 0 | N44: 0 | O44: 237309.12 | P44: 237309.12 | Q44: 0 | R44: 0 | S44: 0 | T44: 0 | U44: 0 | V44: 0 | W44: 0 | X44: 0 | Y44: 237309.12 | AB44: 0 | AH44: =MAX(H44-AB44,0) -> 237309.12
B45: =_xlfn.XLOOKUP(C45,Planilha3!A:A,Planilha3!B:B) -> Additive / Litigation | C45: TERRA FERTILIZANTES LTDA - ARAXÁ | D45: 0 | F45: 0 | G45: -226233.6 | H45: 226233.6 | I45: 0 | J45: 0 | K45: 0 | L45: 0 | M45: 0 | N45: 0 | O45: 226233.6 | P45: 226233.6 | Q45: 0 | R45: 0 | S45: 0 | T45: 0 | U45: 0 | V45: 0 | W45: 0 | X45: 0 | Y45: 226233.6 | AB45: 0 | AH45: =MAX(H45-AB45,0) -> 226233.6
B46: =_xlfn.XLOOKUP(C46,Planilha3!A:A,Planilha3!B:B) -> Fertilizer | C46: TAKI AGRO - POUSO ALEGRE | D46: B | E46: 180 | F46: 500000 | G46: 277191.83 | H46: 222808.17 | I46: 0 | J46: 0 | K46: 0 | L46: 0 | M46: 0 | N46: 0 | O46: 0 | P46: 0 | Q46: 222808.17 | R46: 222808.17 | S46: 0 | T46: 0 | U46: 0 | V46: 0 | W46: 0 | X46: 0 | Y46: 0 | AB46: 300000 | AH46: =MAX(H46-AB46,0) -> 0
B47: =_xlfn.XLOOKUP(C47,Planilha3!A:A,Planilha3!B:B) -> Additive | C47: BIOSAFRA - MARUIM | D47: B | F47: 200000 | G47: -15702.86 | H47: 215702.86 | I47: 0 | J47: 0 | K47: 0 | L47: 0 | M47: 0 | N47: 0 | O47: 0 | P47: 0 | Q47: 215702.86 | R47: 107851.43 | S47: 107851.43 | T47: 0 | U47: 0 | V47: 0 | W47: 0 | X47: 0 | Y47: 0 | AB47: 200000 | AH47: =MAX(H47-AB47,0) -> 15702.86
B48: =_xlfn.XLOOKUP(C48,Planilha3!A:A,Planilha3!B:B) -> Additive / Litigation | C48: ITERUM - RONDONOPOLIS | D48: 0 | F48: 0 | G48: -213750 | H48: 213750 | I48: 0 | J48: 0 | K48: 0 | L48: 0 | M48: 0 | N48: 0 | O48: 213750 | P48: 213750 | Q48: 0 | R48: 0 | S48: 0 | T48: 0 | U48: 0 | V48: 0 | W48: 0 | X48: 0 | Y48: 213750 | AB48: 0 | AH48: =MAX(H48-AB48,0) -> 213750
B49: =_xlfn.XLOOKUP(C49,Planilha3!A:A,Planilha3!B:B) -> Additive | C49: AURORA MINERAÇÃO LTDA | D49: 0 | F49: 0 | G49: -189028.7 | H49: 189028.7 | I49: 37491.5 | J49: 0 | K49: 0 | L49: 0 | M49: 0 | N49: 0 | O49: 0 | P49: 37491.5 | Q49: 151537.2 | R49: 75216.8 | S49: 76320.4 | T49: 0 | U49: 0 | V49: 0 | W49: 0 | X49: 0 | Y49: 0 | AB49: 0 | AH49: =MAX(H49-AB49,0) -> 189028.7
B50: =_xlfn.XLOOKUP(C50,Planilha3!A:A,Planilha3!B:B) -> Additive | C50: GRUPO JOSAPAR | D50: B | F50: 1000000 | G50: 814960 | H50: 185040 | I50: 0 | J50: 0 | K50: 0 | L50: 0 | M50: 0 | N50: 0 | O50: 0 | P50: 0 | Q50: 185040 | R50: 0 | S50: 0 | T50: 185040 | U50: 0 | V50: 0 | W50: 0 | X50: 0 | Y50: 0 | AB50: 1000000 | AH50: =MAX(H50-AB50,0) -> 0
B51: =_xlfn.XLOOKUP(C51,Planilha3!A:A,Planilha3!B:B) -> Fertilizer | C51: TAKI AGRO - SOCORRO | D51: 0 | E51: 180 | F51: 0 | G51: -184217.94 | H51: 184217.94 | I51: 184217.94 | J51: 0 | K51: 0 | L51: 0 | M51: 0 | N51: 0 | O51: 0 | P51: 184217.94 | Q51: 0 | R51: 0 | S51: 0 | T51: 0 | U51: 0 | V51: 0 | W51: 0 | X51: 0 | Y51: 0 | AB51: 0 | AH51: =MAX(H51-AB51,0) -> 184217.94
B52: =_xlfn.XLOOKUP(C52,Planilha3!A:A,Planilha3!B:B) -> Additive Intl. | C52: FERTIMAX PARAGUAY | D52: A | F52: 1375000 | G52: 1217850.5 | H52: 157149.47 | I52: 0 | J52: 0 | K52: 0 | L52: 0 | M52: 0 | N52: 0 | O52: 0 | P52: 0 | Q52: 157149.47 | R52: 157149.47 | S52: 0 | T52: 0 | U52: 0 | V52: 0 | W52: 0 | X52: 0 | Y52: 0 | AB52: 1375000 | AH52: =MAX(H52-AB52,0) -> 0
B53: =_xlfn.XLOOKUP(C53,Planilha3!A:A,Planilha3!B:B) -> Additive | C53: GRUPO AMAGGI | D53: B | F53: 4000000 | G53: 3846736.2 | H53: 153263.8 | I53: 0 | J53: 0 | K53: 0 | L53: 0 | M53: 0 | N53: 0 | O53: 0 | P53: 0 | Q53: 153263.8 | R53: 58917.8 | S53: 94346 | T53: 0 | U53: 0 | V53: 0 | W53: 0 | X53: 0 | Y53: 0 | AB53: 4000000 | AH53: =MAX(H53-AB53,0) -> 0
B54: =_xlfn.XLOOKUP(C54,Planilha3!A:A,Planilha3!B:B) -> Additive Intl. | C54: BUNGE PARAGUAY S.A | D54: B | F54: 962500 | G54: 812435.17 | H54: 150064.83 | I54: 0 | J54: 0 | K54: 0 | L54: 0 | M54: 0 | N54: 0 | O54: 0 | P54: 0 | Q54: 150064.83 | R54: 150064.83 | S54: 0 | T54: 0 | U54: 0 | V54: 0 | W54: 0 | X54: 0 | Y54: 0 | AB54: 962500 | AH54: =MAX(H54-AB54,0) -> 0
B55: =_xlfn.XLOOKUP(C55,Planilha3!A:A,Planilha3!B:B) -> Additive Intl. | C55: SOMAX - PARAGUAI | D55: B | F55: 550000 | G55: 412283.09 | H55: 137716.91 | I55: 0 | J55: 0 | K55: 0 | L55: 0 | M55: 0 | N55: 0 | O55: 0 | P55: 0 | Q55: 137716.91 | R55: 137716.91 | S55: 0 | T55: 0 | U55: 0 | V55: 0 | W55: 0 | X55: 0 | Y55: 0 | AB55: 550000 | AH55: =MAX(H55-AB55,0) -> 0
B56: =_xlfn.XLOOKUP(C56,Planilha3!A:A,Planilha3!B:B) -> Fertilizer | C56: GRUPO BOLSA AGRONEGOCIO | D56: 0 | F56: 1000000 | G56: 866282 | H56: 133718 | I56: 0 | J56: 0 | K56: 0 | L56: 0 | M56: 0 | N56: 0 | O56: 0 | P56: 0 | Q56: 133718 | R56: 133718 | S56: 0 | T56: 0 | U56: 0 | V56: 0 | W56: 0 | X56: 0 | Y56: 0 | AB56: 1000000 | AH56: =MAX(H56-AB56,0) -> 0
B57: =_xlfn.XLOOKUP(C57,Planilha3!A:A,Planilha3!B:B) -> Additive Intl. | C57: ISUSA - URUGUAI | D57: A | F57: 687500 | G57: 555539.94 | H57: 131960.06 | I57: 0 | J57: 0 | K57: 0 | L57: 0 | M57: 0 | N57: 0 | O57: 0 | P57: 0 | Q57: 131960.06 | R57: 131960.06 | S57: 0 | T57: 0 | U57: 0 | V57: 0 | W57: 0 | X57: 0 | Y57: 0 | AB57: 687500 | AH57: =MAX(H57-AB57,0) -> 0
B58: =_xlfn.XLOOKUP(C58,Planilha3!A:A,Planilha3!B:B) -> Fertilizer | C58: VEGA AGRO | D58: 0 | E58: 360 | F58: 1500000 | G58: 1368320 | H58: 131680 | I58: 0 | J58: 0 | K58: 0 | L58: 0 | M58: 0 | N58: 0 | O58: 0 | P58: 0 | Q58: 131680 | R58: 0 | S58: 0 | T58: 0 | U58: 0 | V58: 131680 | W58: 0 | X58: 0 | Y58: 0 | AB58: 660000 | AH58: =MAX(H58-AB58,0) -> 0
B59: =_xlfn.XLOOKUP(C59,Planilha3!A:A,Planilha3!B:B) -> Additive | C59: FERTGROW S.A | D59: B | F59: 3500000 | G59: 3394170.6 | H59: 105829.4 | I59: 0 | J59: 0 | K59: 0 | L59: 0 | M59: 0 | N59: 0 | O59: 0 | P59: 0 | Q59: 105829.4 | R59: 105829.4 | S59: 0 | T59: 0 | U59: 0 | V59: 0 | W59: 0 | X59: 0 | Y59: 0 | AB59: 3500000 | AH59: =MAX(H59-AB59,0) -> 0
B60: =_xlfn.XLOOKUP(C60,Planilha3!A:A,Planilha3!B:B) -> Additive Intl. | C60: TEPEYAC - MÉXICO | D60: B | F60: 1100000 | G60: 996580.11 | H60: 103419.89 | I60: 0 | J60: 0 | K60: 0 | L60: 0 | M60: 0 | N60: 0 | O60: 0 | P60: 0 | Q60: 103419.89 | R60: 103419.89 | S60: 0 | T60: 0 | U60: 0 | V60: 0 | W60: 0 | X60: 0 | Y60: 0 | AB60: 550000 | AH60: =MAX(H60-AB60,0) -> 0
B61: =_xlfn.XLOOKUP(C61,Planilha3!A:A,Planilha3!B:B) -> Additive Intl. | C61: COPEVAL - CHILE | D61: B | F61: 605000 | G61: 512638.82 | H61: 92361.18 | I61: 0 | J61: 0 | K61: 0 | L61: 0 | M61: 0 | N61: 0 | O61: 0 | P61: 0 | Q61: 92361.18 | R61: 0 | S61: 92361.18 | T61: 0 | U61: 0 | V61: 0 | W61: 0 | X61: 0 | Y61: 0 | AB61: 605000 | AH61: =MAX(H61-AB61,0) -> 0
B62: =_xlfn.XLOOKUP(C62,Planilha3!A:A,Planilha3!B:B) -> Additive Intl. | C62: CERES PERU S.A | D62: A | F62: 550000 | G62: 463310.9 | H62: 86689.1 | I62: 0 | J62: 0 | K62: 0 | L62: 0 | M62: 0 | N62: 0 | O62: 0 | P62: 0 | Q62: 86689.1 | R62: 86689.1 | S62: 0 | T62: 0 | U62: 0 | V62: 0 | W62: 0 | X62: 0 | Y62: 0 | AB62: 550000 | AH62: =MAX(H62-AB62,0) -> 0
B63: =_xlfn.XLOOKUP(C63,Planilha3!A:A,Planilha3!B:B) -> Additive | C63: COONAGRO COOPERATIVA - PARANAGUA | D63: B | F63: 2500000 | G63: 2419920.7 | H63: 80079.3 | I63: 0 | J63: 0 | K63: 0 | L63: 0 | M63: 0 | N63: 0 | O63: 0 | P63: 0 | Q63: 80079.3 | R63: 80079.3 | S63: 0 | T63: 0 | U63: 0 | V63: 0 | W63: 0 | X63: 0 | Y63: 0 | AB63: 2500000 | AH63: =MAX(H63-AB63,0) -> 0
B64: =_xlfn.XLOOKUP(C64,Planilha3!A:A,Planilha3!B:B) -> Additive Intl. | C64: AGRO MIL AGROS SAS - COLOMBIA | D64: A | F64: 302500 | G64: 226019.77 | H64: 76480.23 | I64: 0 | J64: 0 | K64: 0 | L64: 0 | M64: 0 | N64: 0 | O64: 0 | P64: 0 | Q64: 76480.23 | R64: 0 | S64: 0 | T64: 0 | U64: 0 | V64: 0 | W64: 76480.23 | X64: 0 | Y64: 0 | AB64: 302500 | AH64: =MAX(H64-AB64,0) -> 0
B65: =_xlfn.XLOOKUP(C65,Planilha3!A:A,Planilha3!B:B) -> Additive | C65: GRUPO ADUBOS ARAGUAIA | D65: B | F65: 500000 | G65: 434670 | H65: 65330 | I65: 0 | J65: 0 | K65: 0 | L65: 0 | M65: 0 | N65: 0 | O65: 0 | P65: 0 | Q65: 65330 | R65: 0 | S65: 0 | T65: 65330 | U65: 0 | V65: 0 | W65: 0 | X65: 0 | Y65: 0 | AB65: 500000 | AH65: =MAX(H65-AB65,0) -> 0
B66: =_xlfn.XLOOKUP(C66,Planilha3!A:A,Planilha3!B:B) -> Additive | C66: GRUPO LOUIS DREYFUS | D66: B | F66: 1500000 | G66: 1437433.6 | H66: 62566.4 | I66: 0 | J66: 0 | K66: 0 | L66: 0 | M66: 0 | N66: 0 | O66: 0 | P66: 0 | Q66: 62566.4 | R66: 0 | S66: 62566.4 | T66: 0 | U66: 0 | V66: 0 | W66: 0 | X66: 0 | Y66: 0 | AB66: 1500000 | AH66: =MAX(H66-AB66,0) -> 0
B67: =_xlfn.XLOOKUP(C67,Planilha3!A:A,Planilha3!B:B) -> Additive Intl. | C67: MACROSOURCE PERU S.R.L. | D67: B | F67: 990000 | G67: 940043.32 | H67: 49956.68 | I67: 0 | J67: 0 | K67: 0 | L67: 0 | M67: 0 | N67: 0 | O67: 0 | P67: 0 | Q67: 49956.68 | R67: 0 | S67: 49956.68 | T67: 0 | U67: 0 | V67: 0 | W67: 0 | X67: 0 | Y67: 0 | AB67: 990000 | AH67: =MAX(H67-AB67,0) -> 0
B68: =_xlfn.XLOOKUP(C68,Planilha3!A:A,Planilha3!B:B) -> Additive | C68: ARSLOG SOLUCOES EM TRANSPORTE | D68: 0 | F68: 0 | G68: -49440 | H68: 49440 | I68: 0 | J68: 49440 | K68: 0 | L68: 0 | M68: 0 | N68: 0 | O68: 0 | P68: 49440 | Q68: 0 | R68: 0 | S68: 0 | T68: 0 | U68: 0 | V68: 0 | W68: 0 | X68: 0 | Y68: 0 | AB68: 0 | AH68: =MAX(H68-AB68,0) -> 49440
B69: =_xlfn.XLOOKUP(C69,Planilha3!A:A,Planilha3!B:B) -> Additive Intl. | C69: GOTLAND EQUADOR (SOLINAG) | D69: 0 | F69: 0 | G69: -45718.46 | H69: 45718.46 | I69: 0 | J69: 0 | K69: 0 | L69: 0 | M69: 0 | N69: 0 | O69: 0 | P69: 0 | Q69: 45718.46 | R69: 0 | S69: 45718.46 | T69: 0 | U69: 0 | V69: 0 | W69: 0 | X69: 0 | Y69: 0 | AB69: 0 | AH69: =MAX(H69-AB69,0) -> 45718.46
B70: =_xlfn.XLOOKUP(C70,Planilha3!A:A,Planilha3!B:B) -> Additive | C70: INTERFERTIL - SAO FRANCISCO DO SUL | D70: B | F70: 200000 | G70: 155081 | H70: 44919 | I70: 0 | J70: 0 | K70: 0 | L70: 0 | M70: 0 | N70: 0 | O70: 0 | P70: 0 | Q70: 44919 | R70: 44919 | S70: 0 | T70: 0 | U70: 0 | V70: 0 | W70: 0 | X70: 0 | Y70: 0 | AB70: 200000 | AH70: =MAX(H70-AB70,0) -> 0
B71: =_xlfn.XLOOKUP(C71,Planilha3!A:A,Planilha3!B:B) -> Additive | C71: GRANUPAR - RIO BRANCO DO SUL | D71: B | F71: 300000 | G71: 256430.25 | H71: 43569.75 | I71: 0 | J71: 0 | K71: 0 | L71: 0 | M71: 0 | N71: 0 | O71: 0 | P71: 0 | Q71: 43569.75 | R71: 0 | S71: 43569.75 | T71: 0 | U71: 0 | V71: 0 | W71: 0 | X71: 0 | Y71: 0 | AB71: 300000 | AH71: =MAX(H71-AB71,0) -> 0
B72: =_xlfn.XLOOKUP(C72,Planilha3!A:A,Planilha3!B:B) -> Additive Intl. | C72: EQUILIBRA PERU S.A | D72: B | F72: 1100000 | G72: 1059982.4 | H72: 40017.64 | I72: 0 | J72: 0 | K72: 0 | L72: 0 | M72: 0 | N72: 0 | O72: 0 | P72: 0 | Q72: 40017.64 | R72: 40017.64 | S72: 0 | T72: 0 | U72: 0 | V72: 0 | W72: 0 | X72: 0 | Y72: 0 | AB72: 1100000 | AH72: =MAX(H72-AB72,0) -> 0
B73: =_xlfn.XLOOKUP(C73,Planilha3!A:A,Planilha3!B:B) -> Additive | C73: ADUBOS LEAO - LARANJEIRAS | D73: 0 | F73: 500000 | G73: 473710 | H73: 26290 | I73: 0 | J73: 0 | K73: 0 | L73: 0 | M73: 0 | N73: 0 | O73: 0 | P73: 0 | Q73: 26290 | R73: 13145 | S73: 13145 | T73: 0 | U73: 0 | V73: 0 | W73: 0 | X73: 0 | Y73: 0 | AB73: 0 | AH73: =MAX(H73-AB73,0) -> 26290
B74: =_xlfn.XLOOKUP(C74,Planilha3!A:A,Planilha3!B:B) -> Additive / Litigation | C74: GLINFERTIL - SAO FRANCISCO DO SUL | D74: 0 | F74: 0 | G74: -20940 | H74: 20940 | I74: 0 | J74: 0 | K74: 0 | L74: 0 | M74: 0 | N74: 0 | O74: 20940 | P74: 20940 | Q74: 0 | R74: 0 | S74: 0 | T74: 0 | U74: 0 | V74: 0 | W74: 0 | X74: 0 | Y74: 20940 | AB74: 0 | AH74: =MAX(H74-AB74,0) -> 20940
B75: =_xlfn.XLOOKUP(C75,Planilha3!A:A,Planilha3!B:B) -> Additive Intl. | C75: FERTIBAL - EQUADOR | D75: B | F75: 275000 | G75: 260451.65 | H75: 14548.35 | I75: 0 | J75: 0 | K75: 0 | L75: 14548.35 | M75: 0 | N75: 0 | O75: 0 | P75: 14548.35 | Q75: 0 | R75: 0 | S75: 0 | T75: 0 | U75: 0 | V75: 0 | W75: 0 | X75: 0 | Y75: 436.4505 | AB75: 275000 | AH75: =MAX(H75-AB75,0) -> 0
B76: =_xlfn.XLOOKUP(C76,Planilha3!A:A,Planilha3!B:B) -> Additive | C76: GRUPO CARGILL | D76: B | F76: 2000000 | G76: 1986569 | H76: 13431 | I76: 0 | J76: 0 | K76: 0 | L76: 0 | M76: 0 | N76: 0 | O76: 0 | P76: 0 | Q76: 13431 | R76: 13431 | S76: 0 | T76: 0 | U76: 0 | V76: 0 | W76: 0 | X76: 0 | Y76: 0 | AB76: 2000000 | AH76: =MAX(H76-AB76,0) -> 0
B77: =_xlfn.XLOOKUP(C77,Planilha3!A:A,Planilha3!B:B) -> Fertilizer | C77: GRUPO SAGRA | D77: B | E77: 360 | F77: 700000 | G77: 694969.5 | H77: 5030.5 | I77: 0 | J77: 0 | K77: 0 | L77: 0 | M77: 0 | N77: 0 | O77: 0 | P77: 0 | Q77: 5030.5 | R77: 0 | S77: 0 | T77: 0 | U77: 5030.5 | V77: 0 | W77: 0 | X77: 0 | Y77: 0 | AB77: 700000 | AH77: =MAX(H77-AB77,0) -> 0
B78: =_xlfn.XLOOKUP(C78,Planilha3!A:A,Planilha3!B:B) -> Additive | C78: MARCELO HONORIO DE CARVALHO RAMOS | D78: 0 | F78: 0 | G78: -1743 | H78: 1743 | I78: 0 | J78: 0 | K78: 0 | L78: 0 | M78: 0 | N78: 0 | O78: 0 | P78: 0 | Q78: 1743 | R78: 581 | S78: 581 | T78: 581 | U78: 0 | V78: 0 | W78: 0 | X78: 0 | Y78: 0 | AB78: 0 | AH78: =MAX(H78-AB78,0) -> 1743
B79: =_xlfn.XLOOKUP(C79,Planilha3!A:A,Planilha3!B:B) -> Additive Intl. | C79: ORGANITEC - PARAGUAY | D79: 0 | F79: 0 | G79: -1380.52 | H79: 1380.52 | I79: 0 | J79: 0 | K79: 0 | L79: 0 | M79: 0 | N79: 527.28 | O79: 0 | P79: 527.28 | Q79: 853.24 | R79: 853.24 | S79: 0 | T79: 0 | U79: 0 | V79: 0 | W79: 0 | X79: 0 | Y79: 15.8184 | AB79: 0 | AH79: =MAX(H79-AB79,0) -> 1380.52
B80: =_xlfn.XLOOKUP(C80,Planilha3!A:A,Planilha3!B:B) -> Additive | C80: ANDRESSA CAROLINA SILVA RODRIGUES | D80: 0 | F80: 0 | G80: -583.34 | H80: 583.34 | I80: 0 | J80: 0 | K80: 0 | L80: 0 | M80: 0 | N80: 0 | O80: 0 | P80: 0 | Q80: 583.34 | R80: 583.34 | S80: 0 | T80: 0 | U80: 0 | V80: 0 | W80: 0 | X80: 0 | Y80: 0 | AB80: 0 | AH80: =MAX(H80-AB80,0) -> 583.34
B81: =_xlfn.XLOOKUP(C81,Planilha3!A:A,Planilha3!B:B) -> Additive | C81: ELYMAR JOSE DA SILVA FERREIRA | D81: 0 | F81: 0 | G81: -331 | H81: 331 | I81: 0 | J81: 0 | K81: 0 | L81: 0 | M81: 0 | N81: 0 | O81: 0 | P81: 0 | Q81: 331 | R81: 0 | S81: 331 | T81: 0 | U81: 0 | V81: 0 | W81: 0 | X81: 0 | Y81: 0 | AB81: 0 | AH81: =MAX(H81-AB81,0) -> 331
B82: =_xlfn.XLOOKUP(C82,Planilha3!A:A,Planilha3!B:B) -> Additive | C82: SEU LIXO | D82: 0 | F82: 0 | G82: -300 | H82: 300 | I82: 0 | J82: 0 | K82: 0 | L82: 0 | M82: 0 | N82: 0 | O82: 300 | P82: 300 | Q82: 0 | R82: 0 | S82: 0 | T82: 0 | U82: 0 | V82: 0 | W82: 0 | X82: 0 | Y82: 300 | AB82: 0 | AH82: =MAX(H82-AB82,0) -> 300
B83: =_xlfn.XLOOKUP(C83,Planilha3!A:A,Planilha3!B:B) -> Additive | C83: KLEYTON DUARTE SOARES | D83: 0 | F83: 0 | G83: -100 | H83: 100 | I83: 0 | J83: 0 | K83: 0 | L83: 0 | M83: 0 | N83: 0 | O83: 100 | P83: 100 | Q83: 0 | R83: 0 | S83: 0 | T83: 0 | U83: 0 | V83: 0 | W83: 0 | X83: 0 | Y83: 100 | AB83: 0 | AH83: =MAX(H83-AB83,0) -> 100
B84: =_xlfn.XLOOKUP(C84,Planilha3!A:A,Planilha3!B:B) -> Additive | C84: JOSÉ FRANCISCO PIRES DE SOUZA | D84: 0 | F84: 0 | G84: -100 | H84: 100 | I84: 100 | J84: 0 | K84: 0 | L84: 0 | M84: 0 | N84: 0 | O84: 0 | P84: 100 | Q84: 0 | R84: 0 | S84: 0 | T84: 0 | U84: 0 | V84: 0 | W84: 0 | X84: 0 | Y84: 0 | AB84: 0 | AH84: =MAX(H84-AB84,0) -> 100
B85: =_xlfn.XLOOKUP(C85,Planilha3!A:A,Planilha3!B:B) -> Additive | C85: MARIA JOSE DA SILVA | D85: 0 | F85: 0 | G85: -50 | H85: 50 | I85: 0 | J85: 0 | K85: 0 | L85: 0 | M85: 0 | N85: 0 | O85: 50 | P85: 50 | Q85: 0 | R85: 0 | S85: 0 | T85: 0 | U85: 0 | V85: 0 | W85: 0 | X85: 0 | Y85: 50 | AB85: 0 | AH85: =MAX(H85-AB85,0) -> 50

Sheet Planilha1
E1: In 27/01/2026 | I1: In 28/01/2026
D2: =SUBTOTAL(9,D4:D27) -> 19842082 | E2: =SUBTOTAL(9,E4:E27) -> 3794382.8 | F2: =SUBTOTAL(9,F4:F27) -> 16047700 | H2: =SUBTOTAL(9,H4:H27) -> #N/A | I2: =SUBTOTAL(9,I4:I27) -> #N/A | J2: =SUBTOTAL(9,J4:J27) -> #N/A
B3: BU | C3: CUSTOMER | D3: Total AR | E3: Overdue | F3: Not Due | H3: Total AR | I3: Overdue | J3: Not Due | K3: Coments
B4: Additive | C4: GRUPO MOSAIC FERTILIZANTES DO BRASIL | D4: 5370037.2 | E4: 16818.92 | F4: 5353218.3 | H4: =_xlfn.XLOOKUP(C4,'Clientes Consolidado.'!$C$4:$C$47,'Clientes Consolidado.'!$H$4:$H$47) -> 2978434.3 | I4: =_xlfn.XLOOKUP(C4,'Clientes Consolidado.'!$C$4:$C$47,'Clientes Consolidado.'!$P$4:$P$47) -> 16818.92 | J4: =_xlfn.XLOOKUP(C4,'Clientes Consolidado.'!$C$4:$C$47,'Clientes Consolidado.'!$Q$4:$Q$47) -> 2961615.4
B5: Additive | C5: GRUPO YARA | D5: 3979397.8 | E5: 5626.32 | F5: 3973771.5 | H5: =_xlfn.XLOOKUP(C5,'Clientes Consolidado.'!$C$4:$C$47,'Clientes Consolidado.'!$H$4:$H$47) -> 4089718.5 | I5: =_xlfn.XLOOKUP(C5,'Clientes Consolidado.'!$C$4:$C$47,'Clientes Consolidado.'!$P$4:$P$47) -> 5626.32 | J5: =_xlfn.XLOOKUP(C5,'Clientes Consolidado.'!$C$4:$C$47,'Clientes Consolidado.'!$Q$4:$Q$47) -> 4084092.2
B6: Additive | C6: FOSNOR - LUIS EDUARDO MAGALHAES | D6: 690300 | E6: 0 | F6: 690300 | H6: =_xlfn.XLOOKUP(C6,'Clientes Consolidado.'!$C$4:$C$47,'Clientes Consolidado.'!$H$4:$H$47) -> 517338.2 | I6: =_xlfn.XLOOKUP(C6,'Clientes Consolidado.'!$C$4:$C$47,'Clientes Consolidado.'!$P$4:$P$47) -> 0 | J6: =_xlfn.XLOOKUP(C6,'Clientes Consolidado.'!$C$4:$C$47,'Clientes Consolidado.'!$Q$4:$Q$47) -> 517338.2
B7: Additive | C7: GRUPO HERINGER | D7: 520371.3 | E7: 220406.5 | F7: 299964.8 | H7: =_xlfn.XLOOKUP(C7,'Clientes Consolidado.'!$C$4:$C$47,'Clientes Consolidado.'!$H$4:$H$47) -> 248897.61 | I7: =_xlfn.XLOOKUP(C7,'Clientes Consolidado.'!$C$4:$C$47,'Clientes Consolidado.'!$P$4:$P$47) -> 0 | J7: =_xlfn.XLOOKUP(C7,'Clientes Consolidado.'!$C$4:$C$47,'Clientes Consolidado.'!$Q$4:$Q$47) -> 248897.61
B8: Additive | C8: EUROCHEM SERRA DO SALITRE | D8: 618802.8 | E8: 149216.4 | F8: 469586.4 | H8: =_xlfn.XLOOKUP(C8,'Clientes Consolidado.'!$C$4:$C$47,'Clientes Consolidado.'!$H$4:$H$47) -> 793811.7 | I8: =_xlfn.XLOOKUP(C8,'Clientes Consolidado.'!$C$4:$C$47,'Clientes Consolidado.'!$P$4:$P$47) -> 315971.7 | J8: =_xlfn.XLOOKUP(C8,'Clientes Consolidado.'!$C$4:$C$47,'Clientes Consolidado.'!$Q$4:$Q$47) -> 477840
B9: Additive | C9: GRUPO FERTILIZ TOCANTINS | D9: 1682538.8 | E9: 0 | F9: 1682538.8 | H9: =_xlfn.XLOOKUP(C9,'Clientes Consolidado.'!$C$4:$C$47,'Clientes Consolidado.'!$H$4:$H$47) -> 409551.4 | I9: =_xlfn.XLOOKUP(C9,'Clientes Consolidado.'!$C$4:$C$47,'Clientes Consolidado.'!$P$4:$P$47) -> 0 | J9: =_xlfn.XLOOKUP(C9,'Clientes Consolidado.'!$C$4:$C$47,'Clientes Consolidado.'!$Q$4:$Q$47) -> 409551.4
B10: Additive | C10: TERRA FERTILIZANTES LTDA - ARAXÁ | D10: 226233.6 | E10: 226233.6 | F10: 0 | H10: =_xlfn.XLOOKUP(C10,'Clientes Consolidado.'!$C$4:$C$47,'Clientes Consolidado.'!$H$4:$H$47) -> 226233.6 | I10: =_xlfn.XLOOKUP(C10,'Clientes Consolidado.'!$C$4:$C$47,'Clientes Consolidado.'!$P$4:$P$47) -> 226233.6 | J10: =_xlfn.XLOOKUP(C10,'Clientes Consolidado.'!$C$4:$C$47,'Clientes Consolidado.'!$Q$4:$Q$47) -> 0
B11: Additive | C11: ITERUM - RONDONOPOLIS | D11: 213750 | E11: 213750 | F11: 0 | H11: =_xlfn.XLOOKUP(C11,'Clientes Consolidado.'!$C$4:$C$47,'Clientes Consolidado.'!$H$4:$H$47) -> #N/A | I11: =_xlfn.XLOOKUP(C11,'Clientes Consolidado.'!$C$4:$C$47,'Clientes Consolidado.'!$P$4:$P$47) -> #N/A | J11: =_xlfn.XLOOKUP(C11,'Clientes Consolidado.'!$C$4:$C$47,'Clientes Consolidado.'!$Q$4:$Q$47) -> #N/A
B12: Additive | C12: GRUPO FERTIPAR FERTILIZANTES DO NORDESTE | D12: 103960.4 | E12: 3393 | F12: 100567.4 | H12: =_xlfn.XLOOKUP(C12,'Clientes Consolidado.'!$C$4:$C$47,'Clientes Consolidado.'!$H$4:$H$47) -> #N/A | I12: =_xlfn.XLOOKUP(C12,'Clientes Consolidado.'!$C$4:$C$47,'Clientes Consolidado.'!$P$4:$P$47) -> #N/A | J12: =_xlfn.XLOOKUP(C12,'Clientes Consolidado.'!$C$4:$C$47,'Clientes Consolidado.'!$Q$4:$Q$47) -> #N/A
B13: Additive | C13: GLINFERTIL - SAO FRANCISCO DO SUL | D13: 20940 | E13: 20940 | F13: 0 | H13: =_xlfn.XLOOKUP(C13,'Clientes Consolidado.'!$C$4:$C$47,'Clientes Consolidado.'!$H$4:$H$47) -> #N/A | I13: =_xlfn.XLOOKUP(C13,'Clientes Consolidado.'!$C$4:$C$47,'Clientes Consolidado.'!$P$4:$P$47) -> #N/A | J13: =_xlfn.XLOOKUP(C13,'Clientes Consolidado.'!$C$4:$C$47,'Clientes Consolidado.'!$Q$4:$Q$47) -> #N/A
B14: Additive | C14: SEU LIXO | D14: 300 | E14: 300 | F14: 0 | H14: =_xlfn.XLOOKUP(C14,'Clientes Consolidado.'!$C$4:$C$47,'Clientes Consolidado.'!$H$4:$H$47) -> #N/A | I14: =_xlfn.XLOOKUP(C14,'Clientes Consolidado.'!$C$4:$C$47,'Clientes Consolidado.'!$P$4:$P$47) -> #N/A | J14: =_xlfn.XLOOKUP(C14,'Clientes Consolidado.'!$C$4:$C$47,'Clientes Consolidado.'!$Q$4:$Q$47) -> #N/A
B15: Additive | C15: KLEYTON DUARTE SOARES | D15: 100 | E15: 100 | F15: 0 | H15: =_xlfn.XLOOKUP(C15,'Clientes Consolidado.'!$C$4:$C$47,'Clientes Consolidado.'!$H$4:$H$47) -> #N/A | I15: =_xlfn.XLOOKUP(C15,'Clientes Consolidado.'!$C$4:$C$47,'Clientes Consolidado.'!$P$4:$P$47) -> #N/A | J15: =_xlfn.XLOOKUP(C15,'Clientes Consolidado.'!$C$4:$C$47,'Clientes Consolidado.'!$Q$4:$Q$47) -> #N/A
... B27: Int'll | C27: ORGANITEC - PARAGUAY | D27: 185521.46 | E27: 527.28 | F27: 184994.18 | H27: =_xlfn.XLOOKUP(C27,'Clientes Consolidado.'!$C$4:$C$47,'Clientes Consolidado.'!$H$4:$H$47) -> #N/A | I27: =_xlfn.XLOOKUP(C27,'Clientes Consolidado.'!$C$4:$C$47,'Clientes Consolidado.'!$P$4:$P$47) -> #N/A | J27: =_xlfn.XLOOKUP(C27,'Clientes Consolidado.'!$C$4:$C$47,'Clientes Consolidado.'!$Q$4:$Q$47) -> #N/A
B29: BU | D29: Total AR | E29: Overdue | F29: Not Due | H29: Total AR | I29: Overdue | J29: Not Due
B30: Additive | D30: =SUM(D4:D16) -> 13426782 | E30: =SUM(E4:E16) -> 856834.74 | F30: =SUM(F4:F16) -> 12569947 | H30: =SUM(H4:H16) -> #N/A | I30: =SUM(I4:I16) -> #N/A | J30: =SUM(J4:J16) -> #N/A
B31: Fertilizer | D31: =+SUM(D17:D19) -> 4005020.7 | E31: =+SUM(E17:E19) -> 1647580.2 | F31: =+SUM(F17:F19) -> 2357440.4 | H31: =+SUM(H17:H19) -> #N/A | I31: =+SUM(I17:I19) -> #N/A | J31: =+SUM(J17:J19) -> #N/A
B32: Int'll | D32: =+SUM(D20:D27) -> 2410279.7 | E32: =+SUM(E20:E27) -> 1289967.8 | F32: =+SUM(F20:F27) -> 1120311.9 | H32: =+SUM(H20:H27) -> #N/A | I32: =+SUM(I20:I27) -> #N/A | J32: =+SUM(J20:J27) -> #N/A
B34: Total | D34: =+D32+D31+D30 -> 19842082 | E34: =+E32+E31+E30 -> 3794382.8 | F34: =+F32+F31+F30 -> 16047700 | H34: =+H32+H31+H30 -> #N/A | I34: =+I32+I31+I30 -> #N/A | J34: =+J32+J31+J30 -> #N/A
B36: Eurochem Group | E36: =E7+E9+E8 -> 369622.9 | H36: Eurochem Group | I36: =+I7+I9 -> 0
B37: Int´l Clients | E37: =SUM(E20:E27) -> 1289967.8 | H37: Int´l Clients | I37: =SUM(I20:I27) -> #N/A
E38: =(+E36+E37)/E34 -> 0.43738094 | F38: Of current overdue | I38: =(+I36+I37)/I34 -> #N/A | J38: Of current overdue
B40: BU | D40: Total AR | E40: Overdue | F40: Not Due
B41: Additive | D41: =SUM(H4:H16) -> #N/A | E41: =SUM(I4:I16) -> #N/A | F41: =SUM(J4:J16) -> #N/A
B42: Fertilizer | D42: =+SUM(H17:H19) -> #N/A | E42: =+SUM(I17:I19) -> #N/A | F42: =+SUM(J17:J19) -> #N/A
B43: Int'll | D43: =+SUM(H20:H27) -> #N/A | E43: =+SUM(I20:I27) -> #N/A | F43: =+SUM(J20:J27) -> #N/A
B45: Total | D45: =+D43+D42+D41 -> #N/A | E45: =+E43+E42+E41 -> #N/A | F45: =+F43+F42+F41 -> #N/A
D47: Eurochem Group | E47: =I7+I9+I8 -> 315971.7
D48: Int´l Clients | E48: =SUM(I20:I27) -> #N/A
E49: =(+E47+E48)/E45 -> #N/A | F49: Of current overdue

Sheet Nova Versão 
C1: 46142 | E1: =SUBTOTAL(9,E3:E997) -> 59371743 | J1: =SUBTOTAL(9,J3:J997) -> 35981291 | K1: =SUBTOTAL(9,K3:K997) -> 16811755 | L1: =SUBTOTAL(9,L3:L84) -> 12509468 | M1: =SUBTOTAL(9,M3:M997) -> 4204236.5 | N1: =SUBTOTAL(9,N3:N997) -> 186261.5 | O1: =SUBTOTAL(9,O3:O997) -> 1796677.1 | P1: =SUBTOTAL(9,P3:P997) -> 376122.31 | Q1: =SUBTOTAL(9,Q3:Q997) -> 96770.01 | R1: =SUBTOTAL(9,R3:R997) -> 1074699.7 | S1: =SUBTOTAL(9,S3:S997) -> 537781.14 | T1: =SUBTOTAL(9,T3:T997) -> 49440 | ... Z1: =SUBTOTAL(9,Z3:Z997) -> 22315752
B2: BU | C2: Customer | D2: Credit Approved | E2: Total AR | F2: Credit Insurance | G2: Open Exposure | H2: Remark for Open Exposure (approved in credit committee,guarantee or credit approved based on credit rating). | J2: AR Not Due | K2: 1-30 Days | L2: 31-60 Days | M2: 61-90 Days | N2: 91-120 Days | O2: 121-180 Days | P2: 181-360 Days | Q2: Above 360 Days | R2: AR Over Due but not in Litigation | S2: 1-30 Days | T2: 31-60 Days | U2: 61-90 Days | V2: 91-120 Days | W2: 121-180 Days | X2: 181-360 Days | Y2: Above 360 Days | Z2: AR in Litigation | AA2: Collection Risk Probable / Possible / Rare
B3: =_xlfn.XLOOKUP(C3,Planilha3!A:A,Planilha3!B:B) -> Fertilizer / Litigation | C3: CENTRAL DO ADUBO COM E REPRESENTACAO LTD | D3: =_xlfn.XLOOKUP(C3,'Limite de crédito'!C:C,'Limite de crédito'!G:G,0) -> 0 | E3: =J3+R3+Z3 -> 7560727.8 | F3: =_xlfn.XLOOKUP('Nova Versão '!C3,'Limite de crédito'!C:C,'Limite de crédito'!O:O,0) -> 0 | G3: =MAX(E3-F3,0) -> 7560727.8 | H3: =_xlfn.XLOOKUP(C3,Planilha3!A:A,Planilha3!C:C) -> Litigation | J3: =K3+L3+M3+N3+O3+P3+Q3 -> 0 | K3: =_xlfn.XLOOKUP(C3,'Clientes Consolidado.'!$C:$C,'Clientes Consolidado.'!R:R,0) -> 0 | L3: =_xlfn.XLOOKUP(C3,'Clientes Consolidado.'!$C:$C,'Clientes Consolidado.'!S:S,0) -> 0 | M3: =_xlfn.XLOOKUP(C3,'Clientes Consolidado.'!$C:$C,'Clientes Consolidado.'!T:T,0) -> 0 | N3: =_xlfn.XLOOKUP(C3,'Clientes Consolidado.'!$C:$C,'Clientes Consolidado.'!U:U,0) -> 0 | O3: =_xlfn.XLOOKUP(C3,'Clientes Consolidado.'!$C:$C,'Clientes Consolidado.'!V:V,0) -> 0 | P3: =_xlfn.XLOOKUP(C3,'Clientes Consolidado.'!$C:$C,'Clientes Consolidado.'!W:W,0) -> 0 | Q3: =_xlfn.XLOOKUP(C3,'Clientes Consolidado.'!$C:$C,'Clientes Consolidado.'!X:X,0) -> 0 | R3: =SUM(S3:Y3) -> 0 | S3: =SUMIFS('Clientes Consolidado.'!I:I,'Clientes Consolidado.'!C:C,C3,'Clientes Consolidado.'!B:B,"Fertilizer") +SUMIFS('Clientes Consolidado.'!I:I,'Clientes Consolidado.'!C:C,C3,'Clientes Consolidado.'!B:B,"Additive") +SUMIFS('Clientes Consolidado.'!I:I,'Clientes Consolidado.'!C:C,C3,'Clientes Consolidado.'!B:B,"Additive Intl.") -> 0 | T3: =SUMIFS('Clientes Consolidado.'!J:J,'Clientes Consolidado.'!C:C,C3,'Clientes Consolidado.'!B:B,"Fertilizer") +SUMIFS('Clientes Consolidado.'!J:J,'Clientes Consolidado.'!C:C,C3,'Clientes Consolidado.'!B:B,"Additive") +SUMIFS('Clientes Consolidado.'!J:J,'Clientes Consolidado.'!C:C,C3,'Clientes Consolidado.'!B:B,"Additive Intl.") -> 0 | U3: =SUMIFS('Clientes Consolidado.'!K:K,'Clientes Consolidado.'!C:C,C3,'Clientes Consolidado.'!B:B,"Fertilizer") +SUMIFS('Clientes Consolidado.'!K:K,'Clientes Consolidado.'!C:C,C3,'Clientes Consolidado.'!B:B,"Additive") +SUMIFS('Clientes Consolidado.'!K:K,'Clientes Consolidado.'!C:C,C3,'Clientes Consolidado.'!B:B,"Additive Intl.") -> 0 | V3: =SUMIFS('Clientes Consolidado.'!L:L,'Clientes Consolidado.'!C:C,C3,'Clientes Consolidado.'!B:B,"Fertilizer") +SUMIFS('Clientes Consolidado.'!L:L,'Clientes Consolidado.'!C:C,C3,'Clientes Consolidado.'!B:B,"Additive") +SUMIFS('Clientes Consolidado.'!L:L,'Clientes Consolidado.'!C:C,C3,'Clientes Consolidado.'!B:B,"Additive Intl.") -> 0 | W3: =SUMIFS('Clientes Consolidado.'!M:M,'Clientes Consolidado.'!C:C,C3,'Clientes Consolidado.'!B:B,"Fertilizer") +SUMIFS('Clientes Consolidado.'!M:M,'Clientes Consolidado.'!C:C,C3,'Clientes Consolidado.'!B:B,"Additive") +SUMIFS('Clientes Consolidado.'!M:M,'Clientes Consolidado.'!C:C,C3,'Clientes Consolidado.'!B:B,"Additive Intl.") -> 0 | X3: =SUMIFS('Clientes Consolidado.'!N:N,'Clientes Consolidado.'!C:C,C3,'Clientes Consolidado.'!B:B,"Fertilizer") +SUMIFS('Clientes Consolidado.'!N:N,'Clientes Consolidado.'!C:C,C3,'Clientes Consolidado.'!B:B,"Additive") +SUMIFS('Clientes Consolidado.'!N:N,'Clientes Consolidado.'!C:C,C3,'Clientes Consolidado.'!B:B,"Additive Intl.") -> 0 | Y3: =SUMIFS('Clientes Consolidado.'!O:O,'Clientes Consolidado.'!C:C,C3,'Clientes Consolidado.'!B:B,"Fertilizer") +SUMIFS('Clientes Consolidado.'!O:O,'Clientes Consolidado.'!C:C,C3,'Clientes Consolidado.'!B:B,"Additive") +SUMIFS('Clientes Consolidado.'!O:O,'Clientes Consolidado.'!C:C,C3,'Clientes Consolidado.'!B:B,"Additive Intl.") -> 0 | Z3: =SUMIFS('Clientes Consolidado.'!P:P,'Clientes Consolidado.'!C:C,'Nova Versão '!C3,'Clientes Consolidado.'!B:B,"Fertilizer / Litigation")+SUMIFS('Clientes Consolidado.'!P:P,'Clientes Consolidado.'!C:C,'Nova Versão '!C3,'Clientes Consolidado.'!B:B,"Additive / Litigation") -> 7560727.8
B4: =_xlfn.XLOOKUP(C4,Planilha3!A:A,Planilha3!B:B) -> Additive | C4: GRUPO MOSAIC FERTILIZANTES P K LTDA | D4: =_xlfn.XLOOKUP(C4,'Limite de crédito'!C:C,'Limite de crédito'!G:G,0) -> 10000000 | E4: =J4+R4+Z4 -> 6765009.9 | F4: =_xlfn.XLOOKUP('Nova Versão '!C4,'Limite de crédito'!C:C,'Limite de crédito'!O:O,0) -> 10000000 | G4: =MAX(E4-F4,0) -> 0 | H4: =_xlfn.XLOOKUP(C4,Planilha3!A:A,Planilha3!C:C) -> Guarantee or credit | J4: =K4+L4+M4+N4+O4+P4+Q4 -> 6765009.9 | K4: =_xlfn.XLOOKUP(C4,'Clientes Consolidado.'!$C:$C,'Clientes Consolidado.'!R:R,0) -> 1136498.7 | L4: =_xlfn.XLOOKUP(C4,'Clientes Consolidado.'!$C:$C,'Clientes Consolidado.'!S:S,0) -> 3096134.7 | M4: =_xlfn.XLOOKUP(C4,'Clientes Consolidado.'!$C:$C,'Clientes Consolidado.'!T:T,0) -> 2532376.5 | N4: =_xlfn.XLOOKUP(C4,'Clientes Consolidado.'!$C:$C,'Clientes Consolidado.'!U:U,0) -> 0 | O4: =_xlfn.XLOOKUP(C4,'Clientes Consolidado.'!$C:$C,'Clientes Consolidado.'!V:V,0) -> 0 | P4: =_xlfn.XLOOKUP(C4,'Clientes Consolidado.'!$C:$C,'Clientes Consolidado.'!W:W,0) -> 0 | Q4: =_xlfn.XLOOKUP(C4,'Clientes Consolidado.'!$C:$C,'Clientes Consolidado.'!X:X,0) -> 0 | R4: =SUM(S4:Y4) -> 0 | S4: =SUMIFS('Clientes Consolidado.'!I:I,'Clientes Consolidado.'!C:C,C4,'Clientes Consolidado.'!B:B,"Fertilizer") +SUMIFS('Clientes Consolidado.'!I:I,'Clientes Consolidado.'!C:C,C4,'Clientes Consolidado.'!B:B,"Additive") +SUMIFS('Clientes Consolidado.'!I:I,'Clientes Consolidado.'!C:C,C4,'Clientes Consolidado.'!B:B,"Additive Intl.") -> 0 | T4: =SUMIFS('Clientes Consolidado.'!J:J,'Clientes Consolidado.'!C:C,C4,'Clientes Consolidado.'!B:B,"Fertilizer") +SUMIFS('Clientes Consolidado.'!J:J,'Clientes Consolidado.'!C:C,C4,'Clientes Consolidado.'!B:B,"Additive") +SUMIFS('Clientes Consolidado.'!J:J,'Clientes Consolidado.'!C:C,C4,'Clientes Consolidado.'!B:B,"Additive Intl.") -> 0 | U4: =SUMIFS('Clientes Consolidado.'!K:K,'Clientes Consolidado.'!C:C,C4,'Clientes Consolidado.'!B:B,"Fertilizer") +SUMIFS('Clientes Consolidado.'!K:K,'Clientes Consolidado.'!C:C,C4,'Clientes Consolidado.'!B:B,"Additive") +SUMIFS('Clientes Consolidado.'!K:K,'Clientes Consolidado.'!C:C,C4,'Clientes Consolidado.'!B:B,"Additive Intl.") -> 0 | V4: =SUMIFS('Clientes Consolidado.'!L:L,'Clientes Consolidado.'!C:C,C4,'Clientes Consolidado.'!B:B,"Fertilizer") +SUMIFS('Clientes Consolidado.'!L:L,'Clientes Consolidado.'!C:C,C4,'Clientes Consolidado.'!B:B,"Additive") +SUMIFS('Clientes Consolidado.'!L:L,'Clientes Consolidado.'!C:C,C4,'Clientes Consolidado.'!B:B,"Additive Intl.") -> 0 | W4: =SUMIFS('Clientes Consolidado.'!M:M,'Clientes Consolidado.'!C:C,C4,'Clientes Consolidado.'!B:B,"Fertilizer") +SUMIFS('Clientes Consolidado.'!M:M,'Clientes Consolidado.'!C:C,C4,'Clientes Consolidado.'!B:B,"Additive") +SUMIFS('Clientes Consolidado.'!M:M,'Clientes Consolidado.'!C:C,C4,'Clientes Consolidado.'!B:B,"Additive Intl.") -> 0 | X4: =SUMIFS('Clientes Consolidado.'!N:N,'Clientes Consolidado.'!C:C,C4,'Clientes Consolidado.'!B:B,"Fertilizer") +SUMIFS('Clientes Consolidado.'!N:N,'Clientes Consolidado.'!C:C,C4,'Clientes Consolidado.'!B:B,"Additive") +SUMIFS('Clientes Consolidado.'!N:N,'Clientes Consolidado.'!C:C,C4,'Clientes Consolidado.'!B:B,"Additive Intl.") -> 0 | Y4: =SUMIFS('Clientes Consolidado.'!O:O,'Clientes Consolidado.'!C:C,C4,'Clientes Consolidado.'!B:B,"Fertilizer") +SUMIFS('Clientes Consolidado.'!O:O,'Clientes Consolidado.'!C:C,C4,'Clientes Consolidado.'!B:B,"Additive") +SUMIFS('Clientes Consolidado.'!O:O,'Clientes Consolidado.'!C:C,C4,'Clientes Consolidado.'!B:B,"Additive Intl.") -> 0 | Z4: =SUMIFS('Clientes Consolidado.'!P:P,'Clientes Consolidado.'!C:C,'Nova Versão '!C4,'Clientes Consolidado.'!B:B,"Fertilizer / Litigation")+SUMIFS('Clientes Consolidado.'!P:P,'Clientes Consolidado.'!C:C,'Nova Versão '!C4,'Clientes Consolidado.'!B:B,"Additive / Litigation") -> 0
B5: =_xlfn.XLOOKUP(C5,Planilha3!A:A,Planilha3!B:B) -> Additive | C5: GRUPO YARA | D5: =_xlfn.XLOOKUP(C5,'Limite de crédito'!C:C,'Limite de crédito'!G:G,0) -> 6000000 | E5: =J5+R5+Z5 -> 4089718.5 | F5: =_xlfn.XLOOKUP('Nova Versão '!C5,'Limite de crédito'!C:C,'Limite de crédito'!O:O,0) -> 6000000 | G5: =MAX(E5-F5,0) -> 0 | H5: =_xlfn.XLOOKUP(C5,Planilha3!A:A,Planilha3!C:C) -> Guarantee or credit | J5: =K5+L5+M5+N5+O5+P5+Q5 -> 4084092.2 | K5: =_xlfn.XLOOKUP(C5,'Clientes Consolidado.'!$C:$C,'Clientes Consolidado.'!R:R,0) -> 2439848.4 | L5: =_xlfn.XLOOKUP(C5,'Clientes Consolidado.'!$C:$C,'Clientes Consolidado.'!S:S,0) -> 1644243.8 | M5: =_xlfn.XLOOKUP(C5,'Clientes Consolidado.'!$C:$C,'Clientes Consolidado.'!T:T,0) -> 0 | N5: =_xlfn.XLOOKUP(C5,'Clientes Consolidado.'!$C:$C,'Clientes Consolidado.'!U:U,0) -> 0 | O5: =_xlfn.XLOOKUP(C5,'Clientes Consolidado.'!$C:$C,'Clientes Consolidado.'!V:V,0) -> 0 | P5: =_xlfn.XLOOKUP(C5,'Clientes Consolidado.'!$C:$C,'Clientes Consolidado.'!W:W,0) -> 0 | Q5: =_xlfn.XLOOKUP(C5,'Clientes Consolidado.'!$C:$C,'Clientes Consolidado.'!X:X,0) -> 0 | R5: =SUM(S5:Y5) -> 5626.32 | S5: =SUMIFS('Clientes Consolidado.'!I:I,'Clientes Consolidado.'!C:C,C5,'Clientes Consolidado.'!B:B,"Fertilizer") +SUMIFS('Clientes Consolidado.'!I:I,'Clientes Consolidado.'!C:C,C5,'Clientes Consolidado.'!B:B,"Additive") +SUMIFS('Clientes Consolidado.'!I:I,'Clientes Consolidado.'!C:C,C5,'Clientes Consolidado.'!B:B,"Additive Intl.") -> 0 | T5: =SUMIFS('Clientes Consolidado.'!J:J,'Clientes Consolidado.'!C:C,C5,'Clientes Consolidado.'!B:B,"Fertilizer") +SUMIFS('Clientes Consolidado.'!J:J,'Clientes Consolidado.'!C:C,C5,'Clientes Consolidado.'!B:B,"Additive") +SUMIFS('Clientes Consolidado.'!J:J,'Clientes Consolidado.'!C:C,C5,'Clientes Consolidado.'!B:B,"Additive Intl.") -> 0 | U5: =SUMIFS('Clientes Consolidado.'!K:K,'Clientes Consolidado.'!C:C,C5,'Clientes Consolidado.'!B:B,"Fertilizer") +SUMIFS('Clientes Consolidado.'!K:K,'Clientes Consolidado.'!C:C,C5,'Clientes Consolidado.'!B:B,"Additive") +SUMIFS('Clientes Consolidado.'!K:K,'Clientes Consolidado.'!C:C,C5,'Clientes Consolidado.'!B:B,"Additive Intl.") -> 0 | V5: =SUMIFS('Clientes Consolidado.'!L:L,'Clientes Consolidado.'!C:C,C5,'Clientes Consolidado.'!B:B,"Fertilizer") +SUMIFS('Clientes Consolidado.'!L:L,'Clientes Consolidado.'!C:C,C5,'Clientes Consolidado.'!B:B,"Additive") +SUMIFS('Clientes Consolidado.'!L:L,'Clientes Consolidado.'!C:C,C5,'Clientes Consolidado.'!B:B,"Additive Intl.") -> 0 | W5: =SUMIFS('Clientes Consolidado.'!M:M,'Clientes Consolidado.'!C:C,C5,'Clientes Consolidado.'!B:B,"Fertilizer") +SUMIFS('Clientes Consolidado.'!M:M,'Clientes Consolidado.'!C:C,C5,'Clientes Consolidado.'!B:B,"Additive") +SUMIFS('Clientes Consolidado.'!M:M,'Clientes Consolidado.'!C:C,C5,'Clientes Consolidado.'!B:B,"Additive Intl.") -> 0 | X5: =SUMIFS('Clientes Consolidado.'!N:N,'Clientes Consolidado.'!C:C,C5,'Clientes Consolidado.'!B:B,"Fertilizer") +SUMIFS('Clientes Consolidado.'!N:N,'Clientes Consolidado.'!C:C,C5,'Clientes Consolidado.'!B:B,"Additive") +SUMIFS('Clientes Consolidado.'!N:N,'Clientes Consolidado.'!C:C,C5,'Clientes Consolidado.'!B:B,"Additive Intl.") -> 0 | Y5: =SUMIFS('Clientes Consolidado.'!O:O,'Clientes Consolidado.'!C:C,C5,'Clientes Consolidado.'!B:B,"Fertilizer") +SUMIFS('Clientes Consolidado.'!O:O,'Clientes Consolidado.'!C:C,C5,'Clientes Consolidado.'!B:B,"Additive") +SUMIFS('Clientes Consolidado.'!O:O,'Clientes Consolidado.'!C:C,C5,'Clientes Consolidado.'!B:B,"Additive Intl.") -> 5626.32 | Z5: =SUMIFS('Clientes Consolidado.'!P:P,'Clientes Consolidado.'!C:C,'Nova Versão '!C5,'Clientes Consolidado.'!B:B,"Fertilizer / Litigation")+SUMIFS('Clientes Consolidado.'!P:P,'Clientes Consolidado.'!C:C,'Nova Versão '!C5,'Clientes Consolidado.'!B:B,"Additive / Litigation") -> 0
B6: =_xlfn.XLOOKUP(C6,Planilha3!A:A,Planilha3!B:B) -> Additive | C6: GRUPO UNIFERTIL | D6: =_xlfn.XLOOKUP(C6,'Limite de crédito'!C:C,'Limite de crédito'!G:G,0) -> 4500000 | E6: =J6+R6+Z6 -> 3756608.9 | F6: =_xlfn.XLOOKUP('Nova Versão '!C6,'Limite de crédito'!C:C,'Limite de crédito'!O:O,0) -> 4500000 | G6: =MAX(E6-F6,0) -> 0 | H6: =_xlfn.XLOOKUP(C6,Planilha3!A:A,Planilha3!C:C) -> Guarantee or credit | J6: =K6+L6+M6+N6+O6+P6+Q6 -> 3756608.9 | K6: =_xlfn.XLOOKUP(C6,'Clientes Consolidado.'!$C:$C,'Clientes Consolidado.'!R:R,0) -> 3756608.9 | L6: =_xlfn.XLOOKUP(C6,'Clientes Consolidado.'!$C:$C,'Clientes Consolidado.'!S:S,0) -> 0 | M6: =_xlfn.XLOOKUP(C6,'Clientes Consolidado.'!$C:$C,'Clientes Consolidado.'!T:T,0) -> 0 | N6: =_xlfn.XLOOKUP(C6,'Clientes Consolidado.'!$C:$C,'Clientes Consolidado.'!U:U,0) -> 0 | O6: =_xlfn.XLOOKUP(C6,'Clientes Consolidado.'!$C:$C,'Clientes Consolidado.'!V:V,0) -> 0 | P6: =_xlfn.XLOOKUP(C6,'Clientes Consolidado.'!$C:$C,'Clientes Consolidado.'!W:W,0) -> 0 | Q6: =_xlfn.XLOOKUP(C6,'Clientes Consolidado.'!$C:$C,'Clientes Consolidado.'!X:X,0) -> 0 | R6: =SUM(S6:Y6) -> 0 | S6: =SUMIFS('Clientes Consolidado.'!I:I,'Clientes Consolidado.'!C:C,C6,'Clientes Consolidado.'!B:B,"Fertilizer") +SUMIFS('Clientes Consolidado.'!I:I,'Clientes Consolidado.'!C:C,C6,'Clientes Consolidado.'!B:B,"Additive") +SUMIFS('Clientes Consolidado.'!I:I,'Clientes Consolidado.'!C:C,C6,'Clientes Consolidado.'!B:B,"Additive Intl.") -> 0 | T6: =SUMIFS('Clientes Consolidado.'!J:J,'Clientes Consolidado.'!C:C,C6,'Clientes Consolidado.'!B:B,"Fertilizer") +SUMIFS('Clientes Consolidado.'!J:J,'Clientes Consolidado.'!C:C,C6,'Clientes Consolidado.'!B:B,"Additive") +SUMIFS('Clientes Consolidado.'!J:J,'Clientes Consolidado.'!C:C,C6,'Clientes Consolidado.'!B:B,"Additive Intl.") -> 0 | U6: =SUMIFS('Clientes Consolidado.'!K:K,'Clientes Consolidado.'!C:C,C6,'Clientes Consolidado.'!B:B,"Fertilizer") +SUMIFS('Clientes Consolidado.'!K:K,'Clientes Consolidado.'!C:C,C6,'Clientes Consolidado.'!B:B,"Additive") +SUMIFS('Clientes Consolidado.'!K:K,'Clientes Consolidado.'!C:C,C6,'Clientes Consolidado.'!B:B,"Additive Intl.") -> 0 | V6: =SUMIFS('Clientes Consolidado.'!L:L,'Clientes Consolidado.'!C:C,C6,'Clientes Consolidado.'!B:B,"Fertilizer") +SUMIFS('Clientes Consolidado.'!L:L,'Clientes Consolidado.'!C:C,C6,'Clientes Consolidado.'!B:B,"Additive") +SUMIFS('Clientes Consolidado.'!L:L,'Clientes Consolidado.'!C:C,C6,'Clientes Consolidado.'!B:B,"Additive Intl.") -> 0 | W6: =SUMIFS('Clientes Consolidado.'!M:M,'Clientes Consolidado.'!C:C,C6,'Clientes Consolidado.'!B:B,"Fertilizer") +SUMIFS('Clientes Consolidado.'!M:M,'Clientes Consolidado.'!C:C,C6,'Clientes Consolidado.'!B:B,"Additive") +SUMIFS('Clientes Consolidado.'!M:M,'Clientes Consolidado.'!C:C,C6,'Clientes Consolidado.'!B:B,"Additive Intl.") -> 0 | X6: =SUMIFS('Clientes Consolidado.'!N:N,'Clientes Consolidado.'!C:C,C6,'Clientes Consolidado.'!B:B,"Fertilizer") +SUMIFS('Clientes Consolidado.'!N:N,'Clientes Consolidado.'!C:C,C6,'Clientes Consolidado.'!B:B,"Additive") +SUMIFS('Clientes Consolidado.'!N:N,'Clientes Consolidado.'!C:C,C6,'Clientes Consolidado.'!B:B,"Additive Intl.") -> 0 | Y6: =SUMIFS('Clientes Consolidado.'!O:O,'Clientes Consolidado.'!C:C,C6,'Clientes Consolidado.'!B:B,"Fertilizer") +SUMIFS('Clientes Consolidado.'!O:O,'Clientes Consolidado.'!C:C,C6,'Clientes Consolidado.'!B:B,"Additive") +SUMIFS('Clientes Consolidado.'!O:O,'Clientes Consolidado.'!C:C,C6,'Clientes Consolidado.'!B:B,"Additive Intl.") -> 0 | Z6: =SUMIFS('Clientes Consolidado.'!P:P,'Clientes Consolidado.'!C:C,'Nova Versão '!C6,'Clientes Consolidado.'!B:B,"Fertilizer / Litigation")+SUMIFS('Clientes Consolidado.'!P:P,'Clientes Consolidado.'!C:C,'Nova Versão '!C6,'Clientes Consolidado.'!B:B,"Additive / Litigation") -> 0
B7: =_xlfn.XLOOKUP(C7,Planilha3!A:A,Planilha3!B:B) -> Additive Intl. | C7: NITROFERT SAS - COLOMBIA | D7: =_xlfn.XLOOKUP(C7,'Limite de crédito'!C:C,'Limite de crédito'!G:G,0) -> 0 | E7: =J7+R7+Z7 -> 3280155.2 | F7: =_xlfn.XLOOKUP('Nova Versão '!C7,'Limite de crédito'!C:C,'Limite de crédito'!O:O,0) -> 0 | G7: =MAX(E7-F7,0) -> 3280155.2 | H7: =_xlfn.XLOOKUP(C7,Planilha3!A:A,Planilha3!C:C) -> Credit without Insurance | J7: =K7+L7+M7+N7+O7+P7+Q7 -> 3280155.2 | K7: =_xlfn.XLOOKUP(C7,'Clientes Consolidado.'!$C:$C,'Clientes Consolidado.'!R:R,0) -> 0 | L7: =_xlfn.XLOOKUP(C7,'Clientes Consolidado.'!$C:$C,'Clientes Consolidado.'!S:S,0) -> 3280155.2 | M7: =_xlfn.XLOOKUP(C7,'Clientes Consolidado.'!$C:$C,'Clientes Consolidado.'!T:T,0) -> 0 | N7: =_xlfn.XLOOKUP(C7,'Clientes Consolidado.'!$C:$C,'Clientes Consolidado.'!U:U,0) -> 0 | O7: =_xlfn.XLOOKUP(C7,'Clientes Consolidado.'!$C:$C,'Clientes Consolidado.'!V:V,0) -> 0 | P7: =_xlfn.XLOOKUP(C7,'Clientes Consolidado.'!$C:$C,'Clientes Consolidado.'!W:W,0) -> 0 | Q7: =_xlfn.XLOOKUP(C7,'Clientes Consolidado.'!$C:$C,'Clientes Consolidado.'!X:X,0) -> 0 | R7: =SUM(S7:Y7) -> 0 | S7: =SUMIFS('Clientes Consolidado.'!I:I,'Clientes Consolidado.'!C:C,C7,'Clientes Consolidado.'!B:B,"Fertilizer") +SUMIFS('Clientes Consolidado.'!I:I,'Clientes Consolidado.'!C:C,C7,'Clientes Consolidado.'!B:B,"Additive") +SUMIFS('Clientes Consolidado.'!I:I,'Clientes Consolidado.'!C:C,C7,'Clientes Consolidado.'!B:B,"Additive Intl.") -> 0 | T7: =SUMIFS('Clientes Consolidado.'!J:J,'Clientes Consolidado.'!C:C,C7,'Clientes Consolidado.'!B:B,"Fertilizer") +SUMIFS('Clientes Consolidado.'!J:J,'Clientes Consolidado.'!C:C,C7,'Clientes Consolidado.'!B:B,"Additive") +SUMIFS('Clientes Consolidado.'!J:J,'Clientes Consolidado.'!C:C,C7,'Clientes Consolidado.'!B:B,"Additive Intl.") -> 0 | U7: =SUMIFS('Clientes Consolidado.'!K:K,'Clientes Consolidado.'!C:C,C7,'Clientes Consolidado.'!B:B,"Fertilizer") +SUMIFS('Clientes Consolidado.'!K:K,'Clientes Consolidado.'!C:C,C7,'Clientes Consolidado.'!B:B,"Additive") +SUMIFS('Clientes Consolidado.'!K:K,'Clientes Consolidado.'!C:C,C7,'Clientes Consolidado.'!B:B,"Additive Intl.") -> 0 | V7: =SUMIFS('Clientes Consolidado.'!L:L,'Clientes Consolidado.'!C:C,C7,'Clientes Consolidado.'!B:B,"Fertilizer") +SUMIFS('Clientes Consolidado.'!L:L,'Clientes Consolidado.'!C:C,C7,'Clientes Consolidado.'!B:B,"Additive") +SUMIFS('Clientes Consolidado.'!L:L,'Clientes Consolidado.'!C:C,C7,'Clientes Consolidado.'!B:B,"Additive Intl.") -> 0 | W7: =SUMIFS('Clientes Consolidado.'!M:M,'Clientes Consolidado.'!C:C,C7,'Clientes Consolidado.'!B:B,"Fertilizer") +SUMIFS('Clientes Consolidado.'!M:M,'Clientes Consolidado.'!C:C,C7,'Clientes Consolidado.'!B:B,"Additive") +SUMIFS('Clientes Consolidado.'!M:M,'Clientes Consolidado.'!C:C,C7,'Clientes Consolidado.'!B:B,"Additive Intl.") -> 0 | X7: =SUMIFS('Clientes Consolidado.'!N:N,'Clientes Consolidado.'!C:C,C7,'Clientes Consolidado.'!B:B,"Fertilizer") +SUMIFS('Clientes Consolidado.'!N:N,'Clientes Consolidado.'!C:C,C7,'Clientes Consolidado.'!B:B,"Additive") +SUMIFS('Clientes Consolidado.'!N:N,'Clientes Consolidado.'!C:C,C7,'Clientes Consolidado.'!B:B,"Additive Intl.") -> 0 | Y7: =SUMIFS('Clientes Consolidado.'!O:O,'Clientes Consolidado.'!C:C,C7,'Clientes Consolidado.'!B:B,"Fertilizer") +SUMIFS('Clientes Consolidado.'!O:O,'Clientes Consolidado.'!C:C,C7,'Clientes Consolidado.'!B:B,"Additive") +SUMIFS('Clientes Consolidado.'!O:O,'Clientes Consolidado.'!C:C,C7,'Clientes Consolidado.'!B:B,"Additive Intl.") -> 0 | Z7: =SUMIFS('Clientes Consolidado.'!P:P,'Clientes Consolidado.'!C:C,'Nova Versão '!C7,'Clientes Consolidado.'!B:B,"Fertilizer / Litigation")+SUMIFS('Clientes Consolidado.'!P:P,'Clientes Consolidado.'!C:C,'Nova Versão '!C7,'Clientes Consolidado.'!B:B,"Additive / Litigation") -> 0
