Workbook
Name \0: #N/A
Name \1: #REF!
Name \2: #REF!
Name \3: #REF!
Name \4: #REF!
Name \5: #REF!
Name \a: #N/A
Name \b: #N/A
Name \c: #N/A
Name \d: #N/A
Name \DSUM: #REF!
Name \e: #N/A
Name \EXP: #REF!
Name \f: #N/A
Name \g: #N/A
Name \GL: #REF!
Name \h: #REF!
Name \I: #REF!
Name \k: #REF!
Name \l: #REF!
Name \m: #N/A
Name \MPR2: #REF!
Name \n: #REF!
Name \o: #REF!
Name \p: #N/A
Name \q: #REF!
Name \R: #REF!
Name \s: #N/A
Name \t: #REF!
Name \u: #N/A
Name \w: #REF!
Name \x: #REF!
Name \y: #REF!
Name \z: #REF!
Name _: #REF!
Name __?Business___Market_Spr: #REF!
Name __?End_Use_Analysis___Sectoral_Gro: #REF!
Name __?INDUSTRY_MATERIAL_BALA: #REF!
Name __?INDUSTRY_MATERIAL_BALANCE___PROJECTI: #REF!
Name __?PE___Q1_REV: #REF!
Name __?PE_1996: #REF!
Name __?PE_BUSINESS___PAST___FUT: #REF!
Name __?PE_REV: #REF!
Name __?PRICE_FORECAST___1995: #REF!
Name __?PROFITABILITY__Q3_1996__: #REF!
Name __?Q3___SUMM: #REF!
Name __?Quarterwise_Collection_P: #REF!
Name __?Quarterwise_Export_P: #REF!
Name __?QUARTERWISE_PERFORMA: #REF!
Name __?RE: #REF!
Name _______________________________DAT5: #REF!
Name _______________________________DAT7: #REF!
Name ______________________________DAT1: #REF!
Name ______________________________DAT10: #REF!
Name _____________________________DAT5: #REF!
Name _____________________________DAT7: #REF!
Name ____________________________DAT1: #REF!
Name ____________________________DAT10: #REF!
Name ____________________________DAT5: #REF!
Name ____________________________DAT7: #REF!

Sheet AR - slide BoD
B1: Amounts in 000
B2: Total receivables | I2: =I22/1000 -> 64140.011 | J2: =J22/1000 -> 105264.99
B4: Receivables as on 28th Feb 25 | D4: BU | E4: Overdue | F4: Not Due | G4: Not Due | I4: Provision | J4: Provision | L4: Provision risks - overdue receivables | P4: Remark
L5: Probable | M5: Possible | N5: Rare
B6: Central do Adubo | D6: Fertilizer | E6: =E26/1000 -> 7560.7278 | F6: =F26/1000 -> 0 | G6: =G26/1000 -> 7560.7278 | I6: =I26/1000 -> 0 | J6: =J26/1000 -> 0 | L6: =L26/1000 -> 0 | M6: =M26/1000 -> 7560.7278 | N6: =N26/1000 -> 0 | P6: Creditor´s assembly Judicial recovery plan has not yet been approved by Creditors. Adfert advisors believe that the AS-IS plan will not be approved and new financial conditions will need to be presented.
B7: SM Agro / Fazenda Baturi | D7: Fertilizer | E7: =E27/1000 -> 3088.5311 | F7: =F27/1000 -> 0 | G7: =G27/1000 -> 3088.5311 | I7: =I27/1000 -> 3088.5311 | J7: =J27/1000 -> 0 | L7: =L27/1000 -> 3088.5311 | M7: =M27/1000 -> 0 | N7: =N27/1000 -> 0 | P7: Judicial collection lawsuit is ongoing.
B8: CBM Fertilizantes | D8: Fertilizer | E8: =E28/1000 -> 3044.8509 | F8: =F28/1000 -> 0 | G8: =G28/1000 -> 3044.8509 | I8: =I28/1000 -> 3044.8509 | J8: =J28/1000 -> 0 | L8: =L28/1000 -> 3044.8509 | M8: =M28/1000 -> 0 | N8: =N28/1000 -> 0 | P8: Adfert has taken legal action and collection recovery lawsuit has been filed. Payment plan was not succesful.
B9: Mogiana Tecno Agro | D9: Fertilizer | E9: =E29/1000 -> 2492.8421 | F9: =F29/1000 -> 0 | G9: =G29/1000 -> 2492.8421 | I9: =I29/1000 -> 0 | J9: =J29/1000 -> 0 | L9: =L29/1000 -> 0 | M9: =M29/1000 -> 2492.8421 | N9: =N29/1000 -> 0 | P9: AFT received a renewalled payment proposal. Monthly payments along 2 yrs, with Machineary as guarantee and worth 25% of Open Exposure. Formal proposal still pending full disclosre on documents and valuation on Machinery.
B10: Casa das Sementes | D10: Fertilizer | E10: =E30/1000 -> 1863.2009 | F10: =F30/1000 -> 0 | G10: =G30/1000 -> 1863.2009 | I10: =I30/1000 -> 1863.2009 | J10: =J30/1000 -> 0 | L10: =L30/1000 -> 1863.2009 | M10: =M30/1000 -> 0 | N10: =N30/1000 -> 0 | P10: Legal process ongoing and 100% of the invoices we provisioned.
B11: Terra Fértil | D11: Fertilizer | E11: =E31/1000 -> 1702.8487 | F11: =F31/1000 -> 0 | G11: =G31/1000 -> 1702.8487 | I11: =I31/1000 -> 1702.8487 | J11: =J31/1000 -> 0 | L11: =L31/1000 -> 1702.8487 | M11: =M31/1000 -> 0 | N11: =N31/1000 -> 0 | P11: AFT has reached a payment agreement: 15% paid by Oct 25 and 3 yearly installments (Oct 26-27-28). No discount on principal and price inflation indexed
B12: Agro Beraldo | D12: Fertilizer | E12: =E32/1000 -> 876.01175 | F12: =F32/1000 -> 0 | G12: =G32/1000 -> 876.01175 | I12: =I32/1000 -> 0 | J12: =J32/1000 -> 0 | L12: =L32/1000 -> 0 | M12: =M32/1000 -> 876.01175 | N12: =N32/1000 -> 0 | P12: Judicial collection lawsuit is ongoing.
B14: Total Over Due in Litigation (TOP 7) | E14: =E39/1000 -> 22315.752 | F14: 0 | G14: 0 | I14: =I39/1000 -> 10937.332 | J14: =J39/1000 -> 0 | L14: =L39/1000 -> 10937.332 | M14: =M39/1000 -> 11378.42 | N14: 0
B15: Total Over Due with Possible Loss | E15: =E45/1000 -> 6.07632 | F15: 0 | G15: 0 | I15: =I45/1000 -> 6.07632 | J15: =J45/1000 -> 0 | L15: =L45/1000 -> 6.07632 | M15: =M45/1000 -> 0 | N15: 0
B16: Low Risk - Expect to Receive soon | E16: =E46/1000 -> 693.20556 | F16: =F46/1000 -> 0 | G16: =G46/1000 -> 693.20556 | I16: =I46/1000 -> 163.97203 | J16: =J46/1000 -> 0 | L16: =L46/1000 -> 0 | M16: =M46/1000 -> 0 | N16: =N46/1000 -> 693.20556 | P16: Provision as per corporate policy
B17: Total | E17: =E16+E15+E14 -> 23015.034 | F17: =F16+F15+F14 -> 0 | G17: =G16+G15+G14 -> 693.20556 | I17: =I16+I15+I14 -> 11107.381 | J17: =J16+J15+J14 -> 0 | L17: =L14+L15 -> 10943.409 | M17: =M16+M14 -> 11378.42 | N17: =N16+N14 -> 693.20556
B19: in BRl
B22: Total receivables | I22: =SUM(E124:F124) -> 64140011 | J22: =SUM(F124:G124) -> 1.0526499e+08
B24: Receivables as on 31th May 26 | D24: BU | E24: Overdue | F24: Not Due | G24: Total | I24: Provision | J24: Write Off | L24: Collection Risk | P24: Remark
L25: Probable | M25: Possible | N25: Rare
B26: CENTRAL DO ADUBO COM E REPRESENTACAO LTD | D26: Fertilizers | E26: 7560727.8 | F26: 0 | G26: =SUM(E26:F26) -> 7560727.8 | I26: 0 | L26: =I26 -> 0 | M26: =E26-I26 -> 7560727.8 | P26: Current Status: Creditor´s Assembly has been approved. All suppliers to receive 35% (65% haircut) of total Outstanding in 10 years (2x per year installments) after a 18-months grace period, corrected by TR inflation index. Prefered suppliers, such as AFT, are eligible to full Overdue recovery based on future sales. 3% of all new CAD Sales to offset Old Overdues and 4% for sales with tenor (credit). This condition is non-binding and the client is to grant AFT a real estate guarantee of BRL 1MM. Upcoming Actions: Decision will now need to undergo approval and pass the entire appeal period. This step may still take a couple months to be completed.
B27: GRUPO LEANDRO SARTI | D27: Fertilizers | E27: 3088531.1 | F27: 0 | G27: =SUM(E27:F27) -> 3088531.1 | I27: 3088531.1 | L27: =I27 -> 3088531.1 | M27: =E27-I27 -> 0 | P27: Current Status: In Litigation via Collection enforcement claim. The judicial process is still in the initial phase, and we are in the period of notifying the parties involved. Upcoming Actions: We will await the procedures set forth by the court.
B28: AGRO BERALDO | D28: Fertilizers | E28: 3044850.9 | F28: 0 | G28: =SUM(E28:F28) -> 3044850.9 | I28: 3044850.9 | L28: =I28 -> 3044850.9 | M28: =E28-I28 -> 0 | P28: Current Status: The Litigation Collection enforcement claim process is ongoing. Upcoming Actions: AFT awaiting for further updates by the court.
B29: TERRA FERTIL - MACHADO | D29: Fertilizers | E29: 2492842.1 | F29: 0 | G29: =SUM(E29:F29) -> 2492842.1 | I29: 0 | L29: =I29 -> 0 | M29: =E29-I29 -> 2492842.1 | P29: Current Status: In Litigation via Collection enforcement claim. An agreement has been reached between parties, under the following terms: (i) Total settlement amount: R$ 3,192,985.64; (ii) Down payment: R$ 478,947.84, to be paid by October 30, 2025; (iii) Remaining balance: R$ 2,714,037.80, to be paid in three annual installments of R$ 904,679.26 each (2026 / 2027 / 2028), to be duly adjusted by inflation/court index. Upcoming Actions: AFT awaiting for the downpayment from the debtor to fulfill the agreement (Oct 20th 2025).
B30: MOGIANA TECNO AGRO | D30: Fertilizers | E30: 1863200.9 | F30: 0 | G30: =SUM(E30:F30) -> 1863200.9 | I30: 1863200.9 | L30: =I30 -> 1863200.9 | M30: =E30-I30 -> 0 | P30: Current Status: In Litigation via Collection enforcement claim. AFT received a proposal agreement, consisting of 12 initial installments of R$ 50,000.00, beginning March 28, which we had previously agreed after trying to negotiate a higher amount. From the 13th month, the proposal would be to rise monthly installments to R$ 100,000.00. This payment agreement would include both principal (R$ 2,502,567.34) and Interest (R$ 204,693.57). We have, via the enforcement collection claim received BRL 29k from the clients account via judicial decison. Upcoming Actions: we´ve not received feedback and are still assessing the viability of an agreed payment plan proposal. AFT is continuing to follow up on a payment schedule definition. AFT continues to follow on enforcement of any assets available from the client.
B31: CASA DAS SEMENTES | D31: Fertilizers | E31: 1702848.7 | F31: 0 | G31: =SUM(E31:F31) -> 1702848.7 | I31: 1702848.7 | L31: =I31 -> 1702848.7 | M31: =E31-I31 -> 0 | P31: Current Status: In Litigation via Collection enforcement claim. The process is ongoing, and we have successfully notified the debtor via judicial court. Upcoming Actions: AFT is seeking to seize assets from the debtor via the judicial claim which is ongoing.
B32: CBM FERTILIZANTES | D32: Fertilizers | E32: 876011.75 | F32: 0 | G32: =SUM(E32:F32) -> 876011.75 | I32: 0 | L32: =I32 -> 0 | M32: =E32-I32 -> 876011.75 | P32: Judicial settlement has been signed, under the following terms: (i) Total settlement amount: R$ 1,179,964.76, to be paid under the following conditions; (ii) Agreed payment in Two installments of R$ 100,000.00 each, due on April 24, 2025, and September 30th, 2025; Client has paid BRL 100k of the 1st installment and 2nd to be paid on the 30th of Sept. (iii) Three annual installments of R$ 326,654.92 , due on September 30, 2026, September 30, 2027, and September 30, 2028; Upcoming Actions: AFT awaiting for the payment plan agreed ofr September (another BRL 100k payment).
B33: GRUPO TRIANGULO AGRO | D33: Fertilizers | E33: 237309.12 | F33: 0 | G33: =SUM(E33:F33) -> 237309.12 | I33: 237309.12 | L33: =I33 -> 237309.12 | M33: =E33-I33 -> 0 | P33: Current Status: Client has issue a Judicial Recovery claim. The judicial process is still in the initial phase, and AFT has been notified. Upcoming Actions: AFT awaiting for the next steps to be set by court.
B34: TERRA FERTILIZANTES LTDA - ARAXÁ | D34: Additives | E34: 226233.6 | F34: 0 | G34: =SUM(E34:F34) -> 226233.6 | I34: 226233.6 | L34: =I34 -> 226233.6 | M34: =E34-I34 -> 0 | P34: May - 2024. In Litigation via collection enforcement. We don´t expect to have the collection. Client has been operation with a different Tax Id and we´re investigating how to link both companies to this claim.
B35: FAZENDA ARCOS SÃO JOÃO | D35: Fertilizers | E35: 988506.24 | F35: 0 | G35: =SUM(E35:F35) -> 988506.24 | I35: 539667.84 | L35: =I35 -> 539667.84 | M35: =E35-I35 -> 448838.4 | P35: Aug- 2025 Payment plan negotiation ongoing.
B36: ITERUM - RONDONOPOLIS | D36: Additives | E36: 213750 | F36: 0 | G36: =SUM(E36:F36) -> 213750 | I36: 213750 | L36: =I36 -> 213750 | M36: =E36-I36 -> 0 | P36: Dec- 2024 - Client facing fanancial difficulties and offered to return non-used final products. AFT is validating samples collected for quality assurance.
B37: GLINFERTIL - SAO FRANCISCO DO SUL | D37: Additives | E37: 20940 | F37: 0 | G37: =SUM(E37:F37) -> 20940 | I37: 20940 | L37: =I37 -> 20940 | M37: =E37-I37 -> 0 | P37: Nov 2023 Overdue. We don´t expect to receive collection from this client. The current status is that the client awaits for a court decision to accept the Judicial recovery process.
B39: Total Over Due in Litigation (TOP 12) | E39: =SUM(E26:E37) -> 22315752 | F39: =SUM(F26:F37) -> 0 | G39: =SUM(G26:G37) -> 22315752 | I39: =SUM(I26:I37) -> 10937332 | J39: =SUM(J26:J37) -> 0 | L39: =SUM(L26:L37) -> 10937332 | M39: =SUM(M26:M37) -> 11378420 | N39: =SUM(N26:N37) -> 0
B40: KLEYTON DUARTE SOARES | D40: Additives | E40: 100 | F40: 0 | G40: =SUM(E40:F40) -> 100 | I40: 100 | L40: =I40 -> 100 | M40: =E40-L40 -> 0 | P40: Jul - 2024 - Sale of old fixed assets to employees (chairs, desks etc) and it was not duly debited in employees payroll. Employee has left the company.
B41: MARIA JOSE DA SILVA | D41: Additives | E41: 50 | F41: 0 | G41: =SUM(E41:F41) -> 50 | I41: 50 | L41: =I41 -> 50 | M41: =E41-L41 -> 0 | P41: Aug - 2024 - Sale of old fixed assets to employees (chairs, desks etc) and it was not duly debited in employees payroll. Employee has left the company.
B42: GRUPO YARA | D42: Additives | E42: 5626.32 | F42: 0 | G42: =SUM(E42:F42) -> 5626.32 | I42: 5626.32 | L42: =I42 -> 5626.32 | M42: =E42-L42 -> 0 | P42: June 2024 - invoice underpayment due client claim of weight divergence
B43: SEU LIXO | D43: Additives | E43: 300 | F43: 0 | G43: =SUM(E43:F43) -> 300 | I43: 300 | L43: =I43 -> 300 | M43: =E43-L43 -> 0 | P43: Nov 2024 - sale of scrap materials.
B45: Total Over Due with Probable Loss | E45: =SUM(E40:E44) -> 6076.32 | F45: =SUM(F40:F44) -> 0 | G45: =SUM(G40:G44) -> 6076.32 | I45: =SUM(I40:I44) -> 6076.32 | J45: =SUM(J40:J44) -> 0 | L45: =SUM(L40:L44) -> 6076.32 | M45: =SUM(M40:M44) -> 0 | N45: =SUM(N40:N44) -> 0
B46: Low Risk - Expect to Receive soon | E46: =SUM(E47:E54) -> 693205.56 | F46: =F55+F56+F57 -> 0 | G46: =SUM(G47:G54) -> 693205.56 | I46: =SUM(I47:I54) -> 163972.03 | J46: =SUM(J47:J54) -> 0 | L46: =SUM(L47:L54) -> 0 | M46: =SUM(M47:M54) -> 0 | N46: =SUM(N47:N54) -> 693205.56 | P46: Provision as per corporate policy
B47: FAZENDA FERRADURA | D47: Fertilizers | E47: 329327.91 | G47: 329327.91 | I47: 0 | N47: =E47 -> 329327.91
B48: FERTIBAL - EQUADOR | D48: Additive Intl. | E48: 14548.35 | G48: =SUM(E48:F48) -> 14548.35 | I48: 436.4505 | N48: =E48 -> 14548.35
B49: CERES PERU S.A | D49: Additive Intl. | E49: 86689.1 | G49: =SUM(E49:F49) -> 86689.1 | I49: 0 | N49: =E49 -> 86689.1
B50: EQUILIBRA PERU S.A | D50: Additive Intl. | E50: 40017.64 | G50: =SUM(E50:F50) -> 40017.64 | I50: 0 | N50: =E50 -> 40017.64
B51: ARSLOG SOLUCOES EM TRANSPORTE | D51: Additives | E51: 49440 | G51: =SUM(E51:F51) -> 49440 | I51: 0 | N51: =E51 -> 49440
B52: GRUPO MOSAIC FERTILIZANTES DO BRASIL | D52: Additives | E52: 16818.92 | G52: =SUM(E52:F52) -> 16818.92 | I52: 16756.646 | N52: =E52 -> 16818.92
B53: ORGANITEC - PARAGUAY | D53: Additive Intl. | E53: 1380.52 | G53: =SUM(E53:F53) -> 1380.52 | I53: 15.8184 | N53: =E53 -> 1380.52
B54: Freight Debit Notes | D54: Additives | E54: 154983.12 | G54: =SUM(E54:F54) -> 154983.12 | I54: 146763.12 | N54: =E54 -> 154983.12
B55: Not Due | D55: Additives
D56: Additive Intl.
D57: Fertilizers
B58: GRUPO MOSAIC FERTILIZANTES DO BRASIL | D58: Additives | F58: 4180140 | G58: =E58+F58 -> 4180140 | O58: 475235
B59: GRUPO YARA | D59: Additives | F59: 5055164.7 | G59: =E59+F59 -> 5055164.7 | O59: 3633158.1
B60: GRUPO MOSAIC FERTILIZANTES P K LTDA | D60: Additives | F60: 7901397.6 | G60: =E60+F60 -> 7901397.6
B61: FERTGROW S.A | D61: Additives | F61: 1521434.2 | G61: =E61+F61 -> 1521434.2
B62: FECOAGRO FEDERACAO DAS COOPERATIVAS | D62: Additives | F62: 1314321.9 | G62: =E62+F62 -> 1314321.9
B63: GRUPO FERTILIZ TOCANTINS | D63: Additives | F63: 921284.1 | G63: =E63+F63 -> 921284.1 | O63: 3231664.8
B64: FOSNOR - LUIS EDUARDO MAGALHAES | D64: Additives | F64: 864461.4 | G64: =E64+F64 -> 864461.4 | O64: 225884.2
B65: STRATOS - ROSARIO DO CATETE | D65: Additives | F65: 850921.6 | G65: =E65+F65 -> 850921.6 | O65: 6158350.9
B66: EUROCHEM SERRA DO SALITRE | D66: Additives | F66: 834367.1 | G66: =E66+F66 -> 834367.1 | O66: 866804.7
B67: ADUFERTIL JUNDIAI | D67: Additives | F67: 793417.97 | G67: =E67+F67 -> 793417.97 | O67: 158126.4
B68: ULTRAFERTIL | D68: Additives | F68: 586679.8 | G68: =E68+F68 -> 586679.8 | O68: 1227102.4
B69: GRUPO FERTIPAR FERTILIZANTES MATO GROSSO | D69: Additives | F69: 487086.6 | G69: =E69+F69 -> 487086.6 | O69: 53489.3
B70: BENTONIT UNIAO - CAMPINA GRANDE | D70: Additives | F70: 486010 | G70: =E70+F70 -> 486010
B71: GRUPO CIBRA | D71: Additives | F71: 359384.3 | G71: =E71+F71 -> 359384.3 | O71: 528498.8
B72: GRUPO UNIFERTIL | D72: Additives | F72: 348528.3 | G72: =E72+F72 -> 348528.3 | O72: 417989.8
B73: ITAFOS - ARRAIAS/TO | D73: Additives | F73: 333624.9 | G73: =E73+F73 -> 333624.9 | O73: 1424871.4
B74: GRUPO HINOVE | D74: Additives | F74: 322885.9 | G74: =E74+F74 -> 322885.9 | O74: 1708772
B75: GRUPO AMAGGI | D75: Additives | F75: 268136.7 | G75: =E75+F75 -> 268136.7 | O75: 324729
B76: BIGFERTIL - CANDEIAS | D76: Additives | F76: 242565.88 | G76: =E76+F76 -> 242565.88 | O76: 1034572.5
B77: AURORA MINERAÇÃO LTDA | D77: Additives | F77: 228927.4 | G77: =E77+F77 -> 228927.4 | O77: 444240
B78: GRUPO FERTIPAR FERTILIZANTES DO NORDESTE | D78: Additives | F78: 222928.82 | G78: =E78+F78 -> 222928.82 | O78: 159679.8
B79: GRUPO HERINGER | D79: Additives | F79: 202028.01 | G79: =E79+F79 -> 202028.01 | O79: 23451.75
B80: GRUPO JOSAPAR | D80: Additives | F80: 185040 | G80: =E80+F80 -> 185040
B81: COONAGRO COOPERATIVA - PARANAGUA | D81: Additives | F81: 179749.5 | G81: =E81+F81 -> 179749.5
B82: GRUPO LOUIS DREYFUS | D82: Additives | F82: 132305.3 | G82: =E82+F82 -> 132305.3
B83: NUTRIENTES IND DE FERTILIZANTES LTDA | D83: Additives | F83: 122180 | G83: =E83+F83 -> 122180
B84: GRUPO AGRO INDUSTRIAL SAO LUIZ LTDA | D84: Additives | F84: 121141.8 | G84: =E84+F84 -> 121141.8
B85: BIOSAFRA - MARUIM | D85: Additives | F85: 107851.43 | G85: =E85+F85 -> 107851.43
B86: GRANUPAR - RIO BRANCO DO SUL | D86: Additives | F86: 91432.8 | G86: =E86+F86 -> 91432.8
B87: FERTIMAXI - CONCEICAO DO JACUIPE | D87: Additives | F87: 86601.42 | G87: =E87+F87 -> 86601.42
B88: INTERFERTIL - SAO FRANCISCO DO SUL | D88: Additives | F88: 83895.3 | G88: =E88+F88 -> 83895.3
B89: BUNGE - SANTOS | D89: Additives | F89: 78835.8 | G89: =E89+F89 -> 78835.8
B90: GRUPO ADUBOS ARAGUAIA | D90: Additives | F90: 65330 | G90: =E90+F90 -> 65330 | O90: 73440
B91: GRUPO CARGILL | D91: Additives | F91: 62249 | G91: =E91+F91 -> 62249 | O91: 112012.5
B92: FERTIPLANTA - VARGEM GRANDE DO SUL | D92: Additives | F92: 49880 | G92: =E92+F92 -> 49880
B93: FERTINE - RECIFE | D93: Additives | F93: 42720 | G93: =E93+F93 -> 42720
B94: NITROBRAS IND. E COM. DE FERTILIZ. LTDA | D94: Additives | F94: 39789 | G94: =E94+F94 -> 39789
B95: FERTALVO FERTILIZANTES - RONDONÓPOLIS | D95: Additives | F95: 34250 | G95: =E95+F95 -> 34250
B96: FERTLIZE AGRO | D96: Additives | F96: 6853.28 | G96: =E96+F96 -> 6853.28
B97: ASSOCIACAO RECICLA TRIANGULO | D97: Additives | F97: 2243.4 | G97: =E97+F97 -> 2243.4
B98: MARCELO HONORIO DE CARVALHO RAMOS | D98: Additives | F98: 1743 | G98: =E98+F98 -> 1743
B99: PATRICIA LARA SOUZA | D99: Additives | F99: 287.28 | G99: =E99+F99 -> 287.28
B100: AGROVIVA | D100: Fertilizers | F100: 994249.16 | G100: =E100+F100 -> 994249.16
B101: ADUFÉRTIL - CAMPEVO | D101: Fertilizers | F101: 953390.54 | G101: =E101+F101 -> 953390.54
B102: CONNTACTA AGRONEGOCIOS | D102: Fertilizers | F102: 739540.06 | G102: =E102+F102 -> 739540.06
B103: AGROREP. REPRESENTACOES AGRICOLAS | D103: Fertilizers | F103: 299642.08 | G103: =E103+F103 -> 299642.08
... B122: MACROSOURCE PERU S.R.L. | D122: Additive Intl. | F122: 49956.68 | G122: =E122+F122 -> 49956.68
G123: =E123+F123 -> 0
B124: Total | E124: =E46+E45+E39+SUM(E58:E123) -> 23015034 | F124: =F46+F45+F39+SUM(F58:F123) -> 41124977 | G124: =G46+G45+G39+SUM(G58:G123) -> 64140011 | I124: =I46+I45+I39+SUM(I58:I123) -> 11107381 | J124: =J46+J45+J39+SUM(J58:J123) -> 0 | L124: =L46+L45+L39+SUM(L58:L123) -> 10943409 | M124: =M46+M45+M39+SUM(M58:M123) -> 11378420 | N124: =N46+N45+N39+SUM(N58:N123) -> 693205.56
D126: Additive Intl. | E126: =SUMIF($D$26:$D$124,$D126,E$26:E$124) -> 142635.61 | F126: =SUMIF($D$26:$D$124,$D126,F$26:F$124) -> 8181369.6 | G126: =SUMIF($D$26:$D$124,$D126,G$26:G$124) -> 8324005.2 | H126: =SUMIF($D$26:$D$124,$D126,H$26:H$124) -> 0 | I126: =SUMIF($D$26:$D$124,$D126,I$26:I$124) -> 452.2689 | J126: =SUMIF($D$26:$D$124,$D126,J$26:J$124) -> 0 | K126: =SUMIF($D$26:$D$124,$D126,K$26:K$124) -> 0 | L126: =SUMIF($D$26:$D$124,$D126,L$26:L$124) -> 0 | ... N126: =SUMIF($D$26:$D$124,$D126,N$26:N$124) -> 142635.61
D127: Fertilizers | E127: =SUMIF($D$26:$D$124,$D127,E$26:E$124) -> 22184156 | F127: =SUMIF($D$26:$D$124,$D127,F$26:F$124) -> 3123532.3 | G127: =SUMIF($D$26:$D$124,$D127,G$26:G$124) -> 25307689 | H127: =SUMIF($D$26:$D$124,$D127,H$26:H$124) -> 0 | I127: =SUMIF($D$26:$D$124,$D127,I$26:I$124) -> 10476409 | J127: =SUMIF($D$26:$D$124,$D127,J$26:J$124) -> 0 | K127: =SUMIF($D$26:$D$124,$D127,K$26:K$124) -> 0 | L127: =SUMIF($D$26:$D$124,$D127,L$26:L$124) -> 10476409 | ... N127: =SUMIF($D$26:$D$124,$D127,N$26:N$124) -> 329327.91
...

Sheet freight debit notes
D1: =SUBTOTAL(9,D3:D999) -> 154983.12 | Q1: 46197
A2: CODPARC | B2: NOMEPARC | C2: CNPJ | D2: Valor | E2: NUFIN | F2: DTVENC | G2: DHBAIXA | H2: AD_BU | I2: NOME_BU | J2: NUMNOTA | K2: DTENTSAI | L2: CODNAT | M2: DESCRNAT | N2: CODTIPOPER | O2: OPERACAO | P2: Grupo | Q2: Dias vencidos
A3: 1787 | B3: MOSAIC - UBERABA (CIU1) | C3: 33.931.486/0014-55 | D3: 3600 | E3: 1246031589 | F3: 44784 | H3: 1 | I3: Adtives | J3: 1246031589 | K3: 44769 | L3: 3041000 | M3: FRETES DIVERSOS | N3: 46 | O3: FINANCEIRO GERAL | P3: GRUPO MOSAIC FERTILIZANTES P K LTDA | Q3: =$Q$1-F3 -> 1413
A4: 1787 | B4: MOSAIC - UBERABA (CIU1) | C4: 33.931.486/0014-55 | D4: 2700 | E4: 1246055596 | F4: 44889 | H4: 1 | I4: Adtives | J4: 1246055596 | K4: 44889 | L4: 3041000 | M4: FRETES DIVERSOS | N4: 46 | O4: FINANCEIRO GERAL | P4: GRUPO MOSAIC FERTILIZANTES P K LTDA | Q4: =$Q$1-F4 -> 1308
A5: 1788 | B5: MOSAIC - UBERABA (CIU2) | C5: 33.931.486/0021-84 | D5: 5400 | E5: 1246055599 | F5: 44889 | H5: 1 | I5: Adtives | J5: 1246055599 | K5: 44889 | L5: 3041000 | M5: FRETES DIVERSOS | N5: 46 | O5: FINANCEIRO GERAL | P5: GRUPO MOSAIC FERTILIZANTES P K LTDA | Q5: =$Q$1-F5 -> 1308
A6: 1788 | B6: MOSAIC - UBERABA (CIU2) | C6: 33.931.486/0021-84 | D6: 1200 | E6: 1246190701 | F6: 45674 | H6: 1 | I6: Adtives | J6: 1246190701 | K6: 45659 | L6: 3041000 | M6: FRETES DIVERSOS | N6: 46 | O6: FINANCEIRO GERAL | P6: GRUPO MOSAIC FERTILIZANTES P K LTDA | Q6: =$Q$1-F6 -> 523
A7: 1789 | B7: MOSAIC - ARAXA (CMA) | C7: 33.931.486/0019-60 | D7: 2700 | E7: 1246120461 | F7: 45294 | H7: 1 | I7: Adtives | J7: 191223 | K7: 45279 | L7: 3041000 | M7: FRETES DIVERSOS | N7: 46 | O7: FINANCEIRO GERAL | P7: GRUPO MOSAIC FERTILIZANTES P K LTDA | Q7: =$Q$1-F7 -> 903
A8: 1789 | B8: MOSAIC - ARAXA (CMA) | C8: 33.931.486/0019-60 | D8: 900 | E8: 1246146095 | F8: 45428 | H8: 1 | I8: Adtives | J8: 1246120461 | K8: 45428 | L8: 3041000 | M8: FRETES DIVERSOS | N8: 46 | O8: FINANCEIRO GERAL | P8: GRUPO MOSAIC FERTILIZANTES P K LTDA | Q8: =$Q$1-F8 -> 769
A9: 43 | B9: CIBRA - CAMACARI | C9: 00.117.842/0001-28 | D9: 2400 | E9: 1246271921 | F9: 46147 | H9: 1 | I9: Adtives | J9: 1246271921 | K9: 46132 | L9: 3042200 | M9: DIÁRIAS E ESTADIA DE MOTORISTAS | N9: 46 | O9: FINANCEIRO GERAL | P9: GRUPO CIBRA | Q9: =$Q$1-F9 -> 50
A10: 1159 | B10: YARA - RIO GRANDE | C10: 92.660.604/0013-16 | D10: 1800 | E10: 1246087936 | F10: 45112 | H10: 1 | I10: Adtives | J10: 1246087936 | K10: 45097 | L10: 3041000 | M10: FRETES DIVERSOS | N10: 46 | O10: FINANCEIRO GERAL | P10: GRUPO YARA | Q10: =$Q$1-F10 -> 1085
A11: 1159 | B11: YARA - RIO GRANDE | C11: 92.660.604/0013-16 | D11: 2700 | E11: 1246087941 | F11: 45112 | H11: 1 | I11: Adtives | J11: 1246087941 | K11: 45097 | L11: 3041000 | M11: FRETES DIVERSOS | N11: 46 | O11: FINANCEIRO GERAL | P11: GRUPO YARA | Q11: =$Q$1-F11 -> 1085
A12: 1159 | B12: YARA - RIO GRANDE | C12: 92.660.604/0013-16 | D12: 1800 | E12: 1246087939 | F12: 45112 | H12: 1 | I12: Adtives | J12: 1246087939 | K12: 45097 | L12: 3041000 | M12: FRETES DIVERSOS | N12: 46 | O12: FINANCEIRO GERAL | P12: GRUPO YARA | Q12: =$Q$1-F12 -> 1085
A13: 1159 | B13: YARA - RIO GRANDE | C13: 92.660.604/0013-16 | D13: 1800 | E13: 1246087937 | F13: 45112 | H13: 1 | I13: Adtives | J13: 1246087937 | K13: 45097 | L13: 3041000 | M13: FRETES DIVERSOS | N13: 46 | O13: FINANCEIRO GERAL | P13: GRUPO YARA | Q13: =$Q$1-F13 -> 1085
A14: 1159 | B14: YARA - RIO GRANDE | C14: 92.660.604/0013-16 | D14: 1800 | E14: 1246087943 | F14: 45112 | H14: 1 | I14: Adtives | J14: 1246087943 | K14: 45097 | L14: 3041000 | M14: FRETES DIVERSOS | N14: 46 | O14: FINANCEIRO GERAL | P14: GRUPO YARA | Q14: =$Q$1-F14 -> 1085
... A49: 7022 | B49: STRATOS - ROSARIO DO CATETE | C49: 31.009.644/0001-74 | D49: 1800 | E49: 1246054442 | F49: 44897 | H49: 1 | I49: Adtives | J49: 1246054442 | K49: 44882 | L49: 3041000 | M49: FRETES DIVERSOS | N49: 46 | O49: FINANCEIRO GERAL | P49: STRATOS - ROSARIO DO CATETE | Q49: =$Q$1-F49 -> 1300
Q50: =$Q$1-F50 -> 46197
Q51: =$Q$1-F51 -> 46197
Q52: =$Q$1-F52 -> 46197
Q53: =$Q$1-F53 -> 46197
Q54: =$Q$1-F54 -> 46197

Sheet Data total
D1: =SUBTOTAL(9,D3:D1079) -> 64126237 | E1: ='Data Additive'!D1+'Data Fertilizers'!D1+'Data International'!D1 -> 63971254 | F1: ='Data Additive'!D1+'Data Fertilizers'!D1+'Data International'!D1+'freight debit notes'!D1 -> 64126237 | G1: =D1-F1 -> 0 | R1: 46197
A2: CODPARC | B2: NOMEPARC | C2: CNPJ | D2: Valor | E2: NUFIN | F2: DTVENC | G2: DHBAIXA | H2: AD_BU | I2: NOME_BU | J2: NUMNOTA | K2: DTENTSAI | L2: CODNAT | M2: DESCRNAT | N2: CODTIPOPER | O2: OPERACAO | P2: Grupo | Q2: Dias vencidos
A3: 1787 | B3: MOSAIC - UBERABA (CIU1) | C3: 33.931.486/0014-55 | D3: 3600 | E3: 1246031589 | F3: 44784 | H3: 1 | I3: Adtives | J3: 1246031589 | K3: 44769 | L3: 3041000 | M3: FRETES DIVERSOS | N3: 46 | O3: FINANCEIRO GERAL | P3: GRUPO MOSAIC FERTILIZANTES P K LTDA | Q3: =$R$1-F3 -> 1413 | R3: =_xlfn.XLOOKUP(E3,'Data Additive'!E:E,'Data Additive'!E:E,0) -> 0
A4: 1787 | B4: MOSAIC - UBERABA (CIU1) | C4: 33.931.486/0014-55 | D4: 2700 | E4: 1246055596 | F4: 44889 | H4: 1 | I4: Adtives | J4: 1246055596 | K4: 44889 | L4: 3041000 | M4: FRETES DIVERSOS | N4: 46 | O4: FINANCEIRO GERAL | P4: GRUPO MOSAIC FERTILIZANTES P K LTDA | Q4: =$R$1-F4 -> 1308 | R4: =_xlfn.XLOOKUP(E4,'Data Additive'!E:E,'Data Additive'!E:E,0) -> 0
A5: 1788 | B5: MOSAIC - UBERABA (CIU2) | C5: 33.931.486/0021-84 | D5: 5400 | E5: 1246055599 | F5: 44889 | H5: 1 | I5: Adtives | J5: 1246055599 | K5: 44889 | L5: 3041000 | M5: FRETES DIVERSOS | N5: 46 | O5: FINANCEIRO GERAL | P5: GRUPO MOSAIC FERTILIZANTES P K LTDA | Q5: =$R$1-F5 -> 1308 | R5: =_xlfn.XLOOKUP(E5,'Data Additive'!E:E,'Data Additive'!E:E,0) -> 0
A6: 1788 | B6: MOSAIC - UBERABA (CIU2) | C6: 33.931.486/0021-84 | D6: 1200 | E6: 1246190701 | F6: 45674 | H6: 1 | I6: Adtives | J6: 1246190701 | K6: 45659 | L6: 3041000 | M6: FRETES DIVERSOS | N6: 46 | O6: FINANCEIRO GERAL | P6: GRUPO MOSAIC FERTILIZANTES P K LTDA | Q6: =$R$1-F6 -> 523 | R6: =_xlfn.XLOOKUP(E6,'Data Additive'!E:E,'Data Additive'!E:E,0) -> 0
A7: 1789 | B7: MOSAIC - ARAXA (CMA) | C7: 33.931.486/0019-60 | D7: 2700 | E7: 1246120461 | F7: 45294 | H7: 1 | I7: Adtives | J7: 191223 | K7: 45279 | L7: 3041000 | M7: FRETES DIVERSOS | N7: 46 | O7: FINANCEIRO GERAL | P7: GRUPO MOSAIC FERTILIZANTES P K LTDA | Q7: =$R$1-F7 -> 903 | R7: =_xlfn.XLOOKUP(E7,'Data Additive'!E:E,'Data Additive'!E:E,0) -> 0
A8: 1789 | B8: MOSAIC - ARAXA (CMA) | C8: 33.931.486/0019-60 | D8: 900 | E8: 1246146095 | F8: 45428 | H8: 1 | I8: Adtives | J8: 1246120461 | K8: 45428 | L8: 3041000 | M8: FRETES DIVERSOS | N8: 46 | O8: FINANCEIRO GERAL | P8: GRUPO MOSAIC FERTILIZANTES P K LTDA | Q8: =$R$1-F8 -> 769 | R8: =_xlfn.XLOOKUP(E8,'Data Additive'!E:E,'Data Additive'!E:E,0) -> 0
A9: 43 | B9: CIBRA - CAMACARI | C9: 00.117.842/0001-28 | D9: 2400 | E9: 1246271921 | F9: 46147 | H9: 1 | I9: Adtives | J9: 1246271921 | K9: 46132 | L9: 3042200 | M9: DIÁRIAS E ESTADIA DE MOTORISTAS | N9: 46 | O9: FINANCEIRO GERAL | P9: GRUPO CIBRA | Q9: =$R$1-F9 -> 50 | R9: =_xlfn.XLOOKUP(E9,'Data Additive'!E:E,'Data Additive'!E:E,0) -> 0
A10: 1159 | B10: YARA - RIO GRANDE | C10: 92.660.604/0013-16 | D10: 1800 | E10: 1246087936 | F10: 45112 | H10: 1 | I10: Adtives | J10: 1246087936 | K10: 45097 | L10: 3041000 | M10: FRETES DIVERSOS | N10: 46 | O10: FINANCEIRO GERAL | P10: GRUPO YARA | Q10: =$R$1-F10 -> 1085 | R10: =_xlfn.XLOOKUP(E10,'Data Additive'!E:E,'Data Additive'!E:E,0) -> 0
A11: 1159 | B11: YARA - RIO GRANDE | C11: 92.660.604/0013-16 | D11: 2700 | E11: 1246087941 | F11: 45112 | H11: 1 | I11: Adtives | J11: 1246087941 | K11: 45097 | L11: 3041000 | M11: FRETES DIVERSOS | N11: 46 | O11: FINANCEIRO GERAL | P11: GRUPO YARA | Q11: =$R$1-F11 -> 1085 | R11: =_xlfn.XLOOKUP(E11,'Data Additive'!E:E,'Data Additive'!E:E,0) -> 0
A12: 1159 | B12: YARA - RIO GRANDE | C12: 92.660.604/0013-16 | D12: 1800 | E12: 1246087939 | F12: 45112 | H12: 1 | I12: Adtives | J12: 1246087939 | K12: 45097 | L12: 3041000 | M12: FRETES DIVERSOS | N12: 46 | O12: FINANCEIRO GERAL | P12: GRUPO YARA | Q12: =$R$1-F12 -> 1085 | R12: =_xlfn.XLOOKUP(E12,'Data Additive'!E:E,'Data Additive'!E:E,0) -> 0
A13: 1159 | B13: YARA - RIO GRANDE | C13: 92.660.604/0013-16 | D13: 1800 | E13: 1246087937 | F13: 45112 | H13: 1 | I13: Adtives | J13: 1246087937 | K13: 45097 | L13: 3041000 | M13: FRETES DIVERSOS | N13: 46 | O13: FINANCEIRO GERAL | P13: GRUPO YARA | Q13: =$R$1-F13 -> 1085 | R13: =_xlfn.XLOOKUP(E13,'Data Additive'!E:E,'Data Additive'!E:E,0) -> 0
A14: 1159 | B14: YARA - RIO GRANDE | C14: 92.660.604/0013-16 | D14: 1800 | E14: 1246087943 | F14: 45112 | H14: 1 | I14: Adtives | J14: 1246087943 | K14: 45097 | L14: 3041000 | M14: FRETES DIVERSOS | N14: 46 | O14: FINANCEIRO GERAL | P14: GRUPO YARA | Q14: =$R$1-F14 -> 1085 | R14: =_xlfn.XLOOKUP(E14,'Data Additive'!E:E,'Data Additive'!E:E,0) -> 0
... A327: 7022 | B327: STRATOS - ROSARIO DO CATETE | C327: 31.009.644/0001-74 | D327: 1800 | E327: 1246054442 | F327: 44897 | H327: 1 | I327: Adtives | J327: 1246054442 | K327: 44882 | L327: 3041000 | M327: FRETES DIVERSOS | N327: 46 | O327: FINANCEIRO GERAL | P327: STRATOS - ROSARIO DO CATETE | Q327: =$R$1-F327 -> 1300 | R327: =_xlfn.XLOOKUP(E327,'Data Additive'!E:E,'Data Additive'!E:E,0) -> 0
A328: 16189 | B328: ARSLOG SOLUCOES EM TRANSPORTE | C328: 05.765.626/0001-02 | D328: 49440 | E328: 1246261824 | F328: 46087 | I328: Não encontrado | J328: 1246261824 | K328: 46055 | L328: 7240000 | M328: PERDA DE MERCADORIA COM SINISTRO | N328: 46 | O328: FINANCEIRO GERAL | P328: ARSLOG SOLUCOES EM TRANSPORTE | Q328: =$R$1-F328 -> 110 | R328: =_xlfn.XLOOKUP(E328,'Data Additive'!E:E,'Data Additive'!E:E,0) -> 1246261824
A329: 7 | B329: START QUIMICA - 22.685.341/0006-95 | C329: 22.685.341/0006-95 | D329: 861.6 | E329: 1246278022 | F329: 46211 | H329: 2 | I329: Fertilizers | J329: 2996 | K329: 46176 | L329: 1010100 | M329: VENDAS MERCADO INTERNO | N329: 39 | O329: REVENDA - NFE | P329: START QUIMICA - 22.685.341/0006-95 | Q329: =$R$1-F329 -> -14 | R329: =_xlfn.XLOOKUP(E329,'Data Additive'!E:E,'Data Additive'!E:E,0) -> 0
A330: 3297 | B330: MACROSOURCE PERU S.R.L. | C330: ..- | D330: 49956.68 | E330: 1246271355 | F330: 46200 | H330: 1 | I330: Adtives | J330: 11123 | K330: 46126 | L330: 1010200 | M330: VENDAS MERCADO EXTERNO | N330: 40 | O330: VENDA - NFE (EXPORTAÇÃO) | P330: MACROSOURCE PERU S.R.L. | Q330: =$R$1-F330 -> -3 | R330: =_xlfn.XLOOKUP(E330,'Data Additive'!E:E,'Data Additive'!E:E,0) -> 0
A331: 2680 | B331: FERMAGRI S.A - EQUADOR | C331: ..- | D331: 175275.24 | E331: 1246272069 | F331: 46194 | H331: 1 | I331: Adtives | J331: 11191 | K331: 46134 | L331: 1010200 | M331: VENDAS MERCADO EXTERNO | N331: 40 | O331: VENDA - NFE (EXPORTAÇÃO) | P331: FERMAGRI S.A - EQUADOR | Q331: =$R$1-F331 -> 3 | R331: =_xlfn.XLOOKUP(E331,'Data Additive'!E:E,'Data Additive'!E:E,0) -> 0
A332: 2696 | B332: MOSAIC FERTILIZANTES PARAGUAY S.R.L. | C332: ..- | D332: 94148.95 | E332: 1246279520 | F332: 46278 | H332: 1 | I332: Adtives | J332: 11712 | K332: 46188 | L332: 1010200 | M332: VENDAS MERCADO EXTERNO | N332: 40 | O332: VENDA - NFE (EXPORTAÇÃO) | P332: MOSAIC FERTILIZANTES PARAGUAY S.R.L. | Q332: =$R$1-F332 -> -81 | R332: =_xlfn.XLOOKUP(E332,'Data Additive'!E:E,'Data Additive'!E:E,0) -> 0
A333: 2696 | B333: MOSAIC FERTILIZANTES PARAGUAY S.R.L. | C333: ..- | D333: 91784.41 | E333: 1246274791 | F333: 46245 | H333: 1 | I333: Adtives | J333: 11378 | K333: 46155 | L333: 1010200 | M333: VENDAS MERCADO EXTERNO | N333: 40 | O333: VENDA - NFE (EXPORTAÇÃO) | P333: MOSAIC FERTILIZANTES PARAGUAY S.R.L. | Q333: =$R$1-F333 -> -48 | R333: =_xlfn.XLOOKUP(E333,'Data Additive'!E:E,'Data Additive'!E:E,0) -> 0
A334: 2696 | B334: MOSAIC FERTILIZANTES PARAGUAY S.R.L. | C334: ..- | D334: 118833.22 | E334: 1246278569 | F334: 46271 | H334: 1 | I334: Adtives | J334: 11641 | K334: 46181 | L334: 1010200 | M334: VENDAS MERCADO EXTERNO | N334: 40 | O334: VENDA - NFE (EXPORTAÇÃO) | P334: MOSAIC FERTILIZANTES PARAGUAY S.R.L. | Q334: =$R$1-F334 -> -74 | R334: =_xlfn.XLOOKUP(E334,'Data Additive'!E:E,'Data Additive'!E:E,0) -> 0
A335: 2696 | B335: MOSAIC FERTILIZANTES PARAGUAY S.R.L. | C335: ..- | D335: 116719.31 | E335: 1246277374 | F335: 46261 | H335: 1 | I335: Adtives | J335: 11551 | K335: 46171 | L335: 1010200 | M335: VENDAS MERCADO EXTERNO | N335: 40 | O335: VENDA - NFE (EXPORTAÇÃO) | P335: MOSAIC FERTILIZANTES PARAGUAY S.R.L. | Q335: =$R$1-F335 -> -64 | R335: =_xlfn.XLOOKUP(E335,'Data Additive'!E:E,'Data Additive'!E:E,0) -> 0
A336: 2696 | B336: MOSAIC FERTILIZANTES PARAGUAY S.R.L. | C336: ..- | D336: 116211.91 | E336: 1246278291 | F336: 46268 | H336: 1 | I336: Adtives | J336: 11599 | K336: 46178 | L336: 1010200 | M336: VENDAS MERCADO EXTERNO | N336: 40 | O336: VENDA - NFE (EXPORTAÇÃO) | P336: MOSAIC FERTILIZANTES PARAGUAY S.R.L. | Q336: =$R$1-F336 -> -71 | R336: =_xlfn.XLOOKUP(E336,'Data Additive'!E:E,'Data Additive'!E:E,0) -> 0
A337: 2645 | B337: ANAGRA - CHILE | C337: ..- | D337: 143222.74 | E337: 1246277225 | F337: 46200 | H337: 1 | I337: Adtives | J337: 11529 | K337: 46170 | L337: 1010200 | M337: VENDAS MERCADO EXTERNO | N337: 40 | O337: VENDA - NFE (EXPORTAÇÃO) | P337: ANAGRA - CHILE | Q337: =$R$1-F337 -> -3 | R337: =_xlfn.XLOOKUP(E337,'Data Additive'!E:E,'Data Additive'!E:E,0) -> 0
A338: 2651 | B338: AGROBROKERS - COLÔMBIA | C338: ..- | D338: 132309.33 | E338: 1246278533 | F338: 46241 | H338: 1 | I338: Adtives | J338: 3002 | K338: 46181 | L338: 1010200 | M338: VENDAS MERCADO EXTERNO | N338: 40 | O338: VENDA - NFE (EXPORTAÇÃO) | P338: AGROBROKERS - COLÔMBIA | Q338: =$R$1-F338 -> -44 | R338: =_xlfn.XLOOKUP(E338,'Data Additive'!E:E,'Data Additive'!E:E,0) -> 0
A339: 2652 | B339: FERTIMAX PARAGUAY | C339: ..- | D339: 166161.39 | E339: 1246279339 | F339: 46215 | H339: 1 | I339: Adtives | J339: 11691 | K339: 46185 | L339: 1010200 | M339: VENDAS MERCADO EXTERNO | N339: 40 | O339: VENDA - NFE (EXPORTAÇÃO) | P339: FERTIMAX PARAGUAY | Q339: =$R$1-F339 -> -18 | R339: =_xlfn.XLOOKUP(E339,'Data Additive'!E:E,'Data Additive'!E:E,0) -> 0
A340: 2287 | B340: BUNGE PARAGUAY S.A | C340: 99.999.999/9999-99 | D340: 152321.99 | E340: 1246279865 | F340: 46220 | H340: 1 | I340: Adtives | J340: 11738 | K340: 46190 | L340: 1010200 | M340: VENDAS MERCADO EXTERNO | N340: 40 | O340: VENDA - NFE (EXPORTAÇÃO) | P340: BUNGE PARAGUAY S.A | Q340: =$R$1-F340 -> -23 | R340: =_xlfn.XLOOKUP(E340,'Data Additive'!E:E,'Data Additive'!E:E,0) -> 0
... A359: 12031 | B359: EVOAGRO NUTRICION S.A.S - COLOMBIA | C359: ..- | D359: 164297.05 | E359: 1246275610 | F359: 46220 | H359: 1 | I359: Adtives | J359: 2948 | K359: 46160 | L359: 1010200 | M359: VENDAS MERCADO EXTERNO | N359: 40 | O359: VENDA - NFE (EXPORTAÇÃO) | P359: EVOAGRO NUTRICION S.A.S - COLOMBIA | Q359: =$R$1-F359 -> -23 | R359: =_xlfn.XLOOKUP(E359,'Data Additive'!E:E,'Data Additive'!E:E,0) -> 0
A360: 13330 | B360: ORGANITEC - PARAGUAY | C360: 800.909.976- | D360: 853.24 | E360: 1246272264 | F360: 46148 | I360: Não encontrado | J360: 11057 | K360: 46118 | L360: 1010200 | M360: VENDAS MERCADO EXTERNO | N360: 40 | O360: VENDA - NFE (EXPORTAÇÃO) | P360: ORGANITEC - PARAGUAY | Q360: =$R$1-F360 -> 49 | R360: =_xlfn.XLOOKUP(E360,'Data Additive'!E:E,'Data Additive'!E:E,0) -> 0
A361: 13330 | B361: ORGANITEC - PARAGUAY | C361: 800.909.976- | D361: 527.28 | E361: 1246238356 | F361: 45927 | I361: Não encontrado | J361: 9092 | K361: 45897 | L361: 1010200 | M361: VENDAS MERCADO EXTERNO | N361: 40 | O361: VENDA - NFE (EXPORTAÇÃO) | P361: ORGANITEC - PARAGUAY | Q361: =$R$1-F361 -> 270 | R361: =_xlfn.XLOOKUP(E361,'Data Additive'!E:E,'Data Additive'!E:E,0) -> 0
A362: 15543 | B362: GOTLAND EQUADOR (SOLINAG) | C362: 19.512.950/9001- | D362: 45718.46 | E362: 1246264533 | F362: 46181 | H362: 1 | I362: Adtives | J362: 10745 | K362: 46076 | L362: 1010200 | M362: VENDAS MERCADO EXTERNO | N362: 40 | O362: VENDA - NFE (EXPORTAÇÃO) | P362: GOTLAND EQUADOR (SOLINAG) | Q362: =$R$1-F362 -> 16 | R362: =_xlfn.XLOOKUP(E362,'Data Additive'!E:E,'Data Additive'!E:E,0) -> 0
A363: 15543 | B363: GOTLAND EQUADOR (SOLINAG) | C363: 19.512.950/9001- | D363: 133756.12 | E363: 1246277124 | F363: 46259 | H363: 1 | I363: Adtives | J363: 11522 | K363: 46169 | L363: 1010200 | M363: VENDAS MERCADO EXTERNO | N363: 40 | O363: VENDA - NFE (EXPORTAÇÃO) | P363: GOTLAND EQUADOR (SOLINAG) | Q363: =$R$1-F363 -> -62 | R363: =_xlfn.XLOOKUP(E363,'Data Additive'!E:E,'Data Additive'!E:E,0) -> 0
A364: 7060 | B364: AGROVIVA | C364: 19.195.655/0001-90 | D364: 202489.44 | E364: 1246233024 | F364: 46264 | H364: 2 | I364: Fertilizers | J364: 9046 | K364: 45895 | L364: 1010100 | M364: VENDAS MERCADO INTERNO | N364: 56 | O364: VENDA A ORDEM | P364: AGROVIVA | Q364: =$R$1-F364 -> -67 | R364: =_xlfn.XLOOKUP(E364,'Data Additive'!E:E,'Data Additive'!E:E,0) -> 0
A365: 7060 | B365: AGROVIVA | C365: 19.195.655/0001-90 | D365: 210926.5 | E365: 1246232491 | F365: 46264 | H365: 2 | I365: Fertilizers | J365: 9006 | K365: 45891 | L365: 1010100 | M365: VENDAS MERCADO INTERNO | N365: 56 | O365: VENDA A ORDEM | P365: AGROVIVA | Q365: =$R$1-F365 -> -67 | R365: =_xlfn.XLOOKUP(E365,'Data Additive'!E:E,'Data Additive'!E:E,0) -> 0
A366: 7060 | B366: AGROVIVA | C366: 19.195.655/0001-90 | D366: 135891.48 | E366: 1246233319 | F366: 46266 | H366: 2 | I366: Fertilizers | J366: 9076 | K366: 45896 | L366: 1010100 | M366: VENDAS MERCADO INTERNO | N366: 56 | O366: VENDA A ORDEM | P366: AGROVIVA | Q366: =$R$1-F366 -> -69 | R366: =_xlfn.XLOOKUP(E366,'Data Additive'!E:E,'Data Additive'!E:E,0) -> 0
A367: 7060 | B367: AGROVIVA | C367: 19.195.655/0001-90 | D367: 160304.14 | E367: 1246232724 | F367: 46264 | H367: 2 | I367: Fertilizers | J367: 9023 | K367: 45894 | L367: 1010100 | M367: VENDAS MERCADO INTERNO | N367: 56 | O367: VENDA A ORDEM | P367: AGROVIVA | Q367: =$R$1-F367 -> -67 | R367: =_xlfn.XLOOKUP(E367,'Data Additive'!E:E,'Data Additive'!E:E,0) -> 0
A368: 7060 | B368: AGROVIVA | C368: 19.195.655/0001-90 | D368: 134992.96 | E368: 1246233318 | F368: 46265 | H368: 2 | I368: Fertilizers | J368: 9075 | K368: 45896 | L368: 1010100 | M368: VENDAS MERCADO INTERNO | N368: 56 | O368: VENDA A ORDEM | P368: AGROVIVA | Q368: =$R$1-F368 -> -68 | R368: =_xlfn.XLOOKUP(E368,'Data Additive'!E:E,'Data Additive'!E:E,0) -> 0
A369: 10413 | B369: BUNGE - SANTOS | C369: 84.046.101/0542-85 | D369: 78993 | E369: 1246279827 | F369: 46218 | H369: 1 | I369: Adtives | J369: 11733 | K369: 46189 | L369: 1010100 | M369: VENDAS MERCADO INTERNO | N369: 56 | O369: VENDA A ORDEM | P369: BUNGE - SANTOS | Q369: =$R$1-F369 -> -21 | R369: =_xlfn.XLOOKUP(E369,'Data Additive'!E:E,'Data Additive'!E:E,0) -> 1246279827
A370: 10413 | B370: BUNGE - SANTOS | C370: 84.046.101/0542-85 | D370: 79019.2 | E370: 1246278424 | F370: 46218 | H370: 1 | I370: Adtives | J370: 11626 | K370: 46178 | L370: 1010100 | M370: VENDAS MERCADO INTERNO | N370: 56 | O370: VENDA A ORDEM | P370: BUNGE - SANTOS | Q370: =$R$1-F370 -> -21 | R370: =_xlfn.XLOOKUP(E370,'Data Additive'!E:E,'Data Additive'!E:E,0) -> 1246278424
A371: 10677 | B371: MARCELO HONORIO DE CARVALHO RAMOS | C371: 007.511.136-54 | D371: 581 | E371: 1246272911 | F371: 46175 | I371: Não encontrado | J371: 11244 | K371: 46140 | L371: 4011600 | M371: APARELHOS DE INFORMÁTICA | N371: 244 | O371: VENDA DE IMOBILIZADO SEM ICMS | P371: MARCELO HONORIO DE CARVALHO RAMOS | Q371: =$R$1-F371 -> 22 | R371: =_xlfn.XLOOKUP(E371,'Data Additive'!E:E,'Data Additive'!E:E,0) -> 1246272911
A372: 10677 | B372: MARCELO HONORIO DE CARVALHO RAMOS | C372: 007.511.136-54 | D372: 581 | E372: 1246272912 | F372: 46200 | I372: Não encontrado | J372: 11244 | K372: 46140 | L372: 4011600 | M372: APARELHOS DE INFORMÁTICA | N372: 244 | O372: VENDA DE IMOBILIZADO SEM ICMS | P372: MARCELO HONORIO DE CARVALHO RAMOS | Q372: =$R$1-F372 -> -3 | R372: =_xlfn.XLOOKUP(E372,'Data Additive'!E:E,'Data Additive'!E:E,0) -> 1246272912
A373: 10677 | B373: MARCELO HONORIO DE CARVALHO RAMOS | C373: 007.511.136-54 | D373: 581 | E373: 1246272913 | F373: 46230 | I373: Não encontrado | J373: 11244 | K373: 46140 | L373: 4011600 | M373: APARELHOS DE INFORMÁTICA | N373: 244 | O373: VENDA DE IMOBILIZADO SEM ICMS | P373: MARCELO HONORIO DE CARVALHO RAMOS | Q373: =$R$1-F373 -> -33 | R373: =_xlfn.XLOOKUP(E373,'Data Additive'!E:E,'Data Additive'!E:E,0) -> 1246272913
A374: 14094 | B374: KLEYTON DUARTE SOARES | C374: 014.415.101-41 | D374: 100 | E374: 1246154530 | F374: 45474 | I374: Não encontrado | J374: 4088 | K374: 45474 | L374: 4010300 | M374: MÓVEIS E UTENSÍLIOS | N374: 244 | O374: VENDA DE IMOBILIZADO SEM ICMS | P374: KLEYTON DUARTE SOARES | Q374: =$R$1-F374 -> 723 | R374: =_xlfn.XLOOKUP(E374,'Data Additive'!E:E,'Data Additive'!E:E,0) -> 1246154530
A375: 13873 | B375: MARIA JOSE DA SILVA | C375: 844.462.855-72 | D375: 50 | E375: 1246166396 | F375: 45525 | I375: Não encontrado | J375: 4854 | K375: 45525 | L375: 4010300 | M375: MÓVEIS E UTENSÍLIOS | N375: 244 | O375: VENDA DE IMOBILIZADO SEM ICMS | P375: MARIA JOSE DA SILVA | Q375: =$R$1-F375 -> 672 | R375: =_xlfn.XLOOKUP(E375,'Data Additive'!E:E,'Data Additive'!E:E,0) -> 1246166396
A376: 14106 | B376: SEU LIXO | C376: 50.454.037/0001-68 | D376: 300 | E376: 1246182736 | F376: 45625 | I376: Não encontrado | J376: 6092 | K376: 45610 | L376: 1020400 | M376: VENDA DE SUCATAS | N376: 136 | O376: VENDA DE SUCATAS | P376: SEU LIXO | Q376: =$R$1-F376 -> 572 | R376: =_xlfn.XLOOKUP(E376,'Data Additive'!E:E,'Data Additive'!E:E,0) -> 1246182736
A377: 707 | B377: TERRA FERTILIZANTES LTDA - ARAXÁ | C377: 10.482.668/0001-76 | D377: 40320 | E377: 1246146706 | F377: 45461 | H377: 1 | I377: Adtives | J377: 3619 | K377: 45433 | L377: 1010100 | M377: VENDAS MERCADO INTERNO | N377: 161 | O377: VENDA PROD. INDUSTRIALIZADO - NFE | P377: TERRA FERTILIZANTES LTDA - ARAXÁ | Q377: =$R$1-F377 -> 736 | R377: =_xlfn.XLOOKUP(E377,'Data Additive'!E:E,'Data Additive'!E:E,0) -> 1246146706
A378: 707 | B378: TERRA FERTILIZANTES LTDA - ARAXÁ | C378: 10.482.668/0001-76 | D378: 14640 | E378: 1246145696 | F378: 45454 | H378: 1 | I378: Adtives | J378: 3538 | K378: 45426 | L378: 1010100 | M378: VENDAS MERCADO INTERNO | N378: 161 | O378: VENDA PROD. INDUSTRIALIZADO - NFE | P378: TERRA FERTILIZANTES LTDA - ARAXÁ | Q378: =$R$1-F378 -> 743 | R378: =_xlfn.XLOOKUP(E378,'Data Additive'!E:E,'Data Additive'!E:E,0) -> 1246145696
A379: 707 | B379: TERRA FERTILIZANTES LTDA - ARAXÁ | C379: 10.482.668/0001-76 | D379: 43920 | E379: 1246148035 | F379: 45469 | H379: 1 | I379: Adtives | J379: 3722 | K379: 45441 | L379: 1010100 | M379: VENDAS MERCADO INTERNO | N379: 161 | O379: VENDA PROD. INDUSTRIALIZADO - NFE | P379: TERRA FERTILIZANTES LTDA - ARAXÁ | Q379: =$R$1-F379 -> 728 | R379: =_xlfn.XLOOKUP(E379,'Data Additive'!E:E,'Data Additive'!E:E,0) -> 1246148035
A380: 707 | B380: TERRA FERTILIZANTES LTDA - ARAXÁ | C380: 10.482.668/0001-76 | D380: 36600 | E380: 1246146938 | F380: 45462 | H380: 1 | I380: Adtives | J380: 3637 | K380: 45434 | L380: 1010100 | M380: VENDAS MERCADO INTERNO | N380: 161 | O380: VENDA PROD. INDUSTRIALIZADO - NFE | P380: TERRA FERTILIZANTES LTDA - ARAXÁ | Q380: =$R$1-F380 -> 735 | R380: =_xlfn.XLOOKUP(E380,'Data Additive'!E:E,'Data Additive'!E:E,0) -> 1246146938
A381: 707 | B381: TERRA FERTILIZANTES LTDA - ARAXÁ | C381: 10.482.668/0001-76 | D381: 33600 | E381: 1246148036 | F381: 45469 | H381: 1 | I381: Adtives | J381: 3723 | K381: 45441 | L381: 1010100 | M381: VENDAS MERCADO INTERNO | N381: 161 | O381: VENDA PROD. INDUSTRIALIZADO - NFE | P381: TERRA FERTILIZANTES LTDA - ARAXÁ | Q381: =$R$1-F381 -> 728 | R381: =_xlfn.XLOOKUP(E381,'Data Additive'!E:E,'Data Additive'!E:E,0) -> 1246148036
A382: 707 | B382: TERRA FERTILIZANTES LTDA - ARAXÁ | C382: 10.482.668/0001-76 | D382: 16800 | E382: 1246141445 | F382: 45433 | H382: 1 | I382: Adtives | J382: 3345 | K382: 45405 | L382: 1010100 | M382: VENDAS MERCADO INTERNO | N382: 161 | O382: VENDA PROD. INDUSTRIALIZADO - NFE | P382: TERRA FERTILIZANTES LTDA - ARAXÁ | Q382: =$R$1-F382 -> 764 | R382: =_xlfn.XLOOKUP(E382,'Data Additive'!E:E,'Data Additive'!E:E,0) -> 1246141445
A383: 707 | B383: TERRA FERTILIZANTES LTDA - ARAXÁ | C383: 10.482.668/0001-76 | D383: 40353.6 | E383: 1246143397 | F383: 45443 | H383: 1 | I383: Adtives | J383: 3448 | K383: 45415 | L383: 1010100 | M383: VENDAS MERCADO INTERNO | N383: 161 | O383: VENDA PROD. INDUSTRIALIZADO - NFE | P383: TERRA FERTILIZANTES LTDA - ARAXÁ | Q383: =$R$1-F383 -> 754 | R383: =_xlfn.XLOOKUP(E383,'Data Additive'!E:E,'Data Additive'!E:E,0) -> 1246143397
A384: 1462 | B384: AURORA MINERAÇÃO LTDA | C384: 02.964.101/0001-08 | D384: 38067.25 | E384: 1246274419 | F384: 46213 | H384: 1 | I384: Adtives | J384: 11350 | K384: 46153 | L384: 1010100 | M384: VENDAS MERCADO INTERNO | N384: 161 | O384: VENDA PROD. INDUSTRIALIZADO - NFE | P384: AURORA MINERAÇÃO LTDA | Q384: =$R$1-F384 -> -16 | R384: =_xlfn.XLOOKUP(E384,'Data Additive'!E:E,'Data Additive'!E:E,0) -> 1246274419
A385: 1462 | B385: AURORA MINERAÇÃO LTDA | C385: 02.964.101/0001-08 | D385: 38067.25 | E385: 1246274420 | F385: 46223 | H385: 1 | I385: Adtives | J385: 11350 | K385: 46153 | L385: 1010100 | M385: VENDAS MERCADO INTERNO | N385: 161 | O385: VENDA PROD. INDUSTRIALIZADO - NFE | P385: AURORA MINERAÇÃO LTDA | Q385: =$R$1-F385 -> -26 | R385: =_xlfn.XLOOKUP(E385,'Data Additive'!E:E,'Data Additive'!E:E,0) -> 1246274420
A386: 1462 | B386: AURORA MINERAÇÃO LTDA | C386: 02.964.101/0001-08 | D386: 38160.2 | E386: 1246270126 | F386: 46174 | H386: 1 | I386: Adtives | J386: 11041 | K386: 46114 | L386: 1010100 | M386: VENDAS MERCADO INTERNO | N386: 161 | O386: VENDA PROD. INDUSTRIALIZADO - NFE | P386: AURORA MINERAÇÃO LTDA | Q386: =$R$1-F386 -> 23 | R386: =_xlfn.XLOOKUP(E386,'Data Additive'!E:E,'Data Additive'!E:E,0) -> 1246270126
A387: 1462 | B387: AURORA MINERAÇÃO LTDA | C387: 02.964.101/0001-08 | D387: 38160.2 | E387: 1246270127 | F387: 46184 | H387: 1 | I387: Adtives | J387: 11041 | K387: 46114 | L387: 1010100 | M387: VENDAS MERCADO INTERNO | N387: 161 | O387: VENDA PROD. INDUSTRIALIZADO - NFE | P387: AURORA MINERAÇÃO LTDA | Q387: =$R$1-F387 -> 13 | R387: =_xlfn.XLOOKUP(E387,'Data Additive'!E:E,'Data Additive'!E:E,0) -> 1246270127
A388: 1462 | B388: AURORA MINERAÇÃO LTDA | C388: 02.964.101/0001-08 | D388: 38236.25 | E388: 1246277330 | F388: 46230 | H388: 1 | I388: Adtives | J388: 11543 | K388: 46170 | L388: 1010100 | M388: VENDAS MERCADO INTERNO | N388: 161 | O388: VENDA PROD. INDUSTRIALIZADO - NFE | P388: AURORA MINERAÇÃO LTDA | Q388: =$R$1-F388 -> -33 | R388: =_xlfn.XLOOKUP(E388,'Data Additive'!E:E,'Data Additive'!E:E,0) -> 1246277330
... A649: 16107 | B649: CONNTACTA AGRONEGOCIOS | C649: 54.764.341/0001-62 | D649: 2217.78 | E649: 1246235696 | F649: 46265 | H649: 2 | I649: Fertilizers | J649: 9248 | K649: 45908 | L649: 1010100 | M649: VENDAS MERCADO INTERNO | N649: 161 | O649: VENDA PROD. INDUSTRIALIZADO - NFE | P649: CONNTACTA AGRONEGOCIOS | Q649: =$R$1-F649 -> -68 | R649: =_xlfn.XLOOKUP(E649,'Data Additive'!E:E,'Data Additive'!E:E,0) -> 0
Q650: =$R$1-F650 -> 46197 | R650: =_xlfn.XLOOKUP(E650,'Data Additive'!E:E,'Data Additive'!E:E,0) -> 0
Q651: =$R$1-F651 -> 46197 | R651: =_xlfn.XLOOKUP(E651,'Data Additive'!E:E,'Data Additive'!E:E,0) -> 0
Q652: =$R$1-F652 -> 46197 | R652: =_xlfn.XLOOKUP(E652,'Data Additive'!E:E,'Data Additive'!E:E,0) -> 0
Q653: =$R$1-F653 -> 46197 | R653: =_xlfn.XLOOKUP(E653,'Data Additive'!E:E,'Data Additive'!E:E,0) -> 0
Q654: =$R$1-F654 -> 46197 | R654: =_xlfn.XLOOKUP(E654,'Data Additive'!E:E,'Data Additive'!E:E,0) -> 0
Q655: =$R$1-F655 -> 46197 | R655: =_xlfn.XLOOKUP(E655,'Data Additive'!E:E,'Data Additive'!E:E,0) -> 0
Q656: =$R$1-F656 -> 46197 | R656: =_xlfn.XLOOKUP(E656,'Data Additive'!E:E,'Data Additive'!E:E,0) -> 0
Q657: =$R$1-F657 -> 46197 | R657: =_xlfn.XLOOKUP(E657,'Data Additive'!E:E,'Data Additive'!E:E,0) -> 0
Q658: =$R$1-F658 -> 46197 | R658: =_xlfn.XLOOKUP(E658,'Data Additive'!E:E,'Data Additive'!E:E,0) -> 0
Q659: =$R$1-F659 -> 46197 | R659: =_xlfn.XLOOKUP(E659,'Data Additive'!E:E,'Data Additive'!E:E,0) -> 0
Q660: =$R$1-F660 -> 46197 | R660: =_xlfn.XLOOKUP(E660,'Data Additive'!E:E,'Data Additive'!E:E,0) -> 0
Q661: =$R$1-F661 -> 46197 | R661: =_xlfn.XLOOKUP(E661,'Data Additive'!E:E,'Data Additive'!E:E,0) -> 0
... Q791: =$R$1-F791 -> 46197 | R791: =_xlfn.XLOOKUP(E791,'Data Additive'!E:E,'Data Additive'!E:E,0) -> 0

Sheet Data Additive
D1: =SUBTOTAL(9,$D$3:$D$863) -> 31818331 | R1: 46197
A2: CODPARC | B2: NOMEPARC | C2: CNPJ | D2: Valor | E2: NUFIN | F2: DTVENC | G2: DHBAIXA | H2: AD_BU | I2: NOME_BU | J2: NUMNOTA | K2: DTENTSAI | L2: CODNAT | M2: DESCRNAT | N2: CODTIPOPER | O2: OPERACAO | P2: Grupo | Q2: Dias vencidos
A3: 1257 | B3: MOSAIC - CAMPO GRANDE | C3: 61.156.501/0081-30 | D3: 1980.8 | E3: 1246032946 | F3: 44774 | H3: 1 | I3: Adtives | J3: 17935 | K3: 44714 | L3: 1010100 | M3: VENDAS MERCADO INTERNO | N3: 56 | O3: VENDA A ORDEM | P3: GRUPO MOSAIC FERTILIZANTES DO BRASIL | Q3: =$R$1-F3 -> 1423 | R3: =_xlfn.XLOOKUP(P3,'Painel Additive'!$B:$B,'Painel Additive'!$B:$B,0) -> GRUPO MOSAIC FERTILIZANTES DO BRASIL | S3: =F3-K3 -> 60
A4: 1936 | B4: CIBRA - PARANAGUÁ II | C4: 95.865.572/0024-36 | D4: 40300 | E4: 1246280425 | F4: 46223 | H4: 1 | I4: Adtives | J4: 11779 | K4: 46195 | L4: 1010100 | M4: VENDAS MERCADO INTERNO | N4: 56 | O4: VENDA A ORDEM | P4: GRUPO AGRO INDUSTRIAL SAO LUIZ LTDA | Q4: =$R$1-F4 -> -26 | R4: =_xlfn.XLOOKUP(P4,'Painel Additive'!$B:$B,'Painel Additive'!$B:$B,0) -> GRUPO AGRO INDUSTRIAL SAO LUIZ LTDA | S4: =F4-K4 -> 28
A5: 1936 | B5: CIBRA - PARANAGUÁ II | C5: 95.865.572/0024-36 | D5: 40300 | E5: 1246278386 | F5: 46206 | H5: 1 | I5: Adtives | J5: 11615 | K5: 46178 | L5: 1010100 | M5: VENDAS MERCADO INTERNO | N5: 56 | O5: VENDA A ORDEM | P5: GRUPO AGRO INDUSTRIAL SAO LUIZ LTDA | Q5: =$R$1-F5 -> -9 | R5: =_xlfn.XLOOKUP(P5,'Painel Additive'!$B:$B,'Painel Additive'!$B:$B,0) -> GRUPO AGRO INDUSTRIAL SAO LUIZ LTDA | S5: =F5-K5 -> 28
A6: 2603 | B6: MOSAIC - SÃO LUIS | C6: 61.156.501/0100-38 | D6: 4522.16 | E6: 1246097965 | F6: 45152 | H6: 1 | I6: Adtives | J6: 21713 | K6: 45092 | L6: 1010100 | M6: VENDAS MERCADO INTERNO | N6: 56 | O6: VENDA A ORDEM | P6: GRUPO MOSAIC FERTILIZANTES DO BRASIL | Q6: =$R$1-F6 -> 1045 | R6: =_xlfn.XLOOKUP(P6,'Painel Additive'!$B:$B,'Painel Additive'!$B:$B,0) -> GRUPO MOSAIC FERTILIZANTES DO BRASIL | S6: =F6-K6 -> 60
A7: 2603 | B7: MOSAIC - SÃO LUIS | C7: 61.156.501/0100-38 | D7: 241850 | E7: 1246273467 | F7: 46236 | H7: 1 | I7: Adtives | J7: 2903 | K7: 46146 | L7: 1010100 | M7: VENDAS MERCADO INTERNO | N7: 56 | O7: VENDA A ORDEM | P7: GRUPO MOSAIC FERTILIZANTES DO BRASIL | Q7: =$R$1-F7 -> -39 | R7: =_xlfn.XLOOKUP(P7,'Painel Additive'!$B:$B,'Painel Additive'!$B:$B,0) -> GRUPO MOSAIC FERTILIZANTES DO BRASIL | S7: =F7-K7 -> 90
A8: 6124 | B8: MOSAIC - UBERABA (UBA III) | C8: 61.156.501/0110-00 | D8: 384000 | E8: 1246277044 | F8: 46259 | H8: 1 | I8: Adtives | J8: 2971 | K8: 46169 | L8: 1010100 | M8: VENDAS MERCADO INTERNO | N8: 56 | O8: VENDA A ORDEM | P8: GRUPO MOSAIC FERTILIZANTES DO BRASIL | Q8: =$R$1-F8 -> -62 | R8: =_xlfn.XLOOKUP(P8,'Painel Additive'!$B:$B,'Painel Additive'!$B:$B,0) -> GRUPO MOSAIC FERTILIZANTES DO BRASIL | S8: =F8-K8 -> 90
A9: 6124 | B9: MOSAIC - UBERABA (UBA III) | C9: 61.156.501/0110-00 | D9: 384000 | E9: 1246279317 | F9: 46275 | H9: 1 | I9: Adtives | J9: 3012 | K9: 46185 | L9: 1010100 | M9: VENDAS MERCADO INTERNO | N9: 56 | O9: VENDA A ORDEM | P9: GRUPO MOSAIC FERTILIZANTES DO BRASIL | Q9: =$R$1-F9 -> -78 | R9: =_xlfn.XLOOKUP(P9,'Painel Additive'!$B:$B,'Painel Additive'!$B:$B,0) -> GRUPO MOSAIC FERTILIZANTES DO BRASIL | S9: =F9-K9 -> 90
A10: 7479 | B10: MOSAIC - CUBATÃO | C10: 61.156.501/0099-60 | D10: 167211.9 | E10: 1246274162 | F10: 46240 | H10: 1 | I10: Adtives | J10: 11335 | K10: 46150 | L10: 1010100 | M10: VENDAS MERCADO INTERNO | N10: 56 | O10: VENDA A ORDEM | P10: GRUPO MOSAIC FERTILIZANTES DO BRASIL | Q10: =$R$1-F10 -> -43 | R10: =_xlfn.XLOOKUP(P10,'Painel Additive'!$B:$B,'Painel Additive'!$B:$B,0) -> GRUPO MOSAIC FERTILIZANTES DO BRASIL | S10: =F10-K10 -> 90
A11: 7479 | B11: MOSAIC - CUBATÃO | C11: 61.156.501/0099-60 | D11: 768000 | E11: 1246280565 | F11: 46286 | H11: 1 | I11: Adtives | J11: 3029 | K11: 46196 | L11: 1010100 | M11: VENDAS MERCADO INTERNO | N11: 56 | O11: VENDA A ORDEM | P11: GRUPO MOSAIC FERTILIZANTES DO BRASIL | Q11: =$R$1-F11 -> -89 | R11: =_xlfn.XLOOKUP(P11,'Painel Additive'!$B:$B,'Painel Additive'!$B:$B,0) -> GRUPO MOSAIC FERTILIZANTES DO BRASIL | S11: =F11-K11 -> 90
A12: 7479 | B12: MOSAIC - CUBATÃO | C12: 61.156.501/0099-60 | D12: 64239.64 | E12: 1246275302 | F12: 46247 | H12: 1 | I12: Adtives | J12: 11401 | K12: 46157 | L12: 1010100 | M12: VENDAS MERCADO INTERNO | N12: 56 | O12: VENDA A ORDEM | P12: GRUPO MOSAIC FERTILIZANTES DO BRASIL | Q12: =$R$1-F12 -> -50 | R12: =_xlfn.XLOOKUP(P12,'Painel Additive'!$B:$B,'Painel Additive'!$B:$B,0) -> GRUPO MOSAIC FERTILIZANTES DO BRASIL | S12: =F12-K12 -> 90
A13: 7479 | B13: MOSAIC - CUBATÃO | C13: 61.156.501/0099-60 | D13: 384000 | E13: 1246277126 | F13: 46259 | H13: 1 | I13: Adtives | J13: 2974 | K13: 46169 | L13: 1010100 | M13: VENDAS MERCADO INTERNO | N13: 56 | O13: VENDA A ORDEM | P13: GRUPO MOSAIC FERTILIZANTES DO BRASIL | Q13: =$R$1-F13 -> -62 | R13: =_xlfn.XLOOKUP(P13,'Painel Additive'!$B:$B,'Painel Additive'!$B:$B,0) -> GRUPO MOSAIC FERTILIZANTES DO BRASIL | S13: =F13-K13 -> 90
A14: 7302 | B14: MOSAIC - PARANAGUA I | C14: 61.156.501/0080-50 | D14: 61000 | E14: 1246278404 | F14: 46268 | H14: 1 | I14: Adtives | J14: 11618 | K14: 46178 | L14: 1010100 | M14: VENDAS MERCADO INTERNO | N14: 56 | O14: VENDA A ORDEM | P14: GRUPO MOSAIC FERTILIZANTES DO BRASIL | Q14: =$R$1-F14 -> -71 | R14: =_xlfn.XLOOKUP(P14,'Painel Additive'!$B:$B,'Painel Additive'!$B:$B,0) -> GRUPO MOSAIC FERTILIZANTES DO BRASIL | S14: =F14-K14 -> 90
... A190: 6477 | B190: MOSAIC - PARANAGUA II | C190: 61.156.501/0109-76 | D190: 184525 | E190: 1246275783 | F190: 46251 | H190: 1 | I190: Adtives | J190: 11440 | K190: 46161 | L190: 1010100 | M190: VENDAS MERCADO INTERNO | N190: 161 | O190: VENDA PROD. INDUSTRIALIZADO - NFE | P190: GRUPO MOSAIC FERTILIZANTES DO BRASIL | Q190: =$R$1-F190 -> -54 | R190: =_xlfn.XLOOKUP(P190,'Painel Additive'!$B:$B,'Painel Additive'!$B:$B,0) -> GRUPO MOSAIC FERTILIZANTES DO BRASIL | S190: =F190-K190 -> 90
A191: 6477 | B191: MOSAIC - PARANAGUA II | C191: 61.156.501/0109-76 | D191: 185135 | E191: 1246276345 | F191: 46254 | H191: 1 | I191: Adtives | J191: 11476 | K191: 46164 | L191: 1010100 | M191: VENDAS MERCADO INTERNO | N191: 161 | O191: VENDA PROD. INDUSTRIALIZADO - NFE | P191: GRUPO MOSAIC FERTILIZANTES DO BRASIL | Q191: =$R$1-F191 -> -57 | R191: =_xlfn.XLOOKUP(P191,'Painel Additive'!$B:$B,'Painel Additive'!$B:$B,0) -> GRUPO MOSAIC FERTILIZANTES DO BRASIL | S191: =F191-K191 -> 90 | T191: =F191-$R$1 -> 57
A192: 6477 | B192: MOSAIC - PARANAGUA II | C192: 61.156.501/0109-76 | D192: 122000 | E192: 1246280250 | F192: 46282 | H192: 1 | I192: Adtives | J192: 11762 | K192: 46192 | L192: 1010100 | M192: VENDAS MERCADO INTERNO | N192: 161 | O192: VENDA PROD. INDUSTRIALIZADO - NFE | P192: GRUPO MOSAIC FERTILIZANTES DO BRASIL | Q192: =$R$1-F192 -> -85 | R192: =_xlfn.XLOOKUP(P192,'Painel Additive'!$B:$B,'Painel Additive'!$B:$B,0) -> GRUPO MOSAIC FERTILIZANTES DO BRASIL | S192: =F192-K192 -> 90 | T192: =F192-$R$1 -> 85
A193: 6477 | B193: MOSAIC - PARANAGUA II | C193: 61.156.501/0109-76 | D193: 35057.43 | E193: 1246277377 | F193: 46261 | H193: 1 | I193: Adtives | J193: 11552 | K193: 46171 | L193: 1010100 | M193: VENDAS MERCADO INTERNO | N193: 161 | O193: VENDA PROD. INDUSTRIALIZADO - NFE | P193: GRUPO MOSAIC FERTILIZANTES DO BRASIL | Q193: =$R$1-F193 -> -64 | R193: =_xlfn.XLOOKUP(P193,'Painel Additive'!$B:$B,'Painel Additive'!$B:$B,0) -> GRUPO MOSAIC FERTILIZANTES DO BRASIL | S193: =F193-K193 -> 90 | T193: =F193-$R$1 -> 64
A194: 6477 | B194: MOSAIC - PARANAGUA II | C194: 61.156.501/0109-76 | D194: 34213.5 | E194: 1246274569 | F194: 46244 | H194: 1 | I194: Adtives | J194: 11361 | K194: 46154 | L194: 1010100 | M194: VENDAS MERCADO INTERNO | N194: 161 | O194: VENDA PROD. INDUSTRIALIZADO - NFE | P194: GRUPO MOSAIC FERTILIZANTES DO BRASIL | Q194: =$R$1-F194 -> -47 | R194: =_xlfn.XLOOKUP(P194,'Painel Additive'!$B:$B,'Painel Additive'!$B:$B,0) -> GRUPO MOSAIC FERTILIZANTES DO BRASIL | S194: =F194-K194 -> 90
A195: 6477 | B195: MOSAIC - PARANAGUA II | C195: 61.156.501/0109-76 | D195: 121878 | E195: 1246278399 | F195: 46268 | H195: 1 | I195: Adtives | J195: 11617 | K195: 46178 | L195: 1010100 | M195: VENDAS MERCADO INTERNO | N195: 161 | O195: VENDA PROD. INDUSTRIALIZADO - NFE | P195: GRUPO MOSAIC FERTILIZANTES DO BRASIL | Q195: =$R$1-F195 -> -71 | R195: =_xlfn.XLOOKUP(P195,'Painel Additive'!$B:$B,'Painel Additive'!$B:$B,0) -> GRUPO MOSAIC FERTILIZANTES DO BRASIL | S195: =F195-K195 -> 90
A196: 6477 | B196: MOSAIC - PARANAGUA II | C196: 61.156.501/0109-76 | D196: 68404.19 | E196: 1246280278 | F196: 46282 | H196: 1 | I196: Adtives | J196: 11769 | K196: 46192 | L196: 1010100 | M196: VENDAS MERCADO INTERNO | N196: 161 | O196: VENDA PROD. INDUSTRIALIZADO - NFE | P196: GRUPO MOSAIC FERTILIZANTES DO BRASIL | Q196: =$R$1-F196 -> -85 | R196: =_xlfn.XLOOKUP(P196,'Painel Additive'!$B:$B,'Painel Additive'!$B:$B,0) -> GRUPO MOSAIC FERTILIZANTES DO BRASIL | S196: =F196-K196 -> 90
A197: 6477 | B197: MOSAIC - PARANAGUA II | C197: 61.156.501/0109-76 | D197: 64184.53 | E197: 1246278952 | F197: 46273 | H197: 1 | I197: Adtives | J197: 11666 | K197: 46183 | L197: 1010100 | M197: VENDAS MERCADO INTERNO | N197: 161 | O197: VENDA PROD. INDUSTRIALIZADO - NFE | P197: GRUPO MOSAIC FERTILIZANTES DO BRASIL | Q197: =$R$1-F197 -> -76 | R197: =_xlfn.XLOOKUP(P197,'Painel Additive'!$B:$B,'Painel Additive'!$B:$B,0) -> GRUPO MOSAIC FERTILIZANTES DO BRASIL | S197: =F197-K197 -> 90
A198: 6477 | B198: MOSAIC - PARANAGUA II | C198: 61.156.501/0109-76 | D198: 183427 | E198: 1246273826 | F198: 46238 | H198: 1 | I198: Adtives | J198: 11314 | K198: 46148 | L198: 1010100 | M198: VENDAS MERCADO INTERNO | N198: 161 | O198: VENDA PROD. INDUSTRIALIZADO - NFE | P198: GRUPO MOSAIC FERTILIZANTES DO BRASIL | Q198: =$R$1-F198 -> -41 | R198: =_xlfn.XLOOKUP(P198,'Painel Additive'!$B:$B,'Painel Additive'!$B:$B,0) -> GRUPO MOSAIC FERTILIZANTES DO BRASIL | S198: =F198-K198 -> 90
A199: 6477 | B199: MOSAIC - PARANAGUA II | C199: 61.156.501/0109-76 | D199: 6302.6 | E199: 1246212732 | F199: 45682 | H199: 1 | I199: Adtives | J199: 6197 | K199: 45622 | L199: 1010100 | M199: VENDAS MERCADO INTERNO | N199: 161 | O199: VENDA PROD. INDUSTRIALIZADO - NFE | P199: GRUPO MOSAIC FERTILIZANTES DO BRASIL | Q199: =$R$1-F199 -> 515 | R199: =_xlfn.XLOOKUP(P199,'Painel Additive'!$B:$B,'Painel Additive'!$B:$B,0) -> GRUPO MOSAIC FERTILIZANTES DO BRASIL | S199: =F199-K199 -> 60
A200: 7097 | B200: MOSAIC - SÃO FRANCISCO SUL | C200: 61.156.501/0125-96 | D200: 174501 | E200: 1246279050 | F200: 46273 | H200: 1 | I200: Adtives | J200: 11673 | K200: 46183 | L200: 1010100 | M200: VENDAS MERCADO INTERNO | N200: 161 | O200: VENDA PROD. INDUSTRIALIZADO - NFE | P200: GRUPO MOSAIC FERTILIZANTES DO BRASIL | Q200: =$R$1-F200 -> -76 | R200: =_xlfn.XLOOKUP(P200,'Painel Additive'!$B:$B,'Painel Additive'!$B:$B,0) -> GRUPO MOSAIC FERTILIZANTES DO BRASIL | S200: =F200-K200 -> 90
A201: 7648 | B201: LOUIS DREYFUS - PARANAGUÁ | C201: 47.067.525/0221-87 | D201: 69092.1 | E201: 1246279181 | F201: 46219 | H201: 1 | I201: Adtives | J201: 11678 | K201: 46184 | L201: 1010100 | M201: VENDAS MERCADO INTERNO | N201: 161 | O201: VENDA PROD. INDUSTRIALIZADO - NFE | P201: GRUPO LOUIS DREYFUS | Q201: =$R$1-F201 -> -22 | R201: =_xlfn.XLOOKUP(P201,'Painel Additive'!$B:$B,'Painel Additive'!$B:$B,0) -> GRUPO LOUIS DREYFUS | S201: =F201-K201 -> 35
A202: 7024 | B202: MOSAIC - SORRISO | C202: 61.156.501/0092-93 | D202: 70855.2 | E202: 1246269662 | F202: 46201 | H202: 1 | I202: Adtives | J202: 11011 | K202: 46111 | L202: 1010100 | M202: VENDAS MERCADO INTERNO | N202: 161 | O202: VENDA PROD. INDUSTRIALIZADO - NFE | P202: GRUPO MOSAIC FERTILIZANTES DO BRASIL | Q202: =$R$1-F202 -> -4 | R202: =_xlfn.XLOOKUP(P202,'Painel Additive'!$B:$B,'Painel Additive'!$B:$B,0) -> GRUPO MOSAIC FERTILIZANTES DO BRASIL | S202: =F202-K202 -> 90
A203: 7024 | B203: MOSAIC - SORRISO | C203: 61.156.501/0092-93 | D203: 70849.5 | E203: 1246278281 | F203: 46268 | H203: 1 | I203: Adtives | J203: 11597 | K203: 46178 | L203: 1010100 | M203: VENDAS MERCADO INTERNO | N203: 161 | O203: VENDA PROD. INDUSTRIALIZADO - NFE | P203: GRUPO MOSAIC FERTILIZANTES DO BRASIL | Q203: =$R$1-F203 -> -71 | R203: =_xlfn.XLOOKUP(P203,'Painel Additive'!$B:$B,'Painel Additive'!$B:$B,0) -> GRUPO MOSAIC FERTILIZANTES DO BRASIL | S203: =F203-K203 -> 90
A204: 7024 | B204: MOSAIC - SORRISO | C204: 61.156.501/0092-93 | D204: 71323.2 | E204: 1246270943 | F204: 46212 | H204: 1 | I204: Adtives | J204: 11084 | K204: 46122 | L204: 1010100 | M204: VENDAS MERCADO INTERNO | N204: 161 | O204: VENDA PROD. INDUSTRIALIZADO - NFE | P204: GRUPO MOSAIC FERTILIZANTES DO BRASIL | Q204: =$R$1-F204 -> -15 | R204: =_xlfn.XLOOKUP(P204,'Painel Additive'!$B:$B,'Painel Additive'!$B:$B,0) -> GRUPO MOSAIC FERTILIZANTES DO BRASIL | S204: =F204-K204 -> 90
A205: 7024 | B205: MOSAIC - SORRISO | C205: 61.156.501/0092-93 | D205: 71038.43 | E205: 1246279215 | F205: 46274 | H205: 1 | I205: Adtives | J205: 11682 | K205: 46184 | L205: 1010100 | M205: VENDAS MERCADO INTERNO | N205: 161 | O205: VENDA PROD. INDUSTRIALIZADO - NFE | P205: GRUPO MOSAIC FERTILIZANTES DO BRASIL | Q205: =$R$1-F205 -> -77 | R205: =_xlfn.XLOOKUP(P205,'Painel Additive'!$B:$B,'Painel Additive'!$B:$B,0) -> GRUPO MOSAIC FERTILIZANTES DO BRASIL | S205: =F205-K205 -> 90
... A241: 16099 | B241: MOSAIC - PALMEIRANTE | C241: 61.156.501/0208-58 | D241: 88185.43 | E241: 1246280413 | F241: 46285 | H241: 1 | I241: Adtives | J241: 11775 | K241: 46195 | L241: 1010100 | M241: VENDAS MERCADO INTERNO | N241: 161 | O241: VENDA PROD. INDUSTRIALIZADO - NFE | P241: GRUPO MOSAIC FERTILIZANTES DO BRASIL | Q241: =$R$1-F241 -> -88 | R241: =_xlfn.XLOOKUP(P241,'Painel Additive'!$B:$B,'Painel Additive'!$B:$B,0) -> GRUPO MOSAIC FERTILIZANTES DO BRASIL | S241: =F241-K241 -> 90
A242: 16189 | B242: ARSLOG SOLUCOES EM TRANSPORTE | C242: 05.765.626/0001-02 | D242: 49440 | E242: 1246261824 | F242: 46087 | I242: Não encontrado | J242: 1246261824 | K242: 46055 | L242: 7240000 | M242: PERDA DE MERCADORIA COM SINISTRO | N242: 46 | O242: FINANCEIRO GERAL | P242: ARSLOG SOLUCOES EM TRANSPORTE | Q242: =$R$1-F242 -> 110 | R242: =_xlfn.XLOOKUP(P242,'Painel Additive'!$B:$B,'Painel Additive'!$B:$B,0) -> ARSLOG SOLUCOES EM TRANSPORTE | S242: =F242-K242 -> 32
A243: 10413 | B243: BUNGE - SANTOS | C243: 84.046.101/0542-85 | D243: 78993 | E243: 1246279827 | F243: 46218 | H243: 1 | I243: Adtives | J243: 11733 | K243: 46189 | L243: 1010100 | M243: VENDAS MERCADO INTERNO | N243: 56 | O243: VENDA A ORDEM | P243: BUNGE - SANTOS | Q243: =$R$1-F243 -> -21 | R243: =_xlfn.XLOOKUP(P243,'Painel Additive'!$B:$B,'Painel Additive'!$B:$B,0) -> BUNGE - SANTOS | S243: =F243-K243 -> 29
A244: 10413 | B244: BUNGE - SANTOS | C244: 84.046.101/0542-85 | D244: 79019.2 | E244: 1246278424 | F244: 46218 | H244: 1 | I244: Adtives | J244: 11626 | K244: 46178 | L244: 1010100 | M244: VENDAS MERCADO INTERNO | N244: 56 | O244: VENDA A ORDEM | P244: BUNGE - SANTOS | Q244: =$R$1-F244 -> -21 | R244: =_xlfn.XLOOKUP(P244,'Painel Additive'!$B:$B,'Painel Additive'!$B:$B,0) -> BUNGE - SANTOS | S244: =F244-K244 -> 40
A245: 10677 | B245: MARCELO HONORIO DE CARVALHO RAMOS | C245: 007.511.136-54 | D245: 581 | E245: 1246272911 | F245: 46175 | I245: Não encontrado | J245: 11244 | K245: 46140 | L245: 4011600 | M245: APARELHOS DE INFORMÁTICA | N245: 244 | O245: VENDA DE IMOBILIZADO SEM ICMS | P245: MARCELO HONORIO DE CARVALHO RAMOS | Q245: =$R$1-F245 -> 22 | R245: =_xlfn.XLOOKUP(P245,'Painel Additive'!$B:$B,'Painel Additive'!$B:$B,0) -> MARCELO HONORIO DE CARVALHO RAMOS | S245: =F245-K245 -> 35
A246: 10677 | B246: MARCELO HONORIO DE CARVALHO RAMOS | C246: 007.511.136-54 | D246: 581 | E246: 1246272912 | F246: 46200 | I246: Não encontrado | J246: 11244 | K246: 46140 | L246: 4011600 | M246: APARELHOS DE INFORMÁTICA | N246: 244 | O246: VENDA DE IMOBILIZADO SEM ICMS | P246: MARCELO HONORIO DE CARVALHO RAMOS | Q246: =$R$1-F246 -> -3 | R246: =_xlfn.XLOOKUP(P246,'Painel Additive'!$B:$B,'Painel Additive'!$B:$B,0) -> MARCELO HONORIO DE CARVALHO RAMOS | S246: =F246-K246 -> 60
A247: 10677 | B247: MARCELO HONORIO DE CARVALHO RAMOS | C247: 007.511.136-54 | D247: 581 | E247: 1246272913 | F247: 46230 | I247: Não encontrado | J247: 11244 | K247: 46140 | L247: 4011600 | M247: APARELHOS DE INFORMÁTICA | N247: 244 | O247: VENDA DE IMOBILIZADO SEM ICMS | P247: MARCELO HONORIO DE CARVALHO RAMOS | Q247: =$R$1-F247 -> -33 | R247: =_xlfn.XLOOKUP(P247,'Painel Additive'!$B:$B,'Painel Additive'!$B:$B,0) -> MARCELO HONORIO DE CARVALHO RAMOS | S247: =F247-K247 -> 90
A248: 14094 | B248: KLEYTON DUARTE SOARES | C248: 014.415.101-41 | D248: 100 | E248: 1246154530 | F248: 45474 | I248: Não encontrado | J248: 4088 | K248: 45474 | L248: 4010300 | M248: MÓVEIS E UTENSÍLIOS | N248: 244 | O248: VENDA DE IMOBILIZADO SEM ICMS | P248: KLEYTON DUARTE SOARES | Q248: =$R$1-F248 -> 723 | R248: =_xlfn.XLOOKUP(P248,'Painel Additive'!$B:$B,'Painel Additive'!$B:$B,0) -> KLEYTON DUARTE SOARES | S248: =F248-K248 -> 0
A249: 13873 | B249: MARIA JOSE DA SILVA | C249: 844.462.855-72 | D249: 50 | E249: 1246166396 | F249: 45525 | I249: Não encontrado | J249: 4854 | K249: 45525 | L249: 4010300 | M249: MÓVEIS E UTENSÍLIOS | N249: 244 | O249: VENDA DE IMOBILIZADO SEM ICMS | P249: MARIA JOSE DA SILVA | Q249: =$R$1-F249 -> 672 | R249: =_xlfn.XLOOKUP(P249,'Painel Additive'!$B:$B,'Painel Additive'!$B:$B,0) -> MARIA JOSE DA SILVA | S249: =F249-K249 -> 0
A250: 14106 | B250: SEU LIXO | C250: 50.454.037/0001-68 | D250: 300 | E250: 1246182736 | F250: 45625 | I250: Não encontrado | J250: 6092 | K250: 45610 | L250: 1020400 | M250: VENDA DE SUCATAS | N250: 136 | O250: VENDA DE SUCATAS | P250: SEU LIXO | Q250: =$R$1-F250 -> 572 | R250: =_xlfn.XLOOKUP(P250,'Painel Additive'!$B:$B,'Painel Additive'!$B:$B,0) -> SEU LIXO | S250: =F250-K250 -> 15
A251: 707 | B251: TERRA FERTILIZANTES LTDA - ARAXÁ | C251: 10.482.668/0001-76 | D251: 40320 | E251: 1246146706 | F251: 45461 | H251: 1 | I251: Adtives | J251: 3619 | K251: 45433 | L251: 1010100 | M251: VENDAS MERCADO INTERNO | N251: 161 | O251: VENDA PROD. INDUSTRIALIZADO - NFE | P251: TERRA FERTILIZANTES LTDA - ARAXÁ | Q251: =$R$1-F251 -> 736 | R251: =_xlfn.XLOOKUP(P251,'Painel Additive'!$B:$B,'Painel Additive'!$B:$B,0) -> TERRA FERTILIZANTES LTDA - ARAXÁ | S251: =F251-K251 -> 28
A252: 707 | B252: TERRA FERTILIZANTES LTDA - ARAXÁ | C252: 10.482.668/0001-76 | D252: 14640 | E252: 1246145696 | F252: 45454 | H252: 1 | I252: Adtives | J252: 3538 | K252: 45426 | L252: 1010100 | M252: VENDAS MERCADO INTERNO | N252: 161 | O252: VENDA PROD. INDUSTRIALIZADO - NFE | P252: TERRA FERTILIZANTES LTDA - ARAXÁ | Q252: =$R$1-F252 -> 743 | R252: =_xlfn.XLOOKUP(P252,'Painel Additive'!$B:$B,'Painel Additive'!$B:$B,0) -> TERRA FERTILIZANTES LTDA - ARAXÁ | S252: =F252-K252 -> 28
A253: 707 | B253: TERRA FERTILIZANTES LTDA - ARAXÁ | C253: 10.482.668/0001-76 | D253: 43920 | E253: 1246148035 | F253: 45469 | H253: 1 | I253: Adtives | J253: 3722 | K253: 45441 | L253: 1010100 | M253: VENDAS MERCADO INTERNO | N253: 161 | O253: VENDA PROD. INDUSTRIALIZADO - NFE | P253: TERRA FERTILIZANTES LTDA - ARAXÁ | Q253: =$R$1-F253 -> 728 | R253: =_xlfn.XLOOKUP(P253,'Painel Additive'!$B:$B,'Painel Additive'!$B:$B,0) -> TERRA FERTILIZANTES LTDA - ARAXÁ | S253: =F253-K253 -> 28
A254: 707 | B254: TERRA FERTILIZANTES LTDA - ARAXÁ | C254: 10.482.668/0001-76 | D254: 36600 | E254: 1246146938 | F254: 45462 | H254: 1 | I254: Adtives | J254: 3637 | K254: 45434 | L254: 1010100 | M254: VENDAS MERCADO INTERNO | N254: 161 | O254: VENDA PROD. INDUSTRIALIZADO - NFE | P254: TERRA FERTILIZANTES LTDA - ARAXÁ | Q254: =$R$1-F254 -> 735 | R254: =_xlfn.XLOOKUP(P254,'Painel Additive'!$B:$B,'Painel Additive'!$B:$B,0) -> TERRA FERTILIZANTES LTDA - ARAXÁ | S254: =F254-K254 -> 28
A255: 707 | B255: TERRA FERTILIZANTES LTDA - ARAXÁ | C255: 10.482.668/0001-76 | D255: 33600 | E255: 1246148036 | F255: 45469 | H255: 1 | I255: Adtives | J255: 3723 | K255: 45441 | L255: 1010100 | M255: VENDAS MERCADO INTERNO | N255: 161 | O255: VENDA PROD. INDUSTRIALIZADO - NFE | P255: TERRA FERTILIZANTES LTDA - ARAXÁ | Q255: =$R$1-F255 -> 728 | R255: =_xlfn.XLOOKUP(P255,'Painel Additive'!$B:$B,'Painel Additive'!$B:$B,0) -> TERRA FERTILIZANTES LTDA - ARAXÁ | S255: =F255-K255 -> 28
A256: 707 | B256: TERRA FERTILIZANTES LTDA - ARAXÁ | C256: 10.482.668/0001-76 | D256: 16800 | E256: 1246141445 | F256: 45433 | H256: 1 | I256: Adtives | J256: 3345 | K256: 45405 | L256: 1010100 | M256: VENDAS MERCADO INTERNO | N256: 161 | O256: VENDA PROD. INDUSTRIALIZADO - NFE | P256: TERRA FERTILIZANTES LTDA - ARAXÁ | Q256: =$R$1-F256 -> 764 | R256: =_xlfn.XLOOKUP(P256,'Painel Additive'!$B:$B,'Painel Additive'!$B:$B,0) -> TERRA FERTILIZANTES LTDA - ARAXÁ | S256: =F256-K256 -> 28
A257: 707 | B257: TERRA FERTILIZANTES LTDA - ARAXÁ | C257: 10.482.668/0001-76 | D257: 40353.6 | E257: 1246143397 | F257: 45443 | H257: 1 | I257: Adtives | J257: 3448 | K257: 45415 | L257: 1010100 | M257: VENDAS MERCADO INTERNO | N257: 161 | O257: VENDA PROD. INDUSTRIALIZADO - NFE | P257: TERRA FERTILIZANTES LTDA - ARAXÁ | Q257: =$R$1-F257 -> 754 | R257: =_xlfn.XLOOKUP(P257,'Painel Additive'!$B:$B,'Painel Additive'!$B:$B,0) -> TERRA FERTILIZANTES LTDA - ARAXÁ | S257: =F257-K257 -> 28
A258: 1462 | B258: AURORA MINERAÇÃO LTDA | C258: 02.964.101/0001-08 | D258: 38067.25 | E258: 1246274419 | F258: 46213 | H258: 1 | I258: Adtives | J258: 11350 | K258: 46153 | L258: 1010100 | M258: VENDAS MERCADO INTERNO | N258: 161 | O258: VENDA PROD. INDUSTRIALIZADO - NFE | P258: AURORA MINERAÇÃO LTDA | Q258: =$R$1-F258 -> -16 | R258: =_xlfn.XLOOKUP(P258,'Painel Additive'!$B:$B,'Painel Additive'!$B:$B,0) -> AURORA MINERAÇÃO LTDA | S258: =F258-K258 -> 60
A259: 1462 | B259: AURORA MINERAÇÃO LTDA | C259: 02.964.101/0001-08 | D259: 38067.25 | E259: 1246274420 | F259: 46223 | H259: 1 | I259: Adtives | J259: 11350 | K259: 46153 | L259: 1010100 | M259: VENDAS MERCADO INTERNO | N259: 161 | O259: VENDA PROD. INDUSTRIALIZADO - NFE | P259: AURORA MINERAÇÃO LTDA | Q259: =$R$1-F259 -> -26 | R259: =_xlfn.XLOOKUP(P259,'Painel Additive'!$B:$B,'Painel Additive'!$B:$B,0) -> AURORA MINERAÇÃO LTDA | S259: =F259-K259 -> 70
A260: 1462 | B260: AURORA MINERAÇÃO LTDA | C260: 02.964.101/0001-08 | D260: 38160.2 | E260: 1246270126 | F260: 46174 | H260: 1 | I260: Adtives | J260: 11041 | K260: 46114 | L260: 1010100 | M260: VENDAS MERCADO INTERNO | N260: 161 | O260: VENDA PROD. INDUSTRIALIZADO - NFE | P260: AURORA MINERAÇÃO LTDA | Q260: =$R$1-F260 -> 23 | R260: =_xlfn.XLOOKUP(P260,'Painel Additive'!$B:$B,'Painel Additive'!$B:$B,0) -> AURORA MINERAÇÃO LTDA | S260: =F260-K260 -> 60
A261: 1462 | B261: AURORA MINERAÇÃO LTDA | C261: 02.964.101/0001-08 | D261: 38160.2 | E261: 1246270127 | F261: 46184 | H261: 1 | I261: Adtives | J261: 11041 | K261: 46114 | L261: 1010100 | M261: VENDAS MERCADO INTERNO | N261: 161 | O261: VENDA PROD. INDUSTRIALIZADO - NFE | P261: AURORA MINERAÇÃO LTDA | Q261: =$R$1-F261 -> 13 | R261: =_xlfn.XLOOKUP(P261,'Painel Additive'!$B:$B,'Painel Additive'!$B:$B,0) -> AURORA MINERAÇÃO LTDA | S261: =F261-K261 -> 70
A262: 1462 | B262: AURORA MINERAÇÃO LTDA | C262: 02.964.101/0001-08 | D262: 38236.25 | E262: 1246277330 | F262: 46230 | H262: 1 | I262: Adtives | J262: 11543 | K262: 46170 | L262: 1010100 | M262: VENDAS MERCADO INTERNO | N262: 161 | O262: VENDA PROD. INDUSTRIALIZADO - NFE | P262: AURORA MINERAÇÃO LTDA | Q262: =$R$1-F262 -> -33 | R262: =_xlfn.XLOOKUP(P262,'Painel Additive'!$B:$B,'Painel Additive'!$B:$B,0) -> AURORA MINERAÇÃO LTDA | S262: =F262-K262 -> 60
... A314: 15749 | B314: FASS AGRO FERTILIZANTES - SERTAOZINHO | C314: 13.341.380/0001-70 | D314: 66740 | E314: 1246279766 | F314: 46217 | H314: 1 | I314: Adtives | J314: 3021 | K314: 46189 | L314: 1010100 | M314: VENDAS MERCADO INTERNO | N314: 161 | O314: VENDA PROD. INDUSTRIALIZADO - NFE | P314: FASS AGRO FERTILIZANTES - SERTAOZINHO | Q314: =$R$1-F314 -> -20 | R314: =_xlfn.XLOOKUP(P314,'Painel Additive'!$B:$B,'Painel Additive'!$B:$B,0) -> FASS AGRO FERTILIZANTES - SERTAOZINHO | S314: =F314-K314 -> 28
Q315: =$R$1-F315 -> 46197 | R315: =_xlfn.XLOOKUP(P315,'Painel Additive'!$B:$B,'Painel Additive'!$B:$B,0) -> 0 | S315: =F315-K315 -> 0
Q316: =$R$1-F316 -> 46197 | R316: =_xlfn.XLOOKUP(P316,'Painel Additive'!$B:$B,'Painel Additive'!$B:$B,0) -> 0 | S316: =F316-K316 -> 0
Q317: =$R$1-F317 -> 46197 | R317: =_xlfn.XLOOKUP(P317,'Painel Additive'!$B:$B,'Painel Additive'!$B:$B,0) -> 0 | S317: =F317-K317 -> 0
Q318: =$R$1-F318 -> 46197 | R318: =_xlfn.XLOOKUP(P318,'Painel Additive'!$B:$B,'Painel Additive'!$B:$B,0) -> 0 | S318: =F318-K318 -> 0
Q319: =$R$1-F319 -> 46197 | R319: =_xlfn.XLOOKUP(P319,'Painel Additive'!$B:$B,'Painel Additive'!$B:$B,0) -> 0 | S319: =F319-K319 -> 0
Q320: =$R$1-F320 -> 46197 | R320: =_xlfn.XLOOKUP(P320,'Painel Additive'!$B:$B,'Painel Additive'!$B:$B,0) -> 0 | S320: =F320-K320 -> 0
Q321: =$R$1-F321 -> 46197 | R321: =_xlfn.XLOOKUP(P321,'Painel Additive'!$B:$B,'Painel Additive'!$B:$B,0) -> 0 | S321: =F321-K321 -> 0

Sheet Data International
D1: =SUBTOTAL(9,D3:D994) -> 7575530 | R1: 46197
A2: CODPARC | B2: NOMEPARC | C2: CNPJ | D2: Valor | E2: NUFIN | F2: DTVENC | G2: DHBAIXA | H2: AD_BU | I2: NOME_BU | J2: NUMNOTA | K2: DTENTSAI | L2: CODNAT | M2: DESCRNAT | N2: CODTIPOPER | O2: OPERACAO | P2: Grupo | Q2: Dias vencidos
A3: 3297 | B3: MACROSOURCE PERU S.R.L. | C3: ..- | D3: 49956.68 | E3: 1246271355 | F3: 46200 | H3: 1 | I3: Adtives | J3: 11123 | K3: 46126 | L3: 1010200 | M3: VENDAS MERCADO EXTERNO | N3: 40 | O3: VENDA - NFE (EXPORTAÇÃO) | P3: MACROSOURCE PERU S.R.L. | Q3: =$R$1-F3 -> -3 | R3: =_xlfn.XLOOKUP(P3,'Painel International'!$B:$B,'Painel International'!$B:$B,0) -> MACROSOURCE PERU S.R.L.
A4: 2680 | B4: FERMAGRI S.A - EQUADOR | C4: ..- | D4: 175275.24 | E4: 1246272069 | F4: 46194 | H4: 1 | I4: Adtives | J4: 11191 | K4: 46134 | L4: 1010200 | M4: VENDAS MERCADO EXTERNO | N4: 40 | O4: VENDA - NFE (EXPORTAÇÃO) | P4: FERMAGRI S.A - EQUADOR | Q4: =$R$1-F4 -> 3 | R4: =_xlfn.XLOOKUP(P4,'Painel International'!$B:$B,'Painel International'!$B:$B,0) -> FERMAGRI S.A - EQUADOR
A5: 2696 | B5: MOSAIC FERTILIZANTES PARAGUAY S.R.L. | C5: ..- | D5: 94148.95 | E5: 1246279520 | F5: 46278 | H5: 1 | I5: Adtives | J5: 11712 | K5: 46188 | L5: 1010200 | M5: VENDAS MERCADO EXTERNO | N5: 40 | O5: VENDA - NFE (EXPORTAÇÃO) | P5: MOSAIC FERTILIZANTES PARAGUAY S.R.L. | Q5: =$R$1-F5 -> -81 | R5: =_xlfn.XLOOKUP(P5,'Painel International'!$B:$B,'Painel International'!$B:$B,0) -> MOSAIC FERTILIZANTES PARAGUAY S.R.L.
A6: 2696 | B6: MOSAIC FERTILIZANTES PARAGUAY S.R.L. | C6: ..- | D6: 91784.41 | E6: 1246274791 | F6: 46245 | H6: 1 | I6: Adtives | J6: 11378 | K6: 46155 | L6: 1010200 | M6: VENDAS MERCADO EXTERNO | N6: 40 | O6: VENDA - NFE (EXPORTAÇÃO) | P6: MOSAIC FERTILIZANTES PARAGUAY S.R.L. | Q6: =$R$1-F6 -> -48 | R6: =_xlfn.XLOOKUP(P6,'Painel International'!$B:$B,'Painel International'!$B:$B,0) -> MOSAIC FERTILIZANTES PARAGUAY S.R.L.
A7: 2696 | B7: MOSAIC FERTILIZANTES PARAGUAY S.R.L. | C7: ..- | D7: 118833.22 | E7: 1246278569 | F7: 46271 | H7: 1 | I7: Adtives | J7: 11641 | K7: 46181 | L7: 1010200 | M7: VENDAS MERCADO EXTERNO | N7: 40 | O7: VENDA - NFE (EXPORTAÇÃO) | P7: MOSAIC FERTILIZANTES PARAGUAY S.R.L. | Q7: =$R$1-F7 -> -74 | R7: =_xlfn.XLOOKUP(P7,'Painel International'!$B:$B,'Painel International'!$B:$B,0) -> MOSAIC FERTILIZANTES PARAGUAY S.R.L.
A8: 2696 | B8: MOSAIC FERTILIZANTES PARAGUAY S.R.L. | C8: ..- | D8: 116719.31 | E8: 1246277374 | F8: 46261 | H8: 1 | I8: Adtives | J8: 11551 | K8: 46171 | L8: 1010200 | M8: VENDAS MERCADO EXTERNO | N8: 40 | O8: VENDA - NFE (EXPORTAÇÃO) | P8: MOSAIC FERTILIZANTES PARAGUAY S.R.L. | Q8: =$R$1-F8 -> -64 | R8: =_xlfn.XLOOKUP(P8,'Painel International'!$B:$B,'Painel International'!$B:$B,0) -> MOSAIC FERTILIZANTES PARAGUAY S.R.L.
A9: 2696 | B9: MOSAIC FERTILIZANTES PARAGUAY S.R.L. | C9: ..- | D9: 116211.91 | E9: 1246278291 | F9: 46268 | H9: 1 | I9: Adtives | J9: 11599 | K9: 46178 | L9: 1010200 | M9: VENDAS MERCADO EXTERNO | N9: 40 | O9: VENDA - NFE (EXPORTAÇÃO) | P9: MOSAIC FERTILIZANTES PARAGUAY S.R.L. | Q9: =$R$1-F9 -> -71 | R9: =_xlfn.XLOOKUP(P9,'Painel International'!$B:$B,'Painel International'!$B:$B,0) -> MOSAIC FERTILIZANTES PARAGUAY S.R.L.
A10: 2645 | B10: ANAGRA - CHILE | C10: ..- | D10: 143222.74 | E10: 1246277225 | F10: 46200 | H10: 1 | I10: Adtives | J10: 11529 | K10: 46170 | L10: 1010200 | M10: VENDAS MERCADO EXTERNO | N10: 40 | O10: VENDA - NFE (EXPORTAÇÃO) | P10: ANAGRA - CHILE | Q10: =$R$1-F10 -> -3 | R10: =_xlfn.XLOOKUP(P10,'Painel International'!$B:$B,'Painel International'!$B:$B,0) -> ANAGRA - CHILE
A11: 2651 | B11: AGROBROKERS - COLÔMBIA | C11: ..- | D11: 132309.33 | E11: 1246278533 | F11: 46241 | H11: 1 | I11: Adtives | J11: 3002 | K11: 46181 | L11: 1010200 | M11: VENDAS MERCADO EXTERNO | N11: 40 | O11: VENDA - NFE (EXPORTAÇÃO) | P11: AGROBROKERS - COLÔMBIA | Q11: =$R$1-F11 -> -44 | R11: =_xlfn.XLOOKUP(P11,'Painel International'!$B:$B,'Painel International'!$B:$B,0) -> AGROBROKERS - COLÔMBIA
A12: 2652 | B12: FERTIMAX PARAGUAY | C12: ..- | D12: 166161.39 | E12: 1246279339 | F12: 46215 | H12: 1 | I12: Adtives | J12: 11691 | K12: 46185 | L12: 1010200 | M12: VENDAS MERCADO EXTERNO | N12: 40 | O12: VENDA - NFE (EXPORTAÇÃO) | P12: FERTIMAX PARAGUAY | Q12: =$R$1-F12 -> -18 | R12: =_xlfn.XLOOKUP(P12,'Painel International'!$B:$B,'Painel International'!$B:$B,0) -> FERTIMAX PARAGUAY
A13: 2287 | B13: BUNGE PARAGUAY S.A | C13: 99.999.999/9999-99 | D13: 152321.99 | E13: 1246279865 | F13: 46220 | H13: 1 | I13: Adtives | J13: 11738 | K13: 46190 | L13: 1010200 | M13: VENDAS MERCADO EXTERNO | N13: 40 | O13: VENDA - NFE (EXPORTAÇÃO) | P13: BUNGE PARAGUAY S.A | Q13: =$R$1-F13 -> -23 | R13: =_xlfn.XLOOKUP(P13,'Painel International'!$B:$B,'Painel International'!$B:$B,0) -> BUNGE PARAGUAY S.A
A14: 2287 | B14: BUNGE PARAGUAY S.A | C14: 99.999.999/9999-99 | D14: 155118.66 | E14: 1246278696 | F14: 46212 | H14: 1 | I14: Adtives | J14: 11655 | K14: 46182 | L14: 1010200 | M14: VENDAS MERCADO EXTERNO | N14: 40 | O14: VENDA - NFE (EXPORTAÇÃO) | P14: BUNGE PARAGUAY S.A | Q14: =$R$1-F14 -> -15 | R14: =_xlfn.XLOOKUP(P14,'Painel International'!$B:$B,'Painel International'!$B:$B,0) -> BUNGE PARAGUAY S.A
... A32: 12031 | B32: EVOAGRO NUTRICION S.A.S - COLOMBIA | C32: ..- | D32: 164297.05 | E32: 1246275610 | F32: 46220 | H32: 1 | I32: Adtives | J32: 2948 | K32: 46160 | L32: 1010200 | M32: VENDAS MERCADO EXTERNO | N32: 40 | O32: VENDA - NFE (EXPORTAÇÃO) | P32: EVOAGRO NUTRICION S.A.S - COLOMBIA | Q32: =$R$1-F32 -> -23 | R32: =_xlfn.XLOOKUP(P32,'Painel International'!$B:$B,'Painel International'!$B:$B,0) -> EVOAGRO NUTRICION S.A.S - COLOMBIA
A33: 13330 | B33: ORGANITEC - PARAGUAY | C33: 800.909.976- | D33: 853.24 | E33: 1246272264 | F33: 46148 | I33: Não encontrado | J33: 11057 | K33: 46118 | L33: 1010200 | M33: VENDAS MERCADO EXTERNO | N33: 40 | O33: VENDA - NFE (EXPORTAÇÃO) | P33: ORGANITEC - PARAGUAY | Q33: =$R$1-F33 -> 49 | R33: =_xlfn.XLOOKUP(P33,'Painel International'!$B:$B,'Painel International'!$B:$B,0) -> ORGANITEC - PARAGUAY
A34: 13330 | B34: ORGANITEC - PARAGUAY | C34: 800.909.976- | D34: 527.28 | E34: 1246238356 | F34: 45927 | I34: Não encontrado | J34: 9092 | K34: 45897 | L34: 1010200 | M34: VENDAS MERCADO EXTERNO | N34: 40 | O34: VENDA - NFE (EXPORTAÇÃO) | P34: ORGANITEC - PARAGUAY | Q34: =$R$1-F34 -> 270 | R34: =_xlfn.XLOOKUP(P34,'Painel International'!$B:$B,'Painel International'!$B:$B,0) -> ORGANITEC - PARAGUAY
A35: 15543 | B35: GOTLAND EQUADOR (SOLINAG) | C35: 19.512.950/9001- | D35: 45718.46 | E35: 1246264533 | F35: 46181 | H35: 1 | I35: Adtives | J35: 10745 | K35: 46076 | L35: 1010200 | M35: VENDAS MERCADO EXTERNO | N35: 40 | O35: VENDA - NFE (EXPORTAÇÃO) | P35: GOTLAND EQUADOR (SOLINAG) | Q35: =$R$1-F35 -> 16 | R35: =_xlfn.XLOOKUP(P35,'Painel International'!$B:$B,'Painel International'!$B:$B,0) -> GOTLAND EQUADOR (SOLINAG)
A36: 15543 | B36: GOTLAND EQUADOR (SOLINAG) | C36: 19.512.950/9001- | D36: 133756.12 | E36: 1246277124 | F36: 46259 | H36: 1 | I36: Adtives | J36: 11522 | K36: 46169 | L36: 1010200 | M36: VENDAS MERCADO EXTERNO | N36: 40 | O36: VENDA - NFE (EXPORTAÇÃO) | P36: GOTLAND EQUADOR (SOLINAG) | Q36: =$R$1-F36 -> -62 | R36: =_xlfn.XLOOKUP(P36,'Painel International'!$B:$B,'Painel International'!$B:$B,0) -> GOTLAND EQUADOR (SOLINAG)
Q37: =$R$1-F37 -> 46197 | R37: =_xlfn.XLOOKUP(P37,'Painel International'!$B:$B,'Painel International'!$B:$B,0) -> 0
Q38: =$R$1-F38 -> 46197 | R38: =_xlfn.XLOOKUP(P38,'Painel International'!$B:$B,'Painel International'!$B:$B,0) -> 0
Q39: =$R$1-F39 -> 46197 | R39: =_xlfn.XLOOKUP(P39,'Painel International'!$B:$B,'Painel International'!$B:$B,0) -> 0
Q40: =$R$1-F40 -> 46197 | R40: =_xlfn.XLOOKUP(P40,'Painel International'!$B:$B,'Painel International'!$B:$B,0) -> 0
Q41: =$R$1-F41 -> 46197 | R41: =_xlfn.XLOOKUP(P41,'Painel International'!$B:$B,'Painel International'!$B:$B,0) -> 0
Q42: =$R$1-F42 -> 46197 | R42: =_xlfn.XLOOKUP(P42,'Painel International'!$B:$B,'Painel International'!$B:$B,0) -> 0
Q43: =$R$1-F43 -> 46197 | R43: =_xlfn.XLOOKUP(P43,'Painel International'!$B:$B,'Painel International'!$B:$B,0) -> 0
Q44: =$R$1-F44 -> 46197 | R44: =_xlfn.XLOOKUP(P44,'Painel International'!$B:$B,'Painel International'!$B:$B,0) -> 0
Q45: =$R$1-F45 -> 46197 | R45: =_xlfn.XLOOKUP(P45,'Painel International'!$B:$B,'Painel International'!$B:$B,0) -> 0
Q46: =$R$1-F46 -> 46197 | R46: =_xlfn.XLOOKUP(P46,'Painel International'!$B:$B,'Painel International'!$B:$B,0) -> 0
Q47: =$R$1-F47 -> 46197 | R47: =_xlfn.XLOOKUP(P47,'Painel International'!$B:$B,'Painel International'!$B:$B,0) -> 0

Sheet Data Fertilizers
D1: =SUBTOTAL(9,D3:D995) -> 24577393 | R1: 46197
A2: CODPARC | B2: NOMEPARC | C2: CNPJ | D2: Valor | E2: NUFIN | F2: DTVENC | G2: DHBAIXA | H2: AD_BU | I2: NOME_BU | J2: NUMNOTA | K2: DTENTSAI | L2: CODNAT | M2: DESCRNAT | N2: CODTIPOPER | O2: OPERACAO | P2: GRUPO | Q2: Dias vencidos
A3: 9824 | B3: TRIANGULO AGRO CONSULTORIA C/PRESCISAO | C3: 11.827.200/0001-39 | D3: 69971.2 | E3: 1246154720 | F3: 45738 | H3: 2 | I3: Fertilizers | J3: 4113 | K3: 45475 | L3: 1010100 | M3: VENDAS MERCADO INTERNO | N3: 161 | O3: VENDA PROD. INDUSTRIALIZADO - NFE | P3: GRUPO TRIANGULO AGRO | Q3: =$R$1-F3 -> 459 | R3: =_xlfn.XLOOKUP(P3,'Painel Fertilizers'!$B:$B,'Painel Fertilizers'!$B:$B,0) -> GRUPO TRIANGULO AGRO
A4: 9824 | B4: TRIANGULO AGRO CONSULTORIA C/PRESCISAO | C4: 11.827.200/0001-39 | D4: 60656 | E4: 1246154724 | F4: 45738 | H4: 2 | I4: Fertilizers | J4: 4114 | K4: 45475 | L4: 1010100 | M4: VENDAS MERCADO INTERNO | N4: 161 | O4: VENDA PROD. INDUSTRIALIZADO - NFE | P4: GRUPO TRIANGULO AGRO | Q4: =$R$1-F4 -> 459 | R4: =_xlfn.XLOOKUP(P4,'Painel Fertilizers'!$B:$B,'Painel Fertilizers'!$B:$B,0) -> GRUPO TRIANGULO AGRO
A5: 10371 | B5: TRIANGULO AGRO – POMPEU | C5: 11.827.200/0004-81 | D5: 56674.77 | E5: 1246161059 | F5: 45736 | H5: 2 | I5: Fertilizers | J5: 4516 | K5: 45502 | L5: 1010100 | M5: VENDAS MERCADO INTERNO | N5: 161 | O5: VENDA PROD. INDUSTRIALIZADO - NFE | P5: GRUPO TRIANGULO AGRO | Q5: =$R$1-F5 -> 461 | R5: =_xlfn.XLOOKUP(P5,'Painel Fertilizers'!$B:$B,'Painel Fertilizers'!$B:$B,0) -> GRUPO TRIANGULO AGRO
A6: 10371 | B6: TRIANGULO AGRO – POMPEU | C6: 11.827.200/0004-81 | D6: 50007.15 | E6: 1246161057 | F6: 45736 | H6: 2 | I6: Fertilizers | J6: 4515 | K6: 45502 | L6: 1010100 | M6: VENDAS MERCADO INTERNO | N6: 161 | O6: VENDA PROD. INDUSTRIALIZADO - NFE | P6: GRUPO TRIANGULO AGRO | Q6: =$R$1-F6 -> 461 | R6: =_xlfn.XLOOKUP(P6,'Painel Fertilizers'!$B:$B,'Painel Fertilizers'!$B:$B,0) -> GRUPO TRIANGULO AGRO
A7: 11207 | B7: S M AGRO | C7: 08.685.699/0001-82 | D7: 153825.49 | E7: 1246067872 | F7: 45412 | H7: 2 | I7: Fertilizers | J7: 20696 | K7: 44973 | L7: 1010100 | M7: VENDAS MERCADO INTERNO | N7: 161 | O7: VENDA PROD. INDUSTRIALIZADO - NFE | P7: GRUPO LEANDRO SARTI | Q7: =$R$1-F7 -> 785 | R7: =_xlfn.XLOOKUP(P7,'Painel Fertilizers'!$B:$B,'Painel Fertilizers'!$B:$B,0) -> GRUPO LEANDRO SARTI
A8: 11207 | B8: S M AGRO | C8: 08.685.699/0001-82 | D8: 118231.86 | E8: 1246074301 | F8: 45412 | H8: 2 | I8: Fertilizers | J8: 21005 | K8: 45015 | L8: 1010100 | M8: VENDAS MERCADO INTERNO | N8: 161 | O8: VENDA PROD. INDUSTRIALIZADO - NFE | P8: GRUPO LEANDRO SARTI | Q8: =$R$1-F8 -> 785 | R8: =_xlfn.XLOOKUP(P8,'Painel Fertilizers'!$B:$B,'Painel Fertilizers'!$B:$B,0) -> GRUPO LEANDRO SARTI
A9: 11207 | B9: S M AGRO | C9: 08.685.699/0001-82 | D9: 91167.15 | E9: 1246075550 | F9: 45412 | H9: 2 | I9: Fertilizers | J9: 21053 | K9: 45022 | L9: 1010100 | M9: VENDAS MERCADO INTERNO | N9: 161 | O9: VENDA PROD. INDUSTRIALIZADO - NFE | P9: GRUPO LEANDRO SARTI | Q9: =$R$1-F9 -> 785 | R9: =_xlfn.XLOOKUP(P9,'Painel Fertilizers'!$B:$B,'Painel Fertilizers'!$B:$B,0) -> GRUPO LEANDRO SARTI
A10: 11207 | B10: S M AGRO | C10: 08.685.699/0001-82 | D10: 43771.16 | E10: 1246094423 | F10: 45423 | H10: 2 | I10: Fertilizers | J10: 356 | K10: 45133 | L10: 1010100 | M10: VENDAS MERCADO INTERNO | N10: 161 | O10: VENDA PROD. INDUSTRIALIZADO - NFE | P10: GRUPO LEANDRO SARTI | Q10: =$R$1-F10 -> 774 | R10: =_xlfn.XLOOKUP(P10,'Painel Fertilizers'!$B:$B,'Painel Fertilizers'!$B:$B,0) -> GRUPO LEANDRO SARTI
A11: 11207 | B11: S M AGRO | C11: 08.685.699/0001-82 | D11: 44760.26 | E11: 1246092027 | F11: 45504 | H11: 2 | I11: Fertilizers | J11: 138 | K11: 45119 | L11: 1010100 | M11: VENDAS MERCADO INTERNO | N11: 161 | O11: VENDA PROD. INDUSTRIALIZADO - NFE | P11: GRUPO LEANDRO SARTI | Q11: =$R$1-F11 -> 693 | R11: =_xlfn.XLOOKUP(P11,'Painel Fertilizers'!$B:$B,'Painel Fertilizers'!$B:$B,0) -> GRUPO LEANDRO SARTI
A12: 11207 | B12: S M AGRO | C12: 08.685.699/0001-82 | D12: 43771.16 | E12: 1246093362 | F12: 45417 | H12: 2 | I12: Fertilizers | J12: 253 | K12: 45127 | L12: 1010100 | M12: VENDAS MERCADO INTERNO | N12: 161 | O12: VENDA PROD. INDUSTRIALIZADO - NFE | P12: GRUPO LEANDRO SARTI | Q12: =$R$1-F12 -> 780 | R12: =_xlfn.XLOOKUP(P12,'Painel Fertilizers'!$B:$B,'Painel Fertilizers'!$B:$B,0) -> GRUPO LEANDRO SARTI
A13: 11207 | B13: S M AGRO | C13: 08.685.699/0001-82 | D13: 47925.4 | E13: 1246094864 | F13: 45544 | H13: 2 | I13: Fertilizers | J13: 407 | K13: 45135 | L13: 1010100 | M13: VENDAS MERCADO INTERNO | N13: 161 | O13: VENDA PROD. INDUSTRIALIZADO - NFE | P13: GRUPO LEANDRO SARTI | Q13: =$R$1-F13 -> 653 | R13: =_xlfn.XLOOKUP(P13,'Painel Fertilizers'!$B:$B,'Painel Fertilizers'!$B:$B,0) -> GRUPO LEANDRO SARTI
A14: 11207 | B14: S M AGRO | C14: 08.685.699/0001-82 | D14: 106301.38 | E14: 1246094863 | F14: 45425 | H14: 2 | I14: Fertilizers | J14: 406 | K14: 45135 | L14: 1010100 | M14: VENDAS MERCADO INTERNO | N14: 161 | O14: VENDA PROD. INDUSTRIALIZADO - NFE | P14: GRUPO LEANDRO SARTI | Q14: =$R$1-F14 -> 772 | R14: =_xlfn.XLOOKUP(P14,'Painel Fertilizers'!$B:$B,'Painel Fertilizers'!$B:$B,0) -> GRUPO LEANDRO SARTI
... A256: 16107 | B256: CONNTACTA AGRONEGOCIOS | C256: 54.764.341/0001-62 | D256: 2217.78 | E256: 1246235696 | F256: 46265 | H256: 2 | I256: Fertilizers | J256: 9248 | K256: 45908 | L256: 1010100 | M256: VENDAS MERCADO INTERNO | N256: 161 | O256: VENDA PROD. INDUSTRIALIZADO - NFE | P256: CONNTACTA AGRONEGOCIOS | Q256: =$R$1-F256 -> -68 | R256: =_xlfn.XLOOKUP(P256,'Painel Fertilizers'!$B:$B,'Painel Fertilizers'!$B:$B,0) -> CONNTACTA AGRONEGOCIOS
Q257: =$R$1-F257 -> 46197 | R257: =_xlfn.XLOOKUP(P257,'Painel Fertilizers'!$B:$B,'Painel Fertilizers'!$B:$B,0) -> 0
Q258: =$R$1-F258 -> 46197 | R258: =_xlfn.XLOOKUP(P258,'Painel Fertilizers'!$B:$B,'Painel Fertilizers'!$B:$B,0) -> 0
Q259: =$R$1-F259 -> 46197 | R259: =_xlfn.XLOOKUP(P259,'Painel Fertilizers'!$B:$B,'Painel Fertilizers'!$B:$B,0) -> 0
Q260: =$R$1-F260 -> 46197 | R260: =_xlfn.XLOOKUP(P260,'Painel Fertilizers'!$B:$B,'Painel Fertilizers'!$B:$B,0) -> 0
Q261: =$R$1-F261 -> 46197 | R261: =_xlfn.XLOOKUP(P261,'Painel Fertilizers'!$B:$B,'Painel Fertilizers'!$B:$B,0) -> 0
Q262: =$R$1-F262 -> 46197 | R262: =_xlfn.XLOOKUP(P262,'Painel Fertilizers'!$B:$B,'Painel Fertilizers'!$B:$B,0) -> 0
Q263: =$R$1-F263 -> 46197 | R263: =_xlfn.XLOOKUP(P263,'Painel Fertilizers'!$B:$B,'Painel Fertilizers'!$B:$B,0) -> 0
Q264: =$R$1-F264 -> 46197 | R264: =_xlfn.XLOOKUP(P264,'Painel Fertilizers'!$B:$B,'Painel Fertilizers'!$B:$B,0) -> 0
Q265: =$R$1-F265 -> 46197 | R265: =_xlfn.XLOOKUP(P265,'Painel Fertilizers'!$B:$B,'Painel Fertilizers'!$B:$B,0) -> 0
Q266: =$R$1-F266 -> 46197 | R266: =_xlfn.XLOOKUP(P266,'Painel Fertilizers'!$B:$B,'Painel Fertilizers'!$B:$B,0) -> 0
Q267: =$R$1-F267 -> 46197 | R267: =_xlfn.XLOOKUP(P267,'Painel Fertilizers'!$B:$B,'Painel Fertilizers'!$B:$B,0) -> 0
Q268: =$R$1-F268 -> 46197 | R268: =_xlfn.XLOOKUP(P268,'Painel Fertilizers'!$B:$B,'Painel Fertilizers'!$B:$B,0) -> 0
... Q391: =$R$1-F391 -> 46197 | R391: =_xlfn.XLOOKUP(P391,'Painel Fertilizers'!$B:$B,'Painel Fertilizers'!$B:$B,0) -> 0
R392: =_xlfn.XLOOKUP(P392,'Painel Fertilizers'!$B:$B,'Painel Fertilizers'!$B:$B,0) -> 0

Sheet Clientes Consolidado.
C1: 46198 | H1: =SUBTOTAL(9,H4:H1048576) -> 63971254 | I1: =SUBTOTAL(9,I4:I1048576) -> 623406.28 | J1: =SUBTOTAL(9,J4:J1048576) -> 416870.25 | K1: =SUBTOTAL(9,K4:K1048576) -> 0 | L1: =SUBTOTAL(9,L4:L1048576) -> 49440 | M1: =SUBTOTAL(9,M4:M1048576) -> 0 | N1: =SUBTOTAL(9,N4:N1048576) -> 463311.48 | O1: =SUBTOTAL(9,O4:O1048576) -> 21875863 | ... Y1: =SUBTOTAL(9,Y4:Y1048576) -> 11105144 | AB1: =SUBTOTAL(9,AB4:AB1048576) -> 92880500 | AH1: =SUBTOTAL(9,AH4:AH1044286) -> 31597220 | AJ1: =P1/H1 -> 0.36624092
I2: Aging Overdue | R2: Aging Not Due | AJ2: Treasury Risk Status
A3: x | B3: BU | C3: CUSTOMER | D3: RATING | F3: Approved Credit | G3: Credit Balance | H3: Total AR | I3: 1-30 Days | J3: 31-60 Days | K3: 61-90 Days | L3: 91-120 Days | M3: 121-180 Days | N3: 181-360 Days | O3: Above 360 Days | P3: Overdue | Q3: Not Due | R3: 1-30 Days | S3: 31-60 Days | T3: 61-90 Days | U3: 91-120 Days | V3: 121-180 Days | W3: 181-360 Days | X3: Above 360 Days | Y3: Bad debt provision | Z3: x | AA3: x | AB3: Credit Insurance | AC3: Guarantee Value | AD3: Type | AE3: Due Date | AF3: Tenor | AG3: x | AH3: Open Exposure | AI3: x | AJ3: Probable | AK3: Possible | AL3: Rare
B4: =_xlfn.XLOOKUP(C4,'Info Clientes'!A:A,'Info Clientes'!B:B) -> Additive | C4: GRUPO MOSAIC FERTILIZANTES P K LTDA | D4: B | F4: 10000000 | G4: 2303506.4 | H4: 7696493.6 | I4: 0 | J4: 0 | K4: 0 | L4: 0 | M4: 0 | N4: 0 | O4: 0 | P4: 0 | Q4: 7696493.6 | R4: 2989374.9 | S4: 1924024.8 | T4: 2535256.7 | U4: 247837.21 | V4: 0 | W4: 0 | X4: 0 | Y4: 16500 | AB4: 10000000 | AH4: =MAX(H4-AB4,0) -> 0
B5: =_xlfn.XLOOKUP(C5,'Info Clientes'!A:A,'Info Clientes'!B:B) -> Fertilizer / Litigation | C5: CENTRAL DO ADUBO COM E REPRESENTACAO LTD | D5: 0 | F5: 0 | G5: -7560727.8 | H5: 7560727.8 | I5: 0 | J5: 0 | K5: 0 | L5: 0 | M5: 0 | N5: 0 | O5: 7560727.8 | P5: 7560727.8 | Q5: 0 | R5: 0 | S5: 0 | T5: 0 | U5: 0 | V5: 0 | W5: 0 | X5: 0 | Y5: 0 | AB5: 0 | AH5: =MAX(H5-AB5,0) -> 7560727.8
B6: =_xlfn.XLOOKUP(C6,'Info Clientes'!A:A,'Info Clientes'!B:B) -> Additive | C6: GRUPO MOSAIC FERTILIZANTES DO BRASIL | D6: B | F6: 15000000 | G6: 7509591.4 | H6: 7490408.6 | I6: 0 | J6: 0 | K6: 0 | L6: 0 | M6: 0 | N6: 64.2 | O6: 16754.72 | P6: 16818.92 | Q6: 7473589.6 | R6: 746905.4 | S6: 2076080.5 | T6: 4650603.8 | U6: 0 | V6: 0 | W6: 0 | X6: 0 | Y6: 84619.766 | AB6: 15000000 | AH6: =MAX(H6-AB6,0) -> 0
B7: =_xlfn.XLOOKUP(C7,'Info Clientes'!A:A,'Info Clientes'!B:B) -> Additive | C7: GRUPO YARA | D7: B | F7: 6000000 | G7: 1215850 | H7: 4784150 | I7: 0 | J7: 0 | K7: 0 | L7: 0 | M7: 0 | N7: 0 | O7: 5626.32 | P7: 5626.32 | Q7: 4778523.7 | R7: 3419201.1 | S7: 1359322.6 | T7: 0 | U7: 0 | V7: 0 | W7: 0 | X7: 0 | Y7: 63226.32 | AB7: 6000000 | AH7: =MAX(H7-AB7,0) -> 0
B8: =_xlfn.XLOOKUP(C8,'Info Clientes'!A:A,'Info Clientes'!B:B) -> Additive Intl. | C8: NITROFERT SAS - COLOMBIA | D8: 0 | F8: 5000000 | G8: 1225424.6 | H8: 3774575.4 | I8: 0 | J8: 0 | K8: 0 | L8: 0 | M8: 0 | N8: 0 | O8: 0 | P8: 0 | Q8: 3774575.4 | R8: 0 | S8: 668371.59 | T8: 3106203.8 | U8: 0 | V8: 0 | W8: 0 | X8: 0 | Y8: 0 | AB8: 0 | AH8: =MAX(H8-AB8,0) -> 3774575.4
B9: =_xlfn.XLOOKUP(C9,'Info Clientes'!A:A,'Info Clientes'!B:B) -> Fertilizer / Litigation | C9: GRUPO LEANDRO SARTI | D9: 0 | F9: 0 | G9: -3088531.1 | H9: 3088531.1 | I9: 0 | J9: 0 | K9: 0 | L9: 0 | M9: 0 | N9: 0 | O9: 3088531.1 | P9: 3088531.1 | Q9: 0 | R9: 0 | S9: 0 | T9: 0 | U9: 0 | V9: 0 | W9: 0 | X9: 0 | Y9: 3088531.1 | AB9: 0 | AH9: =MAX(H9-AB9,0) -> 3088531.1
B10: =_xlfn.XLOOKUP(C10,'Info Clientes'!A:A,'Info Clientes'!B:B) -> Fertilizer / Litigation | C10: AGRO BERALDO | D10: 0 | F10: 0 | G10: -3044850.9 | H10: 3044850.9 | I10: 0 | J10: 0 | K10: 0 | L10: 0 | M10: 0 | N10: 0 | O10: 3044850.9 | P10: 3044850.9 | Q10: 0 | R10: 0 | S10: 0 | T10: 0 | U10: 0 | V10: 0 | W10: 0 | X10: 0 | Y10: 3044850.9 | AB10: 0 | AH10: =MAX(H10-AB10,0) -> 3044850.9
B11: =_xlfn.XLOOKUP(C11,'Info Clientes'!A:A,'Info Clientes'!B:B) -> Fertilizer / Litigation | C11: TERRA FERTIL - MACHADO | D11: 0 | F11: 0 | G11: -2492842.1 | H11: 2492842.1 | I11: 0 | J11: 0 | K11: 0 | L11: 0 | M11: 0 | N11: 0 | O11: 2492842.1 | P11: 2492842.1 | Q11: 0 | R11: 0 | S11: 0 | T11: 0 | U11: 0 | V11: 0 | W11: 0 | X11: 0 | Y11: 0 | AB11: 0 | AH11: =MAX(H11-AB11,0) -> 2492842.1
B12: =_xlfn.XLOOKUP(C12,'Info Clientes'!A:A,'Info Clientes'!B:B) -> Fertilizer / Litigation | C12: MOGIANA TECNO AGRO | D12: 0 | F12: 0 | G12: -1863200.9 | H12: 1863200.9 | I12: 0 | J12: 0 | K12: 0 | L12: 0 | M12: 0 | N12: 0 | O12: 1863200.9 | P12: 1863200.9 | Q12: 0 | R12: 0 | S12: 0 | T12: 0 | U12: 0 | V12: 0 | W12: 0 | X12: 0 | Y12: 1863200.9 | AB12: 0 | AH12: =MAX(H12-AB12,0) -> 1863200.9
B13: =_xlfn.XLOOKUP(C13,'Info Clientes'!A:A,'Info Clientes'!B:B) -> Fertilizer / Litigation | C13: CASA DAS SEMENTES | D13: 0 | F13: 0 | G13: -1702848.7 | H13: 1702848.7 | I13: 0 | J13: 0 | K13: 0 | L13: 0 | M13: 0 | N13: 0 | O13: 1702848.7 | P13: 1702848.7 | Q13: 0 | R13: 0 | S13: 0 | T13: 0 | U13: 0 | V13: 0 | W13: 0 | X13: 0 | Y13: 1702848.7 | AB13: 0 | AH13: =MAX(H13-AB13,0) -> 1702848.7
B14: =_xlfn.XLOOKUP(C14,'Info Clientes'!A:A,'Info Clientes'!B:B) -> Additive | C14: EUROCHEM SERRA DO SALITRE | D14: 0 | F14: 1500000 | G14: 251851.4 | H14: 1248148.6 | I14: 0 | J14: 0 | K14: 0 | L14: 0 | M14: 0 | N14: 0 | O14: 0 | P14: 0 | Q14: 1248148.6 | R14: 161488.2 | S14: 1086660.4 | T14: 0 | U14: 0 | V14: 0 | W14: 0 | X14: 0 | Y14: 0 | AB14: 0 | AH14: =MAX(H14-AB14,0) -> 1248148.6
B15: =_xlfn.XLOOKUP(C15,'Info Clientes'!A:A,'Info Clientes'!B:B) -> Additive | C15: GRUPO FERTILIZ TOCANTINS | D15: 0 | F15: 1500000 | G15: 262380.1 | H15: 1237619.9 | I15: 0 | J15: 0 | K15: 0 | L15: 0 | M15: 0 | N15: 0 | O15: 0 | P15: 0 | Q15: 1237619.9 | R15: 331136.7 | S15: 906483.2 | T15: 0 | U15: 0 | V15: 0 | W15: 0 | X15: 0 | Y15: 0 | AB15: 0 | AH15: =MAX(H15-AB15,0) -> 1237619.9
B16: =_xlfn.XLOOKUP(C16,'Info Clientes'!A:A,'Info Clientes'!B:B) -> Fertilizer / Litigation | C16: FAZENDA ARCOS SÃO JOÃO | D16: 0 | F16: 0 | G16: -988506.24 | H16: 988506.24 | I16: 0 | J16: 0 | K16: 0 | L16: 0 | M16: 0 | N16: 462720 | O16: 525786.24 | P16: 988506.24 | Q16: 0 | R16: 0 | S16: 0 | T16: 0 | U16: 0 | V16: 0 | W16: 0 | X16: 0 | Y16: 539667.84 | AB16: 0 | AH16: =MAX(H16-AB16,0) -> 988506.24
B17: =_xlfn.XLOOKUP(C17,'Info Clientes'!A:A,'Info Clientes'!B:B) -> Fertilizer | C17: AGROVIVA | D17: B | F17: 500000 | G17: -425457.06 | H17: 925457.06 | I17: 0 | J17: 0 | K17: 0 | L17: 0 | M17: 0 | N17: 0 | O17: 0 | P17: 0 | Q17: 925457.06 | R17: 0 | S17: 0 | T17: 925457.06 | U17: 0 | V17: 0 | W17: 0 | X17: 0 | Y17: 0 | AB17: 500000 | AH17: =MAX(H17-AB17,0) -> 425457.06
B18: =_xlfn.XLOOKUP(C18,'Info Clientes'!A:A,'Info Clientes'!B:B) -> Fertilizer / Litigation | C18: CBM FERTILIZANTES | D18: 0 | F18: 0 | G18: -876011.75 | H18: 876011.75 | I18: 0 | J18: 0 | K18: 0 | L18: 0 | M18: 0 | N18: 0 | O18: 876011.75 | P18: 876011.75 | Q18: 0 | R18: 0 | S18: 0 | T18: 0 | U18: 0 | V18: 0 | W18: 0 | X18: 0 | Y18: 0 | AB18: 0 | AH18: =MAX(H18-AB18,0) -> 876011.75
B19: =_xlfn.XLOOKUP(C19,'Info Clientes'!A:A,'Info Clientes'!B:B) -> Additive | C19: GRUPO FERTIPAR FERTILIZANTES MATO GROSSO | D19: B | F19: 1500000 | G19: 684114.4 | H19: 815885.6 | I19: 0 | J19: 0 | K19: 0 | L19: 0 | M19: 0 | N19: 0 | O19: 0 | P19: 0 | Q19: 815885.6 | R19: 815885.6 | S19: 0 | T19: 0 | U19: 0 | V19: 0 | W19: 0 | X19: 0 | Y19: 0 | AB19: 1500000 | AH19: =MAX(H19-AB19,0) -> 0
B20: =_xlfn.XLOOKUP(C20,'Info Clientes'!A:A,'Info Clientes'!B:B) -> Fertilizer | C20: CONNTACTA AGRONEGOCIOS | D20: E | E20: 180 | F20: 500000 | G20: -239540.06 | H20: 739540.06 | I20: 0 | J20: 0 | K20: 0 | L20: 0 | M20: 0 | N20: 0 | O20: 0 | P20: 0 | Q20: 739540.06 | R20: 0 | S20: 0 | T20: 739540.06 | U20: 0 | V20: 0 | W20: 0 | X20: 0 | Y20: 0 | AB20: 500000 | AH20: =MAX(H20-AB20,0) -> 239540.06
B21: =_xlfn.XLOOKUP(C21,'Info Clientes'!A:A,'Info Clientes'!B:B) -> Additive | C21: STRATOS - ROSARIO DO CATETE | D21: A | F21: 1500000 | G21: 789120.8 | H21: 710879.2 | I21: 0 | J21: 0 | K21: 0 | L21: 0 | M21: 0 | N21: 0 | O21: 0 | P21: 0 | Q21: 710879.2 | R21: 0 | S21: 355675.6 | T21: 355203.6 | U21: 0 | V21: 0 | W21: 0 | X21: 0 | Y21: 1800 | AB21: 1500000 | AH21: =MAX(H21-AB21,0) -> 0
B22: =_xlfn.XLOOKUP(C22,'Info Clientes'!A:A,'Info Clientes'!B:B) -> Additive | C22: FOSNOR - LUIS EDUARDO MAGALHAES | D22: B | F22: 2600000 | G22: 1906272.9 | H22: 693727.1 | I22: 0 | J22: 0 | K22: 0 | L22: 0 | M22: 0 | N22: 0 | O22: 0 | P22: 0 | Q22: 693727.1 | R22: 693727.1 | S22: 0 | T22: 0 | U22: 0 | V22: 0 | W22: 0 | X22: 0 | Y22: 0 | AB22: 2600000 | AH22: =MAX(H22-AB22,0) -> 0
B23: =_xlfn.XLOOKUP(C23,'Info Clientes'!A:A,'Info Clientes'!B:B) -> Additive Intl. | C23: YTL S.A. - PARAGUAI | D23: B | F23: 750000 | G23: 104359.17 | H23: 645640.83 | I23: 191959.21 | J23: 0 | K23: 0 | L23: 0 | M23: 0 | N23: 0 | O23: 0 | P23: 191959.21 | Q23: 453681.62 | R23: 453681.62 | S23: 0 | T23: 0 | U23: 0 | V23: 0 | W23: 0 | X23: 0 | Y23: 0 | AB23: 550000 | AH23: =MAX(H23-AB23,0) -> 95640.83
B24: =_xlfn.XLOOKUP(C24,'Info Clientes'!A:A,'Info Clientes'!B:B) -> Additive Intl. | C24: ISUSA - URUGUAI | D24: A | F24: 1375000 | G24: 769948.96 | H24: 605051.04 | I24: 0 | J24: 0 | K24: 0 | L24: 0 | M24: 0 | N24: 0 | O24: 0 | P24: 0 | Q24: 605051.04 | R24: 605051.04 | S24: 0 | T24: 0 | U24: 0 | V24: 0 | W24: 0 | X24: 0 | Y24: 0 | AB24: 1375000 | AH24: =MAX(H24-AB24,0) -> 0
B25: =_xlfn.XLOOKUP(C25,'Info Clientes'!A:A,'Info Clientes'!B:B) -> Additive | C25: GRUPO HERINGER | D25: 0 | F25: 800000 | G25: 246271.39 | H25: 553728.61 | I25: 0 | J25: 0 | K25: 0 | L25: 0 | M25: 0 | N25: 0 | O25: 0 | P25: 0 | Q25: 553728.61 | R25: 456958.6 | S25: 0 | T25: 0 | U25: 0 | V25: 0 | W25: 0 | X25: 96770.01 | Y25: 0 | AB25: 0 | AH25: =MAX(H25-AB25,0) -> 553728.61
B26: =_xlfn.XLOOKUP(C26,'Info Clientes'!A:A,'Info Clientes'!B:B) -> Additive Intl. | C26: MOSAIC FERTILIZANTES PARAGUAY S.R.L. | D26: B | F26: 660000 | G26: 122302.2 | H26: 537697.8 | I26: 0 | J26: 0 | K26: 0 | L26: 0 | M26: 0 | N26: 0 | O26: 0 | P26: 0 | Q26: 537697.8 | R26: 0 | S26: 91784.41 | T26: 445913.39 | U26: 0 | V26: 0 | W26: 0 | X26: 0 | Y26: 0 | AB26: 660000 | AH26: =MAX(H26-AB26,0) -> 0
B27: =_xlfn.XLOOKUP(C27,'Info Clientes'!A:A,'Info Clientes'!B:B) -> Additive | C27: FERTGROW S.A | D27: B | F27: 3500000 | G27: 2973147.5 | H27: 526852.5 | I27: 0 | J27: 0 | K27: 0 | L27: 0 | M27: 0 | N27: 0 | O27: 0 | P27: 0 | Q27: 526852.5 | R27: 526852.5 | S27: 0 | T27: 0 | U27: 0 | V27: 0 | W27: 0 | X27: 0 | Y27: 0 | AB27: 3500000 | AH27: =MAX(H27-AB27,0) -> 0
B28: =_xlfn.XLOOKUP(C28,'Info Clientes'!A:A,'Info Clientes'!B:B) -> Additive | C28: ULTRAFERTIL | D28: B | F28: 1500000 | G28: 980391.4 | H28: 519608.6 | I28: 0 | J28: 0 | K28: 0 | L28: 0 | M28: 0 | N28: 0 | O28: 0 | P28: 0 | Q28: 519608.6 | R28: 394528.6 | S28: 125080 | T28: 0 | U28: 0 | V28: 0 | W28: 0 | X28: 0 | Y28: 0 | AB28: 1500000 | AH28: =MAX(H28-AB28,0) -> 0
B29: =_xlfn.XLOOKUP(C29,'Info Clientes'!A:A,'Info Clientes'!B:B) -> Additive | C29: GRUPO UNIFERTIL | D29: B | F29: 4500000 | G29: 4037070.2 | H29: 462929.8 | I29: 0 | J29: 0 | K29: 0 | L29: 0 | M29: 0 | N29: 0 | O29: 0 | P29: 0 | Q29: 462929.8 | R29: 462929.8 | S29: 0 | T29: 0 | U29: 0 | V29: 0 | W29: 0 | X29: 0 | Y29: 0 | AB29: 4500000 | AH29: =MAX(H29-AB29,0) -> 0
B30: =_xlfn.XLOOKUP(C30,'Info Clientes'!A:A,'Info Clientes'!B:B) -> Additive | C30: GRUPO AMAGGI | D30: B | F30: 4000000 | G30: 3594860 | H30: 405140 | I30: 0 | J30: 0 | K30: 0 | L30: 0 | M30: 0 | N30: 0 | O30: 0 | P30: 0 | Q30: 405140 | R30: 268136.7 | S30: 137003.3 | T30: 0 | U30: 0 | V30: 0 | W30: 0 | X30: 0 | Y30: 0 | AB30: 4000000 | AH30: =MAX(H30-AB30,0) -> 0
B31: =_xlfn.XLOOKUP(C31,'Info Clientes'!A:A,'Info Clientes'!B:B) -> Additive | C31: GRUPO CIBRA | D31: B | F31: 1158000 | G31: 769074.2 | H31: 388925.8 | I31: 0 | J31: 0 | K31: 0 | L31: 0 | M31: 0 | N31: 0 | O31: 0 | P31: 0 | Q31: 388925.8 | R31: 388925.8 | S31: 0 | T31: 0 | U31: 0 | V31: 0 | W31: 0 | X31: 0 | Y31: 1200 | AB31: 1158000 | AH31: =MAX(H31-AB31,0) -> 0
B32: =_xlfn.XLOOKUP(C32,'Info Clientes'!A:A,'Info Clientes'!B:B) -> Additive | C32: ADUFERTIL JUNDIAI | D32: B | F32: 3000000 | G32: 2617438.5 | H32: 382561.45 | I32: 0 | J32: 0 | K32: 0 | L32: 0 | M32: 0 | N32: 0 | O32: 0 | P32: 0 | Q32: 382561.45 | R32: 0 | S32: 382561.45 | T32: 0 | U32: 0 | V32: 0 | W32: 0 | X32: 0 | Y32: 0 | AB32: 3000000 | AH32: =MAX(H32-AB32,0) -> 0
B33: =_xlfn.XLOOKUP(C33,'Info Clientes'!A:A,'Info Clientes'!B:B) -> Additive | C33: FECOAGRO FEDERACAO DAS COOPERATIVAS | D33: B | F33: 3000000 | G33: 2618440.8 | H33: 381559.2 | I33: 0 | J33: 0 | K33: 0 | L33: 0 | M33: 0 | N33: 0 | O33: 0 | P33: 0 | Q33: 381559.2 | R33: 381559.2 | S33: 0 | T33: 0 | U33: 0 | V33: 0 | W33: 0 | X33: 0 | Y33: 0 | AB33: 3000000 | AH33: =MAX(H33-AB33,0) -> 0
B34: =_xlfn.XLOOKUP(C34,'Info Clientes'!A:A,'Info Clientes'!B:B) -> Fertilizer | C34: FAZENDA FERRADURA | D34: 0 | F34: 0 | G34: -329327.91 | H34: 329327.91 | I34: 0 | J34: 329327.91 | K34: 0 | L34: 0 | M34: 0 | N34: 0 | O34: 0 | P34: 329327.91 | Q34: 0 | R34: 0 | S34: 0 | T34: 0 | U34: 0 | V34: 0 | W34: 0 | X34: 0 | Y34: 0 | AB34: 0 | AH34: =MAX(H34-AB34,0) -> 329327.91
B35: =_xlfn.XLOOKUP(C35,'Info Clientes'!A:A,'Info Clientes'!B:B) -> Additive | C35: BENTONIT UNIAO - CAMPINA GRANDE | D35: B | F35: 700000 | G35: 382725 | H35: 317275 | I35: 0 | J35: 0 | K35: 0 | L35: 0 | M35: 0 | N35: 0 | O35: 0 | P35: 0 | Q35: 317275 | R35: 317275 | S35: 0 | T35: 0 | U35: 0 | V35: 0 | W35: 0 | X35: 0 | Y35: 0 | AB35: 700000 | AH35: =MAX(H35-AB35,0) -> 0
B36: =_xlfn.XLOOKUP(C36,'Info Clientes'!A:A,'Info Clientes'!B:B) -> Additive Intl. | C36: BUNGE PARAGUAY S.A | D36: B | F36: 1650000 | G36: 1342559.4 | H36: 307440.65 | I36: 0 | J36: 0 | K36: 0 | L36: 0 | M36: 0 | N36: 0 | O36: 0 | P36: 0 | Q36: 307440.65 | R36: 307440.65 | S36: 0 | T36: 0 | U36: 0 | V36: 0 | W36: 0 | X36: 0 | Y36: 0 | AB36: 1650000 | AH36: =MAX(H36-AB36,0) -> 0
B37: =_xlfn.XLOOKUP(C37,'Info Clientes'!A:A,'Info Clientes'!B:B) -> Fertilizer | C37: AGROREP. REPRESENTACOES AGRICOLAS | D37: B | E37: 180 | F37: 1000000 | G37: 700357.92 | H37: 299642.08 | I37: 0 | J37: 0 | K37: 0 | L37: 0 | M37: 0 | N37: 0 | O37: 0 | P37: 0 | Q37: 299642.08 | R37: 0 | S37: 0 | T37: 0 | U37: 0 | V37: 299642.08 | W37: 0 | X37: 0 | Y37: 0 | AB37: 1000000 | AH37: =MAX(H37-AB37,0) -> 0
B38: =_xlfn.XLOOKUP(C38,'Info Clientes'!A:A,'Info Clientes'!B:B) -> Fertilizer | C38: ADUFÉRTIL - CAMPEVO | D38: B | E38: 180 | F38: 3000000 | G38: 2708975.1 | H38: 291024.86 | I38: 0 | J38: 0 | K38: 0 | L38: 0 | M38: 0 | N38: 0 | O38: 0 | P38: 0 | Q38: 291024.86 | R38: 72587.79 | S38: 218437.07 | T38: 0 | U38: 0 | V38: 0 | W38: 0 | X38: 0 | Y38: 0 | AB38: 3000000 | AH38: =MAX(H38-AB38,0) -> 0
B39: =_xlfn.XLOOKUP(C39,'Info Clientes'!A:A,'Info Clientes'!B:B) -> Additive Intl. | C39: TECNOMYL S.A. - PARAGUAY | D39: B | F39: 990000 | G39: 724957.42 | H39: 265042.58 | I39: 0 | J39: 0 | K39: 0 | L39: 0 | M39: 0 | N39: 0 | O39: 0 | P39: 0 | Q39: 265042.58 | R39: 265042.58 | S39: 0 | T39: 0 | U39: 0 | V39: 0 | W39: 0 | X39: 0 | Y39: 0 | AB39: 990000 | AH39: =MAX(H39-AB39,0) -> 0
B40: =_xlfn.XLOOKUP(C40,'Info Clientes'!A:A,'Info Clientes'!B:B) -> Additive Intl. | C40: ABOPAR - PARAGUAY | D40: B | F40: 275000 | G40: 10165.16 | H40: 264834.84 | I40: 133551.97 | J40: 0 | K40: 0 | L40: 0 | M40: 0 | N40: 0 | O40: 0 | P40: 133551.97 | Q40: 131282.87 | R40: 0 | S40: 131282.87 | T40: 0 | U40: 0 | V40: 0 | W40: 0 | X40: 0 | Y40: 0 | AB40: 275000 | AH40: =MAX(H40-AB40,0) -> 0
B41: =_xlfn.XLOOKUP(C41,'Info Clientes'!A:A,'Info Clientes'!B:B) -> Additive | C41: BIGFERTIL - CANDEIAS | D41: O | F41: 300000 | G41: 57434.12 | H41: 242565.88 | I41: 0 | J41: 0 | K41: 0 | L41: 0 | M41: 0 | N41: 0 | O41: 0 | P41: 0 | Q41: 242565.88 | R41: 121282.94 | S41: 121282.94 | T41: 0 | U41: 0 | V41: 0 | W41: 0 | X41: 0 | Y41: 0 | AB41: 0 | AH41: =MAX(H41-AB41,0) -> 242565.88
B42: =_xlfn.XLOOKUP(C42,'Info Clientes'!A:A,'Info Clientes'!B:B) -> Fertilizer / Litigation | C42: GRUPO TRIANGULO AGRO | D42: 0 | F42: 0 | G42: -237309.12 | H42: 237309.12 | I42: 0 | J42: 0 | K42: 0 | L42: 0 | M42: 0 | N42: 0 | O42: 237309.12 | P42: 237309.12 | Q42: 0 | R42: 0 | S42: 0 | T42: 0 | U42: 0 | V42: 0 | W42: 0 | X42: 0 | Y42: 237309.12 | AB42: 0 | AH42: =MAX(H42-AB42,0) -> 237309.12
B43: =_xlfn.XLOOKUP(C43,'Info Clientes'!A:A,'Info Clientes'!B:B) -> Additive | C43: AURORA MINERAÇÃO LTDA | D43: 0 | F43: 270000 | G43: 41072.6 | H43: 228927.4 | I43: 76320.4 | J43: 0 | K43: 0 | L43: 0 | M43: 0 | N43: 0 | O43: 0 | P43: 76320.4 | Q43: 152607 | R43: 76134.5 | S43: 76472.5 | T43: 0 | U43: 0 | V43: 0 | W43: 0 | X43: 0 | Y43: 0 | AB43: 0 | AH43: =MAX(H43-AB43,0) -> 228927.4
B44: =_xlfn.XLOOKUP(C44,'Info Clientes'!A:A,'Info Clientes'!B:B) -> Additive / Litigation | C44: TERRA FERTILIZANTES LTDA - ARAXÁ | D44: 0 | F44: 0 | G44: -226233.6 | H44: 226233.6 | I44: 0 | J44: 0 | K44: 0 | L44: 0 | M44: 0 | N44: 0 | O44: 226233.6 | P44: 226233.6 | Q44: 0 | R44: 0 | S44: 0 | T44: 0 | U44: 0 | V44: 0 | W44: 0 | X44: 0 | Y44: 226233.6 | AB44: 0 | AH44: =MAX(H44-AB44,0) -> 226233.6
B45: =_xlfn.XLOOKUP(C45,'Info Clientes'!A:A,'Info Clientes'!B:B) -> Additive / Litigation | C45: ITERUM - RONDONOPOLIS | D45: 0 | F45: 0 | G45: -213750 | H45: 213750 | I45: 0 | J45: 0 | K45: 0 | L45: 0 | M45: 0 | N45: 0 | O45: 213750 | P45: 213750 | Q45: 0 | R45: 0 | S45: 0 | T45: 0 | U45: 0 | V45: 0 | W45: 0 | X45: 0 | Y45: 213750 | AB45: 0 | AH45: =MAX(H45-AB45,0) -> 213750
B46: =_xlfn.XLOOKUP(C46,'Info Clientes'!A:A,'Info Clientes'!B:B) -> Additive | C46: GRUPO JOSAPAR | D46: B | F46: 1000000 | G46: 814960 | H46: 185040 | I46: 0 | J46: 0 | K46: 0 | L46: 0 | M46: 0 | N46: 0 | O46: 0 | P46: 0 | Q46: 185040 | R46: 0 | S46: 185040 | T46: 0 | U46: 0 | V46: 0 | W46: 0 | X46: 0 | Y46: 0 | AB46: 1000000 | AH46: =MAX(H46-AB46,0) -> 0
B47: =_xlfn.XLOOKUP(C47,'Info Clientes'!A:A,'Info Clientes'!B:B) -> Additive | C47: GRUPO FERTIPAR FERTILIZANTES PARANA | D47: B | F47: 1500000 | G47: 1319640.8 | H47: 180359.2 | I47: 0 | J47: 0 | K47: 0 | L47: 0 | M47: 0 | N47: 0 | O47: 0 | P47: 0 | Q47: 180359.2 | R47: 180359.2 | S47: 0 | T47: 0 | U47: 0 | V47: 0 | W47: 0 | X47: 0 | Y47: 0 | AB47: 1500000 | AH47: =MAX(H47-AB47,0) -> 0
B48: =_xlfn.XLOOKUP(C48,'Info Clientes'!A:A,'Info Clientes'!B:B) -> Additive Intl. | C48: GOTLAND EQUADOR (SOLINAG) | D48: 0 | F48: 200000 | G48: 20525.42 | H48: 179474.58 | I48: 45718.46 | J48: 0 | K48: 0 | L48: 0 | M48: 0 | N48: 0 | O48: 0 | P48: 45718.46 | Q48: 133756.12 | R48: 0 | S48: 0 | T48: 133756.12 | U48: 0 | V48: 0 | W48: 0 | X48: 0 | Y48: 0 | AB48: 0 | AH48: =MAX(H48-AB48,0) -> 179474.58
B49: =_xlfn.XLOOKUP(C49,'Info Clientes'!A:A,'Info Clientes'!B:B) -> Additive Intl. | C49: FERMAGRI S.A - EQUADOR | D49: A | F49: 770000 | G49: 594724.76 | H49: 175275.24 | I49: 175275.24 | J49: 0 | K49: 0 | L49: 0 | M49: 0 | N49: 0 | O49: 0 | P49: 175275.24 | Q49: 0 | R49: 0 | S49: 0 | T49: 0 | U49: 0 | V49: 0 | W49: 0 | X49: 0 | Y49: 0 | AB49: 770000 | AH49: =MAX(H49-AB49,0) -> 0
B50: =_xlfn.XLOOKUP(C50,'Info Clientes'!A:A,'Info Clientes'!B:B) -> Additive | C50: GRUPO ADUBOS ARAGUAIA | D50: B | F50: 500000 | G50: 329040.6 | H50: 170959.4 | I50: 0 | J50: 0 | K50: 0 | L50: 0 | M50: 0 | N50: 0 | O50: 0 | P50: 0 | Q50: 170959.4 | R50: 65330 | S50: 105629.4 | T50: 0 | U50: 0 | V50: 0 | W50: 0 | X50: 0 | Y50: 0 | AB50: 500000 | AH50: =MAX(H50-AB50,0) -> 0
B51: =_xlfn.XLOOKUP(C51,'Info Clientes'!A:A,'Info Clientes'!B:B) -> Additive Intl. | C51: FERTIMAX PARAGUAY | D51: A | F51: 1375000 | G51: 1208838.6 | H51: 166161.39 | I51: 0 | J51: 0 | K51: 0 | L51: 0 | M51: 0 | N51: 0 | O51: 0 | P51: 0 | Q51: 166161.39 | R51: 166161.39 | S51: 0 | T51: 0 | U51: 0 | V51: 0 | W51: 0 | X51: 0 | Y51: 0 | AB51: 1375000 | AH51: =MAX(H51-AB51,0) -> 0
B52: =_xlfn.XLOOKUP(C52,'Info Clientes'!A:A,'Info Clientes'!B:B) -> Additive Intl. | C52: EVOAGRO NUTRICION S.A.S - COLOMBIA | D52: 0 | F52: 200000 | G52: 35702.95 | H52: 164297.05 | I52: 0 | J52: 0 | K52: 0 | L52: 0 | M52: 0 | N52: 0 | O52: 0 | P52: 0 | Q52: 164297.05 | R52: 164297.05 | S52: 0 | T52: 0 | U52: 0 | V52: 0 | W52: 0 | X52: 0 | Y52: 0 | AB52: 0 | AH52: =MAX(H52-AB52,0) -> 164297.05
B53: =_xlfn.XLOOKUP(C53,'Info Clientes'!A:A,'Info Clientes'!B:B) -> Additive | C53: GRANUPAR - RIO BRANCO DO SUL | D53: B | F53: 300000 | G53: 136047.6 | H53: 163952.4 | I53: 0 | J53: 0 | K53: 0 | L53: 0 | M53: 0 | N53: 0 | O53: 0 | P53: 0 | Q53: 163952.4 | R53: 104834.4 | S53: 59118 | T53: 0 | U53: 0 | V53: 0 | W53: 0 | X53: 0 | Y53: 0 | AB53: 300000 | AH53: =MAX(H53-AB53,0) -> 0
B54: =_xlfn.XLOOKUP(C54,'Info Clientes'!A:A,'Info Clientes'!B:B) -> Additive | C54: COONAGRO COOPERATIVA - PARANAGUA | D54: B | F54: 2500000 | G54: 2338169.8 | H54: 161830.2 | I54: 0 | J54: 0 | K54: 0 | L54: 0 | M54: 0 | N54: 0 | O54: 0 | P54: 0 | Q54: 161830.2 | R54: 161830.2 | S54: 0 | T54: 0 | U54: 0 | V54: 0 | W54: 0 | X54: 0 | Y54: 0 | AB54: 2500000 | AH54: =MAX(H54-AB54,0) -> 0
B55: =_xlfn.XLOOKUP(C55,'Info Clientes'!A:A,'Info Clientes'!B:B) -> Additive | C55: BUNGE - SANTOS | D55: B | F55: 800000 | G55: 641987.8 | H55: 158012.2 | I55: 0 | J55: 0 | K55: 0 | L55: 0 | M55: 0 | N55: 0 | O55: 0 | P55: 0 | Q55: 158012.2 | R55: 158012.2 | S55: 0 | T55: 0 | U55: 0 | V55: 0 | W55: 0 | X55: 0 | Y55: 0 | AB55: 800000 | AH55: =MAX(H55-AB55,0) -> 0
B56: =_xlfn.XLOOKUP(C56,'Info Clientes'!A:A,'Info Clientes'!B:B) -> Additive | C56: GRUPO HINOVE | D56: 0 | F56: 0 | G56: -144324 | H56: 144324 | I56: 0 | J56: 0 | K56: 0 | L56: 0 | M56: 0 | N56: 0 | O56: 0 | P56: 0 | Q56: 144324 | R56: 144324 | S56: 0 | T56: 0 | U56: 0 | V56: 0 | W56: 0 | X56: 0 | Y56: 0 | AB56: 0 | AH56: =MAX(H56-AB56,0) -> 144324
B57: =_xlfn.XLOOKUP(C57,'Info Clientes'!A:A,'Info Clientes'!B:B) -> Additive Intl. | C57: ANAGRA - CHILE | D57: A | F57: 825000 | G57: 681777.26 | H57: 143222.74 | I57: 0 | J57: 0 | K57: 0 | L57: 0 | M57: 0 | N57: 0 | O57: 0 | P57: 0 | Q57: 143222.74 | R57: 143222.74 | S57: 0 | T57: 0 | U57: 0 | V57: 0 | W57: 0 | X57: 0 | Y57: 0 | AB57: 825000 | AH57: =MAX(H57-AB57,0) -> 0
B58: =_xlfn.XLOOKUP(C58,'Info Clientes'!A:A,'Info Clientes'!B:B) -> Additive Intl. | C58: AGROBROKERS - COLÔMBIA | D58: 0 | F58: 320000 | G58: 187690.67 | H58: 132309.33 | I58: 0 | J58: 0 | K58: 0 | L58: 0 | M58: 0 | N58: 0 | O58: 0 | P58: 0 | Q58: 132309.33 | R58: 0 | S58: 132309.33 | T58: 0 | U58: 0 | V58: 0 | W58: 0 | X58: 0 | Y58: 0 | AB58: 0 | AH58: =MAX(H58-AB58,0) -> 132309.33
B59: =_xlfn.XLOOKUP(C59,'Info Clientes'!A:A,'Info Clientes'!B:B) -> Additive | C59: GRUPO LOUIS DREYFUS | D59: B | F59: 1500000 | G59: 1368237.5 | H59: 131762.5 | I59: 0 | J59: 0 | K59: 0 | L59: 0 | M59: 0 | N59: 0 | O59: 0 | P59: 0 | Q59: 131762.5 | R59: 131762.5 | S59: 0 | T59: 0 | U59: 0 | V59: 0 | W59: 0 | X59: 0 | Y59: 0 | AB59: 1500000 | AH59: =MAX(H59-AB59,0) -> 0
B60: =_xlfn.XLOOKUP(C60,'Info Clientes'!A:A,'Info Clientes'!B:B) -> Fertilizer | C60: VEGA AGRO | D60: 0 | E60: 360 | F60: 660000 | G60: 528320 | H60: 131680 | I60: 0 | J60: 0 | K60: 0 | L60: 0 | M60: 0 | N60: 0 | O60: 0 | P60: 0 | Q60: 131680 | R60: 0 | S60: 0 | T60: 131680 | U60: 0 | V60: 0 | W60: 0 | X60: 0 | Y60: 0 | AB60: 660000 | AH60: =MAX(H60-AB60,0) -> 0
B61: =_xlfn.XLOOKUP(C61,'Info Clientes'!A:A,'Info Clientes'!B:B) -> Additive | C61: NUTRIENTES IND DE FERTILIZANTES LTDA | D61: B | F61: 850000 | G61: 727820 | H61: 122180 | I61: 0 | J61: 0 | K61: 0 | L61: 0 | M61: 0 | N61: 0 | O61: 0 | P61: 0 | Q61: 122180 | R61: 122180 | S61: 0 | T61: 0 | U61: 0 | V61: 0 | W61: 0 | X61: 0 | Y61: 0 | AB61: 850000 | AH61: =MAX(H61-AB61,0) -> 0
B62: =_xlfn.XLOOKUP(C62,'Info Clientes'!A:A,'Info Clientes'!B:B) -> Additive | C62: GRUPO FERTIPAR FERTILIZANTES DO NORDESTE | D62: B | F62: 1500000 | G62: 1396800 | H62: 103200.03 | I62: 0 | J62: 0 | K62: 0 | L62: 0 | M62: 0 | N62: 0 | O62: 0 | P62: 0 | Q62: 103200.03 | R62: 103200.03 | S62: 0 | T62: 0 | U62: 0 | V62: 0 | W62: 0 | X62: 0 | Y62: 0 | AB62: 1500000 | AH62: =MAX(H62-AB62,0) -> 0
B63: =_xlfn.XLOOKUP(C63,'Info Clientes'!A:A,'Info Clientes'!B:B) -> Additive Intl. | C63: CERES PERU S.A | D63: A | F63: 550000 | G63: 463310.9 | H63: 86689.1 | I63: 0 | J63: 86689.1 | K63: 0 | L63: 0 | M63: 0 | N63: 0 | O63: 0 | P63: 86689.1 | Q63: 0 | R63: 0 | S63: 0 | T63: 0 | U63: 0 | V63: 0 | W63: 0 | X63: 0 | Y63: 0 | AB63: 550000 | AH63: =MAX(H63-AB63,0) -> 0
B64: =_xlfn.XLOOKUP(C64,'Info Clientes'!A:A,'Info Clientes'!B:B) -> Additive | C64: INTERFERTIL - SAO FRANCISCO DO SUL | D64: B | F64: 200000 | G64: 116606.9 | H64: 83393.1 | I64: 0 | J64: 0 | K64: 0 | L64: 0 | M64: 0 | N64: 0 | O64: 0 | P64: 0 | Q64: 83393.1 | R64: 83393.1 | S64: 0 | T64: 0 | U64: 0 | V64: 0 | W64: 0 | X64: 0 | Y64: 0 | AB64: 200000 | AH64: =MAX(H64-AB64,0) -> 0
B65: =_xlfn.XLOOKUP(C65,'Info Clientes'!A:A,'Info Clientes'!B:B) -> Additive | C65: GRUPO AGRO INDUSTRIAL SAO LUIZ LTDA | D65: 0 | F65: 700000 | G65: 619400 | H65: 80600 | I65: 0 | J65: 0 | K65: 0 | L65: 0 | M65: 0 | N65: 0 | O65: 0 | P65: 0 | Q65: 80600 | R65: 80600 | S65: 0 | T65: 0 | U65: 0 | V65: 0 | W65: 0 | X65: 0 | Y65: 0 | AB65: 0 | AH65: =MAX(H65-AB65,0) -> 80600
B66: =_xlfn.XLOOKUP(C66,'Info Clientes'!A:A,'Info Clientes'!B:B) -> Additive Intl. | C66: AGRO MIL AGROS SAS - COLOMBIA | D66: A | F66: 302500 | G66: 226019.77 | H66: 76480.23 | I66: 0 | J66: 0 | K66: 0 | L66: 0 | M66: 0 | N66: 0 | O66: 0 | P66: 0 | Q66: 76480.23 | R66: 0 | S66: 0 | T66: 0 | U66: 0 | V66: 0 | W66: 76480.23 | X66: 0 | Y66: 0 | AB66: 302500 | AH66: =MAX(H66-AB66,0) -> 0
B67: =_xlfn.XLOOKUP(C67,'Info Clientes'!A:A,'Info Clientes'!B:B) -> Additive | C67: FERTIAL FERTILIZANTES USIFERTIL - MACEIO | D67: 0 | F67: 200000 | G67: 130404 | H67: 69596 | I67: 0 | J67: 0 | K67: 0 | L67: 0 | M67: 0 | N67: 0 | O67: 0 | P67: 0 | Q67: 69596 | R67: 69596 | S67: 0 | T67: 0 | U67: 0 | V67: 0 | W67: 0 | X67: 0 | Y67: 0 | AB67: 200000 | AH67: =MAX(H67-AB67,0) -> 0
B68: =_xlfn.XLOOKUP(C68,'Info Clientes'!A:A,'Info Clientes'!B:B) -> Additive | C68: GRUPO FERTINOR | D68: B | F68: 1300000 | G68: 1231500 | H68: 68500 | I68: 0 | J68: 0 | K68: 0 | L68: 0 | M68: 0 | N68: 0 | O68: 0 | P68: 0 | Q68: 68500 | R68: 68500 | S68: 0 | T68: 0 | U68: 0 | V68: 0 | W68: 0 | X68: 0 | Y68: 0 | AB68: 1300000 | AH68: =MAX(H68-AB68,0) -> 0
B69: =_xlfn.XLOOKUP(C69,'Info Clientes'!A:A,'Info Clientes'!B:B) -> Additive | C69: FASS AGRO FERTILIZANTES - SERTAOZINHO | D69: 0 | F69: 1000000 | G69: 933260 | H69: 66740 | I69: 0 | J69: 0 | K69: 0 | L69: 0 | M69: 0 | N69: 0 | O69: 0 | P69: 0 | Q69: 66740 | R69: 66740 | S69: 0 | T69: 0 | U69: 0 | V69: 0 | W69: 0 | X69: 0 | Y69: 0 | AB69: 1000000 | AH69: =MAX(H69-AB69,0) -> 0
B70: =_xlfn.XLOOKUP(C70,'Info Clientes'!A:A,'Info Clientes'!B:B) -> Additive | C70: MICROSOLO INDUSTRIAL - SETE LAGOAS | D70: 0 | F70: 100000 | G70: 34242 | H70: 65758 | I70: 0 | J70: 0 | K70: 0 | L70: 0 | M70: 0 | N70: 0 | O70: 0 | P70: 0 | Q70: 65758 | R70: 65758 | S70: 0 | T70: 0 | U70: 0 | V70: 0 | W70: 0 | X70: 0 | Y70: 0 | AB70: 0 | AH70: =MAX(H70-AB70,0) -> 65758
B71: =_xlfn.XLOOKUP(C71,'Info Clientes'!A:A,'Info Clientes'!B:B) -> Additive | C71: GRUPO CARGILL | D71: B | F71: 2000000 | G71: 1937410 | H71: 62590 | I71: 0 | J71: 0 | K71: 0 | L71: 0 | M71: 0 | N71: 0 | O71: 0 | P71: 0 | Q71: 62590 | R71: 62590 | S71: 0 | T71: 0 | U71: 0 | V71: 0 | W71: 0 | X71: 0 | Y71: 0 | AB71: 2000000 | AH71: =MAX(H71-AB71,0) -> 0
B72: =_xlfn.XLOOKUP(C72,'Info Clientes'!A:A,'Info Clientes'!B:B) -> Additive Intl. | C72: MACROSOURCE PERU S.R.L. | D72: B | F72: 990000 | G72: 940043.32 | H72: 49956.68 | I72: 0 | J72: 0 | K72: 0 | L72: 0 | M72: 0 | N72: 0 | O72: 0 | P72: 0 | Q72: 49956.68 | R72: 49956.68 | S72: 0 | T72: 0 | U72: 0 | V72: 0 | W72: 0 | X72: 0 | Y72: 0 | AB72: 990000 | AH72: =MAX(H72-AB72,0) -> 0
B73: =_xlfn.XLOOKUP(C73,'Info Clientes'!A:A,'Info Clientes'!B:B) -> Additive | C73: FERTIPLANTA - VARGEM GRANDE DO SUL | D73: 0 | F73: 75000 | G73: 25120 | H73: 49880 | I73: 0 | J73: 0 | K73: 0 | L73: 0 | M73: 0 | N73: 0 | O73: 0 | P73: 0 | Q73: 49880 | R73: 49880 | S73: 0 | T73: 0 | U73: 0 | V73: 0 | W73: 0 | X73: 0 | Y73: 0 | AB73: 0 | AH73: =MAX(H73-AB73,0) -> 49880
B74: =_xlfn.XLOOKUP(C74,'Info Clientes'!A:A,'Info Clientes'!B:B) -> Additive | C74: ARSLOG SOLUCOES EM TRANSPORTE | D74: 0 | F74: 0 | G74: -49440 | H74: 49440 | I74: 0 | J74: 0 | K74: 0 | L74: 49440 | M74: 0 | N74: 0 | O74: 0 | P74: 49440 | Q74: 0 | R74: 0 | S74: 0 | T74: 0 | U74: 0 | V74: 0 | W74: 0 | X74: 0 | Y74: 0 | AB74: 0 | AH74: =MAX(H74-AB74,0) -> 49440
B75: =_xlfn.XLOOKUP(C75,'Info Clientes'!A:A,'Info Clientes'!B:B) -> Additive | C75: CISBRA QUIMICA - FORMOSA | D75: B | F75: 600000 | G75: 551664 | H75: 48336 | I75: 0 | J75: 0 | K75: 0 | L75: 0 | M75: 0 | N75: 0 | O75: 0 | P75: 0 | Q75: 48336 | R75: 48336 | S75: 0 | T75: 0 | U75: 0 | V75: 0 | W75: 0 | X75: 0 | Y75: 0 | AB75: 600000 | AH75: =MAX(H75-AB75,0) -> 0
B76: =_xlfn.XLOOKUP(C76,'Info Clientes'!A:A,'Info Clientes'!B:B) -> Additive | C76: GRUPO GEN FERTILIZANTES | D76: B | F76: 2000000 | G76: 1953410 | H76: 46590.02 | I76: 0 | J76: 0 | K76: 0 | L76: 0 | M76: 0 | N76: 0 | O76: 0 | P76: 0 | Q76: 46590.02 | R76: 46590.02 | S76: 0 | T76: 0 | U76: 0 | V76: 0 | W76: 0 | X76: 0 | Y76: 0 | AB76: 2000000 | AH76: =MAX(H76-AB76,0) -> 0
B77: =_xlfn.XLOOKUP(C77,'Info Clientes'!A:A,'Info Clientes'!B:B) -> Additive | C77: ADUBOS LEAO - LARANJEIRAS | D77: 0 | F77: 70000 | G77: 32340 | H77: 37660 | I77: 0 | J77: 0 | K77: 0 | L77: 0 | M77: 0 | N77: 0 | O77: 0 | P77: 0 | Q77: 37660 | R77: 37660 | S77: 0 | T77: 0 | U77: 0 | V77: 0 | W77: 0 | X77: 0 | Y77: 0 | AB77: 0 | AH77: =MAX(H77-AB77,0) -> 37660
B78: =_xlfn.XLOOKUP(C78,'Info Clientes'!A:A,'Info Clientes'!B:B) -> Additive / Litigation | C78: GLINFERTIL - SAO FRANCISCO DO SUL | D78: 0 | F78: 0 | G78: -20940 | H78: 20940 | I78: 0 | J78: 0 | K78: 0 | L78: 0 | M78: 0 | N78: 0 | O78: 20940 | P78: 20940 | Q78: 0 | R78: 0 | S78: 0 | T78: 0 | U78: 0 | V78: 0 | W78: 0 | X78: 0 | Y78: 20940 | AB78: 0 | AH78: =MAX(H78-AB78,0) -> 20940
B79: =_xlfn.XLOOKUP(C79,'Info Clientes'!A:A,'Info Clientes'!B:B) -> Additive | C79: FERTALVO FERTILIZANTES - RONDONÓPOLIS | D79: B | F79: 120000 | G79: 102875 | H79: 17125 | I79: 0 | J79: 0 | K79: 0 | L79: 0 | M79: 0 | N79: 0 | O79: 0 | P79: 0 | Q79: 17125 | R79: 17125 | S79: 0 | T79: 0 | U79: 0 | V79: 0 | W79: 0 | X79: 0 | Y79: 0 | AB79: 120000 | AH79: =MAX(H79-AB79,0) -> 0
B80: =_xlfn.XLOOKUP(C80,'Info Clientes'!A:A,'Info Clientes'!B:B) -> Fertilizer | C80: GRUPO SAGRA | D80: B | E80: 360 | F80: 700000 | G80: 694969.5 | H80: 5030.5 | I80: 0 | J80: 0 | K80: 0 | L80: 0 | M80: 0 | N80: 0 | O80: 0 | P80: 0 | Q80: 5030.5 | R80: 0 | S80: 5030.5 | T80: 0 | U80: 0 | V80: 0 | W80: 0 | X80: 0 | Y80: 0 | AB80: 700000 | AH80: =MAX(H80-AB80,0) -> 0
B81: =_xlfn.XLOOKUP(C81,'Info Clientes'!A:A,'Info Clientes'!B:B) -> Additive | C81: MARCELO HONORIO DE CARVALHO RAMOS | D81: 0 | F81: 0 | G81: -1743 | H81: 1743 | I81: 581 | J81: 0 | K81: 0 | L81: 0 | M81: 0 | N81: 0 | O81: 0 | P81: 581 | Q81: 1162 | R81: 581 | S81: 581 | T81: 0 | U81: 0 | V81: 0 | W81: 0 | X81: 0 | Y81: 0 | AB81: 0 | AH81: =MAX(H81-AB81,0) -> 1743
B82: =_xlfn.XLOOKUP(C82,'Info Clientes'!A:A,'Info Clientes'!B:B) -> Additive Intl. | C82: ORGANITEC - PARAGUAY | D82: B | F82: 330000 | G82: 328619.48 | H82: 1380.52 | I82: 0 | J82: 853.24 | K82: 0 | L82: 0 | M82: 0 | N82: 527.28 | O82: 0 | P82: 1380.52 | Q82: 0 | R82: 0 | S82: 0 | T82: 0 | U82: 0 | V82: 0 | W82: 0 | X82: 0 | Y82: 15.8184 | AB82: 330000 | AH82: =MAX(H82-AB82,0) -> 0
B83: =_xlfn.XLOOKUP(C83,'Info Clientes'!A:A,'Info Clientes'!B:B) -> Fertilizer | C83: START QUIMICA - 22.685.341/0006-95 | D83: B | E83: 180 | F83: 50000 | G83: 49138.4 | H83: 861.6 | I83: 0 | J83: 0 | K83: 0 | L83: 0 | M83: 0 | N83: 0 | O83: 0 | P83: 0 | Q83: 861.6 | R83: 861.6 | S83: 0 | T83: 0 | U83: 0 | V83: 0 | W83: 0 | X83: 0 | Y83: 0 | AB83: 50000 | AH83: =MAX(H83-AB83,0) -> 0
B84: =_xlfn.XLOOKUP(C84,'Info Clientes'!A:A,'Info Clientes'!B:B) -> Additive | C84: SEU LIXO | D84: 0 | F84: 0 | G84: -300 | H84: 300 | I84: 0 | J84: 0 | K84: 0 | L84: 0 | M84: 0 | N84: 0 | O84: 300 | P84: 300 | Q84: 0 | R84: 0 | S84: 0 | T84: 0 | U84: 0 | V84: 0 | W84: 0 | X84: 0 | Y84: 300 | AB84: 0 | AH84: =MAX(H84-AB84,0) -> 300
B85: =_xlfn.XLOOKUP(C85,'Info Clientes'!A:A,'Info Clientes'!B:B) -> Additive | C85: KLEYTON DUARTE SOARES | D85: 0 | F85: 0 | G85: -100 | H85: 100 | I85: 0 | J85: 0 | K85: 0 | L85: 0 | M85: 0 | N85: 0 | O85: 100 | P85: 100 | Q85: 0 | R85: 0 | S85: 0 | T85: 0 | U85: 0 | V85: 0 | W85: 0 | X85: 0 | Y85: 100 | AB85: 0 | AH85: =MAX(H85-AB85,0) -> 100
B86: =_xlfn.XLOOKUP(C86,'Info Clientes'!A:A,'Info Clientes'!B:B) -> Additive | C86: MARIA JOSE DA SILVA | D86: 0 | F86: 0 | G86: -50 | H86: 50 | I86: 0 | J86: 0 | K86: 0 | L86: 0 | M86: 0 | N86: 0 | O86: 50 | P86: 50 | Q86: 0 | R86: 0 | S86: 0 | T86: 0 | U86: 0 | V86: 0 | W86: 0 | X86: 0 | Y86: 50 | AB86: 0 | AH86: =MAX(H86-AB86,0) -> 50

Sheet Nova Versão 
C1: 46198 | E1: =SUBTOTAL(9,E3:E826) -> 63971254 | G1: =SUBTOTAL(9,G3:G826) -> 31597220 | K1: =SUBTOTAL(9,K3:K826) -> 40542363 | L1: =SUBTOTAL(9,L3:L826) -> 16649787 | M1: =SUBTOTAL(9,M3:M81) -> 10148231 | N1: =SUBTOTAL(9,N3:N826) -> 13023615 | O1: =SUBTOTAL(9,O3:O826) -> 247837.21 | P1: =SUBTOTAL(9,P3:P826) -> 299642.08 | Q1: =SUBTOTAL(9,Q3:Q826) -> 76480.23 | R1: =SUBTOTAL(9,R3:R826) -> 96770.01 | S1: =SUBTOTAL(9,S3:S826) -> 1113139.1 | T1: =SUBTOTAL(9,T3:T826) -> 623406.28 | U1: =SUBTOTAL(9,U3:U826) -> 416870.25 | ... AA1: =SUBTOTAL(9,AA3:AA826) -> 22315752 | AD1: =SUBTOTAL(9,AD3:AD81) -> 1.1268363e+08 | AE1: =SUBTOTAL(9,AE3:AE81) -> 3.1260058e+08 | AG1: =SUBTOTAL(9,AG3:AG81) -> 2.0340978e+08
B2: BU | C2: Customer | D2: Credit Approved | E2: Total AR | F2: Credit Insurance | G2: Open Exposure w/o Credit Insurance | H2: Remark for Open Exposure (approved in credit committee,guarantee or credit approved based on credit rating). | I2: Comments | K2: AR Not Due | L2: 1-30 Days | M2: 31-60 Days | N2: 61-90 Days | O2: 91-120 Days | P2: 121-180 Days | Q2: 181-360 Days | R2: Above 360 Days | S2: AR Over Due but not in Litigation | T2: 1-30 Days | U2: 31-60 Days | V2: 61-90 Days | W2: 91-120 Days | X2: 121-180 Days | Y2: 181-360 Days | Z2: Above 360 Days | AA2: AR in Litigation | AB2: Collection Risk Probable / Possible / Rare | AD2: Invoiced amount | AE2: Buget | AF2: Invoiced percentage | AG2: Remaining amount to be invoiced
B3: =_xlfn.XLOOKUP(C3,'Info Clientes'!A:A,'Info Clientes'!B:B) -> Additive | C3: GRUPO MOSAIC FERTILIZANTES P K LTDA | D3: =_xlfn.XLOOKUP(C3,'Limite de crédito'!C:C,'Limite de crédito'!G:G,0) -> 10000000 | E3: =K3+S3+AA3 -> 7696493.6 | F3: =_xlfn.XLOOKUP('Nova Versão '!C3,'Limite de crédito'!C:C,'Limite de crédito'!O:O,0) -> 10000000 | G3: =MAX(E3-F3,0) -> 0 | H3: =_xlfn.XLOOKUP(C3,'Info Clientes'!A:A,'Info Clientes'!C:C) -> Guarantee or credit | I3: =IF(_xlfn.XLOOKUP(C3,'Info Clientes'!A:A,'Info Clientes'!D:D,"")=0,"",_xlfn.XLOOKUP(C3,'Info Clientes'!A:A,'Info Clientes'!D:D,"")) | K3: =L3+M3+N3+O3+P3+Q3+R3 -> 7696493.6 | L3: =_xlfn.XLOOKUP(C3,'Clientes Consolidado.'!$C:$C,'Clientes Consolidado.'!R:R,0) -> 2989374.9 | M3: =_xlfn.XLOOKUP(C3,'Clientes Consolidado.'!$C:$C,'Clientes Consolidado.'!S:S,0) -> 1924024.8 | N3: =_xlfn.XLOOKUP(C3,'Clientes Consolidado.'!$C:$C,'Clientes Consolidado.'!T:T,0) -> 2535256.7 | O3: =_xlfn.XLOOKUP(C3,'Clientes Consolidado.'!$C:$C,'Clientes Consolidado.'!U:U,0) -> 247837.21 | P3: =_xlfn.XLOOKUP(C3,'Clientes Consolidado.'!$C:$C,'Clientes Consolidado.'!V:V,0) -> 0 | Q3: =_xlfn.XLOOKUP(C3,'Clientes Consolidado.'!$C:$C,'Clientes Consolidado.'!W:W,0) -> 0 | R3: =_xlfn.XLOOKUP(C3,'Clientes Consolidado.'!$C:$C,'Clientes Consolidado.'!X:X,0) -> 0 | S3: =SUM(T3:Z3) -> 0 | T3: =SUMIFS('Clientes Consolidado.'!I:I,'Clientes Consolidado.'!C:C,C3,'Clientes Consolidado.'!B:B,"Fertilizer") +SUMIFS('Clientes Consolidado.'!I:I,'Clientes Consolidado.'!C:C,C3,'Clientes Consolidado.'!B:B,"Additive") +SUMIFS('Clientes Consolidado.'!I:I,'Clientes Consolidado.'!C:C,C3,'Clientes Consolidado.'!B:B,"Additive Intl.") -> 0 | U3: =SUMIFS('Clientes Consolidado.'!J:J,'Clientes Consolidado.'!C:C,C3,'Clientes Consolidado.'!B:B,"Fertilizer") +SUMIFS('Clientes Consolidado.'!J:J,'Clientes Consolidado.'!C:C,C3,'Clientes Consolidado.'!B:B,"Additive") +SUMIFS('Clientes Consolidado.'!J:J,'Clientes Consolidado.'!C:C,C3,'Clientes Consolidado.'!B:B,"Additive Intl.") -> 0 | V3: =SUMIFS('Clientes Consolidado.'!K:K,'Clientes Consolidado.'!C:C,C3,'Clientes Consolidado.'!B:B,"Fertilizer") +SUMIFS('Clientes Consolidado.'!K:K,'Clientes Consolidado.'!C:C,C3,'Clientes Consolidado.'!B:B,"Additive") +SUMIFS('Clientes Consolidado.'!K:K,'Clientes Consolidado.'!C:C,C3,'Clientes Consolidado.'!B:B,"Additive Intl.") -> 0 | W3: =SUMIFS('Clientes Consolidado.'!L:L,'Clientes Consolidado.'!C:C,C3,'Clientes Consolidado.'!B:B,"Fertilizer") +SUMIFS('Clientes Consolidado.'!L:L,'Clientes Consolidado.'!C:C,C3,'Clientes Consolidado.'!B:B,"Additive") +SUMIFS('Clientes Consolidado.'!L:L,'Clientes Consolidado.'!C:C,C3,'Clientes Consolidado.'!B:B,"Additive Intl.") -> 0 | X3: =SUMIFS('Clientes Consolidado.'!M:M,'Clientes Consolidado.'!C:C,C3,'Clientes Consolidado.'!B:B,"Fertilizer") +SUMIFS('Clientes Consolidado.'!M:M,'Clientes Consolidado.'!C:C,C3,'Clientes Consolidado.'!B:B,"Additive") +SUMIFS('Clientes Consolidado.'!M:M,'Clientes Consolidado.'!C:C,C3,'Clientes Consolidado.'!B:B,"Additive Intl.") -> 0 | Y3: =SUMIFS('Clientes Consolidado.'!N:N,'Clientes Consolidado.'!C:C,C3,'Clientes Consolidado.'!B:B,"Fertilizer") +SUMIFS('Clientes Consolidado.'!N:N,'Clientes Consolidado.'!C:C,C3,'Clientes Consolidado.'!B:B,"Additive") +SUMIFS('Clientes Consolidado.'!N:N,'Clientes Consolidado.'!C:C,C3,'Clientes Consolidado.'!B:B,"Additive Intl.") -> 0 | Z3: =SUMIFS('Clientes Consolidado.'!O:O,'Clientes Consolidado.'!C:C,C3,'Clientes Consolidado.'!B:B,"Fertilizer") +SUMIFS('Clientes Consolidado.'!O:O,'Clientes Consolidado.'!C:C,C3,'Clientes Consolidado.'!B:B,"Additive") +SUMIFS('Clientes Consolidado.'!O:O,'Clientes Consolidado.'!C:C,C3,'Clientes Consolidado.'!B:B,"Additive Intl.") -> 0 | AA3: =SUMIFS('Clientes Consolidado.'!P:P,'Clientes Consolidado.'!C:C,'Nova Versão '!C3,'Clientes Consolidado.'!B:B,"Fertilizer / Litigation")+SUMIFS('Clientes Consolidado.'!P:P,'Clientes Consolidado.'!C:C,'Nova Versão '!C3,'Clientes Consolidado.'!B:B,"Additive / Litigation") -> 0 | AD3: =SUMIFS('Invoiced amount'!I:I,'Invoiced amount'!AH:AH,'Nova Versão '!C3) -> 12849715 | AE3: =SUMIFS(Buget!K:K,Buget!E:E,'Nova Versão '!C3) -> 32470400 | AF3: =IF(OR(AE3=0,AE3=""),"",AD3/AE3) -> 0.39573627 | AG3: =MAX(AE3-AD3,0) -> 19620685
B4: =_xlfn.XLOOKUP(C4,'Info Clientes'!A:A,'Info Clientes'!B:B) -> Fertilizer / Litigation | C4: CENTRAL DO ADUBO COM E REPRESENTACAO LTD | D4: =_xlfn.XLOOKUP(C4,'Limite de crédito'!C:C,'Limite de crédito'!G:G,0) -> 0 | E4: =K4+S4+AA4 -> 7560727.8 | F4: =_xlfn.XLOOKUP('Nova Versão '!C4,'Limite de crédito'!C:C,'Limite de crédito'!O:O,0) -> 0 | G4: =MAX(E4-F4,0) -> 7560727.8 | H4: =_xlfn.XLOOKUP(C4,'Info Clientes'!A:A,'Info Clientes'!C:C) -> Litigation | I4: =IF(_xlfn.XLOOKUP(C4,'Info Clientes'!A:A,'Info Clientes'!D:D,"")=0,"",_xlfn.XLOOKUP(C4,'Info Clientes'!A:A,'Info Clientes'!D:D,"")) | K4: =L4+M4+N4+O4+P4+Q4+R4 -> 0 | L4: =_xlfn.XLOOKUP(C4,'Clientes Consolidado.'!$C:$C,'Clientes Consolidado.'!R:R,0) -> 0 | M4: =_xlfn.XLOOKUP(C4,'Clientes Consolidado.'!$C:$C,'Clientes Consolidado.'!S:S,0) -> 0 | N4: =_xlfn.XLOOKUP(C4,'Clientes Consolidado.'!$C:$C,'Clientes Consolidado.'!T:T,0) -> 0 | O4: =_xlfn.XLOOKUP(C4,'Clientes Consolidado.'!$C:$C,'Clientes Consolidado.'!U:U,0) -> 0 | P4: =_xlfn.XLOOKUP(C4,'Clientes Consolidado.'!$C:$C,'Clientes Consolidado.'!V:V,0) -> 0 | Q4: =_xlfn.XLOOKUP(C4,'Clientes Consolidado.'!$C:$C,'Clientes Consolidado.'!W:W,0) -> 0 | R4: =_xlfn.XLOOKUP(C4,'Clientes Consolidado.'!$C:$C,'Clientes Consolidado.'!X:X,0) -> 0 | S4: =SUM(T4:Z4) -> 0 | T4: =SUMIFS('Clientes Consolidado.'!I:I,'Clientes Consolidado.'!C:C,C4,'Clientes Consolidado.'!B:B,"Fertilizer") +SUMIFS('Clientes Consolidado.'!I:I,'Clientes Consolidado.'!C:C,C4,'Clientes Consolidado.'!B:B,"Additive") +SUMIFS('Clientes Consolidado.'!I:I,'Clientes Consolidado.'!C:C,C4,'Clientes Consolidado.'!B:B,"Additive Intl.") -> 0 | U4: =SUMIFS('Clientes Consolidado.'!J:J,'Clientes Consolidado.'!C:C,C4,'Clientes Consolidado.'!B:B,"Fertilizer") +SUMIFS('Clientes Consolidado.'!J:J,'Clientes Consolidado.'!C:C,C4,'Clientes Consolidado.'!B:B,"Additive") +SUMIFS('Clientes Consolidado.'!J:J,'Clientes Consolidado.'!C:C,C4,'Clientes Consolidado.'!B:B,"Additive Intl.") -> 0 | V4: =SUMIFS('Clientes Consolidado.'!K:K,'Clientes Consolidado.'!C:C,C4,'Clientes Consolidado.'!B:B,"Fertilizer") +SUMIFS('Clientes Consolidado.'!K:K,'Clientes Consolidado.'!C:C,C4,'Clientes Consolidado.'!B:B,"Additive") +SUMIFS('Clientes Consolidado.'!K:K,'Clientes Consolidado.'!C:C,C4,'Clientes Consolidado.'!B:B,"Additive Intl.") -> 0 | W4: =SUMIFS('Clientes Consolidado.'!L:L,'Clientes Consolidado.'!C:C,C4,'Clientes Consolidado.'!B:B,"Fertilizer") +SUMIFS('Clientes Consolidado.'!L:L,'Clientes Consolidado.'!C:C,C4,'Clientes Consolidado.'!B:B,"Additive") +SUMIFS('Clientes Consolidado.'!L:L,'Clientes Consolidado.'!C:C,C4,'Clientes Consolidado.'!B:B,"Additive Intl.") -> 0 | X4: =SUMIFS('Clientes Consolidado.'!M:M,'Clientes Consolidado.'!C:C,C4,'Clientes Consolidado.'!B:B,"Fertilizer") +SUMIFS('Clientes Consolidado.'!M:M,'Clientes Consolidado.'!C:C,C4,'Clientes Consolidado.'!B:B,"Additive") +SUMIFS('Clientes Consolidado.'!M:M,'Clientes Consolidado.'!C:C,C4,'Clientes Consolidado.'!B:B,"Additive Intl.") -> 0 | Y4: =SUMIFS('Clientes Consolidado.'!N:N,'Clientes Consolidado.'!C:C,C4,'Clientes Consolidado.'!B:B,"Fertilizer") +SUMIFS('Clientes Consolidado.'!N:N,'Clientes Consolidado.'!C:C,C4,'Clientes Consolidado.'!B:B,"Additive") +SUMIFS('Clientes Consolidado.'!N:N,'Clientes Consolidado.'!C:C,C4,'Clientes Consolidado.'!B:B,"Additive Intl.") -> 0 | Z4: =SUMIFS('Clientes Consolidado.'!O:O,'Clientes Consolidado.'!C:C,C4,'Clientes Consolidado.'!B:B,"Fertilizer") +SUMIFS('Clientes Consolidado.'!O:O,'Clientes Consolidado.'!C:C,C4,'Clientes Consolidado.'!B:B,"Additive") +SUMIFS('Clientes Consolidado.'!O:O,'Clientes Consolidado.'!C:C,C4,'Clientes Consolidado.'!B:B,"Additive Intl.") -> 0 | AA4: =SUMIFS('Clientes Consolidado.'!P:P,'Clientes Consolidado.'!C:C,'Nova Versão '!C4,'Clientes Consolidado.'!B:B,"Fertilizer / Litigation")+SUMIFS('Clientes Consolidado.'!P:P,'Clientes Consolidado.'!C:C,'Nova Versão '!C4,'Clientes Consolidado.'!B:B,"Additive / Litigation") -> 7560727.8 | AD4: =SUMIFS('Invoiced amount'!I:I,'Invoiced amount'!AH:AH,'Nova Versão '!C4) -> 17640 | AE4: =SUMIFS(Buget!K:K,Buget!E:E,'Nova Versão '!C4) -> 0 | AF4: =IF(OR(AE4=0,AE4=""),"",AD4/AE4) | AG4: =MAX(AE4-AD4,0) -> 0
B5: =_xlfn.XLOOKUP(C5,'Info Clientes'!A:A,'Info Clientes'!B:B) -> Additive | C5: GRUPO MOSAIC FERTILIZANTES DO BRASIL | D5: =_xlfn.XLOOKUP(C5,'Limite de crédito'!C:C,'Limite de crédito'!G:G,0) -> 15000000 | E5: =K5+S5+AA5 -> 7490408.6 | F5: =_xlfn.XLOOKUP('Nova Versão '!C5,'Limite de crédito'!C:C,'Limite de crédito'!O:O,0) -> 15000000 | G5: =MAX(E5-F5,0) -> 0 | H5: =_xlfn.XLOOKUP(C5,'Info Clientes'!A:A,'Info Clientes'!C:C) -> Guarantee or credit | I5: =IF(_xlfn.XLOOKUP(C5,'Info Clientes'!A:A,'Info Clientes'!D:D,"")=0,"",_xlfn.XLOOKUP(C5,'Info Clientes'!A:A,'Info Clientes'!D:D,"")) | K5: =L5+M5+N5+O5+P5+Q5+R5 -> 7473589.6 | L5: =_xlfn.XLOOKUP(C5,'Clientes Consolidado.'!$C:$C,'Clientes Consolidado.'!R:R,0) -> 746905.4 | M5: =_xlfn.XLOOKUP(C5,'Clientes Consolidado.'!$C:$C,'Clientes Consolidado.'!S:S,0) -> 2076080.5 | N5: =_xlfn.XLOOKUP(C5,'Clientes Consolidado.'!$C:$C,'Clientes Consolidado.'!T:T,0) -> 4650603.8 | O5: =_xlfn.XLOOKUP(C5,'Clientes Consolidado.'!$C:$C,'Clientes Consolidado.'!U:U,0) -> 0 | P5: =_xlfn.XLOOKUP(C5,'Clientes Consolidado.'!$C:$C,'Clientes Consolidado.'!V:V,0) -> 0 | Q5: =_xlfn.XLOOKUP(C5,'Clientes Consolidado.'!$C:$C,'Clientes Consolidado.'!W:W,0) -> 0 | R5: =_xlfn.XLOOKUP(C5,'Clientes Consolidado.'!$C:$C,'Clientes Consolidado.'!X:X,0) -> 0 | S5: =SUM(T5:Z5) -> 16818.92 | T5: =SUMIFS('Clientes Consolidado.'!I:I,'Clientes Consolidado.'!C:C,C5,'Clientes Consolidado.'!B:B,"Fertilizer") +SUMIFS('Clientes Consolidado.'!I:I,'Clientes Consolidado.'!C:C,C5,'Clientes Consolidado.'!B:B,"Additive") +SUMIFS('Clientes Consolidado.'!I:I,'Clientes Consolidado.'!C:C,C5,'Clientes Consolidado.'!B:B,"Additive Intl.") -> 0 | U5: =SUMIFS('Clientes Consolidado.'!J:J,'Clientes Consolidado.'!C:C,C5,'Clientes Consolidado.'!B:B,"Fertilizer") +SUMIFS('Clientes Consolidado.'!J:J,'Clientes Consolidado.'!C:C,C5,'Clientes Consolidado.'!B:B,"Additive") +SUMIFS('Clientes Consolidado.'!J:J,'Clientes Consolidado.'!C:C,C5,'Clientes Consolidado.'!B:B,"Additive Intl.") -> 0 | V5: =SUMIFS('Clientes Consolidado.'!K:K,'Clientes Consolidado.'!C:C,C5,'Clientes Consolidado.'!B:B,"Fertilizer") +SUMIFS('Clientes Consolidado.'!K:K,'Clientes Consolidado.'!C:C,C5,'Clientes Consolidado.'!B:B,"Additive") +SUMIFS('Clientes Consolidado.'!K:K,'Clientes Consolidado.'!C:C,C5,'Clientes Consolidado.'!B:B,"Additive Intl.") -> 0 | W5: =SUMIFS('Clientes Consolidado.'!L:L,'Clientes Consolidado.'!C:C,C5,'Clientes Consolidado.'!B:B,"Fertilizer") +SUMIFS('Clientes Consolidado.'!L:L,'Clientes Consolidado.'!C:C,C5,'Clientes Consolidado.'!B:B,"Additive") +SUMIFS('Clientes Consolidado.'!L:L,'Clientes Consolidado.'!C:C,C5,'Clientes Consolidado.'!B:B,"Additive Intl.") -> 0 | X5: =SUMIFS('Clientes Consolidado.'!M:M,'Clientes Consolidado.'!C:C,C5,'Clientes Consolidado.'!B:B,"Fertilizer") +SUMIFS('Clientes Consolidado.'!M:M,'Clientes Consolidado.'!C:C,C5,'Clientes Consolidado.'!B:B,"Additive") +SUMIFS('Clientes Consolidado.'!M:M,'Clientes Consolidado.'!C:C,C5,'Clientes Consolidado.'!B:B,"Additive Intl.") -> 0 | Y5: =SUMIFS('Clientes Consolidado.'!N:N,'Clientes Consolidado.'!C:C,C5,'Clientes Consolidado.'!B:B,"Fertilizer") +SUMIFS('Clientes Consolidado.'!N:N,'Clientes Consolidado.'!C:C,C5,'Clientes Consolidado.'!B:B,"Additive") +SUMIFS('Clientes Consolidado.'!N:N,'Clientes Consolidado.'!C:C,C5,'Clientes Consolidado.'!B:B,"Additive Intl.") -> 64.2 | Z5: =SUMIFS('Clientes Consolidado.'!O:O,'Clientes Consolidado.'!C:C,C5,'Clientes Consolidado.'!B:B,"Fertilizer") +SUMIFS('Clientes Consolidado.'!O:O,'Clientes Consolidado.'!C:C,C5,'Clientes Consolidado.'!B:B,"Additive") +SUMIFS('Clientes Consolidado.'!O:O,'Clientes Consolidado.'!C:C,C5,'Clientes Consolidado.'!B:B,"Additive Intl.") -> 16754.72 | AA5: =SUMIFS('Clientes Consolidado.'!P:P,'Clientes Consolidado.'!C:C,'Nova Versão '!C5,'Clientes Consolidado.'!B:B,"Fertilizer / Litigation")+SUMIFS('Clientes Consolidado.'!P:P,'Clientes Consolidado.'!C:C,'Nova Versão '!C5,'Clientes Consolidado.'!B:B,"Additive / Litigation") -> 0 | AD5: =SUMIFS('Invoiced amount'!I:I,'Invoiced amount'!AH:AH,'Nova Versão '!C5) -> 12642848 | AE5: =SUMIFS(Buget!K:K,Buget!E:E,'Nova Versão '!C5) -> 38799849 | AF5: =IF(OR(AE5=0,AE5=""),"",AD5/AE5) -> 0.32584788 | AG5: =MAX(AE5-AD5,0) -> 26157001
B6: =_xlfn.XLOOKUP(C6,'Info Clientes'!A:A,'Info Clientes'!B:B) -> Additive | C6: GRUPO YARA | D6: =_xlfn.XLOOKUP(C6,'Limite de crédito'!C:C,'Limite de crédito'!G:G,0) -> 6000000 | E6: =K6+S6+AA6 -> 4784150 | F6: =_xlfn.XLOOKUP('Nova Versão '!C6,'Limite de crédito'!C:C,'Limite de crédito'!O:O,0) -> 6000000 | G6: =MAX(E6-F6,0) -> 0 | H6: =_xlfn.XLOOKUP(C6,'Info Clientes'!A:A,'Info Clientes'!C:C) -> Guarantee or credit | I6: =IF(_xlfn.XLOOKUP(C6,'Info Clientes'!A:A,'Info Clientes'!D:D,"")=0,"",_xlfn.XLOOKUP(C6,'Info Clientes'!A:A,'Info Clientes'!D:D,"")) | K6: =L6+M6+N6+O6+P6+Q6+R6 -> 4778523.7 | L6: =_xlfn.XLOOKUP(C6,'Clientes Consolidado.'!$C:$C,'Clientes Consolidado.'!R:R,0) -> 3419201.1 | M6: =_xlfn.XLOOKUP(C6,'Clientes Consolidado.'!$C:$C,'Clientes Consolidado.'!S:S,0) -> 1359322.6 | N6: =_xlfn.XLOOKUP(C6,'Clientes Consolidado.'!$C:$C,'Clientes Consolidado.'!T:T,0) -> 0 | O6: =_xlfn.XLOOKUP(C6,'Clientes Consolidado.'!$C:$C,'Clientes Consolidado.'!U:U,0) -> 0 | P6: =_xlfn.XLOOKUP(C6,'Clientes Consolidado.'!$C:$C,'Clientes Consolidado.'!V:V,0) -> 0 | Q6: =_xlfn.XLOOKUP(C6,'Clientes Consolidado.'!$C:$C,'Clientes Consolidado.'!W:W,0) -> 0 | R6: =_xlfn.XLOOKUP(C6,'Clientes Consolidado.'!$C:$C,'Clientes Consolidado.'!X:X,0) -> 0 | S6: =SUM(T6:Z6) -> 5626.32 | T6: =SUMIFS('Clientes Consolidado.'!I:I,'Clientes Consolidado.'!C:C,C6,'Clientes Consolidado.'!B:B,"Fertilizer") +SUMIFS('Clientes Consolidado.'!I:I,'Clientes Consolidado.'!C:C,C6,'Clientes Consolidado.'!B:B,"Additive") +SUMIFS('Clientes Consolidado.'!I:I,'Clientes Consolidado.'!C:C,C6,'Clientes Consolidado.'!B:B,"Additive Intl.") -> 0 | U6: =SUMIFS('Clientes Consolidado.'!J:J,'Clientes Consolidado.'!C:C,C6,'Clientes Consolidado.'!B:B,"Fertilizer") +SUMIFS('Clientes Consolidado.'!J:J,'Clientes Consolidado.'!C:C,C6,'Clientes Consolidado.'!B:B,"Additive") +SUMIFS('Clientes Consolidado.'!J:J,'Clientes Consolidado.'!C:C,C6,'Clientes Consolidado.'!B:B,"Additive Intl.") -> 0 | V6: =SUMIFS('Clientes Consolidado.'!K:K,'Clientes Consolidado.'!C:C,C6,'Clientes Consolidado.'!B:B,"Fertilizer") +SUMIFS('Clientes Consolidado.'!K:K,'Clientes Consolidado.'!C:C,C6,'Clientes Consolidado.'!B:B,"Additive") +SUMIFS('Clientes Consolidado.'!K:K,'Clientes Consolidado.'!C:C,C6,'Clientes Consolidado.'!B:B,"Additive Intl.") -> 0 | W6: =SUMIFS('Clientes Consolidado.'!L:L,'Clientes Consolidado.'!C:C,C6,'Clientes Consolidado.'!B:B,"Fertilizer") +SUMIFS('Clientes Consolidado.'!L:L,'Clientes Consolidado.'!C:C,C6,'Clientes Consolidado.'!B:B,"Additive") +SUMIFS('Clientes Consolidado.'!L:L,'Clientes Consolidado.'!C:C,C6,'Clientes Consolidado.'!B:B,"Additive Intl.") -> 0 | X6: =SUMIFS('Clientes Consolidado.'!M:M,'Clientes Consolidado.'!C:C,C6,'Clientes Consolidado.'!B:B,"Fertilizer") +SUMIFS('Clientes Consolidado.'!M:M,'Clientes Consolidado.'!C:C,C6,'Clientes Consolidado.'!B:B,"Additive") +SUMIFS('Clientes Consolidado.'!M:M,'Clientes Consolidado.'!C:C,C6,'Clientes Consolidado.'!B:B,"Additive Intl.") -> 0 | Y6: =SUMIFS('Clientes Consolidado.'!N:N,'Clientes Consolidado.'!C:C,C6,'Clientes Consolidado.'!B:B,"Fertilizer") +SUMIFS('Clientes Consolidado.'!N:N,'Clientes Consolidado.'!C:C,C6,'Clientes Consolidado.'!B:B,"Additive") +SUMIFS('Clientes Consolidado.'!N:N,'Clientes Consolidado.'!C:C,C6,'Clientes Consolidado.'!B:B,"Additive Intl.") -> 0 | Z6: =SUMIFS('Clientes Consolidado.'!O:O,'Clientes Consolidado.'!C:C,C6,'Clientes Consolidado.'!B:B,"Fertilizer") +SUMIFS('Clientes Consolidado.'!O:O,'Clientes Consolidado.'!C:C,C6,'Clientes Consolidado.'!B:B,"Additive") +SUMIFS('Clientes Consolidado.'!O:O,'Clientes Consolidado.'!C:C,C6,'Clientes Consolidado.'!B:B,"Additive Intl.") -> 5626.32 | AA6: =SUMIFS('Clientes Consolidado.'!P:P,'Clientes Consolidado.'!C:C,'Nova Versão '!C6,'Clientes Consolidado.'!B:B,"Fertilizer / Litigation")+SUMIFS('Clientes Consolidado.'!P:P,'Clientes Consolidado.'!C:C,'Nova Versão '!C6,'Clientes Consolidado.'!B:B,"Additive / Litigation") -> 0 | AD6: =SUMIFS('Invoiced amount'!I:I,'Invoiced amount'!AH:AH,'Nova Versão '!C6) -> 17271600 | AE6: =SUMIFS(Buget!K:K,Buget!E:E,'Nova Versão '!C6) -> 32130000 | AF6: =IF(OR(AE6=0,AE6=""),"",AD6/AE6) -> 0.5375537 | AG6: =MAX(AE6-AD6,0) -> 14858400
B7: =_xlfn.XLOOKUP(C7,'Info Clientes'!A:A,'Info Clientes'!B:B) -> Additive Intl. | C7: NITROFERT SAS - COLOMBIA | D7: =_xlfn.XLOOKUP(C7,'Limite de crédito'!C:C,'Limite de crédito'!G:G,0) -> 5000000 | E7: =K7+S7+AA7 -> 3774575.4 | F7: =_xlfn.XLOOKUP('Nova Versão '!C7,'Limite de crédito'!C:C,'Limite de crédito'!O:O,0) -> 0 | G7: =MAX(E7-F7,0) -> 3774575.4 | H7: =_xlfn.XLOOKUP(C7,'Info Clientes'!A:A,'Info Clientes'!C:C) -> Approved in credit committee | I7: =IF(_xlfn.XLOOKUP(C7,'Info Clientes'!A:A,'Info Clientes'!D:D,"")=0,"",_xlfn.XLOOKUP(C7,'Info Clientes'!A:A,'Info Clientes'!D:D,"")) -> We are finalizing a letter of comfort with the client, signed by the Nitron group. | K7: =L7+M7+N7+O7+P7+Q7+R7 -> 3774575.4 | L7: =_xlfn.XLOOKUP(C7,'Clientes Consolidado.'!$C:$C,'Clientes Consolidado.'!R:R,0) -> 0 | M7: =_xlfn.XLOOKUP(C7,'Clientes Consolidado.'!$C:$C,'Clientes Consolidado.'!S:S,0) -> 668371.59 | N7: =_xlfn.XLOOKUP(C7,'Clientes Consolidado.'!$C:$C,'Clientes Consolidado.'!T:T,0) -> 3106203.8 | O7: =_xlfn.XLOOKUP(C7,'Clientes Consolidado.'!$C:$C,'Clientes Consolidado.'!U:U,0) -> 0 | P7: =_xlfn.XLOOKUP(C7,'Clientes Consolidado.'!$C:$C,'Clientes Consolidado.'!V:V,0) -> 0 | Q7: =_xlfn.XLOOKUP(C7,'Clientes Consolidado.'!$C:$C,'Clientes Consolidado.'!W:W,0) -> 0 | R7: =_xlfn.XLOOKUP(C7,'Clientes Consolidado.'!$C:$C,'Clientes Consolidado.'!X:X,0) -> 0 | S7: =SUM(T7:Z7) -> 0 | T7: =SUMIFS('Clientes Consolidado.'!I:I,'Clientes Consolidado.'!C:C,C7,'Clientes Consolidado.'!B:B,"Fertilizer") +SUMIFS('Clientes Consolidado.'!I:I,'Clientes Consolidado.'!C:C,C7,'Clientes Consolidado.'!B:B,"Additive") +SUMIFS('Clientes Consolidado.'!I:I,'Clientes Consolidado.'!C:C,C7,'Clientes Consolidado.'!B:B,"Additive Intl.") -> 0 | U7: =SUMIFS('Clientes Consolidado.'!J:J,'Clientes Consolidado.'!C:C,C7,'Clientes Consolidado.'!B:B,"Fertilizer") +SUMIFS('Clientes Consolidado.'!J:J,'Clientes Consolidado.'!C:C,C7,'Clientes Consolidado.'!B:B,"Additive") +SUMIFS('Clientes Consolidado.'!J:J,'Clientes Consolidado.'!C:C,C7,'Clientes Consolidado.'!B:B,"Additive Intl.") -> 0 | V7: =SUMIFS('Clientes Consolidado.'!K:K,'Clientes Consolidado.'!C:C,C7,'Clientes Consolidado.'!B:B,"Fertilizer") +SUMIFS('Clientes Consolidado.'!K:K,'Clientes Consolidado.'!C:C,C7,'Clientes Consolidado.'!B:B,"Additive") +SUMIFS('Clientes Consolidado.'!K:K,'Clientes Consolidado.'!C:C,C7,'Clientes Consolidado.'!B:B,"Additive Intl.") -> 0 | W7: =SUMIFS('Clientes Consolidado.'!L:L,'Clientes Consolidado.'!C:C,C7,'Clientes Consolidado.'!B:B,"Fertilizer") +SUMIFS('Clientes Consolidado.'!L:L,'Clientes Consolidado.'!C:C,C7,'Clientes Consolidado.'!B:B,"Additive") +SUMIFS('Clientes Consolidado.'!L:L,'Clientes Consolidado.'!C:C,C7,'Clientes Consolidado.'!B:B,"Additive Intl.") -> 0 | X7: =SUMIFS('Clientes Consolidado.'!M:M,'Clientes Consolidado.'!C:C,C7,'Clientes Consolidado.'!B:B,"Fertilizer") +SUMIFS('Clientes Consolidado.'!M:M,'Clientes Consolidado.'!C:C,C7,'Clientes Consolidado.'!B:B,"Additive") +SUMIFS('Clientes Consolidado.'!M:M,'Clientes Consolidado.'!C:C,C7,'Clientes Consolidado.'!B:B,"Additive Intl.") -> 0 | Y7: =SUMIFS('Clientes Consolidado.'!N:N,'Clientes Consolidado.'!C:C,C7,'Clientes Consolidado.'!B:B,"Fertilizer") +SUMIFS('Clientes Consolidado.'!N:N,'Clientes Consolidado.'!C:C,C7,'Clientes Consolidado.'!B:B,"Additive") +SUMIFS('Clientes Consolidado.'!N:N,'Clientes Consolidado.'!C:C,C7,'Clientes Consolidado.'!B:B,"Additive Intl.") -> 0 | Z7: =SUMIFS('Clientes Consolidado.'!O:O,'Clientes Consolidado.'!C:C,C7,'Clientes Consolidado.'!B:B,"Fertilizer") +SUMIFS('Clientes Consolidado.'!O:O,'Clientes Consolidado.'!C:C,C7,'Clientes Consolidado.'!B:B,"Additive") +SUMIFS('Clientes Consolidado.'!O:O,'Clientes Consolidado.'!C:C,C7,'Clientes Consolidado.'!B:B,"Additive Intl.") -> 0 | AA7: =SUMIFS('Clientes Consolidado.'!P:P,'Clientes Consolidado.'!C:C,'Nova Versão '!C7,'Clientes Consolidado.'!B:B,"Fertilizer / Litigation")+SUMIFS('Clientes Consolidado.'!P:P,'Clientes Consolidado.'!C:C,'Nova Versão '!C7,'Clientes Consolidado.'!B:B,"Additive / Litigation") -> 0 | AD7: =SUMIFS('Invoiced amount'!I:I,'Invoiced amount'!AH:AH,'Nova Versão '!C7) -> 7728141.1 | AE7: =SUMIFS(Buget!K:K,Buget!E:E,'Nova Versão '!C7) -> 7055332.6 | AF7: =IF(OR(AE7=0,AE7=""),"",AD7/AE7) -> 1.0953617 | AG7: =MAX(AE7-AD7,0) -> 0
B8: =_xlfn.XLOOKUP(C8,'Info Clientes'!A:A,'Info Clientes'!B:B) -> Fertilizer / Litigation | C8: GRUPO LEANDRO SARTI | D8: =_xlfn.XLOOKUP(C8,'Limite de crédito'!C:C,'Limite de crédito'!G:G,0) -> 0 | E8: =K8+S8+AA8 -> 3088531.1 | F8: =_xlfn.XLOOKUP('Nova Versão '!C8,'Limite de crédito'!C:C,'Limite de crédito'!O:O,0) -> 0 | G8: =MAX(E8-F8,0) -> 3088531.1 | H8: =_xlfn.XLOOKUP(C8,'Info Clientes'!A:A,'Info Clientes'!C:C) -> Litigation | I8: =IF(_xlfn.XLOOKUP(C8,'Info Clientes'!A:A,'Info Clientes'!D:D,"")=0,"",_xlfn.XLOOKUP(C8,'Info Clientes'!A:A,'Info Clientes'!D:D,"")) | K8: =L8+M8+N8+O8+P8+Q8+R8 -> 0 | L8: =_xlfn.XLOOKUP(C8,'Clientes Consolidado.'!$C:$C,'Clientes Consolidado.'!R:R,0) -> 0 | M8: =_xlfn.XLOOKUP(C8,'Clientes Consolidado.'!$C:$C,'Clientes Consolidado.'!S:S,0) -> 0 | N8: =_xlfn.XLOOKUP(C8,'Clientes Consolidado.'!$C:$C,'Clientes Consolidado.'!T:T,0) -> 0 | O8: =_xlfn.XLOOKUP(C8,'Clientes Consolidado.'!$C:$C,'Clientes Consolidado.'!U:U,0) -> 0 | P8: =_xlfn.XLOOKUP(C8,'Clientes Consolidado.'!$C:$C,'Clientes Consolidado.'!V:V,0) -> 0 | Q8: =_xlfn.XLOOKUP(C8,'Clientes Consolidado.'!$C:$C,'Clientes Consolidado.'!W:W,0) -> 0 | R8: =_xlfn.XLOOKUP(C8,'Clientes Consolidado.'!$C:$C,'Clientes Consolidado.'!X:X,0) -> 0 | S8: =SUM(T8:Z8) -> 0 | T8: =SUMIFS('Clientes Consolidado.'!I:I,'Clientes Consolidado.'!C:C,C8,'Clientes Consolidado.'!B:B,"Fertilizer") +SUMIFS('Clientes Consolidado.'!I:I,'Clientes Consolidado.'!C:C,C8,'Clientes Consolidado.'!B:B,"Additive") +SUMIFS('Clientes Consolidado.'!I:I,'Clientes Consolidado.'!C:C,C8,'Clientes Consolidado.'!B:B,"Additive Intl.") -> 0 | U8: =SUMIFS('Clientes Consolidado.'!J:J,'Clientes Consolidado.'!C:C,C8,'Clientes Consolidado.'!B:B,"Fertilizer") +SUMIFS('Clientes Consolidado.'!J:J,'Clientes Consolidado.'!C:C,C8,'Clientes Consolidado.'!B:B,"Additive") +SUMIFS('Clientes Consolidado.'!J:J,'Clientes Consolidado.'!C:C,C8,'Clientes Consolidado.'!B:B,"Additive Intl.") -> 0 | V8: =SUMIFS('Clientes Consolidado.'!K:K,'Clientes Consolidado.'!C:C,C8,'Clientes Consolidado.'!B:B,"Fertilizer") +SUMIFS('Clientes Consolidado.'!K:K,'Clientes Consolidado.'!C:C,C8,'Clientes Consolidado.'!B:B,"Additive") +SUMIFS('Clientes Consolidado.'!K:K,'Clientes Consolidado.'!C:C,C8,'Clientes Consolidado.'!B:B,"Additive Intl.") -> 0 | W8: =SUMIFS('Clientes Consolidado.'!L:L,'Clientes Consolidado.'!C:C,C8,'Clientes Consolidado.'!B:B,"Fertilizer") +SUMIFS('Clientes Consolidado.'!L:L,'Clientes Consolidado.'!C:C,C8,'Clientes Consolidado.'!B:B,"Additive") +SUMIFS('Clientes Consolidado.'!L:L,'Clientes Consolidado.'!C:C,C8,'Clientes Consolidado.'!B:B,"Additive Intl.") -> 0 | X8: =SUMIFS('Clientes Consolidado.'!M:M,'Clientes Consolidado.'!C:C,C8,'Clientes Consolidado.'!B:B,"Fertilizer") +SUMIFS('Clientes Consolidado.'!M:M,'Clientes Consolidado.'!C:C,C8,'Clientes Consolidado.'!B:B,"Additive") +SUMIFS('Clientes Consolidado.'!M:M,'Clientes Consolidado.'!C:C,C8,'Clientes Consolidado.'!B:B,"Additive Intl.") -> 0 | Y8: =SUMIFS('Clientes Consolidado.'!N:N,'Clientes Consolidado.'!C:C,C8,'Clientes Consolidado.'!B:B,"Fertilizer") +SUMIFS('Clientes Consolidado.'!N:N,'Clientes Consolidado.'!C:C,C8,'Clientes Consolidado.'!B:B,"Additive") +SUMIFS('Clientes Consolidado.'!N:N,'Clientes Consolidado.'!C:C,C8,'Clientes Consolidado.'!B:B,"Additive Intl.") -> 0 | Z8: =SUMIFS('Clientes Consolidado.'!O:O,'Clientes Consolidado.'!C:C,C8,'Clientes Consolidado.'!B:B,"Fertilizer") +SUMIFS('Clientes Consolidado.'!O:O,'Clientes Consolidado.'!C:C,C8,'Clientes Consolidado.'!B:B,"Additive") +SUMIFS('Clientes Consolidado.'!O:O,'Clientes Consolidado.'!C:C,C8,'Clientes Consolidado.'!B:B,"Additive Intl.") -> 0 | AA8: =SUMIFS('Clientes Consolidado.'!P:P,'Clientes Consolidado.'!C:C,'Nova Versão '!C8,'Clientes Consolidado.'!B:B,"Fertilizer / Litigation")+SUMIFS('Clientes Consolidado.'!P:P,'Clientes Consolidado.'!C:C,'Nova Versão '!C8,'Clientes Consolidado.'!B:B,"Additive / Litigation") -> 3088531.1 | AD8: =SUMIFS('Invoiced amount'!I:I,'Invoiced amount'!AH:AH,'Nova Versão '!C8) -> 0 | AE8: =SUMIFS(Buget!K:K,Buget!E:E,'Nova Versão '!C8) -> 0 | AF8: =IF(OR(AE8=0,AE8=""),"",AD8/AE8) | AG8: =MAX(AE8-AD8,0) -> 0
B9: =_xlfn.XLOOKUP(C9,'Info Clientes'!A:A,'Info Clientes'!B:B) -> Fertilizer / Litigation | C9: AGRO BERALDO | D9: =_xlfn.XLOOKUP(C9,'Limite de crédito'!C:C,'Limite de crédito'!G:G,0) -> 0 | E9: =K9+S9+AA9 -> 3044850.9 | F9: =_xlfn.XLOOKUP('Nova Versão '!C9,'Limite de crédito'!C:C,'Limite de crédito'!O:O,0) -> 0 | G9: =MAX(E9-F9,0) -> 3044850.9 | H9: =_xlfn.XLOOKUP(C9,'Info Clientes'!A:A,'Info Clientes'!C:C) -> Litigation | I9: =IF(_xlfn.XLOOKUP(C9,'Info Clientes'!A:A,'Info Clientes'!D:D,"")=0,"",_xlfn.XLOOKUP(C9,'Info Clientes'!A:A,'Info Clientes'!D:D,"")) | K9: =L9+M9+N9+O9+P9+Q9+R9 -> 0 | L9: =_xlfn.XLOOKUP(C9,'Clientes Consolidado.'!$C:$C,'Clientes Consolidado.'!R:R,0) -> 0 | M9: =_xlfn.XLOOKUP(C9,'Clientes Consolidado.'!$C:$C,'Clientes Consolidado.'!S:S,0) -> 0 | N9: =_xlfn.XLOOKUP(C9,'Clientes Consolidado.'!$C:$C,'Clientes Consolidado.'!T:T,0) -> 0 | O9: =_xlfn.XLOOKUP(C9,'Clientes Consolidado.'!$C:$C,'Clientes Consolidado.'!U:U,0) -> 0 | P9: =_xlfn.XLOOKUP(C9,'Clientes Consolidado.'!$C:$C,'Clientes Consolidado.'!V:V,0) -> 0 | Q9: =_xlfn.XLOOKUP(C9,'Clientes Consolidado.'!$C:$C,'Clientes Consolidado.'!W:W,0) -> 0 | R9: =_xlfn.XLOOKUP(C9,'Clientes Consolidado.'!$C:$C,'Clientes Consolidado.'!X:X,0) -> 0 | S9: =SUM(T9:Z9) -> 0 | T9: =SUMIFS('Clientes Consolidado.'!I:I,'Clientes Consolidado.'!C:C,C9,'Clientes Consolidado.'!B:B,"Fertilizer") +SUMIFS('Clientes Consolidado.'!I:I,'Clientes Consolidado.'!C:C,C9,'Clientes Consolidado.'!B:B,"Additive") +SUMIFS('Clientes Consolidado.'!I:I,'Clientes Consolidado.'!C:C,C9,'Clientes Consolidado.'!B:B,"Additive Intl.") -> 0 | U9: =SUMIFS('Clientes Consolidado.'!J:J,'Clientes Consolidado.'!C:C,C9,'Clientes Consolidado.'!B:B,"Fertilizer") +SUMIFS('Clientes Consolidado.'!J:J,'Clientes Consolidado.'!C:C,C9,'Clientes Consolidado.'!B:B,"Additive") +SUMIFS('Clientes Consolidado.'!J:J,'Clientes Consolidado.'!C:C,C9,'Clientes Consolidado.'!B:B,"Additive Intl.") -> 0 | V9: =SUMIFS('Clientes Consolidado.'!K:K,'Clientes Consolidado.'!C:C,C9,'Clientes Consolidado.'!B:B,"Fertilizer") +SUMIFS('Clientes Consolidado.'!K:K,'Clientes Consolidado.'!C:C,C9,'Clientes Consolidado.'!B:B,"Additive") +SUMIFS('Clientes Consolidado.'!K:K,'Clientes Consolidado.'!C:C,C9,'Clientes Consolidado.'!B:B,"Additive Intl.") -> 0 | W9: =SUMIFS('Clientes Consolidado.'!L:L,'Clientes Consolidado.'!C:C,C9,'Clientes Consolidado.'!B:B,"Fertilizer") +SUMIFS('Clientes Consolidado.'!L:L,'Clientes Consolidado.'!C:C,C9,'Clientes Consolidado.'!B:B,"Additive") +SUMIFS('Clientes Consolidado.'!L:L,'Clientes Consolidado.'!C:C,C9,'Clientes Consolidado.'!B:B,"Additive Intl.") -> 0 | X9: =SUMIFS('Clientes Consolidado.'!M:M,'Clientes Consolidado.'!C:C,C9,'Clientes Consolidado.'!B:B,"Fertilizer") +SUMIFS('Clientes Consolidado.'!M:M,'Clientes Consolidado.'!C:C,C9,'Clientes Consolidado.'!B:B,"Additive") +SUMIFS('Clientes Consolidado.'!M:M,'Clientes Consolidado.'!C:C,C9,'Clientes Consolidado.'!B:B,"Additive Intl.") -> 0 | Y9: =SUMIFS('Clientes Consolidado.'!N:N,'Clientes Consolidado.'!C:C,C9,'Clientes Consolidado.'!B:B,"Fertilizer") +SUMIFS('Clientes Consolidado.'!N:N,'Clientes Consolidado.'!C:C,C9,'Clientes Consolidado.'!B:B,"Additive") +SUMIFS('Clientes Consolidado.'!N:N,'Clientes Consolidado.'!C:C,C9,'Clientes Consolidado.'!B:B,"Additive Intl.") -> 0 | Z9: =SUMIFS('Clientes Consolidado.'!O:O,'Clientes Consolidado.'!C:C,C9,'Clientes Consolidado.'!B:B,"Fertilizer") +SUMIFS('Clientes Consolidado.'!O:O,'Clientes Consolidado.'!C:C,C9,'Clientes Consolidado.'!B:B,"Additive") +SUMIFS('Clientes Consolidado.'!O:O,'Clientes Consolidado.'!C:C,C9,'Clientes Consolidado.'!B:B,"Additive Intl.") -> 0 | AA9: =SUMIFS('Clientes Consolidado.'!P:P,'Clientes Consolidado.'!C:C,'Nova Versão '!C9,'Clientes Consolidado.'!B:B,"Fertilizer / Litigation")+SUMIFS('Clientes Consolidado.'!P:P,'Clientes Consolidado.'!C:C,'Nova Versão '!C9,'Clientes Consolidado.'!B:B,"Additive / Litigation") -> 3044850.9 | AD9: =SUMIFS('Invoiced amount'!I:I,'Invoiced amount'!AH:AH,'Nova Versão '!C9) -> 0 | AE9: =SUMIFS(Buget!K:K,Buget!E:E,'Nova Versão '!C9) -> 0 | AF9: =IF(OR(AE9=0,AE9=""),"",AD9/AE9) | AG9: =MAX(AE9-AD9,0) -> 0
B10: =_xlfn.XLOOKUP(C10,'Info Clientes'!A:A,'Info Clientes'!B:B) -> Fertilizer / Litigation | C10: TERRA FERTIL - MACHADO | D10: =_xlfn.XLOOKUP(C10,'Limite de crédito'!C:C,'Limite de crédito'!G:G,0) -> 0 | E10: =K10+S10+AA10 -> 2492842.1 | F10: =_xlfn.XLOOKUP('Nova Versão '!C10,'Limite de crédito'!C:C,'Limite de crédito'!O:O,0) -> 0 | G10: =MAX(E10-F10,0) -> 2492842.1 | H10: =_xlfn.XLOOKUP(C10,'Info Clientes'!A:A,'Info Clientes'!C:C) -> Litigation | I10: =IF(_xlfn.XLOOKUP(C10,'Info Clientes'!A:A,'Info Clientes'!D:D,"")=0,"",_xlfn.XLOOKUP(C10,'Info Clientes'!A:A,'Info Clientes'!D:D,"")) | K10: =L10+M10+N10+O10+P10+Q10+R10 -> 0 | L10: =_xlfn.XLOOKUP(C10,'Clientes Consolidado.'!$C:$C,'Clientes Consolidado.'!R:R,0) -> 0 | M10: =_xlfn.XLOOKUP(C10,'Clientes Consolidado.'!$C:$C,'Clientes Consolidado.'!S:S,0) -> 0 | N10: =_xlfn.XLOOKUP(C10,'Clientes Consolidado.'!$C:$C,'Clientes Consolidado.'!T:T,0) -> 0 | O10: =_xlfn.XLOOKUP(C10,'Clientes Consolidado.'!$C:$C,'Clientes Consolidado.'!U:U,0) -> 0 | P10: =_xlfn.XLOOKUP(C10,'Clientes Consolidado.'!$C:$C,'Clientes Consolidado.'!V:V,0) -> 0 | Q10: =_xlfn.XLOOKUP(C10,'Clientes Consolidado.'!$C:$C,'Clientes Consolidado.'!W:W,0) -> 0 | R10: =_xlfn.XLOOKUP(C10,'Clientes Consolidado.'!$C:$C,'Clientes Consolidado.'!X:X,0) -> 0 | S10: =SUM(T10:Z10) -> 0 | T10: =SUMIFS('Clientes Consolidado.'!I:I,'Clientes Consolidado.'!C:C,C10,'Clientes Consolidado.'!B:B,"Fertilizer") +SUMIFS('Clientes Consolidado.'!I:I,'Clientes Consolidado.'!C:C,C10,'Clientes Consolidado.'!B:B,"Additive") +SUMIFS('Clientes Consolidado.'!I:I,'Clientes Consolidado.'!C:C,C10,'Clientes Consolidado.'!B:B,"Additive Intl.") -> 0 | U10: =SUMIFS('Clientes Consolidado.'!J:J,'Clientes Consolidado.'!C:C,C10,'Clientes Consolidado.'!B:B,"Fertilizer") +SUMIFS('Clientes Consolidado.'!J:J,'Clientes Consolidado.'!C:C,C10,'Clientes Consolidado.'!B:B,"Additive") +SUMIFS('Clientes Consolidado.'!J:J,'Clientes Consolidado.'!C:C,C10,'Clientes Consolidado.'!B:B,"Additive Intl.") -> 0 | V10: =SUMIFS('Clientes Consolidado.'!K:K,'Clientes Consolidado.'!C:C,C10,'Clientes Consolidado.'!B:B,"Fertilizer") +SUMIFS('Clientes Consolidado.'!K:K,'Clientes Consolidado.'!C:C,C10,'Clientes Consolidado.'!B:B,"Additive") +SUMIFS('Clientes Consolidado.'!K:K,'Clientes Consolidado.'!C:C,C10,'Clientes Consolidado.'!B:B,"Additive Intl.") -> 0 | W10: =SUMIFS('Clientes Consolidado.'!L:L,'Clientes Consolidado.'!C:C,C10,'Clientes Consolidado.'!B:B,"Fertilizer") +SUMIFS('Clientes Consolidado.'!L:L,'Clientes Consolidado.'!C:C,C10,'Clientes Consolidado.'!B:B,"Additive") +SUMIFS('Clientes Consolidado.'!L:L,'Clientes Consolidado.'!C:C,C10,'Clientes Consolidado.'!B:B,"Additive Intl.") -> 0 | X10: =SUMIFS('Clientes Consolidado.'!M:M,'Clientes Consolidado.'!C:C,C10,'Clientes Consolidado.'!B:B,"Fertilizer") +SUMIFS('Clientes Consolidado.'!M:M,'Clientes Consolidado.'!C:C,C10,'Clientes Consolidado.'!B:B,"Additive") +SUMIFS('Clientes Consolidado.'!M:M,'Clientes Consolidado.'!C:C,C10,'Clientes Consolidado.'!B:B,"Additive Intl.") -> 0 | Y10: =SUMIFS('Clientes Consolidado.'!N:N,'Clientes Consolidado.'!C:C,C10,'Clientes Consolidado.'!B:B,"Fertilizer") +SUMIFS('Clientes Consolidado.'!N:N,'Clientes Consolidado.'!C:C,C10,'Clientes Consolidado.'!B:B,"Additive") +SUMIFS('Clientes Consolidado.'!N:N,'Clientes Consolidado.'!C:C,C10,'Clientes Consolidado.'!B:B,"Additive Intl.") -> 0 | Z10: =SUMIFS('Clientes Consolidado.'!O:O,'Clientes Consolidado.'!C:C,C10,'Clientes Consolidado.'!B:B,"Fertilizer") +SUMIFS('Clientes Consolidado.'!O:O,'Clientes Consolidado.'!C:C,C10,'Clientes Consolidado.'!B:B,"Additive") +SUMIFS('Clientes Consolidado.'!O:O,'Clientes Consolidado.'!C:C,C10,'Clientes Consolidado.'!B:B,"Additive Intl.") -> 0 | AA10: =SUMIFS('Clientes Consolidado.'!P:P,'Clientes Consolidado.'!C:C,'Nova Versão '!C10,'Clientes Consolidado.'!B:B,"Fertilizer / Litigation")+SUMIFS('Clientes Consolidado.'!P:P,'Clientes Consolidado.'!C:C,'Nova Versão '!C10,'Clientes Consolidado.'!B:B,"Additive / Litigation") -> 2492842.1 | AD10: =SUMIFS('Invoiced amount'!I:I,'Invoiced amount'!AH:AH,'Nova Versão '!C10) -> 0 | AE10: =SUMIFS(Buget!K:K,Buget!E:E,'Nova Versão '!C10) -> 0 | AF10: =IF(OR(AE10=0,AE10=""),"",AD10/AE10) | AG10: =MAX(AE10-AD10,0) -> 0
B11: =_xlfn.XLOOKUP(C11,'Info Clientes'!A:A,'Info Clientes'!B:B) -> Fertilizer / Litigation | C11: MOGIANA TECNO AGRO | D11: =_xlfn.XLOOKUP(C11,'Limite de crédito'!C:C,'Limite de crédito'!G:G,0) -> 0 | E11: =K11+S11+AA11 -> 1863200.9 | F11: =_xlfn.XLOOKUP('Nova Versão '!C11,'Limite de crédito'!C:C,'Limite de crédito'!O:O,0) -> 0 | G11: =MAX(E11-F11,0) -> 1863200.9 | H11: =_xlfn.XLOOKUP(C11,'Info Clientes'!A:A,'Info Clientes'!C:C) -> Litigation | I11: =IF(_xlfn.XLOOKUP(C11,'Info Clientes'!A:A,'Info Clientes'!D:D,"")=0,"",_xlfn.XLOOKUP(C11,'Info Clientes'!A:A,'Info Clientes'!D:D,"")) | K11: =L11+M11+N11+O11+P11+Q11+R11 -> 0 | L11: =_xlfn.XLOOKUP(C11,'Clientes Consolidado.'!$C:$C,'Clientes Consolidado.'!R:R,0) -> 0 | M11: =_xlfn.XLOOKUP(C11,'Clientes Consolidado.'!$C:$C,'Clientes Consolidado.'!S:S,0) -> 0 | N11: =_xlfn.XLOOKUP(C11,'Clientes Consolidado.'!$C:$C,'Clientes Consolidado.'!T:T,0) -> 0 | O11: =_xlfn.XLOOKUP(C11,'Clientes Consolidado.'!$C:$C,'Clientes Consolidado.'!U:U,0) -> 0 | P11: =_xlfn.XLOOKUP(C11,'Clientes Consolidado.'!$C:$C,'Clientes Consolidado.'!V:V,0) -> 0 | Q11: =_xlfn.XLOOKUP(C11,'Clientes Consolidado.'!$C:$C,'Clientes Consolidado.'!W:W,0) -> 0 | R11: =_xlfn.XLOOKUP(C11,'Clientes Consolidado.'!$C:$C,'Clientes Consolidado.'!X:X,0) -> 0 | S11: =SUM(T11:Z11) -> 0 | T11: =SUMIFS('Clientes Consolidado.'!I:I,'Clientes Consolidado.'!C:C,C11,'Clientes Consolidado.'!B:B,"Fertilizer") +SUMIFS('Clientes Consolidado.'!I:I,'Clientes Consolidado.'!C:C,C11,'Clientes Consolidado.'!B:B,"Additive") +SUMIFS('Clientes Consolidado.'!I:I,'Clientes Consolidado.'!C:C,C11,'Clientes Consolidado.'!B:B,"Additive Intl.") -> 0 | U11: =SUMIFS('Clientes Consolidado.'!J:J,'Clientes Consolidado.'!C:C,C11,'Clientes Consolidado.'!B:B,"Fertilizer") +SUMIFS('Clientes Consolidado.'!J:J,'Clientes Consolidado.'!C:C,C11,'Clientes Consolidado.'!B:B,"Additive") +SUMIFS('Clientes Consolidado.'!J:J,'Clientes Consolidado.'!C:C,C11,'Clientes Consolidado.'!B:B,"Additive Intl.") -> 0 | V11: =SUMIFS('Clientes Consolidado.'!K:K,'Clientes Consolidado.'!C:C,C11,'Clientes Consolidado.'!B:B,"Fertilizer") +SUMIFS('Clientes Consolidado.'!K:K,'Clientes Consolidado.'!C:C,C11,'Clientes Consolidado.'!B:B,"Additive") +SUMIFS('Clientes Consolidado.'!K:K,'Clientes Consolidado.'!C:C,C11,'Clientes Consolidado.'!B:B,"Additive Intl.") -> 0 | W11: =SUMIFS('Clientes Consolidado.'!L:L,'Clientes Consolidado.'!C:C,C11,'Clientes Consolidado.'!B:B,"Fertilizer") +SUMIFS('Clientes Consolidado.'!L:L,'Clientes Consolidado.'!C:C,C11,'Clientes Consolidado.'!B:B,"Additive") +SUMIFS('Clientes Consolidado.'!L:L,'Clientes Consolidado.'!C:C,C11,'Clientes Consolidado.'!B:B,"Additive Intl.") -> 0 | X11: =SUMIFS('Clientes Consolidado.'!M:M,'Clientes Consolidado.'!C:C,C11,'Clientes Consolidado.'!B:B,"Fertilizer") +SUMIFS('Clientes Consolidado.'!M:M,'Clientes Consolidado.'!C:C,C11,'Clientes Consolidado.'!B:B,"Additive") +SUMIFS('Clientes Consolidado.'!M:M,'Clientes Consolidado.'!C:C,C11,'Clientes Consolidado.'!B:B,"Additive Intl.") -> 0 | Y11: =SUMIFS('Clientes Consolidado.'!N:N,'Clientes Consolidado.'!C:C,C11,'Clientes Consolidado.'!B:B,"Fertilizer") +SUMIFS('Clientes Consolidado.'!N:N,'Clientes Consolidado.'!C:C,C11,'Clientes Consolidado.'!B:B,"Additive") +SUMIFS('Clientes Consolidado.'!N:N,'Clientes Consolidado.'!C:C,C11,'Clientes Consolidado.'!B:B,"Additive Intl.") -> 0 | Z11: =SUMIFS('Clientes Consolidado.'!O:O,'Clientes Consolidado.'!C:C,C11,'Clientes Consolidado.'!B:B,"Fertilizer") +SUMIFS('Clientes Consolidado.'!O:O,'Clientes Consolidado.'!C:C,C11,'Clientes Consolidado.'!B:B,"Additive") +SUMIFS('Clientes Consolidado.'!O:O,'Clientes Consolidado.'!C:C,C11,'Clientes Consolidado.'!B:B,"Additive Intl.") -> 0 | AA11: =SUMIFS('Clientes Consolidado.'!P:P,'Clientes Consolidado.'!C:C,'Nova Versão '!C11,'Clientes Consolidado.'!B:B,"Fertilizer / Litigation")+SUMIFS('Clientes Consolidado.'!P:P,'Clientes Consolidado.'!C:C,'Nova Versão '!C11,'Clientes Consolidado.'!B:B,"Additive / Litigation") -> 1863200.9 | AD11: =SUMIFS('Invoiced amount'!I:I,'Invoiced amount'!AH:AH,'Nova Versão '!C11) -> 0 | AE11: =SUMIFS(Buget!K:K,Buget!E:E,'Nova Versão '!C11) -> 0 | AF11: =IF(OR(AE11=0,AE11=""),"",AD11/AE11) | AG11: =MAX(AE11-AD11,0) -> 0
B12: =_xlfn.XLOOKUP(C12,'Info Clientes'!A:A,'Info Clientes'!B:B) -> Fertilizer / Litigation | C12: CASA DAS SEMENTES | D12: =_xlfn.XLOOKUP(C12,'Limite de crédito'!C:C,'Limite de crédito'!G:G,0) -> 0 | E12: =K12+S12+AA12 -> 1702848.7 | F12: =_xlfn.XLOOKUP('Nova Versão '!C12,'Limite de crédito'!C:C,'Limite de crédito'!O:O,0) -> 0 | G12: =MAX(E12-F12,0) -> 1702848.7 | H12: =_xlfn.XLOOKUP(C12,'Info Clientes'!A:A,'Info Clientes'!C:C) -> Litigation | I12: =IF(_xlfn.XLOOKUP(C12,'Info Clientes'!A:A,'Info Clientes'!D:D,"")=0,"",_xlfn.XLOOKUP(C12,'Info Clientes'!A:A,'Info Clientes'!D:D,"")) | K12: =L12+M12+N12+O12+P12+Q12+R12 -> 0 | L12: =_xlfn.XLOOKUP(C12,'Clientes Consolidado.'!$C:$C,'Clientes Consolidado.'!R:R,0) -> 0 | M12: =_xlfn.XLOOKUP(C12,'Clientes Consolidado.'!$C:$C,'Clientes Consolidado.'!S:S,0) -> 0 | N12: =_xlfn.XLOOKUP(C12,'Clientes Consolidado.'!$C:$C,'Clientes Consolidado.'!T:T,0) -> 0 | O12: =_xlfn.XLOOKUP(C12,'Clientes Consolidado.'!$C:$C,'Clientes Consolidado.'!U:U,0) -> 0 | P12: =_xlfn.XLOOKUP(C12,'Clientes Consolidado.'!$C:$C,'Clientes Consolidado.'!V:V,0) -> 0 | Q12: =_xlfn.XLOOKUP(C12,'Clientes Consolidado.'!$C:$C,'Clientes Consolidado.'!W:W,0) -> 0 | R12: =_xlfn.XLOOKUP(C12,'Clientes Consolidado.'!$C:$C,'Clientes Consolidado.'!X:X,0) -> 0 | S12: =SUM(T12:Z12) -> 0 | T12: =SUMIFS('Clientes Consolidado.'!I:I,'Clientes Consolidado.'!C:C,C12,'Clientes Consolidado.'!B:B,"Fertilizer") +SUMIFS('Clientes Consolidado.'!I:I,'Clientes Consolidado.'!C:C,C12,'Clientes Consolidado.'!B:B,"Additive") +SUMIFS('Clientes Consolidado.'!I:I,'Clientes Consolidado.'!C:C,C12,'Clientes Consolidado.'!B:B,"Additive Intl.") -> 0 | U12: =SUMIFS('Clientes Consolidado.'!J:J,'Clientes Consolidado.'!C:C,C12,'Clientes Consolidado.'!B:B,"Fertilizer") +SUMIFS('Clientes Consolidado.'!J:J,'Clientes Consolidado.'!C:C,C12,'Clientes Consolidado.'!B:B,"Additive") +SUMIFS('Clientes Consolidado.'!J:J,'Clientes Consolidado.'!C:C,C12,'Clientes Consolidado.'!B:B,"Additive Intl.") -> 0 | V12: =SUMIFS('Clientes Consolidado.'!K:K,'Clientes Consolidado.'!C:C,C12,'Clientes Consolidado.'!B:B,"Fertilizer") +SUMIFS('Clientes Consolidado.'!K:K,'Clientes Consolidado.'!C:C,C12,'Clientes Consolidado.'!B:B,"Additive") +SUMIFS('Clientes Consolidado.'!K:K,'Clientes Consolidado.'!C:C,C12,'Clientes Consolidado.'!B:B,"Additive Intl.") -> 0 | W12: =SUMIFS('Clientes Consolidado.'!L:L,'Clientes Consolidado.'!C:C,C12,'Clientes Consolidado.'!B:B,"Fertilizer") +SUMIFS('Clientes Consolidado.'!L:L,'Clientes Consolidado.'!C:C,C12,'Clientes Consolidado.'!B:B,"Additive") +SUMIFS('Clientes Consolidado.'!L:L,'Clientes Consolidado.'!C:C,C12,'Clientes Consolidado.'!B:B,"Additive Intl.") -> 0 | X12: =SUMIFS('Clientes Consolidado.'!M:M,'Clientes Consolidado.'!C:C,C12,'Clientes Consolidado.'!B:B,"Fertilizer") +SUMIFS('Clientes Consolidado.'!M:M,'Clientes Consolidado.'!C:C,C12,'Clientes Consolidado.'!B:B,"Additive") +SUMIFS('Clientes Consolidado.'!M:M,'Clientes Consolidado.'!C:C,C12,'Clientes Consolidado.'!B:B,"Additive Intl.") -> 0 | Y12: =SUMIFS('Clientes Consolidado.'!N:N,'Clientes Consolidado.'!C:C,C12,'Clientes Consolidado.'!B:B,"Fertilizer") +SUMIFS('Clientes Consolidado.'!N:N,'Clientes Consolidado.'!C:C,C12,'Clientes Consolidado.'!B:B,"Additive") +SUMIFS('Clientes Consolidado.'!N:N,'Clientes Consolidado.'!C:C,C12,'Clientes Consolidado.'!B:B,"Additive Intl.") -> 0 | Z12: =SUMIFS('Clientes Consolidado.'!O:O,'Clientes Consolidado.'!C:C,C12,'Clientes Consolidado.'!B:B,"Fertilizer") +SUMIFS('Clientes Consolidado.'!O:O,'Clientes Consolidado.'!C:C,C12,'Clientes Consolidado.'!B:B,"Additive") +SUMIFS('Clientes Consolidado.'!O:O,'Clientes Consolidado.'!C:C,C12,'Clientes Consolidado.'!B:B,"Additive Intl.") -> 0 | AA12: =SUMIFS('Clientes Consolidado.'!P:P,'Clientes Consolidado.'!C:C,'Nova Versão '!C12,'Clientes Consolidado.'!B:B,"Fertilizer / Litigation")+SUMIFS('Clientes Consolidado.'!P:P,'Clientes Consolidado.'!C:C,'Nova Versão '!C12,'Clientes Consolidado.'!B:B,"Additive / Litigation") -> 1702848.7 | AD12: =SUMIFS('Invoiced amount'!I:I,'Invoiced amount'!AH:AH,'Nova Versão '!C12) -> 0 | AE12: =SUMIFS(Buget!K:K,Buget!E:E,'Nova Versão '!C12) -> 0 | AF12: =IF(OR(AE12=0,AE12=""),"",AD12/AE12) | AG12: =MAX(AE12-AD12,0) -> 0
B13: =_xlfn.XLOOKUP(C13,'Info Clientes'!A:A,'Info Clientes'!B:B) -> Additive | C13: EUROCHEM SERRA DO SALITRE | D13: =_xlfn.XLOOKUP(C13,'Limite de crédito'!C:C,'Limite de crédito'!G:G,0) -> 1500000 | E13: =K13+S13+AA13 -> 1248148.6 | F13: =_xlfn.XLOOKUP('Nova Versão '!C13,'Limite de crédito'!C:C,'Limite de crédito'!O:O,0) -> 0 | G13: =MAX(E13-F13,0) -> 1248148.6 | H13: =_xlfn.XLOOKUP(C13,'Info Clientes'!A:A,'Info Clientes'!C:C) -> Approved in credit committee | I13: =IF(_xlfn.XLOOKUP(C13,'Info Clientes'!A:A,'Info Clientes'!D:D,"")=0,"",_xlfn.XLOOKUP(C13,'Info Clientes'!A:A,'Info Clientes'!D:D,"")) | K13: =L13+M13+N13+O13+P13+Q13+R13 -> 1248148.6 | L13: =_xlfn.XLOOKUP(C13,'Clientes Consolidado.'!$C:$C,'Clientes Consolidado.'!R:R,0) -> 161488.2 | M13: =_xlfn.XLOOKUP(C13,'Clientes Consolidado.'!$C:$C,'Clientes Consolidado.'!S:S,0) -> 1086660.4 | N13: =_xlfn.XLOOKUP(C13,'Clientes Consolidado.'!$C:$C,'Clientes Consolidado.'!T:T,0) -> 0 | O13: =_xlfn.XLOOKUP(C13,'Clientes Consolidado.'!$C:$C,'Clientes Consolidado.'!U:U,0) -> 0 | P13: =_xlfn.XLOOKUP(C13,'Clientes Consolidado.'!$C:$C,'Clientes Consolidado.'!V:V,0) -> 0 | Q13: =_xlfn.XLOOKUP(C13,'Clientes Consolidado.'!$C:$C,'Clientes Consolidado.'!W:W,0) -> 0 | R13: =_xlfn.XLOOKUP(C13,'Clientes Consolidado.'!$C:$C,'Clientes Consolidado.'!X:X,0) -> 0 | S13: =SUM(T13:Z13) -> 0 | T13: =SUMIFS('Clientes Consolidado.'!I:I,'Clientes Consolidado.'!C:C,C13,'Clientes Consolidado.'!B:B,"Fertilizer") +SUMIFS('Clientes Consolidado.'!I:I,'Clientes Consolidado.'!C:C,C13,'Clientes Consolidado.'!B:B,"Additive") +SUMIFS('Clientes Consolidado.'!I:I,'Clientes Consolidado.'!C:C,C13,'Clientes Consolidado.'!B:B,"Additive Intl.") -> 0 | U13: =SUMIFS('Clientes Consolidado.'!J:J,'Clientes Consolidado.'!C:C,C13,'Clientes Consolidado.'!B:B,"Fertilizer") +SUMIFS('Clientes Consolidado.'!J:J,'Clientes Consolidado.'!C:C,C13,'Clientes Consolidado.'!B:B,"Additive") +SUMIFS('Clientes Consolidado.'!J:J,'Clientes Consolidado.'!C:C,C13,'Clientes Consolidado.'!B:B,"Additive Intl.") -> 0 | V13: =SUMIFS('Clientes Consolidado.'!K:K,'Clientes Consolidado.'!C:C,C13,'Clientes Consolidado.'!B:B,"Fertilizer") +SUMIFS('Clientes Consolidado.'!K:K,'Clientes Consolidado.'!C:C,C13,'Clientes Consolidado.'!B:B,"Additive") +SUMIFS('Clientes Consolidado.'!K:K,'Clientes Consolidado.'!C:C,C13,'Clientes Consolidado.'!B:B,"Additive Intl.") -> 0 | W13: =SUMIFS('Clientes Consolidado.'!L:L,'Clientes Consolidado.'!C:C,C13,'Clientes Consolidado.'!B:B,"Fertilizer") +SUMIFS('Clientes Consolidado.'!L:L,'Clientes Consolidado.'!C:C,C13,'Clientes Consolidado.'!B:B,"Additive") +SUMIFS('Clientes Consolidado.'!L:L,'Clientes Consolidado.'!C:C,C13,'Clientes Consolidado.'!B:B,"Additive Intl.") -> 0 | X13: =SUMIFS('Clientes Consolidado.'!M:M,'Clientes Consolidado.'!C:C,C13,'Clientes Consolidado.'!B:B,"Fertilizer") +SUMIFS('Clientes Consolidado.'!M:M,'Clientes Consolidado.'!C:C,C13,'Clientes Consolidado.'!B:B,"Additive") +SUMIFS('Clientes Consolidado.'!M:M,'Clientes Consolidado.'!C:C,C13,'Clientes Consolidado.'!B:B,"Additive Intl.") -> 0 | Y13: =SUMIFS('Clientes Consolidado.'!N:N,'Clientes Consolidado.'!C:C,C13,'Clientes Consolidado.'!B:B,"Fertilizer") +SUMIFS('Clientes Consolidado.'!N:N,'Clientes Consolidado.'!C:C,C13,'Clientes Consolidado.'!B:B,"Additive") +SUMIFS('Clientes Consolidado.'!N:N,'Clientes Consolidado.'!C:C,C13,'Clientes Consolidado.'!B:B,"Additive Intl.") -> 0 | Z13: =SUMIFS('Clientes Consolidado.'!O:O,'Clientes Consolidado.'!C:C,C13,'Clientes Consolidado.'!B:B,"Fertilizer") +SUMIFS('Clientes Consolidado.'!O:O,'Clientes Consolidado.'!C:C,C13,'Clientes Consolidado.'!B:B,"Additive") +SUMIFS('Clientes Consolidado.'!O:O,'Clientes Consolidado.'!C:C,C13,'Clientes Consolidado.'!B:B,"Additive Intl.") -> 0 | AA13: =SUMIFS('Clientes Consolidado.'!P:P,'Clientes Consolidado.'!C:C,'Nova Versão '!C13,'Clientes Consolidado.'!B:B,"Fertilizer / Litigation")+SUMIFS('Clientes Consolidado.'!P:P,'Clientes Consolidado.'!C:C,'Nova Versão '!C13,'Clientes Consolidado.'!B:B,"Additive / Litigation") -> 0 | AD13: =SUMIFS('Invoiced amount'!I:I,'Invoiced amount'!AH:AH,'Nova Versão '!C13) -> 3585858.8 | AE13: =SUMIFS(Buget!K:K,Buget!E:E,'Nova Versão '!C13) -> 5559000 | AF13: =IF(OR(AE13=0,AE13=""),"",AD13/AE13) -> 0.64505465 | AG13: =MAX(AE13-AD13,0) -> 1973141.2
B14: =_xlfn.XLOOKUP(C14,'Info Clientes'!A:A,'Info Clientes'!B:B) -> Additive | C14: GRUPO FERTILIZ TOCANTINS | D14: =_xlfn.XLOOKUP(C14,'Limite de crédito'!C:C,'Limite de crédito'!G:G,0) -> 1500000 | E14: =K14+S14+AA14 -> 1237619.9 | F14: =_xlfn.XLOOKUP('Nova Versão '!C14,'Limite de crédito'!C:C,'Limite de crédito'!O:O,0) -> 0 | G14: =MAX(E14-F14,0) -> 1237619.9 | H14: =_xlfn.XLOOKUP(C14,'Info Clientes'!A:A,'Info Clientes'!C:C) -> Approved in credit committee | I14: =IF(_xlfn.XLOOKUP(C14,'Info Clientes'!A:A,'Info Clientes'!D:D,"")=0,"",_xlfn.XLOOKUP(C14,'Info Clientes'!A:A,'Info Clientes'!D:D,"")) | K14: =L14+M14+N14+O14+P14+Q14+R14 -> 1237619.9 | L14: =_xlfn.XLOOKUP(C14,'Clientes Consolidado.'!$C:$C,'Clientes Consolidado.'!R:R,0) -> 331136.7 | M14: =_xlfn.XLOOKUP(C14,'Clientes Consolidado.'!$C:$C,'Clientes Consolidado.'!S:S,0) -> 906483.2 | N14: =_xlfn.XLOOKUP(C14,'Clientes Consolidado.'!$C:$C,'Clientes Consolidado.'!T:T,0) -> 0 | O14: =_xlfn.XLOOKUP(C14,'Clientes Consolidado.'!$C:$C,'Clientes Consolidado.'!U:U,0) -> 0 | P14: =_xlfn.XLOOKUP(C14,'Clientes Consolidado.'!$C:$C,'Clientes Consolidado.'!V:V,0) -> 0 | Q14: =_xlfn.XLOOKUP(C14,'Clientes Consolidado.'!$C:$C,'Clientes Consolidado.'!W:W,0) -> 0 | R14: =_xlfn.XLOOKUP(C14,'Clientes Consolidado.'!$C:$C,'Clientes Consolidado.'!X:X,0) -> 0 | S14: =SUM(T14:Z14) -> 0 | T14: =SUMIFS('Clientes Consolidado.'!I:I,'Clientes Consolidado.'!C:C,C14,'Clientes Consolidado.'!B:B,"Fertilizer") +SUMIFS('Clientes Consolidado.'!I:I,'Clientes Consolidado.'!C:C,C14,'Clientes Consolidado.'!B:B,"Additive") +SUMIFS('Clientes Consolidado.'!I:I,'Clientes Consolidado.'!C:C,C14,'Clientes Consolidado.'!B:B,"Additive Intl.") -> 0 | U14: =SUMIFS('Clientes Consolidado.'!J:J,'Clientes Consolidado.'!C:C,C14,'Clientes Consolidado.'!B:B,"Fertilizer") +SUMIFS('Clientes Consolidado.'!J:J,'Clientes Consolidado.'!C:C,C14,'Clientes Consolidado.'!B:B,"Additive") +SUMIFS('Clientes Consolidado.'!J:J,'Clientes Consolidado.'!C:C,C14,'Clientes Consolidado.'!B:B,"Additive Intl.") -> 0 | V14: =SUMIFS('Clientes Consolidado.'!K:K,'Clientes Consolidado.'!C:C,C14,'Clientes Consolidado.'!B:B,"Fertilizer") +SUMIFS('Clientes Consolidado.'!K:K,'Clientes Consolidado.'!C:C,C14,'Clientes Consolidado.'!B:B,"Additive") +SUMIFS('Clientes Consolidado.'!K:K,'Clientes Consolidado.'!C:C,C14,'Clientes Consolidado.'!B:B,"Additive Intl.") -> 0 | W14: =SUMIFS('Clientes Consolidado.'!L:L,'Clientes Consolidado.'!C:C,C14,'Clientes Consolidado.'!B:B,"Fertilizer") +SUMIFS('Clientes Consolidado.'!L:L,'Clientes Consolidado.'!C:C,C14,'Clientes Consolidado.'!B:B,"Additive") +SUMIFS('Clientes Consolidado.'!L:L,'Clientes Consolidado.'!C:C,C14,'Clientes Consolidado.'!B:B,"Additive Intl.") -> 0 | X14: =SUMIFS('Clientes Consolidado.'!M:M,'Clientes Consolidado.'!C:C,C14,'Clientes Consolidado.'!B:B,"Fertilizer") +SUMIFS('Clientes Consolidado.'!M:M,'Clientes Consolidado.'!C:C,C14,'Clientes Consolidado.'!B:B,"Additive") +SUMIFS('Clientes Consolidado.'!M:M,'Clientes Consolidado.'!C:C,C14,'Clientes Consolidado.'!B:B,"Additive Intl.") -> 0 | Y14: =SUMIFS('Clientes Consolidado.'!N:N,'Clientes Consolidado.'!C:C,C14,'Clientes Consolidado.'!B:B,"Fertilizer") +SUMIFS('Clientes Consolidado.'!N:N,'Clientes Consolidado.'!C:C,C14,'Clientes Consolidado.'!B:B,"Additive") +SUMIFS('Clientes Consolidado.'!N:N,'Clientes Consolidado.'!C:C,C14,'Clientes Consolidado.'!B:B,"Additive Intl.") -> 0 | Z14: =SUMIFS('Clientes Consolidado.'!O:O,'Clientes Consolidado.'!C:C,C14,'Clientes Consolidado.'!B:B,"Fertilizer") +SUMIFS('Clientes Consolidado.'!O:O,'Clientes Consolidado.'!C:C,C14,'Clientes Consolidado.'!B:B,"Additive") +SUMIFS('Clientes Consolidado.'!O:O,'Clientes Consolidado.'!C:C,C14,'Clientes Consolidado.'!B:B,"Additive Intl.") -> 0 | AA14: =SUMIFS('Clientes Consolidado.'!P:P,'Clientes Consolidado.'!C:C,'Nova Versão '!C14,'Clientes Consolidado.'!B:B,"Fertilizer / Litigation")+SUMIFS('Clientes Consolidado.'!P:P,'Clientes Consolidado.'!C:C,'Nova Versão '!C14,'Clientes Consolidado.'!B:B,"Additive / Litigation") -> 0 | AD14: =SUMIFS('Invoiced amount'!I:I,'Invoiced amount'!AH:AH,'Nova Versão '!C14) -> 3913915.9 | AE14: =SUMIFS(Buget!K:K,Buget!E:E,'Nova Versão '!C14) -> 19253158 | AF14: =IF(OR(AE14=0,AE14=""),"",AD14/AE14) -> 0.20328696 | AG14: =MAX(AE14-AD14,0) -> 15339242
... B85: =_xlfn.XLOOKUP(C85,'Info Clientes'!A:A,'Info Clientes'!B:B) -> Additive | C85: MARIA JOSE DA SILVA | D85: =_xlfn.XLOOKUP(C85,'Limite de crédito'!C:C,'Limite de crédito'!G:G,0) -> 0 | E85: =K85+S85+AA85 -> 50 | F85: =_xlfn.XLOOKUP('Nova Versão '!C85,'Limite de crédito'!C:C,'Limite de crédito'!O:O,0) -> 0 | G85: =MAX(E85-F85,0) -> 50 | H85: =_xlfn.XLOOKUP(C85,'Info Clientes'!A:A,'Info Clientes'!C:C) -> Sales to employees | I85: =IF(_xlfn.XLOOKUP(C85,'Info Clientes'!A:A,'Info Clientes'!D:D,"")=0,"",_xlfn.XLOOKUP(C85,'Info Clientes'!A:A,'Info Clientes'!D:D,"")) | K85: =L85+M85+N85+O85+P85+Q85+R85 -> 0 | L85: =_xlfn.XLOOKUP(C85,'Clientes Consolidado.'!$C:$C,'Clientes Consolidado.'!R:R,0) -> 0 | M85: =_xlfn.XLOOKUP(C85,'Clientes Consolidado.'!$C:$C,'Clientes Consolidado.'!S:S,0) -> 0 | N85: =_xlfn.XLOOKUP(C85,'Clientes Consolidado.'!$C:$C,'Clientes Consolidado.'!T:T,0) -> 0 | O85: =_xlfn.XLOOKUP(C85,'Clientes Consolidado.'!$C:$C,'Clientes Consolidado.'!U:U,0) -> 0 | P85: =_xlfn.XLOOKUP(C85,'Clientes Consolidado.'!$C:$C,'Clientes Consolidado.'!V:V,0) -> 0 | Q85: =_xlfn.XLOOKUP(C85,'Clientes Consolidado.'!$C:$C,'Clientes Consolidado.'!W:W,0) -> 0 | R85: =_xlfn.XLOOKUP(C85,'Clientes Consolidado.'!$C:$C,'Clientes Consolidado.'!X:X,0) -> 0 | S85: =SUM(T85:Z85) -> 50 | T85: =SUMIFS('Clientes Consolidado.'!I:I,'Clientes Consolidado.'!C:C,C85,'Clientes Consolidado.'!B:B,"Fertilizer") +SUMIFS('Clientes Consolidado.'!I:I,'Clientes Consolidado.'!C:C,C85,'Clientes Consolidado.'!B:B,"Additive") +SUMIFS('Clientes Consolidado.'!I:I,'Clientes Consolidado.'!C:C,C85,'Clientes Consolidado.'!B:B,"Additive Intl.") -> 0 | U85: =SUMIFS('Clientes Consolidado.'!J:J,'Clientes Consolidado.'!C:C,C85,'Clientes Consolidado.'!B:B,"Fertilizer") +SUMIFS('Clientes Consolidado.'!J:J,'Clientes Consolidado.'!C:C,C85,'Clientes Consolidado.'!B:B,"Additive") +SUMIFS('Clientes Consolidado.'!J:J,'Clientes Consolidado.'!C:C,C85,'Clientes Consolidado.'!B:B,"Additive Intl.") -> 0 | V85: =SUMIFS('Clientes Consolidado.'!K:K,'Clientes Consolidado.'!C:C,C85,'Clientes Consolidado.'!B:B,"Fertilizer") +SUMIFS('Clientes Consolidado.'!K:K,'Clientes Consolidado.'!C:C,C85,'Clientes Consolidado.'!B:B,"Additive") +SUMIFS('Clientes Consolidado.'!K:K,'Clientes Consolidado.'!C:C,C85,'Clientes Consolidado.'!B:B,"Additive Intl.") -> 0 | W85: =SUMIFS('Clientes Consolidado.'!L:L,'Clientes Consolidado.'!C:C,C85,'Clientes Consolidado.'!B:B,"Fertilizer") +SUMIFS('Clientes Consolidado.'!L:L,'Clientes Consolidado.'!C:C,C85,'Clientes Consolidado.'!B:B,"Additive") +SUMIFS('Clientes Consolidado.'!L:L,'Clientes Consolidado.'!C:C,C85,'Clientes Consolidado.'!B:B,"Additive Intl.") -> 0 | X85: =SUMIFS('Clientes Consolidado.'!M:M,'Clientes Consolidado.'!C:C,C85,'Clientes Consolidado.'!B:B,"Fertilizer") +SUMIFS('Clientes Consolidado.'!M:M,'Clientes Consolidado.'!C:C,C85,'Clientes Consolidado.'!B:B,"Additive") +SUMIFS('Clientes Consolidado.'!M:M,'Clientes Consolidado.'!C:C,C85,'Clientes Consolidado.'!B:B,"Additive Intl.") -> 0 | Y85: =SUMIFS('Clientes Consolidado.'!N:N,'Clientes Consolidado.'!C:C,C85,'Clientes Consolidado.'!B:B,"Fertilizer") +SUMIFS('Clientes Consolidado.'!N:N,'Clientes Consolidado.'!C:C,C85,'Clientes Consolidado.'!B:B,"Additive") +SUMIFS('Clientes Consolidado.'!N:N,'Clientes Consolidado.'!C:C,C85,'Clientes Consolidado.'!B:B,"Additive Intl.") -> 0 | Z85: =SUMIFS('Clientes Consolidado.'!O:O,'Clientes Consolidado.'!C:C,C85,'Clientes Consolidado.'!B:B,"Fertilizer") +SUMIFS('Clientes Consolidado.'!O:O,'Clientes Consolidado.'!C:C,C85,'Clientes Consolidado.'!B:B,"Additive") +SUMIFS('Clientes Consolidado.'!O:O,'Clientes Consolidado.'!C:C,C85,'Clientes Consolidado.'!B:B,"Additive Intl.") -> 50 | AA85: =SUMIFS('Clientes Consolidado.'!P:P,'Clientes Consolidado.'!C:C,'Nova Versão '!C85,'Clientes Consolidado.'!B:B,"Fertilizer / Litigation")+SUMIFS('Clientes Consolidado.'!P:P,'Clientes Consolidado.'!C:C,'Nova Versão '!C85,'Clientes Consolidado.'!B:B,"Additive / Litigation") -> 0 | AD85: =SUMIFS('Invoiced amount'!I:I,'Invoiced amount'!AH:AH,'Nova Versão '!C85) -> 0 | AE85: =SUMIFS(Buget!K:K,Buget!E:E,'Nova Versão '!C85) -> 0 | AF85: =IF(OR(AE85=0,AE85=""),"",AD85/AE85) | AG85: =MAX(AE85-AD85,0) -> 0

Sheet New version Aging AR
AD2: INVOICING 2026
C3: 46198 | E3: =SUBTOTAL(9,E5:E828) -> 63971254 | K3: =SUBTOTAL(9,K5:K828) -> 40542363 | L3: =SUBTOTAL(9,L5:L828) -> 16649787 | M3: =SUBTOTAL(9,M5:M828) -> 10148231 | N3: =SUBTOTAL(9,N5:N828) -> 13023615 | O3: =SUBTOTAL(9,O5:O828) -> 247837.21 | P3: =SUBTOTAL(9,P5:P828) -> 299642.08 | Q3: =SUBTOTAL(9,Q5:Q828) -> 76480.23 | R3: =SUBTOTAL(9,R5:R828) -> 96770.01 | ... AA3: =SUBTOTAL(9,AA5:AA828) -> 22315752 | AD3: =SUBTOTAL(9,AD5:AD828) -> 1.1272671e+08 | AE3: =SUBTOTAL(9,AE5:AE828) -> 3.1260058e+08 | AG3: =SUBTOTAL(9,AG5:AG828) -> 2.0340978e+08
B4: BU | C4: Customer | D4: Credit Approved | E4: Total AR | F4: Credit Insurance | G4: Open Open Exposure w/t Credit Insurance | H4: Remark for Open Exposure (approved in credit committee,guarantee or credit approved based on credit rating). | I4: Comments | K4: AR Not Due | L4: 1-30 Days | M4: 31-60 Days | N4: 61-90 Days | O4: 91-120 Days | P4: 121-180 Days | Q4: 181-360 Days | R4: Above 360 Days | S4: AR Over Due but not in Litigation | T4: 1-30 Days | U4: 31-60 Days | V4: 61-90 Days | W4: 91-120 Days | X4: 121-180 Days | Y4: 181-360 Days | Z4: Above 360 Days | AA4: AR in Litigation | AB4: Collection Risk Probable / Possible / Rare | AD4: Invoiced amount | AE4: Buget | AF4: Invoiced percentage | AG4: Remaining amount to be invoiced
B5: Additive | C5: GRUPO MOSAIC FERTILIZANTES P K LTDA | D5: 10000000 | E5: 7696493.6 | F5: 10000000 | G5: 0 | H5: Guarantee or credit | K5: 7696493.6 | L5: 2989374.9 | M5: 1924024.8 | N5: 2535256.7 | O5: 247837.21 | P5: 0 | Q5: 0 | R5: 0 | S5: 0 | T5: 0 | U5: 0 | V5: 0 | W5: 0 | X5: 0 | Y5: 0 | Z5: 0 | AA5: 0 | AD5: 12849715 | AE5: 32470400 | AF5: 0.39573627 | AG5: 19620685
B6: Fertilizer / Litigation | C6: CENTRAL DO ADUBO COM E REPRESENTACAO LTD | D6: 0 | E6: 7560727.8 | F6: 0 | G6: 7560727.8 | H6: Litigation | K6: 0 | L6: 0 | M6: 0 | N6: 0 | O6: 0 | P6: 0 | Q6: 0 | R6: 0 | S6: 0 | T6: 0 | U6: 0 | V6: 0 | W6: 0 | X6: 0 | Y6: 0 | Z6: 0 | AA6: 7560727.8 | AD6: 17640 | AE6: 0 | AG6: 0
B7: Additive | C7: GRUPO MOSAIC FERTILIZANTES DO BRASIL | D7: 15000000 | E7: 7490408.6 | F7: 15000000 | G7: 0 | H7: Guarantee or credit | K7: 7473589.6 | L7: 746905.4 | M7: 2076080.5 | N7: 4650603.8 | O7: 0 | P7: 0 | Q7: 0 | R7: 0 | S7: 16818.92 | T7: 0 | U7: 0 | V7: 0 | W7: 0 | X7: 0 | Y7: 64.2 | Z7: 16754.72 | AA7: 0 | AD7: 12642848 | AE7: 38799849 | AF7: 0.32584788 | AG7: 26157001
B8: Additive | C8: GRUPO YARA | D8: 6000000 | E8: 4784150 | F8: 6000000 | G8: 0 | H8: Guarantee or credit | K8: 4778523.7 | L8: 3419201.1 | M8: 1359322.6 | N8: 0 | O8: 0 | P8: 0 | Q8: 0 | R8: 0 | S8: 5626.32 | T8: 0 | U8: 0 | V8: 0 | W8: 0 | X8: 0 | Y8: 0 | Z8: 5626.32 | AA8: 0 | AD8: 17271600 | AE8: 32130000 | AF8: 0.5375537 | AG8: 14858400
B9: Additive Intl. | C9: NITROFERT SAS - COLOMBIA | D9: 5000000 | E9: 3774575.4 | F9: 0 | G9: 3774575.4 | H9: Approved in credit committee | I9: We are finalizing a letter of comfort with the client, signed by the Nitron group. | K9: 3774575.4 | L9: 0 | M9: 668371.59 | N9: 3106203.8 | O9: 0 | P9: 0 | Q9: 0 | R9: 0 | S9: 0 | T9: 0 | U9: 0 | V9: 0 | W9: 0 | X9: 0 | Y9: 0 | Z9: 0 | AA9: 0 | AD9: 7728141.1 | AE9: 7055332.6 | AF9: 1.0953617 | AG9: 0
B10: Fertilizer / Litigation | C10: GRUPO LEANDRO SARTI | D10: 0 | E10: 3088531.1 | F10: 0 | G10: 3088531.1 | H10: Litigation | K10: 0 | L10: 0 | M10: 0 | N10: 0 | O10: 0 | P10: 0 | Q10: 0 | R10: 0 | S10: 0 | T10: 0 | U10: 0 | V10: 0 | W10: 0 | X10: 0 | Y10: 0 | Z10: 0 | AA10: 3088531.1 | AD10: 0 | AE10: 0 | AG10: 0
B11: Fertilizer / Litigation | C11: AGRO BERALDO | D11: 0 | E11: 3044850.9 | F11: 0 | G11: 3044850.9 | H11: Litigation | K11: 0 | L11: 0 | M11: 0 | N11: 0 | O11: 0 | P11: 0 | Q11: 0 | R11: 0 | S11: 0 | T11: 0 | U11: 0 | V11: 0 | W11: 0 | X11: 0 | Y11: 0 | Z11: 0 | AA11: 3044850.9 | AD11: 0 | AE11: 0 | AG11: 0
B12: Fertilizer / Litigation | C12: TERRA FERTIL - MACHADO | D12: 0 | E12: 2492842.1 | F12: 0 | G12: 2492842.1 | H12: Litigation | K12: 0 | L12: 0 | M12: 0 | N12: 0 | O12: 0 | P12: 0 | Q12: 0 | R12: 0 | S12: 0 | T12: 0 | U12: 0 | V12: 0 | W12: 0 | X12: 0 | Y12: 0 | Z12: 0 | AA12: 2492842.1 | AD12: 0 | AE12: 0 | AG12: 0
B13: Fertilizer / Litigation | C13: MOGIANA TECNO AGRO | D13: 0 | E13: 1863200.9 | F13: 0 | G13: 1863200.9 | H13: Litigation | K13: 0 | L13: 0 | M13: 0 | N13: 0 | O13: 0 | P13: 0 | Q13: 0 | R13: 0 | S13: 0 | T13: 0 | U13: 0 | V13: 0 | W13: 0 | X13: 0 | Y13: 0 | Z13: 0 | AA13: 1863200.9 | AD13: 0 | AE13: 0 | AG13: 0
B14: Fertilizer / Litigation | C14: CASA DAS SEMENTES | D14: 0 | E14: 1702848.7 | F14: 0 | G14: 1702848.7 | H14: Litigation | K14: 0 | L14: 0 | M14: 0 | N14: 0 | O14: 0 | P14: 0 | Q14: 0 | R14: 0 | S14: 0 | T14: 0 | U14: 0 | V14: 0 | W14: 0 | X14: 0 | Y14: 0 | Z14: 0 | AA14: 1702848.7 | AD14: 0 | AE14: 0 | AG14: 0
B15: Additive | C15: EUROCHEM SERRA DO SALITRE | D15: 1500000 | E15: 1248148.6 | F15: 0 | G15: 1248148.6 | H15: Approved in credit committee | K15: 1248148.6 | L15: 161488.2 | M15: 1086660.4 | N15: 0 | O15: 0 | P15: 0 | Q15: 0 | R15: 0 | S15: 0 | T15: 0 | U15: 0 | V15: 0 | W15: 0 | X15: 0 | Y15: 0 | Z15: 0 | AA15: 0 | AD15: 3585858.8 | AE15: 5559000 | AF15: 0.64505465 | AG15: 1973141.2
B16: Additive | C16: GRUPO FERTILIZ TOCANTINS | D16: 1500000 | E16: 1237619.9 | F16: 0 | G16: 1237619.9 | H16: Approved in credit committee | K16: 1237619.9 | L16: 331136.7 | M16: 906483.2 | N16: 0 | O16: 0 | P16: 0 | Q16: 0 | R16: 0 | S16: 0 | T16: 0 | U16: 0 | V16: 0 | W16: 0 | X16: 0 | Y16: 0 | Z16: 0 | AA16: 0 | AD16: 3913915.9 | AE16: 19253158 | AF16: 0.20328696 | AG16: 15339242
B17: Fertilizer / Litigation | C17: FAZENDA ARCOS SÃO JOÃO | D17: 0 | E17: 988506.24 | F17: 0 | G17: 988506.24 | H17: Litigation | K17: 0 | L17: 0 | M17: 0 | N17: 0 | O17: 0 | P17: 0 | Q17: 0 | R17: 0 | S17: 0 | T17: 0 | U17: 0 | V17: 0 | W17: 0 | X17: 0 | Y17: 0 | Z17: 0 | AA17: 988506.24 | AD17: 0 | AE17: 0 | AG17: 0
B18: Fertilizer | C18: AGROVIVA | D18: 500000 | E18: 925457.06 | F18: 500000 | G18: 425457.06 | H18: Guarantee or credit | I18: In addition to the insurance policy worth 500k, we have a CREDIT OPENING AGREEMENT WITH GUARANTEE worth 1,800k. | K18: 925457.06 | L18: 0 | M18: 0 | N18: 925457.06 | O18: 0 | P18: 0 | Q18: 0 | R18: 0 | S18: 0 | T18: 0 | U18: 0 | V18: 0 | W18: 0 | X18: 0 | Y18: 0 | Z18: 0 | AA18: 0 | AD18: 0 | AE18: 57004 | AF18: 0 | AG18: 57004
B19: Fertilizer / Litigation | C19: CBM FERTILIZANTES | D19: 0 | E19: 876011.75 | F19: 0 | G19: 876011.75 | H19: Litigation | K19: 0 | L19: 0 | M19: 0 | N19: 0 | O19: 0 | P19: 0 | Q19: 0 | R19: 0 | S19: 0 | T19: 0 | U19: 0 | V19: 0 | W19: 0 | X19: 0 | Y19: 0 | Z19: 0 | AA19: 876011.75 | AD19: 0 | AE19: 0 | AG19: 0
B20: Additive | C20: GRUPO FERTIPAR FERTILIZANTES MATO GROSSO | D20: 1500000 | E20: 815885.6 | F20: 1500000 | G20: 0 | H20: Guarantee or credit | K20: 815885.6 | L20: 815885.6 | M20: 0 | N20: 0 | O20: 0 | P20: 0 | Q20: 0 | R20: 0 | S20: 0 | T20: 0 | U20: 0 | V20: 0 | W20: 0 | X20: 0 | Y20: 0 | Z20: 0 | AA20: 0 | AD20: 2226421.4 | AE20: 4967550 | AF20: 0.44819305 | AG20: 2741128.6
B21: Fertilizer | C21: CONNTACTA AGRONEGOCIOS | D21: 500000 | E21: 739540.06 | F21: 500000 | G21: 239540.06 | H21: Guarantee or credit | I21: Coverage via Coface insurance company in the amount of 500k. | K21: 739540.06 | L21: 0 | M21: 0 | N21: 739540.06 | O21: 0 | P21: 0 | Q21: 0 | R21: 0 | S21: 0 | T21: 0 | U21: 0 | V21: 0 | W21: 0 | X21: 0 | Y21: 0 | Z21: 0 | AA21: 0 | AD21: 0 | AE21: 325986.33 | AF21: 0 | AG21: 325986.33
B22: Additive | C22: STRATOS - ROSARIO DO CATETE | D22: 1500000 | E22: 710879.2 | F22: 1500000 | G22: 0 | H22: Guarantee or credit | K22: 710879.2 | L22: 0 | M22: 355675.6 | N22: 355203.6 | O22: 0 | P22: 0 | Q22: 0 | R22: 0 | S22: 0 | T22: 0 | U22: 0 | V22: 0 | W22: 0 | X22: 0 | Y22: 0 | Z22: 0 | AA22: 0 | AD22: 2497258.8 | AE22: 4410300 | AF22: 0.56623332 | AG22: 1913041.2
B23: Additive | C23: FOSNOR - LUIS EDUARDO MAGALHAES | D23: 2600000 | E23: 693727.1 | F23: 2600000 | G23: 0 | H23: Guarantee or credit | K23: 693727.1 | L23: 693727.1 | M23: 0 | N23: 0 | O23: 0 | P23: 0 | Q23: 0 | R23: 0 | S23: 0 | T23: 0 | U23: 0 | V23: 0 | W23: 0 | X23: 0 | Y23: 0 | Z23: 0 | AA23: 0 | AD23: 3467645 | AE23: 9477000 | AF23: 0.36590113 | AG23: 6009355
B24: Additive Intl. | C24: YTL S.A. - PARAGUAI | D24: 750000 | E24: 645640.83 | F24: 550000 | G24: 95640.83 | H24: Guarantee or credit + Credit approved based on credit rating | K24: 453681.62 | L24: 453681.62 | M24: 0 | N24: 0 | O24: 0 | P24: 0 | Q24: 0 | R24: 0 | S24: 191959.21 | T24: 191959.21 | U24: 0 | V24: 0 | W24: 0 | X24: 0 | Y24: 0 | Z24: 0 | AA24: 0 | AD24: 2690327 | AE24: 5338800 | AF24: 0.50391979 | AG24: 2648473
B25: Additive Intl. | C25: ISUSA - URUGUAI | D25: 1375000 | E25: 605051.04 | F25: 1375000 | G25: 0 | H25: Guarantee or credit | K25: 605051.04 | L25: 605051.04 | M25: 0 | N25: 0 | O25: 0 | P25: 0 | Q25: 0 | R25: 0 | S25: 0 | T25: 0 | U25: 0 | V25: 0 | W25: 0 | X25: 0 | Y25: 0 | Z25: 0 | AA25: 0 | AD25: 1363533.3 | AE25: 861803.52 | AF25: 1.5821858 | AG25: 0
B26: Additive | C26: GRUPO HERINGER | D26: 800000 | E26: 553728.61 | F26: 0 | G26: 553728.61 | H26: Approved in credit committee | K26: 553728.61 | L26: 456958.6 | M26: 0 | N26: 0 | O26: 0 | P26: 0 | Q26: 0 | R26: 96770.01 | S26: 0 | T26: 0 | U26: 0 | V26: 0 | W26: 0 | X26: 0 | Y26: 0 | Z26: 0 | AA26: 0 | AD26: 655665.8 | AE26: 5516320.7 | AF26: 0.11885926 | AG26: 4860654.9
B27: Additive Intl. | C27: MOSAIC FERTILIZANTES PARAGUAY S.R.L. | D27: 660000 | E27: 537697.8 | F27: 660000 | G27: 0 | H27: Guarantee or credit | K27: 537697.8 | L27: 0 | M27: 91784.41 | N27: 445913.39 | O27: 0 | P27: 0 | Q27: 0 | R27: 0 | S27: 0 | T27: 0 | U27: 0 | V27: 0 | W27: 0 | X27: 0 | Y27: 0 | Z27: 0 | AA27: 0 | AD27: 751415.52 | AE27: 3026070.6 | AF27: 0.24831394 | AG27: 2274655.1
B28: Additive | C28: FERTGROW S.A | D28: 3500000 | E28: 526852.5 | F28: 3500000 | G28: 0 | H28: Guarantee or credit | K28: 526852.5 | L28: 526852.5 | M28: 0 | N28: 0 | O28: 0 | P28: 0 | Q28: 0 | R28: 0 | S28: 0 | T28: 0 | U28: 0 | V28: 0 | W28: 0 | X28: 0 | Y28: 0 | Z28: 0 | AA28: 0 | AD28: 5533915.7 | AE28: 13156098 | AF28: 0.42063501 | AG28: 7622182.8
B29: Additive | C29: ULTRAFERTIL | D29: 1500000 | E29: 519608.6 | F29: 1500000 | G29: 0 | H29: Guarantee or credit | K29: 519608.6 | L29: 394528.6 | M29: 125080 | N29: 0 | O29: 0 | P29: 0 | Q29: 0 | R29: 0 | S29: 0 | T29: 0 | U29: 0 | V29: 0 | W29: 0 | X29: 0 | Y29: 0 | Z29: 0 | AA29: 0 | AD29: 586679.8 | AE29: 0 | AG29: 0
B30: Additive | C30: GRUPO UNIFERTIL | D30: 4500000 | E30: 462929.8 | F30: 4500000 | G30: 0 | H30: Guarantee or credit | K30: 462929.8 | L30: 462929.8 | M30: 0 | N30: 0 | O30: 0 | P30: 0 | Q30: 0 | R30: 0 | S30: 0 | T30: 0 | U30: 0 | V30: 0 | W30: 0 | X30: 0 | Y30: 0 | Z30: 0 | AA30: 0 | AD30: 7436152.2 | AE30: 21677673 | AF30: 0.34303277 | AG30: 14241521
B31: Additive | C31: GRUPO AMAGGI | D31: 4000000 | E31: 405140 | F31: 4000000 | G31: 0 | H31: Guarantee or credit | K31: 405140 | L31: 268136.7 | M31: 137003.3 | N31: 0 | O31: 0 | P31: 0 | Q31: 0 | R31: 0 | S31: 0 | T31: 0 | U31: 0 | V31: 0 | W31: 0 | X31: 0 | Y31: 0 | Z31: 0 | AA31: 0 | AD31: 591583.9 | AE31: 7894479.6 | AF31: 0.074936402 | AG31: 7302895.7
B32: Additive | C32: GRUPO CIBRA | D32: 1158000 | E32: 388925.8 | F32: 1158000 | G32: 0 | H32: Guarantee or credit | K32: 388925.8 | L32: 388925.8 | M32: 0 | N32: 0 | O32: 0 | P32: 0 | Q32: 0 | R32: 0 | S32: 0 | T32: 0 | U32: 0 | V32: 0 | W32: 0 | X32: 0 | Y32: 0 | Z32: 0 | AA32: 0 | AD32: 2142468.7 | AE32: 6784771.8 | AF32: 0.31577609 | AG32: 4642303.1
B33: Additive | C33: ADUFERTIL JUNDIAI | D33: 3000000 | E33: 382561.45 | F33: 3000000 | G33: 0 | H33: Guarantee or credit | K33: 382561.45 | L33: 0 | M33: 382561.45 | N33: 0 | O33: 0 | P33: 0 | Q33: 0 | R33: 0 | S33: 0 | T33: 0 | U33: 0 | V33: 0 | W33: 0 | X33: 0 | Y33: 0 | Z33: 0 | AA33: 0 | AD33: 1213578.6 | AE33: 7705567.7 | AF33: 0.15749373 | AG33: 6491989.1
B34: Additive | C34: FECOAGRO FEDERACAO DAS COOPERATIVAS | D34: 3000000 | E34: 381559.2 | F34: 3000000 | G34: 0 | H34: Guarantee or credit | K34: 381559.2 | L34: 381559.2 | M34: 0 | N34: 0 | O34: 0 | P34: 0 | Q34: 0 | R34: 0 | S34: 0 | T34: 0 | U34: 0 | V34: 0 | W34: 0 | X34: 0 | Y34: 0 | Z34: 0 | AA34: 0 | AD34: 3877846 | AE34: 20767517 | AF34: 0.18672651 | AG34: 16889671
B35: Fertilizer | C35: FAZENDA FERRADURA | D35: 0 | E35: 329327.91 | F35: 0 | G35: 329327.91 | H35: Credit without Insurance | I35: We are currently evaluating the client’s proposal to provide a tractor as collateral. | K35: 0 | L35: 0 | M35: 0 | N35: 0 | O35: 0 | P35: 0 | Q35: 0 | R35: 0 | S35: 329327.91 | T35: 0 | U35: 329327.91 | V35: 0 | W35: 0 | X35: 0 | Y35: 0 | Z35: 0 | AA35: 0 | AD35: 0 | AE35: 268305.82 | AF35: 0 | AG35: 268305.82
B36: Additive | C36: BENTONIT UNIAO - CAMPINA GRANDE | D36: 700000 | E36: 317275 | F36: 700000 | G36: 0 | H36: Guarantee or credit | K36: 317275 | L36: 317275 | M36: 0 | N36: 0 | O36: 0 | P36: 0 | Q36: 0 | R36: 0 | S36: 0 | T36: 0 | U36: 0 | V36: 0 | W36: 0 | X36: 0 | Y36: 0 | Z36: 0 | AA36: 0 | AD36: 1256610 | AE36: 1601244.8 | AF36: 0.78477069 | AG36: 344634.82
B37: Additive Intl. | C37: BUNGE PARAGUAY S.A | D37: 1650000 | E37: 307440.65 | F37: 1650000 | G37: 0 | H37: Guarantee or credit | K37: 307440.65 | L37: 307440.65 | M37: 0 | N37: 0 | O37: 0 | P37: 0 | Q37: 0 | R37: 0 | S37: 0 | T37: 0 | U37: 0 | V37: 0 | W37: 0 | X37: 0 | Y37: 0 | Z37: 0 | AA37: 0 | AD37: 1985542.7 | AE37: 3498901 | AF37: 0.5674761 | AG37: 1513358.3
B38: Fertilizer | C38: AGROREP. REPRESENTACOES AGRICOLAS | D38: 1000000 | E38: 299642.08 | F38: 1000000 | G38: 0 | H38: Guarantee or credit | K38: 299642.08 | L38: 0 | M38: 0 | N38: 0 | O38: 0 | P38: 299642.08 | Q38: 0 | R38: 0 | S38: 0 | T38: 0 | U38: 0 | V38: 0 | W38: 0 | X38: 0 | Y38: 0 | Z38: 0 | AA38: 0 | AD38: 299642.08 | AE38: 5393775 | AF38: 0.055553314 | AG38: 5094132.9
B39: Fertilizer | C39: ADUFÉRTIL - CAMPEVO | D39: 3000000 | E39: 291024.86 | F39: 3000000 | G39: 0 | H39: Guarantee or credit | K39: 291024.86 | L39: 72587.79 | M39: 218437.07 | N39: 0 | O39: 0 | P39: 0 | Q39: 0 | R39: 0 | S39: 0 | T39: 0 | U39: 0 | V39: 0 | W39: 0 | X39: 0 | Y39: 0 | Z39: 0 | AA39: 0 | AD39: 953390.54 | AE39: 4007620.8 | AF39: 0.2378944 | AG39: 3054230.3
B40: Additive Intl. | C40: TECNOMYL S.A. - PARAGUAY | D40: 990000 | E40: 265042.58 | F40: 990000 | G40: 0 | H40: Guarantee or credit | K40: 265042.58 | L40: 265042.58 | M40: 0 | N40: 0 | O40: 0 | P40: 0 | Q40: 0 | R40: 0 | S40: 0 | T40: 0 | U40: 0 | V40: 0 | W40: 0 | X40: 0 | Y40: 0 | Z40: 0 | AA40: 0 | AD40: 1411238.7 | AE40: 2201656.3 | AF40: 0.64098957 | AG40: 790417.59
B41: Additive Intl. | C41: ABOPAR - PARAGUAY | D41: 275000 | E41: 264834.84 | F41: 275000 | G41: 0 | H41: Guarantee or credit | K41: 131282.87 | L41: 0 | M41: 131282.87 | N41: 0 | O41: 0 | P41: 0 | Q41: 0 | R41: 0 | S41: 133551.97 | T41: 133551.97 | U41: 0 | V41: 0 | W41: 0 | X41: 0 | Y41: 0 | Z41: 0 | AA41: 0 | AD41: 264834.84 | AE41: 519392 | AF41: 0.50989395 | AG41: 254557.16
B42: Additive | C42: BIGFERTIL - CANDEIAS | D42: 300000 | E42: 242565.88 | F42: 0 | G42: 242565.88 | H42: Approved in credit committee | K42: 242565.88 | L42: 121282.94 | M42: 121282.94 | N42: 0 | O42: 0 | P42: 0 | Q42: 0 | R42: 0 | S42: 0 | T42: 0 | U42: 0 | V42: 0 | W42: 0 | X42: 0 | Y42: 0 | Z42: 0 | AA42: 0 | AD42: 560565.88 | AE42: 2267031.1 | AF42: 0.24726872 | AG42: 1706465.3
B43: Fertilizer / Litigation | C43: GRUPO TRIANGULO AGRO | D43: 0 | E43: 237309.12 | F43: 0 | G43: 237309.12 | H43: Litigation | K43: 0 | L43: 0 | M43: 0 | N43: 0 | O43: 0 | P43: 0 | Q43: 0 | R43: 0 | S43: 0 | T43: 0 | U43: 0 | V43: 0 | W43: 0 | X43: 0 | Y43: 0 | Z43: 0 | AA43: 237309.12 | AD43: 0 | AE43: 0 | AG43: 0
B44: Additive | C44: AURORA MINERAÇÃO LTDA | D44: 270000 | E44: 228927.4 | F44: 0 | G44: 228927.4 | H44: Approved in credit committee | I44: We have been monitoring the client in alignment with the commercial team. The client’s exposure must not exceed USD 200k. In addition, changes were made to the formulation of the product purchased by the client in order to improve the contribution margin. | K44: 152607 | L44: 76134.5 | M44: 76472.5 | N44: 0 | O44: 0 | P44: 0 | Q44: 0 | R44: 0 | S44: 76320.4 | T44: 76320.4 | U44: 0 | V44: 0 | W44: 0 | X44: 0 | Y44: 0 | Z44: 0 | AA44: 0 | AD44: 454644.6 | AE44: 1127250 | AF44: 0.40332189 | AG44: 672605.4
B45: Additive / Litigation | C45: TERRA FERTILIZANTES LTDA - ARAXÁ | D45: 0 | E45: 226233.6 | F45: 0 | G45: 226233.6 | H45: Litigation | K45: 0 | L45: 0 | M45: 0 | N45: 0 | O45: 0 | P45: 0 | Q45: 0 | R45: 0 | S45: 0 | T45: 0 | U45: 0 | V45: 0 | W45: 0 | X45: 0 | Y45: 0 | Z45: 0 | AA45: 226233.6 | AD45: 0 | AE45: 0 | AG45: 0
B46: Additive / Litigation | C46: ITERUM - RONDONOPOLIS | D46: 0 | E46: 213750 | F46: 0 | G46: 213750 | H46: Litigation | K46: 0 | L46: 0 | M46: 0 | N46: 0 | O46: 0 | P46: 0 | Q46: 0 | R46: 0 | S46: 0 | T46: 0 | U46: 0 | V46: 0 | W46: 0 | X46: 0 | Y46: 0 | Z46: 0 | AA46: 213750 | AD46: 0 | AE46: 0 | AG46: 0
B47: Additive | C47: GRUPO JOSAPAR | D47: 1000000 | E47: 185040 | F47: 1000000 | G47: 0 | H47: Guarantee or credit | K47: 185040 | L47: 0 | M47: 185040 | N47: 0 | O47: 0 | P47: 0 | Q47: 0 | R47: 0 | S47: 0 | T47: 0 | U47: 0 | V47: 0 | W47: 0 | X47: 0 | Y47: 0 | Z47: 0 | AA47: 0 | AD47: 890184 | AE47: 1252657.6 | AF47: 0.71063635 | AG47: 362473.57
B48: Additive | C48: GRUPO FERTIPAR FERTILIZANTES PARANA | D48: 1500000 | E48: 180359.2 | F48: 1500000 | G48: 0 | H48: Guarantee or credit | K48: 180359.2 | L48: 180359.2 | M48: 0 | N48: 0 | O48: 0 | P48: 0 | Q48: 0 | R48: 0 | S48: 0 | T48: 0 | U48: 0 | V48: 0 | W48: 0 | X48: 0 | Y48: 0 | Z48: 0 | AA48: 0 | AD48: 495161.6 | AE48: 2309012.9 | AF48: 0.21444731 | AG48: 1813851.3
B49: Additive Intl. | C49: GOTLAND EQUADOR (SOLINAG) | D49: 200000 | E49: 179474.58 | F49: 0 | G49: 179474.58 | H49: Approved in credit committee | I49: Coface is analyzing the credit request; a response is expected within 3 to 6 days. ( Previously, sales were handled by Solinag, but they changed the final entity; we are awaiting analysis from the insurance company). | K49: 133756.12 | L49: 0 | M49: 0 | N49: 133756.12 | O49: 0 | P49: 0 | Q49: 0 | R49: 0 | S49: 45718.46 | T49: 45718.46 | U49: 0 | V49: 0 | W49: 0 | X49: 0 | Y49: 0 | Z49: 0 | AA49: 0 | AD49: 179474.58 | AE49: 0 | AG49: 0
B50: Additive Intl. | C50: FERMAGRI S.A - EQUADOR | D50: 770000 | E50: 175275.24 | F50: 770000 | G50: 0 | H50: Guarantee or credit | K50: 0 | L50: 0 | M50: 0 | N50: 0 | O50: 0 | P50: 0 | Q50: 0 | R50: 0 | S50: 175275.24 | T50: 175275.24 | U50: 0 | V50: 0 | W50: 0 | X50: 0 | Y50: 0 | Z50: 0 | AA50: 0 | AD50: 400087.85 | AE50: 980403.09 | AF50: 0.40808506 | AG50: 580315.24
B51: Additive | C51: GRUPO ADUBOS ARAGUAIA | D51: 500000 | E51: 170959.4 | F51: 500000 | G51: 0 | H51: Guarantee or credit | K51: 170959.4 | L51: 65330 | M51: 105629.4 | N51: 0 | O51: 0 | P51: 0 | Q51: 0 | R51: 0 | S51: 0 | T51: 0 | U51: 0 | V51: 0 | W51: 0 | X51: 0 | Y51: 0 | Z51: 0 | AA51: 0 | AD51: 251939.4 | AE51: 7984108.2 | AF51: 0.031555109 | AG51: 7732168.8
B52: Additive Intl. | C52: FERTIMAX PARAGUAY | D52: 1375000 | E52: 166161.39 | F52: 1375000 | G52: 0 | H52: Guarantee or credit | K52: 166161.39 | L52: 166161.39 | M52: 0 | N52: 0 | O52: 0 | P52: 0 | Q52: 0 | R52: 0 | S52: 0 | T52: 0 | U52: 0 | V52: 0 | W52: 0 | X52: 0 | Y52: 0 | Z52: 0 | AA52: 0 | AD52: 645512.31 | AE52: 0 | AG52: 0
B53: Additive Intl. | C53: EVOAGRO NUTRICION S.A.S - COLOMBIA | D53: 200000 | E53: 164297.05 | F53: 0 | G53: 164297.05 | H53: Approved in credit committee | K53: 164297.05 | L53: 164297.05 | M53: 0 | N53: 0 | O53: 0 | P53: 0 | Q53: 0 | R53: 0 | S53: 0 | T53: 0 | U53: 0 | V53: 0 | W53: 0 | X53: 0 | Y53: 0 | Z53: 0 | AA53: 0 | AD53: 404098.14 | AE53: 894647.55 | AF53: 0.45168417 | AG53: 490549.41
B54: Additive | C54: GRANUPAR - RIO BRANCO DO SUL | D54: 300000 | E54: 163952.4 | F54: 300000 | G54: 0 | H54: Guarantee or credit | K54: 163952.4 | L54: 104834.4 | M54: 59118 | N54: 0 | O54: 0 | P54: 0 | Q54: 0 | R54: 0 | S54: 0 | T54: 0 | U54: 0 | V54: 0 | W54: 0 | X54: 0 | Y54: 0 | Z54: 0 | AA54: 0 | AD54: 178572.3 | AE54: 276750 | AF54: 0.6452477 | AG54: 98177.7
B55: Additive | C55: COONAGRO COOPERATIVA - PARANAGUA | D55: 2500000 | E55: 161830.2 | F55: 2500000 | G55: 0 | H55: Guarantee or credit | K55: 161830.2 | L55: 161830.2 | M55: 0 | N55: 0 | O55: 0 | P55: 0 | Q55: 0 | R55: 0 | S55: 0 | T55: 0 | U55: 0 | V55: 0 | W55: 0 | X55: 0 | Y55: 0 | Z55: 0 | AA55: 0 | AD55: 841245.29 | AE55: 3459604.5 | AF55: 0.24316227 | AG55: 2618359.2
B56: Additive | C56: BUNGE - SANTOS | D56: 800000 | E56: 158012.2 | F56: 800000 | G56: 0 | H56: Guarantee or credit | K56: 158012.2 | L56: 158012.2 | M56: 0 | N56: 0 | O56: 0 | P56: 0 | Q56: 0 | R56: 0 | S56: 0 | T56: 0 | U56: 0 | V56: 0 | W56: 0 | X56: 0 | Y56: 0 | Z56: 0 | AA56: 0 | AD56: 533278 | AE56: 0 | AG56: 0
B57: Additive | C57: GRUPO HINOVE | D57: 0 | E57: 144324 | F57: 0 | G57: 144324 | H57: Credit without Insurance | I57: We have requested the audited financial statements for 2025 to assess the possibility of granting a credit limit with Coface. | K57: 144324 | L57: 144324 | M57: 0 | N57: 0 | O57: 0 | P57: 0 | Q57: 0 | R57: 0 | S57: 0 | T57: 0 | U57: 0 | V57: 0 | W57: 0 | X57: 0 | Y57: 0 | Z57: 0 | AA57: 0 | AD57: 1134723.9 | AE57: 6318009.8 | AF57: 0.17960148 | AG57: 5183285.9
