Workbook
Name \0: #N/A
Name \1: #REF!
Name \2: #REF!
Name \3: #REF!
Name \4: #REF!
Name \5: #REF!
Name \a: #N/A
Name \b: #N/A
Name \c: #N/A
Name \d: #N/A
Name \DSUM: #REF!
Name \e: #N/A
Name \EXP: #REF!
Name \f: #N/A
Name \g: #N/A
Name \GL: #REF!
Name \h: #REF!
Name \I: #REF!
Name \k: #REF!
Name \l: #REF!
Name \m: #N/A
Name \MPR2: #REF!
Name \n: #REF!
Name \o: #REF!
Name \p: #N/A
Name \q: #REF!
Name \R: #REF!
Name \s: #N/A
Name \t: #REF!
Name \u: #N/A
Name \w: #REF!
Name \x: #REF!
Name \y: #REF!
Name \z: #REF!
Name _: #REF!
Name __?Business___Market_Spr: #REF!
Name __?End_Use_Analysis___Sectoral_Gro: #REF!
Name __?INDUSTRY_MATERIAL_BALA: #REF!
Name __?INDUSTRY_MATERIAL_BALANCE___PROJECTI: #REF!
Name __?PE___Q1_REV: #REF!
Name __?PE_1996: #REF!
Name __?PE_BUSINESS___PAST___FUT: #REF!
Name __?PE_REV: #REF!
Name __?PRICE_FORECAST___1995: #REF!
Name __?PROFITABILITY__Q3_1996__: #REF!
Name __?Q3___SUMM: #REF!
Name __?Quarterwise_Collection_P: #REF!
Name __?Quarterwise_Export_P: #REF!
Name __?QUARTERWISE_PERFORMA: #REF!
Name __?RE: #REF!
Name _______________________________DAT5: #REF!
Name _______________________________DAT7: #REF!
Name ______________________________DAT1: #REF!
Name ______________________________DAT10: #REF!
Name _____________________________DAT5: #REF!
Name _____________________________DAT7: #REF!
Name ____________________________DAT1: #REF!
Name ____________________________DAT10: #REF!
Name ____________________________DAT5: #REF!
Name ____________________________DAT7: #REF!

Sheet AR - slide BoD
B1: Amounts in 000
B2: Total receivables | I2: =I22/1000 -> 61380.633 | J2: =J22/1000 -> 99724.765
B4: Receivables as on 28th Feb 25 | D4: BU | E4: Overdue | F4: Not Due | G4: Not Due | I4: Provision | J4: Provision | L4: Provision risks - overdue receivables | P4: Remark
L5: Probable | M5: Possible | N5: Rare
B6: Central do Adubo | D6: Fertilizer | E6: =E26/1000 -> 7560.7278 | F6: =F26/1000 -> 0 | G6: =G26/1000 -> 7560.7278 | I6: =I26/1000 -> 0 | J6: =J26/1000 -> 0 | L6: =L26/1000 -> 0 | M6: =M26/1000 -> 7560.7278 | N6: =N26/1000 -> 0 | P6: Creditor´s assembly Judicial recovery plan has not yet been approved by Creditors. Adfert advisors believe that the AS-IS plan will not be approved and new financial conditions will need to be presented.
B7: SM Agro / Fazenda Baturi | D7: Fertilizer | E7: =E27/1000 -> 3088.5311 | F7: =F27/1000 -> 0 | G7: =G27/1000 -> 3088.5311 | I7: =I27/1000 -> 3088.5311 | J7: =J27/1000 -> 0 | L7: =L27/1000 -> 3088.5311 | M7: =M27/1000 -> 0 | N7: =N27/1000 -> 0 | P7: Judicial collection lawsuit is ongoing.
B8: CBM Fertilizantes | D8: Fertilizer | E8: =E28/1000 -> 3044.8509 | F8: =F28/1000 -> 0 | G8: =G28/1000 -> 3044.8509 | I8: =I28/1000 -> 3044.8509 | J8: =J28/1000 -> 0 | L8: =L28/1000 -> 3044.8509 | M8: =M28/1000 -> 0 | N8: =N28/1000 -> 0 | P8: Adfert has taken legal action and collection recovery lawsuit has been filed. Payment plan was not succesful.
B9: Mogiana Tecno Agro | D9: Fertilizer | E9: =E29/1000 -> 2492.8421 | F9: =F29/1000 -> 0 | G9: =G29/1000 -> 2492.8421 | I9: =I29/1000 -> 0 | J9: =J29/1000 -> 0 | L9: =L29/1000 -> 0 | M9: =M29/1000 -> 2492.8421 | N9: =N29/1000 -> 0 | P9: AFT received a renewalled payment proposal. Monthly payments along 2 yrs, with Machineary as guarantee and worth 25% of Open Exposure. Formal proposal still pending full disclosre on documents and valuation on Machinery.
B10: Casa das Sementes | D10: Fertilizer | E10: =E30/1000 -> 1863.2009 | F10: =F30/1000 -> 0 | G10: =G30/1000 -> 1863.2009 | I10: =I30/1000 -> 1863.2009 | J10: =J30/1000 -> 0 | L10: =L30/1000 -> 1863.2009 | M10: =M30/1000 -> 0 | N10: =N30/1000 -> 0 | P10: Legal process ongoing and 100% of the invoices we provisioned.
B11: Terra Fértil | D11: Fertilizer | E11: =E31/1000 -> 1702.8487 | F11: =F31/1000 -> 0 | G11: =G31/1000 -> 1702.8487 | I11: =I31/1000 -> 1702.8487 | J11: =J31/1000 -> 0 | L11: =L31/1000 -> 1702.8487 | M11: =M31/1000 -> 0 | N11: =N31/1000 -> 0 | P11: AFT has reached a payment agreement: 15% paid by Oct 25 and 3 yearly installments (Oct 26-27-28). No discount on principal and price inflation indexed
B12: Agro Beraldo | D12: Fertilizer | E12: =E32/1000 -> 876.01175 | F12: =F32/1000 -> 0 | G12: =G32/1000 -> 876.01175 | I12: =I32/1000 -> 0 | J12: =J32/1000 -> 0 | L12: =L32/1000 -> 0 | M12: =M32/1000 -> 876.01175 | N12: =N32/1000 -> 0 | P12: Judicial collection lawsuit is ongoing.
B14: Total Over Due in Litigation (TOP 7) | E14: =E39/1000 -> 22315.752 | F14: 0 | G14: 0 | I14: =I39/1000 -> 10427.32 | J14: =J39/1000 -> 0 | L14: =L39/1000 -> 10427.32 | M14: =M39/1000 -> 11888.433 | N14: 0
B15: Total Over Due with Possible Loss | E15: =E45/1000 -> 6.07632 | F15: 0 | G15: 0 | I15: =I45/1000 -> 6.07632 | J15: =J45/1000 -> 0 | L15: =L45/1000 -> 6.07632 | M15: =M45/1000 -> 0 | N15: 0
B16: Low Risk - Expect to Receive soon | E16: =E46/1000 -> 714.67217 | F16: =F46/1000 -> 0 | G16: =G46/1000 -> 714.67217 | I16: =I46/1000 -> 177.26661 | J16: =J46/1000 -> 0 | L16: =L46/1000 -> 0 | M16: =M46/1000 -> 0 | N16: =N46/1000 -> 714.67217 | P16: Provision as per corporate policy
B17: Total | E17: =E16+E15+E14 -> 23036.501 | F17: =F16+F15+F14 -> 0 | G17: =G16+G15+G14 -> 714.67217 | I17: =I16+I15+I14 -> 10610.662 | J17: =J16+J15+J14 -> 0 | L17: =L14+L15 -> 10433.396 | M17: =M16+M14 -> 11888.433 | N17: =N16+N14 -> 714.67217
B19: in BRl
B22: Total receivables | I22: =SUM(E132:F132) -> 61380633 | J22: =SUM(F132:G132) -> 99724765
B24: Receivables as on 31th Mar 26 | D24: BU | E24: Overdue | F24: Not Due | G24: Total | I24: Provision | J24: Write Off | L24: Collection Risk | P24: Remark
L25: Probable | M25: Possible | N25: Rare
B26: CENTRAL DO ADUBO COM E REPRESENTACAO LTD | D26: Fertilizers | E26: 7560727.8 | F26: 0 | G26: =SUM(E26:F26) -> 7560727.8 | I26: 0 | L26: =I26 -> 0 | M26: =E26-I26 -> 7560727.8 | P26: Current Status: Creditor´s Assembly has been approved. All suppliers to receive 35% (65% haircut) of total Outstanding in 10 years (2x per year installments) after a 18-months grace period, corrected by TR inflation index. Prefered suppliers, such as AFT, are eligible to full Overdue recovery based on future sales. 3% of all new CAD Sales to offset Old Overdues and 4% for sales with tenor (credit). This condition is non-binding and the client is to grant AFT a real estate guarantee of BRL 1MM. Upcoming Actions: Decision will now need to undergo approval and pass the entire appeal period. This step may still take a couple months to be completed.
B27: GRUPO LEANDRO SARTI | D27: Fertilizers | E27: 3088531.1 | F27: 0 | G27: =SUM(E27:F27) -> 3088531.1 | I27: 3088531.1 | L27: =I27 -> 3088531.1 | M27: =E27-I27 -> 0 | P27: Current Status: In Litigation via Collection enforcement claim. The judicial process is still in the initial phase, and we are in the period of notifying the parties involved. Upcoming Actions: We will await the procedures set forth by the court.
B28: AGRO BERALDO | D28: Fertilizers | E28: 3044850.9 | F28: 0 | G28: =SUM(E28:F28) -> 3044850.9 | I28: 3044850.9 | L28: =I28 -> 3044850.9 | M28: =E28-I28 -> 0 | P28: Current Status: The Litigation Collection enforcement claim process is ongoing. Upcoming Actions: AFT awaiting for further updates by the court.
B29: TERRA FERTIL - MACHADO | D29: Fertilizers | E29: 2492842.1 | F29: 0 | G29: =SUM(E29:F29) -> 2492842.1 | I29: 0 | L29: =I29 -> 0 | M29: =E29-I29 -> 2492842.1 | P29: Current Status: In Litigation via Collection enforcement claim. An agreement has been reached between parties, under the following terms: (i) Total settlement amount: R$ 3,192,985.64; (ii) Down payment: R$ 478,947.84, to be paid by October 30, 2025; (iii) Remaining balance: R$ 2,714,037.80, to be paid in three annual installments of R$ 904,679.26 each (2026 / 2027 / 2028), to be duly adjusted by inflation/court index. Upcoming Actions: AFT awaiting for the downpayment from the debtor to fulfill the agreement (Oct 20th 2025).
B30: MOGIANA TECNO AGRO | D30: Fertilizers | E30: 1863200.9 | F30: 0 | G30: =SUM(E30:F30) -> 1863200.9 | I30: 1863200.9 | L30: =I30 -> 1863200.9 | M30: =E30-I30 -> 0 | P30: Current Status: In Litigation via Collection enforcement claim. AFT received a proposal agreement, consisting of 12 initial installments of R$ 50,000.00, beginning March 28, which we had previously agreed after trying to negotiate a higher amount. From the 13th month, the proposal would be to rise monthly installments to R$ 100,000.00. This payment agreement would include both principal (R$ 2,502,567.34) and Interest (R$ 204,693.57). We have, via the enforcement collection claim received BRL 29k from the clients account via judicial decison. Upcoming Actions: we´ve not received feedback and are still assessing the viability of an agreed payment plan proposal. AFT is continuing to follow up on a payment schedule definition. AFT continues to follow on enforcement of any assets available from the client.
B31: CASA DAS SEMENTES | D31: Fertilizers | E31: 1702848.7 | F31: 0 | G31: =SUM(E31:F31) -> 1702848.7 | I31: 1702848.7 | L31: =I31 -> 1702848.7 | M31: =E31-I31 -> 0 | P31: Current Status: In Litigation via Collection enforcement claim. The process is ongoing, and we have successfully notified the debtor via judicial court. Upcoming Actions: AFT is seeking to seize assets from the debtor via the judicial claim which is ongoing.
B32: CBM FERTILIZANTES | D32: Fertilizers | E32: 876011.75 | F32: 0 | G32: =SUM(E32:F32) -> 876011.75 | I32: 0 | L32: =I32 -> 0 | M32: =E32-I32 -> 876011.75 | P32: Judicial settlement has been signed, under the following terms: (i) Total settlement amount: R$ 1,179,964.76, to be paid under the following conditions; (ii) Agreed payment in Two installments of R$ 100,000.00 each, due on April 24, 2025, and September 30th, 2025; Client has paid BRL 100k of the 1st installment and 2nd to be paid on the 30th of Sept. (iii) Three annual installments of R$ 326,654.92 , due on September 30, 2026, September 30, 2027, and September 30, 2028; Upcoming Actions: AFT awaiting for the payment plan agreed ofr September (another BRL 100k payment).
B33: GRUPO TRIANGULO AGRO | D33: Fertilizers | E33: 237309.12 | F33: 0 | G33: =SUM(E33:F33) -> 237309.12 | I33: 237309.12 | L33: =I33 -> 237309.12 | M33: =E33-I33 -> 0 | P33: Current Status: Client has issue a Judicial Recovery claim. The judicial process is still in the initial phase, and AFT has been notified. Upcoming Actions: AFT awaiting for the next steps to be set by court.
B34: TERRA FERTILIZANTES LTDA - ARAXÁ | D34: Additives | E34: 226233.6 | F34: 0 | G34: =SUM(E34:F34) -> 226233.6 | I34: 226233.6 | L34: =I34 -> 226233.6 | M34: =E34-I34 -> 0 | P34: May - 2024. In Litigation via collection enforcement. We don´t expect to have the collection. Client has been operation with a different Tax Id and we´re investigating how to link both companies to this claim.
B35: FAZENDA ARCOS SÃO JOÃO | D35: Fertilizers | E35: 988506.24 | F35: 0 | G35: =SUM(E35:F35) -> 988506.24 | I35: 29655.187 | L35: =I35 -> 29655.187 | M35: =E35-I35 -> 958851.05 | P35: Aug- 2025 Payment plan negotiation ongoing.
B36: ITERUM - RONDONOPOLIS | D36: Additives | E36: 213750 | F36: 0 | G36: =SUM(E36:F36) -> 213750 | I36: 213750 | L36: =I36 -> 213750 | M36: =E36-I36 -> 0 | P36: Dec- 2024 - Client facing fanancial difficulties and offered to return non-used final products. AFT is validating samples collected for quality assurance.
B37: GLINFERTIL - SAO FRANCISCO DO SUL | D37: Additives | E37: 20940 | F37: 0 | G37: =SUM(E37:F37) -> 20940 | I37: 20940 | L37: =I37 -> 20940 | M37: =E37-I37 -> 0 | P37: Nov 2023 Overdue. We don´t expect to receive collection from this client. The current status is that the client awaits for a court decision to accept the Judicial recovery process.
B39: Total Over Due in Litigation (TOP 12) | E39: =SUM(E26:E37) -> 22315752 | F39: =SUM(F26:F37) -> 0 | G39: =SUM(G26:G37) -> 22315752 | I39: =SUM(I26:I37) -> 10427320 | J39: =SUM(J26:J37) -> 0 | L39: =SUM(L26:L37) -> 10427320 | M39: =SUM(M26:M37) -> 11888433 | N39: =SUM(N26:N37) -> 0
B40: KLEYTON DUARTE SOARES | D40: Additives | E40: 100 | F40: 0 | G40: =SUM(E40:F40) -> 100 | I40: 100 | L40: =I40 -> 100 | M40: =E40-L40 -> 0 | P40: Jul - 2024 - Sale of old fixed assets to employees (chairs, desks etc) and it was not duly debited in employees payroll. Employee has left the company.
B41: MARIA JOSE DA SILVA | D41: Additives | E41: 50 | F41: 0 | G41: =SUM(E41:F41) -> 50 | I41: 50 | L41: =I41 -> 50 | M41: =E41-L41 -> 0 | P41: Aug - 2024 - Sale of old fixed assets to employees (chairs, desks etc) and it was not duly debited in employees payroll. Employee has left the company.
B42: GRUPO YARA | D42: Additives | E42: 5626.32 | F42: 0 | G42: =SUM(E42:F42) -> 5626.32 | I42: 5626.32 | L42: =I42 -> 5626.32 | M42: =E42-L42 -> 0 | P42: June 2024 - invoice underpayment due client claim of weight divergence
B43: SEU LIXO | D43: Additives | E43: 300 | F43: 0 | G43: =SUM(E43:F43) -> 300 | I43: 300 | L43: =I43 -> 300 | M43: =E43-L43 -> 0 | P43: Nov 2024 - sale of scrap materials.
B45: Total Over Due with Probable Loss | E45: =SUM(E40:E44) -> 6076.32 | F45: =SUM(F40:F44) -> 0 | G45: =SUM(G40:G44) -> 6076.32 | I45: =SUM(I40:I44) -> 6076.32 | J45: =SUM(J40:J44) -> 0 | L45: =SUM(L40:L44) -> 6076.32 | M45: =SUM(M40:M44) -> 0 | N45: =SUM(N40:N44) -> 0
B46: Low Risk - Expect to Receive soon | E46: =SUM(E47:E56) -> 714672.17 | F46: =F57+F58+F59 -> 0 | G46: =SUM(G47:G56) -> 714672.17 | I46: =SUM(I47:I56) -> 177266.61 | J46: =SUM(J47:J56) -> 0 | L46: =SUM(L47:L56) -> 0 | M46: =SUM(M47:M56) -> 0 | N46: =SUM(N47:N56) -> 714672.17 | P46: Provision as per corporate policy
B47: AGROBROKERS - COLÔMBIA | D47: Additive Intl. | E47: 449507.69 | F47: 0 | G47: 449507.69 | I47: 13485.231 | N47: =E47 -> 449507.69 | P47: Cargo cleared at Colombia port customs. AFT is in contact with the customer for validation of the payment plan.
B48: FERTIBAL - EQUADOR | D48: Additive Intl. | E48: 14548.35 | G48: =SUM(E48:F48) -> 14548.35 | I48: 0 | N48: =E48 -> 14548.35 | P48: Jan - 2026 The client paid 50% of the amount in January 2026; the remainder will be paid in March.
B49: GRUPO SUPERBAC | D49: Additives | E49: 10200.8 | G49: =SUM(E49:F49) -> 10200.8 | I49: 0 | N49: =E49 -> 10200.8
B50: ARSLOG SOLUCOES EM TRANSPORTE | D50: Additives | E50: 49440 | G50: =SUM(E50:F50) -> 49440 | I50: 0 | N50: =E50 -> 49440 | P50: March - 2026 -
B51: PATRICIA LARA SOUZA | D51: Additives | E51: 1750 | G51: =SUM(E51:F51) -> 1750 | I51: 0 | N51: =E51 -> 1750 | P51: March - 2026 - Sale of fixed assets to employees (chairs, desks etc)
B52: MÁRCIO RODRIGO DA SILVA | D52: Additives | E52: 303.01 | G52: =SUM(E52:F52) -> 303.01 | I52: 0 | N52: =E52 -> 303.01 | P52: Feb - 2026 - Sale of fixed assets to employees (chairs, desks etc)
B53: GRUPO MOSAIC FERTILIZANTES DO BRASIL | D53: Additives | E53: 16818.92 | G53: =SUM(E53:F53) -> 16818.92 | I53: 16756.646 | N53: =E53 -> 16818.92 | P53: Return goods invoices in dispute with client
B54: GRUPO FERTIPAR FERTILIZANTES DO NORDESTE | D54: Additives | E54: 3393 | G54: =SUM(E54:F54) -> 3393 | I54: 101.79 | N54: =E54 -> 3393 | P54: Nov - 2025 - Return goods invoices in dispute with client
B55: ORGANITEC - PARAGUAY | D55: Additive Intl. | E55: 527.28 | G55: =SUM(E55:F55) -> 527.28 | I55: 15.8184 | N55: =E55 -> 527.28 | P55: Sep 2025: Residual value from partial payment.
B56: Freight Debit Notes | D56: Additives | E56: 168183.12 | G56: =SUM(E56:F56) -> 168183.12 | I56: 146907.12 | N56: =E56 -> 168183.12 | P56: In validation - AFT and Logistics companies in agreement to pay only Freight overstay only from 2024 onwards. BRL 112k invoices are from before 2024 and unders discussion to be addressed in Sept month end closing.
B57: Not Due | D57: Additives
D58: Additive Intl.
D59: Fertilizers
B60: GRUPO MOSAIC FERTILIZANTES P K LTDA | D60: Additives | F60: 5607780.3 | G60: =E60+F60 -> 5607780.3 | O60: 475235
B61: GRUPO MOSAIC FERTILIZANTES DO BRASIL | D61: Additives | F61: 5479695.8 | G61: =E61+F61 -> 5479695.8 | O61: 3633158.1
B62: GRUPO YARA | D62: Additives | F62: 3073292.2 | G62: =E62+F62 -> 3073292.2
B63: FECOAGRO FEDERACAO DAS COOPERATIVAS | D63: Additives | F63: 973206.83 | G63: =E63+F63 -> 973206.83
B64: ADUFERTIL JUNDIAI | D64: Additives | F64: 831017.13 | G64: =E64+F64 -> 831017.13
B65: EUROCHEM SERRA DO SALITRE | D65: Additives | F65: 798155.7 | G65: =E65+F65 -> 798155.7 | O65: 3231664.8
B66: GRUPO UNIFERTIL | D66: Additives | F66: 797138.1 | G66: =E66+F66 -> 797138.1 | O66: 225884.2
B67: STRATOS/MOSAIC - ROSARIO DO CATETE | D67: Additives | F67: 782849.8 | G67: =E67+F67 -> 782849.8 | O67: 6158350.9
B68: GRUPO HINOVE | D68: Additives | F68: 631958.3 | G68: =E68+F68 -> 631958.3 | O68: 866804.7
B69: GRUPO FERTIPAR FERTILIZANTES MATO GROSSO | D69: Additives | F69: 611643.6 | G69: =E69+F69 -> 611643.6 | O69: 158126.4
B70: GRUPO JOSAPAR | D70: Additives | F70: 520104 | G70: =E70+F70 -> 520104 | O70: 1227102.4
B71: BENTONIT UNIAO - CAMPINA GRANDE | D71: Additives | F71: 500890 | G71: =E71+F71 -> 500890 | O71: 53489.3
B72: GRUPO CIBRA | D72: Additives | F72: 482208.1 | G72: =E72+F72 -> 482208.1
B73: GRUPO FERTILIZ TOCANTINS | D73: Additives | F73: 408048.2 | G73: =E73+F73 -> 408048.2 | O73: 528498.8
B74: COMIGO - RIO VERDE | D74: Additives | F74: 391080 | G74: =E74+F74 -> 391080 | O74: 417989.8
B75: FOSNOR - LUIS EDUARDO MAGALHAES | D75: Additives | F75: 350989.1 | G75: =E75+F75 -> 350989.1 | O75: 1424871.4
B76: ULTRAFERTIL | D76: Additives | F76: 327257.9 | G76: =E76+F76 -> 327257.9 | O76: 1708772
B77: NUTRIENTES IND DE FERTILIZANTES LTDA | D77: Additives | F77: 244770 | G77: =E77+F77 -> 244770 | O77: 324729
B78: AGROPECUARIA MARATA LTDA - MARUIM | D78: Additives | F78: 218160 | G78: =E78+F78 -> 218160 | O78: 1034572.5
B79: GRUPO HERINGER | D79: Additives | F79: 195071.61 | G79: =E79+F79 -> 195071.61 | O79: 444240
B80: GRUPO LOUIS DREYFUS | D80: Additives | F80: 167464 | G80: =E80+F80 -> 167464 | O80: 159679.8
B81: FERTGROW S.A | D81: Additives | F81: 161379 | G81: =E81+F81 -> 161379 | O81: 23451.75
B82: AURORA MINERAÇÃO LTDA | D82: Additives | F82: 150199.8 | G82: =E82+F82 -> 150199.8
B83: BIOSAFRA - MARUIM | D83: Additives | F83: 148538.92 | G83: =E83+F83 -> 148538.92
B84: COONAGRO COOPERATIVA - PARANAGUA | D84: Additives | F84: 137084.1 | G84: =E84+F84 -> 137084.1
B85: GRUPO FERTILIZE | D85: Additives | F85: 99785 | G85: =E85+F85 -> 99785
B86: GRUPO FERTIPAR FERTILIZANTES DO NORDESTE | D86: Additives | F86: 99532 | G86: =E86+F86 -> 99532
B87: GRANUPAR - RIO BRANCO DO SUL | D87: Additives | F87: 87139.5 | G87: =E87+F87 -> 87139.5
B88: INTERFERTIL - SAO FRANCISCO DO SUL | D88: Additives | F88: 83198.7 | G88: =E88+F88 -> 83198.7
B89: GRUPO ADUBOS ARAGUAIA | D89: Additives | F89: 80980 | G89: =E89+F89 -> 80980 | O89: 73440
B90: BUNGE - SANTOS | D90: Additives | F90: 74021.4 | G90: =E90+F90 -> 74021.4 | O90: 112012.5
B91: FASS AGRO FERTILIZANTES - SERTAOZINHO | D91: Additives | F91: 66740 | G91: =E91+F91 -> 66740 | O91: 42240
B92: MICROSOLO INDUSTRIAL - SETE LAGOAS | D92: Additives | F92: 66308 | G92: =E92+F92 -> 66308 | O92: 462630
B93: GRUPO AMAGGI | D93: Additives | F93: 60117.8 | G93: =E93+F93 -> 60117.8 | O93: 3860
B94: FERTIPLANTA - VARGEM GRANDE DO SUL | D94: Additives | F94: 52840 | G94: =E94+F94 -> 52840 | O94: 105854.98
B95: FERTINE - RECIFE | D95: Additives | F95: 42240 | G95: =E95+F95 -> 42240 | O95: 149397
B96: NUTRISOYA - CATALÃO | D96: Additives | F96: 28444.5 | G96: =E96+F96 -> 28444.5 | O96: 51900
B97: GRUPO SUPERBAC | D97: Additives | F97: 10200.8 | G97: =E97+F97 -> 10200.8 | O97: 71604.4
B98: GRUPO CARGILL | D98: Additives | F98: 2340 | G98: =E98+F98 -> 2340 | O98: 245
B99: MARCELO MARQUES COBRA - PESSOA FISICA | D99: Additives | F99: 1260 | G99: =E99+F99 -> 1260
B100: ANDRESSA CAROLINA SILVA RODRIGUES | D100: Additives | F100: 1166.67 | G100: =E100+F100 -> 1166.67
B101: ELYMAR JOSE DA SILVA FERREIRA | D101: Additives | F101: 662 | G101: =E101+F101 -> 662 | O101: 183510
B102: LUCAS DA CONCEIÇÃO CASSIMIRO | D102: Additives | F102: 292.08 | G102: =E102+F102 -> 292.08
B103: JOSÉ FRANCISCO PIRES DE SOUZA | D103: Additives | F103: 200 | G103: =E103+F103 -> 200
B104: AGROREP. REPRESENTACOES AGRICOLAS | D104: Fertilizers | F104: 2033573.6 | G104: =E104+F104 -> 2033573.6
B105: AGROVIVA | D105: Fertilizers | F105: 1200190.4 | G105: =E105+F105 -> 1200190.4
B106: GA AGRONEGOCIOS | D106: Fertilizers | F106: 815729 | G106: =E106+F106 -> 815729
B107: GRUPO TAKI AGRO | D107: Fertilizers | F107: 770854.72 | G107: =E107+F107 -> 770854.72
B108: CONNTACTA AGRONEGOCIOS | D108: Fertilizers | F108: 739540.06 | G108: =E108+F108 -> 739540.06
...

Sheet AR - slide
B1: in BRl
B2: Receivables as on 31st March 25 | D2: BU | E2: Overdue | F2: Not Due | G2: Provision | I2: Risk Provisions | M2: Remark
I3: Probable | J3: Possible | K3: Rare
B4: Central do Adubo | D4: Fertilizer | E4: 7560727.8 | G4: 3780363.9 | I4: 3780363.9 | J4: 3780363.9 | M4: Creditor´s assembly has been schedulled for May 2025. Central has reached out to Adfert for preferred suppliers status and conditions are in negotiation along April early May to be presented in the Assembly.
B5: SM Agro / Fazenda Baturi | D5: Fertilizer | E5: 3088531.1 | F5: 0 | G5: 3088531.1 | I5: 3088531.1 | M5: Judicial collection lawsuit is ongoing.
B6: CBM Fertilizantes | D6: Fertilizer | E6: 1076345 | F6: 0 | G6: 1076345 | I6: 1076345 | M6: Payment plan in negotiation: 10% payment in 2025 + 3 bullet yearly payments for the remaining debt.
B7: Mogiana Tecno Agro | D7: Fertilizer | E7: 1892360 | F7: 0 | G7: 0 | I7: 0 | J7: 1892360 | M7: AFT received a renewalled payment proposal. Monthly payments along 2 yrs, with Machineary as guarantee and worth 25% of Open Exposure. Formal proposal still pending full disclosre on documents and valuation on Machinery.
B8: Casa das Sementes | D8: Fertilizer | E8: 1716645.3 | G8: 1716645.3 | I8: 1716645.3 | M8: Legal process ongoing and 100% of the invoices we provisioned.
B9: Terra Fértil | D9: Fertilizer | E9: 2971789.9 | G9: 89153.697 | J9: 2971789.9 | M9: AFT has reached a payment agreement: 15% paid by Oct 25 and 3 yearly installments (Oct 26-27-28). No discount on principal and price inflation indexed
B10: Agro Beraldo | D10: Fertilizer | E10: 3044850.9 | F10: 0 | G10: 91345.528 | J10: 3044850.9 | M10: Judicial collection lawsuit is ongoing.
B12: Total Over Due in Litigation (TOP 7) | E12: =SUM(E4:E10) -> 21351250 | F12: =SUM(F4:F10) -> 0 | G12: =SUM(G4:G10) -> 9842384.5 | I12: =SUM(I4:I10) -> 9661885.3 | J12: =SUM(J4:J10) -> 11689365 | K12: =SUM(K4:K10) -> 0
B13: Planta Rica Agronegócios Ltda | D13: Fertilizers | E13: 110528 | F13: 0 | G13: 110528 | I13: 110528 | M13: old overdue
B14: Equilíbrio - Mogi Mirim | D14: Fertilizers | E14: 22222.25 | F14: 0 | G14: 22222.25 | I14: 22222.25 | M14: old overdue due to Quality issues
B15: Terra Fertilizantes Ltda | D15: Additives | E15: 226233.6 | F15: 0 | G15: 6787.008 | I15: 226233.6 | M15: Judicial recovery started
B16: Plant Bem - Paranagua | D16: Additives | E16: 140872.6 | F16: 0 | G16: 140872.6 | I16: 140872.6 | M16: old overdue
B17: Fertisanta Fertilizantes | D17: Additives | E17: 41379 | F17: 0 | G17: 41379 | I17: 41379 | M17: old overdue
B18: GLINFERTIL - SAO FRANCISCO DO SUL | D18: Additives | E18: 20940 | G18: 20940 | I18: 20940
B19: Superbac | D19: Additives | E19: 102008.2 | G19: 3060.25 | I19: 102008.2 | M19: No agreenment on payment. Judicial recovery process to begin
B20: Delcorp S.A | D20: Additives | E20: 84291.45 | F20: 0 | G20: 84291.45 | I20: 84291.45 | M20: old overdue
B21: Total Over Due with Possible Loss | E21: =SUM(E13:E20) -> 748475.1 | F21: =SUM(F13:F20) -> 0 | G21: =SUM(G13:G20) -> 430080.56 | I21: =SUM(I13:I20) -> 748475.1 | J21: =SUM(J13:J20) -> 0 | K21: =SUM(K13:K20) -> 0
B22: Low Risk - Expect to Receive soon | E22: =SUM(E23:E43) -> 7425775.8 | F22: =F44+F45+F46 -> 35847180 | G22: =SUM(G23:G43) -> 526944.99 | M22: Provision as per corporate policy
B23: Grupo Fert Tocantins | D23: Additives | E23: =1991399-67239 -> 1924160 | G23: 67314 | K23: =E23 -> 1924160 | M23: Overdue received in the beginning of March
B24: GRUPO MOSAIC FERTILIZANTES DO BRASIL | D24: Additives | E24: =765704.79-80843.12 -> 684861.67 | G24: 66674.04 | K24: =E24 -> 684861.67
B25: ITERUM - RONDONOPOLIS | D25: Additives | E25: 213750 | G25: 1475.1
B26: GRUPO AMAGGI | D26: Additives | E26: 56400
B27: GRUPO HERINGER | D27: Additives | E27: 397800
B28: GRUPO MOSAIC FERTILIZANTES P K LTDA | D28: Additives | E28: =123685.2-16500 -> 107185.2
B29: GRUPO CIBRA | D29: Additives | E29: =414240-1200 -> 413040
B30: GRUPO YARA | D30: Additives | E30: =63226.32-57600 -> 5626.32
B31: LYCSA Argentina | D31: Int'll | E31: 256935.85 | G31: 256935.85 | J31: 256935.85
B32: FERTYMEND - EQUADOR | D32: Int'll | E32: 69886.47
B33: AGRO MIL AGROS SAS - COLOMBIA | D33: Int'll | E33: 136847.67
B34: FERTIBAL - EQUADOR | D34: Int'll | E34: 82123.57
B35: ASOCIACION DE COOPERATIVAS ARGENTINAS CL | D35: Int'll | E35: 703377.76
B36: TECNOMYL S.A. - PARAGUAY | D36: Int'll | E36: 201503.56
B37: ABOPAR - PARAGUAY | D37: Int'll | E37: 150938.02
B38: C I ACEPALMA SA - COLOMBIA | D38: Int'll | E38: 317041.26 | K38: =E38 -> 317041.26
B39: Indorama Senegal | D39: Int'll | E39: 381748.49 | G39: 0 | K39: =E39 -> 381748.49
B40: GRUPO TRIANGULO AGRO | D40: Fertilizers | E40: 237309.12 | G40: 0 | K40: 117330.4
B41: GRUPO R3 | D41: Fertilizers | E41: 659074 | G41: 0 | J41: 659074
B42: GRUPO TAKI AGRO | D42: Fertilizers | E42: 110937.09
B43: Freight Debit Notes | D43: Additives | E43: 315229.74 | G43: 134546 | J43: 175719.14
B44: Not Due | D44: Additives | F44: =SUM(F47:F78) -> 18871537
D45: Int'll | F45: =SUM(F79:F86) -> 3652295.6
D46: Fertilizers | F46: =SUM(F87:F101) -> 13323347
B47: GRUPO MOSAIC FERTILIZANTES DO BRASIL | D47: Additives | F47: 4854100.6
B48: GRUPO CIBRA | D48: Additives | F48: 1106366.4
B49: GRUPO YARA | D49: Additives | F49: 1274871.2
B50: GRUPO ADUBOS ARAGUAIA | D50: Additives | F50: 731100.8
B51: GRUPO AMAGGI | D51: Additives | F51: 262079.7
B52: GRUPO UNIFERTIL | D52: Additives | F52: 1077992.3
B53: GRUPO HINOVE | D53: Additives | F53: 449952
B54: GRUPO FERTIPAR | D54: Additives | F54: 253506.3
B55: ADUFERTIL JUNDIAI | D55: Additives | F55: 31680
B56: FECOAGRO - SAO FRANCISCO DO SUL | D56: Additives | F56: 52255
B57: AURORA MINERAÇÃO LTDA | D57: Additives | F57: 338567.45
B58: COONAGRO COOPERATIVA - PARANAGUA | D58: Additives | F58: 137577.7
... B101: FAZENDA SANTA ELIZA | D101: Fertilizers | F101: 143620.48
B102: Total | E102: =SUM(E23:E43)+E12+E21+F22 -> 65372681 | F102: =SUM(F21:F22)+F12 -> 35847180 | G102: =+G22+G21+G12 -> 10799410

Sheet AR
J3: Credit Analysis | N3: Guarantee | S3: Remark
C4: CUSTOMER | D4: BU | E4: Total AR | F4: Overdue | G4: Not Due | H4: Provision | J4: Value | K4: Type | L4: Period days | N4: Value | O4: Type | P4: Due date | Q4: Tenor
C5: CENTRAL DO ADUBO | D5: Fertilizer | E5: =F5+G5 -> 7560727.8 | F5: ='Painel Fertilizers'!O4 -> 7560727.8 | G5: ='Painel Fertilizers'!P4 -> 0 | H5: ='Painel Fertilizers'!X4 -> 0 | J5: 0 | K5: 0 | L5: 0 | N5: 0 | O5: 0 | P5: 0 | Q5: 0 | S5: Judicial recovery plan presented but yet to be approved by Creditors Asembly: a meeting was held with AFT and a proposal of 65% discount on face value presented with a 18-month grace period and repayment over 10 years (in 20 installments). Adfert has not received further details on the restructuring plan as previously agreed in the end of Oct. Creditors assembly yet to be marked and a vote will occur for the Debtors recovery plan approval. Adfert advisors have a strong believe that the plan as AS-IS will not be approved and new financial conditions will be needed by the debtors
C6: SM AGRO / FAZ. BATURI | D6: Fertilizer | E6: =F6+G6 -> #REF! | F6: ='Painel Fertilizers'!#REF! -> #REF! | G6: ='Painel Fertilizers'!#REF! -> #REF! | H6: ='Painel Fertilizers'!#REF! -> #REF! | J6: 300000 | K6: Clean | L6: 0 | N6: 740000 | O6: CPR | P6: 45566 | Q6: 10 months | S6: Client has phisycally closed its reseller shop. Current overdue invoices were dully protested at the registry office and legal action has been filed. Awaiting court´s decision ordering the defendants to be served for payment
C7: CBM FERTILIZANTES | D7: Fertilizer | E7: =F7+G7 -> 0 | F7: ='Painel Fertilizers'!O20 -> 0 | G7: 0 | H7: 0 | N7: 4000000 | O7: CPR-G | P7: 45505 | Q7: 1 year | S7: Adfert has taken legal action and collection recovery lawsuit to be filed within November. An agreement for a payment plan was not successfull
C8: MOGIANA TECNO AGRO | D8: Fertilizer | E8: =F8+G8 -> 2026078 | F8: 1892360 | G8: ='Painel Fertilizers'!P20 -> 133718 | H8: ='Painel Fertilizers'!X5 -> 3088531.1 | J8: 1000000 | K8: Surety Bond | L8: 360 | N8: 1892360 | O8: Surety Bond | P8: 45597 | Q8: 1 year | S8: The judicial collection lawsuit plan was signed and filed. Court decision has approved the settement agreement establishing a 24 months payment plan (montlhy payment). 1st installment not paid and the judicial collection is ongoing
C9: CASA DAS SEMENTES | D9: Fertilizer | E9: =F9+G9 -> 3044850.9 | F9: ='Painel Fertilizers'!O6 -> 3044850.9 | G9: ='Painel Fertilizers'!P6 -> 0 | H9: ='Painel Fertilizers'!X6 -> 3044850.9 | J9: 2000000 | K9: Surety Bond | L9: 120 | S9: Provision 100%. Client’s overdues were protested at the registry office. Legal process ongoing
C10: TERRA FERTIL - MACHADO | D10: Fertilizer | E10: =F10+G10 -> 876011.75 | F10: ='Painel Fertilizers'!O10 -> 876011.75 | G10: ='Painel Fertilizers'!P10 -> 0 | H10: ='Painel Fertilizers'!X10 -> 0 | N10: 5517407.7 | O10: Surety Bond | P10: 45606 | Q10: 1 year | S10: Guarantee sent to the legal department so that they begin legal proceedings to collect the amount due
C11: AGROBERALDO | D11: Fertilizer | E11: =F11+G11 -> 0 | F11: ='Painel Fertilizers'!O22 -> 0 | G11: ='Painel Fertilizers'!P22 -> 0 | H11: ='Painel Fertilizers'!X22 -> 0 | N11: 3000000 | O11: Surety Bond | P11: 45627 | Q11: 1 year | S11: Guarantee sent to the legal department so that they begin legal proceedings to collect the amount due
C12: Total Over Due in Litigation | E12: =SUM(E5:E11) -> #REF! | F12: =SUM(F5:F11) -> #REF! | G12: =SUM(G5:G11) -> #REF! | H12: =SUM(H5:H11) -> #REF!
C13: PLANTA RICA AGRONEGÓCIOS LTDA | D13: Fertilizers | E13: =F13+G13 -> 110528 | F13: 110528 | G13: 0 | H13: 110528 | S13: old overdue
C14: FAZENDA BRAVINHOS | D14: Fertilizers | E14: =F14+G14 -> 34132.18 | F14: 34132.18 | G14: 0 | H14: 1023.9654 | S14: Judicial recovery started
C15: EQUILIBRIO - MOGI MIRIM | D15: Fertilizers | E15: =F15+G15 -> 22222.25 | F15: 22222.25 | G15: 0 | H15: 22222.25 | S15: old overdue
C16: TERRA FERTILIZANTES LTDA | D16: Aditives | E16: =F16+G16 -> 226233.6 | F16: 226233.6 | G16: 0 | H16: ='Painel Additive'!X6 -> 63226.32 | S16: Judicial recovery started
C17: PLANT BEM - PARANAGUÁ | D17: Aditives | E17: =F17+G17 -> 140872.6 | F17: 140872.6 | G17: 0 | H17: 140872.6 | S17: old overdue
C18: FERTISANTA FERTILIZANTES | D18: Aditives | E18: =F18+G18 -> 41379 | F18: 41379 | G18: 0 | H18: 41379 | S18: old overdue
C19: DELCORP S.A | D19: Aditives | E19: =F19+G19 -> 84291.45 | F19: 84291.45 | G19: 0 | H19: 84291.45 | S19: old overdue
C20: Total Over Due with Possible Loss | E20: =SUM(E13:E19) -> 659659.08 | F20: =SUM(F13:F19) -> 659659.08 | G20: =SUM(G13:G19) -> 0 | H20: =SUM(H13:H19) -> 463543.59
C21: Low Risk - Expect to Receive soon | E21: =F21+G21 -> #REF! | F21: =-(F20+F12)+'Painel Additive'!O1+'Painel Fertilizers'!O1+'Painel International'!O1 -> #REF! | G21: 0 | H21: ='Bad Debt Provision'!#REF! - (H12+H20) -> #REF! | S21: Provision as per corporate policy
C22: Not Due | E22: =F22+G22 -> 37270137 | F22: 0 | G22: ='Painel Additive'!P1+'Painel Fertilizers'!P1+'Painel International'!P1 -> 37270137 | H22: 0
C23: Total | E23: =SUM(E20:E22)+E12 -> #REF! | F23: =SUM(F20:F22)+F12 -> #REF! | G23: =SUM(G20:G22)+G12 -> #REF! | H23: =SUM(H20:H22)+H12 -> #REF!

Sheet freight debit notes
D1: =SUBTOTAL(9,D3:D999) -> 176583.12 | Q1: 46136
A2: CODPARC | B2: NOMEPARC | C2: CNPJ | D2: Valor | E2: NUFIN | F2: DTVENC | G2: DHBAIXA | H2: AD_BU | I2: NOME_BU | J2: NUMNOTA | K2: DTENTSAI | L2: CODNAT | M2: DESCRNAT | N2: CODTIPOPER | O2: OPERACAO | P2: Grupo | Q2: Dias vencidos
A3: 1787 | B3: MOSAIC - UBERABA (CIU1) | C3: 33.931.486/0014-55 | D3: 3600 | E3: 1246031589 | F3: 44784 | H3: 1 | I3: Adtives | J3: 1246031589 | K3: 44769 | L3: 3041000 | M3: FRETES DIVERSOS | N3: 46 | O3: FINANCEIRO GERAL | P3: GRUPO MOSAIC FERTILIZANTES P K LTDA | Q3: =$Q$1-F3 -> 1352
A4: 1787 | B4: MOSAIC - UBERABA (CIU1) | C4: 33.931.486/0014-55 | D4: 2700 | E4: 1246055596 | F4: 44889 | H4: 1 | I4: Adtives | J4: 1246055596 | K4: 44889 | L4: 3041000 | M4: FRETES DIVERSOS | N4: 46 | O4: FINANCEIRO GERAL | P4: GRUPO MOSAIC FERTILIZANTES P K LTDA | Q4: =$Q$1-F4 -> 1247
A5: 1788 | B5: MOSAIC - UBERABA (CIU2) | C5: 33.931.486/0021-84 | D5: 5400 | E5: 1246055599 | F5: 44889 | H5: 1 | I5: Adtives | J5: 1246055599 | K5: 44889 | L5: 3041000 | M5: FRETES DIVERSOS | N5: 46 | O5: FINANCEIRO GERAL | P5: GRUPO MOSAIC FERTILIZANTES P K LTDA | Q5: =$Q$1-F5 -> 1247
A6: 1788 | B6: MOSAIC - UBERABA (CIU2) | C6: 33.931.486/0021-84 | D6: 1200 | E6: 1246190701 | F6: 45674 | H6: 1 | I6: Adtives | J6: 1246190701 | K6: 45659 | L6: 3041000 | M6: FRETES DIVERSOS | N6: 46 | O6: FINANCEIRO GERAL | P6: GRUPO MOSAIC FERTILIZANTES P K LTDA | Q6: =$Q$1-F6 -> 462
A7: 1789 | B7: MOSAIC - ARAXA (CMA) | C7: 33.931.486/0019-60 | D7: 2700 | E7: 1246120461 | F7: 45294 | H7: 1 | I7: Adtives | J7: 191223 | K7: 45279 | L7: 3041000 | M7: FRETES DIVERSOS | N7: 46 | O7: FINANCEIRO GERAL | P7: GRUPO MOSAIC FERTILIZANTES P K LTDA | Q7: =$Q$1-F7 -> 842
A8: 1789 | B8: MOSAIC - ARAXA (CMA) | C8: 33.931.486/0019-60 | D8: 900 | E8: 1246146095 | F8: 45428 | H8: 1 | I8: Adtives | J8: 1246120461 | K8: 45428 | L8: 3041000 | M8: FRETES DIVERSOS | N8: 46 | O8: FINANCEIRO GERAL | P8: GRUPO MOSAIC FERTILIZANTES P K LTDA | Q8: =$Q$1-F8 -> 708
A9: 43 | B9: CIBRA - CAMACARI | C9: 00.117.842/0001-28 | D9: 3600 | E9: 1246271938 | F9: 46147 | H9: 1 | I9: Adtives | J9: 1246271938 | K9: 46132 | L9: 3042200 | M9: DIÁRIAS E ESTADIA DE MOTORISTAS | N9: 46 | O9: FINANCEIRO GERAL | P9: GRUPO CIBRA | Q9: =$Q$1-F9 -> -11
A10: 43 | B10: CIBRA - CAMACARI | C10: 00.117.842/0001-28 | D10: 3600 | E10: 1246271937 | F10: 46147 | H10: 1 | I10: Adtives | J10: 1246271937 | K10: 46132 | L10: 3042200 | M10: DIÁRIAS E ESTADIA DE MOTORISTAS | N10: 46 | O10: FINANCEIRO GERAL | P10: GRUPO CIBRA | Q10: =$Q$1-F10 -> -11
A11: 43 | B11: CIBRA - CAMACARI | C11: 00.117.842/0001-28 | D11: 3600 | E11: 1246271931 | F11: 46147 | H11: 1 | I11: Adtives | J11: 1246271931 | K11: 46132 | L11: 3042200 | M11: DIÁRIAS E ESTADIA DE MOTORISTAS | N11: 46 | O11: FINANCEIRO GERAL | P11: GRUPO CIBRA | Q11: =$Q$1-F11 -> -11
A12: 43 | B12: CIBRA - CAMACARI | C12: 00.117.842/0001-28 | D12: 6000 | E12: 1246271936 | F12: 46147 | H12: 1 | I12: Adtives | J12: 1246271936 | K12: 46132 | L12: 3042200 | M12: DIÁRIAS E ESTADIA DE MOTORISTAS | N12: 46 | O12: FINANCEIRO GERAL | P12: GRUPO CIBRA | Q12: =$Q$1-F12 -> -11
A13: 43 | B13: CIBRA - CAMACARI | C13: 00.117.842/0001-28 | D13: 2400 | E13: 1246271921 | F13: 46147 | H13: 1 | I13: Adtives | J13: 1246271921 | K13: 46132 | L13: 3042200 | M13: DIÁRIAS E ESTADIA DE MOTORISTAS | N13: 46 | O13: FINANCEIRO GERAL | P13: GRUPO CIBRA | Q13: =$Q$1-F13 -> -11
A14: 1159 | B14: YARA - RIO GRANDE | C14: 92.660.604/0013-16 | D14: 1800 | E14: 1246087936 | F14: 45112 | H14: 1 | I14: Adtives | J14: 1246087936 | K14: 45097 | L14: 3041000 | M14: FRETES DIVERSOS | N14: 46 | O14: FINANCEIRO GERAL | P14: GRUPO YARA | Q14: =$Q$1-F14 -> 1024
... A54: 7022 | B54: STRATOS/MOSAIC - ROSARIO DO CATETE | C54: 31.009.644/0001-74 | D54: 1800 | E54: 1246054442 | F54: 44897 | H54: 1 | I54: Adtives | J54: 1246054442 | K54: 44882 | L54: 3041000 | M54: FRETES DIVERSOS | N54: 46 | O54: FINANCEIRO GERAL | P54: STRATOS/MOSAIC - ROSARIO DO CATETE | Q54: =$Q$1-F54 -> 1239

Sheet Data total
D1: =SUBTOTAL(9,D3:D1088) -> 62360285 | E1: ='Data Additive'!D1+'Data Fertilizers'!D1+'Data International'!D1 -> 62183701 | F1: ='Data Additive'!D1+'Data Fertilizers'!D1+'Data International'!D1+'freight debit notes'!D1 -> 62360285 | G1: =D1-F1 -> 0 | R1: 46136
A2: CODPARC | B2: NOMEPARC | C2: CNPJ | D2: Valor | E2: NUFIN | F2: DTVENC | G2: DHBAIXA | H2: AD_BU | I2: NOME_BU | J2: NUMNOTA | K2: DTENTSAI | L2: CODNAT | M2: DESCRNAT | N2: CODTIPOPER | O2: OPERACAO | P2: Grupo | Q2: Dias vencidos
A3: 205 | B3: FERTIPAR - RONDONÓPOLIS | C3: 09.384.948/0002-43 | D3: 80589.6 | E3: 1246271690 | F3: 46157 | H3: 1 | I3: Adtives | J3: 11158 | K3: 46129 | L3: 1010100 | M3: VENDAS MERCADO INTERNO | N3: 161 | O3: VENDA PROD. INDUSTRIALIZADO - NFE | P3: GRUPO FERTIPAR FERTILIZANTES MATO GROSSO | Q3: =$R$1-F3 -> -21 | R3: =_xlfn.XLOOKUP(E3,'Data Additive'!E:E,'Data Additive'!E:E,0) -> 1246271690
A4: 205 | B4: FERTIPAR - RONDONÓPOLIS | C4: 09.384.948/0002-43 | D4: 75474 | E4: 1246269597 | F4: 46139 | H4: 1 | I4: Adtives | J4: 11003 | K4: 46111 | L4: 1010100 | M4: VENDAS MERCADO INTERNO | N4: 161 | O4: VENDA PROD. INDUSTRIALIZADO - NFE | P4: GRUPO FERTIPAR FERTILIZANTES MATO GROSSO | Q4: =$R$1-F4 -> -3 | R4: =_xlfn.XLOOKUP(E4,'Data Additive'!E:E,'Data Additive'!E:E,0) -> 1246269597
A5: 1257 | B5: MOSAIC - CAMPO GRANDE | C5: 61.156.501/0081-30 | D5: 1980.8 | E5: 1246032946 | F5: 44774 | H5: 1 | I5: Adtives | J5: 17935 | K5: 44714 | L5: 1010100 | M5: VENDAS MERCADO INTERNO | N5: 56 | O5: VENDA A ORDEM | P5: GRUPO MOSAIC FERTILIZANTES DO BRASIL | Q5: =$R$1-F5 -> 1362 | R5: =_xlfn.XLOOKUP(E5,'Data Additive'!E:E,'Data Additive'!E:E,0) -> 1246032946
A6: 1953 | B6: AMAGGI - COMODORO | C6: 77.294.254/0075-20 | D6: 58917.8 | E6: 1246267986 | F6: 46158 | H6: 1 | I6: Adtives | J6: 10907 | K6: 46098 | L6: 1010100 | M6: VENDAS MERCADO INTERNO | N6: 161 | O6: VENDA PROD. INDUSTRIALIZADO - NFE | P6: GRUPO AMAGGI | Q6: =$R$1-F6 -> -22 | R6: =_xlfn.XLOOKUP(E6,'Data Additive'!E:E,'Data Additive'!E:E,0) -> 1246267986
A7: 1787 | B7: MOSAIC - UBERABA (CIU1) | C7: 33.931.486/0014-55 | D7: 3600 | E7: 1246031589 | F7: 44784 | H7: 1 | I7: Adtives | J7: 1246031589 | K7: 44769 | L7: 3041000 | M7: FRETES DIVERSOS | N7: 46 | O7: FINANCEIRO GERAL | P7: GRUPO MOSAIC FERTILIZANTES P K LTDA | Q7: =$R$1-F7 -> 1352 | R7: =_xlfn.XLOOKUP(E7,'Data Additive'!E:E,'Data Additive'!E:E,0) -> 0
A8: 1787 | B8: MOSAIC - UBERABA (CIU1) | C8: 33.931.486/0014-55 | D8: 2700 | E8: 1246055596 | F8: 44889 | H8: 1 | I8: Adtives | J8: 1246055596 | K8: 44889 | L8: 3041000 | M8: FRETES DIVERSOS | N8: 46 | O8: FINANCEIRO GERAL | P8: GRUPO MOSAIC FERTILIZANTES P K LTDA | Q8: =$R$1-F8 -> 1247 | R8: =_xlfn.XLOOKUP(E8,'Data Additive'!E:E,'Data Additive'!E:E,0) -> 0
A9: 1787 | B9: MOSAIC - UBERABA (CIU1) | C9: 33.931.486/0014-55 | D9: 109862.4 | E9: 1246271310 | F9: 46216 | H9: 1 | I9: Adtives | J9: 11116 | K9: 46126 | L9: 1010100 | M9: VENDAS MERCADO INTERNO | N9: 161 | O9: VENDA PROD. INDUSTRIALIZADO - NFE | P9: GRUPO MOSAIC FERTILIZANTES P K LTDA | Q9: =$R$1-F9 -> -80 | R9: =_xlfn.XLOOKUP(E9,'Data Additive'!E:E,'Data Additive'!E:E,0) -> 1246271310
A10: 1787 | B10: MOSAIC - UBERABA (CIU1) | C10: 33.931.486/0014-55 | D10: 116928 | E10: 1246267948 | F10: 46187 | H10: 1 | I10: Adtives | J10: 10899 | K10: 46097 | L10: 1010100 | M10: VENDAS MERCADO INTERNO | N10: 161 | O10: VENDA PROD. INDUSTRIALIZADO - NFE | P10: GRUPO MOSAIC FERTILIZANTES P K LTDA | Q10: =$R$1-F10 -> -51 | R10: =_xlfn.XLOOKUP(E10,'Data Additive'!E:E,'Data Additive'!E:E,0) -> 1246267948
A11: 1787 | B11: MOSAIC - UBERABA (CIU1) | C11: 33.931.486/0014-55 | D11: 115891.2 | E11: 1246262540 | F11: 46149 | H11: 1 | I11: Adtives | J11: 10652 | K11: 46059 | L11: 1010100 | M11: VENDAS MERCADO INTERNO | N11: 161 | O11: VENDA PROD. INDUSTRIALIZADO - NFE | P11: GRUPO MOSAIC FERTILIZANTES P K LTDA | Q11: =$R$1-F11 -> -13 | R11: =_xlfn.XLOOKUP(E11,'Data Additive'!E:E,'Data Additive'!E:E,0) -> 1246262540
A12: 1787 | B12: MOSAIC - UBERABA (CIU1) | C12: 33.931.486/0014-55 | D12: 103795.2 | E12: 1246268633 | F12: 46194 | H12: 1 | I12: Adtives | J12: 10957 | K12: 46104 | L12: 1010100 | M12: VENDAS MERCADO INTERNO | N12: 161 | O12: VENDA PROD. INDUSTRIALIZADO - NFE | P12: GRUPO MOSAIC FERTILIZANTES P K LTDA | Q12: =$R$1-F12 -> -58 | R12: =_xlfn.XLOOKUP(E12,'Data Additive'!E:E,'Data Additive'!E:E,0) -> 1246268633
A13: 1787 | B13: MOSAIC - UBERABA (CIU1) | C13: 33.931.486/0014-55 | D13: 111360 | E13: 1246268748 | F13: 46195 | H13: 1 | I13: Adtives | J13: 10965 | K13: 46105 | L13: 1010100 | M13: VENDAS MERCADO INTERNO | N13: 161 | O13: VENDA PROD. INDUSTRIALIZADO - NFE | P13: GRUPO MOSAIC FERTILIZANTES P K LTDA | Q13: =$R$1-F13 -> -59 | R13: =_xlfn.XLOOKUP(E13,'Data Additive'!E:E,'Data Additive'!E:E,0) -> 1246268748
A14: 1787 | B14: MOSAIC - UBERABA (CIU1) | C14: 33.931.486/0014-55 | D14: 114662.4 | E14: 1246268585 | F14: 46161 | H14: 1 | I14: Adtives | J14: 10953 | K14: 46101 | L14: 1010100 | M14: VENDAS MERCADO INTERNO | N14: 161 | O14: VENDA PROD. INDUSTRIALIZADO - NFE | P14: GRUPO MOSAIC FERTILIZANTES P K LTDA | Q14: =$R$1-F14 -> -25 | R14: =_xlfn.XLOOKUP(E14,'Data Additive'!E:E,'Data Additive'!E:E,0) -> 1246268585
... A444: 6370 | B444: YTL S.A. - PARAGUAI | C444: 00.000.000/0000-00 | D444: 172806.77 | E444: 1246272162 | F444: 46164 | H444: 1 | I444: Adtives | J444: 11193 | K444: 46134 | L444: 1010200 | M444: VENDAS MERCADO EXTERNO | N444: 40 | O444: VENDA - NFE (EXPORTAÇÃO) | P444: YTL S.A. - PARAGUAI | Q444: =$R$1-F444 -> -28 | R444: =_xlfn.XLOOKUP(E444,'Data Additive'!E:E,'Data Additive'!E:E,0) -> 0
A445: 9708 | B445: CARGILL ARGENTINA | C445: ..- | D445: 687688.91 | E445: 1246271322 | F445: 46186 | I445: Não encontrado | J445: 11122 | K445: 46126 | L445: 1010200 | M445: VENDAS MERCADO EXTERNO | N445: 40 | O445: VENDA - NFE (EXPORTAÇÃO) | P445: CARGILL ARGENTINA | Q445: =$R$1-F445 -> -50 | R445: =_xlfn.XLOOKUP(E445,'Data Additive'!E:E,'Data Additive'!E:E,0) -> 0
A446: 8187 | B446: AGROREP. REPRESENTACOES AGRICOLAS | C446: 29.668.745/0001-05 | D446: 299642.08 | E446: 1246270723 | F446: 46357 | H446: 2 | I446: Fertilizers | J446: 11075 | K446: 46120 | L446: 1010100 | M446: VENDAS MERCADO INTERNO | N446: 161 | O446: VENDA PROD. INDUSTRIALIZADO - NFE | P446: AGROREP. REPRESENTACOES AGRICOLAS | Q446: =$R$1-F446 -> -221 | R446: =_xlfn.XLOOKUP(E446,'Data Additive'!E:E,'Data Additive'!E:E,0) -> 0
A447: 9295 | B447: TECNOMYL S.A. - PARAGUAY | C447: 99.999.999/9999-99 | D447: 130127.06 | E447: 1246270982 | F447: 46152 | H447: 1 | I447: Adtives | J447: 11090 | K447: 46122 | L447: 1010200 | M447: VENDAS MERCADO EXTERNO | N447: 40 | O447: VENDA - NFE (EXPORTAÇÃO) | P447: TECNOMYL S.A. - PARAGUAY | Q447: =$R$1-F447 -> -16 | R447: =_xlfn.XLOOKUP(E447,'Data Additive'!E:E,'Data Additive'!E:E,0) -> 0
A448: 9295 | B448: TECNOMYL S.A. - PARAGUAY | C448: 99.999.999/9999-99 | D448: 132185.95 | E448: 1246270621 | F448: 46150 | H448: 1 | I448: Adtives | J448: 11071 | K448: 46120 | L448: 1010200 | M448: VENDAS MERCADO EXTERNO | N448: 40 | O448: VENDA - NFE (EXPORTAÇÃO) | P448: TECNOMYL S.A. - PARAGUAY | Q448: =$R$1-F448 -> -14 | R448: =_xlfn.XLOOKUP(E448,'Data Additive'!E:E,'Data Additive'!E:E,0) -> 0
A449: 9298 | B449: TERRA FERTIL - MACHADO | C449: 15.003.086/0001-83 | D449: 111799 | E449: 1246070436 | F449: 45555 | H449: 2 | I449: Fertilizers | J449: 20815 | K449: 44991 | L449: 1010100 | M449: VENDAS MERCADO INTERNO | N449: 161 | O449: VENDA PROD. INDUSTRIALIZADO - NFE | P449: TERRA FERTIL - MACHADO | Q449: =$R$1-F449 -> 581 | R449: =_xlfn.XLOOKUP(E449,'Data Additive'!E:E,'Data Additive'!E:E,0) -> 0
A450: 9298 | B450: TERRA FERTIL - MACHADO | C450: 15.003.086/0001-83 | D450: 65548 | E450: 1246070905 | F450: 45555 | H450: 2 | I450: Fertilizers | J450: 20839 | K450: 44994 | L450: 1010100 | M450: VENDAS MERCADO INTERNO | N450: 161 | O450: VENDA PROD. INDUSTRIALIZADO - NFE | P450: TERRA FERTIL - MACHADO | Q450: =$R$1-F450 -> 581 | R450: =_xlfn.XLOOKUP(E450,'Data Additive'!E:E,'Data Additive'!E:E,0) -> 0
A451: 9298 | B451: TERRA FERTIL - MACHADO | C451: 15.003.086/0001-83 | D451: 112475 | E451: 1246068948 | F451: 45555 | H451: 2 | I451: Fertilizers | J451: 20763 | K451: 44984 | L451: 1010100 | M451: VENDAS MERCADO INTERNO | N451: 161 | O451: VENDA PROD. INDUSTRIALIZADO - NFE | P451: TERRA FERTIL - MACHADO | Q451: =$R$1-F451 -> 581 | R451: =_xlfn.XLOOKUP(E451,'Data Additive'!E:E,'Data Additive'!E:E,0) -> 0
A452: 9298 | B452: TERRA FERTIL - MACHADO | C452: 15.003.086/0001-83 | D452: 149824 | E452: 1246068778 | F452: 45555 | H452: 2 | I452: Fertilizers | J452: 20750 | K452: 44981 | L452: 1010100 | M452: VENDAS MERCADO INTERNO | N452: 161 | O452: VENDA PROD. INDUSTRIALIZADO - NFE | P452: TERRA FERTIL - MACHADO | Q452: =$R$1-F452 -> 581 | R452: =_xlfn.XLOOKUP(E452,'Data Additive'!E:E,'Data Additive'!E:E,0) -> 0
A453: 9298 | B453: TERRA FERTIL - MACHADO | C453: 15.003.086/0001-83 | D453: 131203 | E453: 1246070820 | F453: 45555 | H453: 2 | I453: Fertilizers | J453: 20836 | K453: 44993 | L453: 1010100 | M453: VENDAS MERCADO INTERNO | N453: 161 | O453: VENDA PROD. INDUSTRIALIZADO - NFE | P453: TERRA FERTIL - MACHADO | Q453: =$R$1-F453 -> 581 | R453: =_xlfn.XLOOKUP(E453,'Data Additive'!E:E,'Data Additive'!E:E,0) -> 0
A454: 9298 | B454: TERRA FERTIL - MACHADO | C454: 15.003.086/0001-83 | D454: 119356.2 | E454: 1246068614 | F454: 45555 | H454: 2 | I454: Fertilizers | J454: 20734 | K454: 44980 | L454: 1010100 | M454: VENDAS MERCADO INTERNO | N454: 161 | O454: VENDA PROD. INDUSTRIALIZADO - NFE | P454: TERRA FERTIL - MACHADO | Q454: =$R$1-F454 -> 581 | R454: =_xlfn.XLOOKUP(E454,'Data Additive'!E:E,'Data Additive'!E:E,0) -> 0
A455: 9298 | B455: TERRA FERTIL - MACHADO | C455: 15.003.086/0001-83 | D455: 122521 | E455: 1246068997 | F455: 45555 | H455: 2 | I455: Fertilizers | J455: 20767 | K455: 44984 | L455: 1010100 | M455: VENDAS MERCADO INTERNO | N455: 161 | O455: VENDA PROD. INDUSTRIALIZADO - NFE | P455: TERRA FERTIL - MACHADO | Q455: =$R$1-F455 -> 581 | R455: =_xlfn.XLOOKUP(E455,'Data Additive'!E:E,'Data Additive'!E:E,0) -> 0
A456: 9298 | B456: TERRA FERTIL - MACHADO | C456: 15.003.086/0001-83 | D456: 118731.49 | E456: 1246083500 | F456: 45555 | H456: 2 | I456: Fertilizers | J456: 21456 | K456: 45070 | L456: 1010100 | M456: VENDAS MERCADO INTERNO | N456: 161 | O456: VENDA PROD. INDUSTRIALIZADO - NFE | P456: TERRA FERTIL - MACHADO | Q456: =$R$1-F456 -> 581 | R456: =_xlfn.XLOOKUP(E456,'Data Additive'!E:E,'Data Additive'!E:E,0) -> 0
A457: 9298 | B457: TERRA FERTIL - MACHADO | C457: 15.003.086/0001-83 | D457: 52557.4 | E457: 1246083593 | F457: 45555 | H457: 2 | I457: Fertilizers | J457: 21460 | K457: 45070 | L457: 1010100 | M457: VENDAS MERCADO INTERNO | N457: 161 | O457: VENDA PROD. INDUSTRIALIZADO - NFE | P457: TERRA FERTIL - MACHADO | Q457: =$R$1-F457 -> 581 | R457: =_xlfn.XLOOKUP(E457,'Data Additive'!E:E,'Data Additive'!E:E,0) -> 0
... A479: 9355 | B479: NITROFERT SAS - COLOMBIA | C479: ..- | D479: 1191855.3 | E479: 1246265200 | F479: 46177 | H479: 1 | I479: Adtives | J479: 2778 | K479: 46078 | L479: 1010200 | M479: VENDAS MERCADO EXTERNO | N479: 40 | O479: VENDA - NFE (EXPORTAÇÃO) | P479: NITROFERT SAS - COLOMBIA | Q479: =$R$1-F479 -> -41 | R479: =_xlfn.XLOOKUP(E479,'Data Additive'!E:E,'Data Additive'!E:E,0) -> 0
A480: 9830 | B480: ELYMAR JOSE DA SILVA FERREIRA | C480: 053.438.381-54 | D480: 331 | E480: 1246266367 | F480: 46145 | I480: Não encontrado | J480: 10813 | K480: 46085 | L480: 4011600 | M480: APARELHOS DE INFORMÁTICA | N480: 244 | O480: VENDA DE IMOBILIZADO SEM ICMS | P480: ELYMAR JOSE DA SILVA FERREIRA | Q480: =$R$1-F480 -> -9 | R480: =_xlfn.XLOOKUP(E480,'Data Additive'!E:E,'Data Additive'!E:E,0) -> 1246266367
A481: 9830 | B481: ELYMAR JOSE DA SILVA FERREIRA | C481: 053.438.381-54 | D481: 331 | E481: 1246266368 | F481: 46175 | I481: Não encontrado | J481: 10813 | K481: 46085 | L481: 4011600 | M481: APARELHOS DE INFORMÁTICA | N481: 244 | O481: VENDA DE IMOBILIZADO SEM ICMS | P481: ELYMAR JOSE DA SILVA FERREIRA | Q481: =$R$1-F481 -> -39 | R481: =_xlfn.XLOOKUP(E481,'Data Additive'!E:E,'Data Additive'!E:E,0) -> 1246266368
A482: 11768 | B482: CERES PERU S.A | C482: ..- | D482: 86689.1 | E482: 1246264534 | F482: 46136 | H482: 1 | I482: Adtives | J482: 10744 | K482: 46076 | L482: 1010200 | M482: VENDAS MERCADO EXTERNO | N482: 40 | O482: VENDA - NFE (EXPORTAÇÃO) | P482: CERES PERU S.A | Q482: =$R$1-F482 -> 0 | R482: =_xlfn.XLOOKUP(E482,'Data Additive'!E:E,'Data Additive'!E:E,0) -> 0
A483: 11770 | B483: FERTIBAL - EQUADOR | C483: ..- | D483: 14548.35 | E483: 1246263524 | F483: 46039 | H483: 1 | I483: Adtives | J483: 9853 | K483: 45959 | L483: 1010200 | M483: VENDAS MERCADO EXTERNO | N483: 40 | O483: VENDA - NFE (EXPORTAÇÃO) | P483: FERTIBAL - EQUADOR | Q483: =$R$1-F483 -> 97 | R483: =_xlfn.XLOOKUP(E483,'Data Additive'!E:E,'Data Additive'!E:E,0) -> 0
A484: 10454 | B484: MOGIANA TECNO AGRO | C484: 33.030.913/0001-00 | D484: 144418.2 | E484: 1246051128 | F484: 45229 | H484: 2 | I484: Fertilizers | J484: 19700 | K484: 44860 | L484: 1010100 | M484: VENDAS MERCADO INTERNO | N484: 161 | O484: VENDA PROD. INDUSTRIALIZADO - NFE | P484: MOGIANA TECNO AGRO | Q484: =$R$1-F484 -> 907 | R484: =_xlfn.XLOOKUP(E484,'Data Additive'!E:E,'Data Additive'!E:E,0) -> 0
A485: 10454 | B485: MOGIANA TECNO AGRO | C485: 33.030.913/0001-00 | D485: 144418.2 | E485: 1246049220 | F485: 45229 | H485: 2 | I485: Fertilizers | J485: 19589 | K485: 44852 | L485: 1010100 | M485: VENDAS MERCADO INTERNO | N485: 161 | O485: VENDA PROD. INDUSTRIALIZADO - NFE | P485: MOGIANA TECNO AGRO | Q485: =$R$1-F485 -> 907 | R485: =_xlfn.XLOOKUP(E485,'Data Additive'!E:E,'Data Additive'!E:E,0) -> 0
A486: 10454 | B486: MOGIANA TECNO AGRO | C486: 33.030.913/0001-00 | D486: 149099.08 | E486: 1246058414 | F486: 45229 | H486: 2 | I486: Fertilizers | J486: 20191 | K486: 44909 | L486: 1010100 | M486: VENDAS MERCADO INTERNO | N486: 161 | O486: VENDA PROD. INDUSTRIALIZADO - NFE | P486: MOGIANA TECNO AGRO | Q486: =$R$1-F486 -> 907 | R486: =_xlfn.XLOOKUP(E486,'Data Additive'!E:E,'Data Additive'!E:E,0) -> 0
A487: 10454 | B487: MOGIANA TECNO AGRO | C487: 33.030.913/0001-00 | D487: 151022.08 | E487: 1246066481 | F487: 45229 | H487: 2 | I487: Fertilizers | J487: 20644 | K487: 44965 | L487: 1010100 | M487: VENDAS MERCADO INTERNO | N487: 161 | O487: VENDA PROD. INDUSTRIALIZADO - NFE | P487: MOGIANA TECNO AGRO | Q487: =$R$1-F487 -> 907 | R487: =_xlfn.XLOOKUP(E487,'Data Additive'!E:E,'Data Additive'!E:E,0) -> 0
A488: 10454 | B488: MOGIANA TECNO AGRO | C488: 33.030.913/0001-00 | D488: 248498.47 | E488: 1246058556 | F488: 45229 | H488: 2 | I488: Fertilizers | J488: 20197 | K488: 44909 | L488: 1010100 | M488: VENDAS MERCADO INTERNO | N488: 161 | O488: VENDA PROD. INDUSTRIALIZADO - NFE | P488: MOGIANA TECNO AGRO | Q488: =$R$1-F488 -> 907 | R488: =_xlfn.XLOOKUP(E488,'Data Additive'!E:E,'Data Additive'!E:E,0) -> 0
A489: 10454 | B489: MOGIANA TECNO AGRO | C489: 33.030.913/0001-00 | D489: 122816.13 | E489: 1246065495 | F489: 45229 | H489: 2 | I489: Fertilizers | J489: 20599 | K489: 44958 | L489: 1010100 | M489: VENDAS MERCADO INTERNO | N489: 161 | O489: VENDA PROD. INDUSTRIALIZADO - NFE | P489: MOGIANA TECNO AGRO | Q489: =$R$1-F489 -> 907 | R489: =_xlfn.XLOOKUP(E489,'Data Additive'!E:E,'Data Additive'!E:E,0) -> 0
A490: 10454 | B490: MOGIANA TECNO AGRO | C490: 33.030.913/0001-00 | D490: 97567.15 | E490: 1246059110 | F490: 45229 | H490: 2 | I490: Fertilizers | J490: 20229 | K490: 44911 | L490: 1010100 | M490: VENDAS MERCADO INTERNO | N490: 161 | O490: VENDA PROD. INDUSTRIALIZADO - NFE | P490: MOGIANA TECNO AGRO | Q490: =$R$1-F490 -> 907 | R490: =_xlfn.XLOOKUP(E490,'Data Additive'!E:E,'Data Additive'!E:E,0) -> 0
A491: 10454 | B491: MOGIANA TECNO AGRO | C491: 33.030.913/0001-00 | D491: 145199.8 | E491: 1246057926 | F491: 45229 | H491: 2 | I491: Fertilizers | J491: 20177 | K491: 44907 | L491: 1010100 | M491: VENDAS MERCADO INTERNO | N491: 161 | O491: VENDA PROD. INDUSTRIALIZADO - NFE | P491: MOGIANA TECNO AGRO | Q491: =$R$1-F491 -> 907 | R491: =_xlfn.XLOOKUP(E491,'Data Additive'!E:E,'Data Additive'!E:E,0) -> 0
A492: 10454 | B492: MOGIANA TECNO AGRO | C492: 33.030.913/0001-00 | D492: 85824.21 | E492: 1246058924 | F492: 45229 | H492: 2 | I492: Fertilizers | J492: 20209 | K492: 44910 | L492: 1010100 | M492: VENDAS MERCADO INTERNO | N492: 161 | O492: VENDA PROD. INDUSTRIALIZADO - NFE | P492: MOGIANA TECNO AGRO | Q492: =$R$1-F492 -> 907 | R492: =_xlfn.XLOOKUP(E492,'Data Additive'!E:E,'Data Additive'!E:E,0) -> 0
A493: 10454 | B493: MOGIANA TECNO AGRO | C493: 33.030.913/0001-00 | D493: 154779.14 | E493: 1246058289 | F493: 45229 | H493: 2 | I493: Fertilizers | J493: 20187 | K493: 44908 | L493: 1010100 | M493: VENDAS MERCADO INTERNO | N493: 161 | O493: VENDA PROD. INDUSTRIALIZADO - NFE | P493: MOGIANA TECNO AGRO | Q493: =$R$1-F493 -> 907 | R493: =_xlfn.XLOOKUP(E493,'Data Additive'!E:E,'Data Additive'!E:E,0) -> 0
... A524: 12629 | B524: EUROCHEM SERRA DO SALITRE | C524: 43.066.666/0001-55 | D524: 162031.2 | E524: 1246271940 | F524: 46162 | H524: 1 | I524: Adtives | J524: 11184 | K524: 46132 | L524: 1010100 | M524: VENDAS MERCADO INTERNO | N524: 161 | O524: VENDA PROD. INDUSTRIALIZADO - NFE | P524: EUROCHEM SERRA DO SALITRE | Q524: =$R$1-F524 -> -26 | R524: =_xlfn.XLOOKUP(E524,'Data Additive'!E:E,'Data Additive'!E:E,0) -> 1246271940
A525: 13330 | B525: ORGANITEC - PARAGUAY | C525: 800.909.976- | D525: 853.24 | E525: 1246272264 | F525: 46148 | I525: Não encontrado | J525: 11057 | K525: 46118 | L525: 1010200 | M525: VENDAS MERCADO EXTERNO | N525: 40 | O525: VENDA - NFE (EXPORTAÇÃO) | P525: ORGANITEC - PARAGUAY | Q525: =$R$1-F525 -> -12 | R525: =_xlfn.XLOOKUP(E525,'Data Additive'!E:E,'Data Additive'!E:E,0) -> 0
A526: 13330 | B526: ORGANITEC - PARAGUAY | C526: 800.909.976- | D526: 527.28 | E526: 1246238356 | F526: 45927 | I526: Não encontrado | J526: 9092 | K526: 45897 | L526: 1010200 | M526: VENDAS MERCADO EXTERNO | N526: 40 | O526: VENDA - NFE (EXPORTAÇÃO) | P526: ORGANITEC - PARAGUAY | Q526: =$R$1-F526 -> 209 | R526: =_xlfn.XLOOKUP(E526,'Data Additive'!E:E,'Data Additive'!E:E,0) -> 0
A527: 12295 | B527: CBM FERTILIZANTES | C527: 37.743.701/0001-20 | D527: 129728 | E527: 1246100036 | F527: 45547 | H527: 2 | I527: Fertilizers | J527: 843 | K527: 45162 | L527: 1010100 | M527: VENDAS MERCADO INTERNO | N527: 161 | O527: VENDA PROD. INDUSTRIALIZADO - NFE | P527: CBM FERTILIZANTES | Q527: =$R$1-F527 -> 589 | R527: =_xlfn.XLOOKUP(E527,'Data Additive'!E:E,'Data Additive'!E:E,0) -> 0
A528: 12295 | B528: CBM FERTILIZANTES | C528: 37.743.701/0001-20 | D528: 126208 | E528: 1246106003 | F528: 45559 | H528: 2 | I528: Fertilizers | J528: 1328 | K528: 45194 | L528: 1010100 | M528: VENDAS MERCADO INTERNO | N528: 161 | O528: VENDA PROD. INDUSTRIALIZADO - NFE | P528: CBM FERTILIZANTES | Q528: =$R$1-F528 -> 577 | R528: =_xlfn.XLOOKUP(E528,'Data Additive'!E:E,'Data Additive'!E:E,0) -> 0
A529: 12295 | B529: CBM FERTILIZANTES | C529: 37.743.701/0001-20 | D529: 19965 | E529: 1246100409 | F529: 45548 | H529: 2 | I529: Fertilizers | J529: 864 | K529: 45163 | L529: 1010100 | M529: VENDAS MERCADO INTERNO | N529: 161 | O529: VENDA PROD. INDUSTRIALIZADO - NFE | P529: CBM FERTILIZANTES | Q529: =$R$1-F529 -> 588 | R529: =_xlfn.XLOOKUP(E529,'Data Additive'!E:E,'Data Additive'!E:E,0) -> 0
A530: 12295 | B530: CBM FERTILIZANTES | C530: 37.743.701/0001-20 | D530: 102625 | E530: 1246100411 | F530: 45548 | H530: 2 | I530: Fertilizers | J530: 865 | K530: 45163 | L530: 1010100 | M530: VENDAS MERCADO INTERNO | N530: 161 | O530: VENDA PROD. INDUSTRIALIZADO - NFE | P530: CBM FERTILIZANTES | Q530: =$R$1-F530 -> 588 | R530: =_xlfn.XLOOKUP(E530,'Data Additive'!E:E,'Data Additive'!E:E,0) -> 0
A531: 12295 | B531: CBM FERTILIZANTES | C531: 37.743.701/0001-20 | D531: 23664 | E531: 1246100034 | F531: 45547 | H531: 2 | I531: Fertilizers | J531: 842 | K531: 45162 | L531: 1010100 | M531: VENDAS MERCADO INTERNO | N531: 161 | O531: VENDA PROD. INDUSTRIALIZADO - NFE | P531: CBM FERTILIZANTES | Q531: =$R$1-F531 -> 589 | R531: =_xlfn.XLOOKUP(E531,'Data Additive'!E:E,'Data Additive'!E:E,0) -> 0
A532: 12295 | B532: CBM FERTILIZANTES | C532: 37.743.701/0001-20 | D532: 126845 | E532: 1246102685 | F532: 45560 | H532: 2 | I532: Fertilizers | J532: 1060 | K532: 45175 | L532: 1010100 | M532: VENDAS MERCADO INTERNO | N532: 161 | O532: VENDA PROD. INDUSTRIALIZADO - NFE | P532: CBM FERTILIZANTES | Q532: =$R$1-F532 -> 576 | R532: =_xlfn.XLOOKUP(E532,'Data Additive'!E:E,'Data Additive'!E:E,0) -> 0
A533: 12295 | B533: CBM FERTILIZANTES | C533: 37.743.701/0001-20 | D533: 119790 | E533: 1246100311 | F533: 45548 | H533: 2 | I533: Fertilizers | J533: 851 | K533: 45163 | L533: 1010100 | M533: VENDAS MERCADO INTERNO | N533: 161 | O533: VENDA PROD. INDUSTRIALIZADO - NFE | P533: CBM FERTILIZANTES | Q533: =$R$1-F533 -> 588 | R533: =_xlfn.XLOOKUP(E533,'Data Additive'!E:E,'Data Additive'!E:E,0) -> 0
A534: 12295 | B534: CBM FERTILIZANTES | C534: 37.743.701/0001-20 | D534: 127776 | E534: 1246102654 | F534: 45560 | H534: 2 | I534: Fertilizers | J534: 1053 | K534: 45175 | L534: 1010100 | M534: VENDAS MERCADO INTERNO | N534: 161 | O534: VENDA PROD. INDUSTRIALIZADO - NFE | P534: CBM FERTILIZANTES | Q534: =$R$1-F534 -> 576 | R534: =_xlfn.XLOOKUP(E534,'Data Additive'!E:E,'Data Additive'!E:E,0) -> 0
A535: 12295 | B535: CBM FERTILIZANTES | C535: 37.743.701/0001-20 | D535: 99410.75 | E535: 1246240412 | F535: 45546 | H535: 2 | I535: Fertilizers | J535: 176 | K535: 45161 | L535: 1010100 | M535: VENDAS MERCADO INTERNO | N535: 161 | O535: VENDA PROD. INDUSTRIALIZADO - NFE | P535: CBM FERTILIZANTES | Q535: =$R$1-F535 -> 590 | R535: =_xlfn.XLOOKUP(E535,'Data Additive'!E:E,'Data Additive'!E:E,0) -> 0
A536: 13069 | B536: JOSÉ FRANCISCO PIRES DE SOUZA | C536: 012.300.516-78 | D536: 100 | E536: 1246258365 | F536: 46118 | I536: Não encontrado | J536: 10425 | K536: 46028 | L536: 4010300 | M536: MÓVEIS E UTENSÍLIOS | N536: 244 | O536: VENDA DE IMOBILIZADO SEM ICMS | P536: JOSÉ FRANCISCO PIRES DE SOUZA | Q536: =$R$1-F536 -> 18 | R536: =_xlfn.XLOOKUP(E536,'Data Additive'!E:E,'Data Additive'!E:E,0) -> 1246258365
A537: 13193 | B537: AGRO BERALDO | C537: 28.321.521/0001-60 | D537: 39218.19 | E537: 1246129675 | F537: 45598 | H537: 2 | I537: Fertilizers | J537: 2817 | K537: 45338 | L537: 1010100 | M537: VENDAS MERCADO INTERNO | N537: 161 | O537: VENDA PROD. INDUSTRIALIZADO - NFE | P537: AGRO BERALDO | Q537: =$R$1-F537 -> 538 | R537: =_xlfn.XLOOKUP(E537,'Data Additive'!E:E,'Data Additive'!E:E,0) -> 0
A538: 13193 | B538: AGRO BERALDO | C538: 28.321.521/0001-60 | D538: 96537.1 | E538: 1246128994 | F538: 45599 | H538: 2 | I538: Fertilizers | J538: 2765 | K538: 45331 | L538: 1010100 | M538: VENDAS MERCADO INTERNO | N538: 161 | O538: VENDA PROD. INDUSTRIALIZADO - NFE | P538: AGRO BERALDO | Q538: =$R$1-F538 -> 537 | R538: =_xlfn.XLOOKUP(E538,'Data Additive'!E:E,'Data Additive'!E:E,0) -> 0
A539: 13193 | B539: AGRO BERALDO | C539: 28.321.521/0001-60 | D539: 14369.79 | E539: 1246129687 | F539: 45594 | H539: 2 | I539: Fertilizers | J539: 2824 | K539: 45338 | L539: 1010100 | M539: VENDAS MERCADO INTERNO | N539: 161 | O539: VENDA PROD. INDUSTRIALIZADO - NFE | P539: AGRO BERALDO | Q539: =$R$1-F539 -> 542 | R539: =_xlfn.XLOOKUP(E539,'Data Additive'!E:E,'Data Additive'!E:E,0) -> 0
A540: 13193 | B540: AGRO BERALDO | C540: 28.321.521/0001-60 | D540: 102482.69 | E540: 1246129689 | F540: 45594 | H540: 2 | I540: Fertilizers | J540: 2825 | K540: 45338 | L540: 1010100 | M540: VENDAS MERCADO INTERNO | N540: 161 | O540: VENDA PROD. INDUSTRIALIZADO - NFE | P540: AGRO BERALDO | Q540: =$R$1-F540 -> 542 | R540: =_xlfn.XLOOKUP(E540,'Data Additive'!E:E,'Data Additive'!E:E,0) -> 0
A541: 13193 | B541: AGRO BERALDO | C541: 28.321.521/0001-60 | D541: 96537.1 | E541: 1246128030 | F541: 45604 | H541: 2 | I541: Fertilizers | J541: 2691 | K541: 45324 | L541: 1010100 | M541: VENDAS MERCADO INTERNO | N541: 161 | O541: VENDA PROD. INDUSTRIALIZADO - NFE | P541: AGRO BERALDO | Q541: =$R$1-F541 -> 532 | R541: =_xlfn.XLOOKUP(E541,'Data Additive'!E:E,'Data Additive'!E:E,0) -> 0
A542: 13193 | B542: AGRO BERALDO | C542: 28.321.521/0001-60 | D542: 96537.1 | E542: 1246129535 | F542: 45597 | H542: 2 | I542: Fertilizers | J542: 2797 | K542: 45337 | L542: 1010100 | M542: VENDAS MERCADO INTERNO | N542: 161 | O542: VENDA PROD. INDUSTRIALIZADO - NFE | P542: AGRO BERALDO | Q542: =$R$1-F542 -> 539 | R542: =_xlfn.XLOOKUP(E542,'Data Additive'!E:E,'Data Additive'!E:E,0) -> 0
A543: 13193 | B543: AGRO BERALDO | C543: 28.321.521/0001-60 | D543: 12586.97 | E543: 1246129615 | F543: 45594 | H543: 2 | I543: Fertilizers | J543: 2804 | K543: 45338 | L543: 1010100 | M543: VENDAS MERCADO INTERNO | N543: 161 | O543: VENDA PROD. INDUSTRIALIZADO - NFE | P543: AGRO BERALDO | Q543: =$R$1-F543 -> 542 | R543: =_xlfn.XLOOKUP(E543,'Data Additive'!E:E,'Data Additive'!E:E,0) -> 0
A544: 13193 | B544: AGRO BERALDO | C544: 28.321.521/0001-60 | D544: 96537.1 | E544: 1246129423 | F544: 45597 | H544: 2 | I544: Fertilizers | J544: 2793 | K544: 45337 | L544: 1010100 | M544: VENDAS MERCADO INTERNO | N544: 161 | O544: VENDA PROD. INDUSTRIALIZADO - NFE | P544: AGRO BERALDO | Q544: =$R$1-F544 -> 539 | R544: =_xlfn.XLOOKUP(E544,'Data Additive'!E:E,'Data Additive'!E:E,0) -> 0
A545: 13193 | B545: AGRO BERALDO | C545: 28.321.521/0001-60 | D545: 96537.1 | E545: 1246129513 | F545: 45605 | H545: 2 | I545: Fertilizers | J545: 2795 | K545: 45337 | L545: 1010100 | M545: VENDAS MERCADO INTERNO | N545: 161 | O545: VENDA PROD. INDUSTRIALIZADO - NFE | P545: AGRO BERALDO | Q545: =$R$1-F545 -> 531 | R545: =_xlfn.XLOOKUP(E545,'Data Additive'!E:E,'Data Additive'!E:E,0) -> 0
A546: 13193 | B546: AGRO BERALDO | C546: 28.321.521/0001-60 | D546: 100695.77 | E546: 1246129348 | F546: 45592 | H546: 2 | I546: Fertilizers | J546: 2788 | K546: 45336 | L546: 1010100 | M546: VENDAS MERCADO INTERNO | N546: 161 | O546: VENDA PROD. INDUSTRIALIZADO - NFE | P546: AGRO BERALDO | Q546: =$R$1-F546 -> 544 | R546: =_xlfn.XLOOKUP(E546,'Data Additive'!E:E,'Data Additive'!E:E,0) -> 0
A547: 13193 | B547: AGRO BERALDO | C547: 28.321.521/0001-60 | D547: 96537.12 | E547: 1246129613 | F547: 45598 | H547: 2 | I547: Fertilizers | J547: 2803 | K547: 45338 | L547: 1010100 | M547: VENDAS MERCADO INTERNO | N547: 161 | O547: VENDA PROD. INDUSTRIALIZADO - NFE | P547: AGRO BERALDO | Q547: =$R$1-F547 -> 538 | R547: =_xlfn.XLOOKUP(E547,'Data Additive'!E:E,'Data Additive'!E:E,0) -> 0
A548: 13193 | B548: AGRO BERALDO | C548: 28.321.521/0001-60 | D548: 114958.39 | E548: 1246126152 | F548: 45594 | H548: 2 | I548: Fertilizers | J548: 2568 | K548: 45314 | L548: 1010100 | M548: VENDAS MERCADO INTERNO | N548: 161 | O548: VENDA PROD. INDUSTRIALIZADO - NFE | P548: AGRO BERALDO | Q548: =$R$1-F548 -> 542 | R548: =_xlfn.XLOOKUP(E548,'Data Additive'!E:E,'Data Additive'!E:E,0) -> 0
... A569: 13193 | B569: AGRO BERALDO | C569: 28.321.521/0001-60 | D569: 96077.53 | E569: 1246135475 | F569: 45600 | H569: 2 | I569: Fertilizers | J569: 3143 | K569: 45373 | L569: 1010100 | M569: VENDAS MERCADO INTERNO | N569: 161 | O569: VENDA PROD. INDUSTRIALIZADO - NFE | P569: AGRO BERALDO | Q569: =$R$1-F569 -> 536 | R569: =_xlfn.XLOOKUP(E569,'Data Additive'!E:E,'Data Additive'!E:E,0) -> 0
A570: 14094 | B570: KLEYTON DUARTE SOARES | C570: 014.415.101-41 | D570: 100 | E570: 1246154530 | F570: 45474 | I570: Não encontrado | J570: 4088 | K570: 45474 | L570: 4010300 | M570: MÓVEIS E UTENSÍLIOS | N570: 244 | O570: VENDA DE IMOBILIZADO SEM ICMS | P570: KLEYTON DUARTE SOARES | Q570: =$R$1-F570 -> 662 | R570: =_xlfn.XLOOKUP(E570,'Data Additive'!E:E,'Data Additive'!E:E,0) -> 1246154530
A571: 13873 | B571: MARIA JOSE DA SILVA | C571: 844.462.855-72 | D571: 50 | E571: 1246166396 | F571: 45525 | I571: Não encontrado | J571: 4854 | K571: 45525 | L571: 4010300 | M571: MÓVEIS E UTENSÍLIOS | N571: 244 | O571: VENDA DE IMOBILIZADO SEM ICMS | P571: MARIA JOSE DA SILVA | Q571: =$R$1-F571 -> 611 | R571: =_xlfn.XLOOKUP(E571,'Data Additive'!E:E,'Data Additive'!E:E,0) -> 1246166396
A572: 14179 | B572: LUCAS DA CONCEIÇÃO CASSIMIRO | C572: 077.998.984-88 | D572: 292.08 | E572: 1246270339 | F572: 46143 | I572: Não encontrado | J572: 10469 | K572: 46035 | L572: 4011600 | M572: APARELHOS DE INFORMÁTICA | N572: 244 | O572: VENDA DE IMOBILIZADO SEM ICMS | P572: LUCAS DA CONCEIÇÃO CASSIMIRO | Q572: =$R$1-F572 -> -7 | R572: =_xlfn.XLOOKUP(E572,'Data Additive'!E:E,'Data Additive'!E:E,0) -> 1246270339
A573: 14106 | B573: SEU LIXO | C573: 50.454.037/0001-68 | D573: 300 | E573: 1246182736 | F573: 45625 | I573: Não encontrado | J573: 6092 | K573: 45610 | L573: 1020400 | M573: VENDA DE SUCATAS | N573: 136 | O573: VENDA DE SUCATAS | P573: SEU LIXO | Q573: =$R$1-F573 -> 511 | R573: =_xlfn.XLOOKUP(E573,'Data Additive'!E:E,'Data Additive'!E:E,0) -> 1246182736
A574: 13567 | B574: TAKI AGRO - POUSO ALEGRE | C574: 07.212.714/0001-02 | D574: 108547.57 | E574: 1246235061 | F574: 46143 | H574: 2 | I574: Fertilizers | J574: 9184 | K574: 45904 | L574: 1010100 | M574: VENDAS MERCADO INTERNO | N574: 56 | O574: VENDA A ORDEM | P574: TAKI AGRO - POUSO ALEGRE | Q574: =$R$1-F574 -> -7 | R574: =_xlfn.XLOOKUP(E574,'Data Additive'!E:E,'Data Additive'!E:E,0) -> 0
A575: 13567 | B575: TAKI AGRO - POUSO ALEGRE | C575: 07.212.714/0001-02 | D575: 114260.6 | E575: 1246235060 | F575: 46143 | H575: 2 | I575: Fertilizers | J575: 9183 | K575: 45904 | L575: 1010100 | M575: VENDAS MERCADO INTERNO | N575: 56 | O575: VENDA A ORDEM | P575: TAKI AGRO - POUSO ALEGRE | Q575: =$R$1-F575 -> -7 | R575: =_xlfn.XLOOKUP(E575,'Data Additive'!E:E,'Data Additive'!E:E,0) -> 0
A576: 14948 | B576: TAKI AGRO - SOCORRO | C576: 39.750.862/0001-77 | D576: 184217.94 | E576: 1246221983 | F576: 46138 | H576: 2 | I576: Fertilizers | J576: 8306 | K576: 45838 | L576: 1010100 | M576: VENDAS MERCADO INTERNO | N576: 56 | O576: VENDA A ORDEM | P576: TAKI AGRO - SOCORRO | Q576: =$R$1-F576 -> -2 | R576: =_xlfn.XLOOKUP(E576,'Data Additive'!E:E,'Data Additive'!E:E,0) -> 0
A577: 14948 | B577: TAKI AGRO - SOCORRO | C577: 39.750.862/0001-77 | D577: 235730.06 | E577: 1246228090 | F577: 46134 | H577: 2 | I577: Fertilizers | J577: 8683 | K577: 45868 | L577: 1010100 | M577: VENDAS MERCADO INTERNO | N577: 56 | O577: VENDA A ORDEM | P577: TAKI AGRO - SOCORRO | Q577: =$R$1-F577 -> 2 | R577: =_xlfn.XLOOKUP(E577,'Data Additive'!E:E,'Data Additive'!E:E,0) -> 0
A578: 15508 | B578: SOMAX - PARAGUAI | C578: 800.553.179- | D578: 137716.91 | E578: 1246270312 | F578: 46148 | H578: 1 | I578: Adtives | J578: 11050 | K578: 46118 | L578: 1010200 | M578: VENDAS MERCADO EXTERNO | N578: 40 | O578: VENDA - NFE (EXPORTAÇÃO) | P578: SOMAX - PARAGUAI | Q578: =$R$1-F578 -> -12 | R578: =_xlfn.XLOOKUP(E578,'Data Additive'!E:E,'Data Additive'!E:E,0) -> 0
A579: 14552 | B579: GA AGRONEGOCIOS | C579: 27.273.296/0001-70 | D579: 91336 | E579: 1246259067 | F579: 46141 | H579: 2 | I579: Fertilizers | J579: 8636 | K579: 45866 | L579: 1010100 | M579: VENDAS MERCADO INTERNO | N579: 7 | O579: VENDA PARA ENTREGA FUTURA | P579: GA AGRONEGOCIOS | Q579: =$R$1-F579 -> -5 | R579: =_xlfn.XLOOKUP(E579,'Data Additive'!E:E,'Data Additive'!E:E,0) -> 0
A580: 14552 | B580: GA AGRONEGOCIOS | C580: 27.273.296/0001-70 | D580: 85316 | E580: 1246259061 | F580: 46142 | H580: 2 | I580: Fertilizers | J580: 8620 | K580: 45863 | L580: 1010100 | M580: VENDAS MERCADO INTERNO | N580: 7 | O580: VENDA PARA ENTREGA FUTURA | P580: GA AGRONEGOCIOS | Q580: =$R$1-F580 -> -6 | R580: =_xlfn.XLOOKUP(E580,'Data Additive'!E:E,'Data Additive'!E:E,0) -> 0
A581: 14552 | B581: GA AGRONEGOCIOS | C581: 27.273.296/0001-70 | D581: 156088 | E581: 1246226199 | F581: 46142 | H581: 2 | I581: Fertilizers | J581: 8567 | K581: 45859 | L581: 1010100 | M581: VENDAS MERCADO INTERNO | N581: 161 | O581: VENDA PROD. INDUSTRIALIZADO - NFE | P581: GA AGRONEGOCIOS | Q581: =$R$1-F581 -> -6 | R581: =_xlfn.XLOOKUP(E581,'Data Additive'!E:E,'Data Additive'!E:E,0) -> 0
A582: 14552 | B582: GA AGRONEGOCIOS | C582: 27.273.296/0001-70 | D582: 194626 | E582: 1246240017 | F582: 46143 | H582: 2 | I582: Fertilizers | J582: 9500 | K582: 45929 | L582: 1010100 | M582: VENDAS MERCADO INTERNO | N582: 161 | O582: VENDA PROD. INDUSTRIALIZADO - NFE | P582: GA AGRONEGOCIOS | Q582: =$R$1-F582 -> -7 | R582: =_xlfn.XLOOKUP(E582,'Data Additive'!E:E,'Data Additive'!E:E,0) -> 0
A583: 14552 | B583: GA AGRONEGOCIOS | C583: 27.273.296/0001-70 | D583: 176320 | E583: 1246225706 | F583: 46145 | H583: 2 | I583: Fertilizers | J583: 8525 | K583: 45855 | L583: 1010100 | M583: VENDAS MERCADO INTERNO | N583: 161 | O583: VENDA PROD. INDUSTRIALIZADO - NFE | P583: GA AGRONEGOCIOS | Q583: =$R$1-F583 -> -9 | R583: =_xlfn.XLOOKUP(E583,'Data Additive'!E:E,'Data Additive'!E:E,0) -> 0
A584: 14552 | B584: GA AGRONEGOCIOS | C584: 27.273.296/0001-70 | D584: 112043 | E584: 1246240517 | F584: 46144 | H584: 2 | I584: Fertilizers | J584: 9522 | K584: 45930 | L584: 1010100 | M584: VENDAS MERCADO INTERNO | N584: 161 | O584: VENDA PROD. INDUSTRIALIZADO - NFE | P584: GA AGRONEGOCIOS | Q584: =$R$1-F584 -> -8 | R584: =_xlfn.XLOOKUP(E584,'Data Additive'!E:E,'Data Additive'!E:E,0) -> 0
A585: 14848 | B585: FAZENDA FERRADURA | C585: 405.350.450-34 | D585: 207773.57 | E585: 1246230064 | F585: 46162 | H585: 2 | I585: Fertilizers | J585: 8811 | K585: 45877 | L585: 1010100 | M585: VENDAS MERCADO INTERNO | N585: 161 | O585: VENDA PROD. INDUSTRIALIZADO - NFE | P585: FAZENDA FERRADURA | Q585: =$R$1-F585 -> -26 | R585: =_xlfn.XLOOKUP(E585,'Data Additive'!E:E,'Data Additive'!E:E,0) -> 0
... A595: 14396 | B595: FAZENDA ARCOS SÃO JOÃO | C595: 006.140.866-20 | D595: 8000 | E595: 1246205781 | F595: 45920 | H595: 2 | I595: Fertilizers | J595: 7423 | K595: 45744 | L595: 1010100 | M595: VENDAS MERCADO INTERNO | N595: 161 | O595: VENDA PROD. INDUSTRIALIZADO - NFE | P595: FAZENDA ARCOS SÃO JOÃO | Q595: =$R$1-F595 -> 216 | R595: =_xlfn.XLOOKUP(E595,'Data Additive'!E:E,'Data Additive'!E:E,0) -> 0
A596: 15543 | B596: GOTLAND EQUADOR (SOLINAG) | C596: 19.512.950/9001- | D596: 45718.46 | E596: 1246264533 | F596: 46181 | I596: Não encontrado | J596: 10745 | K596: 46076 | L596: 1010200 | M596: VENDAS MERCADO EXTERNO | N596: 40 | O596: VENDA - NFE (EXPORTAÇÃO) | P596: GOTLAND EQUADOR (SOLINAG) | Q596: =$R$1-F596 -> -45 | R596: =_xlfn.XLOOKUP(E596,'Data Additive'!E:E,'Data Additive'!E:E,0) -> 0
A597: 16032 | B597: ANDRESSA CAROLINA SILVA RODRIGUES | C597: 096.141.946-69 | D597: 583.34 | E597: 1246264383 | F597: 46163 | I597: Não encontrado | J597: 10732 | K597: 46073 | L597: 4011600 | M597: APARELHOS DE INFORMÁTICA | N597: 244 | O597: VENDA DE IMOBILIZADO SEM ICMS | P597: ANDRESSA CAROLINA SILVA RODRIGUES | Q597: =$R$1-F597 -> -27 | R597: =_xlfn.XLOOKUP(E597,'Data Additive'!E:E,'Data Additive'!E:E,0) -> 1246264383
A598: 16107 | B598: CONNTACTA AGRONEGOCIOS | C598: 54.764.341/0001-62 | D598: 58579.74 | E598: 1246235692 | F598: 46142 | H598: 2 | I598: Fertilizers | J598: 9246 | K598: 45908 | L598: 1010100 | M598: VENDAS MERCADO INTERNO | N598: 161 | O598: VENDA PROD. INDUSTRIALIZADO - NFE | P598: CONNTACTA AGRONEGOCIOS | Q598: =$R$1-F598 -> -6 | R598: =_xlfn.XLOOKUP(E598,'Data Additive'!E:E,'Data Additive'!E:E,0) -> 0
A599: 16107 | B599: CONNTACTA AGRONEGOCIOS | C599: 54.764.341/0001-62 | D599: 120293.94 | E599: 1246234013 | F599: 46164 | H599: 2 | I599: Fertilizers | J599: 9130 | K599: 45898 | L599: 1010100 | M599: VENDAS MERCADO INTERNO | N599: 161 | O599: VENDA PROD. INDUSTRIALIZADO - NFE | P599: CONNTACTA AGRONEGOCIOS | Q599: =$R$1-F599 -> -28 | R599: =_xlfn.XLOOKUP(E599,'Data Additive'!E:E,'Data Additive'!E:E,0) -> 0
A600: 16107 | B600: CONNTACTA AGRONEGOCIOS | C600: 54.764.341/0001-62 | D600: 52795.36 | E600: 1246231811 | F600: 46144 | H600: 2 | I600: Fertilizers | J600: 8929 | K600: 45888 | L600: 1010100 | M600: VENDAS MERCADO INTERNO | N600: 161 | O600: VENDA PROD. INDUSTRIALIZADO - NFE | P600: CONNTACTA AGRONEGOCIOS | Q600: =$R$1-F600 -> -8 | R600: =_xlfn.XLOOKUP(E600,'Data Additive'!E:E,'Data Additive'!E:E,0) -> 0
A601: 16107 | B601: CONNTACTA AGRONEGOCIOS | C601: 54.764.341/0001-62 | D601: 92391.88 | E601: 1246232362 | F601: 46144 | H601: 2 | I601: Fertilizers | J601: 8978 | K601: 45890 | L601: 1010100 | M601: VENDAS MERCADO INTERNO | N601: 161 | O601: VENDA PROD. INDUSTRIALIZADO - NFE | P601: CONNTACTA AGRONEGOCIOS | Q601: =$R$1-F601 -> -8 | R601: =_xlfn.XLOOKUP(E601,'Data Additive'!E:E,'Data Additive'!E:E,0) -> 0
A602: 16107 | B602: CONNTACTA AGRONEGOCIOS | C602: 54.764.341/0001-62 | D602: 94968.9 | E602: 1246234271 | F602: 46167 | H602: 2 | I602: Fertilizers | J602: 9136 | K602: 45901 | L602: 1010100 | M602: VENDAS MERCADO INTERNO | N602: 161 | O602: VENDA PROD. INDUSTRIALIZADO - NFE | P602: CONNTACTA AGRONEGOCIOS | Q602: =$R$1-F602 -> -31 | R602: =_xlfn.XLOOKUP(E602,'Data Additive'!E:E,'Data Additive'!E:E,0) -> 0
A603: 16107 | B603: CONNTACTA AGRONEGOCIOS | C603: 54.764.341/0001-62 | D603: 101300.16 | E603: 1246233237 | F603: 46162 | H603: 2 | I603: Fertilizers | J603: 9072 | K603: 45896 | L603: 1010100 | M603: VENDAS MERCADO INTERNO | N603: 161 | O603: VENDA PROD. INDUSTRIALIZADO - NFE | P603: CONNTACTA AGRONEGOCIOS | Q603: =$R$1-F603 -> -26 | R603: =_xlfn.XLOOKUP(E603,'Data Additive'!E:E,'Data Additive'!E:E,0) -> 0
A604: 16107 | B604: CONNTACTA AGRONEGOCIOS | C604: 54.764.341/0001-62 | D604: 27054.5 | E604: 1246235694 | F604: 46142 | H604: 2 | I604: Fertilizers | J604: 9247 | K604: 45908 | L604: 1010100 | M604: VENDAS MERCADO INTERNO | N604: 161 | O604: VENDA PROD. INDUSTRIALIZADO - NFE | P604: CONNTACTA AGRONEGOCIOS | Q604: =$R$1-F604 -> -6 | R604: =_xlfn.XLOOKUP(E604,'Data Additive'!E:E,'Data Additive'!E:E,0) -> 0
A605: 16107 | B605: CONNTACTA AGRONEGOCIOS | C605: 54.764.341/0001-62 | D605: 94968.9 | E605: 1246233894 | F605: 46164 | H605: 2 | I605: Fertilizers | J605: 9120 | K605: 45898 | L605: 1010100 | M605: VENDAS MERCADO INTERNO | N605: 161 | O605: VENDA PROD. INDUSTRIALIZADO - NFE | P605: CONNTACTA AGRONEGOCIOS | Q605: =$R$1-F605 -> -28 | R605: =_xlfn.XLOOKUP(E605,'Data Additive'!E:E,'Data Additive'!E:E,0) -> 0
A606: 16107 | B606: CONNTACTA AGRONEGOCIOS | C606: 54.764.341/0001-62 | D606: 94968.9 | E606: 1246238555 | F606: 46164 | H606: 2 | I606: Fertilizers | J606: 9444 | K606: 45924 | L606: 1010100 | M606: VENDAS MERCADO INTERNO | N606: 161 | O606: VENDA PROD. INDUSTRIALIZADO - NFE | P606: CONNTACTA AGRONEGOCIOS | Q606: =$R$1-F606 -> -28 | R606: =_xlfn.XLOOKUP(E606,'Data Additive'!E:E,'Data Additive'!E:E,0) -> 0
A607: 16107 | B607: CONNTACTA AGRONEGOCIOS | C607: 54.764.341/0001-62 | D607: 2217.78 | E607: 1246235696 | F607: 46142 | H607: 2 | I607: Fertilizers | J607: 9248 | K607: 45908 | L607: 1010100 | M607: VENDAS MERCADO INTERNO | N607: 161 | O607: VENDA PROD. INDUSTRIALIZADO - NFE | P607: CONNTACTA AGRONEGOCIOS | Q607: =$R$1-F607 -> -6 | R607: =_xlfn.XLOOKUP(E607,'Data Additive'!E:E,'Data Additive'!E:E,0) -> 0
A608: 16189 | B608: ARSLOG SOLUCOES EM TRANSPORTE | C608: 05.765.626/0001-02 | D608: 49440 | E608: 1246261824 | F608: 46087 | I608: Não encontrado | J608: 1246261824 | K608: 46055 | L608: 7240000 | M608: PERDA DE MERCADORIA COM SINISTRO | N608: 46 | O608: FINANCEIRO GERAL | P608: ARSLOG SOLUCOES EM TRANSPORTE | Q608: =$R$1-F608 -> 49 | R608: =_xlfn.XLOOKUP(E608,'Data Additive'!E:E,'Data Additive'!E:E,0) -> 1246261824
A609: 15917 | B609: MINAS FARM | C609: 41.841.473/0001-07 | D609: 8176 | E609: 1246241844 | F609: 46143 | H609: 2 | I609: Fertilizers | J609: 9608 | K609: 45937 | L609: 1010100 | M609: VENDAS MERCADO INTERNO | N609: 161 | O609: VENDA PROD. INDUSTRIALIZADO - NFE | P609: MINAS FARM | Q609: =$R$1-F609 -> -7 | R609: =_xlfn.XLOOKUP(E609,'Data Additive'!E:E,'Data Additive'!E:E,0) -> 0
...

Sheet Data Additive
D1: =SUBTOTAL(9,$D$3:$D$868) -> 27655916 | R1: 46136
A2: CODPARC | B2: NOMEPARC | C2: CNPJ | D2: Valor | E2: NUFIN | F2: DTVENC | G2: DHBAIXA | H2: AD_BU | I2: NOME_BU | J2: NUMNOTA | K2: DTENTSAI | L2: CODNAT | M2: DESCRNAT | N2: CODTIPOPER | O2: OPERACAO | P2: Grupo | Q2: Dias vencidos
A3: 205 | B3: FERTIPAR - RONDONÓPOLIS | C3: 09.384.948/0002-43 | D3: 80589.6 | E3: 1246271690 | F3: 46157 | H3: 1 | I3: Adtives | J3: 11158 | K3: 46129 | L3: 1010100 | M3: VENDAS MERCADO INTERNO | N3: 161 | O3: VENDA PROD. INDUSTRIALIZADO - NFE | P3: GRUPO FERTIPAR FERTILIZANTES MATO GROSSO | Q3: =$R$1-F3 -> -21 | R3: =_xlfn.XLOOKUP(P3,'Painel Additive'!$B:$B,'Painel Additive'!$B:$B,0) -> GRUPO FERTIPAR FERTILIZANTES MATO GROSSO | S3: =F3-K3 -> 28
A4: 205 | B4: FERTIPAR - RONDONÓPOLIS | C4: 09.384.948/0002-43 | D4: 75474 | E4: 1246269597 | F4: 46139 | H4: 1 | I4: Adtives | J4: 11003 | K4: 46111 | L4: 1010100 | M4: VENDAS MERCADO INTERNO | N4: 161 | O4: VENDA PROD. INDUSTRIALIZADO - NFE | P4: GRUPO FERTIPAR FERTILIZANTES MATO GROSSO | Q4: =$R$1-F4 -> -3 | R4: =_xlfn.XLOOKUP(P4,'Painel Additive'!$B:$B,'Painel Additive'!$B:$B,0) -> GRUPO FERTIPAR FERTILIZANTES MATO GROSSO | S4: =F4-K4 -> 28
A5: 1257 | B5: MOSAIC - CAMPO GRANDE | C5: 61.156.501/0081-30 | D5: 1980.8 | E5: 1246032946 | F5: 44774 | H5: 1 | I5: Adtives | J5: 17935 | K5: 44714 | L5: 1010100 | M5: VENDAS MERCADO INTERNO | N5: 56 | O5: VENDA A ORDEM | P5: GRUPO MOSAIC FERTILIZANTES DO BRASIL | Q5: =$R$1-F5 -> 1362 | R5: =_xlfn.XLOOKUP(P5,'Painel Additive'!$B:$B,'Painel Additive'!$B:$B,0) -> GRUPO MOSAIC FERTILIZANTES DO BRASIL | S5: =F5-K5 -> 60
A6: 1953 | B6: AMAGGI - COMODORO | C6: 77.294.254/0075-20 | D6: 58917.8 | E6: 1246267986 | F6: 46158 | H6: 1 | I6: Adtives | J6: 10907 | K6: 46098 | L6: 1010100 | M6: VENDAS MERCADO INTERNO | N6: 161 | O6: VENDA PROD. INDUSTRIALIZADO - NFE | P6: GRUPO AMAGGI | Q6: =$R$1-F6 -> -22 | R6: =_xlfn.XLOOKUP(P6,'Painel Additive'!$B:$B,'Painel Additive'!$B:$B,0) -> GRUPO AMAGGI | S6: =F6-K6 -> 60
A7: 1787 | B7: MOSAIC - UBERABA (CIU1) | C7: 33.931.486/0014-55 | D7: 109862.4 | E7: 1246271310 | F7: 46216 | H7: 1 | I7: Adtives | J7: 11116 | K7: 46126 | L7: 1010100 | M7: VENDAS MERCADO INTERNO | N7: 161 | O7: VENDA PROD. INDUSTRIALIZADO - NFE | P7: GRUPO MOSAIC FERTILIZANTES P K LTDA | Q7: =$R$1-F7 -> -80 | R7: =_xlfn.XLOOKUP(P7,'Painel Additive'!$B:$B,'Painel Additive'!$B:$B,0) -> GRUPO MOSAIC FERTILIZANTES P K LTDA | S7: =F7-K7 -> 90
A8: 1787 | B8: MOSAIC - UBERABA (CIU1) | C8: 33.931.486/0014-55 | D8: 116928 | E8: 1246267948 | F8: 46187 | H8: 1 | I8: Adtives | J8: 10899 | K8: 46097 | L8: 1010100 | M8: VENDAS MERCADO INTERNO | N8: 161 | O8: VENDA PROD. INDUSTRIALIZADO - NFE | P8: GRUPO MOSAIC FERTILIZANTES P K LTDA | Q8: =$R$1-F8 -> -51 | R8: =_xlfn.XLOOKUP(P8,'Painel Additive'!$B:$B,'Painel Additive'!$B:$B,0) -> GRUPO MOSAIC FERTILIZANTES P K LTDA | S8: =F8-K8 -> 90
A9: 1787 | B9: MOSAIC - UBERABA (CIU1) | C9: 33.931.486/0014-55 | D9: 115891.2 | E9: 1246262540 | F9: 46149 | H9: 1 | I9: Adtives | J9: 10652 | K9: 46059 | L9: 1010100 | M9: VENDAS MERCADO INTERNO | N9: 161 | O9: VENDA PROD. INDUSTRIALIZADO - NFE | P9: GRUPO MOSAIC FERTILIZANTES P K LTDA | Q9: =$R$1-F9 -> -13 | R9: =_xlfn.XLOOKUP(P9,'Painel Additive'!$B:$B,'Painel Additive'!$B:$B,0) -> GRUPO MOSAIC FERTILIZANTES P K LTDA | S9: =F9-K9 -> 90
A10: 1787 | B10: MOSAIC - UBERABA (CIU1) | C10: 33.931.486/0014-55 | D10: 103795.2 | E10: 1246268633 | F10: 46194 | H10: 1 | I10: Adtives | J10: 10957 | K10: 46104 | L10: 1010100 | M10: VENDAS MERCADO INTERNO | N10: 161 | O10: VENDA PROD. INDUSTRIALIZADO - NFE | P10: GRUPO MOSAIC FERTILIZANTES P K LTDA | Q10: =$R$1-F10 -> -58 | R10: =_xlfn.XLOOKUP(P10,'Painel Additive'!$B:$B,'Painel Additive'!$B:$B,0) -> GRUPO MOSAIC FERTILIZANTES P K LTDA | S10: =F10-K10 -> 90
A11: 1787 | B11: MOSAIC - UBERABA (CIU1) | C11: 33.931.486/0014-55 | D11: 111360 | E11: 1246268748 | F11: 46195 | H11: 1 | I11: Adtives | J11: 10965 | K11: 46105 | L11: 1010100 | M11: VENDAS MERCADO INTERNO | N11: 161 | O11: VENDA PROD. INDUSTRIALIZADO - NFE | P11: GRUPO MOSAIC FERTILIZANTES P K LTDA | Q11: =$R$1-F11 -> -59 | R11: =_xlfn.XLOOKUP(P11,'Painel Additive'!$B:$B,'Painel Additive'!$B:$B,0) -> GRUPO MOSAIC FERTILIZANTES P K LTDA | S11: =F11-K11 -> 90
A12: 1787 | B12: MOSAIC - UBERABA (CIU1) | C12: 33.931.486/0014-55 | D12: 114662.4 | E12: 1246268585 | F12: 46161 | H12: 1 | I12: Adtives | J12: 10953 | K12: 46101 | L12: 1010100 | M12: VENDAS MERCADO INTERNO | N12: 161 | O12: VENDA PROD. INDUSTRIALIZADO - NFE | P12: GRUPO MOSAIC FERTILIZANTES P K LTDA | Q12: =$R$1-F12 -> -25 | R12: =_xlfn.XLOOKUP(P12,'Painel Additive'!$B:$B,'Painel Additive'!$B:$B,0) -> GRUPO MOSAIC FERTILIZANTES P K LTDA | S12: =F12-K12 -> 60
A13: 1787 | B13: MOSAIC - UBERABA (CIU1) | C13: 33.931.486/0014-55 | D13: 115852.8 | E13: 1246270635 | F13: 46210 | H13: 1 | I13: Adtives | J13: 11072 | K13: 46120 | L13: 1010100 | M13: VENDAS MERCADO INTERNO | N13: 161 | O13: VENDA PROD. INDUSTRIALIZADO - NFE | P13: GRUPO MOSAIC FERTILIZANTES P K LTDA | Q13: =$R$1-F13 -> -74 | R13: =_xlfn.XLOOKUP(P13,'Painel Additive'!$B:$B,'Painel Additive'!$B:$B,0) -> GRUPO MOSAIC FERTILIZANTES P K LTDA | S13: =F13-K13 -> 90
A14: 1787 | B14: MOSAIC - UBERABA (CIU1) | C14: 33.931.486/0014-55 | D14: 114739.2 | E14: 1246271165 | F14: 46215 | H14: 1 | I14: Adtives | J14: 11105 | K14: 46125 | L14: 1010100 | M14: VENDAS MERCADO INTERNO | N14: 161 | O14: VENDA PROD. INDUSTRIALIZADO - NFE | P14: GRUPO MOSAIC FERTILIZANTES P K LTDA | Q14: =$R$1-F14 -> -79 | R14: =_xlfn.XLOOKUP(P14,'Painel Additive'!$B:$B,'Painel Additive'!$B:$B,0) -> GRUPO MOSAIC FERTILIZANTES P K LTDA | S14: =F14-K14 -> 90
... A190: 707 | B190: TERRA FERTILIZANTES LTDA - ARAXÁ | C190: 10.482.668/0001-76 | D190: 40353.6 | E190: 1246143397 | F190: 45443 | H190: 1 | I190: Adtives | J190: 3448 | K190: 45415 | L190: 1010100 | M190: VENDAS MERCADO INTERNO | N190: 161 | O190: VENDA PROD. INDUSTRIALIZADO - NFE | P190: TERRA FERTILIZANTES LTDA - ARAXÁ | Q190: =$R$1-F190 -> 693 | R190: =_xlfn.XLOOKUP(P190,'Painel Additive'!$B:$B,'Painel Additive'!$B:$B,0) -> TERRA FERTILIZANTES LTDA - ARAXÁ | S190: =F190-K190 -> 28
A191: 1462 | B191: AURORA MINERAÇÃO LTDA | C191: 02.964.101/0001-08 | D191: 37608.4 | E191: 1246266894 | F191: 46147 | H191: 1 | I191: Adtives | J191: 10834 | K191: 46087 | L191: 1010100 | M191: VENDAS MERCADO INTERNO | N191: 161 | O191: VENDA PROD. INDUSTRIALIZADO - NFE | P191: AURORA MINERAÇÃO LTDA | Q191: =$R$1-F191 -> -11 | R191: =_xlfn.XLOOKUP(P191,'Painel Additive'!$B:$B,'Painel Additive'!$B:$B,0) -> AURORA MINERAÇÃO LTDA | S191: =F191-K191 -> 60 | T191: =F191-$R$1 -> 11
A192: 1462 | B192: AURORA MINERAÇÃO LTDA | C192: 02.964.101/0001-08 | D192: 37608.4 | E192: 1246266895 | F192: 46157 | H192: 1 | I192: Adtives | J192: 10834 | K192: 46087 | L192: 1010100 | M192: VENDAS MERCADO INTERNO | N192: 161 | O192: VENDA PROD. INDUSTRIALIZADO - NFE | P192: AURORA MINERAÇÃO LTDA | Q192: =$R$1-F192 -> -21 | R192: =_xlfn.XLOOKUP(P192,'Painel Additive'!$B:$B,'Painel Additive'!$B:$B,0) -> AURORA MINERAÇÃO LTDA | S192: =F192-K192 -> 70 | T192: =F192-$R$1 -> 21
A193: 1462 | B193: AURORA MINERAÇÃO LTDA | C193: 02.964.101/0001-08 | D193: 38160.2 | E193: 1246270126 | F193: 46174 | H193: 1 | I193: Adtives | J193: 11041 | K193: 46114 | L193: 1010100 | M193: VENDAS MERCADO INTERNO | N193: 161 | O193: VENDA PROD. INDUSTRIALIZADO - NFE | P193: AURORA MINERAÇÃO LTDA | Q193: =$R$1-F193 -> -38 | R193: =_xlfn.XLOOKUP(P193,'Painel Additive'!$B:$B,'Painel Additive'!$B:$B,0) -> AURORA MINERAÇÃO LTDA | S193: =F193-K193 -> 60 | T193: =F193-$R$1 -> 38
A194: 1462 | B194: AURORA MINERAÇÃO LTDA | C194: 02.964.101/0001-08 | D194: 38160.2 | E194: 1246270127 | F194: 46184 | H194: 1 | I194: Adtives | J194: 11041 | K194: 46114 | L194: 1010100 | M194: VENDAS MERCADO INTERNO | N194: 161 | O194: VENDA PROD. INDUSTRIALIZADO - NFE | P194: AURORA MINERAÇÃO LTDA | Q194: =$R$1-F194 -> -48 | R194: =_xlfn.XLOOKUP(P194,'Painel Additive'!$B:$B,'Painel Additive'!$B:$B,0) -> AURORA MINERAÇÃO LTDA | S194: =F194-K194 -> 70
A195: 1462 | B195: AURORA MINERAÇÃO LTDA | C195: 02.964.101/0001-08 | D195: 37491.5 | E195: 1246262009 | F195: 46125 | H195: 1 | I195: Adtives | J195: 10624 | K195: 46055 | L195: 1010100 | M195: VENDAS MERCADO INTERNO | N195: 161 | O195: VENDA PROD. INDUSTRIALIZADO - NFE | P195: AURORA MINERAÇÃO LTDA | Q195: =$R$1-F195 -> 11 | R195: =_xlfn.XLOOKUP(P195,'Painel Additive'!$B:$B,'Painel Additive'!$B:$B,0) -> AURORA MINERAÇÃO LTDA | S195: =F195-K195 -> 70
A196: 2011 | B196: FERTGROW S.A | C196: 14.267.717/0001-09 | D196: 106570.7 | E196: 1246270108 | F196: 46142 | H196: 1 | I196: Adtives | J196: 11036 | K196: 46114 | L196: 1010100 | M196: VENDAS MERCADO INTERNO | N196: 161 | O196: VENDA PROD. INDUSTRIALIZADO - NFE | P196: FERTGROW S.A | Q196: =$R$1-F196 -> -6 | R196: =_xlfn.XLOOKUP(P196,'Painel Additive'!$B:$B,'Painel Additive'!$B:$B,0) -> FERTGROW S.A | S196: =F196-K196 -> 28
A197: 2011 | B197: FERTGROW S.A | C197: 14.267.717/0001-09 | D197: 105829.4 | E197: 1246271331 | F197: 46154 | H197: 1 | I197: Adtives | J197: 11121 | K197: 46126 | L197: 1010100 | M197: VENDAS MERCADO INTERNO | N197: 161 | O197: VENDA PROD. INDUSTRIALIZADO - NFE | P197: FERTGROW S.A | Q197: =$R$1-F197 -> -18 | R197: =_xlfn.XLOOKUP(P197,'Painel Additive'!$B:$B,'Painel Additive'!$B:$B,0) -> FERTGROW S.A | S197: =F197-K197 -> 28
A198: 31 | B198: SUL GOIANA - GOIATUBA | C198: 37.309.283/0001-68 | D198: 120000 | E198: 1246269899 | F198: 46141 | H198: 1 | I198: Adtives | J198: 2861 | K198: 46113 | L198: 1010100 | M198: VENDAS MERCADO INTERNO | N198: 161 | O198: VENDA PROD. INDUSTRIALIZADO - NFE | P198: SUL GOIANA - GOIATUBA | Q198: =$R$1-F198 -> -5 | R198: =_xlfn.XLOOKUP(P198,'Painel Additive'!$B:$B,'Painel Additive'!$B:$B,0) -> SUL GOIANA - GOIATUBA | S198: =F198-K198 -> 28
A199: 2247 | B199: ADUBOS LEAO - LARANJEIRAS | C199: 27.360.944/0001-26 | D199: 12189 | E199: 1246272759 | F199: 46167 | H199: 1 | I199: Adtives | J199: 2896 | K199: 46139 | L199: 1010100 | M199: VENDAS MERCADO INTERNO | N199: 161 | O199: VENDA PROD. INDUSTRIALIZADO - NFE | P199: ADUBOS LEAO - LARANJEIRAS | Q199: =$R$1-F199 -> -31 | R199: =_xlfn.XLOOKUP(P199,'Painel Additive'!$B:$B,'Painel Additive'!$B:$B,0) -> ADUBOS LEAO - LARANJEIRAS | S199: =F199-K199 -> 28
A200: 2247 | B200: ADUBOS LEAO - LARANJEIRAS | C200: 27.360.944/0001-26 | D200: 12189 | E200: 1246272760 | F200: 46195 | H200: 1 | I200: Adtives | J200: 2896 | K200: 46139 | L200: 1010100 | M200: VENDAS MERCADO INTERNO | N200: 161 | O200: VENDA PROD. INDUSTRIALIZADO - NFE | P200: ADUBOS LEAO - LARANJEIRAS | Q200: =$R$1-F200 -> -59 | R200: =_xlfn.XLOOKUP(P200,'Painel Additive'!$B:$B,'Painel Additive'!$B:$B,0) -> ADUBOS LEAO - LARANJEIRAS | S200: =F200-K200 -> 56
A201: 2247 | B201: ADUBOS LEAO - LARANJEIRAS | C201: 27.360.944/0001-26 | D201: 956 | E201: 1246272577 | F201: 46164 | H201: 1 | I201: Adtives | J201: 2892 | K201: 46136 | L201: 1010100 | M201: VENDAS MERCADO INTERNO | N201: 161 | O201: VENDA PROD. INDUSTRIALIZADO - NFE | P201: ADUBOS LEAO - LARANJEIRAS | Q201: =$R$1-F201 -> -28 | R201: =_xlfn.XLOOKUP(P201,'Painel Additive'!$B:$B,'Painel Additive'!$B:$B,0) -> ADUBOS LEAO - LARANJEIRAS | S201: =F201-K201 -> 28
A202: 2247 | B202: ADUBOS LEAO - LARANJEIRAS | C202: 27.360.944/0001-26 | D202: 956 | E202: 1246272578 | F202: 46192 | H202: 1 | I202: Adtives | J202: 2892 | K202: 46136 | L202: 1010100 | M202: VENDAS MERCADO INTERNO | N202: 161 | O202: VENDA PROD. INDUSTRIALIZADO - NFE | P202: ADUBOS LEAO - LARANJEIRAS | Q202: =$R$1-F202 -> -56 | R202: =_xlfn.XLOOKUP(P202,'Painel Additive'!$B:$B,'Painel Additive'!$B:$B,0) -> ADUBOS LEAO - LARANJEIRAS | S202: =F202-K202 -> 56
A203: 3142 | B203: INTERFERTIL - SAO FRANCISCO DO SUL | C203: 01.094.764/0002-37 | D203: 44919 | E203: 1246272504 | F203: 46164 | H203: 1 | I203: Adtives | J203: 11215 | K203: 46136 | L203: 1010100 | M203: VENDAS MERCADO INTERNO | N203: 161 | O203: VENDA PROD. INDUSTRIALIZADO - NFE | P203: INTERFERTIL - SAO FRANCISCO DO SUL | Q203: =$R$1-F203 -> -28 | R203: =_xlfn.XLOOKUP(P203,'Painel Additive'!$B:$B,'Painel Additive'!$B:$B,0) -> INTERFERTIL - SAO FRANCISCO DO SUL | S203: =F203-K203 -> 28
A204: 2900 | B204: BIOSAFRA - MARUIM | C204: 04.251.044/0001-45 | D204: 17017.16 | E204: 1246267967 | F204: 46157 | H204: 1 | I204: Adtives | J204: 10901 | K204: 46097 | L204: 1010100 | M204: VENDAS MERCADO INTERNO | N204: 161 | O204: VENDA PROD. INDUSTRIALIZADO - NFE | P204: BIOSAFRA - MARUIM | Q204: =$R$1-F204 -> -21 | R204: =_xlfn.XLOOKUP(P204,'Painel Additive'!$B:$B,'Painel Additive'!$B:$B,0) -> BIOSAFRA - MARUIM | S204: =F204-K204 -> 60
A205: 2900 | B205: BIOSAFRA - MARUIM | C205: 04.251.044/0001-45 | D205: 17017.16 | E205: 1246267968 | F205: 46187 | H205: 1 | I205: Adtives | J205: 10901 | K205: 46097 | L205: 1010100 | M205: VENDAS MERCADO INTERNO | N205: 161 | O205: VENDA PROD. INDUSTRIALIZADO - NFE | P205: BIOSAFRA - MARUIM | Q205: =$R$1-F205 -> -51 | R205: =_xlfn.XLOOKUP(P205,'Painel Additive'!$B:$B,'Painel Additive'!$B:$B,0) -> BIOSAFRA - MARUIM | S205: =F205-K205 -> 90
... A234: 7022 | B234: STRATOS/MOSAIC - ROSARIO DO CATETE | C234: 31.009.644/0001-74 | D234: 70752.8 | E234: 1246265339 | F234: 46139 | H234: 1 | I234: Adtives | J234: 10774 | K234: 46079 | L234: 1010100 | M234: VENDAS MERCADO INTERNO | N234: 161 | O234: VENDA PROD. INDUSTRIALIZADO - NFE | P234: STRATOS/MOSAIC - ROSARIO DO CATETE | Q234: =$R$1-F234 -> -3 | R234: =_xlfn.XLOOKUP(P234,'Painel Additive'!$B:$B,'Painel Additive'!$B:$B,0) -> STRATOS/MOSAIC - ROSARIO DO CATETE | S234: =F234-K234 -> 60
A235: 9830 | B235: ELYMAR JOSE DA SILVA FERREIRA | C235: 053.438.381-54 | D235: 331 | E235: 1246266367 | F235: 46145 | I235: Não encontrado | J235: 10813 | K235: 46085 | L235: 4011600 | M235: APARELHOS DE INFORMÁTICA | N235: 244 | O235: VENDA DE IMOBILIZADO SEM ICMS | P235: ELYMAR JOSE DA SILVA FERREIRA | Q235: =$R$1-F235 -> -9 | R235: =_xlfn.XLOOKUP(P235,'Painel Additive'!$B:$B,'Painel Additive'!$B:$B,0) -> ELYMAR JOSE DA SILVA FERREIRA | S235: =F235-K235 -> 60
A236: 9830 | B236: ELYMAR JOSE DA SILVA FERREIRA | C236: 053.438.381-54 | D236: 331 | E236: 1246266368 | F236: 46175 | I236: Não encontrado | J236: 10813 | K236: 46085 | L236: 4011600 | M236: APARELHOS DE INFORMÁTICA | N236: 244 | O236: VENDA DE IMOBILIZADO SEM ICMS | P236: ELYMAR JOSE DA SILVA FERREIRA | Q236: =$R$1-F236 -> -39 | R236: =_xlfn.XLOOKUP(P236,'Painel Additive'!$B:$B,'Painel Additive'!$B:$B,0) -> ELYMAR JOSE DA SILVA FERREIRA | S236: =F236-K236 -> 90
A237: 11637 | B237: AGROPECUARIA MARATA LTDA - MARUIM | C237: 32.821.183/0004-45 | D237: 290220 | E237: 1246272018 | F237: 46162 | H237: 1 | I237: Adtives | J237: 2884 | K237: 46134 | L237: 1010100 | M237: VENDAS MERCADO INTERNO | N237: 161 | O237: VENDA PROD. INDUSTRIALIZADO - NFE | P237: AGROPECUARIA MARATA LTDA - MARUIM | Q237: =$R$1-F237 -> -26 | R237: =_xlfn.XLOOKUP(P237,'Painel Additive'!$B:$B,'Painel Additive'!$B:$B,0) -> AGROPECUARIA MARATA LTDA - MARUIM | S237: =F237-K237 -> 28
A238: 12943 | B238: ITERUM - RONDONOPOLIS | C238: 07.571.116/0015-25 | D238: 82290 | E238: 1246187828 | F238: 45667 | H238: 1 | I238: Adtives | J238: 1585 | K238: 45639 | L238: 1010100 | M238: VENDAS MERCADO INTERNO | N238: 161 | O238: VENDA PROD. INDUSTRIALIZADO - NFE | P238: ITERUM - RONDONOPOLIS | Q238: =$R$1-F238 -> 469 | R238: =_xlfn.XLOOKUP(P238,'Painel Additive'!$B:$B,'Painel Additive'!$B:$B,0) -> ITERUM - RONDONOPOLIS | S238: =F238-K238 -> 28
A239: 12943 | B239: ITERUM - RONDONOPOLIS | C239: 07.571.116/0015-25 | D239: 82290 | E239: 1246187829 | F239: 45695 | H239: 1 | I239: Adtives | J239: 1585 | K239: 45639 | L239: 1010100 | M239: VENDAS MERCADO INTERNO | N239: 161 | O239: VENDA PROD. INDUSTRIALIZADO - NFE | P239: ITERUM - RONDONOPOLIS | Q239: =$R$1-F239 -> 441 | R239: =_xlfn.XLOOKUP(P239,'Painel Additive'!$B:$B,'Painel Additive'!$B:$B,0) -> ITERUM - RONDONOPOLIS | S239: =F239-K239 -> 56
A240: 12943 | B240: ITERUM - RONDONOPOLIS | C240: 07.571.116/0015-25 | D240: 49170 | E240: 1246183176 | F240: 45642 | H240: 1 | I240: Adtives | J240: 6129 | K240: 45614 | L240: 1010100 | M240: VENDAS MERCADO INTERNO | N240: 161 | O240: VENDA PROD. INDUSTRIALIZADO - NFE | P240: ITERUM - RONDONOPOLIS | Q240: =$R$1-F240 -> 494 | R240: =_xlfn.XLOOKUP(P240,'Painel Additive'!$B:$B,'Painel Additive'!$B:$B,0) -> ITERUM - RONDONOPOLIS | S240: =F240-K240 -> 28
A241: 12629 | B241: EUROCHEM SERRA DO SALITRE | C241: 43.066.666/0001-55 | D241: 162357 | E241: 1246269970 | F241: 46143 | H241: 1 | I241: Adtives | J241: 11028 | K241: 46113 | L241: 1010100 | M241: VENDAS MERCADO INTERNO | N241: 161 | O241: VENDA PROD. INDUSTRIALIZADO - NFE | P241: EUROCHEM SERRA DO SALITRE | Q241: =$R$1-F241 -> -7 | R241: =_xlfn.XLOOKUP(P241,'Painel Additive'!$B:$B,'Painel Additive'!$B:$B,0) -> EUROCHEM SERRA DO SALITRE | S241: =F241-K241 -> 30
A242: 12629 | B242: EUROCHEM SERRA DO SALITRE | C242: 43.066.666/0001-55 | D242: 153506.1 | E242: 1246268563 | F242: 46131 | H242: 1 | I242: Adtives | J242: 10948 | K242: 46101 | L242: 1010100 | M242: VENDAS MERCADO INTERNO | N242: 161 | O242: VENDA PROD. INDUSTRIALIZADO - NFE | P242: EUROCHEM SERRA DO SALITRE | Q242: =$R$1-F242 -> 5 | R242: =_xlfn.XLOOKUP(P242,'Painel Additive'!$B:$B,'Painel Additive'!$B:$B,0) -> EUROCHEM SERRA DO SALITRE | S242: =F242-K242 -> 30
A243: 12629 | B243: EUROCHEM SERRA DO SALITRE | C243: 43.066.666/0001-55 | D243: 162465.6 | E243: 1246269412 | F243: 46138 | H243: 1 | I243: Adtives | J243: 10987 | K243: 46108 | L243: 1010100 | M243: VENDAS MERCADO INTERNO | N243: 161 | O243: VENDA PROD. INDUSTRIALIZADO - NFE | P243: EUROCHEM SERRA DO SALITRE | Q243: =$R$1-F243 -> -2 | R243: =_xlfn.XLOOKUP(P243,'Painel Additive'!$B:$B,'Painel Additive'!$B:$B,0) -> EUROCHEM SERRA DO SALITRE | S243: =F243-K243 -> 30
A244: 12629 | B244: EUROCHEM SERRA DO SALITRE | C244: 43.066.666/0001-55 | D244: 153451.8 | E244: 1246270416 | F244: 46148 | H244: 1 | I244: Adtives | J244: 11059 | K244: 46118 | L244: 1010100 | M244: VENDAS MERCADO INTERNO | N244: 161 | O244: VENDA PROD. INDUSTRIALIZADO - NFE | P244: EUROCHEM SERRA DO SALITRE | Q244: =$R$1-F244 -> -12 | R244: =_xlfn.XLOOKUP(P244,'Painel Additive'!$B:$B,'Painel Additive'!$B:$B,0) -> EUROCHEM SERRA DO SALITRE | S244: =F244-K244 -> 30
A245: 12629 | B245: EUROCHEM SERRA DO SALITRE | C245: 43.066.666/0001-55 | D245: 162031.2 | E245: 1246271940 | F245: 46162 | H245: 1 | I245: Adtives | J245: 11184 | K245: 46132 | L245: 1010100 | M245: VENDAS MERCADO INTERNO | N245: 161 | O245: VENDA PROD. INDUSTRIALIZADO - NFE | P245: EUROCHEM SERRA DO SALITRE | Q245: =$R$1-F245 -> -26 | R245: =_xlfn.XLOOKUP(P245,'Painel Additive'!$B:$B,'Painel Additive'!$B:$B,0) -> EUROCHEM SERRA DO SALITRE | S245: =F245-K245 -> 30
A246: 13069 | B246: JOSÉ FRANCISCO PIRES DE SOUZA | C246: 012.300.516-78 | D246: 100 | E246: 1246258365 | F246: 46118 | I246: Não encontrado | J246: 10425 | K246: 46028 | L246: 4010300 | M246: MÓVEIS E UTENSÍLIOS | N246: 244 | O246: VENDA DE IMOBILIZADO SEM ICMS | P246: JOSÉ FRANCISCO PIRES DE SOUZA | Q246: =$R$1-F246 -> 18 | R246: =_xlfn.XLOOKUP(P246,'Painel Additive'!$B:$B,'Painel Additive'!$B:$B,0) -> JOSÉ FRANCISCO PIRES DE SOUZA | S246: =F246-K246 -> 90
A247: 14094 | B247: KLEYTON DUARTE SOARES | C247: 014.415.101-41 | D247: 100 | E247: 1246154530 | F247: 45474 | I247: Não encontrado | J247: 4088 | K247: 45474 | L247: 4010300 | M247: MÓVEIS E UTENSÍLIOS | N247: 244 | O247: VENDA DE IMOBILIZADO SEM ICMS | P247: KLEYTON DUARTE SOARES | Q247: =$R$1-F247 -> 662 | R247: =_xlfn.XLOOKUP(P247,'Painel Additive'!$B:$B,'Painel Additive'!$B:$B,0) -> KLEYTON DUARTE SOARES | S247: =F247-K247 -> 0
A248: 13873 | B248: MARIA JOSE DA SILVA | C248: 844.462.855-72 | D248: 50 | E248: 1246166396 | F248: 45525 | I248: Não encontrado | J248: 4854 | K248: 45525 | L248: 4010300 | M248: MÓVEIS E UTENSÍLIOS | N248: 244 | O248: VENDA DE IMOBILIZADO SEM ICMS | P248: MARIA JOSE DA SILVA | Q248: =$R$1-F248 -> 611 | R248: =_xlfn.XLOOKUP(P248,'Painel Additive'!$B:$B,'Painel Additive'!$B:$B,0) -> MARIA JOSE DA SILVA | S248: =F248-K248 -> 0
A249: 14179 | B249: LUCAS DA CONCEIÇÃO CASSIMIRO | C249: 077.998.984-88 | D249: 292.08 | E249: 1246270339 | F249: 46143 | I249: Não encontrado | J249: 10469 | K249: 46035 | L249: 4011600 | M249: APARELHOS DE INFORMÁTICA | N249: 244 | O249: VENDA DE IMOBILIZADO SEM ICMS | P249: LUCAS DA CONCEIÇÃO CASSIMIRO | Q249: =$R$1-F249 -> -7 | R249: =_xlfn.XLOOKUP(P249,'Painel Additive'!$B:$B,'Painel Additive'!$B:$B,0) -> LUCAS DA CONCEIÇÃO CASSIMIRO | S249: =F249-K249 -> 108
A250: 14106 | B250: SEU LIXO | C250: 50.454.037/0001-68 | D250: 300 | E250: 1246182736 | F250: 45625 | I250: Não encontrado | J250: 6092 | K250: 45610 | L250: 1020400 | M250: VENDA DE SUCATAS | N250: 136 | O250: VENDA DE SUCATAS | P250: SEU LIXO | Q250: =$R$1-F250 -> 511 | R250: =_xlfn.XLOOKUP(P250,'Painel Additive'!$B:$B,'Painel Additive'!$B:$B,0) -> SEU LIXO | S250: =F250-K250 -> 15
A251: 16032 | B251: ANDRESSA CAROLINA SILVA RODRIGUES | C251: 096.141.946-69 | D251: 583.34 | E251: 1246264383 | F251: 46163 | I251: Não encontrado | J251: 10732 | K251: 46073 | L251: 4011600 | M251: APARELHOS DE INFORMÁTICA | N251: 244 | O251: VENDA DE IMOBILIZADO SEM ICMS | P251: ANDRESSA CAROLINA SILVA RODRIGUES | Q251: =$R$1-F251 -> -27 | R251: =_xlfn.XLOOKUP(P251,'Painel Additive'!$B:$B,'Painel Additive'!$B:$B,0) -> ANDRESSA CAROLINA SILVA RODRIGUES | S251: =F251-K251 -> 90
A252: 16189 | B252: ARSLOG SOLUCOES EM TRANSPORTE | C252: 05.765.626/0001-02 | D252: 49440 | E252: 1246261824 | F252: 46087 | I252: Não encontrado | J252: 1246261824 | K252: 46055 | L252: 7240000 | M252: PERDA DE MERCADORIA COM SINISTRO | N252: 46 | O252: FINANCEIRO GERAL | P252: ARSLOG SOLUCOES EM TRANSPORTE | Q252: =$R$1-F252 -> 49 | R252: =_xlfn.XLOOKUP(P252,'Painel Additive'!$B:$B,'Painel Additive'!$B:$B,0) -> ARSLOG SOLUCOES EM TRANSPORTE | S252: =F252-K252 -> 32
Q253: =$R$1-F253 -> 46136 | R253: =_xlfn.XLOOKUP(P253,'Painel Additive'!$B:$B,'Painel Additive'!$B:$B,0) -> 0 | S253: =F253-K253 -> 0
Q254: =$R$1-F254 -> 46136 | R254: =_xlfn.XLOOKUP(P254,'Painel Additive'!$B:$B,'Painel Additive'!$B:$B,0) -> 0 | S254: =F254-K254 -> 0
Q255: =$R$1-F255 -> 46136 | R255: =_xlfn.XLOOKUP(P255,'Painel Additive'!$B:$B,'Painel Additive'!$B:$B,0) -> 0 | S255: =F255-K255 -> 0
Q256: =$R$1-F256 -> 46136 | R256: =_xlfn.XLOOKUP(P256,'Painel Additive'!$B:$B,'Painel Additive'!$B:$B,0) -> 0 | S256: =F256-K256 -> 0
Q257: =$R$1-F257 -> 46136 | R257: =_xlfn.XLOOKUP(P257,'Painel Additive'!$B:$B,'Painel Additive'!$B:$B,0) -> 0 | S257: =F257-K257 -> 0
Q258: =$R$1-F258 -> 46136 | R258: =_xlfn.XLOOKUP(P258,'Painel Additive'!$B:$B,'Painel Additive'!$B:$B,0) -> 0 | S258: =F258-K258 -> 0
Q259: =$R$1-F259 -> 46136 | R259: =_xlfn.XLOOKUP(P259,'Painel Additive'!$B:$B,'Painel Additive'!$B:$B,0) -> 0 | S259: =F259-K259 -> 0
Q260: =$R$1-F260 -> 46136 | R260: =_xlfn.XLOOKUP(P260,'Painel Additive'!$B:$B,'Painel Additive'!$B:$B,0) -> 0 | S260: =F260-K260 -> 0
Q261: =$R$1-F261 -> 46136 | R261: =_xlfn.XLOOKUP(P261,'Painel Additive'!$B:$B,'Painel Additive'!$B:$B,0) -> 0 | S261: =F261-K261 -> 0
Q262: =$R$1-F262 -> 46136 | R262: =_xlfn.XLOOKUP(P262,'Painel Additive'!$B:$B,'Painel Additive'!$B:$B,0) -> 0 | S262: =F262-K262 -> 0
Q263: =$R$1-F263 -> 46136 | R263: =_xlfn.XLOOKUP(P263,'Painel Additive'!$B:$B,'Painel Additive'!$B:$B,0) -> 0 | S263: =F263-K263 -> 0
Q264: =$R$1-F264 -> 46136 | R264: =_xlfn.XLOOKUP(P264,'Painel Additive'!$B:$B,'Painel Additive'!$B:$B,0) -> 0 | S264: =F264-K264 -> 0
... Q288: =$R$1-F288 -> 46136 | R288: =_xlfn.XLOOKUP(P288,'Painel Additive'!$B:$B,'Painel Additive'!$B:$B,0) -> 0 | S288: =F288-K288 -> 0

Sheet Data International
D1: =SUBTOTAL(9,D3:D995) -> 6984269.3 | R1: 46136
A2: CODPARC | B2: NOMEPARC | C2: CNPJ | D2: Valor | E2: NUFIN | F2: DTVENC | G2: DHBAIXA | H2: AD_BU | I2: NOME_BU | J2: NUMNOTA | K2: DTENTSAI | L2: CODNAT | M2: DESCRNAT | N2: CODTIPOPER | O2: OPERACAO | P2: Grupo | Q2: Dias vencidos
A3: 3297 | B3: MACROSOURCE PERU S.R.L. | C3: ..- | D3: 49956.68 | E3: 1246271355 | F3: 46186 | H3: 1 | I3: Adtives | J3: 11123 | K3: 46126 | L3: 1010200 | M3: VENDAS MERCADO EXTERNO | N3: 40 | O3: VENDA - NFE (EXPORTAÇÃO) | P3: MACROSOURCE PERU S.R.L. | Q3: =$R$1-F3 -> -50 | R3: =_xlfn.XLOOKUP(P3,'Painel International'!$B:$B,'Painel International'!$B:$B,0) -> MACROSOURCE PERU S.R.L.
A4: 3426 | B4: C I ACEPALMA SA - COLOMBIA | C4: 00.000.000/0000-00 | D4: 250261.53 | E4: 1246272081 | F4: 46194 | H4: 1 | I4: Adtives | J4: 2886 | K4: 46134 | L4: 1010200 | M4: VENDAS MERCADO EXTERNO | N4: 40 | O4: VENDA - NFE (EXPORTAÇÃO) | P4: C I ACEPALMA SA - COLOMBIA | Q4: =$R$1-F4 -> -58 | R4: =_xlfn.XLOOKUP(P4,'Painel International'!$B:$B,'Painel International'!$B:$B,0) -> C I ACEPALMA SA - COLOMBIA
A5: 2680 | B5: FERMAGRI S.A - EQUADOR | C5: ..- | D5: 224812.61 | E5: 1246263810 | F5: 46144 | H5: 1 | I5: Adtives | J5: 2743 | K5: 46069 | L5: 1010200 | M5: VENDAS MERCADO EXTERNO | N5: 40 | O5: VENDA - NFE (EXPORTAÇÃO) | P5: FERMAGRI S.A - EQUADOR | Q5: =$R$1-F5 -> -8 | R5: =_xlfn.XLOOKUP(P5,'Painel International'!$B:$B,'Painel International'!$B:$B,0) -> FERMAGRI S.A - EQUADOR
A6: 2680 | B6: FERMAGRI S.A - EQUADOR | C6: ..- | D6: 175275.24 | E6: 1246272069 | F6: 46194 | H6: 1 | I6: Adtives | J6: 11191 | K6: 46134 | L6: 1010200 | M6: VENDAS MERCADO EXTERNO | N6: 40 | O6: VENDA - NFE (EXPORTAÇÃO) | P6: FERMAGRI S.A - EQUADOR | Q6: =$R$1-F6 -> -58 | R6: =_xlfn.XLOOKUP(P6,'Painel International'!$B:$B,'Painel International'!$B:$B,0) -> FERMAGRI S.A - EQUADOR
A7: 2346 | B7: TEPEYAC - MÉXICO | C7: 11.091.524/0001-51 | D7: 103419.89 | E7: 1246265843 | F7: 46170 | H7: 1 | I7: Adtives | J7: 2789 | K7: 46080 | L7: 1010200 | M7: VENDAS MERCADO EXTERNO | N7: 40 | O7: VENDA - NFE (EXPORTAÇÃO) | P7: TEPEYAC - MÉXICO | Q7: =$R$1-F7 -> -34 | R7: =_xlfn.XLOOKUP(P7,'Painel International'!$B:$B,'Painel International'!$B:$B,0) -> TEPEYAC - MÉXICO
A8: 2651 | B8: AGROBROKERS - COLÔMBIA | C8: ..- | D8: 252226.12 | E8: 1246223341 | F8: 45935 | H8: 1 | I8: Adtives | J8: 8388 | K8: 45845 | L8: 1010200 | M8: VENDAS MERCADO EXTERNO | N8: 40 | O8: VENDA - NFE (EXPORTAÇÃO) | P8: AGROBROKERS - COLÔMBIA | Q8: =$R$1-F8 -> 201 | R8: =_xlfn.XLOOKUP(P8,'Painel International'!$B:$B,'Painel International'!$B:$B,0) -> AGROBROKERS - COLÔMBIA
A9: 2651 | B9: AGROBROKERS - COLÔMBIA | C9: ..- | D9: 197281.57 | E9: 1246213269 | F9: 45849 | H9: 1 | I9: Adtives | J9: 1965 | K9: 45789 | L9: 1010200 | M9: VENDAS MERCADO EXTERNO | N9: 40 | O9: VENDA - NFE (EXPORTAÇÃO) | P9: AGROBROKERS - COLÔMBIA | Q9: =$R$1-F9 -> 287 | R9: =_xlfn.XLOOKUP(P9,'Painel International'!$B:$B,'Painel International'!$B:$B,0) -> AGROBROKERS - COLÔMBIA
A10: 2652 | B10: FERTIMAX PARAGUAY | C10: ..- | D10: 157149.47 | E10: 1246271559 | F10: 46158 | H10: 1 | I10: Adtives | J10: 11137 | K10: 46128 | L10: 1010200 | M10: VENDAS MERCADO EXTERNO | N10: 40 | O10: VENDA - NFE (EXPORTAÇÃO) | P10: FERTIMAX PARAGUAY | Q10: =$R$1-F10 -> -22 | R10: =_xlfn.XLOOKUP(P10,'Painel International'!$B:$B,'Painel International'!$B:$B,0) -> FERTIMAX PARAGUAY
A11: 2287 | B11: BUNGE PARAGUAY S.A | C11: 99.999.999/9999-99 | D11: 149613.57 | E11: 1246271939 | F11: 46162 | H11: 1 | I11: Adtives | J11: 11183 | K11: 46132 | L11: 1010200 | M11: VENDAS MERCADO EXTERNO | N11: 40 | O11: VENDA - NFE (EXPORTAÇÃO) | P11: BUNGE PARAGUAY S.A | Q11: =$R$1-F11 -> -26 | R11: =_xlfn.XLOOKUP(P11,'Painel International'!$B:$B,'Painel International'!$B:$B,0) -> BUNGE PARAGUAY S.A
A12: 2287 | B12: BUNGE PARAGUAY S.A | C12: 99.999.999/9999-99 | D12: 151987.66 | E12: 1246270954 | F12: 46152 | H12: 1 | I12: Adtives | J12: 11086 | K12: 46122 | L12: 1010200 | M12: VENDAS MERCADO EXTERNO | N12: 40 | O12: VENDA - NFE (EXPORTAÇÃO) | P12: BUNGE PARAGUAY S.A | Q12: =$R$1-F12 -> -16 | R12: =_xlfn.XLOOKUP(P12,'Painel International'!$B:$B,'Painel International'!$B:$B,0) -> BUNGE PARAGUAY S.A
A13: 2287 | B13: BUNGE PARAGUAY S.A | C13: 99.999.999/9999-99 | D13: 157607.13 | E13: 1246268026 | F13: 46128 | H13: 1 | I13: Adtives | J13: 10909 | K13: 46098 | L13: 1010200 | M13: VENDAS MERCADO EXTERNO | N13: 40 | O13: VENDA - NFE (EXPORTAÇÃO) | P13: BUNGE PARAGUAY S.A | Q13: =$R$1-F13 -> 8 | R13: =_xlfn.XLOOKUP(P13,'Painel International'!$B:$B,'Painel International'!$B:$B,0) -> BUNGE PARAGUAY S.A
A14: 2655 | B14: EQUILIBRA PERU S.A | C14: ..- | D14: 40017.64 | E14: 1246268741 | F14: 46165 | H14: 1 | I14: Adtives | J14: 10964 | K14: 46105 | L14: 1010200 | M14: VENDAS MERCADO EXTERNO | N14: 40 | O14: VENDA - NFE (EXPORTAÇÃO) | P14: EQUILIBRA PERU S.A | Q14: =$R$1-F14 -> -29 | R14: =_xlfn.XLOOKUP(P14,'Painel International'!$B:$B,'Painel International'!$B:$B,0) -> EQUILIBRA PERU S.A
... A17: 6370 | B17: YTL S.A. - PARAGUAI | C17: 00.000.000/0000-00 | D17: 172806.77 | E17: 1246272162 | F17: 46164 | H17: 1 | I17: Adtives | J17: 11193 | K17: 46134 | L17: 1010200 | M17: VENDAS MERCADO EXTERNO | N17: 40 | O17: VENDA - NFE (EXPORTAÇÃO) | P17: YTL S.A. - PARAGUAI | Q17: =$R$1-F17 -> -28 | R17: =_xlfn.XLOOKUP(P17,'Painel International'!$B:$B,'Painel International'!$B:$B,0) -> YTL S.A. - PARAGUAI
A18: 9708 | B18: CARGILL ARGENTINA | C18: ..- | D18: 687688.91 | E18: 1246271322 | F18: 46186 | I18: Não encontrado | J18: 11122 | K18: 46126 | L18: 1010200 | M18: VENDAS MERCADO EXTERNO | N18: 40 | O18: VENDA - NFE (EXPORTAÇÃO) | P18: CARGILL ARGENTINA | Q18: =$R$1-F18 -> -50 | R18: =_xlfn.XLOOKUP(P18,'Painel International'!$B:$B,'Painel International'!$B:$B,0) -> CARGILL ARGENTINA
A19: 9295 | B19: TECNOMYL S.A. - PARAGUAY | C19: 99.999.999/9999-99 | D19: 130127.06 | E19: 1246270982 | F19: 46152 | H19: 1 | I19: Adtives | J19: 11090 | K19: 46122 | L19: 1010200 | M19: VENDAS MERCADO EXTERNO | N19: 40 | O19: VENDA - NFE (EXPORTAÇÃO) | P19: TECNOMYL S.A. - PARAGUAY | Q19: =$R$1-F19 -> -16 | R19: =_xlfn.XLOOKUP(P19,'Painel International'!$B:$B,'Painel International'!$B:$B,0) -> TECNOMYL S.A. - PARAGUAY
A20: 9295 | B20: TECNOMYL S.A. - PARAGUAY | C20: 99.999.999/9999-99 | D20: 132185.95 | E20: 1246270621 | F20: 46150 | H20: 1 | I20: Adtives | J20: 11071 | K20: 46120 | L20: 1010200 | M20: VENDAS MERCADO EXTERNO | N20: 40 | O20: VENDA - NFE (EXPORTAÇÃO) | P20: TECNOMYL S.A. - PARAGUAY | Q20: =$R$1-F20 -> -14 | R20: =_xlfn.XLOOKUP(P20,'Painel International'!$B:$B,'Painel International'!$B:$B,0) -> TECNOMYL S.A. - PARAGUAY
A21: 9355 | B21: NITROFERT SAS - COLOMBIA | C21: ..- | D21: 604265.82 | E21: 1246264749 | F21: 46177 | H21: 1 | I21: Adtives | J21: 2768 | K21: 46077 | L21: 1010200 | M21: VENDAS MERCADO EXTERNO | N21: 40 | O21: VENDA - NFE (EXPORTAÇÃO) | P21: NITROFERT SAS - COLOMBIA | Q21: =$R$1-F21 -> -41 | R21: =_xlfn.XLOOKUP(P21,'Painel International'!$B:$B,'Painel International'!$B:$B,0) -> NITROFERT SAS - COLOMBIA
A22: 9355 | B22: NITROFERT SAS - COLOMBIA | C22: ..- | D22: 1191855.3 | E22: 1246265046 | F22: 46180 | H22: 1 | I22: Adtives | J22: 10762 | K22: 46078 | L22: 1010200 | M22: VENDAS MERCADO EXTERNO | N22: 40 | O22: VENDA - NFE (EXPORTAÇÃO) | P22: NITROFERT SAS - COLOMBIA | Q22: =$R$1-F22 -> -44 | R22: =_xlfn.XLOOKUP(P22,'Painel International'!$B:$B,'Painel International'!$B:$B,0) -> NITROFERT SAS - COLOMBIA
A23: 9355 | B23: NITROFERT SAS - COLOMBIA | C23: ..- | D23: 292178.84 | E23: 1246264769 | F23: 46180 | H23: 1 | I23: Adtives | J23: 10753 | K23: 46077 | L23: 1010200 | M23: VENDAS MERCADO EXTERNO | N23: 40 | O23: VENDA - NFE (EXPORTAÇÃO) | P23: NITROFERT SAS - COLOMBIA | Q23: =$R$1-F23 -> -44 | R23: =_xlfn.XLOOKUP(P23,'Painel International'!$B:$B,'Painel International'!$B:$B,0) -> NITROFERT SAS - COLOMBIA
A24: 9355 | B24: NITROFERT SAS - COLOMBIA | C24: ..- | D24: 1191855.3 | E24: 1246265200 | F24: 46177 | H24: 1 | I24: Adtives | J24: 2778 | K24: 46078 | L24: 1010200 | M24: VENDAS MERCADO EXTERNO | N24: 40 | O24: VENDA - NFE (EXPORTAÇÃO) | P24: NITROFERT SAS - COLOMBIA | Q24: =$R$1-F24 -> -41 | R24: =_xlfn.XLOOKUP(P24,'Painel International'!$B:$B,'Painel International'!$B:$B,0) -> NITROFERT SAS - COLOMBIA
A25: 11768 | B25: CERES PERU S.A | C25: ..- | D25: 86689.1 | E25: 1246264534 | F25: 46136 | H25: 1 | I25: Adtives | J25: 10744 | K25: 46076 | L25: 1010200 | M25: VENDAS MERCADO EXTERNO | N25: 40 | O25: VENDA - NFE (EXPORTAÇÃO) | P25: CERES PERU S.A | Q25: =$R$1-F25 -> 0 | R25: =_xlfn.XLOOKUP(P25,'Painel International'!$B:$B,'Painel International'!$B:$B,0) -> CERES PERU S.A
A26: 11770 | B26: FERTIBAL - EQUADOR | C26: ..- | D26: 14548.35 | E26: 1246263524 | F26: 46039 | H26: 1 | I26: Adtives | J26: 9853 | K26: 45959 | L26: 1010200 | M26: VENDAS MERCADO EXTERNO | N26: 40 | O26: VENDA - NFE (EXPORTAÇÃO) | P26: FERTIBAL - EQUADOR | Q26: =$R$1-F26 -> 97 | R26: =_xlfn.XLOOKUP(P26,'Painel International'!$B:$B,'Painel International'!$B:$B,0) -> FERTIBAL - EQUADOR
A27: 11580 | B27: AGRO MIL AGROS SAS - COLOMBIA | C27: ..- | D27: 76480.23 | E27: 1246268734 | F27: 46440 | H27: 1 | I27: Adtives | J27: 2837 | K27: 46105 | L27: 1010200 | M27: VENDAS MERCADO EXTERNO | N27: 40 | O27: VENDA - NFE (EXPORTAÇÃO) | P27: AGRO MIL AGROS SAS - COLOMBIA | Q27: =$R$1-F27 -> -304 | R27: =_xlfn.XLOOKUP(P27,'Painel International'!$B:$B,'Painel International'!$B:$B,0) -> AGRO MIL AGROS SAS - COLOMBIA
A28: 13330 | B28: ORGANITEC - PARAGUAY | C28: 800.909.976- | D28: 853.24 | E28: 1246272264 | F28: 46148 | I28: Não encontrado | J28: 11057 | K28: 46118 | L28: 1010200 | M28: VENDAS MERCADO EXTERNO | N28: 40 | O28: VENDA - NFE (EXPORTAÇÃO) | P28: ORGANITEC - PARAGUAY | Q28: =$R$1-F28 -> -12 | R28: =_xlfn.XLOOKUP(P28,'Painel International'!$B:$B,'Painel International'!$B:$B,0) -> ORGANITEC - PARAGUAY
A29: 13330 | B29: ORGANITEC - PARAGUAY | C29: 800.909.976- | D29: 527.28 | E29: 1246238356 | F29: 45927 | I29: Não encontrado | J29: 9092 | K29: 45897 | L29: 1010200 | M29: VENDAS MERCADO EXTERNO | N29: 40 | O29: VENDA - NFE (EXPORTAÇÃO) | P29: ORGANITEC - PARAGUAY | Q29: =$R$1-F29 -> 209 | R29: =_xlfn.XLOOKUP(P29,'Painel International'!$B:$B,'Painel International'!$B:$B,0) -> ORGANITEC - PARAGUAY
A30: 15508 | B30: SOMAX - PARAGUAI | C30: 800.553.179- | D30: 137716.91 | E30: 1246270312 | F30: 46148 | H30: 1 | I30: Adtives | J30: 11050 | K30: 46118 | L30: 1010200 | M30: VENDAS MERCADO EXTERNO | N30: 40 | O30: VENDA - NFE (EXPORTAÇÃO) | P30: SOMAX - PARAGUAI | Q30: =$R$1-F30 -> -12 | R30: =_xlfn.XLOOKUP(P30,'Painel International'!$B:$B,'Painel International'!$B:$B,0) -> SOMAX - PARAGUAI
A31: 15543 | B31: GOTLAND EQUADOR (SOLINAG) | C31: 19.512.950/9001- | D31: 45718.46 | E31: 1246264533 | F31: 46181 | I31: Não encontrado | J31: 10745 | K31: 46076 | L31: 1010200 | M31: VENDAS MERCADO EXTERNO | N31: 40 | O31: VENDA - NFE (EXPORTAÇÃO) | P31: GOTLAND EQUADOR (SOLINAG) | Q31: =$R$1-F31 -> -45 | R31: =_xlfn.XLOOKUP(P31,'Painel International'!$B:$B,'Painel International'!$B:$B,0) -> GOTLAND EQUADOR (SOLINAG)
Q32: =$R$1-F32 -> 46136 | R32: =_xlfn.XLOOKUP(P32,'Painel International'!$B:$B,'Painel International'!$B:$B,0) -> 0
Q33: =$R$1-F33 -> 46136 | R33: =_xlfn.XLOOKUP(P33,'Painel International'!$B:$B,'Painel International'!$B:$B,0) -> 0
Q34: =$R$1-F34 -> 46136 | R34: =_xlfn.XLOOKUP(P34,'Painel International'!$B:$B,'Painel International'!$B:$B,0) -> 0
Q35: =$R$1-F35 -> 46136 | R35: =_xlfn.XLOOKUP(P35,'Painel International'!$B:$B,'Painel International'!$B:$B,0) -> 0
Q36: =$R$1-F36 -> 46136 | R36: =_xlfn.XLOOKUP(P36,'Painel International'!$B:$B,'Painel International'!$B:$B,0) -> 0
Q37: =$R$1-F37 -> 46136 | R37: =_xlfn.XLOOKUP(P37,'Painel International'!$B:$B,'Painel International'!$B:$B,0) -> 0
Q38: =$R$1-F38 -> 46136 | R38: =_xlfn.XLOOKUP(P38,'Painel International'!$B:$B,'Painel International'!$B:$B,0) -> 0
Q39: =$R$1-F39 -> 46136 | R39: =_xlfn.XLOOKUP(P39,'Painel International'!$B:$B,'Painel International'!$B:$B,0) -> 0
Q40: =$R$1-F40 -> 46136 | R40: =_xlfn.XLOOKUP(P40,'Painel International'!$B:$B,'Painel International'!$B:$B,0) -> 0
Q41: =$R$1-F41 -> 46136 | R41: =_xlfn.XLOOKUP(P41,'Painel International'!$B:$B,'Painel International'!$B:$B,0) -> 0

Sheet Data Fertilizers
D1: =SUBTOTAL(9,D3:D995) -> 27543516 | R1: 46135
A2: CODPARC | B2: NOMEPARC | C2: CNPJ | D2: Valor | E2: NUFIN | F2: DTVENC | G2: DHBAIXA | H2: AD_BU | I2: NOME_BU | J2: NUMNOTA | K2: DTENTSAI | L2: CODNAT | M2: DESCRNAT | N2: CODTIPOPER | O2: OPERACAO | P2: GRUPO | Q2: Dias vencidos
A3: 9824 | B3: TRIANGULO AGRO CONSULTORIA C/PRESCISAO | C3: 11.827.200/0001-39 | D3: 69971.2 | E3: 1246154720 | F3: 45738 | H3: 2 | I3: Fertilizers | J3: 4113 | K3: 45475 | L3: 1010100 | M3: VENDAS MERCADO INTERNO | N3: 161 | O3: VENDA PROD. INDUSTRIALIZADO - NFE | P3: GRUPO TRIANGULO AGRO | Q3: =$R$1-F3 -> 397 | R3: =_xlfn.XLOOKUP(P3,'Painel Fertilizers'!$B:$B,'Painel Fertilizers'!$B:$B,0) -> GRUPO TRIANGULO AGRO
A4: 9824 | B4: TRIANGULO AGRO CONSULTORIA C/PRESCISAO | C4: 11.827.200/0001-39 | D4: 60656 | E4: 1246154724 | F4: 45738 | H4: 2 | I4: Fertilizers | J4: 4114 | K4: 45475 | L4: 1010100 | M4: VENDAS MERCADO INTERNO | N4: 161 | O4: VENDA PROD. INDUSTRIALIZADO - NFE | P4: GRUPO TRIANGULO AGRO | Q4: =$R$1-F4 -> 397 | R4: =_xlfn.XLOOKUP(P4,'Painel Fertilizers'!$B:$B,'Painel Fertilizers'!$B:$B,0) -> GRUPO TRIANGULO AGRO
A5: 10371 | B5: TRIANGULO AGRO – POMPEU | C5: 11.827.200/0004-81 | D5: 56674.77 | E5: 1246161059 | F5: 45736 | H5: 2 | I5: Fertilizers | J5: 4516 | K5: 45502 | L5: 1010100 | M5: VENDAS MERCADO INTERNO | N5: 161 | O5: VENDA PROD. INDUSTRIALIZADO - NFE | P5: GRUPO TRIANGULO AGRO | Q5: =$R$1-F5 -> 399 | R5: =_xlfn.XLOOKUP(P5,'Painel Fertilizers'!$B:$B,'Painel Fertilizers'!$B:$B,0) -> GRUPO TRIANGULO AGRO
A6: 10371 | B6: TRIANGULO AGRO – POMPEU | C6: 11.827.200/0004-81 | D6: 50007.15 | E6: 1246161057 | F6: 45736 | H6: 2 | I6: Fertilizers | J6: 4515 | K6: 45502 | L6: 1010100 | M6: VENDAS MERCADO INTERNO | N6: 161 | O6: VENDA PROD. INDUSTRIALIZADO - NFE | P6: GRUPO TRIANGULO AGRO | Q6: =$R$1-F6 -> 399 | R6: =_xlfn.XLOOKUP(P6,'Painel Fertilizers'!$B:$B,'Painel Fertilizers'!$B:$B,0) -> GRUPO TRIANGULO AGRO
A7: 11207 | B7: S M AGRO | C7: 08.685.699/0001-82 | D7: 153825.49 | E7: 1246067872 | F7: 45412 | H7: 2 | I7: Fertilizers | J7: 20696 | K7: 44973 | L7: 1010100 | M7: VENDAS MERCADO INTERNO | N7: 161 | O7: VENDA PROD. INDUSTRIALIZADO - NFE | P7: GRUPO LEANDRO SARTI | Q7: =$R$1-F7 -> 723 | R7: =_xlfn.XLOOKUP(P7,'Painel Fertilizers'!$B:$B,'Painel Fertilizers'!$B:$B,0) -> GRUPO LEANDRO SARTI
A8: 11207 | B8: S M AGRO | C8: 08.685.699/0001-82 | D8: 118231.86 | E8: 1246074301 | F8: 45412 | H8: 2 | I8: Fertilizers | J8: 21005 | K8: 45015 | L8: 1010100 | M8: VENDAS MERCADO INTERNO | N8: 161 | O8: VENDA PROD. INDUSTRIALIZADO - NFE | P8: GRUPO LEANDRO SARTI | Q8: =$R$1-F8 -> 723 | R8: =_xlfn.XLOOKUP(P8,'Painel Fertilizers'!$B:$B,'Painel Fertilizers'!$B:$B,0) -> GRUPO LEANDRO SARTI
A9: 11207 | B9: S M AGRO | C9: 08.685.699/0001-82 | D9: 91167.15 | E9: 1246075550 | F9: 45412 | H9: 2 | I9: Fertilizers | J9: 21053 | K9: 45022 | L9: 1010100 | M9: VENDAS MERCADO INTERNO | N9: 161 | O9: VENDA PROD. INDUSTRIALIZADO - NFE | P9: GRUPO LEANDRO SARTI | Q9: =$R$1-F9 -> 723 | R9: =_xlfn.XLOOKUP(P9,'Painel Fertilizers'!$B:$B,'Painel Fertilizers'!$B:$B,0) -> GRUPO LEANDRO SARTI
A10: 11207 | B10: S M AGRO | C10: 08.685.699/0001-82 | D10: 43771.16 | E10: 1246094423 | F10: 45423 | H10: 2 | I10: Fertilizers | J10: 356 | K10: 45133 | L10: 1010100 | M10: VENDAS MERCADO INTERNO | N10: 161 | O10: VENDA PROD. INDUSTRIALIZADO - NFE | P10: GRUPO LEANDRO SARTI | Q10: =$R$1-F10 -> 712 | R10: =_xlfn.XLOOKUP(P10,'Painel Fertilizers'!$B:$B,'Painel Fertilizers'!$B:$B,0) -> GRUPO LEANDRO SARTI
A11: 11207 | B11: S M AGRO | C11: 08.685.699/0001-82 | D11: 44760.26 | E11: 1246092027 | F11: 45504 | H11: 2 | I11: Fertilizers | J11: 138 | K11: 45119 | L11: 1010100 | M11: VENDAS MERCADO INTERNO | N11: 161 | O11: VENDA PROD. INDUSTRIALIZADO - NFE | P11: GRUPO LEANDRO SARTI | Q11: =$R$1-F11 -> 631 | R11: =_xlfn.XLOOKUP(P11,'Painel Fertilizers'!$B:$B,'Painel Fertilizers'!$B:$B,0) -> GRUPO LEANDRO SARTI
A12: 11207 | B12: S M AGRO | C12: 08.685.699/0001-82 | D12: 43771.16 | E12: 1246093362 | F12: 45417 | H12: 2 | I12: Fertilizers | J12: 253 | K12: 45127 | L12: 1010100 | M12: VENDAS MERCADO INTERNO | N12: 161 | O12: VENDA PROD. INDUSTRIALIZADO - NFE | P12: GRUPO LEANDRO SARTI | Q12: =$R$1-F12 -> 718 | R12: =_xlfn.XLOOKUP(P12,'Painel Fertilizers'!$B:$B,'Painel Fertilizers'!$B:$B,0) -> GRUPO LEANDRO SARTI
A13: 11207 | B13: S M AGRO | C13: 08.685.699/0001-82 | D13: 47925.4 | E13: 1246094864 | F13: 45544 | H13: 2 | I13: Fertilizers | J13: 407 | K13: 45135 | L13: 1010100 | M13: VENDAS MERCADO INTERNO | N13: 161 | O13: VENDA PROD. INDUSTRIALIZADO - NFE | P13: GRUPO LEANDRO SARTI | Q13: =$R$1-F13 -> 591 | R13: =_xlfn.XLOOKUP(P13,'Painel Fertilizers'!$B:$B,'Painel Fertilizers'!$B:$B,0) -> GRUPO LEANDRO SARTI
A14: 11207 | B14: S M AGRO | C14: 08.685.699/0001-82 | D14: 106301.38 | E14: 1246094863 | F14: 45425 | H14: 2 | I14: Fertilizers | J14: 406 | K14: 45135 | L14: 1010100 | M14: VENDAS MERCADO INTERNO | N14: 161 | O14: VENDA PROD. INDUSTRIALIZADO - NFE | P14: GRUPO LEANDRO SARTI | Q14: =$R$1-F14 -> 710 | R14: =_xlfn.XLOOKUP(P14,'Painel Fertilizers'!$B:$B,'Painel Fertilizers'!$B:$B,0) -> GRUPO LEANDRO SARTI
... A281: 15917 | B281: MINAS FARM | C281: 41.841.473/0001-07 | D281: 6293.7 | E281: 1246241843 | F281: 46143 | H281: 2 | I281: Fertilizers | J281: 9607 | K281: 45937 | L281: 1010100 | M281: VENDAS MERCADO INTERNO | N281: 161 | O281: VENDA PROD. INDUSTRIALIZADO - NFE | P281: MINAS FARM | Q281: =$R$1-F281 -> -8 | R281: =_xlfn.XLOOKUP(P281,'Painel Fertilizers'!$B:$B,'Painel Fertilizers'!$B:$B,0) -> MINAS FARM
Q282: =$R$1-F282 -> 46135 | R282: =_xlfn.XLOOKUP(P282,'Painel Fertilizers'!$B:$B,'Painel Fertilizers'!$B:$B,0) -> 0
Q283: =$R$1-F283 -> 46135 | R283: =_xlfn.XLOOKUP(P283,'Painel Fertilizers'!$B:$B,'Painel Fertilizers'!$B:$B,0) -> 0
Q284: =$R$1-F284 -> 46135 | R284: =_xlfn.XLOOKUP(P284,'Painel Fertilizers'!$B:$B,'Painel Fertilizers'!$B:$B,0) -> 0
Q285: =$R$1-F285 -> 46135 | R285: =_xlfn.XLOOKUP(P285,'Painel Fertilizers'!$B:$B,'Painel Fertilizers'!$B:$B,0) -> 0
Q286: =$R$1-F286 -> 46135 | R286: =_xlfn.XLOOKUP(P286,'Painel Fertilizers'!$B:$B,'Painel Fertilizers'!$B:$B,0) -> 0
Q287: =$R$1-F287 -> 46135 | R287: =_xlfn.XLOOKUP(P287,'Painel Fertilizers'!$B:$B,'Painel Fertilizers'!$B:$B,0) -> 0
Q288: =$R$1-F288 -> 46135 | R288: =_xlfn.XLOOKUP(P288,'Painel Fertilizers'!$B:$B,'Painel Fertilizers'!$B:$B,0) -> 0
Q289: =$R$1-F289 -> 46135 | R289: =_xlfn.XLOOKUP(P289,'Painel Fertilizers'!$B:$B,'Painel Fertilizers'!$B:$B,0) -> 0
Q290: =$R$1-F290 -> 46135 | R290: =_xlfn.XLOOKUP(P290,'Painel Fertilizers'!$B:$B,'Painel Fertilizers'!$B:$B,0) -> 0
Q291: =$R$1-F291 -> 46135 | R291: =_xlfn.XLOOKUP(P291,'Painel Fertilizers'!$B:$B,'Painel Fertilizers'!$B:$B,0) -> 0
Q292: =$R$1-F292 -> 46135 | R292: =_xlfn.XLOOKUP(P292,'Painel Fertilizers'!$B:$B,'Painel Fertilizers'!$B:$B,0) -> 0
Q293: =$R$1-F293 -> 46135 | R293: =_xlfn.XLOOKUP(P293,'Painel Fertilizers'!$B:$B,'Painel Fertilizers'!$B:$B,0) -> 0
... Q392: =$R$1-F392 -> 46135 | R392: =_xlfn.XLOOKUP(P392,'Painel Fertilizers'!$B:$B,'Painel Fertilizers'!$B:$B,0) -> 0

Sheet Clientes Consolidado
C1: 46139 | H1: =SUBTOTAL(9,H4:H1048576) -> 62183702 | I1: =SUBTOTAL(9,I4:I1048576) -> 584434.79 | J1: =SUBTOTAL(9,J4:J1048576) -> 49440 | K1: =SUBTOTAL(9,K4:K1048576) -> 0 | L1: =SUBTOTAL(9,L4:L1048576) -> 14548.35 | M1: =SUBTOTAL(9,M4:M1048576) -> 0 | N1: =SUBTOTAL(9,N4:N1048576) -> 1438605.4 | O1: =SUBTOTAL(9,O4:O1048576) -> 21350077 | ... Y1: =SUBTOTAL(9,Y4:Y1048576) -> 10608761 | AB1: =SUBTOTAL(9,AB4:AB1048576) -> 87572500 | AH1: =SUBTOTAL(9,AH4:AH1048576) -> 25388799 | AJ1: =P1/H1 -> 0.3769011
I2: Aging Overdue | R2: Aging Not Due | AJ2: Treasury Risk Status
A3: x | B3: BU | C3: CUSTOMER | D3: RATING | F3: Approved Credit | G3: Credit Balance | H3: Total AR | I3: 1-30 Days | J3: 31-60 Days | K3: 61-90 Days | L3: 91-120 Days | M3: 121-180 Days | N3: 181-360 Days | O3: Above 360 Days | P3: Overdue | Q3: Not Due | R3: 1-30 Days | S3: 31-60 Days | T3: 61-90 Days | U3: 91-120 Days | V3: 121-180 Days | W3: 181-360 Days | X3: Above 360 Days | Y3: Bad debt provision | Z3: x | AA3: x | AB3: Credit Insurance | AC3: Guarantee Value | AD3: Type | AE3: Due Date | AF3: Tenor | AG3: x | AH3: Open Exposure | AI3: x | AJ3: Probable | AK3: Possible | AL3: Rare
B4: Fertilizer / Litigation | C4: CENTRAL DO ADUBO COM E REPRESENTACAO LTD | D4: 0 | F4: 0 | G4: -7560727.8 | H4: 7560727.8 | I4: 0 | J4: 0 | K4: 0 | L4: 0 | M4: 0 | N4: 0 | O4: 7560727.8 | P4: 7560727.8 | Q4: 0 | R4: 0 | S4: 0 | T4: 0 | U4: 0 | V4: 0 | W4: 0 | X4: 0 | Y4: 0 | AB4: 0 | AH4: =AB4-H4 -> -7560727.8
B5: Additive | C5: GRUPO MOSAIC FERTILIZANTES P K LTDA | D5: B | F5: 10000000 | G5: 3010042.9 | H5: 6989957.1 | I5: 0 | J5: 0 | K5: 0 | L5: 0 | M5: 0 | N5: 0 | O5: 0 | P5: 0 | Q5: 6989957.1 | R5: 1127577.6 | S5: 2992083 | T5: 2644466.1 | U5: 225830.4 | V5: 0 | W5: 0 | X5: 0 | Y5: 16500 | AB5: 10000000 | AH5: =AB5-H5 -> 3010042.9 | AN5: Additive Intl.
B6: Additive | C6: GRUPO YARA | D6: B | F6: 6000000 | G6: 2042616.9 | H6: 3957383.1 | I6: 0 | J6: 0 | K6: 0 | L6: 0 | M6: 0 | N6: 0 | O6: 5626.32 | P6: 5626.32 | Q6: 3951756.8 | R6: 2997325.2 | S6: 954431.55 | T6: 0 | U6: 0 | V6: 0 | W6: 0 | X6: 0 | Y6: 63226.32 | AB6: 6000000 | AH6: =AB6-H6 -> 2042616.9 | AN6: Additive
B7: Additive | C7: GRUPO MOSAIC FERTILIZANTES DO BRASIL | D7: 0 | F7: 20000000 | G7: 16128759 | H7: 3871241.1 | I7: 0 | J7: 0 | K7: 0 | L7: 0 | M7: 0 | N7: 64.2 | O7: 16754.72 | P7: 16818.92 | Q7: 3854422.2 | R7: 1696548.6 | S7: 1268599.2 | T7: 852594.6 | U7: 36679.8 | V7: 0 | W7: 0 | X7: 0 | Y7: 84763.766 | AB7: 15000000 | AH7: =AB7-H7 -> 11128759 | AN7: Fertilizer
B8: Additive | C8: GRUPO UNIFERTIL | D8: B | F8: 3500000 | G8: -173754.8 | H8: 3673754.8 | I8: 0 | J8: 0 | K8: 0 | L8: 0 | M8: 0 | N8: 0 | O8: 0 | P8: 0 | Q8: 3673754.8 | R8: 956954.8 | S8: 2716800 | T8: 0 | U8: 0 | V8: 0 | W8: 0 | X8: 0 | Y8: 0 | AB8: 4500000 | AH8: =AB8-H8 -> 826245.2
B9: Additive Intl. | C9: NITROFERT SAS - COLOMBIA | D9: 0 | F9: 0 | G9: -3280155.2 | H9: 3280155.2 | I9: 0 | J9: 0 | K9: 0 | L9: 0 | M9: 0 | N9: 0 | O9: 0 | P9: 0 | Q9: 3280155.2 | R9: 0 | S9: 3280155.2 | T9: 0 | U9: 0 | V9: 0 | W9: 0 | X9: 0 | Y9: 0 | AB9: 0 | AH9: =AB9-H9 -> -3280155.2 | AN9: Fertilizer / Litigation
B10: Fertilizer / Litigation | C10: GRUPO LEANDRO SARTI | D10: 0 | F10: 0 | G10: -3088531.1 | H10: 3088531.1 | I10: 0 | J10: 0 | K10: 0 | L10: 0 | M10: 0 | N10: 0 | O10: 3088531.1 | P10: 3088531.1 | Q10: 0 | R10: 0 | S10: 0 | T10: 0 | U10: 0 | V10: 0 | W10: 0 | X10: 0 | Y10: 3088531.1 | AB10: 0 | AH10: =AB10-H10 -> -3088531.1 | AN10: Additive / Litigation
B11: Fertilizer / Litigation | C11: AGRO BERALDO | D11: 0 | F11: 0 | G11: -3044850.9 | H11: 3044850.9 | I11: 0 | J11: 0 | K11: 0 | L11: 0 | M11: 0 | N11: 0 | O11: 3044850.9 | P11: 3044850.9 | Q11: 0 | R11: 0 | S11: 0 | T11: 0 | U11: 0 | V11: 0 | W11: 0 | X11: 0 | Y11: 3044850.9 | AB11: 0 | AH11: =AB11-H11 -> -3044850.9
B12: Fertilizer / Litigation | C12: TERRA FERTIL - MACHADO | D12: 0 | F12: 0 | G12: -2492842.1 | H12: 2492842.1 | I12: 0 | J12: 0 | K12: 0 | L12: 0 | M12: 0 | N12: 0 | O12: 2492842.1 | P12: 2492842.1 | Q12: 0 | R12: 0 | S12: 0 | T12: 0 | U12: 0 | V12: 0 | W12: 0 | X12: 0 | Y12: 0 | AB12: 0 | AH12: =AB12-H12 -> -2492842.1
B13: Fertilizer / Litigation | C13: MOGIANA TECNO AGRO | D13: 0 | F13: 0 | G13: -1863200.9 | H13: 1863200.9 | I13: 0 | J13: 0 | K13: 0 | L13: 0 | M13: 0 | N13: 0 | O13: 1863200.9 | P13: 1863200.9 | Q13: 0 | R13: 0 | S13: 0 | T13: 0 | U13: 0 | V13: 0 | W13: 0 | X13: 0 | Y13: 1863200.9 | AB13: 0 | AH13: =AB13-H13 -> -1863200.9
B14: Fertilizer / Litigation | C14: CASA DAS SEMENTES | D14: 0 | F14: 0 | G14: -1702848.7 | H14: 1702848.7 | I14: 0 | J14: 0 | K14: 0 | L14: 0 | M14: 0 | N14: 0 | O14: 1702848.7 | P14: 1702848.7 | Q14: 0 | R14: 0 | S14: 0 | T14: 0 | U14: 0 | V14: 0 | W14: 0 | X14: 0 | Y14: 1702848.7 | AB14: 0 | AH14: =AB14-H14 -> -1702848.7
B15: Fertilizer | C15: AGROVIVA | D15: B | F15: 1800000 | G15: 599809.58 | H15: 1200190.4 | I15: 0 | J15: 0 | K15: 0 | L15: 0 | M15: 0 | N15: 0 | O15: 0 | P15: 0 | Q15: 1200190.4 | R15: 274733.36 | S15: 0 | T15: 0 | U15: 0 | V15: 925457.06 | W15: 0 | X15: 0 | Y15: 0 | AB15: 500000 | AH15: =AB15-H15 -> -700190.42
B16: Additive | C16: FECOAGRO FEDERACAO DAS COOPERATIVAS | D16: B | F16: 3000000 | G16: 1897185.2 | H16: 1102814.8 | I16: 0 | J16: 0 | K16: 0 | L16: 0 | M16: 0 | N16: 0 | O16: 0 | P16: 0 | Q16: 1102814.8 | R16: 1102814.8 | S16: 0 | T16: 0 | U16: 0 | V16: 0 | W16: 0 | X16: 0 | Y16: 0 | AB16: 3000000 | AH16: =AB16-H16 -> 1897185.2
B17: Additive | C17: STRATOS/MOSAIC - ROSARIO DO CATETE | D17: A | F17: 1500000 | G17: 437150.4 | H17: 1062849.6 | I17: 0 | J17: 0 | K17: 0 | L17: 0 | M17: 0 | N17: 0 | O17: 0 | P17: 0 | Q17: 1062849.6 | R17: 426003.6 | S17: 70705.6 | T17: 566140.4 | U17: 0 | V17: 0 | W17: 0 | X17: 0 | Y17: 1800 | AB17: 1500000 | AH17: =AB17-H17 -> 437150.4
B18: Fertilizer / Litigation | C18: FAZENDA ARCOS SÃO JOÃO | D18: 0 | F18: 0 | G18: -988506.24 | H18: 988506.24 | I18: 0 | J18: 0 | K18: 0 | L18: 0 | M18: 0 | N18: 988506.24 | O18: 0 | P18: 988506.24 | Q18: 0 | R18: 0 | S18: 0 | T18: 0 | U18: 0 | V18: 0 | W18: 0 | X18: 0 | Y18: 29655.187 | AB18: 0 | AH18: =AB18-H18 -> -988506.24
B19: Fertilizer / Litigation | C19: CBM FERTILIZANTES | D19: 0 | F19: 0 | G19: -876011.75 | H19: 876011.75 | I19: 0 | J19: 0 | K19: 0 | L19: 0 | M19: 0 | N19: 0 | O19: 876011.75 | P19: 876011.75 | Q19: 0 | R19: 0 | S19: 0 | T19: 0 | U19: 0 | V19: 0 | W19: 0 | X19: 0 | Y19: 0 | AB19: 0 | AH19: =AB19-H19 -> -876011.75
B20: Fertilizer | C20: GA AGRONEGOCIOS | D20: C | F20: 500000 | G20: -315729 | H20: 815729 | I20: 0 | J20: 0 | K20: 0 | L20: 0 | M20: 0 | N20: 0 | O20: 0 | P20: 0 | Q20: 815729 | R20: 815729 | S20: 0 | T20: 0 | U20: 0 | V20: 0 | W20: 0 | X20: 0 | Y20: 0 | AB20: 500000 | AH20: =AB20-H20 -> -315729
B21: Additive | C21: EUROCHEM SERRA DO SALITRE | D21: 0 | F21: 2500000 | G21: 1706188.3 | H21: 793811.7 | I21: 153506.1 | J21: 0 | K21: 0 | L21: 0 | M21: 0 | N21: 0 | O21: 0 | P21: 153506.1 | Q21: 640305.6 | R21: 640305.6 | S21: 0 | T21: 0 | U21: 0 | V21: 0 | W21: 0 | X21: 0 | Y21: 0 | AB21: 0 | AH21: =AB21-H21 -> -793811.7
B22: Additive | C22: GRUPO HINOVE | D22: 0 | F22: 0 | G22: -775264 | H22: 775264 | I22: 0 | J22: 0 | K22: 0 | L22: 0 | M22: 0 | N22: 0 | O22: 0 | P22: 0 | Q22: 775264 | R22: 171254.1 | S22: 459685.9 | T22: 144324 | U22: 0 | V22: 0 | W22: 0 | X22: 0 | Y22: 0 | AB22: 0 | AH22: =AB22-H22 -> -775264
B23: Fertilizer | C23: CONNTACTA AGRONEGOCIOS | D23: 0 | E23: 180 | F23: 0 | G23: -739540.06 | H23: 739540.06 | I23: 0 | J23: 0 | K23: 0 | L23: 0 | M23: 0 | N23: 0 | O23: 0 | P23: 0 | Q23: 739540.06 | R23: 644571.16 | S23: 94968.9 | T23: 0 | U23: 0 | V23: 0 | W23: 0 | X23: 0 | Y23: 0 | AB23: 500000 | AH23: =AB23-H23 -> -239540.06
B24: Fertilizer | C24: ADUFERTIL JUNDIAI | D24: B | E24: 180 | F24: 3000000 | G24: 2265046.5 | H24: 734953.47 | I24: 0 | J24: 0 | K24: 0 | L24: 0 | M24: 0 | N24: 0 | O24: 0 | P24: 0 | Q24: 734953.47 | R24: 0 | S24: 332685.28 | T24: 402268.19 | U24: 0 | V24: 0 | W24: 0 | X24: 0 | Y24: 0 | AB24: 3000000 | AH24: =AB24-H24 -> 2265046.5
B25: Additive Intl. | C25: CARGILL ARGENTINA | D25: A | F25: 1100000 | G25: 412311.09 | H25: 687688.91 | I25: 0 | J25: 0 | K25: 0 | L25: 0 | M25: 0 | N25: 0 | O25: 0 | P25: 0 | Q25: 687688.91 | R25: 0 | S25: 687688.91 | T25: 0 | U25: 0 | V25: 0 | W25: 0 | X25: 0 | Y25: 0 | AB25: 1100000 | AH25: =AB25-H25 -> 412311.09
B26: Additive | C26: FOSNOR - LUIS EDUARDO MAGALHAES | D26: B | F26: 2600000 | G26: 2076372.5 | H26: 523627.5 | I26: 0 | J26: 0 | K26: 0 | L26: 0 | M26: 0 | N26: 0 | O26: 0 | P26: 0 | Q26: 523627.5 | R26: 523627.5 | S26: 0 | T26: 0 | U26: 0 | V26: 0 | W26: 0 | X26: 0 | Y26: 0 | AB26: 2600000 | AH26: =AB26-H26 -> 2076372.5
B27: Additive | C27: ULTRAFERTIL | D27: B | F27: 1500000 | G27: 983388.6 | H27: 516611.4 | I27: 0 | J27: 0 | K27: 0 | L27: 0 | M27: 0 | N27: 0 | O27: 0 | P27: 0 | Q27: 516611.4 | R27: 516611.4 | S27: 0 | T27: 0 | U27: 0 | V27: 0 | W27: 0 | X27: 0 | Y27: 0 | AB27: 1500000 | AH27: =AB27-H27 -> 983388.6
B28: Additive | C28: GRUPO CIBRA | D28: 0 | F28: 6900000 | G28: 6388978 | H28: 511022 | I28: 0 | J28: 0 | K28: 0 | L28: 0 | M28: 0 | N28: 0 | O28: 0 | P28: 0 | Q28: 511022 | R28: 511022 | S28: 0 | T28: 0 | U28: 0 | V28: 0 | W28: 0 | X28: 0 | Y28: 1200 | AB28: 2315000 | AH28: =AB28-H28 -> 1803978
B29: Additive | C29: GRUPO FERTILIZ TOCANTINS | D29: 0 | F29: 10000000 | G29: 9490920.4 | H29: 509079.6 | I29: 0 | J29: 0 | K29: 0 | L29: 0 | M29: 0 | N29: 0 | O29: 0 | P29: 0 | Q29: 509079.6 | R29: 169290.6 | S29: 339789 | T29: 0 | U29: 0 | V29: 0 | W29: 0 | X29: 0 | Y29: 0 | AB29: 0 | AH29: =AB29-H29 -> -509079.6
B30: Fertilizer | C30: GRUPO TAKI AGRO | D30: B | E30: 270 | F30: 1500000 | G30: 1001781.6 | H30: 498218.4 | I30: 0 | J30: 0 | K30: 0 | L30: 0 | M30: 0 | N30: 0 | O30: 0 | P30: 0 | Q30: 498218.4 | R30: 498218.4 | S30: 0 | T30: 0 | U30: 0 | V30: 0 | W30: 0 | X30: 0 | Y30: 0 | AB30: 1000000 | AH30: =AB30-H30 -> 501781.6
B31: Additive Intl. | C31: BUNGE PARAGUAY S.A | D31: B | F31: 962500 | G31: 503291.64 | H31: 459208.36 | I31: 157607.13 | J31: 0 | K31: 0 | L31: 0 | M31: 0 | N31: 0 | O31: 0 | P31: 157607.13 | Q31: 301601.23 | R31: 301601.23 | S31: 0 | T31: 0 | U31: 0 | V31: 0 | W31: 0 | X31: 0 | Y31: 0 | AB31: 962500 | AH31: =AB31-H31 -> 503291.64
B32: Additive Intl. | C32: AGROBROKERS - COLÔMBIA | D32: 0 | F32: 0 | G32: -449507.69 | H32: 449507.69 | I32: 0 | J32: 0 | K32: 0 | L32: 0 | M32: 0 | N32: 449507.69 | O32: 0 | P32: 449507.69 | Q32: 0 | R32: 0 | S32: 0 | T32: 0 | U32: 0 | V32: 0 | W32: 0 | X32: 0 | Y32: 13485.231 | AB32: 0 | AH32: =AB32-H32 -> -449507.69
B33: Fertilizer | C33: TAKI AGRO - SOCORRO | D33: 0 | E33: 180 | F33: 0 | G33: -419948 | H33: 419948 | I33: 235730.06 | J33: 0 | K33: 0 | L33: 0 | M33: 0 | N33: 0 | O33: 0 | P33: 235730.06 | Q33: 184217.94 | R33: 184217.94 | S33: 0 | T33: 0 | U33: 0 | V33: 0 | W33: 0 | X33: 0 | Y33: 0 | AB33: 0 | AH33: =AB33-H33 -> -419948
B34: Additive | C34: ADUFERTIL JUNDIAI | D34: B | F34: 3000000 | G34: 2589143.5 | H34: 410856.52 | I34: 0 | J34: 0 | K34: 0 | L34: 0 | M34: 0 | N34: 0 | O34: 0 | P34: 0 | Q34: 410856.52 | R34: 0 | S34: 410856.52 | T34: 0 | U34: 0 | V34: 0 | W34: 0 | X34: 0 | Y34: 0 | AB34: 3000000 | AH34: =AB34-H34 -> 2589143.5
B35: Additive Intl. | C35: FERMAGRI S.A - EQUADOR | D35: A | F35: 770000 | G35: 369912.15 | H35: 400087.85 | I35: 0 | J35: 0 | K35: 0 | L35: 0 | M35: 0 | N35: 0 | O35: 0 | P35: 0 | Q35: 400087.85 | R35: 224812.61 | S35: 175275.24 | T35: 0 | U35: 0 | V35: 0 | W35: 0 | X35: 0 | Y35: 0 | AB35: 770000 | AH35: =AB35-H35 -> 369912.15
B36: Additive Intl. | C36: YTL S.A. - PARAGUAI | D36: B | F36: 550000 | G36: 199990.55 | H36: 350009.45 | I36: 0 | J36: 0 | K36: 0 | L36: 0 | M36: 0 | N36: 0 | O36: 0 | P36: 0 | Q36: 350009.45 | R36: 350009.45 | S36: 0 | T36: 0 | U36: 0 | V36: 0 | W36: 0 | X36: 0 | Y36: 0 | AB36: 550000 | AH36: =AB36-H36 -> 199990.55
B37: Additive | C37: GRUPO JOSAPAR | D37: B | F37: 1000000 | G37: 664936 | H37: 335064 | I37: 0 | J37: 0 | K37: 0 | L37: 0 | M37: 0 | N37: 0 | O37: 0 | P37: 0 | Q37: 335064 | R37: 150024 | S37: 0 | T37: 0 | U37: 185040 | V37: 0 | W37: 0 | X37: 0 | Y37: 0 | AB37: 1000000 | AH37: =AB37-H37 -> 664936
B38: Fertilizer | C38: FAZENDA FERRADURA | D38: 0 | F38: 350000 | G38: 20672.09 | H38: 329327.91 | I38: 0 | J38: 0 | K38: 0 | L38: 0 | M38: 0 | N38: 0 | O38: 0 | P38: 0 | Q38: 329327.91 | R38: 329327.91 | S38: 0 | T38: 0 | U38: 0 | V38: 0 | W38: 0 | X38: 0 | Y38: 0 | AB38: 0 | AH38: =AB38-H38 -> -329327.91
B39: Fertilizer | C39: AGROREP. REPRESENTACOES AGRICOLAS | D39: B | E39: 180 | F39: 4000000 | G39: 3700357.9 | H39: 299642.08 | I39: 0 | J39: 0 | K39: 0 | L39: 0 | M39: 0 | N39: 0 | O39: 0 | P39: 0 | Q39: 299642.08 | R39: 0 | S39: 0 | T39: 0 | U39: 0 | V39: 0 | W39: 299642.08 | X39: 0 | Y39: 0 | AB39: 1000000 | AH39: =AB39-H39 -> 700357.92
B40: Additive | C40: AGROPECUARIA MARATA LTDA - MARUIM | D40: 0 | F40: 0 | G40: -290220 | H40: 290220 | I40: 0 | J40: 0 | K40: 0 | L40: 0 | M40: 0 | N40: 0 | O40: 0 | P40: 0 | Q40: 290220 | R40: 290220 | S40: 0 | T40: 0 | U40: 0 | V40: 0 | W40: 0 | X40: 0 | Y40: 0 | AB40: 0 | AH40: =AB40-H40 -> -290220
B41: Fertilizer | C41: VEGA AGRO | D41: 0 | E41: 360 | F41: 1500000 | G41: 1230944 | H41: 269056 | I41: 0 | J41: 0 | K41: 0 | L41: 0 | M41: 0 | N41: 0 | O41: 0 | P41: 0 | Q41: 269056 | R41: 137376 | S41: 0 | T41: 0 | U41: 0 | V41: 131680 | W41: 0 | X41: 0 | Y41: 0 | AB41: 660000 | AH41: =AB41-H41 -> 390944
B42: Additive Intl. | C42: TECNOMYL S.A. - PARAGUAY | D42: B | F42: 990000 | G42: 727686.99 | H42: 262313.01 | I42: 0 | J42: 0 | K42: 0 | L42: 0 | M42: 0 | N42: 0 | O42: 0 | P42: 0 | Q42: 262313.01 | R42: 262313.01 | S42: 0 | T42: 0 | U42: 0 | V42: 0 | W42: 0 | X42: 0 | Y42: 0 | AB42: 990000 | AH42: =AB42-H42 -> 727686.99
B43: Additive Intl. | C43: C I ACEPALMA SA - COLOMBIA | D43: A | F43: 660000 | G43: 409738.47 | H43: 250261.53 | I43: 0 | J43: 0 | K43: 0 | L43: 0 | M43: 0 | N43: 0 | O43: 0 | P43: 0 | Q43: 250261.53 | R43: 0 | S43: 250261.53 | T43: 0 | U43: 0 | V43: 0 | W43: 0 | X43: 0 | Y43: 0 | AB43: 660000 | AH43: =AB43-H43 -> 409738.47
B44: Additive | C44: GRUPO HERINGER | D44: B | F44: 3000000 | G44: 2751102.4 | H44: 248897.61 | I44: 0 | J44: 0 | K44: 0 | L44: 0 | M44: 0 | N44: 0 | O44: 0 | P44: 0 | Q44: 248897.61 | R44: 99167.6 | S44: 52960 | T44: 0 | U44: 0 | V44: 0 | W44: 0 | X44: 96770.01 | Y44: 0 | AB44: 0 | AH44: =AB44-H44 -> -248897.61
B45: Fertilizer / Litigation | C45: GRUPO TRIANGULO AGRO | D45: 0 | F45: 0 | G45: -237309.12 | H45: 237309.12 | I45: 0 | J45: 0 | K45: 0 | L45: 0 | M45: 0 | N45: 0 | O45: 237309.12 | P45: 237309.12 | Q45: 0 | R45: 0 | S45: 0 | T45: 0 | U45: 0 | V45: 0 | W45: 0 | X45: 0 | Y45: 237309.12 | AB45: 0 | AH45: =AB45-H45 -> -237309.12
B46: Additive / Litigation | C46: TERRA FERTILIZANTES LTDA - ARAXÁ | D46: 0 | F46: 0 | G46: -226233.6 | H46: 226233.6 | I46: 0 | J46: 0 | K46: 0 | L46: 0 | M46: 0 | N46: 0 | O46: 226233.6 | P46: 226233.6 | Q46: 0 | R46: 0 | S46: 0 | T46: 0 | U46: 0 | V46: 0 | W46: 0 | X46: 0 | Y46: 226233.6 | AB46: 0 | AH46: =AB46-H46 -> -226233.6
B47: Fertilizer | C47: TAKI AGRO - POUSO ALEGRE | D47: B | E47: 180 | F47: 500000 | G47: 277191.83 | H47: 222808.17 | I47: 0 | J47: 0 | K47: 0 | L47: 0 | M47: 0 | N47: 0 | O47: 0 | P47: 0 | Q47: 222808.17 | R47: 222808.17 | S47: 0 | T47: 0 | U47: 0 | V47: 0 | W47: 0 | X47: 0 | Y47: 0 | AB47: 300000 | AH47: =AB47-H47 -> 77191.83
B48: Additive / Litigation | C48: ITERUM - RONDONOPOLIS | D48: 0 | F48: 0 | G48: -213750 | H48: 213750 | I48: 0 | J48: 0 | K48: 0 | L48: 0 | M48: 0 | N48: 0 | O48: 213750 | P48: 213750 | Q48: 0 | R48: 0 | S48: 0 | T48: 0 | U48: 0 | V48: 0 | W48: 0 | X48: 0 | Y48: 213750 | AB48: 0 | AH48: =AB48-H48 -> -213750
B49: Additive | C49: FERTGROW S.A | D49: B | F49: 3500000 | G49: 3287599.9 | H49: 212400.1 | I49: 0 | J49: 0 | K49: 0 | L49: 0 | M49: 0 | N49: 0 | O49: 0 | P49: 0 | Q49: 212400.1 | R49: 212400.1 | S49: 0 | T49: 0 | U49: 0 | V49: 0 | W49: 0 | X49: 0 | Y49: 0 | AB49: 3500000 | AH49: =AB49-H49 -> 3287599.9
B50: Additive | C50: BENTONIT UNIAO - CAMPINA GRANDE | D50: B | F50: 700000 | G50: 488085 | H50: 211915 | I50: 0 | J50: 0 | K50: 0 | L50: 0 | M50: 0 | N50: 0 | O50: 0 | P50: 0 | Q50: 211915 | R50: 134855 | S50: 77060 | T50: 0 | U50: 0 | V50: 0 | W50: 0 | X50: 0 | Y50: 0 | AB50: 700000 | AH50: =AB50-H50 -> 488085
B51: Additive | C51: AURORA MINERAÇÃO LTDA | D51: 0 | F51: 270000 | G51: 80971.3 | H51: 189028.7 | I51: 37491.5 | J51: 0 | K51: 0 | L51: 0 | M51: 0 | N51: 0 | O51: 0 | P51: 37491.5 | Q51: 151537.2 | R51: 75216.8 | S51: 76320.4 | T51: 0 | U51: 0 | V51: 0 | W51: 0 | X51: 0 | Y51: 0 | AB51: 0 | AH51: =AB51-H51 -> -189028.7
B52: Additive Intl. | C52: FERTIMAX PARAGUAY | D52: A | F52: 1375000 | G52: 1217850.5 | H52: 157149.47 | I52: 0 | J52: 0 | K52: 0 | L52: 0 | M52: 0 | N52: 0 | O52: 0 | P52: 0 | Q52: 157149.47 | R52: 157149.47 | S52: 0 | T52: 0 | U52: 0 | V52: 0 | W52: 0 | X52: 0 | Y52: 0 | AB52: 1375000 | AH52: =AB52-H52 -> 1217850.5
B53: Additive | C53: GRUPO FERTIPAR FERTILIZANTES MATO GROSSO | D53: B | F53: 1500000 | G53: 1343936.4 | H53: 156063.6 | I53: 0 | J53: 0 | K53: 0 | L53: 0 | M53: 0 | N53: 0 | O53: 0 | P53: 0 | Q53: 156063.6 | R53: 156063.6 | S53: 0 | T53: 0 | U53: 0 | V53: 0 | W53: 0 | X53: 0 | Y53: 0 | AB53: 1500000 | AH53: =AB53-H53 -> 1343936.4
B54: Additive Intl. | C54: SOMAX - PARAGUAI | D54: B | F54: 550000 | G54: 412283.09 | H54: 137716.91 | I54: 0 | J54: 0 | K54: 0 | L54: 0 | M54: 0 | N54: 0 | O54: 0 | P54: 0 | Q54: 137716.91 | R54: 137716.91 | S54: 0 | T54: 0 | U54: 0 | V54: 0 | W54: 0 | X54: 0 | Y54: 0 | AB54: 550000 | AH54: =AB54-H54 -> 412283.09
B55: Fertilizer | C55: GRUPO BOLSA AGRONEGOCIO | D55: 0 | F55: 1000000 | G55: 866282 | H55: 133718 | I55: 0 | J55: 0 | K55: 0 | L55: 0 | M55: 0 | N55: 0 | O55: 0 | P55: 0 | Q55: 133718 | R55: 133718 | S55: 0 | T55: 0 | U55: 0 | V55: 0 | W55: 0 | X55: 0 | Y55: 0 | AB55: 1000000 | AH55: =AB55-H55 -> 866282
B56: Additive Intl. | C56: ISUSA - URUGUAI | D56: A | F56: 687500 | G56: 555539.94 | H56: 131960.06 | I56: 0 | J56: 0 | K56: 0 | L56: 0 | M56: 0 | N56: 0 | O56: 0 | P56: 0 | Q56: 131960.06 | R56: 131960.06 | S56: 0 | T56: 0 | U56: 0 | V56: 0 | W56: 0 | X56: 0 | Y56: 0 | AB56: 687500 | AH56: =AB56-H56 -> 555539.94
B57: Additive | C57: NUTRIENTES IND DE FERTILIZANTES LTDA | D57: B | F57: 850000 | G57: 728148 | H57: 121852 | I57: 0 | J57: 0 | K57: 0 | L57: 0 | M57: 0 | N57: 0 | O57: 0 | P57: 0 | Q57: 121852 | R57: 0 | S57: 121852 | T57: 0 | U57: 0 | V57: 0 | W57: 0 | X57: 0 | Y57: 0 | AB57: 850000 | AH57: =AB57-H57 -> 728148
B58: Additive | C58: SUL GOIANA - GOIATUBA | D58: B | F58: 500000 | G58: 380000 | H58: 120000 | I58: 0 | J58: 0 | K58: 0 | L58: 0 | M58: 0 | N58: 0 | O58: 0 | P58: 0 | Q58: 120000 | R58: 120000 | S58: 0 | T58: 0 | U58: 0 | V58: 0 | W58: 0 | X58: 0 | Y58: 0 | AB58: 500000 | AH58: =AB58-H58 -> 380000
B59: Additive Intl. | C59: TEPEYAC - MÉXICO | D59: B | F59: 1100000 | G59: 996580.11 | H59: 103419.89 | I59: 0 | J59: 0 | K59: 0 | L59: 0 | M59: 0 | N59: 0 | O59: 0 | P59: 0 | Q59: 103419.89 | R59: 0 | S59: 103419.89 | T59: 0 | U59: 0 | V59: 0 | W59: 0 | X59: 0 | Y59: 0 | AB59: 550000 | AH59: =AB59-H59 -> 446580.11
B60: Additive | C60: BIOSAFRA - MARUIM | D60: B | F60: 200000 | G60: 100974.05 | H60: 99025.95 | I60: 0 | J60: 0 | K60: 0 | L60: 0 | M60: 0 | N60: 0 | O60: 0 | P60: 0 | Q60: 99025.95 | R60: 49512.97 | S60: 49512.98 | T60: 0 | U60: 0 | V60: 0 | W60: 0 | X60: 0 | Y60: 0 | AB60: 200000 | AH60: =AB60-H60 -> 100974.05
B61: Additive | C61: GRANUPAR - RIO BRANCO DO SUL | D61: B | F61: 300000 | G61: 212860.5 | H61: 87139.5 | I61: 0 | J61: 0 | K61: 0 | L61: 0 | M61: 0 | N61: 0 | O61: 0 | P61: 0 | Q61: 87139.5 | R61: 43569.75 | S61: 43569.75 | T61: 0 | U61: 0 | V61: 0 | W61: 0 | X61: 0 | Y61: 0 | AB61: 300000 | AH61: =AB61-H61 -> 212860.5
B62: Additive Intl. | C62: CERES PERU S.A | D62: A | F62: 550000 | G62: 463310.9 | H62: 86689.1 | I62: 0 | J62: 0 | K62: 0 | L62: 0 | M62: 0 | N62: 0 | O62: 0 | P62: 0 | Q62: 86689.1 | R62: 86689.1 | S62: 0 | T62: 0 | U62: 0 | V62: 0 | W62: 0 | X62: 0 | Y62: 0 | AB62: 550000 | AH62: =AB62-H62 -> 463310.9
B63: Additive | C63: COONAGRO COOPERATIVA - PARANAGUA | D63: B | F63: 2500000 | G63: 2419920.7 | H63: 80079.3 | I63: 0 | J63: 0 | K63: 0 | L63: 0 | M63: 0 | N63: 0 | O63: 0 | P63: 0 | Q63: 80079.3 | R63: 80079.3 | S63: 0 | T63: 0 | U63: 0 | V63: 0 | W63: 0 | X63: 0 | Y63: 0 | AB63: 2500000 | AH63: =AB63-H63 -> 2419920.7
B64: Additive Intl. | C64: AGRO MIL AGROS SAS - COLOMBIA | D64: A | F64: 302500 | G64: 226019.77 | H64: 76480.23 | I64: 0 | J64: 0 | K64: 0 | L64: 0 | M64: 0 | N64: 0 | O64: 0 | P64: 0 | Q64: 76480.23 | R64: 0 | S64: 0 | T64: 0 | U64: 0 | V64: 0 | W64: 76480.23 | X64: 0 | Y64: 0 | AB64: 302500 | AH64: =AB64-H64 -> 226019.77
B65: Additive | C65: MICROSOLO INDUSTRIAL - SETE LAGOAS | D65: 0 | F65: 0 | G65: -66176 | H65: 66176 | I65: 0 | J65: 0 | K65: 0 | L65: 0 | M65: 0 | N65: 0 | O65: 0 | P65: 0 | Q65: 66176 | R65: 66176 | S65: 0 | T65: 0 | U65: 0 | V65: 0 | W65: 0 | X65: 0 | Y65: 0 | AB65: 0 | AH65: =AB65-H65 -> -66176
B66: Additive | C66: GRUPO AMAGGI | D66: B | F66: 4000000 | G66: 3941082.2 | H66: 58917.8 | I66: 0 | J66: 0 | K66: 0 | L66: 0 | M66: 0 | N66: 0 | O66: 0 | P66: 0 | Q66: 58917.8 | R66: 58917.8 | S66: 0 | T66: 0 | U66: 0 | V66: 0 | W66: 0 | X66: 0 | Y66: 0 | AB66: 4000000 | AH66: =AB66-H66 -> 3941082.2
B67: Additive | C67: FERTIPLANTA - VARGEM GRANDE DO SUL | D67: 0 | F67: 0 | G67: -52840 | H67: 52840 | I67: 0 | J67: 0 | K67: 0 | L67: 0 | M67: 0 | N67: 0 | O67: 0 | P67: 0 | Q67: 52840 | R67: 52840 | S67: 0 | T67: 0 | U67: 0 | V67: 0 | W67: 0 | X67: 0 | Y67: 0 | AB67: 0 | AH67: =AB67-H67 -> -52840
B68: Additive Intl. | C68: MACROSOURCE PERU S.R.L. | D68: B | F68: 550000 | G68: 500043.32 | H68: 49956.68 | I68: 0 | J68: 0 | K68: 0 | L68: 0 | M68: 0 | N68: 0 | O68: 0 | P68: 0 | Q68: 49956.68 | R68: 0 | S68: 49956.68 | T68: 0 | U68: 0 | V68: 0 | W68: 0 | X68: 0 | Y68: 0 | AB68: 550000 | AH68: =AB68-H68 -> 500043.32
B69: Additive | C69: ARSLOG SOLUCOES EM TRANSPORTE | D69: 0 | F69: 0 | G69: -49440 | H69: 49440 | I69: 0 | J69: 49440 | K69: 0 | L69: 0 | M69: 0 | N69: 0 | O69: 0 | P69: 49440 | Q69: 0 | R69: 0 | S69: 0 | T69: 0 | U69: 0 | V69: 0 | W69: 0 | X69: 0 | Y69: 0 | AB69: 0 | AH69: =AB69-H69 -> -49440
B70: Additive Intl. | C70: GOTLAND EQUADOR (SOLINAG) | D70: D | F70: 275000 | G70: 229281.54 | H70: 45718.46 | I70: 0 | J70: 0 | K70: 0 | L70: 0 | M70: 0 | N70: 0 | O70: 0 | P70: 0 | Q70: 45718.46 | R70: 0 | S70: 45718.46 | T70: 0 | U70: 0 | V70: 0 | W70: 0 | X70: 0 | Y70: 0 | AB70: 275000 | AH70: =AB70-H70 -> 229281.54
B71: Additive | C71: INTERFERTIL - SAO FRANCISCO DO SUL | D71: B | F71: 200000 | G71: 155081 | H71: 44919 | I71: 0 | J71: 0 | K71: 0 | L71: 0 | M71: 0 | N71: 0 | O71: 0 | P71: 0 | Q71: 44919 | R71: 44919 | S71: 0 | T71: 0 | U71: 0 | V71: 0 | W71: 0 | X71: 0 | Y71: 0 | AB71: 200000 | AH71: =AB71-H71 -> 155081
B72: Additive | C72: GRUPO CARGILL | D72: B | F72: 2000000 | G72: 1955637 | H72: 44363 | I72: 0 | J72: 0 | K72: 0 | L72: 0 | M72: 0 | N72: 0 | O72: 0 | P72: 0 | Q72: 44363 | R72: 44363 | S72: 0 | T72: 0 | U72: 0 | V72: 0 | W72: 0 | X72: 0 | Y72: 0 | AB72: 2000000 | AH72: =AB72-H72 -> 1955637
B73: Additive Intl. | C73: EQUILIBRA PERU S.A | D73: B | F73: 1100000 | G73: 1059982.4 | H73: 40017.64 | I73: 0 | J73: 0 | K73: 0 | L73: 0 | M73: 0 | N73: 0 | O73: 0 | P73: 0 | Q73: 40017.64 | R73: 40017.64 | S73: 0 | T73: 0 | U73: 0 | V73: 0 | W73: 0 | X73: 0 | Y73: 0 | AB73: 1100000 | AH73: =AB73-H73 -> 1059982.4
B74: Additive | C74: ADUBOS LEAO - LARANJEIRAS | D74: 0 | F74: 500000 | G74: 473710 | H74: 26290 | I74: 0 | J74: 0 | K74: 0 | L74: 0 | M74: 0 | N74: 0 | O74: 0 | P74: 0 | Q74: 26290 | R74: 956 | S74: 25334 | T74: 0 | U74: 0 | V74: 0 | W74: 0 | X74: 0 | Y74: 0 | AB74: 0 | AH74: =AB74-H74 -> -26290
B75: Additive / Litigation | C75: GLINFERTIL - SAO FRANCISCO DO SUL | D75: 0 | F75: 0 | G75: -20940 | H75: 20940 | I75: 0 | J75: 0 | K75: 0 | L75: 0 | M75: 0 | N75: 0 | O75: 20940 | P75: 20940 | Q75: 0 | R75: 0 | S75: 0 | T75: 0 | U75: 0 | V75: 0 | W75: 0 | X75: 0 | Y75: 20940 | AB75: 0 | AH75: =AB75-H75 -> -20940
B76: Fertilizer | C76: MINAS FARM | D76: B | E76: 180 | F76: 1200000 | G76: 1179474.2 | H76: 20525.8 | I76: 0 | J76: 0 | K76: 0 | L76: 0 | M76: 0 | N76: 0 | O76: 0 | P76: 0 | Q76: 20525.8 | R76: 20525.8 | S76: 0 | T76: 0 | U76: 0 | V76: 0 | W76: 0 | X76: 0 | Y76: 0 | AB76: 500000 | AH76: =AB76-H76 -> 479474.2
B77: Additive Intl. | C77: FERTIBAL - EQUADOR | D77: B | F77: 275000 | G77: 260451.65 | H77: 14548.35 | I77: 0 | J77: 0 | K77: 0 | L77: 14548.35 | M77: 0 | N77: 0 | O77: 0 | P77: 14548.35 | Q77: 0 | R77: 0 | S77: 0 | T77: 0 | U77: 0 | V77: 0 | W77: 0 | X77: 0 | Y77: 0 | AB77: 275000 | AH77: =AB77-H77 -> 260451.65
B78: Fertilizer | C78: GRUPO SAGRA | D78: B | E78: 360 | F78: 700000 | G78: 694969.5 | H78: 5030.5 | I78: 0 | J78: 0 | K78: 0 | L78: 0 | M78: 0 | N78: 0 | O78: 0 | P78: 0 | Q78: 5030.5 | R78: 0 | S78: 0 | T78: 0 | U78: 5030.5 | V78: 0 | W78: 0 | X78: 0 | Y78: 0 | AB78: 700000 | AH78: =AB78-H78 -> 694969.5
B79: Additive Intl. | C79: ORGANITEC - PARAGUAY | D79: 0 | F79: 0 | G79: -1380.52 | H79: 1380.52 | I79: 0 | J79: 0 | K79: 0 | L79: 0 | M79: 0 | N79: 527.28 | O79: 0 | P79: 527.28 | Q79: 853.24 | R79: 853.24 | S79: 0 | T79: 0 | U79: 0 | V79: 0 | W79: 0 | X79: 0 | Y79: 15.8184 | AB79: 0 | AH79: =AB79-H79 -> -1380.52
B80: Additive | C80: ELYMAR JOSE DA SILVA FERREIRA | D80: 0 | F80: 0 | G80: -662 | H80: 662 | I80: 0 | J80: 0 | K80: 0 | L80: 0 | M80: 0 | N80: 0 | O80: 0 | P80: 0 | Q80: 662 | R80: 331 | S80: 331 | T80: 0 | U80: 0 | V80: 0 | W80: 0 | X80: 0 | Y80: 0 | AB80: 0 | AH80: =AB80-H80 -> -662
B81: Additive | C81: ANDRESSA CAROLINA SILVA RODRIGUES | D81: 0 | F81: 0 | G81: -583.34 | H81: 583.34 | I81: 0 | J81: 0 | K81: 0 | L81: 0 | M81: 0 | N81: 0 | O81: 0 | P81: 0 | Q81: 583.34 | R81: 583.34 | S81: 0 | T81: 0 | U81: 0 | V81: 0 | W81: 0 | X81: 0 | Y81: 0 | AB81: 0 | AH81: =AB81-H81 -> -583.34
B82: Additive | C82: SEU LIXO | D82: 0 | F82: 0 | G82: -300 | H82: 300 | I82: 0 | J82: 0 | K82: 0 | L82: 0 | M82: 0 | N82: 0 | O82: 300 | P82: 300 | Q82: 0 | R82: 0 | S82: 0 | T82: 0 | U82: 0 | V82: 0 | W82: 0 | X82: 0 | Y82: 300 | AB82: 0 | AH82: =AB82-H82 -> -300
B83: Additive | C83: LUCAS DA CONCEIÇÃO CASSIMIRO | D83: 0 | F83: 0 | G83: -292.08 | H83: 292.08 | I83: 0 | J83: 0 | K83: 0 | L83: 0 | M83: 0 | N83: 0 | O83: 0 | P83: 0 | Q83: 292.08 | R83: 292.08 | S83: 0 | T83: 0 | U83: 0 | V83: 0 | W83: 0 | X83: 0 | Y83: 0 | AB83: 0 | AH83: =AB83-H83 -> -292.08
B84: Additive | C84: KLEYTON DUARTE SOARES | D84: 0 | F84: 0 | G84: -100 | H84: 100 | I84: 0 | J84: 0 | K84: 0 | L84: 0 | M84: 0 | N84: 0 | O84: 100 | P84: 100 | Q84: 0 | R84: 0 | S84: 0 | T84: 0 | U84: 0 | V84: 0 | W84: 0 | X84: 0 | Y84: 100 | AB84: 0 | AH84: =AB84-H84 -> -100
B85: Additive | C85: JOSÉ FRANCISCO PIRES DE SOUZA | D85: 0 | F85: 0 | G85: -100 | H85: 100 | I85: 100 | J85: 0 | K85: 0 | L85: 0 | M85: 0 | N85: 0 | O85: 0 | P85: 100 | Q85: 0 | R85: 0 | S85: 0 | T85: 0 | U85: 0 | V85: 0 | W85: 0 | X85: 0 | Y85: 0 | AB85: 0 | AH85: =AB85-H85 -> -100
B86: Additive | C86: MARIA JOSE DA SILVA | D86: 0 | F86: 0 | G86: -50 | H86: 50 | I86: 0 | J86: 0 | K86: 0 | L86: 0 | M86: 0 | N86: 0 | O86: 50 | P86: 50 | Q86: 0 | R86: 0 | S86: 0 | T86: 0 | U86: 0 | V86: 0 | W86: 0 | X86: 0 | Y86: 50 | AB86: 0 | AH86: =AB86-H86 -> -50

Sheet Planilha1
E1: In 27/01/2026 | I1: In 28/01/2026
D2: =SUBTOTAL(9,D4:D27) -> 19842082 | E2: =SUBTOTAL(9,E4:E27) -> 3794382.8 | F2: =SUBTOTAL(9,F4:F27) -> 16047700 | H2: =SUBTOTAL(9,H4:H27) -> #N/A | I2: =SUBTOTAL(9,I4:I27) -> #N/A | J2: =SUBTOTAL(9,J4:J27) -> #N/A
B3: BU | C3: CUSTOMER | D3: Total AR | E3: Overdue | F3: Not Due | H3: Total AR | I3: Overdue | J3: Not Due | K3: Coments
B4: Additive | C4: GRUPO MOSAIC FERTILIZANTES DO BRASIL | D4: 5370037.2 | E4: 16818.92 | F4: 5353218.3 | H4: =_xlfn.XLOOKUP(C4,'Clientes Consolidado'!$C$4:$C$86,'Clientes Consolidado'!$H$4:$H$86) -> 3871241.1 | I4: =_xlfn.XLOOKUP(C4,'Clientes Consolidado'!$C$4:$C$86,'Clientes Consolidado'!$P$4:$P$86) -> 16818.92 | J4: =_xlfn.XLOOKUP(C4,'Clientes Consolidado'!$C$4:$C$86,'Clientes Consolidado'!$Q$4:$Q$86) -> 3854422.2
B5: Additive | C5: GRUPO YARA | D5: 3979397.8 | E5: 5626.32 | F5: 3973771.5 | H5: =_xlfn.XLOOKUP(C5,'Clientes Consolidado'!$C$4:$C$86,'Clientes Consolidado'!$H$4:$H$86) -> 3957383.1 | I5: =_xlfn.XLOOKUP(C5,'Clientes Consolidado'!$C$4:$C$86,'Clientes Consolidado'!$P$4:$P$86) -> 5626.32 | J5: =_xlfn.XLOOKUP(C5,'Clientes Consolidado'!$C$4:$C$86,'Clientes Consolidado'!$Q$4:$Q$86) -> 3951756.8
B6: Additive | C6: FOSNOR - LUIS EDUARDO MAGALHAES | D6: 690300 | E6: 0 | F6: 690300 | H6: =_xlfn.XLOOKUP(C6,'Clientes Consolidado'!$C$4:$C$86,'Clientes Consolidado'!$H$4:$H$86) -> 523627.5 | I6: =_xlfn.XLOOKUP(C6,'Clientes Consolidado'!$C$4:$C$86,'Clientes Consolidado'!$P$4:$P$86) -> 0 | J6: =_xlfn.XLOOKUP(C6,'Clientes Consolidado'!$C$4:$C$86,'Clientes Consolidado'!$Q$4:$Q$86) -> 523627.5
B7: Additive | C7: GRUPO HERINGER | D7: 520371.3 | E7: 220406.5 | F7: 299964.8 | H7: =_xlfn.XLOOKUP(C7,'Clientes Consolidado'!$C$4:$C$86,'Clientes Consolidado'!$H$4:$H$86) -> 248897.61 | I7: =_xlfn.XLOOKUP(C7,'Clientes Consolidado'!$C$4:$C$86,'Clientes Consolidado'!$P$4:$P$86) -> 0 | J7: =_xlfn.XLOOKUP(C7,'Clientes Consolidado'!$C$4:$C$86,'Clientes Consolidado'!$Q$4:$Q$86) -> 248897.61
B8: Additive | C8: EUROCHEM SERRA DO SALITRE | D8: 618802.8 | E8: 149216.4 | F8: 469586.4 | H8: =_xlfn.XLOOKUP(C8,'Clientes Consolidado'!$C$4:$C$86,'Clientes Consolidado'!$H$4:$H$86) -> 793811.7 | I8: =_xlfn.XLOOKUP(C8,'Clientes Consolidado'!$C$4:$C$86,'Clientes Consolidado'!$P$4:$P$86) -> 153506.1 | J8: =_xlfn.XLOOKUP(C8,'Clientes Consolidado'!$C$4:$C$86,'Clientes Consolidado'!$Q$4:$Q$86) -> 640305.6
B9: Additive | C9: GRUPO FERTILIZ TOCANTINS | D9: 1682538.8 | E9: 0 | F9: 1682538.8 | H9: =_xlfn.XLOOKUP(C9,'Clientes Consolidado'!$C$4:$C$86,'Clientes Consolidado'!$H$4:$H$86) -> 509079.6 | I9: =_xlfn.XLOOKUP(C9,'Clientes Consolidado'!$C$4:$C$86,'Clientes Consolidado'!$P$4:$P$86) -> 0 | J9: =_xlfn.XLOOKUP(C9,'Clientes Consolidado'!$C$4:$C$86,'Clientes Consolidado'!$Q$4:$Q$86) -> 509079.6
B10: Additive | C10: TERRA FERTILIZANTES LTDA - ARAXÁ | D10: 226233.6 | E10: 226233.6 | F10: 0 | H10: =_xlfn.XLOOKUP(C10,'Clientes Consolidado'!$C$4:$C$86,'Clientes Consolidado'!$H$4:$H$86) -> 226233.6 | I10: =_xlfn.XLOOKUP(C10,'Clientes Consolidado'!$C$4:$C$86,'Clientes Consolidado'!$P$4:$P$86) -> 226233.6 | J10: =_xlfn.XLOOKUP(C10,'Clientes Consolidado'!$C$4:$C$86,'Clientes Consolidado'!$Q$4:$Q$86) -> 0
B11: Additive | C11: ITERUM - RONDONOPOLIS | D11: 213750 | E11: 213750 | F11: 0 | H11: =_xlfn.XLOOKUP(C11,'Clientes Consolidado'!$C$4:$C$86,'Clientes Consolidado'!$H$4:$H$86) -> 213750 | I11: =_xlfn.XLOOKUP(C11,'Clientes Consolidado'!$C$4:$C$86,'Clientes Consolidado'!$P$4:$P$86) -> 213750 | J11: =_xlfn.XLOOKUP(C11,'Clientes Consolidado'!$C$4:$C$86,'Clientes Consolidado'!$Q$4:$Q$86) -> 0
B12: Additive | C12: GRUPO FERTIPAR FERTILIZANTES DO NORDESTE | D12: 103960.4 | E12: 3393 | F12: 100567.4 | H12: =_xlfn.XLOOKUP(C12,'Clientes Consolidado'!$C$4:$C$86,'Clientes Consolidado'!$H$4:$H$86) -> #N/A | I12: =_xlfn.XLOOKUP(C12,'Clientes Consolidado'!$C$4:$C$86,'Clientes Consolidado'!$P$4:$P$86) -> #N/A | J12: =_xlfn.XLOOKUP(C12,'Clientes Consolidado'!$C$4:$C$86,'Clientes Consolidado'!$Q$4:$Q$86) -> #N/A
B13: Additive | C13: GLINFERTIL - SAO FRANCISCO DO SUL | D13: 20940 | E13: 20940 | F13: 0 | H13: =_xlfn.XLOOKUP(C13,'Clientes Consolidado'!$C$4:$C$86,'Clientes Consolidado'!$H$4:$H$86) -> 20940 | I13: =_xlfn.XLOOKUP(C13,'Clientes Consolidado'!$C$4:$C$86,'Clientes Consolidado'!$P$4:$P$86) -> 20940 | J13: =_xlfn.XLOOKUP(C13,'Clientes Consolidado'!$C$4:$C$86,'Clientes Consolidado'!$Q$4:$Q$86) -> 0
B14: Additive | C14: SEU LIXO | D14: 300 | E14: 300 | F14: 0 | H14: =_xlfn.XLOOKUP(C14,'Clientes Consolidado'!$C$4:$C$86,'Clientes Consolidado'!$H$4:$H$86) -> 300 | I14: =_xlfn.XLOOKUP(C14,'Clientes Consolidado'!$C$4:$C$86,'Clientes Consolidado'!$P$4:$P$86) -> 300 | J14: =_xlfn.XLOOKUP(C14,'Clientes Consolidado'!$C$4:$C$86,'Clientes Consolidado'!$Q$4:$Q$86) -> 0
B15: Additive | C15: KLEYTON DUARTE SOARES | D15: 100 | E15: 100 | F15: 0 | H15: =_xlfn.XLOOKUP(C15,'Clientes Consolidado'!$C$4:$C$86,'Clientes Consolidado'!$H$4:$H$86) -> 100 | I15: =_xlfn.XLOOKUP(C15,'Clientes Consolidado'!$C$4:$C$86,'Clientes Consolidado'!$P$4:$P$86) -> 100 | J15: =_xlfn.XLOOKUP(C15,'Clientes Consolidado'!$C$4:$C$86,'Clientes Consolidado'!$Q$4:$Q$86) -> 0
... B27: Int'll | C27: ORGANITEC - PARAGUAY | D27: 185521.46 | E27: 527.28 | F27: 184994.18 | H27: =_xlfn.XLOOKUP(C27,'Clientes Consolidado'!$C$4:$C$86,'Clientes Consolidado'!$H$4:$H$86) -> 1380.52 | I27: =_xlfn.XLOOKUP(C27,'Clientes Consolidado'!$C$4:$C$86,'Clientes Consolidado'!$P$4:$P$86) -> 527.28 | J27: =_xlfn.XLOOKUP(C27,'Clientes Consolidado'!$C$4:$C$86,'Clientes Consolidado'!$Q$4:$Q$86) -> 853.24
B29: BU | D29: Total AR | E29: Overdue | F29: Not Due | H29: Total AR | I29: Overdue | J29: Not Due
B30: Additive | D30: =SUM(D4:D16) -> 13426782 | E30: =SUM(E4:E16) -> 856834.74 | F30: =SUM(F4:F16) -> 12569947 | H30: =SUM(H4:H16) -> #N/A | I30: =SUM(I4:I16) -> #N/A | J30: =SUM(J4:J16) -> #N/A
B31: Fertilizer | D31: =+SUM(D17:D19) -> 4005020.7 | E31: =+SUM(E17:E19) -> 1647580.2 | F31: =+SUM(F17:F19) -> 2357440.4 | H31: =+SUM(H17:H19) -> #N/A | I31: =+SUM(I17:I19) -> #N/A | J31: =+SUM(J17:J19) -> #N/A
B32: Int'll | D32: =+SUM(D20:D27) -> 2410279.7 | E32: =+SUM(E20:E27) -> 1289967.8 | F32: =+SUM(F20:F27) -> 1120311.9 | H32: =+SUM(H20:H27) -> #N/A | I32: =+SUM(I20:I27) -> #N/A | J32: =+SUM(J20:J27) -> #N/A
B34: Total | D34: =+D32+D31+D30 -> 19842082 | E34: =+E32+E31+E30 -> 3794382.8 | F34: =+F32+F31+F30 -> 16047700 | H34: =+H32+H31+H30 -> #N/A | I34: =+I32+I31+I30 -> #N/A | J34: =+J32+J31+J30 -> #N/A
B36: Eurochem Group | E36: =E7+E9+E8 -> 369622.9 | H36: Eurochem Group | I36: =+I7+I9 -> 0
B37: Int´l Clients | E37: =SUM(E20:E27) -> 1289967.8 | H37: Int´l Clients | I37: =SUM(I20:I27) -> #N/A
E38: =(+E36+E37)/E34 -> 0.43738094 | F38: Of current overdue | I38: =(+I36+I37)/I34 -> #N/A | J38: Of current overdue
B40: BU | D40: Total AR | E40: Overdue | F40: Not Due
B41: Additive | D41: =SUM(H4:H16) -> #N/A | E41: =SUM(I4:I16) -> #N/A | F41: =SUM(J4:J16) -> #N/A
B42: Fertilizer | D42: =+SUM(H17:H19) -> #N/A | E42: =+SUM(I17:I19) -> #N/A | F42: =+SUM(J17:J19) -> #N/A
B43: Int'll | D43: =+SUM(H20:H27) -> #N/A | E43: =+SUM(I20:I27) -> #N/A | F43: =+SUM(J20:J27) -> #N/A
B45: Total | D45: =+D43+D42+D41 -> #N/A | E45: =+E43+E42+E41 -> #N/A | F45: =+F43+F42+F41 -> #N/A
D47: Eurochem Group | E47: =I7+I9+I8 -> 153506.1
D48: Int´l Clients | E48: =SUM(I20:I27) -> #N/A
E49: =(+E47+E48)/E45 -> #N/A | F49: Of current overdue

Sheet Painel Additive
B1: 46135 | G1: =SUBTOTAL(9,G4:G101) -> 26130017 | H1: =SUBTOTAL(9,H4:H101) -> 191097.6 | I1: =SUBTOTAL(9,I4:I101) -> 0 | J1: =SUBTOTAL(9,J4:J101) -> 0 | K1: =SUBTOTAL(9,K4:K101) -> 0 | L1: =SUBTOTAL(9,L4:L101) -> 0 | M1: =SUBTOTAL(9,M4:M101) -> 64.2 | N1: =SUBTOTAL(9,N4:N101) -> 483754.64 | ... P1: =SUBTOTAL(9,P4:P101) -> 25455100 | Q1: =SUM(Q4:Q102) -> 11802393 | R1: =SUM(R4:R102) -> 9467002.3 | S1: =SUM(S4:S102) -> 3641384.7 | T1: =SUM(T4:T102) -> 447550.2 | U1: =SUM(U4:U102) -> 0 | V1: =SUM(V4:V102) -> 0 | W1: =SUM(W4:W102) -> 96770.01 | X1: =SUBTOTAL(9,X4:X101) -> 628965.48 | AA1: =SUBTOTAL(9,AA4:AA1048576) -> 92737000 | AG1: =SUBTOTAL(9,AG4:AG106) -> 59616763 | AI1: =O1/G1 -> 0.025829162
H2: Aging Overdue | Q2: Aging Not Due | AI2: Treasury Risk Status
A3: x | B3: CUSTOMER | C3: RATING | D3: Payment Term | E3: Approved Credit | F3: Credit Balance | G3: Total AR | H3: 1-30 Days | I3: 31-60 Days | J3: 61-90 Days | K3: 91-120 Days | L3: 121-180 Days | M3: 181-360 Days | N3: Above 360 Days | O3: Overdue | P3: Not Due | Q3: 1-30 Days | R3: 31-60 Days | S3: 61-90 Days | T3: 91-120 Days | U3: 121-180 Days | V3: 181-360 Days | W3: Above 360 Days | X3: Bad debt provision | Y3: x | Z3: x | AA3: Credit Insurance | AB3: Guarantee Value | AC3: Type | AD3: Due date | AE3: Tenor | AF3: x | AG3: Open Exposure | AH3: x | AI3: Probable | AJ3: Possible | AK3: Rare
B4: GRUPO MOSAIC FERTILIZANTES DO BRASIL | C4: =IFERROR(_xlfn.XLOOKUP(B4,'Limite de crédito'!C:C,'Limite de crédito'!L:L,),0) -> 0 | E4: =_xlfn.XLOOKUP(B4,'Limite de crédito'!C:C,'Limite de crédito'!G:G,0) -> 20000000 | F4: =E4-G4 -> 16128759 | G4: =P4+O4 -> 3871241.1 | H4: =SUMIFS('Data Additive'!$D:$D,'Data Additive'!$P:$P,'Painel Additive'!$B4,'Data Additive'!$Q:$Q,">0",'Data Additive'!$Q:$Q,"<=30") -> 0 | I4: =SUMIFS('Data Additive'!$D:$D,'Data Additive'!$P:$P,'Painel Additive'!$B4,'Data Additive'!$Q:$Q,">30",'Data Additive'!$Q:$Q,"<=60") -> 0 | J4: =SUMIFS('Data Additive'!$D:$D,'Data Additive'!$P:$P,'Painel Additive'!$B4,'Data Additive'!$Q:$Q,">60",'Data Additive'!$Q:$Q,"<=90") -> 0 | K4: =SUMIFS('Data Additive'!$D:$D,'Data Additive'!$P:$P,'Painel Additive'!$B4,'Data Additive'!$Q:$Q,">90",'Data Additive'!$Q:$Q,"<=120") -> 0 | L4: =SUMIFS('Data Additive'!$D:$D,'Data Additive'!$P:$P,'Painel Additive'!$B4,'Data Additive'!$Q:$Q,">120",'Data Additive'!$Q:$Q,"<=180") -> 0 | M4: =SUMIFS('Data Additive'!$D:$D,'Data Additive'!$P:$P,'Painel Additive'!$B4,'Data Additive'!$Q:$Q,">180",'Data Additive'!$Q:$Q,"<=360") -> 64.2 | N4: =SUMIFS('Data Additive'!$D:$D,'Data Additive'!$P:$P,'Painel Additive'!$B4,'Data Additive'!$Q:$Q,">360") -> 16754.72 | O4: =SUMIFS('Data Additive'!$D:$D,'Data Additive'!$P:$P,'Painel Additive'!$B4,'Data Additive'!$Q:$Q,">0") -> 16818.92 | P4: =SUM(Q4:W4) -> 3854422.2 | Q4: =SUMIFS('Data Additive'!$D:$D,'Data Additive'!$P:$P,'Painel Additive'!$B4,'Data Additive'!$Q:$Q,"<=0",'Data Additive'!$Q:$Q,">=-30") -> 1696548.6 | R4: =SUMIFS('Data Additive'!$D:$D,'Data Additive'!$P:$P,'Painel Additive'!$B4,'Data Additive'!$Q:$Q,"<=-31",'Data Additive'!$Q:$Q,">=-60") -> 1268599.2 | S4: =SUMIFS('Data Additive'!$D:$D,'Data Additive'!$P:$P,'Painel Additive'!$B4,'Data Additive'!$Q:$Q,"<=-61",'Data Additive'!$Q:$Q,">=-90") -> 852594.6 | T4: =SUMIFS('Data Additive'!$D:$D,'Data Additive'!$P:$P,'Painel Additive'!$B4,'Data Additive'!$Q:$Q,"<=-91",'Data Additive'!$Q:$Q,">=-120") -> 36679.8 | U4: =SUMIFS('Data Additive'!$D:$D,'Data Additive'!$P:$P,'Painel Additive'!$B4,'Data Additive'!$Q:$Q,"<=-121",'Data Additive'!$Q:$Q,">=-180") -> 0 | V4: =SUMIFS('Data Additive'!$D:$D,'Data Additive'!$P:$P,'Painel Additive'!$B4,'Data Additive'!$Q:$Q,"<=-181",'Data Additive'!$Q:$Q,">=-360") -> 0 | W4: =SUMIFS('Data Additive'!$D:$D,'Data Additive'!$P:$P,'Painel Additive'!$B4,'Data Additive'!$Q:$Q,"<-360") -> 0 | X4: =SUMIFS('Bad Debt Provision'!AB:AB,'Bad Debt Provision'!B:B,'Painel Additive'!B4) -> 84763.766 | AA4: =IFERROR(_xlfn.XLOOKUP(B4,'Limite de crédito'!C:C,'Limite de crédito'!O:O,),0) -> 15000000 | AG4: =AA4-G4 -> 11128759
B5: GRUPO CIBRA | C5: =IFERROR(_xlfn.XLOOKUP(B5,'Limite de crédito'!C:C,'Limite de crédito'!L:L,),0) -> 0 | E5: =_xlfn.XLOOKUP(B5,'Limite de crédito'!C:C,'Limite de crédito'!G:G,0) -> 6900000 | F5: =E5-G5 -> 6388978 | G5: =P5+O5 -> 511022 | H5: =SUMIFS('Data Additive'!$D:$D,'Data Additive'!$P:$P,'Painel Additive'!$B5,'Data Additive'!$Q:$Q,">0",'Data Additive'!$Q:$Q,"<=30") -> 0 | I5: =SUMIFS('Data Additive'!$D:$D,'Data Additive'!$P:$P,'Painel Additive'!$B5,'Data Additive'!$Q:$Q,">30",'Data Additive'!$Q:$Q,"<=60") -> 0 | J5: =SUMIFS('Data Additive'!$D:$D,'Data Additive'!$P:$P,'Painel Additive'!$B5,'Data Additive'!$Q:$Q,">60",'Data Additive'!$Q:$Q,"<=90") -> 0 | K5: =SUMIFS('Data Additive'!$D:$D,'Data Additive'!$P:$P,'Painel Additive'!$B5,'Data Additive'!$Q:$Q,">90",'Data Additive'!$Q:$Q,"<=120") -> 0 | L5: =SUMIFS('Data Additive'!$D:$D,'Data Additive'!$P:$P,'Painel Additive'!$B5,'Data Additive'!$Q:$Q,">120",'Data Additive'!$Q:$Q,"<=180") -> 0 | M5: =SUMIFS('Data Additive'!$D:$D,'Data Additive'!$P:$P,'Painel Additive'!$B5,'Data Additive'!$Q:$Q,">180",'Data Additive'!$Q:$Q,"<=360") -> 0 | N5: =SUMIFS('Data Additive'!$D:$D,'Data Additive'!$P:$P,'Painel Additive'!$B5,'Data Additive'!$Q:$Q,">360") -> 0 | O5: =SUMIFS('Data Additive'!$D:$D,'Data Additive'!$P:$P,'Painel Additive'!$B5,'Data Additive'!$Q:$Q,">0") -> 0 | P5: =SUM(Q5:W5) -> 511022 | Q5: =SUMIFS('Data Additive'!$D:$D,'Data Additive'!$P:$P,'Painel Additive'!$B5,'Data Additive'!$Q:$Q,"<=0",'Data Additive'!$Q:$Q,">=-30") -> 511022 | R5: =SUMIFS('Data Additive'!$D:$D,'Data Additive'!$P:$P,'Painel Additive'!$B5,'Data Additive'!$Q:$Q,"<=-31",'Data Additive'!$Q:$Q,">=-60") -> 0 | S5: =SUMIFS('Data Additive'!$D:$D,'Data Additive'!$P:$P,'Painel Additive'!$B5,'Data Additive'!$Q:$Q,"<=-61",'Data Additive'!$Q:$Q,">=-90") -> 0 | T5: =SUMIFS('Data Additive'!$D:$D,'Data Additive'!$P:$P,'Painel Additive'!$B5,'Data Additive'!$Q:$Q,"<=-91",'Data Additive'!$Q:$Q,">=-120") -> 0 | U5: =SUMIFS('Data Additive'!$D:$D,'Data Additive'!$P:$P,'Painel Additive'!$B5,'Data Additive'!$Q:$Q,"<=-121",'Data Additive'!$Q:$Q,">=-180") -> 0 | V5: =SUMIFS('Data Additive'!$D:$D,'Data Additive'!$P:$P,'Painel Additive'!$B5,'Data Additive'!$Q:$Q,"<=-181",'Data Additive'!$Q:$Q,">=-360") -> 0 | W5: =SUMIFS('Data Additive'!$D:$D,'Data Additive'!$P:$P,'Painel Additive'!$B5,'Data Additive'!$Q:$Q,"<-360") -> 0 | X5: =SUMIFS('Bad Debt Provision'!AB:AB,'Bad Debt Provision'!B:B,'Painel Additive'!B5) -> 1200 | AA5: =IFERROR(_xlfn.XLOOKUP(B5,'Limite de crédito'!C:C,'Limite de crédito'!O:O,),0) -> 2315000 | AG5: =AA5-G5 -> 1803978
B6: GRUPO YARA | C6: =IFERROR(_xlfn.XLOOKUP(B6,'Limite de crédito'!C:C,'Limite de crédito'!L:L,),0) -> B | E6: =_xlfn.XLOOKUP(B6,'Limite de crédito'!C:C,'Limite de crédito'!G:G,0) -> 6000000 | F6: =E6-G6 -> 2042616.9 | G6: =P6+O6 -> 3957383.1 | H6: =SUMIFS('Data Additive'!$D:$D,'Data Additive'!$P:$P,'Painel Additive'!$B6,'Data Additive'!$Q:$Q,">0",'Data Additive'!$Q:$Q,"<=30") -> 0 | I6: =SUMIFS('Data Additive'!$D:$D,'Data Additive'!$P:$P,'Painel Additive'!$B6,'Data Additive'!$Q:$Q,">30",'Data Additive'!$Q:$Q,"<=60") -> 0 | J6: =SUMIFS('Data Additive'!$D:$D,'Data Additive'!$P:$P,'Painel Additive'!$B6,'Data Additive'!$Q:$Q,">60",'Data Additive'!$Q:$Q,"<=90") -> 0 | K6: =SUMIFS('Data Additive'!$D:$D,'Data Additive'!$P:$P,'Painel Additive'!$B6,'Data Additive'!$Q:$Q,">90",'Data Additive'!$Q:$Q,"<=120") -> 0 | L6: =SUMIFS('Data Additive'!$D:$D,'Data Additive'!$P:$P,'Painel Additive'!$B6,'Data Additive'!$Q:$Q,">120",'Data Additive'!$Q:$Q,"<=180") -> 0 | M6: =SUMIFS('Data Additive'!$D:$D,'Data Additive'!$P:$P,'Painel Additive'!$B6,'Data Additive'!$Q:$Q,">180",'Data Additive'!$Q:$Q,"<=360") -> 0 | N6: =SUMIFS('Data Additive'!$D:$D,'Data Additive'!$P:$P,'Painel Additive'!$B6,'Data Additive'!$Q:$Q,">360") -> 5626.32 | O6: =SUMIFS('Data Additive'!$D:$D,'Data Additive'!$P:$P,'Painel Additive'!$B6,'Data Additive'!$Q:$Q,">0") -> 5626.32 | P6: =SUM(Q6:W6) -> 3951756.8 | Q6: =SUMIFS('Data Additive'!$D:$D,'Data Additive'!$P:$P,'Painel Additive'!$B6,'Data Additive'!$Q:$Q,"<=0",'Data Additive'!$Q:$Q,">=-30") -> 2997325.2 | R6: =SUMIFS('Data Additive'!$D:$D,'Data Additive'!$P:$P,'Painel Additive'!$B6,'Data Additive'!$Q:$Q,"<=-31",'Data Additive'!$Q:$Q,">=-60") -> 954431.55 | S6: =SUMIFS('Data Additive'!$D:$D,'Data Additive'!$P:$P,'Painel Additive'!$B6,'Data Additive'!$Q:$Q,"<=-61",'Data Additive'!$Q:$Q,">=-90") -> 0 | T6: =SUMIFS('Data Additive'!$D:$D,'Data Additive'!$P:$P,'Painel Additive'!$B6,'Data Additive'!$Q:$Q,"<=-91",'Data Additive'!$Q:$Q,">=-120") -> 0 | U6: =SUMIFS('Data Additive'!$D:$D,'Data Additive'!$P:$P,'Painel Additive'!$B6,'Data Additive'!$Q:$Q,"<=-121",'Data Additive'!$Q:$Q,">=-180") -> 0 | V6: =SUMIFS('Data Additive'!$D:$D,'Data Additive'!$P:$P,'Painel Additive'!$B6,'Data Additive'!$Q:$Q,"<=-181",'Data Additive'!$Q:$Q,">=-360") -> 0 | W6: =SUMIFS('Data Additive'!$D:$D,'Data Additive'!$P:$P,'Painel Additive'!$B6,'Data Additive'!$Q:$Q,"<-360") -> 0 | X6: =SUMIFS('Bad Debt Provision'!AB:AB,'Bad Debt Provision'!B:B,'Painel Additive'!B6) -> 63226.32 | AA6: =IFERROR(_xlfn.XLOOKUP(B6,'Limite de crédito'!C:C,'Limite de crédito'!O:O,),0) -> 6000000 | AG6: =AA6-G6 -> 2042616.9 | AL6: Total AR | AM6: =G1+'Painel Fertilizers'!G1+'Painel International'!G1-AM8 -> 39196024
B7: GRUPO ADUBOS ARAGUAIA | C7: =IFERROR(_xlfn.XLOOKUP(B7,'Limite de crédito'!C:C,'Limite de crédito'!L:L,),0) -> B | E7: =_xlfn.XLOOKUP(B7,'Limite de crédito'!C:C,'Limite de crédito'!G:G,0) -> 500000 | F7: =E7-G7 -> 500000 | G7: =P7+O7 -> 0 | H7: =SUMIFS('Data Additive'!$D:$D,'Data Additive'!$P:$P,'Painel Additive'!$B7,'Data Additive'!$Q:$Q,">0",'Data Additive'!$Q:$Q,"<=30") -> 0 | I7: =SUMIFS('Data Additive'!$D:$D,'Data Additive'!$P:$P,'Painel Additive'!$B7,'Data Additive'!$Q:$Q,">30",'Data Additive'!$Q:$Q,"<=60") -> 0 | J7: =SUMIFS('Data Additive'!$D:$D,'Data Additive'!$P:$P,'Painel Additive'!$B7,'Data Additive'!$Q:$Q,">60",'Data Additive'!$Q:$Q,"<=90") -> 0 | K7: =SUMIFS('Data Additive'!$D:$D,'Data Additive'!$P:$P,'Painel Additive'!$B7,'Data Additive'!$Q:$Q,">90",'Data Additive'!$Q:$Q,"<=120") -> 0 | L7: =SUMIFS('Data Additive'!$D:$D,'Data Additive'!$P:$P,'Painel Additive'!$B7,'Data Additive'!$Q:$Q,">120",'Data Additive'!$Q:$Q,"<=180") -> 0 | M7: =SUMIFS('Data Additive'!$D:$D,'Data Additive'!$P:$P,'Painel Additive'!$B7,'Data Additive'!$Q:$Q,">180",'Data Additive'!$Q:$Q,"<=360") -> 0 | N7: =SUMIFS('Data Additive'!$D:$D,'Data Additive'!$P:$P,'Painel Additive'!$B7,'Data Additive'!$Q:$Q,">360") -> 0 | O7: =SUMIFS('Data Additive'!$D:$D,'Data Additive'!$P:$P,'Painel Additive'!$B7,'Data Additive'!$Q:$Q,">0") -> 0 | P7: =SUM(Q7:W7) -> 0 | Q7: =SUMIFS('Data Additive'!$D:$D,'Data Additive'!$P:$P,'Painel Additive'!$B7,'Data Additive'!$Q:$Q,"<=0",'Data Additive'!$Q:$Q,">=-30") -> 0 | R7: =SUMIFS('Data Additive'!$D:$D,'Data Additive'!$P:$P,'Painel Additive'!$B7,'Data Additive'!$Q:$Q,"<=-31",'Data Additive'!$Q:$Q,">=-60") -> 0 | S7: =SUMIFS('Data Additive'!$D:$D,'Data Additive'!$P:$P,'Painel Additive'!$B7,'Data Additive'!$Q:$Q,"<=-61",'Data Additive'!$Q:$Q,">=-90") -> 0 | T7: =SUMIFS('Data Additive'!$D:$D,'Data Additive'!$P:$P,'Painel Additive'!$B7,'Data Additive'!$Q:$Q,"<=-91",'Data Additive'!$Q:$Q,">=-120") -> 0 | U7: =SUMIFS('Data Additive'!$D:$D,'Data Additive'!$P:$P,'Painel Additive'!$B7,'Data Additive'!$Q:$Q,"<=-121",'Data Additive'!$Q:$Q,">=-180") -> 0 | V7: =SUMIFS('Data Additive'!$D:$D,'Data Additive'!$P:$P,'Painel Additive'!$B7,'Data Additive'!$Q:$Q,"<=-181",'Data Additive'!$Q:$Q,">=-360") -> 0 | W7: =SUMIFS('Data Additive'!$D:$D,'Data Additive'!$P:$P,'Painel Additive'!$B7,'Data Additive'!$Q:$Q,"<-360") -> 0 | X7: =SUMIFS('Bad Debt Provision'!AB:AB,'Bad Debt Provision'!B:B,'Painel Additive'!B7) -> 0 | AA7: =IFERROR(_xlfn.XLOOKUP(B7,'Limite de crédito'!C:C,'Limite de crédito'!O:O,),0) -> 500000 | AG7: =AA7-G7 -> 500000 | AL7: Exposição | AM7: =AG1+'Painel Fertilizers'!AG1+'Painel International'!AG1 -> 97280991
B8: GRUPO AMAGGI | C8: =IFERROR(_xlfn.XLOOKUP(B8,'Limite de crédito'!C:C,'Limite de crédito'!L:L,),0) -> B | E8: =_xlfn.XLOOKUP(B8,'Limite de crédito'!C:C,'Limite de crédito'!G:G,0) -> 4000000 | F8: =E8-G8 -> 3941082.2 | G8: =P8+O8 -> 58917.8 | H8: =SUMIFS('Data Additive'!$D:$D,'Data Additive'!$P:$P,'Painel Additive'!$B8,'Data Additive'!$Q:$Q,">0",'Data Additive'!$Q:$Q,"<=30") -> 0 | I8: =SUMIFS('Data Additive'!$D:$D,'Data Additive'!$P:$P,'Painel Additive'!$B8,'Data Additive'!$Q:$Q,">30",'Data Additive'!$Q:$Q,"<=60") -> 0 | J8: =SUMIFS('Data Additive'!$D:$D,'Data Additive'!$P:$P,'Painel Additive'!$B8,'Data Additive'!$Q:$Q,">60",'Data Additive'!$Q:$Q,"<=90") -> 0 | K8: =SUMIFS('Data Additive'!$D:$D,'Data Additive'!$P:$P,'Painel Additive'!$B8,'Data Additive'!$Q:$Q,">90",'Data Additive'!$Q:$Q,"<=120") -> 0 | L8: =SUMIFS('Data Additive'!$D:$D,'Data Additive'!$P:$P,'Painel Additive'!$B8,'Data Additive'!$Q:$Q,">120",'Data Additive'!$Q:$Q,"<=180") -> 0 | M8: =SUMIFS('Data Additive'!$D:$D,'Data Additive'!$P:$P,'Painel Additive'!$B8,'Data Additive'!$Q:$Q,">180",'Data Additive'!$Q:$Q,"<=360") -> 0 | N8: =SUMIFS('Data Additive'!$D:$D,'Data Additive'!$P:$P,'Painel Additive'!$B8,'Data Additive'!$Q:$Q,">360") -> 0 | O8: =SUMIFS('Data Additive'!$D:$D,'Data Additive'!$P:$P,'Painel Additive'!$B8,'Data Additive'!$Q:$Q,">0") -> 0 | P8: =SUM(Q8:W8) -> 58917.8 | Q8: =SUMIFS('Data Additive'!$D:$D,'Data Additive'!$P:$P,'Painel Additive'!$B8,'Data Additive'!$Q:$Q,"<=0",'Data Additive'!$Q:$Q,">=-30") -> 58917.8 | R8: =SUMIFS('Data Additive'!$D:$D,'Data Additive'!$P:$P,'Painel Additive'!$B8,'Data Additive'!$Q:$Q,"<=-31",'Data Additive'!$Q:$Q,">=-60") -> 0 | S8: =SUMIFS('Data Additive'!$D:$D,'Data Additive'!$P:$P,'Painel Additive'!$B8,'Data Additive'!$Q:$Q,"<=-61",'Data Additive'!$Q:$Q,">=-90") -> 0 | T8: =SUMIFS('Data Additive'!$D:$D,'Data Additive'!$P:$P,'Painel Additive'!$B8,'Data Additive'!$Q:$Q,"<=-91",'Data Additive'!$Q:$Q,">=-120") -> 0 | U8: =SUMIFS('Data Additive'!$D:$D,'Data Additive'!$P:$P,'Painel Additive'!$B8,'Data Additive'!$Q:$Q,"<=-121",'Data Additive'!$Q:$Q,">=-180") -> 0 | V8: =SUMIFS('Data Additive'!$D:$D,'Data Additive'!$P:$P,'Painel Additive'!$B8,'Data Additive'!$Q:$Q,"<=-181",'Data Additive'!$Q:$Q,">=-360") -> 0 | W8: =SUMIFS('Data Additive'!$D:$D,'Data Additive'!$P:$P,'Painel Additive'!$B8,'Data Additive'!$Q:$Q,"<-360") -> 0 | X8: =SUMIFS('Bad Debt Provision'!AB:AB,'Bad Debt Provision'!B:B,'Painel Additive'!B8) -> 0 | AA8: =IFERROR(_xlfn.XLOOKUP(B8,'Limite de crédito'!C:C,'Limite de crédito'!O:O,),0) -> 4000000 | AG8: =AA8-G8 -> 3941082.2 | AM8: 21461778
B9: GRUPO UNIFERTIL | C9: =IFERROR(_xlfn.XLOOKUP(B9,'Limite de crédito'!C:C,'Limite de crédito'!L:L,),0) -> B | E9: =_xlfn.XLOOKUP(B9,'Limite de crédito'!C:C,'Limite de crédito'!G:G,0) -> 3500000 | F9: =E9-G9 -> -173754.8 | G9: =P9+O9 -> 3673754.8 | H9: =SUMIFS('Data Additive'!$D:$D,'Data Additive'!$P:$P,'Painel Additive'!$B9,'Data Additive'!$Q:$Q,">0",'Data Additive'!$Q:$Q,"<=30") -> 0 | I9: =SUMIFS('Data Additive'!$D:$D,'Data Additive'!$P:$P,'Painel Additive'!$B9,'Data Additive'!$Q:$Q,">30",'Data Additive'!$Q:$Q,"<=60") -> 0 | J9: =SUMIFS('Data Additive'!$D:$D,'Data Additive'!$P:$P,'Painel Additive'!$B9,'Data Additive'!$Q:$Q,">60",'Data Additive'!$Q:$Q,"<=90") -> 0 | K9: =SUMIFS('Data Additive'!$D:$D,'Data Additive'!$P:$P,'Painel Additive'!$B9,'Data Additive'!$Q:$Q,">90",'Data Additive'!$Q:$Q,"<=120") -> 0 | L9: =SUMIFS('Data Additive'!$D:$D,'Data Additive'!$P:$P,'Painel Additive'!$B9,'Data Additive'!$Q:$Q,">120",'Data Additive'!$Q:$Q,"<=180") -> 0 | M9: =SUMIFS('Data Additive'!$D:$D,'Data Additive'!$P:$P,'Painel Additive'!$B9,'Data Additive'!$Q:$Q,">180",'Data Additive'!$Q:$Q,"<=360") -> 0 | N9: =SUMIFS('Data Additive'!$D:$D,'Data Additive'!$P:$P,'Painel Additive'!$B9,'Data Additive'!$Q:$Q,">360") -> 0 | O9: =SUMIFS('Data Additive'!$D:$D,'Data Additive'!$P:$P,'Painel Additive'!$B9,'Data Additive'!$Q:$Q,">0") -> 0 | P9: =SUM(Q9:W9) -> 3673754.8 | Q9: =SUMIFS('Data Additive'!$D:$D,'Data Additive'!$P:$P,'Painel Additive'!$B9,'Data Additive'!$Q:$Q,"<=0",'Data Additive'!$Q:$Q,">=-30") -> 956954.8 | R9: =SUMIFS('Data Additive'!$D:$D,'Data Additive'!$P:$P,'Painel Additive'!$B9,'Data Additive'!$Q:$Q,"<=-31",'Data Additive'!$Q:$Q,">=-60") -> 2716800 | S9: =SUMIFS('Data Additive'!$D:$D,'Data Additive'!$P:$P,'Painel Additive'!$B9,'Data Additive'!$Q:$Q,"<=-61",'Data Additive'!$Q:$Q,">=-90") -> 0 | T9: =SUMIFS('Data Additive'!$D:$D,'Data Additive'!$P:$P,'Painel Additive'!$B9,'Data Additive'!$Q:$Q,"<=-91",'Data Additive'!$Q:$Q,">=-120") -> 0 | U9: =SUMIFS('Data Additive'!$D:$D,'Data Additive'!$P:$P,'Painel Additive'!$B9,'Data Additive'!$Q:$Q,"<=-121",'Data Additive'!$Q:$Q,">=-180") -> 0 | V9: =SUMIFS('Data Additive'!$D:$D,'Data Additive'!$P:$P,'Painel Additive'!$B9,'Data Additive'!$Q:$Q,"<=-181",'Data Additive'!$Q:$Q,">=-360") -> 0 | W9: =SUMIFS('Data Additive'!$D:$D,'Data Additive'!$P:$P,'Painel Additive'!$B9,'Data Additive'!$Q:$Q,"<-360") -> 0 | X9: =SUMIFS('Bad Debt Provision'!AB:AB,'Bad Debt Provision'!B:B,'Painel Additive'!B9) -> 0 | AA9: =IFERROR(_xlfn.XLOOKUP(B9,'Limite de crédito'!C:C,'Limite de crédito'!O:O,),0) -> 3500000 | AG9: =AA9-G9 -> -173754.8 | AM9: =AM7+AM8 -> 1.1874277e+08
B10: GRUPO HINOVE | C10: =IFERROR(_xlfn.XLOOKUP(B10,'Limite de crédito'!C:C,'Limite de crédito'!L:L,),0) -> 0 | E10: =_xlfn.XLOOKUP(B10,'Limite de crédito'!C:C,'Limite de crédito'!G:G,0) -> 0 | F10: =E10-G10 -> -775264 | G10: =P10+O10 -> 775264 | H10: =SUMIFS('Data Additive'!$D:$D,'Data Additive'!$P:$P,'Painel Additive'!$B10,'Data Additive'!$Q:$Q,">0",'Data Additive'!$Q:$Q,"<=30") -> 0 | I10: =SUMIFS('Data Additive'!$D:$D,'Data Additive'!$P:$P,'Painel Additive'!$B10,'Data Additive'!$Q:$Q,">30",'Data Additive'!$Q:$Q,"<=60") -> 0 | J10: =SUMIFS('Data Additive'!$D:$D,'Data Additive'!$P:$P,'Painel Additive'!$B10,'Data Additive'!$Q:$Q,">60",'Data Additive'!$Q:$Q,"<=90") -> 0 | K10: =SUMIFS('Data Additive'!$D:$D,'Data Additive'!$P:$P,'Painel Additive'!$B10,'Data Additive'!$Q:$Q,">90",'Data Additive'!$Q:$Q,"<=120") -> 0 | L10: =SUMIFS('Data Additive'!$D:$D,'Data Additive'!$P:$P,'Painel Additive'!$B10,'Data Additive'!$Q:$Q,">120",'Data Additive'!$Q:$Q,"<=180") -> 0 | M10: =SUMIFS('Data Additive'!$D:$D,'Data Additive'!$P:$P,'Painel Additive'!$B10,'Data Additive'!$Q:$Q,">180",'Data Additive'!$Q:$Q,"<=360") -> 0 | N10: =SUMIFS('Data Additive'!$D:$D,'Data Additive'!$P:$P,'Painel Additive'!$B10,'Data Additive'!$Q:$Q,">360") -> 0 | O10: =SUMIFS('Data Additive'!$D:$D,'Data Additive'!$P:$P,'Painel Additive'!$B10,'Data Additive'!$Q:$Q,">0") -> 0 | P10: =SUM(Q10:W10) -> 775264 | Q10: =SUMIFS('Data Additive'!$D:$D,'Data Additive'!$P:$P,'Painel Additive'!$B10,'Data Additive'!$Q:$Q,"<=0",'Data Additive'!$Q:$Q,">=-30") -> 171254.1 | R10: =SUMIFS('Data Additive'!$D:$D,'Data Additive'!$P:$P,'Painel Additive'!$B10,'Data Additive'!$Q:$Q,"<=-31",'Data Additive'!$Q:$Q,">=-60") -> 459685.9 | S10: =SUMIFS('Data Additive'!$D:$D,'Data Additive'!$P:$P,'Painel Additive'!$B10,'Data Additive'!$Q:$Q,"<=-61",'Data Additive'!$Q:$Q,">=-90") -> 144324 | T10: =SUMIFS('Data Additive'!$D:$D,'Data Additive'!$P:$P,'Painel Additive'!$B10,'Data Additive'!$Q:$Q,"<=-91",'Data Additive'!$Q:$Q,">=-120") -> 0 | U10: =SUMIFS('Data Additive'!$D:$D,'Data Additive'!$P:$P,'Painel Additive'!$B10,'Data Additive'!$Q:$Q,"<=-121",'Data Additive'!$Q:$Q,">=-180") -> 0 | V10: =SUMIFS('Data Additive'!$D:$D,'Data Additive'!$P:$P,'Painel Additive'!$B10,'Data Additive'!$Q:$Q,"<=-181",'Data Additive'!$Q:$Q,">=-360") -> 0 | W10: =SUMIFS('Data Additive'!$D:$D,'Data Additive'!$P:$P,'Painel Additive'!$B10,'Data Additive'!$Q:$Q,"<-360") -> 0 | X10: =SUMIFS('Bad Debt Provision'!AB:AB,'Bad Debt Provision'!B:B,'Painel Additive'!B10) -> 0 | AA10: =IFERROR(_xlfn.XLOOKUP(B10,'Limite de crédito'!C:C,'Limite de crédito'!O:O,),0) -> 0 | AG10: =AA10-G10 -> -775264 | AM10: =AM9*-1/AM6 -> -3.0294595
B11: FERTGROW - SÃO LUIS | C11: =IFERROR(_xlfn.XLOOKUP(B11,'Limite de crédito'!C:C,'Limite de crédito'!L:L,),0) -> 0 | E11: =_xlfn.XLOOKUP(B11,'Limite de crédito'!C:C,'Limite de crédito'!G:G,0) -> 0 | F11: =E11-G11 -> 0 | G11: =P11+O11 -> 0 | H11: =SUMIFS('Data Additive'!$D:$D,'Data Additive'!$P:$P,'Painel Additive'!$B11,'Data Additive'!$Q:$Q,">0",'Data Additive'!$Q:$Q,"<=30") -> 0 | I11: =SUMIFS('Data Additive'!$D:$D,'Data Additive'!$P:$P,'Painel Additive'!$B11,'Data Additive'!$Q:$Q,">30",'Data Additive'!$Q:$Q,"<=60") -> 0 | J11: =SUMIFS('Data Additive'!$D:$D,'Data Additive'!$P:$P,'Painel Additive'!$B11,'Data Additive'!$Q:$Q,">60",'Data Additive'!$Q:$Q,"<=90") -> 0 | K11: =SUMIFS('Data Additive'!$D:$D,'Data Additive'!$P:$P,'Painel Additive'!$B11,'Data Additive'!$Q:$Q,">90",'Data Additive'!$Q:$Q,"<=120") -> 0 | L11: =SUMIFS('Data Additive'!$D:$D,'Data Additive'!$P:$P,'Painel Additive'!$B11,'Data Additive'!$Q:$Q,">120",'Data Additive'!$Q:$Q,"<=180") -> 0 | M11: =SUMIFS('Data Additive'!$D:$D,'Data Additive'!$P:$P,'Painel Additive'!$B11,'Data Additive'!$Q:$Q,">180",'Data Additive'!$Q:$Q,"<=360") -> 0 | N11: =SUMIFS('Data Additive'!$D:$D,'Data Additive'!$P:$P,'Painel Additive'!$B11,'Data Additive'!$Q:$Q,">360") -> 0 | O11: =SUMIFS('Data Additive'!$D:$D,'Data Additive'!$P:$P,'Painel Additive'!$B11,'Data Additive'!$Q:$Q,">0") -> 0 | P11: =SUM(Q11:W11) -> 0 | Q11: =SUMIFS('Data Additive'!$D:$D,'Data Additive'!$P:$P,'Painel Additive'!$B11,'Data Additive'!$Q:$Q,"<=0",'Data Additive'!$Q:$Q,">=-30") -> 0 | R11: =SUMIFS('Data Additive'!$D:$D,'Data Additive'!$P:$P,'Painel Additive'!$B11,'Data Additive'!$Q:$Q,"<=-31",'Data Additive'!$Q:$Q,">=-60") -> 0 | S11: =SUMIFS('Data Additive'!$D:$D,'Data Additive'!$P:$P,'Painel Additive'!$B11,'Data Additive'!$Q:$Q,"<=-61",'Data Additive'!$Q:$Q,">=-90") -> 0 | T11: =SUMIFS('Data Additive'!$D:$D,'Data Additive'!$P:$P,'Painel Additive'!$B11,'Data Additive'!$Q:$Q,"<=-91",'Data Additive'!$Q:$Q,">=-120") -> 0 | U11: =SUMIFS('Data Additive'!$D:$D,'Data Additive'!$P:$P,'Painel Additive'!$B11,'Data Additive'!$Q:$Q,"<=-121",'Data Additive'!$Q:$Q,">=-180") -> 0 | V11: =SUMIFS('Data Additive'!$D:$D,'Data Additive'!$P:$P,'Painel Additive'!$B11,'Data Additive'!$Q:$Q,"<=-181",'Data Additive'!$Q:$Q,">=-360") -> 0 | W11: =SUMIFS('Data Additive'!$D:$D,'Data Additive'!$P:$P,'Painel Additive'!$B11,'Data Additive'!$Q:$Q,"<-360") -> 0 | X11: =SUMIFS('Bad Debt Provision'!AB:AB,'Bad Debt Provision'!B:B,'Painel Additive'!B11) -> 0 | AA11: =IFERROR(_xlfn.XLOOKUP(B11,'Limite de crédito'!C:C,'Limite de crédito'!O:O,),0) -> 0 | AG11: =AA11-G11 -> 0
B12: GRUPO GEN FERTILIZANTES | C12: =IFERROR(_xlfn.XLOOKUP(B12,'Limite de crédito'!C:C,'Limite de crédito'!L:L,),0) -> B | E12: =_xlfn.XLOOKUP(B12,'Limite de crédito'!C:C,'Limite de crédito'!G:G,0) -> 2000000 | F12: =E12-G12 -> 2000000 | G12: =P12+O12 -> 0 | H12: =SUMIFS('Data Additive'!$D:$D,'Data Additive'!$P:$P,'Painel Additive'!$B12,'Data Additive'!$Q:$Q,">0",'Data Additive'!$Q:$Q,"<=30") -> 0 | I12: =SUMIFS('Data Additive'!$D:$D,'Data Additive'!$P:$P,'Painel Additive'!$B12,'Data Additive'!$Q:$Q,">30",'Data Additive'!$Q:$Q,"<=60") -> 0 | J12: =SUMIFS('Data Additive'!$D:$D,'Data Additive'!$P:$P,'Painel Additive'!$B12,'Data Additive'!$Q:$Q,">60",'Data Additive'!$Q:$Q,"<=90") -> 0 | K12: =SUMIFS('Data Additive'!$D:$D,'Data Additive'!$P:$P,'Painel Additive'!$B12,'Data Additive'!$Q:$Q,">90",'Data Additive'!$Q:$Q,"<=120") -> 0 | L12: =SUMIFS('Data Additive'!$D:$D,'Data Additive'!$P:$P,'Painel Additive'!$B12,'Data Additive'!$Q:$Q,">120",'Data Additive'!$Q:$Q,"<=180") -> 0 | M12: =SUMIFS('Data Additive'!$D:$D,'Data Additive'!$P:$P,'Painel Additive'!$B12,'Data Additive'!$Q:$Q,">180",'Data Additive'!$Q:$Q,"<=360") -> 0 | N12: =SUMIFS('Data Additive'!$D:$D,'Data Additive'!$P:$P,'Painel Additive'!$B12,'Data Additive'!$Q:$Q,">360") -> 0 | O12: =SUMIFS('Data Additive'!$D:$D,'Data Additive'!$P:$P,'Painel Additive'!$B12,'Data Additive'!$Q:$Q,">0") -> 0 | P12: =SUM(Q12:W12) -> 0 | Q12: =SUMIFS('Data Additive'!$D:$D,'Data Additive'!$P:$P,'Painel Additive'!$B12,'Data Additive'!$Q:$Q,"<=0",'Data Additive'!$Q:$Q,">=-30") -> 0 | R12: =SUMIFS('Data Additive'!$D:$D,'Data Additive'!$P:$P,'Painel Additive'!$B12,'Data Additive'!$Q:$Q,"<=-31",'Data Additive'!$Q:$Q,">=-60") -> 0 | S12: =SUMIFS('Data Additive'!$D:$D,'Data Additive'!$P:$P,'Painel Additive'!$B12,'Data Additive'!$Q:$Q,"<=-61",'Data Additive'!$Q:$Q,">=-90") -> 0 | T12: =SUMIFS('Data Additive'!$D:$D,'Data Additive'!$P:$P,'Painel Additive'!$B12,'Data Additive'!$Q:$Q,"<=-91",'Data Additive'!$Q:$Q,">=-120") -> 0 | U12: =SUMIFS('Data Additive'!$D:$D,'Data Additive'!$P:$P,'Painel Additive'!$B12,'Data Additive'!$Q:$Q,"<=-121",'Data Additive'!$Q:$Q,">=-180") -> 0 | V12: =SUMIFS('Data Additive'!$D:$D,'Data Additive'!$P:$P,'Painel Additive'!$B12,'Data Additive'!$Q:$Q,"<=-181",'Data Additive'!$Q:$Q,">=-360") -> 0 | W12: =SUMIFS('Data Additive'!$D:$D,'Data Additive'!$P:$P,'Painel Additive'!$B12,'Data Additive'!$Q:$Q,"<-360") -> 0 | X12: =SUMIFS('Bad Debt Provision'!AB:AB,'Bad Debt Provision'!B:B,'Painel Additive'!B12) -> 0 | AA12: =IFERROR(_xlfn.XLOOKUP(B12,'Limite de crédito'!C:C,'Limite de crédito'!O:O,),0) -> 2000000 | AG12: =AA12-G12 -> 2000000
B13: FOSNOR - LUIS EDUARDO MAGALHAES | C13: =IFERROR(_xlfn.XLOOKUP(B13,'Limite de crédito'!C:C,'Limite de crédito'!L:L,),0) -> B | E13: =_xlfn.XLOOKUP(B13,'Limite de crédito'!C:C,'Limite de crédito'!G:G,0) -> 2600000 | F13: =E13-G13 -> 2076372.5 | G13: =P13+O13 -> 523627.5 | H13: =SUMIFS('Data Additive'!$D:$D,'Data Additive'!$P:$P,'Painel Additive'!$B13,'Data Additive'!$Q:$Q,">0",'Data Additive'!$Q:$Q,"<=30") -> 0 | I13: =SUMIFS('Data Additive'!$D:$D,'Data Additive'!$P:$P,'Painel Additive'!$B13,'Data Additive'!$Q:$Q,">30",'Data Additive'!$Q:$Q,"<=60") -> 0 | J13: =SUMIFS('Data Additive'!$D:$D,'Data Additive'!$P:$P,'Painel Additive'!$B13,'Data Additive'!$Q:$Q,">60",'Data Additive'!$Q:$Q,"<=90") -> 0 | K13: =SUMIFS('Data Additive'!$D:$D,'Data Additive'!$P:$P,'Painel Additive'!$B13,'Data Additive'!$Q:$Q,">90",'Data Additive'!$Q:$Q,"<=120") -> 0 | L13: =SUMIFS('Data Additive'!$D:$D,'Data Additive'!$P:$P,'Painel Additive'!$B13,'Data Additive'!$Q:$Q,">120",'Data Additive'!$Q:$Q,"<=180") -> 0 | M13: =SUMIFS('Data Additive'!$D:$D,'Data Additive'!$P:$P,'Painel Additive'!$B13,'Data Additive'!$Q:$Q,">180",'Data Additive'!$Q:$Q,"<=360") -> 0 | N13: =SUMIFS('Data Additive'!$D:$D,'Data Additive'!$P:$P,'Painel Additive'!$B13,'Data Additive'!$Q:$Q,">360") -> 0 | O13: =SUMIFS('Data Additive'!$D:$D,'Data Additive'!$P:$P,'Painel Additive'!$B13,'Data Additive'!$Q:$Q,">0") -> 0 | P13: =SUM(Q13:W13) -> 523627.5 | Q13: =SUMIFS('Data Additive'!$D:$D,'Data Additive'!$P:$P,'Painel Additive'!$B13,'Data Additive'!$Q:$Q,"<=0",'Data Additive'!$Q:$Q,">=-30") -> 523627.5 | R13: =SUMIFS('Data Additive'!$D:$D,'Data Additive'!$P:$P,'Painel Additive'!$B13,'Data Additive'!$Q:$Q,"<=-31",'Data Additive'!$Q:$Q,">=-60") -> 0 | S13: =SUMIFS('Data Additive'!$D:$D,'Data Additive'!$P:$P,'Painel Additive'!$B13,'Data Additive'!$Q:$Q,"<=-61",'Data Additive'!$Q:$Q,">=-90") -> 0 | T13: =SUMIFS('Data Additive'!$D:$D,'Data Additive'!$P:$P,'Painel Additive'!$B13,'Data Additive'!$Q:$Q,"<=-91",'Data Additive'!$Q:$Q,">=-120") -> 0 | U13: =SUMIFS('Data Additive'!$D:$D,'Data Additive'!$P:$P,'Painel Additive'!$B13,'Data Additive'!$Q:$Q,"<=-121",'Data Additive'!$Q:$Q,">=-180") -> 0 | V13: =SUMIFS('Data Additive'!$D:$D,'Data Additive'!$P:$P,'Painel Additive'!$B13,'Data Additive'!$Q:$Q,"<=-181",'Data Additive'!$Q:$Q,">=-360") -> 0 | W13: =SUMIFS('Data Additive'!$D:$D,'Data Additive'!$P:$P,'Painel Additive'!$B13,'Data Additive'!$Q:$Q,"<-360") -> 0 | X13: =SUMIFS('Bad Debt Provision'!AB:AB,'Bad Debt Provision'!B:B,'Painel Additive'!B13) -> 0 | AA13: =IFERROR(_xlfn.XLOOKUP(B13,'Limite de crédito'!C:C,'Limite de crédito'!O:O,),0) -> 2600000 | AG13: =AA13-G13 -> 2076372.5
B14: ADUFERTIL JUNDIAI | C14: =IFERROR(_xlfn.XLOOKUP(B14,'Limite de crédito'!C:C,'Limite de crédito'!L:L,),0) -> B | E14: =_xlfn.XLOOKUP(B14,'Limite de crédito'!C:C,'Limite de crédito'!G:G,0) -> 3000000 | F14: =E14-G14 -> 2589143.5 | G14: =P14+O14 -> 410856.52 | H14: =SUMIFS('Data Additive'!$D:$D,'Data Additive'!$P:$P,'Painel Additive'!$B14,'Data Additive'!$Q:$Q,">0",'Data Additive'!$Q:$Q,"<=30") -> 0 | I14: =SUMIFS('Data Additive'!$D:$D,'Data Additive'!$P:$P,'Painel Additive'!$B14,'Data Additive'!$Q:$Q,">30",'Data Additive'!$Q:$Q,"<=60") -> 0 | J14: =SUMIFS('Data Additive'!$D:$D,'Data Additive'!$P:$P,'Painel Additive'!$B14,'Data Additive'!$Q:$Q,">60",'Data Additive'!$Q:$Q,"<=90") -> 0 | K14: =SUMIFS('Data Additive'!$D:$D,'Data Additive'!$P:$P,'Painel Additive'!$B14,'Data Additive'!$Q:$Q,">90",'Data Additive'!$Q:$Q,"<=120") -> 0 | L14: =SUMIFS('Data Additive'!$D:$D,'Data Additive'!$P:$P,'Painel Additive'!$B14,'Data Additive'!$Q:$Q,">120",'Data Additive'!$Q:$Q,"<=180") -> 0 | M14: =SUMIFS('Data Additive'!$D:$D,'Data Additive'!$P:$P,'Painel Additive'!$B14,'Data Additive'!$Q:$Q,">180",'Data Additive'!$Q:$Q,"<=360") -> 0 | N14: =SUMIFS('Data Additive'!$D:$D,'Data Additive'!$P:$P,'Painel Additive'!$B14,'Data Additive'!$Q:$Q,">360") -> 0 | O14: =SUMIFS('Data Additive'!$D:$D,'Data Additive'!$P:$P,'Painel Additive'!$B14,'Data Additive'!$Q:$Q,">0") -> 0 | P14: =SUM(Q14:W14) -> 410856.52 | Q14: =SUMIFS('Data Additive'!$D:$D,'Data Additive'!$P:$P,'Painel Additive'!$B14,'Data Additive'!$Q:$Q,"<=0",'Data Additive'!$Q:$Q,">=-30") -> 0 | R14: =SUMIFS('Data Additive'!$D:$D,'Data Additive'!$P:$P,'Painel Additive'!$B14,'Data Additive'!$Q:$Q,"<=-31",'Data Additive'!$Q:$Q,">=-60") -> 410856.52 | S14: =SUMIFS('Data Additive'!$D:$D,'Data Additive'!$P:$P,'Painel Additive'!$B14,'Data Additive'!$Q:$Q,"<=-61",'Data Additive'!$Q:$Q,">=-90") -> 0 | T14: =SUMIFS('Data Additive'!$D:$D,'Data Additive'!$P:$P,'Painel Additive'!$B14,'Data Additive'!$Q:$Q,"<=-91",'Data Additive'!$Q:$Q,">=-120") -> 0 | U14: =SUMIFS('Data Additive'!$D:$D,'Data Additive'!$P:$P,'Painel Additive'!$B14,'Data Additive'!$Q:$Q,"<=-121",'Data Additive'!$Q:$Q,">=-180") -> 0 | V14: =SUMIFS('Data Additive'!$D:$D,'Data Additive'!$P:$P,'Painel Additive'!$B14,'Data Additive'!$Q:$Q,"<=-181",'Data Additive'!$Q:$Q,">=-360") -> 0 | W14: =SUMIFS('Data Additive'!$D:$D,'Data Additive'!$P:$P,'Painel Additive'!$B14,'Data Additive'!$Q:$Q,"<-360") -> 0 | X14: =SUMIFS('Bad Debt Provision'!AB:AB,'Bad Debt Provision'!B:B,'Painel Additive'!B14) -> 0 | AA14: =IFERROR(_xlfn.XLOOKUP(B14,'Limite de crédito'!C:C,'Limite de crédito'!O:O,),0) -> 3000000 | AG14: =AA14-G14 -> 2589143.5
B15: AURORA MINERAÇÃO LTDA | C15: =IFERROR(_xlfn.XLOOKUP(B15,'Limite de crédito'!C:C,'Limite de crédito'!L:L,),0) -> 0 | E15: =_xlfn.XLOOKUP(B15,'Limite de crédito'!C:C,'Limite de crédito'!G:G,0) -> 270000 | F15: =E15-G15 -> 80971.3 | G15: =P15+O15 -> 189028.7 | H15: =SUMIFS('Data Additive'!$D:$D,'Data Additive'!$P:$P,'Painel Additive'!$B15,'Data Additive'!$Q:$Q,">0",'Data Additive'!$Q:$Q,"<=30") -> 37491.5 | I15: =SUMIFS('Data Additive'!$D:$D,'Data Additive'!$P:$P,'Painel Additive'!$B15,'Data Additive'!$Q:$Q,">30",'Data Additive'!$Q:$Q,"<=60") -> 0 | J15: =SUMIFS('Data Additive'!$D:$D,'Data Additive'!$P:$P,'Painel Additive'!$B15,'Data Additive'!$Q:$Q,">60",'Data Additive'!$Q:$Q,"<=90") -> 0 | K15: =SUMIFS('Data Additive'!$D:$D,'Data Additive'!$P:$P,'Painel Additive'!$B15,'Data Additive'!$Q:$Q,">90",'Data Additive'!$Q:$Q,"<=120") -> 0 | L15: =SUMIFS('Data Additive'!$D:$D,'Data Additive'!$P:$P,'Painel Additive'!$B15,'Data Additive'!$Q:$Q,">120",'Data Additive'!$Q:$Q,"<=180") -> 0 | M15: =SUMIFS('Data Additive'!$D:$D,'Data Additive'!$P:$P,'Painel Additive'!$B15,'Data Additive'!$Q:$Q,">180",'Data Additive'!$Q:$Q,"<=360") -> 0 | N15: =SUMIFS('Data Additive'!$D:$D,'Data Additive'!$P:$P,'Painel Additive'!$B15,'Data Additive'!$Q:$Q,">360") -> 0 | O15: =SUMIFS('Data Additive'!$D:$D,'Data Additive'!$P:$P,'Painel Additive'!$B15,'Data Additive'!$Q:$Q,">0") -> 37491.5 | P15: =SUM(Q15:W15) -> 151537.2 | Q15: =SUMIFS('Data Additive'!$D:$D,'Data Additive'!$P:$P,'Painel Additive'!$B15,'Data Additive'!$Q:$Q,"<=0",'Data Additive'!$Q:$Q,">=-30") -> 75216.8 | R15: =SUMIFS('Data Additive'!$D:$D,'Data Additive'!$P:$P,'Painel Additive'!$B15,'Data Additive'!$Q:$Q,"<=-31",'Data Additive'!$Q:$Q,">=-60") -> 76320.4 | S15: =SUMIFS('Data Additive'!$D:$D,'Data Additive'!$P:$P,'Painel Additive'!$B15,'Data Additive'!$Q:$Q,"<=-61",'Data Additive'!$Q:$Q,">=-90") -> 0 | T15: =SUMIFS('Data Additive'!$D:$D,'Data Additive'!$P:$P,'Painel Additive'!$B15,'Data Additive'!$Q:$Q,"<=-91",'Data Additive'!$Q:$Q,">=-120") -> 0 | U15: =SUMIFS('Data Additive'!$D:$D,'Data Additive'!$P:$P,'Painel Additive'!$B15,'Data Additive'!$Q:$Q,"<=-121",'Data Additive'!$Q:$Q,">=-180") -> 0 | V15: =SUMIFS('Data Additive'!$D:$D,'Data Additive'!$P:$P,'Painel Additive'!$B15,'Data Additive'!$Q:$Q,"<=-181",'Data Additive'!$Q:$Q,">=-360") -> 0 | W15: =SUMIFS('Data Additive'!$D:$D,'Data Additive'!$P:$P,'Painel Additive'!$B15,'Data Additive'!$Q:$Q,"<-360") -> 0 | X15: =SUMIFS('Bad Debt Provision'!AB:AB,'Bad Debt Provision'!B:B,'Painel Additive'!B15) -> 0 | AA15: =IFERROR(_xlfn.XLOOKUP(B15,'Limite de crédito'!C:C,'Limite de crédito'!O:O,),0) -> 0 | AG15: =AA15-G15 -> -189028.7
B16: COONAGRO COOPERATIVA - PARANAGUA | C16: =IFERROR(_xlfn.XLOOKUP(B16,'Limite de crédito'!C:C,'Limite de crédito'!L:L,),0) -> B | E16: =_xlfn.XLOOKUP(B16,'Limite de crédito'!C:C,'Limite de crédito'!G:G,0) -> 2500000 | F16: =E16-G16 -> 2419920.7 | G16: =P16+O16 -> 80079.3 | H16: =SUMIFS('Data Additive'!$D:$D,'Data Additive'!$P:$P,'Painel Additive'!$B16,'Data Additive'!$Q:$Q,">0",'Data Additive'!$Q:$Q,"<=30") -> 0 | I16: =SUMIFS('Data Additive'!$D:$D,'Data Additive'!$P:$P,'Painel Additive'!$B16,'Data Additive'!$Q:$Q,">30",'Data Additive'!$Q:$Q,"<=60") -> 0 | J16: =SUMIFS('Data Additive'!$D:$D,'Data Additive'!$P:$P,'Painel Additive'!$B16,'Data Additive'!$Q:$Q,">60",'Data Additive'!$Q:$Q,"<=90") -> 0 | K16: =SUMIFS('Data Additive'!$D:$D,'Data Additive'!$P:$P,'Painel Additive'!$B16,'Data Additive'!$Q:$Q,">90",'Data Additive'!$Q:$Q,"<=120") -> 0 | L16: =SUMIFS('Data Additive'!$D:$D,'Data Additive'!$P:$P,'Painel Additive'!$B16,'Data Additive'!$Q:$Q,">120",'Data Additive'!$Q:$Q,"<=180") -> 0 | M16: =SUMIFS('Data Additive'!$D:$D,'Data Additive'!$P:$P,'Painel Additive'!$B16,'Data Additive'!$Q:$Q,">180",'Data Additive'!$Q:$Q,"<=360") -> 0 | N16: =SUMIFS('Data Additive'!$D:$D,'Data Additive'!$P:$P,'Painel Additive'!$B16,'Data Additive'!$Q:$Q,">360") -> 0 | O16: =SUMIFS('Data Additive'!$D:$D,'Data Additive'!$P:$P,'Painel Additive'!$B16,'Data Additive'!$Q:$Q,">0") -> 0 | P16: =SUM(Q16:W16) -> 80079.3 | Q16: =SUMIFS('Data Additive'!$D:$D,'Data Additive'!$P:$P,'Painel Additive'!$B16,'Data Additive'!$Q:$Q,"<=0",'Data Additive'!$Q:$Q,">=-30") -> 80079.3 | R16: =SUMIFS('Data Additive'!$D:$D,'Data Additive'!$P:$P,'Painel Additive'!$B16,'Data Additive'!$Q:$Q,"<=-31",'Data Additive'!$Q:$Q,">=-60") -> 0 | S16: =SUMIFS('Data Additive'!$D:$D,'Data Additive'!$P:$P,'Painel Additive'!$B16,'Data Additive'!$Q:$Q,"<=-61",'Data Additive'!$Q:$Q,">=-90") -> 0 | T16: =SUMIFS('Data Additive'!$D:$D,'Data Additive'!$P:$P,'Painel Additive'!$B16,'Data Additive'!$Q:$Q,"<=-91",'Data Additive'!$Q:$Q,">=-120") -> 0 | U16: =SUMIFS('Data Additive'!$D:$D,'Data Additive'!$P:$P,'Painel Additive'!$B16,'Data Additive'!$Q:$Q,"<=-121",'Data Additive'!$Q:$Q,">=-180") -> 0 | V16: =SUMIFS('Data Additive'!$D:$D,'Data Additive'!$P:$P,'Painel Additive'!$B16,'Data Additive'!$Q:$Q,"<=-181",'Data Additive'!$Q:$Q,">=-360") -> 0 | W16: =SUMIFS('Data Additive'!$D:$D,'Data Additive'!$P:$P,'Painel Additive'!$B16,'Data Additive'!$Q:$Q,"<-360") -> 0 | X16: =SUMIFS('Bad Debt Provision'!AB:AB,'Bad Debt Provision'!B:B,'Painel Additive'!B16) -> 0 | AA16: =IFERROR(_xlfn.XLOOKUP(B16,'Limite de crédito'!C:C,'Limite de crédito'!O:O,),0) -> 2500000 | AG16: =AA16-G16 -> 2419920.7
B17: TERRA FERTILIZANTES LTDA - ARAXÁ | C17: =IFERROR(_xlfn.XLOOKUP(B17,'Limite de crédito'!C:C,'Limite de crédito'!L:L,),0) -> 0 | E17: =_xlfn.XLOOKUP(B17,'Limite de crédito'!C:C,'Limite de crédito'!G:G,0) -> 0 | F17: =E17-G17 -> -226233.6 | G17: =P17+O17 -> 226233.6 | H17: =SUMIFS('Data Additive'!$D:$D,'Data Additive'!$P:$P,'Painel Additive'!$B17,'Data Additive'!$Q:$Q,">0",'Data Additive'!$Q:$Q,"<=30") -> 0 | I17: =SUMIFS('Data Additive'!$D:$D,'Data Additive'!$P:$P,'Painel Additive'!$B17,'Data Additive'!$Q:$Q,">30",'Data Additive'!$Q:$Q,"<=60") -> 0 | J17: =SUMIFS('Data Additive'!$D:$D,'Data Additive'!$P:$P,'Painel Additive'!$B17,'Data Additive'!$Q:$Q,">60",'Data Additive'!$Q:$Q,"<=90") -> 0 | K17: =SUMIFS('Data Additive'!$D:$D,'Data Additive'!$P:$P,'Painel Additive'!$B17,'Data Additive'!$Q:$Q,">90",'Data Additive'!$Q:$Q,"<=120") -> 0 | L17: =SUMIFS('Data Additive'!$D:$D,'Data Additive'!$P:$P,'Painel Additive'!$B17,'Data Additive'!$Q:$Q,">120",'Data Additive'!$Q:$Q,"<=180") -> 0 | M17: =SUMIFS('Data Additive'!$D:$D,'Data Additive'!$P:$P,'Painel Additive'!$B17,'Data Additive'!$Q:$Q,">180",'Data Additive'!$Q:$Q,"<=360") -> 0 | N17: =SUMIFS('Data Additive'!$D:$D,'Data Additive'!$P:$P,'Painel Additive'!$B17,'Data Additive'!$Q:$Q,">360") -> 226233.6 | O17: =SUMIFS('Data Additive'!$D:$D,'Data Additive'!$P:$P,'Painel Additive'!$B17,'Data Additive'!$Q:$Q,">0") -> 226233.6 | P17: =SUM(Q17:W17) -> 0 | Q17: =SUMIFS('Data Additive'!$D:$D,'Data Additive'!$P:$P,'Painel Additive'!$B17,'Data Additive'!$Q:$Q,"<=0",'Data Additive'!$Q:$Q,">=-30") -> 0 | R17: =SUMIFS('Data Additive'!$D:$D,'Data Additive'!$P:$P,'Painel Additive'!$B17,'Data Additive'!$Q:$Q,"<=-31",'Data Additive'!$Q:$Q,">=-60") -> 0 | S17: =SUMIFS('Data Additive'!$D:$D,'Data Additive'!$P:$P,'Painel Additive'!$B17,'Data Additive'!$Q:$Q,"<=-61",'Data Additive'!$Q:$Q,">=-90") -> 0 | T17: =SUMIFS('Data Additive'!$D:$D,'Data Additive'!$P:$P,'Painel Additive'!$B17,'Data Additive'!$Q:$Q,"<=-91",'Data Additive'!$Q:$Q,">=-120") -> 0 | U17: =SUMIFS('Data Additive'!$D:$D,'Data Additive'!$P:$P,'Painel Additive'!$B17,'Data Additive'!$Q:$Q,"<=-121",'Data Additive'!$Q:$Q,">=-180") -> 0 | V17: =SUMIFS('Data Additive'!$D:$D,'Data Additive'!$P:$P,'Painel Additive'!$B17,'Data Additive'!$Q:$Q,"<=-181",'Data Additive'!$Q:$Q,">=-360") -> 0 | W17: =SUMIFS('Data Additive'!$D:$D,'Data Additive'!$P:$P,'Painel Additive'!$B17,'Data Additive'!$Q:$Q,"<-360") -> 0 | X17: =SUMIFS('Bad Debt Provision'!AB:AB,'Bad Debt Provision'!B:B,'Painel Additive'!B17) -> 226233.6 | AA17: =IFERROR(_xlfn.XLOOKUP(B17,'Limite de crédito'!C:C,'Limite de crédito'!O:O,),0) -> 0 | AG17: =AA17-G17 -> -226233.6
B18: ITERUM - RONDONOPOLIS | C18: =IFERROR(_xlfn.XLOOKUP(B18,'Limite de crédito'!C:C,'Limite de crédito'!L:L,),0) -> 0 | E18: =_xlfn.XLOOKUP(B18,'Limite de crédito'!C:C,'Limite de crédito'!G:G,0) -> 0 | F18: =E18-G18 -> -213750 | G18: =P18+O18 -> 213750 | H18: =SUMIFS('Data Additive'!$D:$D,'Data Additive'!$P:$P,'Painel Additive'!$B18,'Data Additive'!$Q:$Q,">0",'Data Additive'!$Q:$Q,"<=30") -> 0 | I18: =SUMIFS('Data Additive'!$D:$D,'Data Additive'!$P:$P,'Painel Additive'!$B18,'Data Additive'!$Q:$Q,">30",'Data Additive'!$Q:$Q,"<=60") -> 0 | J18: =SUMIFS('Data Additive'!$D:$D,'Data Additive'!$P:$P,'Painel Additive'!$B18,'Data Additive'!$Q:$Q,">60",'Data Additive'!$Q:$Q,"<=90") -> 0 | K18: =SUMIFS('Data Additive'!$D:$D,'Data Additive'!$P:$P,'Painel Additive'!$B18,'Data Additive'!$Q:$Q,">90",'Data Additive'!$Q:$Q,"<=120") -> 0 | L18: =SUMIFS('Data Additive'!$D:$D,'Data Additive'!$P:$P,'Painel Additive'!$B18,'Data Additive'!$Q:$Q,">120",'Data Additive'!$Q:$Q,"<=180") -> 0 | M18: =SUMIFS('Data Additive'!$D:$D,'Data Additive'!$P:$P,'Painel Additive'!$B18,'Data Additive'!$Q:$Q,">180",'Data Additive'!$Q:$Q,"<=360") -> 0 | N18: =SUMIFS('Data Additive'!$D:$D,'Data Additive'!$P:$P,'Painel Additive'!$B18,'Data Additive'!$Q:$Q,">360") -> 213750 | O18: =SUMIFS('Data Additive'!$D:$D,'Data Additive'!$P:$P,'Painel Additive'!$B18,'Data Additive'!$Q:$Q,">0") -> 213750 | P18: =SUM(Q18:W18) -> 0 | Q18: =SUMIFS('Data Additive'!$D:$D,'Data Additive'!$P:$P,'Painel Additive'!$B18,'Data Additive'!$Q:$Q,"<=0",'Data Additive'!$Q:$Q,">=-30") -> 0 | R18: =SUMIFS('Data Additive'!$D:$D,'Data Additive'!$P:$P,'Painel Additive'!$B18,'Data Additive'!$Q:$Q,"<=-31",'Data Additive'!$Q:$Q,">=-60") -> 0 | S18: =SUMIFS('Data Additive'!$D:$D,'Data Additive'!$P:$P,'Painel Additive'!$B18,'Data Additive'!$Q:$Q,"<=-61",'Data Additive'!$Q:$Q,">=-90") -> 0 | T18: =SUMIFS('Data Additive'!$D:$D,'Data Additive'!$P:$P,'Painel Additive'!$B18,'Data Additive'!$Q:$Q,"<=-91",'Data Additive'!$Q:$Q,">=-120") -> 0 | U18: =SUMIFS('Data Additive'!$D:$D,'Data Additive'!$P:$P,'Painel Additive'!$B18,'Data Additive'!$Q:$Q,"<=-121",'Data Additive'!$Q:$Q,">=-180") -> 0 | V18: =SUMIFS('Data Additive'!$D:$D,'Data Additive'!$P:$P,'Painel Additive'!$B18,'Data Additive'!$Q:$Q,"<=-181",'Data Additive'!$Q:$Q,">=-360") -> 0 | W18: =SUMIFS('Data Additive'!$D:$D,'Data Additive'!$P:$P,'Painel Additive'!$B18,'Data Additive'!$Q:$Q,"<-360") -> 0 | X18: =SUMIFS('Bad Debt Provision'!AB:AB,'Bad Debt Provision'!B:B,'Painel Additive'!B18) -> 213750 | AA18: =IFERROR(_xlfn.XLOOKUP(B18,'Limite de crédito'!C:C,'Limite de crédito'!O:O,),0) -> 0 | AG18: =AA18-G18 -> -213750
B19: GRUPO FERTILIZE | C19: =IFERROR(_xlfn.XLOOKUP(B19,'Limite de crédito'!C:C,'Limite de crédito'!L:L,),0) -> B | E19: =_xlfn.XLOOKUP(B19,'Limite de crédito'!C:C,'Limite de crédito'!G:G,0) -> 1500000 | F19: =E19-G19 -> 1500000 | G19: =P19+O19 -> 0 | H19: =SUMIFS('Data Additive'!$D:$D,'Data Additive'!$P:$P,'Painel Additive'!$B19,'Data Additive'!$Q:$Q,">0",'Data Additive'!$Q:$Q,"<=30") -> 0 | I19: =SUMIFS('Data Additive'!$D:$D,'Data Additive'!$P:$P,'Painel Additive'!$B19,'Data Additive'!$Q:$Q,">30",'Data Additive'!$Q:$Q,"<=60") -> 0 | J19: =SUMIFS('Data Additive'!$D:$D,'Data Additive'!$P:$P,'Painel Additive'!$B19,'Data Additive'!$Q:$Q,">60",'Data Additive'!$Q:$Q,"<=90") -> 0 | K19: =SUMIFS('Data Additive'!$D:$D,'Data Additive'!$P:$P,'Painel Additive'!$B19,'Data Additive'!$Q:$Q,">90",'Data Additive'!$Q:$Q,"<=120") -> 0 | L19: =SUMIFS('Data Additive'!$D:$D,'Data Additive'!$P:$P,'Painel Additive'!$B19,'Data Additive'!$Q:$Q,">120",'Data Additive'!$Q:$Q,"<=180") -> 0 | M19: =SUMIFS('Data Additive'!$D:$D,'Data Additive'!$P:$P,'Painel Additive'!$B19,'Data Additive'!$Q:$Q,">180",'Data Additive'!$Q:$Q,"<=360") -> 0 | N19: =SUMIFS('Data Additive'!$D:$D,'Data Additive'!$P:$P,'Painel Additive'!$B19,'Data Additive'!$Q:$Q,">360") -> 0 | O19: =SUMIFS('Data Additive'!$D:$D,'Data Additive'!$P:$P,'Painel Additive'!$B19,'Data Additive'!$Q:$Q,">0") -> 0 | P19: =SUM(Q19:W19) -> 0 | Q19: =SUMIFS('Data Additive'!$D:$D,'Data Additive'!$P:$P,'Painel Additive'!$B19,'Data Additive'!$Q:$Q,"<=0",'Data Additive'!$Q:$Q,">=-30") -> 0 | R19: =SUMIFS('Data Additive'!$D:$D,'Data Additive'!$P:$P,'Painel Additive'!$B19,'Data Additive'!$Q:$Q,"<=-31",'Data Additive'!$Q:$Q,">=-60") -> 0 | S19: =SUMIFS('Data Additive'!$D:$D,'Data Additive'!$P:$P,'Painel Additive'!$B19,'Data Additive'!$Q:$Q,"<=-61",'Data Additive'!$Q:$Q,">=-90") -> 0 | T19: =SUMIFS('Data Additive'!$D:$D,'Data Additive'!$P:$P,'Painel Additive'!$B19,'Data Additive'!$Q:$Q,"<=-91",'Data Additive'!$Q:$Q,">=-120") -> 0 | U19: =SUMIFS('Data Additive'!$D:$D,'Data Additive'!$P:$P,'Painel Additive'!$B19,'Data Additive'!$Q:$Q,"<=-121",'Data Additive'!$Q:$Q,">=-180") -> 0 | V19: =SUMIFS('Data Additive'!$D:$D,'Data Additive'!$P:$P,'Painel Additive'!$B19,'Data Additive'!$Q:$Q,"<=-181",'Data Additive'!$Q:$Q,">=-360") -> 0 | W19: =SUMIFS('Data Additive'!$D:$D,'Data Additive'!$P:$P,'Painel Additive'!$B19,'Data Additive'!$Q:$Q,"<-360") -> 0 | X19: =SUMIFS('Bad Debt Provision'!AB:AB,'Bad Debt Provision'!B:B,'Painel Additive'!B19) -> 0 | AA19: =IFERROR(_xlfn.XLOOKUP(B19,'Limite de crédito'!C:C,'Limite de crédito'!O:O,),0) -> 750000 | AG19: =AA19-G19 -> 750000
B20: GRUPO LOUIS DREYFUS | C20: =IFERROR(_xlfn.XLOOKUP(B20,'Limite de crédito'!C:C,'Limite de crédito'!L:L,),0) -> B | E20: =_xlfn.XLOOKUP(B20,'Limite de crédito'!C:C,'Limite de crédito'!G:G,0) -> 1500000 | F20: =E20-G20 -> 1500000 | G20: =P20+O20 -> 0 | H20: =SUMIFS('Data Additive'!$D:$D,'Data Additive'!$P:$P,'Painel Additive'!$B20,'Data Additive'!$Q:$Q,">0",'Data Additive'!$Q:$Q,"<=30") -> 0 | I20: =SUMIFS('Data Additive'!$D:$D,'Data Additive'!$P:$P,'Painel Additive'!$B20,'Data Additive'!$Q:$Q,">30",'Data Additive'!$Q:$Q,"<=60") -> 0 | J20: =SUMIFS('Data Additive'!$D:$D,'Data Additive'!$P:$P,'Painel Additive'!$B20,'Data Additive'!$Q:$Q,">60",'Data Additive'!$Q:$Q,"<=90") -> 0 | K20: =SUMIFS('Data Additive'!$D:$D,'Data Additive'!$P:$P,'Painel Additive'!$B20,'Data Additive'!$Q:$Q,">90",'Data Additive'!$Q:$Q,"<=120") -> 0 | L20: =SUMIFS('Data Additive'!$D:$D,'Data Additive'!$P:$P,'Painel Additive'!$B20,'Data Additive'!$Q:$Q,">120",'Data Additive'!$Q:$Q,"<=180") -> 0 | M20: =SUMIFS('Data Additive'!$D:$D,'Data Additive'!$P:$P,'Painel Additive'!$B20,'Data Additive'!$Q:$Q,">180",'Data Additive'!$Q:$Q,"<=360") -> 0 | N20: =SUMIFS('Data Additive'!$D:$D,'Data Additive'!$P:$P,'Painel Additive'!$B20,'Data Additive'!$Q:$Q,">360") -> 0 | O20: =SUMIFS('Data Additive'!$D:$D,'Data Additive'!$P:$P,'Painel Additive'!$B20,'Data Additive'!$Q:$Q,">0") -> 0 | P20: =SUM(Q20:W20) -> 0 | Q20: =SUMIFS('Data Additive'!$D:$D,'Data Additive'!$P:$P,'Painel Additive'!$B20,'Data Additive'!$Q:$Q,"<=0",'Data Additive'!$Q:$Q,">=-30") -> 0 | R20: =SUMIFS('Data Additive'!$D:$D,'Data Additive'!$P:$P,'Painel Additive'!$B20,'Data Additive'!$Q:$Q,"<=-31",'Data Additive'!$Q:$Q,">=-60") -> 0 | S20: =SUMIFS('Data Additive'!$D:$D,'Data Additive'!$P:$P,'Painel Additive'!$B20,'Data Additive'!$Q:$Q,"<=-61",'Data Additive'!$Q:$Q,">=-90") -> 0 | T20: =SUMIFS('Data Additive'!$D:$D,'Data Additive'!$P:$P,'Painel Additive'!$B20,'Data Additive'!$Q:$Q,"<=-91",'Data Additive'!$Q:$Q,">=-120") -> 0 | U20: =SUMIFS('Data Additive'!$D:$D,'Data Additive'!$P:$P,'Painel Additive'!$B20,'Data Additive'!$Q:$Q,"<=-121",'Data Additive'!$Q:$Q,">=-180") -> 0 | V20: =SUMIFS('Data Additive'!$D:$D,'Data Additive'!$P:$P,'Painel Additive'!$B20,'Data Additive'!$Q:$Q,"<=-181",'Data Additive'!$Q:$Q,">=-360") -> 0 | W20: =SUMIFS('Data Additive'!$D:$D,'Data Additive'!$P:$P,'Painel Additive'!$B20,'Data Additive'!$Q:$Q,"<-360") -> 0 | X20: =SUMIFS('Bad Debt Provision'!AB:AB,'Bad Debt Provision'!B:B,'Painel Additive'!B20) -> 0 | AA20: =IFERROR(_xlfn.XLOOKUP(B20,'Limite de crédito'!C:C,'Limite de crédito'!O:O,),0) -> 1500000 | AG20: =AA20-G20 -> 1500000
